Workbook

Sheet Cover
B2: AZALEA HOSPICE & PALLIATIVE CARE
B3: Refuge Hospice, LLC Acquisition - Financial Proforma
B4: Revision 4.10 | July 2026 | Tyler Hospice Hold, LLC (EIN 41-4966640)
B6: Prepared for the SBA 7(a) application (SourceFunding / The Brownmiller Group) and company planning.
B7: 36 monthly periods (Jul-2026 to Jun-2029). Every calculated cell is a live formula; all inputs on the Control Tower.
B8: Working-capital policy: the model assumes no revolving credit facility. Any cash shortfall is presented
B9: explicitly as an additional funding requirement rather than absorbed by an assumed facility.
B11: HEADLINE METRICS (all cells below are live links)
B12: Net patient revenue - Year 1 / 2 / 3 | C12: ='3-Year Summary'!B5 | D12: ='3-Year Summary'!C5 | E12: ='3-Year Summary'!D5
B13: EBITDA (pre-debt-service) - Year 1 / 2 / 3 | C13: ='3-Year Summary'!B6 | D13: ='3-Year Summary'!C6 | E13: ='3-Year Summary'!D6
B14: Minimum cash across 36 months (base case) | C14: ='Cash Flow & Runway'!B46
B15: Peak additional funding requirement (base case) | C15: ='Cash Flow & Runway'!B47
B16: Month-36 ending cash | C16: ='Cash Flow & Runway'!AL43
B17: Master integrity check (0 = clean) | C17: ='Checks'!B12
B19: FINANCING SEQUENCE (Path A)
B20: Aug 2026 - Equity ($250,000: J. Bullard $195K + G. Schackmann $55K) funds the $125,000 license down payment (49%)
B21: Sep 2026 - Interim bank note ($500,000, 6%, 36-mo) pays the sellers in full; surplus to working capital
B22: Oct-Dec - Bank note service of $15,211/month; management salary deferral until break-even census (repaid January)
B23: Jan 2027 - SBA 7(a) $500,000 funds at the 51% transfer (42 CFR 424.550(b)) and refinances the bank note
B24: Feb 2027 - Single SBA payment of $6,747/month (10.5%, 10-year); recurring coverage 3.8x / 8.6x / 12.2x
B26: WORKBOOK CONTENTS
B27: Control Tower | D27: All model inputs - deal terms, census, rates, staffing, and scenario settings
B28: Census Waterfall | D28: Admissions, discharge waterfall, ADC, patient days
B29: Revenue Model | D29: CMS rate build, payer mix, net patient revenue
B30: Staffing | D30: FTEs (census-driven with staged hiring), payroll, PRN supplement, management salary deferral schedule
B31: Operating Budget | D31: Direct patient care, facility, G&A, contingency
B32: P&L | D32: Accrual P&L with account codes; EBITDA and margins
B33: Cash Flow & Runway | D33: Collections timing, all debt schedules, ending cash, funding requirement (if any)
B34: Balance Sheet | D34: Fully articulated balance sheet; check row equals zero in every month
B35: Checks | D35: Model integrity tests and funding-requirement metrics
B36: Dashboard | D36: Key indicators: DSCR, DSO, Medicare cap cushion, margins
B37: 3-Year Summary | D37: Annual rollup and global DSCR
B38: Actuals vs Budget | D38: Enter actuals monthly; variances compute
B40: Confidential - prepared for lender and investor diligence. All figures verified by an automated 23-point test harness.

Sheet Control Tower
A1: AZALEA HOSPICE - REFUGE OPERATING MODEL
A2: CONTROL TOWER - all model inputs. Yellow cells are inputs; all other cells in the workbook are formulas.
A4: COMPANY & DEAL (current Refuge structure)
A5: Starting capital on deposit (equity) | B5: 250000 | D5: Jim Bullard $195K + owner $55K
A6: Pre-opening / startup spend from capital | B6: 0 | D6: 0 = funded elsewhere
A7: Refuge license purchase price (100% membership CHOW) | B7: 500000 | D7: Acct 1980 intangible
A8: Down payment at closing (Month 1) | B8: 125000
A9: Seller monthly payment (MIPA 7/14/2026) | B9: 31250 | D9: $31,250/mo Sep-Dec per executed MIPA
A10: First seller payment month | B10: 3 | D10: 3 = September
A11: Last seller payment month | B11: 6 | D11: 6 = December
A12: Seller note simple interest (APR) | B12: 0.06
A13: Balloon month (36-month rule / January) | B13: 7
A14: Balloon takeout note rate (APR) | B14: 0.06 | D14: BASE CASE: SBA/bank funds the Jan balloon; modeled at the conservative 6%/36 basis
A15: Balloon takeout note term (months) | B15: 36
A16: INTERIM BANK NOTE (1 = $500K/6%/36 funds Sept - base case) | B16: 1 | D16: Base case: interim bank note retires the seller balance in September; 0 = seller carried to the January balloon per the MIPA
A17: Full-refi funding month | B17: 3 | D17: 3 = September
A18: Full-refi amount | B18: 500000
A19: Full-refi rate (APR) | B19: 0.06
A20: Full-refi term (months) | B20: 36
A21: SBA 7(a) LOAN (1 = funds and refinances the bank note - base case) | B21: 1 | D21: SBA proceeds retire the bank-note balance at the funding month
A22: SBA funding month | B22: 7 | D22: 7 = January (51% transfer / 42 CFR 424.550(b) date)
A23: SBA amount | B23: 500000
A24: SBA rate (APR) | B24: 0.105
A25: SBA term (months) | B25: 120 | D25: 10-year 7(a); ~$6,747/mo at 10.5%
A26: License intangible amortization (yrs, Acct 7200) | B26: 15
A27: CHOW / go-live month (amortization starts) | B27: 1
A28: CENSUS (admissions row lives on Census Waterfall - blue)
A29: Days per month (model uniform) | B29: 30.4
A30: Average length of stay (days) | B30: 82 | D30: drives discharges = BOM x days/ALOS
A31: Deaths as share of discharges | B31: 0.55
A32: SCENARIO CASES (1 = Base, 2 = Downside, 3 = Upside; active values are formulas)
A33: ACTIVE CASE | B33: 1 | D33: flip 1/2/3 - drives capture, payroll adj, CHOW hold
A34: Case matrix: | B34: Base | C34: Downside | D34: Upside
A35: Census capture | B35: 1 | C35: 0.85 | D35: 1.1
A36: Payroll adjustment | B36: 0 | C36: 0.1 | D36: 0
A37: CHOW hold (months) | B37: 1 | C37: 2 | D37: 0
A38: ACTIVE census capture (formula) | B38: =CHOOSE('Control Tower'!$B$33,'Control Tower'!$B$35,'Control Tower'!$C$35,'Control Tower'!$D$35)
A39: ACTIVE payroll adjustment (formula) | B39: =CHOOSE('Control Tower'!$B$33,'Control Tower'!$B$36,'Control Tower'!$C$36,'Control Tower'!$D$36)
A40: ACTIVE CHOW hold (formula) | B40: =CHOOSE('Control Tower'!$B$33,'Control Tower'!$B$37,'Control Tower'!$C$37,'Control Tower'!$D$37)
A41: REVENUE - CMS FY2026 SMITH COUNTY (Acct 3000/3010)
A42: Medicare RHC HIGH rate, days 1-60 ($/day, net of seq.) | B42: 212.76 | D42: 217.10 x 98 pct
A43: Medicare RHC LOW rate, days 61+ ($/day, net of seq.) | B43: 167.7 | D43: 171.12 x 98 pct
A44: Texas Medicaid rate ($/day) | B44: 155 | D44: verify with TMHP
A45: Medicare payer mix | B45: 1
A46: % Medicare days at HIGH rate | B46: 0.15 | D46: transfer panel mostly days 61+
A47: Billing company fee (% of gross, Acct 6510-Z) | B47: 0.015
A48: CMS rate escalation (annual, yrs 2-3) | B48: 0.025
A49: Opex inflation on fixed G&A/facility (annual, yrs 2-3) | B49: 0.03
A50: COLLECTIONS TIMING (cash engine)
A51: % collected same month | B51: 0
A52: % collected month +1 | B52: 1
A53: % collected month +2 | B53: 0
A54: CLINICAL LABOR (Acct 4000; benefits and workers compensation loads)
A55: Benefits & payroll tax load (employed) | B55: 0.22 | D55: industry range 22-28%; modeled at 22%
A56: Workers comp (% of employed payroll) | B56: 0.03
A57: Salary escalation (annual, yrs 2-3) | B57: 0.03
A58: RN Case Manager salary | B58: 80000
A59: RN caseload (patients : 1 FTE) | B59: 12
A60: RN On-Call salary (per 1.0 FTE) | B60: 80000
A61: RN On-Call minimum FTE | B61: 0.25
A62: Hospice Aide / CNA salary | B62: 48000
A63: CNA caseload (patients : 1 FTE) | B63: 10
A64: MSW salary | B64: 60000
A65: MSW caseload (patients : 1 FTE) | B65: 30
A66: Chaplain base PRN contract ($/mo, Acct 4020-0-6-7) | B66: 600
A67: Medical director stipend ($/mo, Acct 4020-0-6-M) | B67: 4000
A68: Medical director start month | B68: 1
A69: PRN PER-VISIT SUPPLEMENT (1099; applies when FTE capacity is below required visits)
A70: RN required visits / patient / month | B70: 2 | D70: CoP 418.56 - q14 days
A71: RN visits capacity / FTE / month | B71: 24
A72: RN PRN rate ($/visit) | B72: 85
A73: Aide required visits / patient / month | B73: 8
A74: Aide visits capacity / FTE / month | B74: 80
A75: Aide PRN rate ($/visit) | B75: 45
A76: MSW required visits / patient / month | B76: 1
A77: MSW visits capacity / FTE / month | B77: 20
A78: MSW PRN rate ($/visit) | B78: 75
A79: Chaplain required visits / patient / month | B79: 1
A80: Chaplain visits covered by base contract | B80: 8
A81: Chaplain PRN rate ($/visit) | B81: 60
A82: INDIRECT LABOR - ADMIN & LEADERSHIP (Acct 4000-0-*)
A83: Silas Shelton - Executive Director salary | B83: 150000
A84: start month | B84: 2
A85: Dana Davenport - Director of Nursing salary | B85: 120000
A86: start month | B86: 2
A87: Brad Woodard - Director of Sales salary | B87: 120000
A88: start month | B88: 1
A89: Rhonda Smith - ADON / Intake salary | B89: 60000
A90: start month | B90: 1
A91: Volunteer + Bereavement Coordinator salary | B91: 50000
A92: start month | B92: 1
A93: QAPI / Compliance salary (per 1.0 FTE) | B93: 70000
A94: QAPI 0.5 FTE begins at ADC >= | B94: 40
A95: DIRECT PATIENT CARE - per patient-day (Acct 5050-5120)
A96: DME rental ($/PD, 5050) | B96: 9
A97: Medications ($/PD, 5100) | B97: 3.5
A98: Medical supplies ($/PD, 5090) | B98: 3
A99: Clinical mileage ($/PD, 5110) | B99: 0.5
A100: Mobile communications - clinical ($/mo, 5120) | B100: 50
A101: FACILITY (700 N Main St - Acct 6010-6150; rent steps with census)
...

Sheet Census Waterfall
A1: AZALEA HOSPICE - REFUGE OPERATING MODEL
A2: CENSUS WATERFALL - admissions are the operating lever (blue). Discharges follow ALOS. 36 months.
A4: Month # | C4: 1 | D4: 2 | E4: 3 | F4: 4 | G4: 5 | H4: 6 | I4: 7 | J4: 8 | K4: 9 | L4: 10 | M4: 11 | N4: 12 | O4: 13 | P4: 14 | Q4: 15 | R4: 16 | S4: 17 | T4: 18 | U4: 19 | V4: 20 | W4: 21 | X4: 22 | Y4: 23 | Z4: 24 | AA4: 25 | AB4: 26 | AC4: 27 | AD4: 28 | AE4: 29 | AF4: 30 | AG4: 31 | AH4: 32 | AI4: 33 | AJ4: 34 | AK4: 35 | AL4: 36
C5: Jul-26 | D5: Aug-26 | E5: Sep-26 | F5: Oct-26 | G5: Nov-26 | H5: Dec-26 | I5: Jan-27 | J5: Feb-27 | K5: Mar-27 | L5: Apr-27 | M5: May-27 | N5: Jun-27 | O5: Jul-27 | P5: Aug-27 | Q5: Sep-27 | R5: Oct-27 | S5: Nov-27 | T5: Dec-27 | U5: Jan-28 | V5: Feb-28 | W5: Mar-28 | X5: Apr-28 | Y5: May-28 | Z5: Jun-28 | AA5: Jul-28 | AB5: Aug-28 | AC5: Sep-28 | AD5: Oct-28 | AE5: Nov-28 | AF5: Dec-28 | AG5: Jan-29 | AH5: Feb-29 | AI5: Mar-29 | AJ5: Apr-29 | AK5: May-29 | AL5: Jun-29
A6: Beginning-of-month census (BOM) | C6: =0 | D6: =C9 | E6: =D9 | F6: =E9 | G6: =F9 | H6: =G9 | I6: =H9 | J6: =I9 | K6: =J9 | ... AL6: =AK9
A7: + New admissions [INPUT - 7/6 plan default] | C7: 20 | D7: 11.41 | E7: 11.4 | F7: 12.32 | G7: 13.25 | H7: 14.18 | I7: 13.6 | J7: 13.98 | K7: 14.35 | L7: 14.72 | M7: 15.09 | N7: 15.46 | O7: 15.66 | P7: 15.98 | Q7: 16.28 | R7: 16.59 | S7: 16.9 | T7: 17.21 | U7: 17.51 | V7: 17.83 | W7: 18.13 | X7: 18.44 | Y7: 18.76 | Z7: 19.06 | AA7: 19.04 | AB7: 19.22 | AC7: 19.41 | AD7: 19.59 | AE7: 19.78 | AF7: 19.96 | AG7: 20.15 | AH7: 20.33 | AI7: 20.52 | AJ7: 20.7 | AK7: 20.89 | AL7: 21.08
A8: - Discharges (deaths + revocations) = BOM x days/ALOS | C8: =C6*'Control Tower'!$B$29/'Control Tower'!$B$30 | D8: =D6*'Control Tower'!$B$29/'Control Tower'!$B$30 | E8: =E6*'Control Tower'!$B$29/'Control Tower'!$B$30 | F8: =F6*'Control Tower'!$B$29/'Control Tower'!$B$30 | G8: =G6*'Control Tower'!$B$29/'Control Tower'!$B$30 | H8: =H6*'Control Tower'!$B$29/'Control Tower'!$B$30 | I8: =I6*'Control Tower'!$B$29/'Control Tower'!$B$30 | J8: =J6*'Control Tower'!$B$29/'Control Tower'!$B$30 | ... AL8: =AL6*'Control Tower'!$B$29/'Control Tower'!$B$30
A9: End-of-month census (EOM) | C9: =C6+C7-C8 | D9: =D6+D7-D8 | E9: =E6+E7-E8 | F9: =F6+F7-F8 | G9: =G6+G7-G8 | H9: =H6+H7-H8 | I9: =I6+I7-I8 | J9: =J6+J7-J8 | ... AL9: =AL6+AL7-AL8
A10: of which deaths (bereavement trigger) | C10: =C8*'Control Tower'!$B$31 | D10: =D8*'Control Tower'!$B$31 | E10: =E8*'Control Tower'!$B$31 | F10: =F8*'Control Tower'!$B$31 | G10: =G8*'Control Tower'!$B$31 | H10: =H8*'Control Tower'!$B$31 | I10: =I8*'Control Tower'!$B$31 | J10: =J8*'Control Tower'!$B$31 | ... AL10: =AL8*'Control Tower'!$B$31
A11: ADC = (BOM + EOM)/2 x capture | C11: =(C6+C9)/2*'Control Tower'!$B$38 | D11: =(D6+D9)/2*'Control Tower'!$B$38 | E11: =(E6+E9)/2*'Control Tower'!$B$38 | F11: =(F6+F9)/2*'Control Tower'!$B$38 | G11: =(G6+G9)/2*'Control Tower'!$B$38 | H11: =(H6+H9)/2*'Control Tower'!$B$38 | I11: =(I6+I9)/2*'Control Tower'!$B$38 | J11: =(J6+J9)/2*'Control Tower'!$B$38 | ... AL11: =(AL6+AL9)/2*'Control Tower'!$B$38
A12: Patient days (ADC x days/month) | C12: =C11*'Control Tower'!$B$29 | D12: =D11*'Control Tower'!$B$29 | E12: =E11*'Control Tower'!$B$29 | F12: =F11*'Control Tower'!$B$29 | G12: =G11*'Control Tower'!$B$29 | H12: =H11*'Control Tower'!$B$29 | I12: =I11*'Control Tower'!$B$29 | J12: =J11*'Control Tower'!$B$29 | ... AL12: =AL11*'Control Tower'!$B$29
A13: Monthly discharge rate (of BOM) | C13: =IF(C6=0,0,C8/C6) | D13: =IF(D6=0,0,D8/D6) | E13: =IF(E6=0,0,E8/E6) | F13: =IF(F6=0,0,F8/F6) | G13: =IF(G6=0,0,G8/G6) | H13: =IF(H6=0,0,H8/H6) | I13: =IF(I6=0,0,I8/I6) | J13: =IF(J6=0,0,J8/J6) | ... AL13: =IF(AL6=0,0,AL8/AL6)

Sheet Revenue Model
A1: AZALEA HOSPICE - REFUGE OPERATING MODEL
A2: REVENUE - patient days x CMS rates (high/low split), less billing fee -> NET PATIENT REVENUE (accrual).
A4: Month # | C4: 1 | D4: 2 | E4: 3 | F4: 4 | G4: 5 | H4: 6 | I4: 7 | J4: 8 | K4: 9 | L4: 10 | M4: 11 | N4: 12 | O4: 13 | P4: 14 | Q4: 15 | R4: 16 | S4: 17 | T4: 18 | U4: 19 | V4: 20 | W4: 21 | X4: 22 | Y4: 23 | Z4: 24 | AA4: 25 | AB4: 26 | AC4: 27 | AD4: 28 | AE4: 29 | AF4: 30 | AG4: 31 | AH4: 32 | AI4: 33 | AJ4: 34 | AK4: 35 | AL4: 36
C5: Jul-26 | D5: Aug-26 | E5: Sep-26 | F5: Oct-26 | G5: Nov-26 | H5: Dec-26 | I5: Jan-27 | J5: Feb-27 | K5: Mar-27 | L5: Apr-27 | M5: May-27 | N5: Jun-27 | O5: Jul-27 | P5: Aug-27 | Q5: Sep-27 | R5: Oct-27 | S5: Nov-27 | T5: Dec-27 | U5: Jan-28 | V5: Feb-28 | W5: Mar-28 | X5: Apr-28 | Y5: May-28 | Z5: Jun-28 | AA5: Jul-28 | AB5: Aug-28 | AC5: Sep-28 | AD5: Oct-28 | AE5: Nov-28 | AF5: Dec-28 | AG5: Jan-29 | AH5: Feb-29 | AI5: Mar-29 | AJ5: Apr-29 | AK5: May-29 | AL5: Jun-29
A6: Medicare RHC HIGH (days 1-60, 3000-R-6-0) | C6: ='Census Waterfall'!C12*'Control Tower'!$B$45*'Control Tower'!$B$46*'Control Tower'!$B$42*(1+'Control Tower'!$B$48)^0 | D6: ='Census Waterfall'!D12*'Control Tower'!$B$45*'Control Tower'!$B$46*'Control Tower'!$B$42*(1+'Control Tower'!$B$48)^0 | E6: ='Census Waterfall'!E12*'Control Tower'!$B$45*'Control Tower'!$B$46*'Control Tower'!$B$42*(1+'Control Tower'!$B$48)^0 | F6: ='Census Waterfall'!F12*'Control Tower'!$B$45*'Control Tower'!$B$46*'Control Tower'!$B$42*(1+'Control Tower'!$B$48)^0 | G6: ='Census Waterfall'!G12*'Control Tower'!$B$45*'Control Tower'!$B$46*'Control Tower'!$B$42*(1+'Control Tower'!$B$48)^0 | H6: ='Census Waterfall'!H12*'Control Tower'!$B$45*'Control Tower'!$B$46*'Control Tower'!$B$42*(1+'Control Tower'!$B$48)^0 | I6: ='Census Waterfall'!I12*'Control Tower'!$B$45*'Control Tower'!$B$46*'Control Tower'!$B$42*(1+'Control Tower'!$B$48)^0 | J6: ='Census Waterfall'!J12*'Control Tower'!$B$45*'Control Tower'!$B$46*'Control Tower'!$B$42*(1+'Control Tower'!$B$48)^0 | ... N6: ='Census Waterfall'!N12*'Control Tower'!$B$45*'Control Tower'!$B$46*'Control Tower'!$B$42*(1+'Control Tower'!$B$48)^0 | O6: ='Census Waterfall'!O12*'Control Tower'!$B$45*'Control Tower'!$B$46*'Control Tower'!$B$42*(1+'Control Tower'!$B$48)^1 | P6: ='Census Waterfall'!P12*'Control Tower'!$B$45*'Control Tower'!$B$46*'Control Tower'!$B$42*(1+'Control Tower'!$B$48)^1 | Q6: ='Census Waterfall'!Q12*'Control Tower'!$B$45*'Control Tower'!$B$46*'Control Tower'!$B$42*(1+'Control Tower'!$B$48)^1 | R6: ='Census Waterfall'!R12*'Control Tower'!$B$45*'Control Tower'!$B$46*'Control Tower'!$B$42*(1+'Control Tower'!$B$48)^1 | S6: ='Census Waterfall'!S12*'Control Tower'!$B$45*'Control Tower'!$B$46*'Control Tower'!$B$42*(1+'Control Tower'!$B$48)^1 | T6: ='Census Waterfall'!T12*'Control Tower'!$B$45*'Control Tower'!$B$46*'Control Tower'!$B$42*(1+'Control Tower'!$B$48)^1 | U6: ='Census Waterfall'!U12*'Control Tower'!$B$45*'Control Tower'!$B$46*'Control Tower'!$B$42*(1+'Control Tower'!$B$48)^1 | V6: ='Census Waterfall'!V12*'Control Tower'!$B$45*'Control Tower'!$B$46*'Control Tower'!$B$42*(1+'Control Tower'!$B$48)^1 | ... Z6: ='Census Waterfall'!Z12*'Control Tower'!$B$45*'Control Tower'!$B$46*'Control Tower'!$B$42*(1+'Control Tower'!$B$48)^1 | AA6: ='Census Waterfall'!AA12*'Control Tower'!$B$45*'Control Tower'!$B$46*'Control Tower'!$B$42*(1+'Control Tower'!$B$48)^2 | AB6: ='Census Waterfall'!AB12*'Control Tower'!$B$45*'Control Tower'!$B$46*'Control Tower'!$B$42*(1+'Control Tower'!$B$48)^2 | AC6: ='Census Waterfall'!AC12*'Control Tower'!$B$45*'Control Tower'!$B$46*'Control Tower'!$B$42*(1+'Control Tower'!$B$48)^2 | AD6: ='Census Waterfall'!AD12*'Control Tower'!$B$45*'Control Tower'!$B$46*'Control Tower'!$B$42*(1+'Control Tower'!$B$48)^2 | AE6: ='Census Waterfall'!AE12*'Control Tower'!$B$45*'Control Tower'!$B$46*'Control Tower'!$B$42*(1+'Control Tower'!$B$48)^2 | AF6: ='Census Waterfall'!AF12*'Control Tower'!$B$45*'Control Tower'!$B$46*'Control Tower'!$B$42*(1+'Control Tower'!$B$48)^2 | AG6: ='Census Waterfall'!AG12*'Control Tower'!$B$45*'Control Tower'!$B$46*'Control Tower'!$B$42*(1+'Control Tower'!$B$48)^2 | AH6: ='Census Waterfall'!AH12*'Control Tower'!$B$45*'Control Tower'!$B$46*'Control Tower'!$B$42*(1+'Control Tower'!$B$48)^2 | ... AL6: ='Census Waterfall'!AL12*'Control Tower'!$B$45*'Control Tower'!$B$46*'Control Tower'!$B$42*(1+'Control Tower'!$B$48)^2
A7: Medicare RHC LOW (days 61+, 3000-R-6-0) | C7: ='Census Waterfall'!C12*'Control Tower'!$B$45*(1-'Control Tower'!$B$46)*'Control Tower'!$B$43*(1+'Control Tower'!$B$48)^0 | D7: ='Census Waterfall'!D12*'Control Tower'!$B$45*(1-'Control Tower'!$B$46)*'Control Tower'!$B$43*(1+'Control Tower'!$B$48)^0 | E7: ='Census Waterfall'!E12*'Control Tower'!$B$45*(1-'Control Tower'!$B$46)*'Control Tower'!$B$43*(1+'Control Tower'!$B$48)^0 | F7: ='Census Waterfall'!F12*'Control Tower'!$B$45*(1-'Control Tower'!$B$46)*'Control Tower'!$B$43*(1+'Control Tower'!$B$48)^0 | G7: ='Census Waterfall'!G12*'Control Tower'!$B$45*(1-'Control Tower'!$B$46)*'Control Tower'!$B$43*(1+'Control Tower'!$B$48)^0 | H7: ='Census Waterfall'!H12*'Control Tower'!$B$45*(1-'Control Tower'!$B$46)*'Control Tower'!$B$43*(1+'Control Tower'!$B$48)^0 | I7: ='Census Waterfall'!I12*'Control Tower'!$B$45*(1-'Control Tower'!$B$46)*'Control Tower'!$B$43*(1+'Control Tower'!$B$48)^0 | J7: ='Census Waterfall'!J12*'Control Tower'!$B$45*(1-'Control Tower'!$B$46)*'Control Tower'!$B$43*(1+'Control Tower'!$B$48)^0 | ... N7: ='Census Waterfall'!N12*'Control Tower'!$B$45*(1-'Control Tower'!$B$46)*'Control Tower'!$B$43*(1+'Control Tower'!$B$48)^0 | O7: ='Census Waterfall'!O12*'Control Tower'!$B$45*(1-'Control Tower'!$B$46)*'Control Tower'!$B$43*(1+'Control Tower'!$B$48)^1 | P7: ='Census Waterfall'!P12*'Control Tower'!$B$45*(1-'Control Tower'!$B$46)*'Control Tower'!$B$43*(1+'Control Tower'!$B$48)^1 | Q7: ='Census Waterfall'!Q12*'Control Tower'!$B$45*(1-'Control Tower'!$B$46)*'Control Tower'!$B$43*(1+'Control Tower'!$B$48)^1 | R7: ='Census Waterfall'!R12*'Control Tower'!$B$45*(1-'Control Tower'!$B$46)*'Control Tower'!$B$43*(1+'Control Tower'!$B$48)^1 | S7: ='Census Waterfall'!S12*'Control Tower'!$B$45*(1-'Control Tower'!$B$46)*'Control Tower'!$B$43*(1+'Control Tower'!$B$48)^1 | T7: ='Census Waterfall'!T12*'Control Tower'!$B$45*(1-'Control Tower'!$B$46)*'Control Tower'!$B$43*(1+'Control Tower'!$B$48)^1 | U7: ='Census Waterfall'!U12*'Control Tower'!$B$45*(1-'Control Tower'!$B$46)*'Control Tower'!$B$43*(1+'Control Tower'!$B$48)^1 | V7: ='Census Waterfall'!V12*'Control Tower'!$B$45*(1-'Control Tower'!$B$46)*'Control Tower'!$B$43*(1+'Control Tower'!$B$48)^1 | ... Z7: ='Census Waterfall'!Z12*'Control Tower'!$B$45*(1-'Control Tower'!$B$46)*'Control Tower'!$B$43*(1+'Control Tower'!$B$48)^1 | AA7: ='Census Waterfall'!AA12*'Control Tower'!$B$45*(1-'Control Tower'!$B$46)*'Control Tower'!$B$43*(1+'Control Tower'!$B$48)^2 | AB7: ='Census Waterfall'!AB12*'Control Tower'!$B$45*(1-'Control Tower'!$B$46)*'Control Tower'!$B$43*(1+'Control Tower'!$B$48)^2 | AC7: ='Census Waterfall'!AC12*'Control Tower'!$B$45*(1-'Control Tower'!$B$46)*'Control Tower'!$B$43*(1+'Control Tower'!$B$48)^2 | AD7: ='Census Waterfall'!AD12*'Control Tower'!$B$45*(1-'Control Tower'!$B$46)*'Control Tower'!$B$43*(1+'Control Tower'!$B$48)^2 | AE7: ='Census Waterfall'!AE12*'Control Tower'!$B$45*(1-'Control Tower'!$B$46)*'Control Tower'!$B$43*(1+'Control Tower'!$B$48)^2 | AF7: ='Census Waterfall'!AF12*'Control Tower'!$B$45*(1-'Control Tower'!$B$46)*'Control Tower'!$B$43*(1+'Control Tower'!$B$48)^2 | AG7: ='Census Waterfall'!AG12*'Control Tower'!$B$45*(1-'Control Tower'!$B$46)*'Control Tower'!$B$43*(1+'Control Tower'!$B$48)^2 | AH7: ='Census Waterfall'!AH12*'Control Tower'!$B$45*(1-'Control Tower'!$B$46)*'Control Tower'!$B$43*(1+'Control Tower'!$B$48)^2 | ... AL7: ='Census Waterfall'!AL12*'Control Tower'!$B$45*(1-'Control Tower'!$B$46)*'Control Tower'!$B$43*(1+'Control Tower'!$B$48)^2
A8: Medicaid RHC (3010-R-6-0) | C8: ='Census Waterfall'!C12*(1-'Control Tower'!$B$45)*'Control Tower'!$B$44*(1+'Control Tower'!$B$48)^0 | D8: ='Census Waterfall'!D12*(1-'Control Tower'!$B$45)*'Control Tower'!$B$44*(1+'Control Tower'!$B$48)^0 | E8: ='Census Waterfall'!E12*(1-'Control Tower'!$B$45)*'Control Tower'!$B$44*(1+'Control Tower'!$B$48)^0 | F8: ='Census Waterfall'!F12*(1-'Control Tower'!$B$45)*'Control Tower'!$B$44*(1+'Control Tower'!$B$48)^0 | G8: ='Census Waterfall'!G12*(1-'Control Tower'!$B$45)*'Control Tower'!$B$44*(1+'Control Tower'!$B$48)^0 | H8: ='Census Waterfall'!H12*(1-'Control Tower'!$B$45)*'Control Tower'!$B$44*(1+'Control Tower'!$B$48)^0 | I8: ='Census Waterfall'!I12*(1-'Control Tower'!$B$45)*'Control Tower'!$B$44*(1+'Control Tower'!$B$48)^0 | J8: ='Census Waterfall'!J12*(1-'Control Tower'!$B$45)*'Control Tower'!$B$44*(1+'Control Tower'!$B$48)^0 | ... N8: ='Census Waterfall'!N12*(1-'Control Tower'!$B$45)*'Control Tower'!$B$44*(1+'Control Tower'!$B$48)^0 | O8: ='Census Waterfall'!O12*(1-'Control Tower'!$B$45)*'Control Tower'!$B$44*(1+'Control Tower'!$B$48)^1 | P8: ='Census Waterfall'!P12*(1-'Control Tower'!$B$45)*'Control Tower'!$B$44*(1+'Control Tower'!$B$48)^1 | Q8: ='Census Waterfall'!Q12*(1-'Control Tower'!$B$45)*'Control Tower'!$B$44*(1+'Control Tower'!$B$48)^1 | R8: ='Census Waterfall'!R12*(1-'Control Tower'!$B$45)*'Control Tower'!$B$44*(1+'Control Tower'!$B$48)^1 | S8: ='Census Waterfall'!S12*(1-'Control Tower'!$B$45)*'Control Tower'!$B$44*(1+'Control Tower'!$B$48)^1 | T8: ='Census Waterfall'!T12*(1-'Control Tower'!$B$45)*'Control Tower'!$B$44*(1+'Control Tower'!$B$48)^1 | U8: ='Census Waterfall'!U12*(1-'Control Tower'!$B$45)*'Control Tower'!$B$44*(1+'Control Tower'!$B$48)^1 | V8: ='Census Waterfall'!V12*(1-'Control Tower'!$B$45)*'Control Tower'!$B$44*(1+'Control Tower'!$B$48)^1 | ... Z8: ='Census Waterfall'!Z12*(1-'Control Tower'!$B$45)*'Control Tower'!$B$44*(1+'Control Tower'!$B$48)^1 | AA8: ='Census Waterfall'!AA12*(1-'Control Tower'!$B$45)*'Control Tower'!$B$44*(1+'Control Tower'!$B$48)^2 | AB8: ='Census Waterfall'!AB12*(1-'Control Tower'!$B$45)*'Control Tower'!$B$44*(1+'Control Tower'!$B$48)^2 | AC8: ='Census Waterfall'!AC12*(1-'Control Tower'!$B$45)*'Control Tower'!$B$44*(1+'Control Tower'!$B$48)^2 | AD8: ='Census Waterfall'!AD12*(1-'Control Tower'!$B$45)*'Control Tower'!$B$44*(1+'Control Tower'!$B$48)^2 | AE8: ='Census Waterfall'!AE12*(1-'Control Tower'!$B$45)*'Control Tower'!$B$44*(1+'Control Tower'!$B$48)^2 | AF8: ='Census Waterfall'!AF12*(1-'Control Tower'!$B$45)*'Control Tower'!$B$44*(1+'Control Tower'!$B$48)^2 | AG8: ='Census Waterfall'!AG12*(1-'Control Tower'!$B$45)*'Control Tower'!$B$44*(1+'Control Tower'!$B$48)^2 | AH8: ='Census Waterfall'!AH12*(1-'Control Tower'!$B$45)*'Control Tower'!$B$44*(1+'Control Tower'!$B$48)^2 | ... AL8: ='Census Waterfall'!AL12*(1-'Control Tower'!$B$45)*'Control Tower'!$B$44*(1+'Control Tower'!$B$48)^2
A9: TOTAL GROSS REVENUE | C9: =C6+C7+C8 | D9: =D6+D7+D8 | E9: =E6+E7+E8 | F9: =F6+F7+F8 | G9: =G6+G7+G8 | H9: =H6+H7+H8 | I9: =I6+I7+I8 | J9: =J6+J7+J8 | ... AL9: =AL6+AL7+AL8
A10: Less: billing company fee (6510-Z) | C10: =-C9*'Control Tower'!$B$47 | D10: =-D9*'Control Tower'!$B$47 | E10: =-E9*'Control Tower'!$B$47 | F10: =-F9*'Control Tower'!$B$47 | G10: =-G9*'Control Tower'!$B$47 | H10: =-H9*'Control Tower'!$B$47 | I10: =-I9*'Control Tower'!$B$47 | J10: =-J9*'Control Tower'!$B$47 | ... AL10: =-AL9*'Control Tower'!$B$47
A11: NET PATIENT REVENUE (accrual) | C11: =C9+C10 | D11: =D9+D10 | E11: =E9+E10 | F11: =F9+F10 | G11: =G9+G10 | H11: =H9+H10 | I11: =I9+I10 | J11: =J9+J10 | ... AL11: =AL9+AL10

Sheet Staffing
A1: AZALEA HOSPICE - REFUGE OPERATING MODEL
A2: STAFFING - FTEs scale with census on caseload ratios; PRN 1099 supplement covers visits above FTE capacity.
A4: Month # | C4: 1 | D4: 2 | E4: 3 | F4: 4 | G4: 5 | H4: 6 | I4: 7 | J4: 8 | K4: 9 | L4: 10 | M4: 11 | N4: 12 | O4: 13 | P4: 14 | Q4: 15 | R4: 16 | S4: 17 | T4: 18 | U4: 19 | V4: 20 | W4: 21 | X4: 22 | Y4: 23 | Z4: 24 | AA4: 25 | AB4: 26 | AC4: 27 | AD4: 28 | AE4: 29 | AF4: 30 | AG4: 31 | AH4: 32 | AI4: 33 | AJ4: 34 | AK4: 35 | AL4: 36
C5: Jul-26 | D5: Aug-26 | E5: Sep-26 | F5: Oct-26 | G5: Nov-26 | H5: Dec-26 | I5: Jan-27 | J5: Feb-27 | K5: Mar-27 | L5: Apr-27 | M5: May-27 | N5: Jun-27 | O5: Jul-27 | P5: Aug-27 | Q5: Sep-27 | R5: Oct-27 | S5: Nov-27 | T5: Dec-27 | U5: Jan-28 | V5: Feb-28 | W5: Mar-28 | X5: Apr-28 | Y5: May-28 | Z5: Jun-28 | AA5: Jul-28 | AB5: Aug-28 | AC5: Sep-28 | AD5: Oct-28 | AE5: Nov-28 | AF5: Dec-28 | AG5: Jan-29 | AH5: Feb-29 | AI5: Mar-29 | AJ5: Apr-29 | AK5: May-29 | AL5: Jun-29
A6: CLINICAL IDG - EMPLOYED (Acct 4000; FTE = LAGGED census/caseload in 0.5 steps, with day-1 core floors)
A7: RN Case Manager (4000-0-6-1) - FTE | C7: =MAX('Control Tower'!$B$127,ROUNDUP(IF('Control Tower'!$B$126=1,0,'Census Waterfall'!C11)/'Control Tower'!$B$59*2,0)/2) | D7: =MAX('Control Tower'!$B$127,ROUNDUP(IF('Control Tower'!$B$126=1,'Census Waterfall'!C11,'Census Waterfall'!D11)/'Control Tower'!$B$59*2,0)/2) | E7: =MAX('Control Tower'!$B$127,ROUNDUP(IF('Control Tower'!$B$126=1,'Census Waterfall'!D11,'Census Waterfall'!E11)/'Control Tower'!$B$59*2,0)/2) | F7: =MAX('Control Tower'!$B$127,ROUNDUP(IF('Control Tower'!$B$126=1,'Census Waterfall'!E11,'Census Waterfall'!F11)/'Control Tower'!$B$59*2,0)/2) | G7: =MAX('Control Tower'!$B$127,ROUNDUP(IF('Control Tower'!$B$126=1,'Census Waterfall'!F11,'Census Waterfall'!G11)/'Control Tower'!$B$59*2,0)/2) | H7: =MAX('Control Tower'!$B$127,ROUNDUP(IF('Control Tower'!$B$126=1,'Census Waterfall'!G11,'Census Waterfall'!H11)/'Control Tower'!$B$59*2,0)/2) | I7: =MAX('Control Tower'!$B$127,ROUNDUP(IF('Control Tower'!$B$126=1,'Census Waterfall'!H11,'Census Waterfall'!I11)/'Control Tower'!$B$59*2,0)/2) | J7: =MAX('Control Tower'!$B$127,ROUNDUP(IF('Control Tower'!$B$126=1,'Census Waterfall'!I11,'Census Waterfall'!J11)/'Control Tower'!$B$59*2,0)/2) | K7: =MAX('Control Tower'!$B$127,ROUNDUP(IF('Control Tower'!$B$126=1,'Census Waterfall'!J11,'Census Waterfall'!K11)/'Control Tower'!$B$59*2,0)/2) | ... AL7: =MAX('Control Tower'!$B$127,ROUNDUP(IF('Control Tower'!$B$126=1,'Census Waterfall'!AK11,'Census Waterfall'!AL11)/'Control Tower'!$B$59*2,0)/2)
A8: RN Case Manager (4000-0-6-1) - wages | C8: =C7*'Control Tower'!$B$58/12*(1+'Control Tower'!$B$57)^0*(1+'Control Tower'!$B$39) | D8: =D7*'Control Tower'!$B$58/12*(1+'Control Tower'!$B$57)^0*(1+'Control Tower'!$B$39) | E8: =E7*'Control Tower'!$B$58/12*(1+'Control Tower'!$B$57)^0*(1+'Control Tower'!$B$39) | F8: =F7*'Control Tower'!$B$58/12*(1+'Control Tower'!$B$57)^0*(1+'Control Tower'!$B$39) | G8: =G7*'Control Tower'!$B$58/12*(1+'Control Tower'!$B$57)^0*(1+'Control Tower'!$B$39) | H8: =H7*'Control Tower'!$B$58/12*(1+'Control Tower'!$B$57)^0*(1+'Control Tower'!$B$39) | I8: =I7*'Control Tower'!$B$58/12*(1+'Control Tower'!$B$57)^0*(1+'Control Tower'!$B$39) | J8: =J7*'Control Tower'!$B$58/12*(1+'Control Tower'!$B$57)^0*(1+'Control Tower'!$B$39) | ... N8: =N7*'Control Tower'!$B$58/12*(1+'Control Tower'!$B$57)^0*(1+'Control Tower'!$B$39) | O8: =O7*'Control Tower'!$B$58/12*(1+'Control Tower'!$B$57)^1*(1+'Control Tower'!$B$39) | P8: =P7*'Control Tower'!$B$58/12*(1+'Control Tower'!$B$57)^1*(1+'Control Tower'!$B$39) | Q8: =Q7*'Control Tower'!$B$58/12*(1+'Control Tower'!$B$57)^1*(1+'Control Tower'!$B$39) | R8: =R7*'Control Tower'!$B$58/12*(1+'Control Tower'!$B$57)^1*(1+'Control Tower'!$B$39) | S8: =S7*'Control Tower'!$B$58/12*(1+'Control Tower'!$B$57)^1*(1+'Control Tower'!$B$39) | T8: =T7*'Control Tower'!$B$58/12*(1+'Control Tower'!$B$57)^1*(1+'Control Tower'!$B$39) | U8: =U7*'Control Tower'!$B$58/12*(1+'Control Tower'!$B$57)^1*(1+'Control Tower'!$B$39) | V8: =V7*'Control Tower'!$B$58/12*(1+'Control Tower'!$B$57)^1*(1+'Control Tower'!$B$39) | ... Z8: =Z7*'Control Tower'!$B$58/12*(1+'Control Tower'!$B$57)^1*(1+'Control Tower'!$B$39) | AA8: =AA7*'Control Tower'!$B$58/12*(1+'Control Tower'!$B$57)^2*(1+'Control Tower'!$B$39) | AB8: =AB7*'Control Tower'!$B$58/12*(1+'Control Tower'!$B$57)^2*(1+'Control Tower'!$B$39) | AC8: =AC7*'Control Tower'!$B$58/12*(1+'Control Tower'!$B$57)^2*(1+'Control Tower'!$B$39) | AD8: =AD7*'Control Tower'!$B$58/12*(1+'Control Tower'!$B$57)^2*(1+'Control Tower'!$B$39) | AE8: =AE7*'Control Tower'!$B$58/12*(1+'Control Tower'!$B$57)^2*(1+'Control Tower'!$B$39) | AF8: =AF7*'Control Tower'!$B$58/12*(1+'Control Tower'!$B$57)^2*(1+'Control Tower'!$B$39) | AG8: =AG7*'Control Tower'!$B$58/12*(1+'Control Tower'!$B$57)^2*(1+'Control Tower'!$B$39) | AH8: =AH7*'Control Tower'!$B$58/12*(1+'Control Tower'!$B$57)^2*(1+'Control Tower'!$B$39) | ... AL8: =AL7*'Control Tower'!$B$58/12*(1+'Control Tower'!$B$57)^2*(1+'Control Tower'!$B$39)
A9: RN On-Call / part-time (4000-R-6-3) - FTE | C9: =MAX('Control Tower'!$B$61,ROUNDUP('Census Waterfall'!C11/60*2,0)/2) | D9: =MAX('Control Tower'!$B$61,ROUNDUP('Census Waterfall'!D11/60*2,0)/2) | E9: =MAX('Control Tower'!$B$61,ROUNDUP('Census Waterfall'!E11/60*2,0)/2) | F9: =MAX('Control Tower'!$B$61,ROUNDUP('Census Waterfall'!F11/60*2,0)/2) | G9: =MAX('Control Tower'!$B$61,ROUNDUP('Census Waterfall'!G11/60*2,0)/2) | H9: =MAX('Control Tower'!$B$61,ROUNDUP('Census Waterfall'!H11/60*2,0)/2) | I9: =MAX('Control Tower'!$B$61,ROUNDUP('Census Waterfall'!I11/60*2,0)/2) | J9: =MAX('Control Tower'!$B$61,ROUNDUP('Census Waterfall'!J11/60*2,0)/2) | ... AL9: =MAX('Control Tower'!$B$61,ROUNDUP('Census Waterfall'!AL11/60*2,0)/2)
A10: RN On-Call / part-time (4000-R-6-3) - wages | C10: =C9*'Control Tower'!$B$60/12*(1+'Control Tower'!$B$57)^0*(1+'Control Tower'!$B$39) | D10: =D9*'Control Tower'!$B$60/12*(1+'Control Tower'!$B$57)^0*(1+'Control Tower'!$B$39) | E10: =E9*'Control Tower'!$B$60/12*(1+'Control Tower'!$B$57)^0*(1+'Control Tower'!$B$39) | F10: =F9*'Control Tower'!$B$60/12*(1+'Control Tower'!$B$57)^0*(1+'Control Tower'!$B$39) | G10: =G9*'Control Tower'!$B$60/12*(1+'Control Tower'!$B$57)^0*(1+'Control Tower'!$B$39) | H10: =H9*'Control Tower'!$B$60/12*(1+'Control Tower'!$B$57)^0*(1+'Control Tower'!$B$39) | I10: =I9*'Control Tower'!$B$60/12*(1+'Control Tower'!$B$57)^0*(1+'Control Tower'!$B$39) | J10: =J9*'Control Tower'!$B$60/12*(1+'Control Tower'!$B$57)^0*(1+'Control Tower'!$B$39) | ... N10: =N9*'Control Tower'!$B$60/12*(1+'Control Tower'!$B$57)^0*(1+'Control Tower'!$B$39) | O10: =O9*'Control Tower'!$B$60/12*(1+'Control Tower'!$B$57)^1*(1+'Control Tower'!$B$39) | P10: =P9*'Control Tower'!$B$60/12*(1+'Control Tower'!$B$57)^1*(1+'Control Tower'!$B$39) | Q10: =Q9*'Control Tower'!$B$60/12*(1+'Control Tower'!$B$57)^1*(1+'Control Tower'!$B$39) | R10: =R9*'Control Tower'!$B$60/12*(1+'Control Tower'!$B$57)^1*(1+'Control Tower'!$B$39) | S10: =S9*'Control Tower'!$B$60/12*(1+'Control Tower'!$B$57)^1*(1+'Control Tower'!$B$39) | T10: =T9*'Control Tower'!$B$60/12*(1+'Control Tower'!$B$57)^1*(1+'Control Tower'!$B$39) | U10: =U9*'Control Tower'!$B$60/12*(1+'Control Tower'!$B$57)^1*(1+'Control Tower'!$B$39) | V10: =V9*'Control Tower'!$B$60/12*(1+'Control Tower'!$B$57)^1*(1+'Control Tower'!$B$39) | ... Z10: =Z9*'Control Tower'!$B$60/12*(1+'Control Tower'!$B$57)^1*(1+'Control Tower'!$B$39) | AA10: =AA9*'Control Tower'!$B$60/12*(1+'Control Tower'!$B$57)^2*(1+'Control Tower'!$B$39) | AB10: =AB9*'Control Tower'!$B$60/12*(1+'Control Tower'!$B$57)^2*(1+'Control Tower'!$B$39) | AC10: =AC9*'Control Tower'!$B$60/12*(1+'Control Tower'!$B$57)^2*(1+'Control Tower'!$B$39) | AD10: =AD9*'Control Tower'!$B$60/12*(1+'Control Tower'!$B$57)^2*(1+'Control Tower'!$B$39) | AE10: =AE9*'Control Tower'!$B$60/12*(1+'Control Tower'!$B$57)^2*(1+'Control Tower'!$B$39) | AF10: =AF9*'Control Tower'!$B$60/12*(1+'Control Tower'!$B$57)^2*(1+'Control Tower'!$B$39) | AG10: =AG9*'Control Tower'!$B$60/12*(1+'Control Tower'!$B$57)^2*(1+'Control Tower'!$B$39) | AH10: =AH9*'Control Tower'!$B$60/12*(1+'Control Tower'!$B$57)^2*(1+'Control Tower'!$B$39) | ... AL10: =AL9*'Control Tower'!$B$60/12*(1+'Control Tower'!$B$57)^2*(1+'Control Tower'!$B$39)
A11: Hospice Aide / CNA (4000-R-6-5) - FTE | C11: =MAX('Control Tower'!$B$128,ROUNDUP(IF('Control Tower'!$B$126=1,0,'Census Waterfall'!C11)/'Control Tower'!$B$63*2,0)/2) | D11: =MAX('Control Tower'!$B$128,ROUNDUP(IF('Control Tower'!$B$126=1,'Census Waterfall'!C11,'Census Waterfall'!D11)/'Control Tower'!$B$63*2,0)/2) | E11: =MAX('Control Tower'!$B$128,ROUNDUP(IF('Control Tower'!$B$126=1,'Census Waterfall'!D11,'Census Waterfall'!E11)/'Control Tower'!$B$63*2,0)/2) | F11: =MAX('Control Tower'!$B$128,ROUNDUP(IF('Control Tower'!$B$126=1,'Census Waterfall'!E11,'Census Waterfall'!F11)/'Control Tower'!$B$63*2,0)/2) | G11: =MAX('Control Tower'!$B$128,ROUNDUP(IF('Control Tower'!$B$126=1,'Census Waterfall'!F11,'Census Waterfall'!G11)/'Control Tower'!$B$63*2,0)/2) | H11: =MAX('Control Tower'!$B$128,ROUNDUP(IF('Control Tower'!$B$126=1,'Census Waterfall'!G11,'Census Waterfall'!H11)/'Control Tower'!$B$63*2,0)/2) | I11: =MAX('Control Tower'!$B$128,ROUNDUP(IF('Control Tower'!$B$126=1,'Census Waterfall'!H11,'Census Waterfall'!I11)/'Control Tower'!$B$63*2,0)/2) | J11: =MAX('Control Tower'!$B$128,ROUNDUP(IF('Control Tower'!$B$126=1,'Census Waterfall'!I11,'Census Waterfall'!J11)/'Control Tower'!$B$63*2,0)/2) | K11: =MAX('Control Tower'!$B$128,ROUNDUP(IF('Control Tower'!$B$126=1,'Census Waterfall'!J11,'Census Waterfall'!K11)/'Control Tower'!$B$63*2,0)/2) | ... AL11: =MAX('Control Tower'!$B$128,ROUNDUP(IF('Control Tower'!$B$126=1,'Census Waterfall'!AK11,'Census Waterfall'!AL11)/'Control Tower'!$B$63*2,0)/2)
A12: Hospice Aide / CNA (4000-R-6-5) - wages | C12: =C11*'Control Tower'!$B$62/12*(1+'Control Tower'!$B$57)^0*(1+'Control Tower'!$B$39) | D12: =D11*'Control Tower'!$B$62/12*(1+'Control Tower'!$B$57)^0*(1+'Control Tower'!$B$39) | E12: =E11*'Control Tower'!$B$62/12*(1+'Control Tower'!$B$57)^0*(1+'Control Tower'!$B$39) | F12: =F11*'Control Tower'!$B$62/12*(1+'Control Tower'!$B$57)^0*(1+'Control Tower'!$B$39) | G12: =G11*'Control Tower'!$B$62/12*(1+'Control Tower'!$B$57)^0*(1+'Control Tower'!$B$39) | H12: =H11*'Control Tower'!$B$62/12*(1+'Control Tower'!$B$57)^0*(1+'Control Tower'!$B$39) | I12: =I11*'Control Tower'!$B$62/12*(1+'Control Tower'!$B$57)^0*(1+'Control Tower'!$B$39) | J12: =J11*'Control Tower'!$B$62/12*(1+'Control Tower'!$B$57)^0*(1+'Control Tower'!$B$39) | ... N12: =N11*'Control Tower'!$B$62/12*(1+'Control Tower'!$B$57)^0*(1+'Control Tower'!$B$39) | O12: =O11*'Control Tower'!$B$62/12*(1+'Control Tower'!$B$57)^1*(1+'Control Tower'!$B$39) | P12: =P11*'Control Tower'!$B$62/12*(1+'Control Tower'!$B$57)^1*(1+'Control Tower'!$B$39) | Q12: =Q11*'Control Tower'!$B$62/12*(1+'Control Tower'!$B$57)^1*(1+'Control Tower'!$B$39) | R12: =R11*'Control Tower'!$B$62/12*(1+'Control Tower'!$B$57)^1*(1+'Control Tower'!$B$39) | S12: =S11*'Control Tower'!$B$62/12*(1+'Control Tower'!$B$57)^1*(1+'Control Tower'!$B$39) | T12: =T11*'Control Tower'!$B$62/12*(1+'Control Tower'!$B$57)^1*(1+'Control Tower'!$B$39) | U12: =U11*'Control Tower'!$B$62/12*(1+'Control Tower'!$B$57)^1*(1+'Control Tower'!$B$39) | V12: =V11*'Control Tower'!$B$62/12*(1+'Control Tower'!$B$57)^1*(1+'Control Tower'!$B$39) | ... Z12: =Z11*'Control Tower'!$B$62/12*(1+'Control Tower'!$B$57)^1*(1+'Control Tower'!$B$39) | AA12: =AA11*'Control Tower'!$B$62/12*(1+'Control Tower'!$B$57)^2*(1+'Control Tower'!$B$39) | AB12: =AB11*'Control Tower'!$B$62/12*(1+'Control Tower'!$B$57)^2*(1+'Control Tower'!$B$39) | AC12: =AC11*'Control Tower'!$B$62/12*(1+'Control Tower'!$B$57)^2*(1+'Control Tower'!$B$39) | AD12: =AD11*'Control Tower'!$B$62/12*(1+'Control Tower'!$B$57)^2*(1+'Control Tower'!$B$39) | AE12: =AE11*'Control Tower'!$B$62/12*(1+'Control Tower'!$B$57)^2*(1+'Control Tower'!$B$39) | AF12: =AF11*'Control Tower'!$B$62/12*(1+'Control Tower'!$B$57)^2*(1+'Control Tower'!$B$39) | AG12: =AG11*'Control Tower'!$B$62/12*(1+'Control Tower'!$B$57)^2*(1+'Control Tower'!$B$39) | AH12: =AH11*'Control Tower'!$B$62/12*(1+'Control Tower'!$B$57)^2*(1+'Control Tower'!$B$39) | ... AL12: =AL11*'Control Tower'!$B$62/12*(1+'Control Tower'!$B$57)^2*(1+'Control Tower'!$B$39)
A13: Medical Social Worker (4000-R-6-6) - FTE | C13: =ROUNDUP(IF('Control Tower'!$B$126=1,0,'Census Waterfall'!C11)/'Control Tower'!$B$65*2,0)/2 | D13: =ROUNDUP(IF('Control Tower'!$B$126=1,'Census Waterfall'!C11,'Census Waterfall'!D11)/'Control Tower'!$B$65*2,0)/2 | E13: =ROUNDUP(IF('Control Tower'!$B$126=1,'Census Waterfall'!D11,'Census Waterfall'!E11)/'Control Tower'!$B$65*2,0)/2 | F13: =ROUNDUP(IF('Control Tower'!$B$126=1,'Census Waterfall'!E11,'Census Waterfall'!F11)/'Control Tower'!$B$65*2,0)/2 | G13: =ROUNDUP(IF('Control Tower'!$B$126=1,'Census Waterfall'!F11,'Census Waterfall'!G11)/'Control Tower'!$B$65*2,0)/2 | H13: =ROUNDUP(IF('Control Tower'!$B$126=1,'Census Waterfall'!G11,'Census Waterfall'!H11)/'Control Tower'!$B$65*2,0)/2 | I13: =ROUNDUP(IF('Control Tower'!$B$126=1,'Census Waterfall'!H11,'Census Waterfall'!I11)/'Control Tower'!$B$65*2,0)/2 | J13: =ROUNDUP(IF('Control Tower'!$B$126=1,'Census Waterfall'!I11,'Census Waterfall'!J11)/'Control Tower'!$B$65*2,0)/2 | K13: =ROUNDUP(IF('Control Tower'!$B$126=1,'Census Waterfall'!J11,'Census Waterfall'!K11)/'Control Tower'!$B$65*2,0)/2 | ... AL13: =ROUNDUP(IF('Control Tower'!$B$126=1,'Census Waterfall'!AK11,'Census Waterfall'!AL11)/'Control Tower'!$B$65*2,0)/2
A14: Medical Social Worker (4000-R-6-6) - wages | C14: =C13*'Control Tower'!$B$64/12*(1+'Control Tower'!$B$57)^0*(1+'Control Tower'!$B$39) | D14: =D13*'Control Tower'!$B$64/12*(1+'Control Tower'!$B$57)^0*(1+'Control Tower'!$B$39) | E14: =E13*'Control Tower'!$B$64/12*(1+'Control Tower'!$B$57)^0*(1+'Control Tower'!$B$39) | F14: =F13*'Control Tower'!$B$64/12*(1+'Control Tower'!$B$57)^0*(1+'Control Tower'!$B$39) | G14: =G13*'Control Tower'!$B$64/12*(1+'Control Tower'!$B$57)^0*(1+'Control Tower'!$B$39) | H14: =H13*'Control Tower'!$B$64/12*(1+'Control Tower'!$B$57)^0*(1+'Control Tower'!$B$39) | I14: =I13*'Control Tower'!$B$64/12*(1+'Control Tower'!$B$57)^0*(1+'Control Tower'!$B$39) | J14: =J13*'Control Tower'!$B$64/12*(1+'Control Tower'!$B$57)^0*(1+'Control Tower'!$B$39) | ... N14: =N13*'Control Tower'!$B$64/12*(1+'Control Tower'!$B$57)^0*(1+'Control Tower'!$B$39) | O14: =O13*'Control Tower'!$B$64/12*(1+'Control Tower'!$B$57)^1*(1+'Control Tower'!$B$39) | P14: =P13*'Control Tower'!$B$64/12*(1+'Control Tower'!$B$57)^1*(1+'Control Tower'!$B$39) | Q14: =Q13*'Control Tower'!$B$64/12*(1+'Control Tower'!$B$57)^1*(1+'Control Tower'!$B$39) | R14: =R13*'Control Tower'!$B$64/12*(1+'Control Tower'!$B$57)^1*(1+'Control Tower'!$B$39) | S14: =S13*'Control Tower'!$B$64/12*(1+'Control Tower'!$B$57)^1*(1+'Control Tower'!$B$39) | T14: =T13*'Control Tower'!$B$64/12*(1+'Control Tower'!$B$57)^1*(1+'Control Tower'!$B$39) | U14: =U13*'Control Tower'!$B$64/12*(1+'Control Tower'!$B$57)^1*(1+'Control Tower'!$B$39) | V14: =V13*'Control Tower'!$B$64/12*(1+'Control Tower'!$B$57)^1*(1+'Control Tower'!$B$39) | ... Z14: =Z13*'Control Tower'!$B$64/12*(1+'Control Tower'!$B$57)^1*(1+'Control Tower'!$B$39) | AA14: =AA13*'Control Tower'!$B$64/12*(1+'Control Tower'!$B$57)^2*(1+'Control Tower'!$B$39) | AB14: =AB13*'Control Tower'!$B$64/12*(1+'Control Tower'!$B$57)^2*(1+'Control Tower'!$B$39) | AC14: =AC13*'Control Tower'!$B$64/12*(1+'Control Tower'!$B$57)^2*(1+'Control Tower'!$B$39) | AD14: =AD13*'Control Tower'!$B$64/12*(1+'Control Tower'!$B$57)^2*(1+'Control Tower'!$B$39) | AE14: =AE13*'Control Tower'!$B$64/12*(1+'Control Tower'!$B$57)^2*(1+'Control Tower'!$B$39) | AF14: =AF13*'Control Tower'!$B$64/12*(1+'Control Tower'!$B$57)^2*(1+'Control Tower'!$B$39) | AG14: =AG13*'Control Tower'!$B$64/12*(1+'Control Tower'!$B$57)^2*(1+'Control Tower'!$B$39) | AH14: =AH13*'Control Tower'!$B$64/12*(1+'Control Tower'!$B$57)^2*(1+'Control Tower'!$B$39) | ... AL14: =AL13*'Control Tower'!$B$64/12*(1+'Control Tower'!$B$57)^2*(1+'Control Tower'!$B$39)
A15: Employed clinical wages | C15: =C8+C10+C12+C14 | D15: =D8+D10+D12+D14 | E15: =E8+E10+E12+E14 | F15: =F8+F10+F12+F14 | G15: =G8+G10+G12+G14 | H15: =H8+H10+H12+H14 | I15: =I8+I10+I12+I14 | J15: =J8+J10+J12+J14 | ... AL15: =AL8+AL10+AL12+AL14
A16: PRN 1099 SUPPLEMENT (Acct 4025 - no benefits)
A17: PRN RN supplement (4025-0-6-1) | C17: =MAX(0,'Census Waterfall'!C11*'Control Tower'!$B$70-C7*'Control Tower'!$B$71)*'Control Tower'!$B$72*(1+'Control Tower'!$B$39) | D17: =MAX(0,'Census Waterfall'!D11*'Control Tower'!$B$70-D7*'Control Tower'!$B$71)*'Control Tower'!$B$72*(1+'Control Tower'!$B$39) | E17: =MAX(0,'Census Waterfall'!E11*'Control Tower'!$B$70-E7*'Control Tower'!$B$71)*'Control Tower'!$B$72*(1+'Control Tower'!$B$39) | F17: =MAX(0,'Census Waterfall'!F11*'Control Tower'!$B$70-F7*'Control Tower'!$B$71)*'Control Tower'!$B$72*(1+'Control Tower'!$B$39) | G17: =MAX(0,'Census Waterfall'!G11*'Control Tower'!$B$70-G7*'Control Tower'!$B$71)*'Control Tower'!$B$72*(1+'Control Tower'!$B$39) | H17: =MAX(0,'Census Waterfall'!H11*'Control Tower'!$B$70-H7*'Control Tower'!$B$71)*'Control Tower'!$B$72*(1+'Control Tower'!$B$39) | I17: =MAX(0,'Census Waterfall'!I11*'Control Tower'!$B$70-I7*'Control Tower'!$B$71)*'Control Tower'!$B$72*(1+'Control Tower'!$B$39) | J17: =MAX(0,'Census Waterfall'!J11*'Control Tower'!$B$70-J7*'Control Tower'!$B$71)*'Control Tower'!$B$72*(1+'Control Tower'!$B$39) | ... AL17: =MAX(0,'Census Waterfall'!AL11*'Control Tower'!$B$70-AL7*'Control Tower'!$B$71)*'Control Tower'!$B$72*(1+'Control Tower'!$B$39)
A18: PRN Aide supplement (4025-0-6-5) | C18: =MAX(0,'Census Waterfall'!C11*'Control Tower'!$B$73-C11*'Control Tower'!$B$74)*'Control Tower'!$B$75*(1+'Control Tower'!$B$39) | D18: =MAX(0,'Census Waterfall'!D11*'Control Tower'!$B$73-D11*'Control Tower'!$B$74)*'Control Tower'!$B$75*(1+'Control Tower'!$B$39) | E18: =MAX(0,'Census Waterfall'!E11*'Control Tower'!$B$73-E11*'Control Tower'!$B$74)*'Control Tower'!$B$75*(1+'Control Tower'!$B$39) | F18: =MAX(0,'Census Waterfall'!F11*'Control Tower'!$B$73-F11*'Control Tower'!$B$74)*'Control Tower'!$B$75*(1+'Control Tower'!$B$39) | G18: =MAX(0,'Census Waterfall'!G11*'Control Tower'!$B$73-G11*'Control Tower'!$B$74)*'Control Tower'!$B$75*(1+'Control Tower'!$B$39) | H18: =MAX(0,'Census Waterfall'!H11*'Control Tower'!$B$73-H11*'Control Tower'!$B$74)*'Control Tower'!$B$75*(1+'Control Tower'!$B$39) | I18: =MAX(0,'Census Waterfall'!I11*'Control Tower'!$B$73-I11*'Control Tower'!$B$74)*'Control Tower'!$B$75*(1+'Control Tower'!$B$39) | J18: =MAX(0,'Census Waterfall'!J11*'Control Tower'!$B$73-J11*'Control Tower'!$B$74)*'Control Tower'!$B$75*(1+'Control Tower'!$B$39) | ... AL18: =MAX(0,'Census Waterfall'!AL11*'Control Tower'!$B$73-AL11*'Control Tower'!$B$74)*'Control Tower'!$B$75*(1+'Control Tower'!$B$39)
A19: PRN MSW supplement (4025-0-6-6) | C19: =MAX(0,'Census Waterfall'!C11*'Control Tower'!$B$76-C13*'Control Tower'!$B$77)*'Control Tower'!$B$78*(1+'Control Tower'!$B$39) | D19: =MAX(0,'Census Waterfall'!D11*'Control Tower'!$B$76-D13*'Control Tower'!$B$77)*'Control Tower'!$B$78*(1+'Control Tower'!$B$39) | E19: =MAX(0,'Census Waterfall'!E11*'Control Tower'!$B$76-E13*'Control Tower'!$B$77)*'Control Tower'!$B$78*(1+'Control Tower'!$B$39) | F19: =MAX(0,'Census Waterfall'!F11*'Control Tower'!$B$76-F13*'Control Tower'!$B$77)*'Control Tower'!$B$78*(1+'Control Tower'!$B$39) | G19: =MAX(0,'Census Waterfall'!G11*'Control Tower'!$B$76-G13*'Control Tower'!$B$77)*'Control Tower'!$B$78*(1+'Control Tower'!$B$39) | H19: =MAX(0,'Census Waterfall'!H11*'Control Tower'!$B$76-H13*'Control Tower'!$B$77)*'Control Tower'!$B$78*(1+'Control Tower'!$B$39) | I19: =MAX(0,'Census Waterfall'!I11*'Control Tower'!$B$76-I13*'Control Tower'!$B$77)*'Control Tower'!$B$78*(1+'Control Tower'!$B$39) | J19: =MAX(0,'Census Waterfall'!J11*'Control Tower'!$B$76-J13*'Control Tower'!$B$77)*'Control Tower'!$B$78*(1+'Control Tower'!$B$39) | ... AL19: =MAX(0,'Census Waterfall'!AL11*'Control Tower'!$B$76-AL13*'Control Tower'!$B$77)*'Control Tower'!$B$78*(1+'Control Tower'!$B$39)
A20: PRN Chaplain above base (4025-0-6-7) | C20: =MAX(0,'Census Waterfall'!C11*'Control Tower'!$B$79-'Control Tower'!$B$80)*'Control Tower'!$B$81*(1+'Control Tower'!$B$39) | D20: =MAX(0,'Census Waterfall'!D11*'Control Tower'!$B$79-'Control Tower'!$B$80)*'Control Tower'!$B$81*(1+'Control Tower'!$B$39) | E20: =MAX(0,'Census Waterfall'!E11*'Control Tower'!$B$79-'Control Tower'!$B$80)*'Control Tower'!$B$81*(1+'Control Tower'!$B$39) | F20: =MAX(0,'Census Waterfall'!F11*'Control Tower'!$B$79-'Control Tower'!$B$80)*'Control Tower'!$B$81*(1+'Control Tower'!$B$39) | G20: =MAX(0,'Census Waterfall'!G11*'Control Tower'!$B$79-'Control Tower'!$B$80)*'Control Tower'!$B$81*(1+'Control Tower'!$B$39) | H20: =MAX(0,'Census Waterfall'!H11*'Control Tower'!$B$79-'Control Tower'!$B$80)*'Control Tower'!$B$81*(1+'Control Tower'!$B$39) | I20: =MAX(0,'Census Waterfall'!I11*'Control Tower'!$B$79-'Control Tower'!$B$80)*'Control Tower'!$B$81*(1+'Control Tower'!$B$39) | J20: =MAX(0,'Census Waterfall'!J11*'Control Tower'!$B$79-'Control Tower'!$B$80)*'Control Tower'!$B$81*(1+'Control Tower'!$B$39) | ... AL20: =MAX(0,'Census Waterfall'!AL11*'Control Tower'!$B$79-'Control Tower'!$B$80)*'Control Tower'!$B$81*(1+'Control Tower'!$B$39)
A21: Total PRN supplement | C21: =C17+C18+C19+C20 | D21: =D17+D18+D19+D20 | E21: =E17+E18+E19+E20 | F21: =F17+F18+F19+F20 | G21: =G17+G18+G19+G20 | H21: =H17+H18+H19+H20 | I21: =I17+I18+I19+I20 | J21: =J17+J18+J19+J20 | ... AL21: =AL17+AL18+AL19+AL20
A22: CONTRACT & INDIRECT (leadership per Control Tower start months)
A23: Chaplain base contract (4020-0-6-7) | C23: ='Control Tower'!$B$66*(1+'Control Tower'!$B$57)^0 | D23: ='Control Tower'!$B$66*(1+'Control Tower'!$B$57)^0 | E23: ='Control Tower'!$B$66*(1+'Control Tower'!$B$57)^0 | F23: ='Control Tower'!$B$66*(1+'Control Tower'!$B$57)^0 | G23: ='Control Tower'!$B$66*(1+'Control Tower'!$B$57)^0 | H23: ='Control Tower'!$B$66*(1+'Control Tower'!$B$57)^0 | I23: ='Control Tower'!$B$66*(1+'Control Tower'!$B$57)^0 | J23: ='Control Tower'!$B$66*(1+'Control Tower'!$B$57)^0 | ... N23: ='Control Tower'!$B$66*(1+'Control Tower'!$B$57)^0 | O23: ='Control Tower'!$B$66*(1+'Control Tower'!$B$57)^1 | P23: ='Control Tower'!$B$66*(1+'Control Tower'!$B$57)^1 | Q23: ='Control Tower'!$B$66*(1+'Control Tower'!$B$57)^1 | R23: ='Control Tower'!$B$66*(1+'Control Tower'!$B$57)^1 | S23: ='Control Tower'!$B$66*(1+'Control Tower'!$B$57)^1 | T23: ='Control Tower'!$B$66*(1+'Control Tower'!$B$57)^1 | U23: ='Control Tower'!$B$66*(1+'Control Tower'!$B$57)^1 | V23: ='Control Tower'!$B$66*(1+'Control Tower'!$B$57)^1 | ... Z23: ='Control Tower'!$B$66*(1+'Control Tower'!$B$57)^1 | AA23: ='Control Tower'!$B$66*(1+'Control Tower'!$B$57)^2 | AB23: ='Control Tower'!$B$66*(1+'Control Tower'!$B$57)^2 | AC23: ='Control Tower'!$B$66*(1+'Control Tower'!$B$57)^2 | AD23: ='Control Tower'!$B$66*(1+'Control Tower'!$B$57)^2 | AE23: ='Control Tower'!$B$66*(1+'Control Tower'!$B$57)^2 | AF23: ='Control Tower'!$B$66*(1+'Control Tower'!$B$57)^2 | AG23: ='Control Tower'!$B$66*(1+'Control Tower'!$B$57)^2 | AH23: ='Control Tower'!$B$66*(1+'Control Tower'!$B$57)^2 | ... AL23: ='Control Tower'!$B$66*(1+'Control Tower'!$B$57)^2
A24: Medical director (4020-0-6-M) | C24: =IF(1>='Control Tower'!$B$68,'Control Tower'!$B$67*(1+'Control Tower'!$B$57)^0,0) | D24: =IF(2>='Control Tower'!$B$68,'Control Tower'!$B$67*(1+'Control Tower'!$B$57)^0,0) | E24: =IF(3>='Control Tower'!$B$68,'Control Tower'!$B$67*(1+'Control Tower'!$B$57)^0,0) | F24: =IF(4>='Control Tower'!$B$68,'Control Tower'!$B$67*(1+'Control Tower'!$B$57)^0,0) | G24: =IF(5>='Control Tower'!$B$68,'Control Tower'!$B$67*(1+'Control Tower'!$B$57)^0,0) | H24: =IF(6>='Control Tower'!$B$68,'Control Tower'!$B$67*(1+'Control Tower'!$B$57)^0,0) | I24: =IF(7>='Control Tower'!$B$68,'Control Tower'!$B$67*(1+'Control Tower'!$B$57)^0,0) | J24: =IF(8>='Control Tower'!$B$68,'Control Tower'!$B$67*(1+'Control Tower'!$B$57)^0,0) | K24: =IF(9>='Control Tower'!$B$68,'Control Tower'!$B$67*(1+'Control Tower'!$B$57)^0,0) | L24: =IF(10>='Control Tower'!$B$68,'Control Tower'!$B$67*(1+'Control Tower'!$B$57)^0,0) | M24: =IF(11>='Control Tower'!$B$68,'Control Tower'!$B$67*(1+'Control Tower'!$B$57)^0,0) | N24: =IF(12>='Control Tower'!$B$68,'Control Tower'!$B$67*(1+'Control Tower'!$B$57)^0,0) | O24: =IF(13>='Control Tower'!$B$68,'Control Tower'!$B$67*(1+'Control Tower'!$B$57)^1,0) | P24: =IF(14>='Control Tower'!$B$68,'Control Tower'!$B$67*(1+'Control Tower'!$B$57)^1,0) | Q24: =IF(15>='Control Tower'!$B$68,'Control Tower'!$B$67*(1+'Control Tower'!$B$57)^1,0) | R24: =IF(16>='Control Tower'!$B$68,'Control Tower'!$B$67*(1+'Control Tower'!$B$57)^1,0) | S24: =IF(17>='Control Tower'!$B$68,'Control Tower'!$B$67*(1+'Control Tower'!$B$57)^1,0) | T24: =IF(18>='Control Tower'!$B$68,'Control Tower'!$B$67*(1+'Control Tower'!$B$57)^1,0) | U24: =IF(19>='Control Tower'!$B$68,'Control Tower'!$B$67*(1+'Control Tower'!$B$57)^1,0) | V24: =IF(20>='Control Tower'!$B$68,'Control Tower'!$B$67*(1+'Control Tower'!$B$57)^1,0) | W24: =IF(21>='Control Tower'!$B$68,'Control Tower'!$B$67*(1+'Control Tower'!$B$57)^1,0) | X24: =IF(22>='Control Tower'!$B$68,'Control Tower'!$B$67*(1+'Control Tower'!$B$57)^1,0) | Y24: =IF(23>='Control Tower'!$B$68,'Control Tower'!$B$67*(1+'Control Tower'!$B$57)^1,0) | Z24: =IF(24>='Control Tower'!$B$68,'Control Tower'!$B$67*(1+'Control Tower'!$B$57)^1,0) | AA24: =IF(25>='Control Tower'!$B$68,'Control Tower'!$B$67*(1+'Control Tower'!$B$57)^2,0) | AB24: =IF(26>='Control Tower'!$B$68,'Control Tower'!$B$67*(1+'Control Tower'!$B$57)^2,0) | AC24: =IF(27>='Control Tower'!$B$68,'Control Tower'!$B$67*(1+'Control Tower'!$B$57)^2,0) | AD24: =IF(28>='Control Tower'!$B$68,'Control Tower'!$B$67*(1+'Control Tower'!$B$57)^2,0) | AE24: =IF(29>='Control Tower'!$B$68,'Control Tower'!$B$67*(1+'Control Tower'!$B$57)^2,0) | AF24: =IF(30>='Control Tower'!$B$68,'Control Tower'!$B$67*(1+'Control Tower'!$B$57)^2,0) | AG24: =IF(31>='Control Tower'!$B$68,'Control Tower'!$B$67*(1+'Control Tower'!$B$57)^2,0) | AH24: =IF(32>='Control Tower'!$B$68,'Control Tower'!$B$67*(1+'Control Tower'!$B$57)^2,0) | AI24: =IF(33>='Control Tower'!$B$68,'Control Tower'!$B$67*(1+'Control Tower'!$B$57)^2,0) | AJ24: =IF(34>='Control Tower'!$B$68,'Control Tower'!$B$67*(1+'Control Tower'!$B$57)^2,0) | AK24: =IF(35>='Control Tower'!$B$68,'Control Tower'!$B$67*(1+'Control Tower'!$B$57)^2,0) | AL24: =IF(36>='Control Tower'!$B$68,'Control Tower'!$B$67*(1+'Control Tower'!$B$57)^2,0)
A25: Silas Shelton - Executive Director (4000-0-A-0) | C25: =IF(1>='Control Tower'!$B$84,'Control Tower'!$B$83/12*(1+'Control Tower'!$B$57)^0*(1+'Control Tower'!$B$39),0) | D25: =IF(2>='Control Tower'!$B$84,'Control Tower'!$B$83/12*(1+'Control Tower'!$B$57)^0*(1+'Control Tower'!$B$39),0) | E25: =IF(3>='Control Tower'!$B$84,'Control Tower'!$B$83/12*(1+'Control Tower'!$B$57)^0*(1+'Control Tower'!$B$39),0) | F25: =IF(4>='Control Tower'!$B$84,'Control Tower'!$B$83/12*(1+'Control Tower'!$B$57)^0*(1+'Control Tower'!$B$39),0) | G25: =IF(5>='Control Tower'!$B$84,'Control Tower'!$B$83/12*(1+'Control Tower'!$B$57)^0*(1+'Control Tower'!$B$39),0) | H25: =IF(6>='Control Tower'!$B$84,'Control Tower'!$B$83/12*(1+'Control Tower'!$B$57)^0*(1+'Control Tower'!$B$39),0) | I25: =IF(7>='Control Tower'!$B$84,'Control Tower'!$B$83/12*(1+'Control Tower'!$B$57)^0*(1+'Control Tower'!$B$39),0) | J25: =IF(8>='Control Tower'!$B$84,'Control Tower'!$B$83/12*(1+'Control Tower'!$B$57)^0*(1+'Control Tower'!$B$39),0) | K25: =IF(9>='Control Tower'!$B$84,'Control Tower'!$B$83/12*(1+'Control Tower'!$B$57)^0*(1+'Control Tower'!$B$39),0) | L25: =IF(10>='Control Tower'!$B$84,'Control Tower'!$B$83/12*(1+'Control Tower'!$B$57)^0*(1+'Control Tower'!$B$39),0) | M25: =IF(11>='Control Tower'!$B$84,'Control Tower'!$B$83/12*(1+'Control Tower'!$B$57)^0*(1+'Control Tower'!$B$39),0) | N25: =IF(12>='Control Tower'!$B$84,'Control Tower'!$B$83/12*(1+'Control Tower'!$B$57)^0*(1+'Control Tower'!$B$39),0) | O25: =IF(13>='Control Tower'!$B$84,'Control Tower'!$B$83/12*(1+'Control Tower'!$B$57)^1*(1+'Control Tower'!$B$39),0) | P25: =IF(14>='Control Tower'!$B$84,'Control Tower'!$B$83/12*(1+'Control Tower'!$B$57)^1*(1+'Control Tower'!$B$39),0) | Q25: =IF(15>='Control Tower'!$B$84,'Control Tower'!$B$83/12*(1+'Control Tower'!$B$57)^1*(1+'Control Tower'!$B$39),0) | R25: =IF(16>='Control Tower'!$B$84,'Control Tower'!$B$83/12*(1+'Control Tower'!$B$57)^1*(1+'Control Tower'!$B$39),0) | S25: =IF(17>='Control Tower'!$B$84,'Control Tower'!$B$83/12*(1+'Control Tower'!$B$57)^1*(1+'Control Tower'!$B$39),0) | T25: =IF(18>='Control Tower'!$B$84,'Control Tower'!$B$83/12*(1+'Control Tower'!$B$57)^1*(1+'Control Tower'!$B$39),0) | U25: =IF(19>='Control Tower'!$B$84,'Control Tower'!$B$83/12*(1+'Control Tower'!$B$57)^1*(1+'Control Tower'!$B$39),0) | V25: =IF(20>='Control Tower'!$B$84,'Control Tower'!$B$83/12*(1+'Control Tower'!$B$57)^1*(1+'Control Tower'!$B$39),0) | W25: =IF(21>='Control Tower'!$B$84,'Control Tower'!$B$83/12*(1+'Control Tower'!$B$57)^1*(1+'Control Tower'!$B$39),0) | X25: =IF(22>='Control Tower'!$B$84,'Control Tower'!$B$83/12*(1+'Control Tower'!$B$57)^1*(1+'Control Tower'!$B$39),0) | Y25: =IF(23>='Control Tower'!$B$84,'Control Tower'!$B$83/12*(1+'Control Tower'!$B$57)^1*(1+'Control Tower'!$B$39),0) | Z25: =IF(24>='Control Tower'!$B$84,'Control Tower'!$B$83/12*(1+'Control Tower'!$B$57)^1*(1+'Control Tower'!$B$39),0) | AA25: =IF(25>='Control Tower'!$B$84,'Control Tower'!$B$83/12*(1+'Control Tower'!$B$57)^2*(1+'Control Tower'!$B$39),0) | AB25: =IF(26>='Control Tower'!$B$84,'Control Tower'!$B$83/12*(1+'Control Tower'!$B$57)^2*(1+'Control Tower'!$B$39),0) | AC25: =IF(27>='Control Tower'!$B$84,'Control Tower'!$B$83/12*(1+'Control Tower'!$B$57)^2*(1+'Control Tower'!$B$39),0) | AD25: =IF(28>='Control Tower'!$B$84,'Control Tower'!$B$83/12*(1+'Control Tower'!$B$57)^2*(1+'Control Tower'!$B$39),0) | AE25: =IF(29>='Control Tower'!$B$84,'Control Tower'!$B$83/12*(1+'Control Tower'!$B$57)^2*(1+'Control Tower'!$B$39),0) | AF25: =IF(30>='Control Tower'!$B$84,'Control Tower'!$B$83/12*(1+'Control Tower'!$B$57)^2*(1+'Control Tower'!$B$39),0) | AG25: =IF(31>='Control Tower'!$B$84,'Control Tower'!$B$83/12*(1+'Control Tower'!$B$57)^2*(1+'Control Tower'!$B$39),0) | AH25: =IF(32>='Control Tower'!$B$84,'Control Tower'!$B$83/12*(1+'Control Tower'!$B$57)^2*(1+'Control Tower'!$B$39),0) | AI25: =IF(33>='Control Tower'!$B$84,'Control Tower'!$B$83/12*(1+'Control Tower'!$B$57)^2*(1+'Control Tower'!$B$39),0) | AJ25: =IF(34>='Control Tower'!$B$84,'Control Tower'!$B$83/12*(1+'Control Tower'!$B$57)^2*(1+'Control Tower'!$B$39),0) | AK25: =IF(35>='Control Tower'!$B$84,'Control Tower'!$B$83/12*(1+'Control Tower'!$B$57)^2*(1+'Control Tower'!$B$39),0) | AL25: =IF(36>='Control Tower'!$B$84,'Control Tower'!$B$83/12*(1+'Control Tower'!$B$57)^2*(1+'Control Tower'!$B$39),0)
A26: Dana Davenport - Director of Nursing (4000-0-C-0) | C26: =IF(1>='Control Tower'!$B$86,'Control Tower'!$B$85/12*(1+'Control Tower'!$B$57)^0*(1+'Control Tower'!$B$39),0) | D26: =IF(2>='Control Tower'!$B$86,'Control Tower'!$B$85/12*(1+'Control Tower'!$B$57)^0*(1+'Control Tower'!$B$39),0) | E26: =IF(3>='Control Tower'!$B$86,'Control Tower'!$B$85/12*(1+'Control Tower'!$B$57)^0*(1+'Control Tower'!$B$39),0) | F26: =IF(4>='Control Tower'!$B$86,'Control Tower'!$B$85/12*(1+'Control Tower'!$B$57)^0*(1+'Control Tower'!$B$39),0) | G26: =IF(5>='Control Tower'!$B$86,'Control Tower'!$B$85/12*(1+'Control Tower'!$B$57)^0*(1+'Control Tower'!$B$39),0) | H26: =IF(6>='Control Tower'!$B$86,'Control Tower'!$B$85/12*(1+'Control Tower'!$B$57)^0*(1+'Control Tower'!$B$39),0) | I26: =IF(7>='Control Tower'!$B$86,'Control Tower'!$B$85/12*(1+'Control Tower'!$B$57)^0*(1+'Control Tower'!$B$39),0) | J26: =IF(8>='Control Tower'!$B$86,'Control Tower'!$B$85/12*(1+'Control Tower'!$B$57)^0*(1+'Control Tower'!$B$39),0) | K26: =IF(9>='Control Tower'!$B$86,'Control Tower'!$B$85/12*(1+'Control Tower'!$B$57)^0*(1+'Control Tower'!$B$39),0) | L26: =IF(10>='Control Tower'!$B$86,'Control Tower'!$B$85/12*(1+'Control Tower'!$B$57)^0*(1+'Control Tower'!$B$39),0) | M26: =IF(11>='Control Tower'!$B$86,'Control Tower'!$B$85/12*(1+'Control Tower'!$B$57)^0*(1+'Control Tower'!$B$39),0) | N26: =IF(12>='Control Tower'!$B$86,'Control Tower'!$B$85/12*(1+'Control Tower'!$B$57)^0*(1+'Control Tower'!$B$39),0) | O26: =IF(13>='Control Tower'!$B$86,'Control Tower'!$B$85/12*(1+'Control Tower'!$B$57)^1*(1+'Control Tower'!$B$39),0) | P26: =IF(14>='Control Tower'!$B$86,'Control Tower'!$B$85/12*(1+'Control Tower'!$B$57)^1*(1+'Control Tower'!$B$39),0) | Q26: =IF(15>='Control Tower'!$B$86,'Control Tower'!$B$85/12*(1+'Control Tower'!$B$57)^1*(1+'Control Tower'!$B$39),0) | R26: =IF(16>='Control Tower'!$B$86,'Control Tower'!$B$85/12*(1+'Control Tower'!$B$57)^1*(1+'Control Tower'!$B$39),0) | S26: =IF(17>='Control Tower'!$B$86,'Control Tower'!$B$85/12*(1+'Control Tower'!$B$57)^1*(1+'Control Tower'!$B$39),0) | T26: =IF(18>='Control Tower'!$B$86,'Control Tower'!$B$85/12*(1+'Control Tower'!$B$57)^1*(1+'Control Tower'!$B$39),0) | U26: =IF(19>='Control Tower'!$B$86,'Control Tower'!$B$85/12*(1+'Control Tower'!$B$57)^1*(1+'Control Tower'!$B$39),0) | V26: =IF(20>='Control Tower'!$B$86,'Control Tower'!$B$85/12*(1+'Control Tower'!$B$57)^1*(1+'Control Tower'!$B$39),0) | W26: =IF(21>='Control Tower'!$B$86,'Control Tower'!$B$85/12*(1+'Control Tower'!$B$57)^1*(1+'Control Tower'!$B$39),0) | X26: =IF(22>='Control Tower'!$B$86,'Control Tower'!$B$85/12*(1+'Control Tower'!$B$57)^1*(1+'Control Tower'!$B$39),0) | Y26: =IF(23>='Control Tower'!$B$86,'Control Tower'!$B$85/12*(1+'Control Tower'!$B$57)^1*(1+'Control Tower'!$B$39),0) | Z26: =IF(24>='Control Tower'!$B$86,'Control Tower'!$B$85/12*(1+'Control Tower'!$B$57)^1*(1+'Control Tower'!$B$39),0) | AA26: =IF(25>='Control Tower'!$B$86,'Control Tower'!$B$85/12*(1+'Control Tower'!$B$57)^2*(1+'Control Tower'!$B$39),0) | AB26: =IF(26>='Control Tower'!$B$86,'Control Tower'!$B$85/12*(1+'Control Tower'!$B$57)^2*(1+'Control Tower'!$B$39),0) | AC26: =IF(27>='Control Tower'!$B$86,'Control Tower'!$B$85/12*(1+'Control Tower'!$B$57)^2*(1+'Control Tower'!$B$39),0) | AD26: =IF(28>='Control Tower'!$B$86,'Control Tower'!$B$85/12*(1+'Control Tower'!$B$57)^2*(1+'Control Tower'!$B$39),0) | AE26: =IF(29>='Control Tower'!$B$86,'Control Tower'!$B$85/12*(1+'Control Tower'!$B$57)^2*(1+'Control Tower'!$B$39),0) | AF26: =IF(30>='Control Tower'!$B$86,'Control Tower'!$B$85/12*(1+'Control Tower'!$B$57)^2*(1+'Control Tower'!$B$39),0) | AG26: =IF(31>='Control Tower'!$B$86,'Control Tower'!$B$85/12*(1+'Control Tower'!$B$57)^2*(1+'Control Tower'!$B$39),0) | AH26: =IF(32>='Control Tower'!$B$86,'Control Tower'!$B$85/12*(1+'Control Tower'!$B$57)^2*(1+'Control Tower'!$B$39),0) | AI26: =IF(33>='Control Tower'!$B$86,'Control Tower'!$B$85/12*(1+'Control Tower'!$B$57)^2*(1+'Control Tower'!$B$39),0) | AJ26: =IF(34>='Control Tower'!$B$86,'Control Tower'!$B$85/12*(1+'Control Tower'!$B$57)^2*(1+'Control Tower'!$B$39),0) | AK26: =IF(35>='Control Tower'!$B$86,'Control Tower'!$B$85/12*(1+'Control Tower'!$B$57)^2*(1+'Control Tower'!$B$39),0) | AL26: =IF(36>='Control Tower'!$B$86,'Control Tower'!$B$85/12*(1+'Control Tower'!$B$57)^2*(1+'Control Tower'!$B$39),0)
A27: Brad Woodard - Director of Sales (4000-0-M-0) | C27: =IF(1>='Control Tower'!$B$88,'Control Tower'!$B$87/12*(1+'Control Tower'!$B$57)^0*(1+'Control Tower'!$B$39),0) | D27: =IF(2>='Control Tower'!$B$88,'Control Tower'!$B$87/12*(1+'Control Tower'!$B$57)^0*(1+'Control Tower'!$B$39),0) | E27: =IF(3>='Control Tower'!$B$88,'Control Tower'!$B$87/12*(1+'Control Tower'!$B$57)^0*(1+'Control Tower'!$B$39),0) | F27: =IF(4>='Control Tower'!$B$88,'Control Tower'!$B$87/12*(1+'Control Tower'!$B$57)^0*(1+'Control Tower'!$B$39),0) | G27: =IF(5>='Control Tower'!$B$88,'Control Tower'!$B$87/12*(1+'Control Tower'!$B$57)^0*(1+'Control Tower'!$B$39),0) | H27: =IF(6>='Control Tower'!$B$88,'Control Tower'!$B$87/12*(1+'Control Tower'!$B$57)^0*(1+'Control Tower'!$B$39),0) | I27: =IF(7>='Control Tower'!$B$88,'Control Tower'!$B$87/12*(1+'Control Tower'!$B$57)^0*(1+'Control Tower'!$B$39),0) | J27: =IF(8>='Control Tower'!$B$88,'Control Tower'!$B$87/12*(1+'Control Tower'!$B$57)^0*(1+'Control Tower'!$B$39),0) | K27: =IF(9>='Control Tower'!$B$88,'Control Tower'!$B$87/12*(1+'Control Tower'!$B$57)^0*(1+'Control Tower'!$B$39),0) | L27: =IF(10>='Control Tower'!$B$88,'Control Tower'!$B$87/12*(1+'Control Tower'!$B$57)^0*(1+'Control Tower'!$B$39),0) | M27: =IF(11>='Control Tower'!$B$88,'Control Tower'!$B$87/12*(1+'Control Tower'!$B$57)^0*(1+'Control Tower'!$B$39),0) | N27: =IF(12>='Control Tower'!$B$88,'Control Tower'!$B$87/12*(1+'Control Tower'!$B$57)^0*(1+'Control Tower'!$B$39),0) | O27: =IF(13>='Control Tower'!$B$88,'Control Tower'!$B$87/12*(1+'Control Tower'!$B$57)^1*(1+'Control Tower'!$B$39),0) | P27: =IF(14>='Control Tower'!$B$88,'Control Tower'!$B$87/12*(1+'Control Tower'!$B$57)^1*(1+'Control Tower'!$B$39),0) | Q27: =IF(15>='Control Tower'!$B$88,'Control Tower'!$B$87/12*(1+'Control Tower'!$B$57)^1*(1+'Control Tower'!$B$39),0) | R27: =IF(16>='Control Tower'!$B$88,'Control Tower'!$B$87/12*(1+'Control Tower'!$B$57)^1*(1+'Control Tower'!$B$39),0) | S27: =IF(17>='Control Tower'!$B$88,'Control Tower'!$B$87/12*(1+'Control Tower'!$B$57)^1*(1+'Control Tower'!$B$39),0) | T27: =IF(18>='Control Tower'!$B$88,'Control Tower'!$B$87/12*(1+'Control Tower'!$B$57)^1*(1+'Control Tower'!$B$39),0) | U27: =IF(19>='Control Tower'!$B$88,'Control Tower'!$B$87/12*(1+'Control Tower'!$B$57)^1*(1+'Control Tower'!$B$39),0) | V27: =IF(20>='Control Tower'!$B$88,'Control Tower'!$B$87/12*(1+'Control Tower'!$B$57)^1*(1+'Control Tower'!$B$39),0) | W27: =IF(21>='Control Tower'!$B$88,'Control Tower'!$B$87/12*(1+'Control Tower'!$B$57)^1*(1+'Control Tower'!$B$39),0) | X27: =IF(22>='Control Tower'!$B$88,'Control Tower'!$B$87/12*(1+'Control Tower'!$B$57)^1*(1+'Control Tower'!$B$39),0) | Y27: =IF(23>='Control Tower'!$B$88,'Control Tower'!$B$87/12*(1+'Control Tower'!$B$57)^1*(1+'Control Tower'!$B$39),0) | Z27: =IF(24>='Control Tower'!$B$88,'Control Tower'!$B$87/12*(1+'Control Tower'!$B$57)^1*(1+'Control Tower'!$B$39),0) | AA27: =IF(25>='Control Tower'!$B$88,'Control Tower'!$B$87/12*(1+'Control Tower'!$B$57)^2*(1+'Control Tower'!$B$39),0) | AB27: =IF(26>='Control Tower'!$B$88,'Control Tower'!$B$87/12*(1+'Control Tower'!$B$57)^2*(1+'Control Tower'!$B$39),0) | AC27: =IF(27>='Control Tower'!$B$88,'Control Tower'!$B$87/12*(1+'Control Tower'!$B$57)^2*(1+'Control Tower'!$B$39),0) | AD27: =IF(28>='Control Tower'!$B$88,'Control Tower'!$B$87/12*(1+'Control Tower'!$B$57)^2*(1+'Control Tower'!$B$39),0) | AE27: =IF(29>='Control Tower'!$B$88,'Control Tower'!$B$87/12*(1+'Control Tower'!$B$57)^2*(1+'Control Tower'!$B$39),0) | AF27: =IF(30>='Control Tower'!$B$88,'Control Tower'!$B$87/12*(1+'Control Tower'!$B$57)^2*(1+'Control Tower'!$B$39),0) | AG27: =IF(31>='Control Tower'!$B$88,'Control Tower'!$B$87/12*(1+'Control Tower'!$B$57)^2*(1+'Control Tower'!$B$39),0) | AH27: =IF(32>='Control Tower'!$B$88,'Control Tower'!$B$87/12*(1+'Control Tower'!$B$57)^2*(1+'Control Tower'!$B$39),0) | AI27: =IF(33>='Control Tower'!$B$88,'Control Tower'!$B$87/12*(1+'Control Tower'!$B$57)^2*(1+'Control Tower'!$B$39),0) | AJ27: =IF(34>='Control Tower'!$B$88,'Control Tower'!$B$87/12*(1+'Control Tower'!$B$57)^2*(1+'Control Tower'!$B$39),0) | AK27: =IF(35>='Control Tower'!$B$88,'Control Tower'!$B$87/12*(1+'Control Tower'!$B$57)^2*(1+'Control Tower'!$B$39),0) | AL27: =IF(36>='Control Tower'!$B$88,'Control Tower'!$B$87/12*(1+'Control Tower'!$B$57)^2*(1+'Control Tower'!$B$39),0)
A28: Rhonda Smith - ADON / Intake (4000-0-I-1) | C28: =IF(1>='Control Tower'!$B$90,'Control Tower'!$B$89/12*(1+'Control Tower'!$B$57)^0*(1+'Control Tower'!$B$39),0) | D28: =IF(2>='Control Tower'!$B$90,'Control Tower'!$B$89/12*(1+'Control Tower'!$B$57)^0*(1+'Control Tower'!$B$39),0) | E28: =IF(3>='Control Tower'!$B$90,'Control Tower'!$B$89/12*(1+'Control Tower'!$B$57)^0*(1+'Control Tower'!$B$39),0) | F28: =IF(4>='Control Tower'!$B$90,'Control Tower'!$B$89/12*(1+'Control Tower'!$B$57)^0*(1+'Control Tower'!$B$39),0) | G28: =IF(5>='Control Tower'!$B$90,'Control Tower'!$B$89/12*(1+'Control Tower'!$B$57)^0*(1+'Control Tower'!$B$39),0) | H28: =IF(6>='Control Tower'!$B$90,'Control Tower'!$B$89/12*(1+'Control Tower'!$B$57)^0*(1+'Control Tower'!$B$39),0) | I28: =IF(7>='Control Tower'!$B$90,'Control Tower'!$B$89/12*(1+'Control Tower'!$B$57)^0*(1+'Control Tower'!$B$39),0) | J28: =IF(8>='Control Tower'!$B$90,'Control Tower'!$B$89/12*(1+'Control Tower'!$B$57)^0*(1+'Control Tower'!$B$39),0) | K28: =IF(9>='Control Tower'!$B$90,'Control Tower'!$B$89/12*(1+'Control Tower'!$B$57)^0*(1+'Control Tower'!$B$39),0) | L28: =IF(10>='Control Tower'!$B$90,'Control Tower'!$B$89/12*(1+'Control Tower'!$B$57)^0*(1+'Control Tower'!$B$39),0) | M28: =IF(11>='Control Tower'!$B$90,'Control Tower'!$B$89/12*(1+'Control Tower'!$B$57)^0*(1+'Control Tower'!$B$39),0) | N28: =IF(12>='Control Tower'!$B$90,'Control Tower'!$B$89/12*(1+'Control Tower'!$B$57)^0*(1+'Control Tower'!$B$39),0) | O28: =IF(13>='Control Tower'!$B$90,'Control Tower'!$B$89/12*(1+'Control Tower'!$B$57)^1*(1+'Control Tower'!$B$39),0) | P28: =IF(14>='Control Tower'!$B$90,'Control Tower'!$B$89/12*(1+'Control Tower'!$B$57)^1*(1+'Control Tower'!$B$39),0) | Q28: =IF(15>='Control Tower'!$B$90,'Control Tower'!$B$89/12*(1+'Control Tower'!$B$57)^1*(1+'Control Tower'!$B$39),0) | R28: =IF(16>='Control Tower'!$B$90,'Control Tower'!$B$89/12*(1+'Control Tower'!$B$57)^1*(1+'Control Tower'!$B$39),0) | S28: =IF(17>='Control Tower'!$B$90,'Control Tower'!$B$89/12*(1+'Control Tower'!$B$57)^1*(1+'Control Tower'!$B$39),0) | T28: =IF(18>='Control Tower'!$B$90,'Control Tower'!$B$89/12*(1+'Control Tower'!$B$57)^1*(1+'Control Tower'!$B$39),0) | U28: =IF(19>='Control Tower'!$B$90,'Control Tower'!$B$89/12*(1+'Control Tower'!$B$57)^1*(1+'Control Tower'!$B$39),0) | V28: =IF(20>='Control Tower'!$B$90,'Control Tower'!$B$89/12*(1+'Control Tower'!$B$57)^1*(1+'Control Tower'!$B$39),0) | W28: =IF(21>='Control Tower'!$B$90,'Control Tower'!$B$89/12*(1+'Control Tower'!$B$57)^1*(1+'Control Tower'!$B$39),0) | X28: =IF(22>='Control Tower'!$B$90,'Control Tower'!$B$89/12*(1+'Control Tower'!$B$57)^1*(1+'Control Tower'!$B$39),0) | Y28: =IF(23>='Control Tower'!$B$90,'Control Tower'!$B$89/12*(1+'Control Tower'!$B$57)^1*(1+'Control Tower'!$B$39),0) | Z28: =IF(24>='Control Tower'!$B$90,'Control Tower'!$B$89/12*(1+'Control Tower'!$B$57)^1*(1+'Control Tower'!$B$39),0) | AA28: =IF(25>='Control Tower'!$B$90,'Control Tower'!$B$89/12*(1+'Control Tower'!$B$57)^2*(1+'Control Tower'!$B$39),0) | AB28: =IF(26>='Control Tower'!$B$90,'Control Tower'!$B$89/12*(1+'Control Tower'!$B$57)^2*(1+'Control Tower'!$B$39),0) | AC28: =IF(27>='Control Tower'!$B$90,'Control Tower'!$B$89/12*(1+'Control Tower'!$B$57)^2*(1+'Control Tower'!$B$39),0) | AD28: =IF(28>='Control Tower'!$B$90,'Control Tower'!$B$89/12*(1+'Control Tower'!$B$57)^2*(1+'Control Tower'!$B$39),0) | AE28: =IF(29>='Control Tower'!$B$90,'Control Tower'!$B$89/12*(1+'Control Tower'!$B$57)^2*(1+'Control Tower'!$B$39),0) | AF28: =IF(30>='Control Tower'!$B$90,'Control Tower'!$B$89/12*(1+'Control Tower'!$B$57)^2*(1+'Control Tower'!$B$39),0) | AG28: =IF(31>='Control Tower'!$B$90,'Control Tower'!$B$89/12*(1+'Control Tower'!$B$57)^2*(1+'Control Tower'!$B$39),0) | AH28: =IF(32>='Control Tower'!$B$90,'Control Tower'!$B$89/12*(1+'Control Tower'!$B$57)^2*(1+'Control Tower'!$B$39),0) | AI28: =IF(33>='Control Tower'!$B$90,'Control Tower'!$B$89/12*(1+'Control Tower'!$B$57)^2*(1+'Control Tower'!$B$39),0) | AJ28: =IF(34>='Control Tower'!$B$90,'Control Tower'!$B$89/12*(1+'Control Tower'!$B$57)^2*(1+'Control Tower'!$B$39),0) | AK28: =IF(35>='Control Tower'!$B$90,'Control Tower'!$B$89/12*(1+'Control Tower'!$B$57)^2*(1+'Control Tower'!$B$39),0) | AL28: =IF(36>='Control Tower'!$B$90,'Control Tower'!$B$89/12*(1+'Control Tower'!$B$57)^2*(1+'Control Tower'!$B$39),0)
A29: Volunteer + Bereavement Coordinator (4000-0-A-0) | C29: =IF(1>='Control Tower'!$B$92,'Control Tower'!$B$91/12*(1+'Control Tower'!$B$57)^0*(1+'Control Tower'!$B$39),0) | D29: =IF(2>='Control Tower'!$B$92,'Control Tower'!$B$91/12*(1+'Control Tower'!$B$57)^0*(1+'Control Tower'!$B$39),0) | E29: =IF(3>='Control Tower'!$B$92,'Control Tower'!$B$91/12*(1+'Control Tower'!$B$57)^0*(1+'Control Tower'!$B$39),0) | F29: =IF(4>='Control Tower'!$B$92,'Control Tower'!$B$91/12*(1+'Control Tower'!$B$57)^0*(1+'Control Tower'!$B$39),0) | G29: =IF(5>='Control Tower'!$B$92,'Control Tower'!$B$91/12*(1+'Control Tower'!$B$57)^0*(1+'Control Tower'!$B$39),0) | H29: =IF(6>='Control Tower'!$B$92,'Control Tower'!$B$91/12*(1+'Control Tower'!$B$57)^0*(1+'Control Tower'!$B$39),0) | I29: =IF(7>='Control Tower'!$B$92,'Control Tower'!$B$91/12*(1+'Control Tower'!$B$57)^0*(1+'Control Tower'!$B$39),0) | J29: =IF(8>='Control Tower'!$B$92,'Control Tower'!$B$91/12*(1+'Control Tower'!$B$57)^0*(1+'Control Tower'!$B$39),0) | K29: =IF(9>='Control Tower'!$B$92,'Control Tower'!$B$91/12*(1+'Control Tower'!$B$57)^0*(1+'Control Tower'!$B$39),0) | L29: =IF(10>='Control Tower'!$B$92,'Control Tower'!$B$91/12*(1+'Control Tower'!$B$57)^0*(1+'Control Tower'!$B$39),0) | M29: =IF(11>='Control Tower'!$B$92,'Control Tower'!$B$91/12*(1+'Control Tower'!$B$57)^0*(1+'Control Tower'!$B$39),0) | N29: =IF(12>='Control Tower'!$B$92,'Control Tower'!$B$91/12*(1+'Control Tower'!$B$57)^0*(1+'Control Tower'!$B$39),0) | O29: =IF(13>='Control Tower'!$B$92,'Control Tower'!$B$91/12*(1+'Control Tower'!$B$57)^1*(1+'Control Tower'!$B$39),0) | P29: =IF(14>='Control Tower'!$B$92,'Control Tower'!$B$91/12*(1+'Control Tower'!$B$57)^1*(1+'Control Tower'!$B$39),0) | Q29: =IF(15>='Control Tower'!$B$92,'Control Tower'!$B$91/12*(1+'Control Tower'!$B$57)^1*(1+'Control Tower'!$B$39),0) | R29: =IF(16>='Control Tower'!$B$92,'Control Tower'!$B$91/12*(1+'Control Tower'!$B$57)^1*(1+'Control Tower'!$B$39),0) | S29: =IF(17>='Control Tower'!$B$92,'Control Tower'!$B$91/12*(1+'Control Tower'!$B$57)^1*(1+'Control Tower'!$B$39),0) | T29: =IF(18>='Control Tower'!$B$92,'Control Tower'!$B$91/12*(1+'Control Tower'!$B$57)^1*(1+'Control Tower'!$B$39),0) | U29: =IF(19>='Control Tower'!$B$92,'Control Tower'!$B$91/12*(1+'Control Tower'!$B$57)^1*(1+'Control Tower'!$B$39),0) | V29: =IF(20>='Control Tower'!$B$92,'Control Tower'!$B$91/12*(1+'Control Tower'!$B$57)^1*(1+'Control Tower'!$B$39),0) | W29: =IF(21>='Control Tower'!$B$92,'Control Tower'!$B$91/12*(1+'Control Tower'!$B$57)^1*(1+'Control Tower'!$B$39),0) | X29: =IF(22>='Control Tower'!$B$92,'Control Tower'!$B$91/12*(1+'Control Tower'!$B$57)^1*(1+'Control Tower'!$B$39),0) | Y29: =IF(23>='Control Tower'!$B$92,'Control Tower'!$B$91/12*(1+'Control Tower'!$B$57)^1*(1+'Control Tower'!$B$39),0) | Z29: =IF(24>='Control Tower'!$B$92,'Control Tower'!$B$91/12*(1+'Control Tower'!$B$57)^1*(1+'Control Tower'!$B$39),0) | AA29: =IF(25>='Control Tower'!$B$92,'Control Tower'!$B$91/12*(1+'Control Tower'!$B$57)^2*(1+'Control Tower'!$B$39),0) | AB29: =IF(26>='Control Tower'!$B$92,'Control Tower'!$B$91/12*(1+'Control Tower'!$B$57)^2*(1+'Control Tower'!$B$39),0) | AC29: =IF(27>='Control Tower'!$B$92,'Control Tower'!$B$91/12*(1+'Control Tower'!$B$57)^2*(1+'Control Tower'!$B$39),0) | AD29: =IF(28>='Control Tower'!$B$92,'Control Tower'!$B$91/12*(1+'Control Tower'!$B$57)^2*(1+'Control Tower'!$B$39),0) | AE29: =IF(29>='Control Tower'!$B$92,'Control Tower'!$B$91/12*(1+'Control Tower'!$B$57)^2*(1+'Control Tower'!$B$39),0) | AF29: =IF(30>='Control Tower'!$B$92,'Control Tower'!$B$91/12*(1+'Control Tower'!$B$57)^2*(1+'Control Tower'!$B$39),0) | AG29: =IF(31>='Control Tower'!$B$92,'Control Tower'!$B$91/12*(1+'Control Tower'!$B$57)^2*(1+'Control Tower'!$B$39),0) | AH29: =IF(32>='Control Tower'!$B$92,'Control Tower'!$B$91/12*(1+'Control Tower'!$B$57)^2*(1+'Control Tower'!$B$39),0) | AI29: =IF(33>='Control Tower'!$B$92,'Control Tower'!$B$91/12*(1+'Control Tower'!$B$57)^2*(1+'Control Tower'!$B$39),0) | AJ29: =IF(34>='Control Tower'!$B$92,'Control Tower'!$B$91/12*(1+'Control Tower'!$B$57)^2*(1+'Control Tower'!$B$39),0) | AK29: =IF(35>='Control Tower'!$B$92,'Control Tower'!$B$91/12*(1+'Control Tower'!$B$57)^2*(1+'Control Tower'!$B$39),0) | AL29: =IF(36>='Control Tower'!$B$92,'Control Tower'!$B$91/12*(1+'Control Tower'!$B$57)^2*(1+'Control Tower'!$B$39),0)
A30: QAPI / Compliance 0.5 FTE (begins at ADC threshold) | C30: =IF('Census Waterfall'!C11>='Control Tower'!$B$94,0.5*'Control Tower'!$B$93/12*(1+'Control Tower'!$B$57)^0*(1+'Control Tower'!$B$39),0) | D30: =IF('Census Waterfall'!D11>='Control Tower'!$B$94,0.5*'Control Tower'!$B$93/12*(1+'Control Tower'!$B$57)^0*(1+'Control Tower'!$B$39),0) | E30: =IF('Census Waterfall'!E11>='Control Tower'!$B$94,0.5*'Control Tower'!$B$93/12*(1+'Control Tower'!$B$57)^0*(1+'Control Tower'!$B$39),0) | F30: =IF('Census Waterfall'!F11>='Control Tower'!$B$94,0.5*'Control Tower'!$B$93/12*(1+'Control Tower'!$B$57)^0*(1+'Control Tower'!$B$39),0) | G30: =IF('Census Waterfall'!G11>='Control Tower'!$B$94,0.5*'Control Tower'!$B$93/12*(1+'Control Tower'!$B$57)^0*(1+'Control Tower'!$B$39),0) | H30: =IF('Census Waterfall'!H11>='Control Tower'!$B$94,0.5*'Control Tower'!$B$93/12*(1+'Control Tower'!$B$57)^0*(1+'Control Tower'!$B$39),0) | I30: =IF('Census Waterfall'!I11>='Control Tower'!$B$94,0.5*'Control Tower'!$B$93/12*(1+'Control Tower'!$B$57)^0*(1+'Control Tower'!$B$39),0) | J30: =IF('Census Waterfall'!J11>='Control Tower'!$B$94,0.5*'Control Tower'!$B$93/12*(1+'Control Tower'!$B$57)^0*(1+'Control Tower'!$B$39),0) | ... N30: =IF('Census Waterfall'!N11>='Control Tower'!$B$94,0.5*'Control Tower'!$B$93/12*(1+'Control Tower'!$B$57)^0*(1+'Control Tower'!$B$39),0) | O30: =IF('Census Waterfall'!O11>='Control Tower'!$B$94,0.5*'Control Tower'!$B$93/12*(1+'Control Tower'!$B$57)^1*(1+'Control Tower'!$B$39),0) | P30: =IF('Census Waterfall'!P11>='Control Tower'!$B$94,0.5*'Control Tower'!$B$93/12*(1+'Control Tower'!$B$57)^1*(1+'Control Tower'!$B$39),0) | Q30: =IF('Census Waterfall'!Q11>='Control Tower'!$B$94,0.5*'Control Tower'!$B$93/12*(1+'Control Tower'!$B$57)^1*(1+'Control Tower'!$B$39),0) | R30: =IF('Census Waterfall'!R11>='Control Tower'!$B$94,0.5*'Control Tower'!$B$93/12*(1+'Control Tower'!$B$57)^1*(1+'Control Tower'!$B$39),0) | S30: =IF('Census Waterfall'!S11>='Control Tower'!$B$94,0.5*'Control Tower'!$B$93/12*(1+'Control Tower'!$B$57)^1*(1+'Control Tower'!$B$39),0) | T30: =IF('Census Waterfall'!T11>='Control Tower'!$B$94,0.5*'Control Tower'!$B$93/12*(1+'Control Tower'!$B$57)^1*(1+'Control Tower'!$B$39),0) | U30: =IF('Census Waterfall'!U11>='Control Tower'!$B$94,0.5*'Control Tower'!$B$93/12*(1+'Control Tower'!$B$57)^1*(1+'Control Tower'!$B$39),0) | V30: =IF('Census Waterfall'!V11>='Control Tower'!$B$94,0.5*'Control Tower'!$B$93/12*(1+'Control Tower'!$B$57)^1*(1+'Control Tower'!$B$39),0) | ... Z30: =IF('Census Waterfall'!Z11>='Control Tower'!$B$94,0.5*'Control Tower'!$B$93/12*(1+'Control Tower'!$B$57)^1*(1+'Control Tower'!$B$39),0) | AA30: =IF('Census Waterfall'!AA11>='Control Tower'!$B$94,0.5*'Control Tower'!$B$93/12*(1+'Control Tower'!$B$57)^2*(1+'Control Tower'!$B$39),0) | AB30: =IF('Census Waterfall'!AB11>='Control Tower'!$B$94,0.5*'Control Tower'!$B$93/12*(1+'Control Tower'!$B$57)^2*(1+'Control Tower'!$B$39),0) | AC30: =IF('Census Waterfall'!AC11>='Control Tower'!$B$94,0.5*'Control Tower'!$B$93/12*(1+'Control Tower'!$B$57)^2*(1+'Control Tower'!$B$39),0) | AD30: =IF('Census Waterfall'!AD11>='Control Tower'!$B$94,0.5*'Control Tower'!$B$93/12*(1+'Control Tower'!$B$57)^2*(1+'Control Tower'!$B$39),0) | AE30: =IF('Census Waterfall'!AE11>='Control Tower'!$B$94,0.5*'Control Tower'!$B$93/12*(1+'Control Tower'!$B$57)^2*(1+'Control Tower'!$B$39),0) | AF30: =IF('Census Waterfall'!AF11>='Control Tower'!$B$94,0.5*'Control Tower'!$B$93/12*(1+'Control Tower'!$B$57)^2*(1+'Control Tower'!$B$39),0) | AG30: =IF('Census Waterfall'!AG11>='Control Tower'!$B$94,0.5*'Control Tower'!$B$93/12*(1+'Control Tower'!$B$57)^2*(1+'Control Tower'!$B$39),0) | AH30: =IF('Census Waterfall'!AH11>='Control Tower'!$B$94,0.5*'Control Tower'!$B$93/12*(1+'Control Tower'!$B$57)^2*(1+'Control Tower'!$B$39),0) | ... AL30: =IF('Census Waterfall'!AL11>='Control Tower'!$B$94,0.5*'Control Tower'!$B$93/12*(1+'Control Tower'!$B$57)^2*(1+'Control Tower'!$B$39),0)
A31: Indirect employed wages | C31: =C25+C26+C27+C28+C29+C30 | D31: =D25+D26+D27+D28+D29+D30 | E31: =E25+E26+E27+E28+E29+E30 | F31: =F25+F26+F27+F28+F29+F30 | G31: =G25+G26+G27+G28+G29+G30 | H31: =H25+H26+H27+H28+H29+H30 | I31: =I25+I26+I27+I28+I29+I30 | J31: =J25+J26+J27+J28+J29+J30 | ... AL31: =AL25+AL26+AL27+AL28+AL29+AL30
A32: LOADS (employed wages only - Acct 4110/4120/4130)
A33: Clinical benefits load | C33: =C15*'Control Tower'!$B$55 | D33: =D15*'Control Tower'!$B$55 | E33: =E15*'Control Tower'!$B$55 | F33: =F15*'Control Tower'!$B$55 | G33: =G15*'Control Tower'!$B$55 | H33: =H15*'Control Tower'!$B$55 | I33: =I15*'Control Tower'!$B$55 | J33: =J15*'Control Tower'!$B$55 | ... AL33: =AL15*'Control Tower'!$B$55
A34: Clinical workers comp | C34: =C15*'Control Tower'!$B$56 | D34: =D15*'Control Tower'!$B$56 | E34: =E15*'Control Tower'!$B$56 | F34: =F15*'Control Tower'!$B$56 | G34: =G15*'Control Tower'!$B$56 | H34: =H15*'Control Tower'!$B$56 | I34: =I15*'Control Tower'!$B$56 | J34: =J15*'Control Tower'!$B$56 | ... AL34: =AL15*'Control Tower'!$B$56
A35: Indirect benefits load | C35: =C31*'Control Tower'!$B$55 | D35: =D31*'Control Tower'!$B$55 | E35: =E31*'Control Tower'!$B$55 | F35: =F31*'Control Tower'!$B$55 | G35: =G31*'Control Tower'!$B$55 | H35: =H31*'Control Tower'!$B$55 | I35: =I31*'Control Tower'!$B$55 | J35: =J31*'Control Tower'!$B$55 | ... AL35: =AL31*'Control Tower'!$B$55
A36: Indirect workers comp | C36: =C31*'Control Tower'!$B$56 | D36: =D31*'Control Tower'!$B$56 | E36: =E31*'Control Tower'!$B$56 | F36: =F31*'Control Tower'!$B$56 | G36: =G31*'Control Tower'!$B$56 | H36: =H31*'Control Tower'!$B$56 | I36: =I31*'Control Tower'!$B$56 | J36: =J31*'Control Tower'!$B$56 | ... AL36: =AL31*'Control Tower'!$B$56
A37: TOTAL CLINICAL LABOR (employed + loads + contract + PRN) | C37: =C15+C33+C34+C23+C24+C21 | D37: =D15+D33+D34+D23+D24+D21 | E37: =E15+E33+E34+E23+E24+E21 | F37: =F15+F33+F34+F23+F24+F21 | G37: =G15+G33+G34+G23+G24+G21 | H37: =H15+H33+H34+H23+H24+H21 | I37: =I15+I33+I34+I23+I24+I21 | J37: =J15+J33+J34+J23+J24+J21 | ... AL37: =AL15+AL33+AL34+AL23+AL24+AL21
A38: TOTAL INDIRECT LABOR (employed + loads) | C38: =C31+C35+C36 | D38: =D31+D35+D36 | E38: =E31+E35+E36 | F38: =F31+F35+F36 | G38: =G31+G35+G36 | H38: =H31+H35+H36 | I38: =I31+I35+I36 | J38: =J31+J35+J36 | ... AL38: =AL31+AL35+AL36
A39: Total employed payroll cash (wages + loads) | C39: =C15+C31+C33+C34+C35+C36 | D39: =D15+D31+D33+D34+D35+D36 | E39: =E15+E31+E33+E34+E35+E36 | F39: =F15+F31+F33+F34+F35+F36 | G39: =G15+G31+G33+G34+G35+G36 | H39: =H15+H31+H33+H34+H35+H36 | I39: =I15+I31+I33+I34+I35+I36 | J39: =J15+J31+J33+J34+J35+J36 | ... AL39: =AL15+AL31+AL33+AL34+AL35+AL36
A40: MANAGEMENT SALARY DEFERRAL (owner-operator wages accrue until break-even census; P&L expense unchanged)
A41: Deferral active this month (1 = wages accruing) | C41: =IF(AND('Control Tower'!$B$123=1,0<'Control Tower'!$B$124,1<'Control Tower'!$B$125),1,0) | D41: =IF(AND('Control Tower'!$B$123=1,'Census Waterfall'!C11<'Control Tower'!$B$124,2<'Control Tower'!$B$125),1,0) | E41: =IF(AND('Control Tower'!$B$123=1,'Census Waterfall'!D11<'Control Tower'!$B$124,3<'Control Tower'!$B$125),1,0) | F41: =IF(AND('Control Tower'!$B$123=1,'Census Waterfall'!E11<'Control Tower'!$B$124,4<'Control Tower'!$B$125),1,0) | G41: =IF(AND('Control Tower'!$B$123=1,'Census Waterfall'!F11<'Control Tower'!$B$124,5<'Control Tower'!$B$125),1,0) | H41: =IF(AND('Control Tower'!$B$123=1,'Census Waterfall'!G11<'Control Tower'!$B$124,6<'Control Tower'!$B$125),1,0) | I41: =IF(AND('Control Tower'!$B$123=1,'Census Waterfall'!H11<'Control Tower'!$B$124,7<'Control Tower'!$B$125),1,0) | J41: =IF(AND('Control Tower'!$B$123=1,'Census Waterfall'!I11<'Control Tower'!$B$124,8<'Control Tower'!$B$125),1,0) | K41: =IF(AND('Control Tower'!$B$123=1,'Census Waterfall'!J11<'Control Tower'!$B$124,9<'Control Tower'!$B$125),1,0) | L41: =IF(AND('Control Tower'!$B$123=1,'Census Waterfall'!K11<'Control Tower'!$B$124,10<'Control Tower'!$B$125),1,0) | M41: =IF(AND('Control Tower'!$B$123=1,'Census Waterfall'!L11<'Control Tower'!$B$124,11<'Control Tower'!$B$125),1,0) | N41: =IF(AND('Control Tower'!$B$123=1,'Census Waterfall'!M11<'Control Tower'!$B$124,12<'Control Tower'!$B$125),1,0) | O41: =IF(AND('Control Tower'!$B$123=1,'Census Waterfall'!N11<'Control Tower'!$B$124,13<'Control Tower'!$B$125),1,0) | P41: =IF(AND('Control Tower'!$B$123=1,'Census Waterfall'!O11<'Control Tower'!$B$124,14<'Control Tower'!$B$125),1,0) | Q41: =IF(AND('Control Tower'!$B$123=1,'Census Waterfall'!P11<'Control Tower'!$B$124,15<'Control Tower'!$B$125),1,0) | R41: =IF(AND('Control Tower'!$B$123=1,'Census Waterfall'!Q11<'Control Tower'!$B$124,16<'Control Tower'!$B$125),1,0) | S41: =IF(AND('Control Tower'!$B$123=1,'Census Waterfall'!R11<'Control Tower'!$B$124,17<'Control Tower'!$B$125),1,0) | T41: =IF(AND('Control Tower'!$B$123=1,'Census Waterfall'!S11<'Control Tower'!$B$124,18<'Control Tower'!$B$125),1,0) | U41: =IF(AND('Control Tower'!$B$123=1,'Census Waterfall'!T11<'Control Tower'!$B$124,19<'Control Tower'!$B$125),1,0) | V41: =IF(AND('Control Tower'!$B$123=1,'Census Waterfall'!U11<'Control Tower'!$B$124,20<'Control Tower'!$B$125),1,0) | W41: =IF(AND('Control Tower'!$B$123=1,'Census Waterfall'!V11<'Control Tower'!$B$124,21<'Control Tower'!$B$125),1,0) | X41: =IF(AND('Control Tower'!$B$123=1,'Census Waterfall'!W11<'Control Tower'!$B$124,22<'Control Tower'!$B$125),1,0) | Y41: =IF(AND('Control Tower'!$B$123=1,'Census Waterfall'!X11<'Control Tower'!$B$124,23<'Control Tower'!$B$125),1,0) | Z41: =IF(AND('Control Tower'!$B$123=1,'Census Waterfall'!Y11<'Control Tower'!$B$124,24<'Control Tower'!$B$125),1,0) | AA41: =IF(AND('Control Tower'!$B$123=1,'Census Waterfall'!Z11<'Control Tower'!$B$124,25<'Control Tower'!$B$125),1,0) | AB41: =IF(AND('Control Tower'!$B$123=1,'Census Waterfall'!AA11<'Control Tower'!$B$124,26<'Control Tower'!$B$125),1,0) | AC41: =IF(AND('Control Tower'!$B$123=1,'Census Waterfall'!AB11<'Control Tower'!$B$124,27<'Control Tower'!$B$125),1,0) | AD41: =IF(AND('Control Tower'!$B$123=1,'Census Waterfall'!AC11<'Control Tower'!$B$124,28<'Control Tower'!$B$125),1,0) | AE41: =IF(AND('Control Tower'!$B$123=1,'Census Waterfall'!AD11<'Control Tower'!$B$124,29<'Control Tower'!$B$125),1,0) | AF41: =IF(AND('Control Tower'!$B$123=1,'Census Waterfall'!AE11<'Control Tower'!$B$124,30<'Control Tower'!$B$125),1,0) | AG41: =IF(AND('Control Tower'!$B$123=1,'Census Waterfall'!AF11<'Control Tower'!$B$124,31<'Control Tower'!$B$125),1,0) | AH41: =IF(AND('Control Tower'!$B$123=1,'Census Waterfall'!AG11<'Control Tower'!$B$124,32<'Control Tower'!$B$125),1,0) | AI41: =IF(AND('Control Tower'!$B$123=1,'Census Waterfall'!AH11<'Control Tower'!$B$124,33<'Control Tower'!$B$125),1,0) | AJ41: =IF(AND('Control Tower'!$B$123=1,'Census Waterfall'!AI11<'Control Tower'!$B$124,34<'Control Tower'!$B$125),1,0) | AK41: =IF(AND('Control Tower'!$B$123=1,'Census Waterfall'!AJ11<'Control Tower'!$B$124,35<'Control Tower'!$B$125),1,0) | AL41: =IF(AND('Control Tower'!$B$123=1,'Census Waterfall'!AK11<'Control Tower'!$B$124,36<'Control Tower'!$B$125),1,0)
A42: Owner wages deferred (accrued, not paid) | C42: =C41*(C25+C26+C27) | D42: =D41*(D25+D26+D27) | E42: =E41*(E25+E26+E27) | F42: =F41*(F25+F26+F27) | G42: =G41*(G25+G26+G27) | H42: =H41*(H25+H26+H27) | I42: =I41*(I25+I26+I27) | J42: =J41*(J25+J26+J27) | ... AL42: =AL41*(AL25+AL26+AL27)
A43: Deferred-comp repayment (cash out at repay month) | C43: =IF(1='Control Tower'!$B$125,SUM($C$42:C42),0) | D43: =IF(2='Control Tower'!$B$125,SUM($C$42:D42),0) | E43: =IF(3='Control Tower'!$B$125,SUM($C$42:E42),0) | F43: =IF(4='Control Tower'!$B$125,SUM($C$42:F42),0) | G43: =IF(5='Control Tower'!$B$125,SUM($C$42:G42),0) | H43: =IF(6='Control Tower'!$B$125,SUM($C$42:H42),0) | I43: =IF(7='Control Tower'!$B$125,SUM($C$42:I42),0) | J43: =IF(8='Control Tower'!$B$125,SUM($C$42:J42),0) | K43: =IF(9='Control Tower'!$B$125,SUM($C$42:K42),0) | L43: =IF(10='Control Tower'!$B$125,SUM($C$42:L42),0) | M43: =IF(11='Control Tower'!$B$125,SUM($C$42:M42),0) | N43: =IF(12='Control Tower'!$B$125,SUM($C$42:N42),0) | O43: =IF(13='Control Tower'!$B$125,SUM($C$42:O42),0) | P43: =IF(14='Control Tower'!$B$125,SUM($C$42:P42),0) | Q43: =IF(15='Control Tower'!$B$125,SUM($C$42:Q42),0) | R43: =IF(16='Control Tower'!$B$125,SUM($C$42:R42),0) | S43: =IF(17='Control Tower'!$B$125,SUM($C$42:S42),0) | T43: =IF(18='Control Tower'!$B$125,SUM($C$42:T42),0) | U43: =IF(19='Control Tower'!$B$125,SUM($C$42:U42),0) | V43: =IF(20='Control Tower'!$B$125,SUM($C$42:V42),0) | W43: =IF(21='Control Tower'!$B$125,SUM($C$42:W42),0) | X43: =IF(22='Control Tower'!$B$125,SUM($C$42:X42),0) | Y43: =IF(23='Control Tower'!$B$125,SUM($C$42:Y42),0) | Z43: =IF(24='Control Tower'!$B$125,SUM($C$42:Z42),0) | AA43: =IF(25='Control Tower'!$B$125,SUM($C$42:AA42),0) | AB43: =IF(26='Control Tower'!$B$125,SUM($C$42:AB42),0) | AC43: =IF(27='Control Tower'!$B$125,SUM($C$42:AC42),0) | AD43: =IF(28='Control Tower'!$B$125,SUM($C$42:AD42),0) | AE43: =IF(29='Control Tower'!$B$125,SUM($C$42:AE42),0) | AF43: =IF(30='Control Tower'!$B$125,SUM($C$42:AF42),0) | AG43: =IF(31='Control Tower'!$B$125,SUM($C$42:AG42),0) | AH43: =IF(32='Control Tower'!$B$125,SUM($C$42:AH42),0) | AI43: =IF(33='Control Tower'!$B$125,SUM($C$42:AI42),0) | AJ43: =IF(34='Control Tower'!$B$125,SUM($C$42:AJ42),0) | AK43: =IF(35='Control Tower'!$B$125,SUM($C$42:AK42),0) | AL43: =IF(36='Control Tower'!$B$125,SUM($C$42:AL42),0)
A44: Deferred-comp balance (end) | C44: =SUM($C$42:C42)-SUM($C$43:C43) | D44: =SUM($C$42:D42)-SUM($C$43:D43) | E44: =SUM($C$42:E42)-SUM($C$43:E43) | F44: =SUM($C$42:F42)-SUM($C$43:F43) | G44: =SUM($C$42:G42)-SUM($C$43:G43) | H44: =SUM($C$42:H42)-SUM($C$43:H43) | I44: =SUM($C$42:I42)-SUM($C$43:I43) | J44: =SUM($C$42:J42)-SUM($C$43:J43) | ... AL44: =SUM($C$42:AL42)-SUM($C$43:AL43)

Sheet Operating Budget
A1: AZALEA HOSPICE - REFUGE OPERATING MODEL
A2: OPERATING BUDGET - direct patient care per patient-day; facility (stepped rent); G&A at the greater of fixed or % of revenue.
A4: Month # | C4: 1 | D4: 2 | E4: 3 | F4: 4 | G4: 5 | H4: 6 | I4: 7 | J4: 8 | K4: 9 | L4: 10 | M4: 11 | N4: 12 | O4: 13 | P4: 14 | Q4: 15 | R4: 16 | S4: 17 | T4: 18 | U4: 19 | V4: 20 | W4: 21 | X4: 22 | Y4: 23 | Z4: 24 | AA4: 25 | AB4: 26 | AC4: 27 | AD4: 28 | AE4: 29 | AF4: 30 | AG4: 31 | AH4: 32 | AI4: 33 | AJ4: 34 | AK4: 35 | AL4: 36
C5: Jul-26 | D5: Aug-26 | E5: Sep-26 | F5: Oct-26 | G5: Nov-26 | H5: Dec-26 | I5: Jan-27 | J5: Feb-27 | K5: Mar-27 | L5: Apr-27 | M5: May-27 | N5: Jun-27 | O5: Jul-27 | P5: Aug-27 | Q5: Sep-27 | R5: Oct-27 | S5: Nov-27 | T5: Dec-27 | U5: Jan-28 | V5: Feb-28 | W5: Mar-28 | X5: Apr-28 | Y5: May-28 | Z5: Jun-28 | AA5: Jul-28 | AB5: Aug-28 | AC5: Sep-28 | AD5: Oct-28 | AE5: Nov-28 | AF5: Dec-28 | AG5: Jan-29 | AH5: Feb-29 | AI5: Mar-29 | AJ5: Apr-29 | AK5: May-29 | AL5: Jun-29
A6: DIRECT PATIENT CARE (contracted variable - Acct 5050-5120)
A7: DME rental (5050) | C7: ='Census Waterfall'!C12*'Control Tower'!$B$96 | D7: ='Census Waterfall'!D12*'Control Tower'!$B$96 | E7: ='Census Waterfall'!E12*'Control Tower'!$B$96 | F7: ='Census Waterfall'!F12*'Control Tower'!$B$96 | G7: ='Census Waterfall'!G12*'Control Tower'!$B$96 | H7: ='Census Waterfall'!H12*'Control Tower'!$B$96 | I7: ='Census Waterfall'!I12*'Control Tower'!$B$96 | J7: ='Census Waterfall'!J12*'Control Tower'!$B$96 | ... AL7: ='Census Waterfall'!AL12*'Control Tower'!$B$96
A8: Medications (5100) | C8: ='Census Waterfall'!C12*'Control Tower'!$B$97 | D8: ='Census Waterfall'!D12*'Control Tower'!$B$97 | E8: ='Census Waterfall'!E12*'Control Tower'!$B$97 | F8: ='Census Waterfall'!F12*'Control Tower'!$B$97 | G8: ='Census Waterfall'!G12*'Control Tower'!$B$97 | H8: ='Census Waterfall'!H12*'Control Tower'!$B$97 | I8: ='Census Waterfall'!I12*'Control Tower'!$B$97 | J8: ='Census Waterfall'!J12*'Control Tower'!$B$97 | ... AL8: ='Census Waterfall'!AL12*'Control Tower'!$B$97
A9: Medical supplies (5090) | C9: ='Census Waterfall'!C12*'Control Tower'!$B$98 | D9: ='Census Waterfall'!D12*'Control Tower'!$B$98 | E9: ='Census Waterfall'!E12*'Control Tower'!$B$98 | F9: ='Census Waterfall'!F12*'Control Tower'!$B$98 | G9: ='Census Waterfall'!G12*'Control Tower'!$B$98 | H9: ='Census Waterfall'!H12*'Control Tower'!$B$98 | I9: ='Census Waterfall'!I12*'Control Tower'!$B$98 | J9: ='Census Waterfall'!J12*'Control Tower'!$B$98 | ... AL9: ='Census Waterfall'!AL12*'Control Tower'!$B$98
A10: Clinical mileage (5110) | C10: ='Census Waterfall'!C12*'Control Tower'!$B$99 | D10: ='Census Waterfall'!D12*'Control Tower'!$B$99 | E10: ='Census Waterfall'!E12*'Control Tower'!$B$99 | F10: ='Census Waterfall'!F12*'Control Tower'!$B$99 | G10: ='Census Waterfall'!G12*'Control Tower'!$B$99 | H10: ='Census Waterfall'!H12*'Control Tower'!$B$99 | I10: ='Census Waterfall'!I12*'Control Tower'!$B$99 | J10: ='Census Waterfall'!J12*'Control Tower'!$B$99 | ... AL10: ='Census Waterfall'!AL12*'Control Tower'!$B$99
A11: Mobile communications - clinical (5120) | C11: ='Control Tower'!$B$100*(1+'Control Tower'!$B$49)^0 | D11: ='Control Tower'!$B$100*(1+'Control Tower'!$B$49)^0 | E11: ='Control Tower'!$B$100*(1+'Control Tower'!$B$49)^0 | F11: ='Control Tower'!$B$100*(1+'Control Tower'!$B$49)^0 | G11: ='Control Tower'!$B$100*(1+'Control Tower'!$B$49)^0 | H11: ='Control Tower'!$B$100*(1+'Control Tower'!$B$49)^0 | I11: ='Control Tower'!$B$100*(1+'Control Tower'!$B$49)^0 | J11: ='Control Tower'!$B$100*(1+'Control Tower'!$B$49)^0 | ... N11: ='Control Tower'!$B$100*(1+'Control Tower'!$B$49)^0 | O11: ='Control Tower'!$B$100*(1+'Control Tower'!$B$49)^1 | P11: ='Control Tower'!$B$100*(1+'Control Tower'!$B$49)^1 | Q11: ='Control Tower'!$B$100*(1+'Control Tower'!$B$49)^1 | R11: ='Control Tower'!$B$100*(1+'Control Tower'!$B$49)^1 | S11: ='Control Tower'!$B$100*(1+'Control Tower'!$B$49)^1 | T11: ='Control Tower'!$B$100*(1+'Control Tower'!$B$49)^1 | U11: ='Control Tower'!$B$100*(1+'Control Tower'!$B$49)^1 | V11: ='Control Tower'!$B$100*(1+'Control Tower'!$B$49)^1 | ... Z11: ='Control Tower'!$B$100*(1+'Control Tower'!$B$49)^1 | AA11: ='Control Tower'!$B$100*(1+'Control Tower'!$B$49)^2 | AB11: ='Control Tower'!$B$100*(1+'Control Tower'!$B$49)^2 | AC11: ='Control Tower'!$B$100*(1+'Control Tower'!$B$49)^2 | AD11: ='Control Tower'!$B$100*(1+'Control Tower'!$B$49)^2 | AE11: ='Control Tower'!$B$100*(1+'Control Tower'!$B$49)^2 | AF11: ='Control Tower'!$B$100*(1+'Control Tower'!$B$49)^2 | AG11: ='Control Tower'!$B$100*(1+'Control Tower'!$B$49)^2 | AH11: ='Control Tower'!$B$100*(1+'Control Tower'!$B$49)^2 | ... AL11: ='Control Tower'!$B$100*(1+'Control Tower'!$B$49)^2
A12: TOTAL DIRECT PATIENT CARE | C12: =C7+C8+C9+C10+C11 | D12: =D7+D8+D9+D10+D11 | E12: =E7+E8+E9+E10+E11 | F12: =F7+F8+F9+F10+F11 | G12: =G7+G8+G9+G10+G11 | H12: =H7+H8+H9+H10+H11 | I12: =I7+I8+I9+I10+I11 | J12: =J7+J8+J9+J10+J11 | ... AL12: =AL7+AL8+AL9+AL10+AL11
A13: FACILITY (Acct 6010-6150; rent steps by year)
A14: Rent (6045-Z) | C14: ='Control Tower'!$B$102 | D14: ='Control Tower'!$B$102 | E14: ='Control Tower'!$B$102 | F14: ='Control Tower'!$B$102 | G14: ='Control Tower'!$B$102 | H14: ='Control Tower'!$B$102 | I14: ='Control Tower'!$B$102 | J14: ='Control Tower'!$B$102 | ... N14: ='Control Tower'!$B$102 | O14: ='Control Tower'!$B$103 | P14: ='Control Tower'!$B$103 | Q14: ='Control Tower'!$B$103 | R14: ='Control Tower'!$B$103 | S14: ='Control Tower'!$B$103 | T14: ='Control Tower'!$B$103 | U14: ='Control Tower'!$B$103 | V14: ='Control Tower'!$B$103 | ... Z14: ='Control Tower'!$B$103 | AA14: ='Control Tower'!$B$104 | AB14: ='Control Tower'!$B$104 | AC14: ='Control Tower'!$B$104 | AD14: ='Control Tower'!$B$104 | AE14: ='Control Tower'!$B$104 | AF14: ='Control Tower'!$B$104 | AG14: ='Control Tower'!$B$104 | AH14: ='Control Tower'!$B$104 | ... AL14: ='Control Tower'!$B$104
A15: Utilities (6150) | C15: ='Control Tower'!$B$105*(1+'Control Tower'!$B$49)^0 | D15: ='Control Tower'!$B$105*(1+'Control Tower'!$B$49)^0 | E15: ='Control Tower'!$B$105*(1+'Control Tower'!$B$49)^0 | F15: ='Control Tower'!$B$105*(1+'Control Tower'!$B$49)^0 | G15: ='Control Tower'!$B$105*(1+'Control Tower'!$B$49)^0 | H15: ='Control Tower'!$B$105*(1+'Control Tower'!$B$49)^0 | I15: ='Control Tower'!$B$105*(1+'Control Tower'!$B$49)^0 | J15: ='Control Tower'!$B$105*(1+'Control Tower'!$B$49)^0 | ... N15: ='Control Tower'!$B$105*(1+'Control Tower'!$B$49)^0 | O15: ='Control Tower'!$B$105*(1+'Control Tower'!$B$49)^1 | P15: ='Control Tower'!$B$105*(1+'Control Tower'!$B$49)^1 | Q15: ='Control Tower'!$B$105*(1+'Control Tower'!$B$49)^1 | R15: ='Control Tower'!$B$105*(1+'Control Tower'!$B$49)^1 | S15: ='Control Tower'!$B$105*(1+'Control Tower'!$B$49)^1 | T15: ='Control Tower'!$B$105*(1+'Control Tower'!$B$49)^1 | U15: ='Control Tower'!$B$105*(1+'Control Tower'!$B$49)^1 | V15: ='Control Tower'!$B$105*(1+'Control Tower'!$B$49)^1 | ... Z15: ='Control Tower'!$B$105*(1+'Control Tower'!$B$49)^1 | AA15: ='Control Tower'!$B$105*(1+'Control Tower'!$B$49)^2 | AB15: ='Control Tower'!$B$105*(1+'Control Tower'!$B$49)^2 | AC15: ='Control Tower'!$B$105*(1+'Control Tower'!$B$49)^2 | AD15: ='Control Tower'!$B$105*(1+'Control Tower'!$B$49)^2 | AE15: ='Control Tower'!$B$105*(1+'Control Tower'!$B$49)^2 | AF15: ='Control Tower'!$B$105*(1+'Control Tower'!$B$49)^2 | AG15: ='Control Tower'!$B$105*(1+'Control Tower'!$B$49)^2 | AH15: ='Control Tower'!$B$105*(1+'Control Tower'!$B$49)^2 | ... AL15: ='Control Tower'!$B$105*(1+'Control Tower'!$B$49)^2
A16: Maintenance & repairs (6060) | C16: ='Control Tower'!$B$106*(1+'Control Tower'!$B$49)^0 | D16: ='Control Tower'!$B$106*(1+'Control Tower'!$B$49)^0 | E16: ='Control Tower'!$B$106*(1+'Control Tower'!$B$49)^0 | F16: ='Control Tower'!$B$106*(1+'Control Tower'!$B$49)^0 | G16: ='Control Tower'!$B$106*(1+'Control Tower'!$B$49)^0 | H16: ='Control Tower'!$B$106*(1+'Control Tower'!$B$49)^0 | I16: ='Control Tower'!$B$106*(1+'Control Tower'!$B$49)^0 | J16: ='Control Tower'!$B$106*(1+'Control Tower'!$B$49)^0 | ... N16: ='Control Tower'!$B$106*(1+'Control Tower'!$B$49)^0 | O16: ='Control Tower'!$B$106*(1+'Control Tower'!$B$49)^1 | P16: ='Control Tower'!$B$106*(1+'Control Tower'!$B$49)^1 | Q16: ='Control Tower'!$B$106*(1+'Control Tower'!$B$49)^1 | R16: ='Control Tower'!$B$106*(1+'Control Tower'!$B$49)^1 | S16: ='Control Tower'!$B$106*(1+'Control Tower'!$B$49)^1 | T16: ='Control Tower'!$B$106*(1+'Control Tower'!$B$49)^1 | U16: ='Control Tower'!$B$106*(1+'Control Tower'!$B$49)^1 | V16: ='Control Tower'!$B$106*(1+'Control Tower'!$B$49)^1 | ... Z16: ='Control Tower'!$B$106*(1+'Control Tower'!$B$49)^1 | AA16: ='Control Tower'!$B$106*(1+'Control Tower'!$B$49)^2 | AB16: ='Control Tower'!$B$106*(1+'Control Tower'!$B$49)^2 | AC16: ='Control Tower'!$B$106*(1+'Control Tower'!$B$49)^2 | AD16: ='Control Tower'!$B$106*(1+'Control Tower'!$B$49)^2 | AE16: ='Control Tower'!$B$106*(1+'Control Tower'!$B$49)^2 | AF16: ='Control Tower'!$B$106*(1+'Control Tower'!$B$49)^2 | AG16: ='Control Tower'!$B$106*(1+'Control Tower'!$B$49)^2 | AH16: ='Control Tower'!$B$106*(1+'Control Tower'!$B$49)^2 | ... AL16: ='Control Tower'!$B$106*(1+'Control Tower'!$B$49)^2
A17: Alarm (6010) | C17: ='Control Tower'!$B$107*(1+'Control Tower'!$B$49)^0 | D17: ='Control Tower'!$B$107*(1+'Control Tower'!$B$49)^0 | E17: ='Control Tower'!$B$107*(1+'Control Tower'!$B$49)^0 | F17: ='Control Tower'!$B$107*(1+'Control Tower'!$B$49)^0 | G17: ='Control Tower'!$B$107*(1+'Control Tower'!$B$49)^0 | H17: ='Control Tower'!$B$107*(1+'Control Tower'!$B$49)^0 | I17: ='Control Tower'!$B$107*(1+'Control Tower'!$B$49)^0 | J17: ='Control Tower'!$B$107*(1+'Control Tower'!$B$49)^0 | ... N17: ='Control Tower'!$B$107*(1+'Control Tower'!$B$49)^0 | O17: ='Control Tower'!$B$107*(1+'Control Tower'!$B$49)^1 | P17: ='Control Tower'!$B$107*(1+'Control Tower'!$B$49)^1 | Q17: ='Control Tower'!$B$107*(1+'Control Tower'!$B$49)^1 | R17: ='Control Tower'!$B$107*(1+'Control Tower'!$B$49)^1 | S17: ='Control Tower'!$B$107*(1+'Control Tower'!$B$49)^1 | T17: ='Control Tower'!$B$107*(1+'Control Tower'!$B$49)^1 | U17: ='Control Tower'!$B$107*(1+'Control Tower'!$B$49)^1 | V17: ='Control Tower'!$B$107*(1+'Control Tower'!$B$49)^1 | ... Z17: ='Control Tower'!$B$107*(1+'Control Tower'!$B$49)^1 | AA17: ='Control Tower'!$B$107*(1+'Control Tower'!$B$49)^2 | AB17: ='Control Tower'!$B$107*(1+'Control Tower'!$B$49)^2 | AC17: ='Control Tower'!$B$107*(1+'Control Tower'!$B$49)^2 | AD17: ='Control Tower'!$B$107*(1+'Control Tower'!$B$49)^2 | AE17: ='Control Tower'!$B$107*(1+'Control Tower'!$B$49)^2 | AF17: ='Control Tower'!$B$107*(1+'Control Tower'!$B$49)^2 | AG17: ='Control Tower'!$B$107*(1+'Control Tower'!$B$49)^2 | AH17: ='Control Tower'!$B$107*(1+'Control Tower'!$B$49)^2 | ... AL17: ='Control Tower'!$B$107*(1+'Control Tower'!$B$49)^2
A18: TOTAL FACILITY | C18: =C14+C15+C16+C17 | D18: =D14+D15+D16+D17 | E18: =E14+E15+E16+E17 | F18: =F14+F15+F16+F17 | G18: =G14+G15+G16+G17 | H18: =H14+H15+H16+H17 | I18: =I14+I15+I16+I17 | J18: =J14+J15+J16+J17 | ... AL18: =AL14+AL15+AL16+AL17
A19: G&A (MAX(fixed, % of NPR); legal starts M4)
A20: EMR - base + per active patient (6530-Z) | C20: =('Control Tower'!$B$109+'Census Waterfall'!C9*'Control Tower'!$B$110)*(1+'Control Tower'!$B$49)^0 | D20: =('Control Tower'!$B$109+'Census Waterfall'!D9*'Control Tower'!$B$110)*(1+'Control Tower'!$B$49)^0 | E20: =('Control Tower'!$B$109+'Census Waterfall'!E9*'Control Tower'!$B$110)*(1+'Control Tower'!$B$49)^0 | F20: =('Control Tower'!$B$109+'Census Waterfall'!F9*'Control Tower'!$B$110)*(1+'Control Tower'!$B$49)^0 | G20: =('Control Tower'!$B$109+'Census Waterfall'!G9*'Control Tower'!$B$110)*(1+'Control Tower'!$B$49)^0 | H20: =('Control Tower'!$B$109+'Census Waterfall'!H9*'Control Tower'!$B$110)*(1+'Control Tower'!$B$49)^0 | I20: =('Control Tower'!$B$109+'Census Waterfall'!I9*'Control Tower'!$B$110)*(1+'Control Tower'!$B$49)^0 | J20: =('Control Tower'!$B$109+'Census Waterfall'!J9*'Control Tower'!$B$110)*(1+'Control Tower'!$B$49)^0 | ... N20: =('Control Tower'!$B$109+'Census Waterfall'!N9*'Control Tower'!$B$110)*(1+'Control Tower'!$B$49)^0 | O20: =('Control Tower'!$B$109+'Census Waterfall'!O9*'Control Tower'!$B$110)*(1+'Control Tower'!$B$49)^1 | P20: =('Control Tower'!$B$109+'Census Waterfall'!P9*'Control Tower'!$B$110)*(1+'Control Tower'!$B$49)^1 | Q20: =('Control Tower'!$B$109+'Census Waterfall'!Q9*'Control Tower'!$B$110)*(1+'Control Tower'!$B$49)^1 | R20: =('Control Tower'!$B$109+'Census Waterfall'!R9*'Control Tower'!$B$110)*(1+'Control Tower'!$B$49)^1 | S20: =('Control Tower'!$B$109+'Census Waterfall'!S9*'Control Tower'!$B$110)*(1+'Control Tower'!$B$49)^1 | T20: =('Control Tower'!$B$109+'Census Waterfall'!T9*'Control Tower'!$B$110)*(1+'Control Tower'!$B$49)^1 | U20: =('Control Tower'!$B$109+'Census Waterfall'!U9*'Control Tower'!$B$110)*(1+'Control Tower'!$B$49)^1 | V20: =('Control Tower'!$B$109+'Census Waterfall'!V9*'Control Tower'!$B$110)*(1+'Control Tower'!$B$49)^1 | ... Z20: =('Control Tower'!$B$109+'Census Waterfall'!Z9*'Control Tower'!$B$110)*(1+'Control Tower'!$B$49)^1 | AA20: =('Control Tower'!$B$109+'Census Waterfall'!AA9*'Control Tower'!$B$110)*(1+'Control Tower'!$B$49)^2 | AB20: =('Control Tower'!$B$109+'Census Waterfall'!AB9*'Control Tower'!$B$110)*(1+'Control Tower'!$B$49)^2 | AC20: =('Control Tower'!$B$109+'Census Waterfall'!AC9*'Control Tower'!$B$110)*(1+'Control Tower'!$B$49)^2 | AD20: =('Control Tower'!$B$109+'Census Waterfall'!AD9*'Control Tower'!$B$110)*(1+'Control Tower'!$B$49)^2 | AE20: =('Control Tower'!$B$109+'Census Waterfall'!AE9*'Control Tower'!$B$110)*(1+'Control Tower'!$B$49)^2 | AF20: =('Control Tower'!$B$109+'Census Waterfall'!AF9*'Control Tower'!$B$110)*(1+'Control Tower'!$B$49)^2 | AG20: =('Control Tower'!$B$109+'Census Waterfall'!AG9*'Control Tower'!$B$110)*(1+'Control Tower'!$B$49)^2 | AH20: =('Control Tower'!$B$109+'Census Waterfall'!AH9*'Control Tower'!$B$110)*(1+'Control Tower'!$B$49)^2 | ... AL20: =('Control Tower'!$B$109+'Census Waterfall'!AL9*'Control Tower'!$B$110)*(1+'Control Tower'!$B$49)^2
A21: Malpractice / professional liability (6580-Z) | C21: =MAX('Control Tower'!$B$111*(1+'Control Tower'!$B$49)^0,'Revenue Model'!C11*'Control Tower'!$C$111) | D21: =MAX('Control Tower'!$B$111*(1+'Control Tower'!$B$49)^0,'Revenue Model'!D11*'Control Tower'!$C$111) | E21: =MAX('Control Tower'!$B$111*(1+'Control Tower'!$B$49)^0,'Revenue Model'!E11*'Control Tower'!$C$111) | F21: =MAX('Control Tower'!$B$111*(1+'Control Tower'!$B$49)^0,'Revenue Model'!F11*'Control Tower'!$C$111) | G21: =MAX('Control Tower'!$B$111*(1+'Control Tower'!$B$49)^0,'Revenue Model'!G11*'Control Tower'!$C$111) | H21: =MAX('Control Tower'!$B$111*(1+'Control Tower'!$B$49)^0,'Revenue Model'!H11*'Control Tower'!$C$111) | I21: =MAX('Control Tower'!$B$111*(1+'Control Tower'!$B$49)^0,'Revenue Model'!I11*'Control Tower'!$C$111) | J21: =MAX('Control Tower'!$B$111*(1+'Control Tower'!$B$49)^0,'Revenue Model'!J11*'Control Tower'!$C$111) | ... N21: =MAX('Control Tower'!$B$111*(1+'Control Tower'!$B$49)^0,'Revenue Model'!N11*'Control Tower'!$C$111) | O21: =MAX('Control Tower'!$B$111*(1+'Control Tower'!$B$49)^1,'Revenue Model'!O11*'Control Tower'!$C$111) | P21: =MAX('Control Tower'!$B$111*(1+'Control Tower'!$B$49)^1,'Revenue Model'!P11*'Control Tower'!$C$111) | Q21: =MAX('Control Tower'!$B$111*(1+'Control Tower'!$B$49)^1,'Revenue Model'!Q11*'Control Tower'!$C$111) | R21: =MAX('Control Tower'!$B$111*(1+'Control Tower'!$B$49)^1,'Revenue Model'!R11*'Control Tower'!$C$111) | S21: =MAX('Control Tower'!$B$111*(1+'Control Tower'!$B$49)^1,'Revenue Model'!S11*'Control Tower'!$C$111) | T21: =MAX('Control Tower'!$B$111*(1+'Control Tower'!$B$49)^1,'Revenue Model'!T11*'Control Tower'!$C$111) | U21: =MAX('Control Tower'!$B$111*(1+'Control Tower'!$B$49)^1,'Revenue Model'!U11*'Control Tower'!$C$111) | V21: =MAX('Control Tower'!$B$111*(1+'Control Tower'!$B$49)^1,'Revenue Model'!V11*'Control Tower'!$C$111) | ... Z21: =MAX('Control Tower'!$B$111*(1+'Control Tower'!$B$49)^1,'Revenue Model'!Z11*'Control Tower'!$C$111) | AA21: =MAX('Control Tower'!$B$111*(1+'Control Tower'!$B$49)^2,'Revenue Model'!AA11*'Control Tower'!$C$111) | AB21: =MAX('Control Tower'!$B$111*(1+'Control Tower'!$B$49)^2,'Revenue Model'!AB11*'Control Tower'!$C$111) | AC21: =MAX('Control Tower'!$B$111*(1+'Control Tower'!$B$49)^2,'Revenue Model'!AC11*'Control Tower'!$C$111) | AD21: =MAX('Control Tower'!$B$111*(1+'Control Tower'!$B$49)^2,'Revenue Model'!AD11*'Control Tower'!$C$111) | AE21: =MAX('Control Tower'!$B$111*(1+'Control Tower'!$B$49)^2,'Revenue Model'!AE11*'Control Tower'!$C$111) | AF21: =MAX('Control Tower'!$B$111*(1+'Control Tower'!$B$49)^2,'Revenue Model'!AF11*'Control Tower'!$C$111) | AG21: =MAX('Control Tower'!$B$111*(1+'Control Tower'!$B$49)^2,'Revenue Model'!AG11*'Control Tower'!$C$111) | AH21: =MAX('Control Tower'!$B$111*(1+'Control Tower'!$B$49)^2,'Revenue Model'!AH11*'Control Tower'!$C$111) | ... AL21: =MAX('Control Tower'!$B$111*(1+'Control Tower'!$B$49)^2,'Revenue Model'!AL11*'Control Tower'!$C$111)
A22: General liability insurance (6580-Z) | C22: =MAX('Control Tower'!$B$112*(1+'Control Tower'!$B$49)^0,'Revenue Model'!C11*'Control Tower'!$C$112) | D22: =MAX('Control Tower'!$B$112*(1+'Control Tower'!$B$49)^0,'Revenue Model'!D11*'Control Tower'!$C$112) | E22: =MAX('Control Tower'!$B$112*(1+'Control Tower'!$B$49)^0,'Revenue Model'!E11*'Control Tower'!$C$112) | F22: =MAX('Control Tower'!$B$112*(1+'Control Tower'!$B$49)^0,'Revenue Model'!F11*'Control Tower'!$C$112) | G22: =MAX('Control Tower'!$B$112*(1+'Control Tower'!$B$49)^0,'Revenue Model'!G11*'Control Tower'!$C$112) | H22: =MAX('Control Tower'!$B$112*(1+'Control Tower'!$B$49)^0,'Revenue Model'!H11*'Control Tower'!$C$112) | I22: =MAX('Control Tower'!$B$112*(1+'Control Tower'!$B$49)^0,'Revenue Model'!I11*'Control Tower'!$C$112) | J22: =MAX('Control Tower'!$B$112*(1+'Control Tower'!$B$49)^0,'Revenue Model'!J11*'Control Tower'!$C$112) | ... N22: =MAX('Control Tower'!$B$112*(1+'Control Tower'!$B$49)^0,'Revenue Model'!N11*'Control Tower'!$C$112) | O22: =MAX('Control Tower'!$B$112*(1+'Control Tower'!$B$49)^1,'Revenue Model'!O11*'Control Tower'!$C$112) | P22: =MAX('Control Tower'!$B$112*(1+'Control Tower'!$B$49)^1,'Revenue Model'!P11*'Control Tower'!$C$112) | Q22: =MAX('Control Tower'!$B$112*(1+'Control Tower'!$B$49)^1,'Revenue Model'!Q11*'Control Tower'!$C$112) | R22: =MAX('Control Tower'!$B$112*(1+'Control Tower'!$B$49)^1,'Revenue Model'!R11*'Control Tower'!$C$112) | S22: =MAX('Control Tower'!$B$112*(1+'Control Tower'!$B$49)^1,'Revenue Model'!S11*'Control Tower'!$C$112) | T22: =MAX('Control Tower'!$B$112*(1+'Control Tower'!$B$49)^1,'Revenue Model'!T11*'Control Tower'!$C$112) | U22: =MAX('Control Tower'!$B$112*(1+'Control Tower'!$B$49)^1,'Revenue Model'!U11*'Control Tower'!$C$112) | V22: =MAX('Control Tower'!$B$112*(1+'Control Tower'!$B$49)^1,'Revenue Model'!V11*'Control Tower'!$C$112) | ... Z22: =MAX('Control Tower'!$B$112*(1+'Control Tower'!$B$49)^1,'Revenue Model'!Z11*'Control Tower'!$C$112) | AA22: =MAX('Control Tower'!$B$112*(1+'Control Tower'!$B$49)^2,'Revenue Model'!AA11*'Control Tower'!$C$112) | AB22: =MAX('Control Tower'!$B$112*(1+'Control Tower'!$B$49)^2,'Revenue Model'!AB11*'Control Tower'!$C$112) | AC22: =MAX('Control Tower'!$B$112*(1+'Control Tower'!$B$49)^2,'Revenue Model'!AC11*'Control Tower'!$C$112) | AD22: =MAX('Control Tower'!$B$112*(1+'Control Tower'!$B$49)^2,'Revenue Model'!AD11*'Control Tower'!$C$112) | AE22: =MAX('Control Tower'!$B$112*(1+'Control Tower'!$B$49)^2,'Revenue Model'!AE11*'Control Tower'!$C$112) | AF22: =MAX('Control Tower'!$B$112*(1+'Control Tower'!$B$49)^2,'Revenue Model'!AF11*'Control Tower'!$C$112) | AG22: =MAX('Control Tower'!$B$112*(1+'Control Tower'!$B$49)^2,'Revenue Model'!AG11*'Control Tower'!$C$112) | AH22: =MAX('Control Tower'!$B$112*(1+'Control Tower'!$B$49)^2,'Revenue Model'!AH11*'Control Tower'!$C$112) | ... AL22: =MAX('Control Tower'!$B$112*(1+'Control Tower'!$B$49)^2,'Revenue Model'!AL11*'Control Tower'!$C$112)
A23: Phone & internet (6710-Z) | C23: =MAX('Control Tower'!$B$113*(1+'Control Tower'!$B$49)^0,'Revenue Model'!C11*'Control Tower'!$C$113) | D23: =MAX('Control Tower'!$B$113*(1+'Control Tower'!$B$49)^0,'Revenue Model'!D11*'Control Tower'!$C$113) | E23: =MAX('Control Tower'!$B$113*(1+'Control Tower'!$B$49)^0,'Revenue Model'!E11*'Control Tower'!$C$113) | F23: =MAX('Control Tower'!$B$113*(1+'Control Tower'!$B$49)^0,'Revenue Model'!F11*'Control Tower'!$C$113) | G23: =MAX('Control Tower'!$B$113*(1+'Control Tower'!$B$49)^0,'Revenue Model'!G11*'Control Tower'!$C$113) | H23: =MAX('Control Tower'!$B$113*(1+'Control Tower'!$B$49)^0,'Revenue Model'!H11*'Control Tower'!$C$113) | I23: =MAX('Control Tower'!$B$113*(1+'Control Tower'!$B$49)^0,'Revenue Model'!I11*'Control Tower'!$C$113) | J23: =MAX('Control Tower'!$B$113*(1+'Control Tower'!$B$49)^0,'Revenue Model'!J11*'Control Tower'!$C$113) | ... N23: =MAX('Control Tower'!$B$113*(1+'Control Tower'!$B$49)^0,'Revenue Model'!N11*'Control Tower'!$C$113) | O23: =MAX('Control Tower'!$B$113*(1+'Control Tower'!$B$49)^1,'Revenue Model'!O11*'Control Tower'!$C$113) | P23: =MAX('Control Tower'!$B$113*(1+'Control Tower'!$B$49)^1,'Revenue Model'!P11*'Control Tower'!$C$113) | Q23: =MAX('Control Tower'!$B$113*(1+'Control Tower'!$B$49)^1,'Revenue Model'!Q11*'Control Tower'!$C$113) | R23: =MAX('Control Tower'!$B$113*(1+'Control Tower'!$B$49)^1,'Revenue Model'!R11*'Control Tower'!$C$113) | S23: =MAX('Control Tower'!$B$113*(1+'Control Tower'!$B$49)^1,'Revenue Model'!S11*'Control Tower'!$C$113) | T23: =MAX('Control Tower'!$B$113*(1+'Control Tower'!$B$49)^1,'Revenue Model'!T11*'Control Tower'!$C$113) | U23: =MAX('Control Tower'!$B$113*(1+'Control Tower'!$B$49)^1,'Revenue Model'!U11*'Control Tower'!$C$113) | V23: =MAX('Control Tower'!$B$113*(1+'Control Tower'!$B$49)^1,'Revenue Model'!V11*'Control Tower'!$C$113) | ... Z23: =MAX('Control Tower'!$B$113*(1+'Control Tower'!$B$49)^1,'Revenue Model'!Z11*'Control Tower'!$C$113) | AA23: =MAX('Control Tower'!$B$113*(1+'Control Tower'!$B$49)^2,'Revenue Model'!AA11*'Control Tower'!$C$113) | AB23: =MAX('Control Tower'!$B$113*(1+'Control Tower'!$B$49)^2,'Revenue Model'!AB11*'Control Tower'!$C$113) | AC23: =MAX('Control Tower'!$B$113*(1+'Control Tower'!$B$49)^2,'Revenue Model'!AC11*'Control Tower'!$C$113) | AD23: =MAX('Control Tower'!$B$113*(1+'Control Tower'!$B$49)^2,'Revenue Model'!AD11*'Control Tower'!$C$113) | AE23: =MAX('Control Tower'!$B$113*(1+'Control Tower'!$B$49)^2,'Revenue Model'!AE11*'Control Tower'!$C$113) | AF23: =MAX('Control Tower'!$B$113*(1+'Control Tower'!$B$49)^2,'Revenue Model'!AF11*'Control Tower'!$C$113) | AG23: =MAX('Control Tower'!$B$113*(1+'Control Tower'!$B$49)^2,'Revenue Model'!AG11*'Control Tower'!$C$113) | AH23: =MAX('Control Tower'!$B$113*(1+'Control Tower'!$B$49)^2,'Revenue Model'!AH11*'Control Tower'!$C$113) | ... AL23: =MAX('Control Tower'!$B$113*(1+'Control Tower'!$B$49)^2,'Revenue Model'!AL11*'Control Tower'!$C$113)
A24: Marketing & referral development (6800-M) | C24: =MAX('Control Tower'!$B$114*(1+'Control Tower'!$B$49)^0,'Revenue Model'!C11*'Control Tower'!$C$114) | D24: =MAX('Control Tower'!$B$114*(1+'Control Tower'!$B$49)^0,'Revenue Model'!D11*'Control Tower'!$C$114) | E24: =MAX('Control Tower'!$B$114*(1+'Control Tower'!$B$49)^0,'Revenue Model'!E11*'Control Tower'!$C$114) | F24: =MAX('Control Tower'!$B$114*(1+'Control Tower'!$B$49)^0,'Revenue Model'!F11*'Control Tower'!$C$114) | G24: =MAX('Control Tower'!$B$114*(1+'Control Tower'!$B$49)^0,'Revenue Model'!G11*'Control Tower'!$C$114) | H24: =MAX('Control Tower'!$B$114*(1+'Control Tower'!$B$49)^0,'Revenue Model'!H11*'Control Tower'!$C$114) | I24: =MAX('Control Tower'!$B$114*(1+'Control Tower'!$B$49)^0,'Revenue Model'!I11*'Control Tower'!$C$114) | J24: =MAX('Control Tower'!$B$114*(1+'Control Tower'!$B$49)^0,'Revenue Model'!J11*'Control Tower'!$C$114) | ... N24: =MAX('Control Tower'!$B$114*(1+'Control Tower'!$B$49)^0,'Revenue Model'!N11*'Control Tower'!$C$114) | O24: =MAX('Control Tower'!$B$114*(1+'Control Tower'!$B$49)^1,'Revenue Model'!O11*'Control Tower'!$C$114) | P24: =MAX('Control Tower'!$B$114*(1+'Control Tower'!$B$49)^1,'Revenue Model'!P11*'Control Tower'!$C$114) | Q24: =MAX('Control Tower'!$B$114*(1+'Control Tower'!$B$49)^1,'Revenue Model'!Q11*'Control Tower'!$C$114) | R24: =MAX('Control Tower'!$B$114*(1+'Control Tower'!$B$49)^1,'Revenue Model'!R11*'Control Tower'!$C$114) | S24: =MAX('Control Tower'!$B$114*(1+'Control Tower'!$B$49)^1,'Revenue Model'!S11*'Control Tower'!$C$114) | T24: =MAX('Control Tower'!$B$114*(1+'Control Tower'!$B$49)^1,'Revenue Model'!T11*'Control Tower'!$C$114) | U24: =MAX('Control Tower'!$B$114*(1+'Control Tower'!$B$49)^1,'Revenue Model'!U11*'Control Tower'!$C$114) | V24: =MAX('Control Tower'!$B$114*(1+'Control Tower'!$B$49)^1,'Revenue Model'!V11*'Control Tower'!$C$114) | ... Z24: =MAX('Control Tower'!$B$114*(1+'Control Tower'!$B$49)^1,'Revenue Model'!Z11*'Control Tower'!$C$114) | AA24: =MAX('Control Tower'!$B$114*(1+'Control Tower'!$B$49)^2,'Revenue Model'!AA11*'Control Tower'!$C$114) | AB24: =MAX('Control Tower'!$B$114*(1+'Control Tower'!$B$49)^2,'Revenue Model'!AB11*'Control Tower'!$C$114) | AC24: =MAX('Control Tower'!$B$114*(1+'Control Tower'!$B$49)^2,'Revenue Model'!AC11*'Control Tower'!$C$114) | AD24: =MAX('Control Tower'!$B$114*(1+'Control Tower'!$B$49)^2,'Revenue Model'!AD11*'Control Tower'!$C$114) | AE24: =MAX('Control Tower'!$B$114*(1+'Control Tower'!$B$49)^2,'Revenue Model'!AE11*'Control Tower'!$C$114) | AF24: =MAX('Control Tower'!$B$114*(1+'Control Tower'!$B$49)^2,'Revenue Model'!AF11*'Control Tower'!$C$114) | AG24: =MAX('Control Tower'!$B$114*(1+'Control Tower'!$B$49)^2,'Revenue Model'!AG11*'Control Tower'!$C$114) | AH24: =MAX('Control Tower'!$B$114*(1+'Control Tower'!$B$49)^2,'Revenue Model'!AH11*'Control Tower'!$C$114) | ... AL24: =MAX('Control Tower'!$B$114*(1+'Control Tower'!$B$49)^2,'Revenue Model'!AL11*'Control Tower'!$C$114)
A25: Accounting & bookkeeping (6510-Z) | C25: =MAX('Control Tower'!$B$115*(1+'Control Tower'!$B$49)^0,'Revenue Model'!C11*'Control Tower'!$C$115) | D25: =MAX('Control Tower'!$B$115*(1+'Control Tower'!$B$49)^0,'Revenue Model'!D11*'Control Tower'!$C$115) | E25: =MAX('Control Tower'!$B$115*(1+'Control Tower'!$B$49)^0,'Revenue Model'!E11*'Control Tower'!$C$115) | F25: =MAX('Control Tower'!$B$115*(1+'Control Tower'!$B$49)^0,'Revenue Model'!F11*'Control Tower'!$C$115) | G25: =MAX('Control Tower'!$B$115*(1+'Control Tower'!$B$49)^0,'Revenue Model'!G11*'Control Tower'!$C$115) | H25: =MAX('Control Tower'!$B$115*(1+'Control Tower'!$B$49)^0,'Revenue Model'!H11*'Control Tower'!$C$115) | I25: =MAX('Control Tower'!$B$115*(1+'Control Tower'!$B$49)^0,'Revenue Model'!I11*'Control Tower'!$C$115) | J25: =MAX('Control Tower'!$B$115*(1+'Control Tower'!$B$49)^0,'Revenue Model'!J11*'Control Tower'!$C$115) | ... N25: =MAX('Control Tower'!$B$115*(1+'Control Tower'!$B$49)^0,'Revenue Model'!N11*'Control Tower'!$C$115) | O25: =MAX('Control Tower'!$B$115*(1+'Control Tower'!$B$49)^1,'Revenue Model'!O11*'Control Tower'!$C$115) | P25: =MAX('Control Tower'!$B$115*(1+'Control Tower'!$B$49)^1,'Revenue Model'!P11*'Control Tower'!$C$115) | Q25: =MAX('Control Tower'!$B$115*(1+'Control Tower'!$B$49)^1,'Revenue Model'!Q11*'Control Tower'!$C$115) | R25: =MAX('Control Tower'!$B$115*(1+'Control Tower'!$B$49)^1,'Revenue Model'!R11*'Control Tower'!$C$115) | S25: =MAX('Control Tower'!$B$115*(1+'Control Tower'!$B$49)^1,'Revenue Model'!S11*'Control Tower'!$C$115) | T25: =MAX('Control Tower'!$B$115*(1+'Control Tower'!$B$49)^1,'Revenue Model'!T11*'Control Tower'!$C$115) | U25: =MAX('Control Tower'!$B$115*(1+'Control Tower'!$B$49)^1,'Revenue Model'!U11*'Control Tower'!$C$115) | V25: =MAX('Control Tower'!$B$115*(1+'Control Tower'!$B$49)^1,'Revenue Model'!V11*'Control Tower'!$C$115) | ... Z25: =MAX('Control Tower'!$B$115*(1+'Control Tower'!$B$49)^1,'Revenue Model'!Z11*'Control Tower'!$C$115) | AA25: =MAX('Control Tower'!$B$115*(1+'Control Tower'!$B$49)^2,'Revenue Model'!AA11*'Control Tower'!$C$115) | AB25: =MAX('Control Tower'!$B$115*(1+'Control Tower'!$B$49)^2,'Revenue Model'!AB11*'Control Tower'!$C$115) | AC25: =MAX('Control Tower'!$B$115*(1+'Control Tower'!$B$49)^2,'Revenue Model'!AC11*'Control Tower'!$C$115) | AD25: =MAX('Control Tower'!$B$115*(1+'Control Tower'!$B$49)^2,'Revenue Model'!AD11*'Control Tower'!$C$115) | AE25: =MAX('Control Tower'!$B$115*(1+'Control Tower'!$B$49)^2,'Revenue Model'!AE11*'Control Tower'!$C$115) | AF25: =MAX('Control Tower'!$B$115*(1+'Control Tower'!$B$49)^2,'Revenue Model'!AF11*'Control Tower'!$C$115) | AG25: =MAX('Control Tower'!$B$115*(1+'Control Tower'!$B$49)^2,'Revenue Model'!AG11*'Control Tower'!$C$115) | AH25: =MAX('Control Tower'!$B$115*(1+'Control Tower'!$B$49)^2,'Revenue Model'!AH11*'Control Tower'!$C$115) | ... AL25: =MAX('Control Tower'!$B$115*(1+'Control Tower'!$B$49)^2,'Revenue Model'!AL11*'Control Tower'!$C$115)
A26: Legal & compliance (6600-Z) | C26: =IF(1>=4,MAX('Control Tower'!$B$116*(1+'Control Tower'!$B$49)^0,'Revenue Model'!C11*'Control Tower'!$C$116),0) | D26: =IF(2>=4,MAX('Control Tower'!$B$116*(1+'Control Tower'!$B$49)^0,'Revenue Model'!D11*'Control Tower'!$C$116),0) | E26: =IF(3>=4,MAX('Control Tower'!$B$116*(1+'Control Tower'!$B$49)^0,'Revenue Model'!E11*'Control Tower'!$C$116),0) | F26: =IF(4>=4,MAX('Control Tower'!$B$116*(1+'Control Tower'!$B$49)^0,'Revenue Model'!F11*'Control Tower'!$C$116),0) | G26: =IF(5>=4,MAX('Control Tower'!$B$116*(1+'Control Tower'!$B$49)^0,'Revenue Model'!G11*'Control Tower'!$C$116),0) | H26: =IF(6>=4,MAX('Control Tower'!$B$116*(1+'Control Tower'!$B$49)^0,'Revenue Model'!H11*'Control Tower'!$C$116),0) | I26: =IF(7>=4,MAX('Control Tower'!$B$116*(1+'Control Tower'!$B$49)^0,'Revenue Model'!I11*'Control Tower'!$C$116),0) | J26: =IF(8>=4,MAX('Control Tower'!$B$116*(1+'Control Tower'!$B$49)^0,'Revenue Model'!J11*'Control Tower'!$C$116),0) | K26: =IF(9>=4,MAX('Control Tower'!$B$116*(1+'Control Tower'!$B$49)^0,'Revenue Model'!K11*'Control Tower'!$C$116),0) | L26: =IF(10>=4,MAX('Control Tower'!$B$116*(1+'Control Tower'!$B$49)^0,'Revenue Model'!L11*'Control Tower'!$C$116),0) | M26: =IF(11>=4,MAX('Control Tower'!$B$116*(1+'Control Tower'!$B$49)^0,'Revenue Model'!M11*'Control Tower'!$C$116),0) | N26: =IF(12>=4,MAX('Control Tower'!$B$116*(1+'Control Tower'!$B$49)^0,'Revenue Model'!N11*'Control Tower'!$C$116),0) | O26: =IF(13>=4,MAX('Control Tower'!$B$116*(1+'Control Tower'!$B$49)^1,'Revenue Model'!O11*'Control Tower'!$C$116),0) | P26: =IF(14>=4,MAX('Control Tower'!$B$116*(1+'Control Tower'!$B$49)^1,'Revenue Model'!P11*'Control Tower'!$C$116),0) | Q26: =IF(15>=4,MAX('Control Tower'!$B$116*(1+'Control Tower'!$B$49)^1,'Revenue Model'!Q11*'Control Tower'!$C$116),0) | R26: =IF(16>=4,MAX('Control Tower'!$B$116*(1+'Control Tower'!$B$49)^1,'Revenue Model'!R11*'Control Tower'!$C$116),0) | S26: =IF(17>=4,MAX('Control Tower'!$B$116*(1+'Control Tower'!$B$49)^1,'Revenue Model'!S11*'Control Tower'!$C$116),0) | T26: =IF(18>=4,MAX('Control Tower'!$B$116*(1+'Control Tower'!$B$49)^1,'Revenue Model'!T11*'Control Tower'!$C$116),0) | U26: =IF(19>=4,MAX('Control Tower'!$B$116*(1+'Control Tower'!$B$49)^1,'Revenue Model'!U11*'Control Tower'!$C$116),0) | V26: =IF(20>=4,MAX('Control Tower'!$B$116*(1+'Control Tower'!$B$49)^1,'Revenue Model'!V11*'Control Tower'!$C$116),0) | W26: =IF(21>=4,MAX('Control Tower'!$B$116*(1+'Control Tower'!$B$49)^1,'Revenue Model'!W11*'Control Tower'!$C$116),0) | X26: =IF(22>=4,MAX('Control Tower'!$B$116*(1+'Control Tower'!$B$49)^1,'Revenue Model'!X11*'Control Tower'!$C$116),0) | Y26: =IF(23>=4,MAX('Control Tower'!$B$116*(1+'Control Tower'!$B$49)^1,'Revenue Model'!Y11*'Control Tower'!$C$116),0) | Z26: =IF(24>=4,MAX('Control Tower'!$B$116*(1+'Control Tower'!$B$49)^1,'Revenue Model'!Z11*'Control Tower'!$C$116),0) | AA26: =IF(25>=4,MAX('Control Tower'!$B$116*(1+'Control Tower'!$B$49)^2,'Revenue Model'!AA11*'Control Tower'!$C$116),0) | AB26: =IF(26>=4,MAX('Control Tower'!$B$116*(1+'Control Tower'!$B$49)^2,'Revenue Model'!AB11*'Control Tower'!$C$116),0) | AC26: =IF(27>=4,MAX('Control Tower'!$B$116*(1+'Control Tower'!$B$49)^2,'Revenue Model'!AC11*'Control Tower'!$C$116),0) | AD26: =IF(28>=4,MAX('Control Tower'!$B$116*(1+'Control Tower'!$B$49)^2,'Revenue Model'!AD11*'Control Tower'!$C$116),0) | AE26: =IF(29>=4,MAX('Control Tower'!$B$116*(1+'Control Tower'!$B$49)^2,'Revenue Model'!AE11*'Control Tower'!$C$116),0) | AF26: =IF(30>=4,MAX('Control Tower'!$B$116*(1+'Control Tower'!$B$49)^2,'Revenue Model'!AF11*'Control Tower'!$C$116),0) | AG26: =IF(31>=4,MAX('Control Tower'!$B$116*(1+'Control Tower'!$B$49)^2,'Revenue Model'!AG11*'Control Tower'!$C$116),0) | AH26: =IF(32>=4,MAX('Control Tower'!$B$116*(1+'Control Tower'!$B$49)^2,'Revenue Model'!AH11*'Control Tower'!$C$116),0) | AI26: =IF(33>=4,MAX('Control Tower'!$B$116*(1+'Control Tower'!$B$49)^2,'Revenue Model'!AI11*'Control Tower'!$C$116),0) | AJ26: =IF(34>=4,MAX('Control Tower'!$B$116*(1+'Control Tower'!$B$49)^2,'Revenue Model'!AJ11*'Control Tower'!$C$116),0) | AK26: =IF(35>=4,MAX('Control Tower'!$B$116*(1+'Control Tower'!$B$49)^2,'Revenue Model'!AK11*'Control Tower'!$C$116),0) | AL26: =IF(36>=4,MAX('Control Tower'!$B$116*(1+'Control Tower'!$B$49)^2,'Revenue Model'!AL11*'Control Tower'!$C$116),0)
A27: Office supplies (6650-Z) | C27: =MAX('Control Tower'!$B$117*(1+'Control Tower'!$B$49)^0,'Revenue Model'!C11*'Control Tower'!$C$117) | D27: =MAX('Control Tower'!$B$117*(1+'Control Tower'!$B$49)^0,'Revenue Model'!D11*'Control Tower'!$C$117) | E27: =MAX('Control Tower'!$B$117*(1+'Control Tower'!$B$49)^0,'Revenue Model'!E11*'Control Tower'!$C$117) | F27: =MAX('Control Tower'!$B$117*(1+'Control Tower'!$B$49)^0,'Revenue Model'!F11*'Control Tower'!$C$117) | G27: =MAX('Control Tower'!$B$117*(1+'Control Tower'!$B$49)^0,'Revenue Model'!G11*'Control Tower'!$C$117) | H27: =MAX('Control Tower'!$B$117*(1+'Control Tower'!$B$49)^0,'Revenue Model'!H11*'Control Tower'!$C$117) | I27: =MAX('Control Tower'!$B$117*(1+'Control Tower'!$B$49)^0,'Revenue Model'!I11*'Control Tower'!$C$117) | J27: =MAX('Control Tower'!$B$117*(1+'Control Tower'!$B$49)^0,'Revenue Model'!J11*'Control Tower'!$C$117) | ... N27: =MAX('Control Tower'!$B$117*(1+'Control Tower'!$B$49)^0,'Revenue Model'!N11*'Control Tower'!$C$117) | O27: =MAX('Control Tower'!$B$117*(1+'Control Tower'!$B$49)^1,'Revenue Model'!O11*'Control Tower'!$C$117) | P27: =MAX('Control Tower'!$B$117*(1+'Control Tower'!$B$49)^1,'Revenue Model'!P11*'Control Tower'!$C$117) | Q27: =MAX('Control Tower'!$B$117*(1+'Control Tower'!$B$49)^1,'Revenue Model'!Q11*'Control Tower'!$C$117) | R27: =MAX('Control Tower'!$B$117*(1+'Control Tower'!$B$49)^1,'Revenue Model'!R11*'Control Tower'!$C$117) | S27: =MAX('Control Tower'!$B$117*(1+'Control Tower'!$B$49)^1,'Revenue Model'!S11*'Control Tower'!$C$117) | T27: =MAX('Control Tower'!$B$117*(1+'Control Tower'!$B$49)^1,'Revenue Model'!T11*'Control Tower'!$C$117) | U27: =MAX('Control Tower'!$B$117*(1+'Control Tower'!$B$49)^1,'Revenue Model'!U11*'Control Tower'!$C$117) | V27: =MAX('Control Tower'!$B$117*(1+'Control Tower'!$B$49)^1,'Revenue Model'!V11*'Control Tower'!$C$117) | ... Z27: =MAX('Control Tower'!$B$117*(1+'Control Tower'!$B$49)^1,'Revenue Model'!Z11*'Control Tower'!$C$117) | AA27: =MAX('Control Tower'!$B$117*(1+'Control Tower'!$B$49)^2,'Revenue Model'!AA11*'Control Tower'!$C$117) | AB27: =MAX('Control Tower'!$B$117*(1+'Control Tower'!$B$49)^2,'Revenue Model'!AB11*'Control Tower'!$C$117) | AC27: =MAX('Control Tower'!$B$117*(1+'Control Tower'!$B$49)^2,'Revenue Model'!AC11*'Control Tower'!$C$117) | AD27: =MAX('Control Tower'!$B$117*(1+'Control Tower'!$B$49)^2,'Revenue Model'!AD11*'Control Tower'!$C$117) | AE27: =MAX('Control Tower'!$B$117*(1+'Control Tower'!$B$49)^2,'Revenue Model'!AE11*'Control Tower'!$C$117) | AF27: =MAX('Control Tower'!$B$117*(1+'Control Tower'!$B$49)^2,'Revenue Model'!AF11*'Control Tower'!$C$117) | AG27: =MAX('Control Tower'!$B$117*(1+'Control Tower'!$B$49)^2,'Revenue Model'!AG11*'Control Tower'!$C$117) | AH27: =MAX('Control Tower'!$B$117*(1+'Control Tower'!$B$49)^2,'Revenue Model'!AH11*'Control Tower'!$C$117) | ... AL27: =MAX('Control Tower'!$B$117*(1+'Control Tower'!$B$49)^2,'Revenue Model'!AL11*'Control Tower'!$C$117)
A28: Continuing education & licensing (6560-Z) | C28: =MAX('Control Tower'!$B$118*(1+'Control Tower'!$B$49)^0,'Revenue Model'!C11*'Control Tower'!$C$118) | D28: =MAX('Control Tower'!$B$118*(1+'Control Tower'!$B$49)^0,'Revenue Model'!D11*'Control Tower'!$C$118) | E28: =MAX('Control Tower'!$B$118*(1+'Control Tower'!$B$49)^0,'Revenue Model'!E11*'Control Tower'!$C$118) | F28: =MAX('Control Tower'!$B$118*(1+'Control Tower'!$B$49)^0,'Revenue Model'!F11*'Control Tower'!$C$118) | G28: =MAX('Control Tower'!$B$118*(1+'Control Tower'!$B$49)^0,'Revenue Model'!G11*'Control Tower'!$C$118) | H28: =MAX('Control Tower'!$B$118*(1+'Control Tower'!$B$49)^0,'Revenue Model'!H11*'Control Tower'!$C$118) | I28: =MAX('Control Tower'!$B$118*(1+'Control Tower'!$B$49)^0,'Revenue Model'!I11*'Control Tower'!$C$118) | J28: =MAX('Control Tower'!$B$118*(1+'Control Tower'!$B$49)^0,'Revenue Model'!J11*'Control Tower'!$C$118) | ... N28: =MAX('Control Tower'!$B$118*(1+'Control Tower'!$B$49)^0,'Revenue Model'!N11*'Control Tower'!$C$118) | O28: =MAX('Control Tower'!$B$118*(1+'Control Tower'!$B$49)^1,'Revenue Model'!O11*'Control Tower'!$C$118) | P28: =MAX('Control Tower'!$B$118*(1+'Control Tower'!$B$49)^1,'Revenue Model'!P11*'Control Tower'!$C$118) | Q28: =MAX('Control Tower'!$B$118*(1+'Control Tower'!$B$49)^1,'Revenue Model'!Q11*'Control Tower'!$C$118) | R28: =MAX('Control Tower'!$B$118*(1+'Control Tower'!$B$49)^1,'Revenue Model'!R11*'Control Tower'!$C$118) | S28: =MAX('Control Tower'!$B$118*(1+'Control Tower'!$B$49)^1,'Revenue Model'!S11*'Control Tower'!$C$118) | T28: =MAX('Control Tower'!$B$118*(1+'Control Tower'!$B$49)^1,'Revenue Model'!T11*'Control Tower'!$C$118) | U28: =MAX('Control Tower'!$B$118*(1+'Control Tower'!$B$49)^1,'Revenue Model'!U11*'Control Tower'!$C$118) | V28: =MAX('Control Tower'!$B$118*(1+'Control Tower'!$B$49)^1,'Revenue Model'!V11*'Control Tower'!$C$118) | ... Z28: =MAX('Control Tower'!$B$118*(1+'Control Tower'!$B$49)^1,'Revenue Model'!Z11*'Control Tower'!$C$118) | AA28: =MAX('Control Tower'!$B$118*(1+'Control Tower'!$B$49)^2,'Revenue Model'!AA11*'Control Tower'!$C$118) | AB28: =MAX('Control Tower'!$B$118*(1+'Control Tower'!$B$49)^2,'Revenue Model'!AB11*'Control Tower'!$C$118) | AC28: =MAX('Control Tower'!$B$118*(1+'Control Tower'!$B$49)^2,'Revenue Model'!AC11*'Control Tower'!$C$118) | AD28: =MAX('Control Tower'!$B$118*(1+'Control Tower'!$B$49)^2,'Revenue Model'!AD11*'Control Tower'!$C$118) | AE28: =MAX('Control Tower'!$B$118*(1+'Control Tower'!$B$49)^2,'Revenue Model'!AE11*'Control Tower'!$C$118) | AF28: =MAX('Control Tower'!$B$118*(1+'Control Tower'!$B$49)^2,'Revenue Model'!AF11*'Control Tower'!$C$118) | AG28: =MAX('Control Tower'!$B$118*(1+'Control Tower'!$B$49)^2,'Revenue Model'!AG11*'Control Tower'!$C$118) | AH28: =MAX('Control Tower'!$B$118*(1+'Control Tower'!$B$49)^2,'Revenue Model'!AH11*'Control Tower'!$C$118) | ... AL28: =MAX('Control Tower'!$B$118*(1+'Control Tower'!$B$49)^2,'Revenue Model'!AL11*'Control Tower'!$C$118)
A29: Dues & subscriptions (6570/6705) | C29: =MAX('Control Tower'!$B$119*(1+'Control Tower'!$B$49)^0,'Revenue Model'!C11*'Control Tower'!$C$119) | D29: =MAX('Control Tower'!$B$119*(1+'Control Tower'!$B$49)^0,'Revenue Model'!D11*'Control Tower'!$C$119) | E29: =MAX('Control Tower'!$B$119*(1+'Control Tower'!$B$49)^0,'Revenue Model'!E11*'Control Tower'!$C$119) | F29: =MAX('Control Tower'!$B$119*(1+'Control Tower'!$B$49)^0,'Revenue Model'!F11*'Control Tower'!$C$119) | G29: =MAX('Control Tower'!$B$119*(1+'Control Tower'!$B$49)^0,'Revenue Model'!G11*'Control Tower'!$C$119) | H29: =MAX('Control Tower'!$B$119*(1+'Control Tower'!$B$49)^0,'Revenue Model'!H11*'Control Tower'!$C$119) | I29: =MAX('Control Tower'!$B$119*(1+'Control Tower'!$B$49)^0,'Revenue Model'!I11*'Control Tower'!$C$119) | J29: =MAX('Control Tower'!$B$119*(1+'Control Tower'!$B$49)^0,'Revenue Model'!J11*'Control Tower'!$C$119) | ... N29: =MAX('Control Tower'!$B$119*(1+'Control Tower'!$B$49)^0,'Revenue Model'!N11*'Control Tower'!$C$119) | O29: =MAX('Control Tower'!$B$119*(1+'Control Tower'!$B$49)^1,'Revenue Model'!O11*'Control Tower'!$C$119) | P29: =MAX('Control Tower'!$B$119*(1+'Control Tower'!$B$49)^1,'Revenue Model'!P11*'Control Tower'!$C$119) | Q29: =MAX('Control Tower'!$B$119*(1+'Control Tower'!$B$49)^1,'Revenue Model'!Q11*'Control Tower'!$C$119) | R29: =MAX('Control Tower'!$B$119*(1+'Control Tower'!$B$49)^1,'Revenue Model'!R11*'Control Tower'!$C$119) | S29: =MAX('Control Tower'!$B$119*(1+'Control Tower'!$B$49)^1,'Revenue Model'!S11*'Control Tower'!$C$119) | T29: =MAX('Control Tower'!$B$119*(1+'Control Tower'!$B$49)^1,'Revenue Model'!T11*'Control Tower'!$C$119) | U29: =MAX('Control Tower'!$B$119*(1+'Control Tower'!$B$49)^1,'Revenue Model'!U11*'Control Tower'!$C$119) | V29: =MAX('Control Tower'!$B$119*(1+'Control Tower'!$B$49)^1,'Revenue Model'!V11*'Control Tower'!$C$119) | ... Z29: =MAX('Control Tower'!$B$119*(1+'Control Tower'!$B$49)^1,'Revenue Model'!Z11*'Control Tower'!$C$119) | AA29: =MAX('Control Tower'!$B$119*(1+'Control Tower'!$B$49)^2,'Revenue Model'!AA11*'Control Tower'!$C$119) | AB29: =MAX('Control Tower'!$B$119*(1+'Control Tower'!$B$49)^2,'Revenue Model'!AB11*'Control Tower'!$C$119) | AC29: =MAX('Control Tower'!$B$119*(1+'Control Tower'!$B$49)^2,'Revenue Model'!AC11*'Control Tower'!$C$119) | AD29: =MAX('Control Tower'!$B$119*(1+'Control Tower'!$B$49)^2,'Revenue Model'!AD11*'Control Tower'!$C$119) | AE29: =MAX('Control Tower'!$B$119*(1+'Control Tower'!$B$49)^2,'Revenue Model'!AE11*'Control Tower'!$C$119) | AF29: =MAX('Control Tower'!$B$119*(1+'Control Tower'!$B$49)^2,'Revenue Model'!AF11*'Control Tower'!$C$119) | AG29: =MAX('Control Tower'!$B$119*(1+'Control Tower'!$B$49)^2,'Revenue Model'!AG11*'Control Tower'!$C$119) | AH29: =MAX('Control Tower'!$B$119*(1+'Control Tower'!$B$49)^2,'Revenue Model'!AH11*'Control Tower'!$C$119) | ... AL29: =MAX('Control Tower'!$B$119*(1+'Control Tower'!$B$49)^2,'Revenue Model'!AL11*'Control Tower'!$C$119)
A30: Postage, printing & copier (6565/6670) | C30: =MAX('Control Tower'!$B$120*(1+'Control Tower'!$B$49)^0,'Revenue Model'!C11*'Control Tower'!$C$120) | D30: =MAX('Control Tower'!$B$120*(1+'Control Tower'!$B$49)^0,'Revenue Model'!D11*'Control Tower'!$C$120) | E30: =MAX('Control Tower'!$B$120*(1+'Control Tower'!$B$49)^0,'Revenue Model'!E11*'Control Tower'!$C$120) | F30: =MAX('Control Tower'!$B$120*(1+'Control Tower'!$B$49)^0,'Revenue Model'!F11*'Control Tower'!$C$120) | G30: =MAX('Control Tower'!$B$120*(1+'Control Tower'!$B$49)^0,'Revenue Model'!G11*'Control Tower'!$C$120) | H30: =MAX('Control Tower'!$B$120*(1+'Control Tower'!$B$49)^0,'Revenue Model'!H11*'Control Tower'!$C$120) | I30: =MAX('Control Tower'!$B$120*(1+'Control Tower'!$B$49)^0,'Revenue Model'!I11*'Control Tower'!$C$120) | J30: =MAX('Control Tower'!$B$120*(1+'Control Tower'!$B$49)^0,'Revenue Model'!J11*'Control Tower'!$C$120) | ... N30: =MAX('Control Tower'!$B$120*(1+'Control Tower'!$B$49)^0,'Revenue Model'!N11*'Control Tower'!$C$120) | O30: =MAX('Control Tower'!$B$120*(1+'Control Tower'!$B$49)^1,'Revenue Model'!O11*'Control Tower'!$C$120) | P30: =MAX('Control Tower'!$B$120*(1+'Control Tower'!$B$49)^1,'Revenue Model'!P11*'Control Tower'!$C$120) | Q30: =MAX('Control Tower'!$B$120*(1+'Control Tower'!$B$49)^1,'Revenue Model'!Q11*'Control Tower'!$C$120) | R30: =MAX('Control Tower'!$B$120*(1+'Control Tower'!$B$49)^1,'Revenue Model'!R11*'Control Tower'!$C$120) | S30: =MAX('Control Tower'!$B$120*(1+'Control Tower'!$B$49)^1,'Revenue Model'!S11*'Control Tower'!$C$120) | T30: =MAX('Control Tower'!$B$120*(1+'Control Tower'!$B$49)^1,'Revenue Model'!T11*'Control Tower'!$C$120) | U30: =MAX('Control Tower'!$B$120*(1+'Control Tower'!$B$49)^1,'Revenue Model'!U11*'Control Tower'!$C$120) | V30: =MAX('Control Tower'!$B$120*(1+'Control Tower'!$B$49)^1,'Revenue Model'!V11*'Control Tower'!$C$120) | ... Z30: =MAX('Control Tower'!$B$120*(1+'Control Tower'!$B$49)^1,'Revenue Model'!Z11*'Control Tower'!$C$120) | AA30: =MAX('Control Tower'!$B$120*(1+'Control Tower'!$B$49)^2,'Revenue Model'!AA11*'Control Tower'!$C$120) | AB30: =MAX('Control Tower'!$B$120*(1+'Control Tower'!$B$49)^2,'Revenue Model'!AB11*'Control Tower'!$C$120) | AC30: =MAX('Control Tower'!$B$120*(1+'Control Tower'!$B$49)^2,'Revenue Model'!AC11*'Control Tower'!$C$120) | AD30: =MAX('Control Tower'!$B$120*(1+'Control Tower'!$B$49)^2,'Revenue Model'!AD11*'Control Tower'!$C$120) | AE30: =MAX('Control Tower'!$B$120*(1+'Control Tower'!$B$49)^2,'Revenue Model'!AE11*'Control Tower'!$C$120) | AF30: =MAX('Control Tower'!$B$120*(1+'Control Tower'!$B$49)^2,'Revenue Model'!AF11*'Control Tower'!$C$120) | AG30: =MAX('Control Tower'!$B$120*(1+'Control Tower'!$B$49)^2,'Revenue Model'!AG11*'Control Tower'!$C$120) | AH30: =MAX('Control Tower'!$B$120*(1+'Control Tower'!$B$49)^2,'Revenue Model'!AH11*'Control Tower'!$C$120) | ... AL30: =MAX('Control Tower'!$B$120*(1+'Control Tower'!$B$49)^2,'Revenue Model'!AL11*'Control Tower'!$C$120)
A31: TOTAL G&A (excl. contingency) | C31: =C20+C21+C22+C23+C24+C25+C26+C27+C28+C29+C30 | D31: =D20+D21+D22+D23+D24+D25+D26+D27+D28+D29+D30 | E31: =E20+E21+E22+E23+E24+E25+E26+E27+E28+E29+E30 | F31: =F20+F21+F22+F23+F24+F25+F26+F27+F28+F29+F30 | G31: =G20+G21+G22+G23+G24+G25+G26+G27+G28+G29+G30 | H31: =H20+H21+H22+H23+H24+H25+H26+H27+H28+H29+H30 | I31: =I20+I21+I22+I23+I24+I25+I26+I27+I28+I29+I30 | J31: =J20+J21+J22+J23+J24+J25+J26+J27+J28+J29+J30 | ... AL31: =AL20+AL21+AL22+AL23+AL24+AL25+AL26+AL27+AL28+AL29+AL30
A32: Contingency reserve (below EBITDA - non-GAAP buffer) (6640-Z) | C32: =MAX('Control Tower'!$B$121*(1+'Control Tower'!$B$49)^0,'Revenue Model'!C11*'Control Tower'!$C$121) | D32: =MAX('Control Tower'!$B$121*(1+'Control Tower'!$B$49)^0,'Revenue Model'!D11*'Control Tower'!$C$121) | E32: =MAX('Control Tower'!$B$121*(1+'Control Tower'!$B$49)^0,'Revenue Model'!E11*'Control Tower'!$C$121) | F32: =MAX('Control Tower'!$B$121*(1+'Control Tower'!$B$49)^0,'Revenue Model'!F11*'Control Tower'!$C$121) | G32: =MAX('Control Tower'!$B$121*(1+'Control Tower'!$B$49)^0,'Revenue Model'!G11*'Control Tower'!$C$121) | H32: =MAX('Control Tower'!$B$121*(1+'Control Tower'!$B$49)^0,'Revenue Model'!H11*'Control Tower'!$C$121) | I32: =MAX('Control Tower'!$B$121*(1+'Control Tower'!$B$49)^0,'Revenue Model'!I11*'Control Tower'!$C$121) | J32: =MAX('Control Tower'!$B$121*(1+'Control Tower'!$B$49)^0,'Revenue Model'!J11*'Control Tower'!$C$121) | ... N32: =MAX('Control Tower'!$B$121*(1+'Control Tower'!$B$49)^0,'Revenue Model'!N11*'Control Tower'!$C$121) | O32: =MAX('Control Tower'!$B$121*(1+'Control Tower'!$B$49)^1,'Revenue Model'!O11*'Control Tower'!$C$121) | P32: =MAX('Control Tower'!$B$121*(1+'Control Tower'!$B$49)^1,'Revenue Model'!P11*'Control Tower'!$C$121) | Q32: =MAX('Control Tower'!$B$121*(1+'Control Tower'!$B$49)^1,'Revenue Model'!Q11*'Control Tower'!$C$121) | R32: =MAX('Control Tower'!$B$121*(1+'Control Tower'!$B$49)^1,'Revenue Model'!R11*'Control Tower'!$C$121) | S32: =MAX('Control Tower'!$B$121*(1+'Control Tower'!$B$49)^1,'Revenue Model'!S11*'Control Tower'!$C$121) | T32: =MAX('Control Tower'!$B$121*(1+'Control Tower'!$B$49)^1,'Revenue Model'!T11*'Control Tower'!$C$121) | U32: =MAX('Control Tower'!$B$121*(1+'Control Tower'!$B$49)^1,'Revenue Model'!U11*'Control Tower'!$C$121) | V32: =MAX('Control Tower'!$B$121*(1+'Control Tower'!$B$49)^1,'Revenue Model'!V11*'Control Tower'!$C$121) | ... Z32: =MAX('Control Tower'!$B$121*(1+'Control Tower'!$B$49)^1,'Revenue Model'!Z11*'Control Tower'!$C$121) | AA32: =MAX('Control Tower'!$B$121*(1+'Control Tower'!$B$49)^2,'Revenue Model'!AA11*'Control Tower'!$C$121) | AB32: =MAX('Control Tower'!$B$121*(1+'Control Tower'!$B$49)^2,'Revenue Model'!AB11*'Control Tower'!$C$121) | AC32: =MAX('Control Tower'!$B$121*(1+'Control Tower'!$B$49)^2,'Revenue Model'!AC11*'Control Tower'!$C$121) | AD32: =MAX('Control Tower'!$B$121*(1+'Control Tower'!$B$49)^2,'Revenue Model'!AD11*'Control Tower'!$C$121) | AE32: =MAX('Control Tower'!$B$121*(1+'Control Tower'!$B$49)^2,'Revenue Model'!AE11*'Control Tower'!$C$121) | AF32: =MAX('Control Tower'!$B$121*(1+'Control Tower'!$B$49)^2,'Revenue Model'!AF11*'Control Tower'!$C$121) | AG32: =MAX('Control Tower'!$B$121*(1+'Control Tower'!$B$49)^2,'Revenue Model'!AG11*'Control Tower'!$C$121) | AH32: =MAX('Control Tower'!$B$121*(1+'Control Tower'!$B$49)^2,'Revenue Model'!AH11*'Control Tower'!$C$121) | ... AL32: =MAX('Control Tower'!$B$121*(1+'Control Tower'!$B$49)^2,'Revenue Model'!AL11*'Control Tower'!$C$121)

Sheet P&L
A1: AZALEA HOSPICE - REFUGE OPERATING MODEL
A2: P&L - COA-backed, accrual. Clinical labor above gross profit. Every cell is a link or formula.
A4: Month # | C4: 1 | D4: 2 | E4: 3 | F4: 4 | G4: 5 | H4: 6 | I4: 7 | J4: 8 | K4: 9 | L4: 10 | M4: 11 | N4: 12 | O4: 13 | P4: 14 | Q4: 15 | R4: 16 | S4: 17 | T4: 18 | U4: 19 | V4: 20 | W4: 21 | X4: 22 | Y4: 23 | Z4: 24 | AA4: 25 | AB4: 26 | AC4: 27 | AD4: 28 | AE4: 29 | AF4: 30 | AG4: 31 | AH4: 32 | AI4: 33 | AJ4: 34 | AK4: 35 | AL4: 36
C5: Jul-26 | D5: Aug-26 | E5: Sep-26 | F5: Oct-26 | G5: Nov-26 | H5: Dec-26 | I5: Jan-27 | J5: Feb-27 | K5: Mar-27 | L5: Apr-27 | M5: May-27 | N5: Jun-27 | O5: Jul-27 | P5: Aug-27 | Q5: Sep-27 | R5: Oct-27 | S5: Nov-27 | T5: Dec-27 | U5: Jan-28 | V5: Feb-28 | W5: Mar-28 | X5: Apr-28 | Y5: May-28 | Z5: Jun-28 | AA5: Jul-28 | AB5: Aug-28 | AC5: Sep-28 | AD5: Oct-28 | AE5: Nov-28 | AF5: Dec-28 | AG5: Jan-29 | AH5: Feb-29 | AI5: Mar-29 | AJ5: Apr-29 | AK5: May-29 | AL5: Jun-29
A6: Average Daily Census | C6: ='Census Waterfall'!C11 | D6: ='Census Waterfall'!D11 | E6: ='Census Waterfall'!E11 | F6: ='Census Waterfall'!F11 | G6: ='Census Waterfall'!G11 | H6: ='Census Waterfall'!H11 | I6: ='Census Waterfall'!I11 | J6: ='Census Waterfall'!J11 | ... AL6: ='Census Waterfall'!AL11
A7: REVENUE
A8: Medicare RHC high / low / Medicaid -> gross (3000/3010) | C8: ='Revenue Model'!C9 | D8: ='Revenue Model'!D9 | E8: ='Revenue Model'!E9 | F8: ='Revenue Model'!F9 | G8: ='Revenue Model'!G9 | H8: ='Revenue Model'!H9 | I8: ='Revenue Model'!I9 | J8: ='Revenue Model'!J9 | ... AL8: ='Revenue Model'!AL9
A9: Less: billing company fee (6510-Z) | C9: ='Revenue Model'!C10 | D9: ='Revenue Model'!D10 | E9: ='Revenue Model'!E10 | F9: ='Revenue Model'!F10 | G9: ='Revenue Model'!G10 | H9: ='Revenue Model'!H10 | I9: ='Revenue Model'!I10 | J9: ='Revenue Model'!J10 | ... AL9: ='Revenue Model'!AL10
A10: NET PATIENT REVENUE | C10: ='Revenue Model'!C11 | D10: ='Revenue Model'!D11 | E10: ='Revenue Model'!E11 | F10: ='Revenue Model'!F11 | G10: ='Revenue Model'!G11 | H10: ='Revenue Model'!H11 | I10: ='Revenue Model'!I11 | J10: ='Revenue Model'!J11 | ... AL10: ='Revenue Model'!AL11
A11: COST OF SERVICES
A12: Total direct patient care (5050-5120) | C12: ='Operating Budget'!C12 | D12: ='Operating Budget'!D12 | E12: ='Operating Budget'!E12 | F12: ='Operating Budget'!F12 | G12: ='Operating Budget'!G12 | H12: ='Operating Budget'!H12 | I12: ='Operating Budget'!I12 | J12: ='Operating Budget'!J12 | ... AL12: ='Operating Budget'!AL12
A13: Total direct clinical labor (4000/4025/4020) | C13: ='Staffing'!C37 | D13: ='Staffing'!D37 | E13: ='Staffing'!E37 | F13: ='Staffing'!F37 | G13: ='Staffing'!G37 | H13: ='Staffing'!H37 | I13: ='Staffing'!I37 | J13: ='Staffing'!J37 | ... AL13: ='Staffing'!AL37
A14: TOTAL COST OF SERVICES | C14: =C12+C13 | D14: =D12+D13 | E14: =E12+E13 | F14: =F12+F13 | G14: =G12+G13 | H14: =H12+H13 | I14: =I12+I13 | J14: =J12+J13 | ... AL14: =AL12+AL13
A15: GROSS PROFIT | C15: =C10-C14 | D15: =D10-D14 | E15: =E10-E14 | F15: =F10-F14 | G15: =G10-G14 | H15: =H10-H14 | I15: =I10-I14 | J15: =J10-J14 | ... AL15: =AL10-AL14
A16: Gross margin % | C16: =IF(C10=0,0,C15/C10) | D16: =IF(D10=0,0,D15/D10) | E16: =IF(E10=0,0,E15/E10) | F16: =IF(F10=0,0,F15/F10) | G16: =IF(G10=0,0,G15/G10) | H16: =IF(H10=0,0,H15/H10) | I16: =IF(I10=0,0,I15/I10) | J16: =IF(J10=0,0,J15/J10) | ... AL16: =IF(AL10=0,0,AL15/AL10)
A17: OPERATING EXPENSES
A18: Total indirect labor (4000-0-*) | C18: ='Staffing'!C38 | D18: ='Staffing'!D38 | E18: ='Staffing'!E38 | F18: ='Staffing'!F38 | G18: ='Staffing'!G38 | H18: ='Staffing'!H38 | I18: ='Staffing'!I38 | J18: ='Staffing'!J38 | ... AL18: ='Staffing'!AL38
A19: Total facility (6010-6150) | C19: ='Operating Budget'!C18 | D19: ='Operating Budget'!D18 | E19: ='Operating Budget'!E18 | F19: ='Operating Budget'!F18 | G19: ='Operating Budget'!G18 | H19: ='Operating Budget'!H18 | I19: ='Operating Budget'!I18 | J19: ='Operating Budget'!J18 | ... AL19: ='Operating Budget'!AL18
A20: Total G&A (6510-6810) | C20: ='Operating Budget'!C31 | D20: ='Operating Budget'!D31 | E20: ='Operating Budget'!E31 | F20: ='Operating Budget'!F31 | G20: ='Operating Budget'!G31 | H20: ='Operating Budget'!H31 | I20: ='Operating Budget'!I31 | J20: ='Operating Budget'!J31 | ... AL20: ='Operating Budget'!AL31
A21: License intangible amortization (7200) | C21: =IF(1>='Control Tower'!$B$27,'Control Tower'!$B$7/'Control Tower'!$B$26/12,0) | D21: =IF(2>='Control Tower'!$B$27,'Control Tower'!$B$7/'Control Tower'!$B$26/12,0) | E21: =IF(3>='Control Tower'!$B$27,'Control Tower'!$B$7/'Control Tower'!$B$26/12,0) | F21: =IF(4>='Control Tower'!$B$27,'Control Tower'!$B$7/'Control Tower'!$B$26/12,0) | G21: =IF(5>='Control Tower'!$B$27,'Control Tower'!$B$7/'Control Tower'!$B$26/12,0) | H21: =IF(6>='Control Tower'!$B$27,'Control Tower'!$B$7/'Control Tower'!$B$26/12,0) | I21: =IF(7>='Control Tower'!$B$27,'Control Tower'!$B$7/'Control Tower'!$B$26/12,0) | J21: =IF(8>='Control Tower'!$B$27,'Control Tower'!$B$7/'Control Tower'!$B$26/12,0) | K21: =IF(9>='Control Tower'!$B$27,'Control Tower'!$B$7/'Control Tower'!$B$26/12,0) | L21: =IF(10>='Control Tower'!$B$27,'Control Tower'!$B$7/'Control Tower'!$B$26/12,0) | M21: =IF(11>='Control Tower'!$B$27,'Control Tower'!$B$7/'Control Tower'!$B$26/12,0) | N21: =IF(12>='Control Tower'!$B$27,'Control Tower'!$B$7/'Control Tower'!$B$26/12,0) | O21: =IF(13>='Control Tower'!$B$27,'Control Tower'!$B$7/'Control Tower'!$B$26/12,0) | P21: =IF(14>='Control Tower'!$B$27,'Control Tower'!$B$7/'Control Tower'!$B$26/12,0) | Q21: =IF(15>='Control Tower'!$B$27,'Control Tower'!$B$7/'Control Tower'!$B$26/12,0) | R21: =IF(16>='Control Tower'!$B$27,'Control Tower'!$B$7/'Control Tower'!$B$26/12,0) | S21: =IF(17>='Control Tower'!$B$27,'Control Tower'!$B$7/'Control Tower'!$B$26/12,0) | T21: =IF(18>='Control Tower'!$B$27,'Control Tower'!$B$7/'Control Tower'!$B$26/12,0) | U21: =IF(19>='Control Tower'!$B$27,'Control Tower'!$B$7/'Control Tower'!$B$26/12,0) | V21: =IF(20>='Control Tower'!$B$27,'Control Tower'!$B$7/'Control Tower'!$B$26/12,0) | W21: =IF(21>='Control Tower'!$B$27,'Control Tower'!$B$7/'Control Tower'!$B$26/12,0) | X21: =IF(22>='Control Tower'!$B$27,'Control Tower'!$B$7/'Control Tower'!$B$26/12,0) | Y21: =IF(23>='Control Tower'!$B$27,'Control Tower'!$B$7/'Control Tower'!$B$26/12,0) | Z21: =IF(24>='Control Tower'!$B$27,'Control Tower'!$B$7/'Control Tower'!$B$26/12,0) | AA21: =IF(25>='Control Tower'!$B$27,'Control Tower'!$B$7/'Control Tower'!$B$26/12,0) | AB21: =IF(26>='Control Tower'!$B$27,'Control Tower'!$B$7/'Control Tower'!$B$26/12,0) | AC21: =IF(27>='Control Tower'!$B$27,'Control Tower'!$B$7/'Control Tower'!$B$26/12,0) | AD21: =IF(28>='Control Tower'!$B$27,'Control Tower'!$B$7/'Control Tower'!$B$26/12,0) | AE21: =IF(29>='Control Tower'!$B$27,'Control Tower'!$B$7/'Control Tower'!$B$26/12,0) | AF21: =IF(30>='Control Tower'!$B$27,'Control Tower'!$B$7/'Control Tower'!$B$26/12,0) | AG21: =IF(31>='Control Tower'!$B$27,'Control Tower'!$B$7/'Control Tower'!$B$26/12,0) | AH21: =IF(32>='Control Tower'!$B$27,'Control Tower'!$B$7/'Control Tower'!$B$26/12,0) | AI21: =IF(33>='Control Tower'!$B$27,'Control Tower'!$B$7/'Control Tower'!$B$26/12,0) | AJ21: =IF(34>='Control Tower'!$B$27,'Control Tower'!$B$7/'Control Tower'!$B$26/12,0) | AK21: =IF(35>='Control Tower'!$B$27,'Control Tower'!$B$7/'Control Tower'!$B$26/12,0) | AL21: =IF(36>='Control Tower'!$B$27,'Control Tower'!$B$7/'Control Tower'!$B$26/12,0)
A22: TOTAL OPERATING EXPENSES | C22: =C18+C19+C20+C21 | D22: =D18+D19+D20+D21 | E22: =E18+E19+E20+E21 | F22: =F18+F19+F20+F21 | G22: =G18+G19+G20+G21 | H22: =H18+H19+H20+H21 | I22: =I18+I19+I20+I21 | J22: =J18+J19+J20+J21 | ... AL22: =AL18+AL19+AL20+AL21
A23: EBIT (NOI) | C23: =C15-C22 | D23: =D15-D22 | E23: =E15-E22 | F23: =F15-F22 | G23: =G15-G22 | H23: =H15-H22 | I23: =I15-I22 | J23: =J15-J22 | ... AL23: =AL15-AL22
A24: EBITDA | C24: =C23+C21 | D24: =D23+D21 | E24: =E23+E21 | F24: =F23+F21 | G24: =G23+G21 | H24: =H23+H21 | I24: =I23+I21 | J24: =J23+J21 | ... AL24: =AL23+AL21
A25: EBITDA margin % | C25: =IF(C10=0,0,C24/C10) | D25: =IF(D10=0,0,D24/D10) | E25: =IF(E10=0,0,E24/E10) | F25: =IF(F10=0,0,F24/F10) | G25: =IF(G10=0,0,G24/G10) | H25: =IF(H10=0,0,H24/H10) | I25: =IF(I10=0,0,I24/I10) | J25: =IF(J10=0,0,J24/J10) | ... AL25: =IF(AL10=0,0,AL24/AL10)
A26: Contingency provision (below EBITDA, 6640-Z) | C26: ='Operating Budget'!C32 | D26: ='Operating Budget'!D32 | E26: ='Operating Budget'!E32 | F26: ='Operating Budget'!F32 | G26: ='Operating Budget'!G32 | H26: ='Operating Budget'!H32 | I26: ='Operating Budget'!I32 | J26: ='Operating Budget'!J32 | ... AL26: ='Operating Budget'!AL32

Sheet Cash Flow & Runway
A1: AZALEA HOSPICE - REFUGE OPERATING MODEL
A2: CASH FLOW - collections timing and payment hold; payroll in month; patient-care costs net-30; complete debt schedules. Direct method.
A4: Month # | C4: 1 | D4: 2 | E4: 3 | F4: 4 | G4: 5 | H4: 6 | I4: 7 | J4: 8 | K4: 9 | L4: 10 | M4: 11 | N4: 12 | O4: 13 | P4: 14 | Q4: 15 | R4: 16 | S4: 17 | T4: 18 | U4: 19 | V4: 20 | W4: 21 | X4: 22 | Y4: 23 | Z4: 24 | AA4: 25 | AB4: 26 | AC4: 27 | AD4: 28 | AE4: 29 | AF4: 30 | AG4: 31 | AH4: 32 | AI4: 33 | AJ4: 34 | AK4: 35 | AL4: 36
C5: Jul-26 | D5: Aug-26 | E5: Sep-26 | F5: Oct-26 | G5: Nov-26 | H5: Dec-26 | I5: Jan-27 | J5: Feb-27 | K5: Mar-27 | L5: Apr-27 | M5: May-27 | N5: Jun-27 | O5: Jul-27 | P5: Aug-27 | Q5: Sep-27 | R5: Oct-27 | S5: Nov-27 | T5: Dec-27 | U5: Jan-28 | V5: Feb-28 | W5: Mar-28 | X5: Apr-28 | Y5: May-28 | Z5: Jun-28 | AA5: Jul-28 | AB5: Aug-28 | AC5: Sep-28 | AD5: Oct-28 | AE5: Nov-28 | AF5: Dec-28 | AG5: Jan-29 | AH5: Feb-29 | AI5: Mar-29 | AJ5: Apr-29 | AK5: May-29 | AL5: Jun-29
A6: COLLECTIONS ENGINE
A7: Collection month for service month (lag + hold on first claims) | C7: =1+1+MAX(0,'Control Tower'!$B$40-0) | D7: =2+1+MAX(0,'Control Tower'!$B$40-1) | E7: =3+1+MAX(0,'Control Tower'!$B$40-2) | F7: =4+1+MAX(0,'Control Tower'!$B$40-3) | G7: =5+1+MAX(0,'Control Tower'!$B$40-4) | H7: =6+1+MAX(0,'Control Tower'!$B$40-5) | I7: =7+1+MAX(0,'Control Tower'!$B$40-6) | J7: =8+1+MAX(0,'Control Tower'!$B$40-7) | K7: =9+1+MAX(0,'Control Tower'!$B$40-8) | L7: =10+1+MAX(0,'Control Tower'!$B$40-9) | M7: =11+1+MAX(0,'Control Tower'!$B$40-10) | N7: =12+1+MAX(0,'Control Tower'!$B$40-11) | O7: =13+1+MAX(0,'Control Tower'!$B$40-12) | P7: =14+1+MAX(0,'Control Tower'!$B$40-13) | Q7: =15+1+MAX(0,'Control Tower'!$B$40-14) | R7: =16+1+MAX(0,'Control Tower'!$B$40-15) | S7: =17+1+MAX(0,'Control Tower'!$B$40-16) | T7: =18+1+MAX(0,'Control Tower'!$B$40-17) | U7: =19+1+MAX(0,'Control Tower'!$B$40-18) | V7: =20+1+MAX(0,'Control Tower'!$B$40-19) | W7: =21+1+MAX(0,'Control Tower'!$B$40-20) | X7: =22+1+MAX(0,'Control Tower'!$B$40-21) | Y7: =23+1+MAX(0,'Control Tower'!$B$40-22) | Z7: =24+1+MAX(0,'Control Tower'!$B$40-23) | AA7: =25+1+MAX(0,'Control Tower'!$B$40-24) | AB7: =26+1+MAX(0,'Control Tower'!$B$40-25) | AC7: =27+1+MAX(0,'Control Tower'!$B$40-26) | AD7: =28+1+MAX(0,'Control Tower'!$B$40-27) | AE7: =29+1+MAX(0,'Control Tower'!$B$40-28) | AF7: =30+1+MAX(0,'Control Tower'!$B$40-29) | AG7: =31+1+MAX(0,'Control Tower'!$B$40-30) | AH7: =32+1+MAX(0,'Control Tower'!$B$40-31) | AI7: =33+1+MAX(0,'Control Tower'!$B$40-32) | AJ7: =34+1+MAX(0,'Control Tower'!$B$40-33) | AK7: =35+1+MAX(0,'Control Tower'!$B$40-34) | AL7: =36+1+MAX(0,'Control Tower'!$B$40-35)
A8: NPR earned (link) | C8: ='Revenue Model'!C11 | D8: ='Revenue Model'!D11 | E8: ='Revenue Model'!E11 | F8: ='Revenue Model'!F11 | G8: ='Revenue Model'!G11 | H8: ='Revenue Model'!H11 | I8: ='Revenue Model'!I11 | J8: ='Revenue Model'!J11 | ... AL8: ='Revenue Model'!AL11
A9: CASH COLLECTIONS | C9: ='Control Tower'!$B$51*SUMPRODUCT(($C$7:$AL$7-1=1)*$C$8:$AL$8)+'Control Tower'!$B$52*SUMPRODUCT(($C$7:$AL$7=1)*$C$8:$AL$8)+'Control Tower'!$B$53*SUMPRODUCT(($C$7:$AL$7=0)*$C$8:$AL$8) | D9: ='Control Tower'!$B$51*SUMPRODUCT(($C$7:$AL$7-1=2)*$C$8:$AL$8)+'Control Tower'!$B$52*SUMPRODUCT(($C$7:$AL$7=2)*$C$8:$AL$8)+'Control Tower'!$B$53*SUMPRODUCT(($C$7:$AL$7=1)*$C$8:$AL$8) | E9: ='Control Tower'!$B$51*SUMPRODUCT(($C$7:$AL$7-1=3)*$C$8:$AL$8)+'Control Tower'!$B$52*SUMPRODUCT(($C$7:$AL$7=3)*$C$8:$AL$8)+'Control Tower'!$B$53*SUMPRODUCT(($C$7:$AL$7=2)*$C$8:$AL$8) | F9: ='Control Tower'!$B$51*SUMPRODUCT(($C$7:$AL$7-1=4)*$C$8:$AL$8)+'Control Tower'!$B$52*SUMPRODUCT(($C$7:$AL$7=4)*$C$8:$AL$8)+'Control Tower'!$B$53*SUMPRODUCT(($C$7:$AL$7=3)*$C$8:$AL$8) | G9: ='Control Tower'!$B$51*SUMPRODUCT(($C$7:$AL$7-1=5)*$C$8:$AL$8)+'Control Tower'!$B$52*SUMPRODUCT(($C$7:$AL$7=5)*$C$8:$AL$8)+'Control Tower'!$B$53*SUMPRODUCT(($C$7:$AL$7=4)*$C$8:$AL$8) | H9: ='Control Tower'!$B$51*SUMPRODUCT(($C$7:$AL$7-1=6)*$C$8:$AL$8)+'Control Tower'!$B$52*SUMPRODUCT(($C$7:$AL$7=6)*$C$8:$AL$8)+'Control Tower'!$B$53*SUMPRODUCT(($C$7:$AL$7=5)*$C$8:$AL$8) | I9: ='Control Tower'!$B$51*SUMPRODUCT(($C$7:$AL$7-1=7)*$C$8:$AL$8)+'Control Tower'!$B$52*SUMPRODUCT(($C$7:$AL$7=7)*$C$8:$AL$8)+'Control Tower'!$B$53*SUMPRODUCT(($C$7:$AL$7=6)*$C$8:$AL$8) | J9: ='Control Tower'!$B$51*SUMPRODUCT(($C$7:$AL$7-1=8)*$C$8:$AL$8)+'Control Tower'!$B$52*SUMPRODUCT(($C$7:$AL$7=8)*$C$8:$AL$8)+'Control Tower'!$B$53*SUMPRODUCT(($C$7:$AL$7=7)*$C$8:$AL$8) | K9: ='Control Tower'!$B$51*SUMPRODUCT(($C$7:$AL$7-1=9)*$C$8:$AL$8)+'Control Tower'!$B$52*SUMPRODUCT(($C$7:$AL$7=9)*$C$8:$AL$8)+'Control Tower'!$B$53*SUMPRODUCT(($C$7:$AL$7=8)*$C$8:$AL$8) | L9: ='Control Tower'!$B$51*SUMPRODUCT(($C$7:$AL$7-1=10)*$C$8:$AL$8)+'Control Tower'!$B$52*SUMPRODUCT(($C$7:$AL$7=10)*$C$8:$AL$8)+'Control Tower'!$B$53*SUMPRODUCT(($C$7:$AL$7=9)*$C$8:$AL$8) | M9: ='Control Tower'!$B$51*SUMPRODUCT(($C$7:$AL$7-1=11)*$C$8:$AL$8)+'Control Tower'!$B$52*SUMPRODUCT(($C$7:$AL$7=11)*$C$8:$AL$8)+'Control Tower'!$B$53*SUMPRODUCT(($C$7:$AL$7=10)*$C$8:$AL$8) | N9: ='Control Tower'!$B$51*SUMPRODUCT(($C$7:$AL$7-1=12)*$C$8:$AL$8)+'Control Tower'!$B$52*SUMPRODUCT(($C$7:$AL$7=12)*$C$8:$AL$8)+'Control Tower'!$B$53*SUMPRODUCT(($C$7:$AL$7=11)*$C$8:$AL$8) | O9: ='Control Tower'!$B$51*SUMPRODUCT(($C$7:$AL$7-1=13)*$C$8:$AL$8)+'Control Tower'!$B$52*SUMPRODUCT(($C$7:$AL$7=13)*$C$8:$AL$8)+'Control Tower'!$B$53*SUMPRODUCT(($C$7:$AL$7=12)*$C$8:$AL$8) | P9: ='Control Tower'!$B$51*SUMPRODUCT(($C$7:$AL$7-1=14)*$C$8:$AL$8)+'Control Tower'!$B$52*SUMPRODUCT(($C$7:$AL$7=14)*$C$8:$AL$8)+'Control Tower'!$B$53*SUMPRODUCT(($C$7:$AL$7=13)*$C$8:$AL$8) | Q9: ='Control Tower'!$B$51*SUMPRODUCT(($C$7:$AL$7-1=15)*$C$8:$AL$8)+'Control Tower'!$B$52*SUMPRODUCT(($C$7:$AL$7=15)*$C$8:$AL$8)+'Control Tower'!$B$53*SUMPRODUCT(($C$7:$AL$7=14)*$C$8:$AL$8) | R9: ='Control Tower'!$B$51*SUMPRODUCT(($C$7:$AL$7-1=16)*$C$8:$AL$8)+'Control Tower'!$B$52*SUMPRODUCT(($C$7:$AL$7=16)*$C$8:$AL$8)+'Control Tower'!$B$53*SUMPRODUCT(($C$7:$AL$7=15)*$C$8:$AL$8) | S9: ='Control Tower'!$B$51*SUMPRODUCT(($C$7:$AL$7-1=17)*$C$8:$AL$8)+'Control Tower'!$B$52*SUMPRODUCT(($C$7:$AL$7=17)*$C$8:$AL$8)+'Control Tower'!$B$53*SUMPRODUCT(($C$7:$AL$7=16)*$C$8:$AL$8) | T9: ='Control Tower'!$B$51*SUMPRODUCT(($C$7:$AL$7-1=18)*$C$8:$AL$8)+'Control Tower'!$B$52*SUMPRODUCT(($C$7:$AL$7=18)*$C$8:$AL$8)+'Control Tower'!$B$53*SUMPRODUCT(($C$7:$AL$7=17)*$C$8:$AL$8) | U9: ='Control Tower'!$B$51*SUMPRODUCT(($C$7:$AL$7-1=19)*$C$8:$AL$8)+'Control Tower'!$B$52*SUMPRODUCT(($C$7:$AL$7=19)*$C$8:$AL$8)+'Control Tower'!$B$53*SUMPRODUCT(($C$7:$AL$7=18)*$C$8:$AL$8) | V9: ='Control Tower'!$B$51*SUMPRODUCT(($C$7:$AL$7-1=20)*$C$8:$AL$8)+'Control Tower'!$B$52*SUMPRODUCT(($C$7:$AL$7=20)*$C$8:$AL$8)+'Control Tower'!$B$53*SUMPRODUCT(($C$7:$AL$7=19)*$C$8:$AL$8) | W9: ='Control Tower'!$B$51*SUMPRODUCT(($C$7:$AL$7-1=21)*$C$8:$AL$8)+'Control Tower'!$B$52*SUMPRODUCT(($C$7:$AL$7=21)*$C$8:$AL$8)+'Control Tower'!$B$53*SUMPRODUCT(($C$7:$AL$7=20)*$C$8:$AL$8) | X9: ='Control Tower'!$B$51*SUMPRODUCT(($C$7:$AL$7-1=22)*$C$8:$AL$8)+'Control Tower'!$B$52*SUMPRODUCT(($C$7:$AL$7=22)*$C$8:$AL$8)+'Control Tower'!$B$53*SUMPRODUCT(($C$7:$AL$7=21)*$C$8:$AL$8) | Y9: ='Control Tower'!$B$51*SUMPRODUCT(($C$7:$AL$7-1=23)*$C$8:$AL$8)+'Control Tower'!$B$52*SUMPRODUCT(($C$7:$AL$7=23)*$C$8:$AL$8)+'Control Tower'!$B$53*SUMPRODUCT(($C$7:$AL$7=22)*$C$8:$AL$8) | Z9: ='Control Tower'!$B$51*SUMPRODUCT(($C$7:$AL$7-1=24)*$C$8:$AL$8)+'Control Tower'!$B$52*SUMPRODUCT(($C$7:$AL$7=24)*$C$8:$AL$8)+'Control Tower'!$B$53*SUMPRODUCT(($C$7:$AL$7=23)*$C$8:$AL$8) | AA9: ='Control Tower'!$B$51*SUMPRODUCT(($C$7:$AL$7-1=25)*$C$8:$AL$8)+'Control Tower'!$B$52*SUMPRODUCT(($C$7:$AL$7=25)*$C$8:$AL$8)+'Control Tower'!$B$53*SUMPRODUCT(($C$7:$AL$7=24)*$C$8:$AL$8) | AB9: ='Control Tower'!$B$51*SUMPRODUCT(($C$7:$AL$7-1=26)*$C$8:$AL$8)+'Control Tower'!$B$52*SUMPRODUCT(($C$7:$AL$7=26)*$C$8:$AL$8)+'Control Tower'!$B$53*SUMPRODUCT(($C$7:$AL$7=25)*$C$8:$AL$8) | AC9: ='Control Tower'!$B$51*SUMPRODUCT(($C$7:$AL$7-1=27)*$C$8:$AL$8)+'Control Tower'!$B$52*SUMPRODUCT(($C$7:$AL$7=27)*$C$8:$AL$8)+'Control Tower'!$B$53*SUMPRODUCT(($C$7:$AL$7=26)*$C$8:$AL$8) | AD9: ='Control Tower'!$B$51*SUMPRODUCT(($C$7:$AL$7-1=28)*$C$8:$AL$8)+'Control Tower'!$B$52*SUMPRODUCT(($C$7:$AL$7=28)*$C$8:$AL$8)+'Control Tower'!$B$53*SUMPRODUCT(($C$7:$AL$7=27)*$C$8:$AL$8) | AE9: ='Control Tower'!$B$51*SUMPRODUCT(($C$7:$AL$7-1=29)*$C$8:$AL$8)+'Control Tower'!$B$52*SUMPRODUCT(($C$7:$AL$7=29)*$C$8:$AL$8)+'Control Tower'!$B$53*SUMPRODUCT(($C$7:$AL$7=28)*$C$8:$AL$8) | AF9: ='Control Tower'!$B$51*SUMPRODUCT(($C$7:$AL$7-1=30)*$C$8:$AL$8)+'Control Tower'!$B$52*SUMPRODUCT(($C$7:$AL$7=30)*$C$8:$AL$8)+'Control Tower'!$B$53*SUMPRODUCT(($C$7:$AL$7=29)*$C$8:$AL$8) | AG9: ='Control Tower'!$B$51*SUMPRODUCT(($C$7:$AL$7-1=31)*$C$8:$AL$8)+'Control Tower'!$B$52*SUMPRODUCT(($C$7:$AL$7=31)*$C$8:$AL$8)+'Control Tower'!$B$53*SUMPRODUCT(($C$7:$AL$7=30)*$C$8:$AL$8) | AH9: ='Control Tower'!$B$51*SUMPRODUCT(($C$7:$AL$7-1=32)*$C$8:$AL$8)+'Control Tower'!$B$52*SUMPRODUCT(($C$7:$AL$7=32)*$C$8:$AL$8)+'Control Tower'!$B$53*SUMPRODUCT(($C$7:$AL$7=31)*$C$8:$AL$8) | AI9: ='Control Tower'!$B$51*SUMPRODUCT(($C$7:$AL$7-1=33)*$C$8:$AL$8)+'Control Tower'!$B$52*SUMPRODUCT(($C$7:$AL$7=33)*$C$8:$AL$8)+'Control Tower'!$B$53*SUMPRODUCT(($C$7:$AL$7=32)*$C$8:$AL$8) | AJ9: ='Control Tower'!$B$51*SUMPRODUCT(($C$7:$AL$7-1=34)*$C$8:$AL$8)+'Control Tower'!$B$52*SUMPRODUCT(($C$7:$AL$7=34)*$C$8:$AL$8)+'Control Tower'!$B$53*SUMPRODUCT(($C$7:$AL$7=33)*$C$8:$AL$8) | AK9: ='Control Tower'!$B$51*SUMPRODUCT(($C$7:$AL$7-1=35)*$C$8:$AL$8)+'Control Tower'!$B$52*SUMPRODUCT(($C$7:$AL$7=35)*$C$8:$AL$8)+'Control Tower'!$B$53*SUMPRODUCT(($C$7:$AL$7=34)*$C$8:$AL$8) | AL9: ='Control Tower'!$B$51*SUMPRODUCT(($C$7:$AL$7-1=36)*$C$8:$AL$8)+'Control Tower'!$B$52*SUMPRODUCT(($C$7:$AL$7=36)*$C$8:$AL$8)+'Control Tower'!$B$53*SUMPRODUCT(($C$7:$AL$7=35)*$C$8:$AL$8)
A10: A/R balance (earned - collected, cumulative) | C10: =SUM($C$8:C8)-SUM($C$9:C9) | D10: =SUM($C$8:D8)-SUM($C$9:D9) | E10: =SUM($C$8:E8)-SUM($C$9:E9) | F10: =SUM($C$8:F8)-SUM($C$9:F9) | G10: =SUM($C$8:G8)-SUM($C$9:G9) | H10: =SUM($C$8:H8)-SUM($C$9:H9) | I10: =SUM($C$8:I8)-SUM($C$9:I9) | J10: =SUM($C$8:J8)-SUM($C$9:J9) | ... AL10: =SUM($C$8:AL8)-SUM($C$9:AL9)
A11: DEBT - SELLER NOTE (accepted terms; auto-payoff if full-refi ON)
A12: Seller beg balance | C12: ='Control Tower'!$B$7-'Control Tower'!$B$8 | D12: =C16 | E12: =D16 | F12: =E16 | G12: =F16 | H12: =G16 | I12: =H16 | J12: =I16 | K12: =J16 | ... AL12: =AK16
A13: Seller interest accrued (6% simple) | C13: =C12*'Control Tower'!$B$12/12 | D13: =D12*'Control Tower'!$B$12/12 | E13: =E12*'Control Tower'!$B$12/12 | F13: =F12*'Control Tower'!$B$12/12 | G13: =G12*'Control Tower'!$B$12/12 | H13: =H12*'Control Tower'!$B$12/12 | I13: =I12*'Control Tower'!$B$12/12 | J13: =J12*'Control Tower'!$B$12/12 | ... AL13: =AL12*'Control Tower'!$B$12/12
A14: Seller principal paid | C14: =IF(C12<=0,0,IF(AND('Control Tower'!$B$16=1,1='Control Tower'!$B$17),C12,IF(AND(1>='Control Tower'!$B$10,1<='Control Tower'!$B$11),'Control Tower'!$B$9*(1-'Control Tower'!$B$129),IF(1='Control Tower'!$B$13,C12,0)))) | D14: =IF(D12<=0,0,IF(AND('Control Tower'!$B$16=1,2='Control Tower'!$B$17),D12,IF(AND(2>='Control Tower'!$B$10,2<='Control Tower'!$B$11),'Control Tower'!$B$9*(1-'Control Tower'!$B$129),IF(2='Control Tower'!$B$13,D12,0)))) | E14: =IF(E12<=0,0,IF(AND('Control Tower'!$B$16=1,3='Control Tower'!$B$17),E12,IF(AND(3>='Control Tower'!$B$10,3<='Control Tower'!$B$11),'Control Tower'!$B$9*(1-'Control Tower'!$B$129),IF(3='Control Tower'!$B$13,E12,0)))) | F14: =IF(F12<=0,0,IF(AND('Control Tower'!$B$16=1,4='Control Tower'!$B$17),F12,IF(AND(4>='Control Tower'!$B$10,4<='Control Tower'!$B$11),'Control Tower'!$B$9*(1-'Control Tower'!$B$129),IF(4='Control Tower'!$B$13,F12,0)))) | G14: =IF(G12<=0,0,IF(AND('Control Tower'!$B$16=1,5='Control Tower'!$B$17),G12,IF(AND(5>='Control Tower'!$B$10,5<='Control Tower'!$B$11),'Control Tower'!$B$9*(1-'Control Tower'!$B$129),IF(5='Control Tower'!$B$13,G12,0)))) | H14: =IF(H12<=0,0,IF(AND('Control Tower'!$B$16=1,6='Control Tower'!$B$17),H12,IF(AND(6>='Control Tower'!$B$10,6<='Control Tower'!$B$11),'Control Tower'!$B$9*(1-'Control Tower'!$B$129),IF(6='Control Tower'!$B$13,H12,0)))) | I14: =IF(I12<=0,0,IF(AND('Control Tower'!$B$16=1,7='Control Tower'!$B$17),I12,IF(AND(7>='Control Tower'!$B$10,7<='Control Tower'!$B$11),'Control Tower'!$B$9*(1-'Control Tower'!$B$129),IF(7='Control Tower'!$B$13,I12,0)))) | J14: =IF(J12<=0,0,IF(AND('Control Tower'!$B$16=1,8='Control Tower'!$B$17),J12,IF(AND(8>='Control Tower'!$B$10,8<='Control Tower'!$B$11),'Control Tower'!$B$9*(1-'Control Tower'!$B$129),IF(8='Control Tower'!$B$13,J12,0)))) | K14: =IF(K12<=0,0,IF(AND('Control Tower'!$B$16=1,9='Control Tower'!$B$17),K12,IF(AND(9>='Control Tower'!$B$10,9<='Control Tower'!$B$11),'Control Tower'!$B$9*(1-'Control Tower'!$B$129),IF(9='Control Tower'!$B$13,K12,0)))) | L14: =IF(L12<=0,0,IF(AND('Control Tower'!$B$16=1,10='Control Tower'!$B$17),L12,IF(AND(10>='Control Tower'!$B$10,10<='Control Tower'!$B$11),'Control Tower'!$B$9*(1-'Control Tower'!$B$129),IF(10='Control Tower'!$B$13,L12,0)))) | M14: =IF(M12<=0,0,IF(AND('Control Tower'!$B$16=1,11='Control Tower'!$B$17),M12,IF(AND(11>='Control Tower'!$B$10,11<='Control Tower'!$B$11),'Control Tower'!$B$9*(1-'Control Tower'!$B$129),IF(11='Control Tower'!$B$13,M12,0)))) | N14: =IF(N12<=0,0,IF(AND('Control Tower'!$B$16=1,12='Control Tower'!$B$17),N12,IF(AND(12>='Control Tower'!$B$10,12<='Control Tower'!$B$11),'Control Tower'!$B$9*(1-'Control Tower'!$B$129),IF(12='Control Tower'!$B$13,N12,0)))) | O14: =IF(O12<=0,0,IF(AND('Control Tower'!$B$16=1,13='Control Tower'!$B$17),O12,IF(AND(13>='Control Tower'!$B$10,13<='Control Tower'!$B$11),'Control Tower'!$B$9*(1-'Control Tower'!$B$129),IF(13='Control Tower'!$B$13,O12,0)))) | P14: =IF(P12<=0,0,IF(AND('Control Tower'!$B$16=1,14='Control Tower'!$B$17),P12,IF(AND(14>='Control Tower'!$B$10,14<='Control Tower'!$B$11),'Control Tower'!$B$9*(1-'Control Tower'!$B$129),IF(14='Control Tower'!$B$13,P12,0)))) | Q14: =IF(Q12<=0,0,IF(AND('Control Tower'!$B$16=1,15='Control Tower'!$B$17),Q12,IF(AND(15>='Control Tower'!$B$10,15<='Control Tower'!$B$11),'Control Tower'!$B$9*(1-'Control Tower'!$B$129),IF(15='Control Tower'!$B$13,Q12,0)))) | R14: =IF(R12<=0,0,IF(AND('Control Tower'!$B$16=1,16='Control Tower'!$B$17),R12,IF(AND(16>='Control Tower'!$B$10,16<='Control Tower'!$B$11),'Control Tower'!$B$9*(1-'Control Tower'!$B$129),IF(16='Control Tower'!$B$13,R12,0)))) | S14: =IF(S12<=0,0,IF(AND('Control Tower'!$B$16=1,17='Control Tower'!$B$17),S12,IF(AND(17>='Control Tower'!$B$10,17<='Control Tower'!$B$11),'Control Tower'!$B$9*(1-'Control Tower'!$B$129),IF(17='Control Tower'!$B$13,S12,0)))) | T14: =IF(T12<=0,0,IF(AND('Control Tower'!$B$16=1,18='Control Tower'!$B$17),T12,IF(AND(18>='Control Tower'!$B$10,18<='Control Tower'!$B$11),'Control Tower'!$B$9*(1-'Control Tower'!$B$129),IF(18='Control Tower'!$B$13,T12,0)))) | U14: =IF(U12<=0,0,IF(AND('Control Tower'!$B$16=1,19='Control Tower'!$B$17),U12,IF(AND(19>='Control Tower'!$B$10,19<='Control Tower'!$B$11),'Control Tower'!$B$9*(1-'Control Tower'!$B$129),IF(19='Control Tower'!$B$13,U12,0)))) | V14: =IF(V12<=0,0,IF(AND('Control Tower'!$B$16=1,20='Control Tower'!$B$17),V12,IF(AND(20>='Control Tower'!$B$10,20<='Control Tower'!$B$11),'Control Tower'!$B$9*(1-'Control Tower'!$B$129),IF(20='Control Tower'!$B$13,V12,0)))) | W14: =IF(W12<=0,0,IF(AND('Control Tower'!$B$16=1,21='Control Tower'!$B$17),W12,IF(AND(21>='Control Tower'!$B$10,21<='Control Tower'!$B$11),'Control Tower'!$B$9*(1-'Control Tower'!$B$129),IF(21='Control Tower'!$B$13,W12,0)))) | X14: =IF(X12<=0,0,IF(AND('Control Tower'!$B$16=1,22='Control Tower'!$B$17),X12,IF(AND(22>='Control Tower'!$B$10,22<='Control Tower'!$B$11),'Control Tower'!$B$9*(1-'Control Tower'!$B$129),IF(22='Control Tower'!$B$13,X12,0)))) | Y14: =IF(Y12<=0,0,IF(AND('Control Tower'!$B$16=1,23='Control Tower'!$B$17),Y12,IF(AND(23>='Control Tower'!$B$10,23<='Control Tower'!$B$11),'Control Tower'!$B$9*(1-'Control Tower'!$B$129),IF(23='Control Tower'!$B$13,Y12,0)))) | Z14: =IF(Z12<=0,0,IF(AND('Control Tower'!$B$16=1,24='Control Tower'!$B$17),Z12,IF(AND(24>='Control Tower'!$B$10,24<='Control Tower'!$B$11),'Control Tower'!$B$9*(1-'Control Tower'!$B$129),IF(24='Control Tower'!$B$13,Z12,0)))) | AA14: =IF(AA12<=0,0,IF(AND('Control Tower'!$B$16=1,25='Control Tower'!$B$17),AA12,IF(AND(25>='Control Tower'!$B$10,25<='Control Tower'!$B$11),'Control Tower'!$B$9*(1-'Control Tower'!$B$129),IF(25='Control Tower'!$B$13,AA12,0)))) | AB14: =IF(AB12<=0,0,IF(AND('Control Tower'!$B$16=1,26='Control Tower'!$B$17),AB12,IF(AND(26>='Control Tower'!$B$10,26<='Control Tower'!$B$11),'Control Tower'!$B$9*(1-'Control Tower'!$B$129),IF(26='Control Tower'!$B$13,AB12,0)))) | AC14: =IF(AC12<=0,0,IF(AND('Control Tower'!$B$16=1,27='Control Tower'!$B$17),AC12,IF(AND(27>='Control Tower'!$B$10,27<='Control Tower'!$B$11),'Control Tower'!$B$9*(1-'Control Tower'!$B$129),IF(27='Control Tower'!$B$13,AC12,0)))) | AD14: =IF(AD12<=0,0,IF(AND('Control Tower'!$B$16=1,28='Control Tower'!$B$17),AD12,IF(AND(28>='Control Tower'!$B$10,28<='Control Tower'!$B$11),'Control Tower'!$B$9*(1-'Control Tower'!$B$129),IF(28='Control Tower'!$B$13,AD12,0)))) | AE14: =IF(AE12<=0,0,IF(AND('Control Tower'!$B$16=1,29='Control Tower'!$B$17),AE12,IF(AND(29>='Control Tower'!$B$10,29<='Control Tower'!$B$11),'Control Tower'!$B$9*(1-'Control Tower'!$B$129),IF(29='Control Tower'!$B$13,AE12,0)))) | AF14: =IF(AF12<=0,0,IF(AND('Control Tower'!$B$16=1,30='Control Tower'!$B$17),AF12,IF(AND(30>='Control Tower'!$B$10,30<='Control Tower'!$B$11),'Control Tower'!$B$9*(1-'Control Tower'!$B$129),IF(30='Control Tower'!$B$13,AF12,0)))) | AG14: =IF(AG12<=0,0,IF(AND('Control Tower'!$B$16=1,31='Control Tower'!$B$17),AG12,IF(AND(31>='Control Tower'!$B$10,31<='Control Tower'!$B$11),'Control Tower'!$B$9*(1-'Control Tower'!$B$129),IF(31='Control Tower'!$B$13,AG12,0)))) | AH14: =IF(AH12<=0,0,IF(AND('Control Tower'!$B$16=1,32='Control Tower'!$B$17),AH12,IF(AND(32>='Control Tower'!$B$10,32<='Control Tower'!$B$11),'Control Tower'!$B$9*(1-'Control Tower'!$B$129),IF(32='Control Tower'!$B$13,AH12,0)))) | AI14: =IF(AI12<=0,0,IF(AND('Control Tower'!$B$16=1,33='Control Tower'!$B$17),AI12,IF(AND(33>='Control Tower'!$B$10,33<='Control Tower'!$B$11),'Control Tower'!$B$9*(1-'Control Tower'!$B$129),IF(33='Control Tower'!$B$13,AI12,0)))) | AJ14: =IF(AJ12<=0,0,IF(AND('Control Tower'!$B$16=1,34='Control Tower'!$B$17),AJ12,IF(AND(34>='Control Tower'!$B$10,34<='Control Tower'!$B$11),'Control Tower'!$B$9*(1-'Control Tower'!$B$129),IF(34='Control Tower'!$B$13,AJ12,0)))) | AK14: =IF(AK12<=0,0,IF(AND('Control Tower'!$B$16=1,35='Control Tower'!$B$17),AK12,IF(AND(35>='Control Tower'!$B$10,35<='Control Tower'!$B$11),'Control Tower'!$B$9*(1-'Control Tower'!$B$129),IF(35='Control Tower'!$B$13,AK12,0)))) | AL14: =IF(AL12<=0,0,IF(AND('Control Tower'!$B$16=1,36='Control Tower'!$B$17),AL12,IF(AND(36>='Control Tower'!$B$10,36<='Control Tower'!$B$11),'Control Tower'!$B$9*(1-'Control Tower'!$B$129),IF(36='Control Tower'!$B$13,AL12,0))))
A15: Seller interest paid (at payoff) | C15: =IF(OR(AND('Control Tower'!$B$16=1,1='Control Tower'!$B$17),AND('Control Tower'!$B$16=0,1='Control Tower'!$B$13)),SUM($C$13:C13),0) | D15: =IF(OR(AND('Control Tower'!$B$16=1,2='Control Tower'!$B$17),AND('Control Tower'!$B$16=0,2='Control Tower'!$B$13)),SUM($C$13:D13),0) | E15: =IF(OR(AND('Control Tower'!$B$16=1,3='Control Tower'!$B$17),AND('Control Tower'!$B$16=0,3='Control Tower'!$B$13)),SUM($C$13:E13),0) | F15: =IF(OR(AND('Control Tower'!$B$16=1,4='Control Tower'!$B$17),AND('Control Tower'!$B$16=0,4='Control Tower'!$B$13)),SUM($C$13:F13),0) | G15: =IF(OR(AND('Control Tower'!$B$16=1,5='Control Tower'!$B$17),AND('Control Tower'!$B$16=0,5='Control Tower'!$B$13)),SUM($C$13:G13),0) | H15: =IF(OR(AND('Control Tower'!$B$16=1,6='Control Tower'!$B$17),AND('Control Tower'!$B$16=0,6='Control Tower'!$B$13)),SUM($C$13:H13),0) | I15: =IF(OR(AND('Control Tower'!$B$16=1,7='Control Tower'!$B$17),AND('Control Tower'!$B$16=0,7='Control Tower'!$B$13)),SUM($C$13:I13),0) | J15: =IF(OR(AND('Control Tower'!$B$16=1,8='Control Tower'!$B$17),AND('Control Tower'!$B$16=0,8='Control Tower'!$B$13)),SUM($C$13:J13),0) | K15: =IF(OR(AND('Control Tower'!$B$16=1,9='Control Tower'!$B$17),AND('Control Tower'!$B$16=0,9='Control Tower'!$B$13)),SUM($C$13:K13),0) | L15: =IF(OR(AND('Control Tower'!$B$16=1,10='Control Tower'!$B$17),AND('Control Tower'!$B$16=0,10='Control Tower'!$B$13)),SUM($C$13:L13),0) | M15: =IF(OR(AND('Control Tower'!$B$16=1,11='Control Tower'!$B$17),AND('Control Tower'!$B$16=0,11='Control Tower'!$B$13)),SUM($C$13:M13),0) | N15: =IF(OR(AND('Control Tower'!$B$16=1,12='Control Tower'!$B$17),AND('Control Tower'!$B$16=0,12='Control Tower'!$B$13)),SUM($C$13:N13),0) | O15: =IF(OR(AND('Control Tower'!$B$16=1,13='Control Tower'!$B$17),AND('Control Tower'!$B$16=0,13='Control Tower'!$B$13)),SUM($C$13:O13),0) | P15: =IF(OR(AND('Control Tower'!$B$16=1,14='Control Tower'!$B$17),AND('Control Tower'!$B$16=0,14='Control Tower'!$B$13)),SUM($C$13:P13),0) | Q15: =IF(OR(AND('Control Tower'!$B$16=1,15='Control Tower'!$B$17),AND('Control Tower'!$B$16=0,15='Control Tower'!$B$13)),SUM($C$13:Q13),0) | R15: =IF(OR(AND('Control Tower'!$B$16=1,16='Control Tower'!$B$17),AND('Control Tower'!$B$16=0,16='Control Tower'!$B$13)),SUM($C$13:R13),0) | S15: =IF(OR(AND('Control Tower'!$B$16=1,17='Control Tower'!$B$17),AND('Control Tower'!$B$16=0,17='Control Tower'!$B$13)),SUM($C$13:S13),0) | T15: =IF(OR(AND('Control Tower'!$B$16=1,18='Control Tower'!$B$17),AND('Control Tower'!$B$16=0,18='Control Tower'!$B$13)),SUM($C$13:T13),0) | U15: =IF(OR(AND('Control Tower'!$B$16=1,19='Control Tower'!$B$17),AND('Control Tower'!$B$16=0,19='Control Tower'!$B$13)),SUM($C$13:U13),0) | V15: =IF(OR(AND('Control Tower'!$B$16=1,20='Control Tower'!$B$17),AND('Control Tower'!$B$16=0,20='Control Tower'!$B$13)),SUM($C$13:V13),0) | W15: =IF(OR(AND('Control Tower'!$B$16=1,21='Control Tower'!$B$17),AND('Control Tower'!$B$16=0,21='Control Tower'!$B$13)),SUM($C$13:W13),0) | X15: =IF(OR(AND('Control Tower'!$B$16=1,22='Control Tower'!$B$17),AND('Control Tower'!$B$16=0,22='Control Tower'!$B$13)),SUM($C$13:X13),0) | Y15: =IF(OR(AND('Control Tower'!$B$16=1,23='Control Tower'!$B$17),AND('Control Tower'!$B$16=0,23='Control Tower'!$B$13)),SUM($C$13:Y13),0) | Z15: =IF(OR(AND('Control Tower'!$B$16=1,24='Control Tower'!$B$17),AND('Control Tower'!$B$16=0,24='Control Tower'!$B$13)),SUM($C$13:Z13),0) | AA15: =IF(OR(AND('Control Tower'!$B$16=1,25='Control Tower'!$B$17),AND('Control Tower'!$B$16=0,25='Control Tower'!$B$13)),SUM($C$13:AA13),0) | AB15: =IF(OR(AND('Control Tower'!$B$16=1,26='Control Tower'!$B$17),AND('Control Tower'!$B$16=0,26='Control Tower'!$B$13)),SUM($C$13:AB13),0) | AC15: =IF(OR(AND('Control Tower'!$B$16=1,27='Control Tower'!$B$17),AND('Control Tower'!$B$16=0,27='Control Tower'!$B$13)),SUM($C$13:AC13),0) | AD15: =IF(OR(AND('Control Tower'!$B$16=1,28='Control Tower'!$B$17),AND('Control Tower'!$B$16=0,28='Control Tower'!$B$13)),SUM($C$13:AD13),0) | AE15: =IF(OR(AND('Control Tower'!$B$16=1,29='Control Tower'!$B$17),AND('Control Tower'!$B$16=0,29='Control Tower'!$B$13)),SUM($C$13:AE13),0) | AF15: =IF(OR(AND('Control Tower'!$B$16=1,30='Control Tower'!$B$17),AND('Control Tower'!$B$16=0,30='Control Tower'!$B$13)),SUM($C$13:AF13),0) | AG15: =IF(OR(AND('Control Tower'!$B$16=1,31='Control Tower'!$B$17),AND('Control Tower'!$B$16=0,31='Control Tower'!$B$13)),SUM($C$13:AG13),0) | AH15: =IF(OR(AND('Control Tower'!$B$16=1,32='Control Tower'!$B$17),AND('Control Tower'!$B$16=0,32='Control Tower'!$B$13)),SUM($C$13:AH13),0) | AI15: =IF(OR(AND('Control Tower'!$B$16=1,33='Control Tower'!$B$17),AND('Control Tower'!$B$16=0,33='Control Tower'!$B$13)),SUM($C$13:AI13),0) | AJ15: =IF(OR(AND('Control Tower'!$B$16=1,34='Control Tower'!$B$17),AND('Control Tower'!$B$16=0,34='Control Tower'!$B$13)),SUM($C$13:AJ13),0) | AK15: =IF(OR(AND('Control Tower'!$B$16=1,35='Control Tower'!$B$17),AND('Control Tower'!$B$16=0,35='Control Tower'!$B$13)),SUM($C$13:AK13),0) | AL15: =IF(OR(AND('Control Tower'!$B$16=1,36='Control Tower'!$B$17),AND('Control Tower'!$B$16=0,36='Control Tower'!$B$13)),SUM($C$13:AL13),0)
A16: Seller end balance | C16: =C12-C14 | D16: =D12-D14 | E16: =E12-E14 | F16: =F12-F14 | G16: =G12-G14 | H16: =H12-H14 | I16: =I12-I14 | J16: =J12-J14 | ... AL16: =AL12-AL14
A17: DEBT - BALLOON REFINANCING / INTERIM BANK NOTE / SBA 7(a) (per scenario settings)
A18: Balloon refi amount | B18: =IF(OR('Control Tower'!$B$16=1,'Control Tower'!$B$21=1),0,SUMPRODUCT(($C$4:$AL$4='Control Tower'!$B$13)*($C$14:$AL$14+$C$15:$AL$15)))
A19: Balloon refi - payment (P&I) | C19: =IF(AND(AND('Control Tower'!$B$16=0,'Control Tower'!$B$21=0),1>'Control Tower'!$B$13,1<='Control Tower'!$B$13+'Control Tower'!$B$15),-PMT('Control Tower'!$B$14/12,'Control Tower'!$B$15,$B$18),0) | D19: =IF(AND(AND('Control Tower'!$B$16=0,'Control Tower'!$B$21=0),2>'Control Tower'!$B$13,2<='Control Tower'!$B$13+'Control Tower'!$B$15),-PMT('Control Tower'!$B$14/12,'Control Tower'!$B$15,$B$18),0) | E19: =IF(AND(AND('Control Tower'!$B$16=0,'Control Tower'!$B$21=0),3>'Control Tower'!$B$13,3<='Control Tower'!$B$13+'Control Tower'!$B$15),-PMT('Control Tower'!$B$14/12,'Control Tower'!$B$15,$B$18),0) | F19: =IF(AND(AND('Control Tower'!$B$16=0,'Control Tower'!$B$21=0),4>'Control Tower'!$B$13,4<='Control Tower'!$B$13+'Control Tower'!$B$15),-PMT('Control Tower'!$B$14/12,'Control Tower'!$B$15,$B$18),0) | G19: =IF(AND(AND('Control Tower'!$B$16=0,'Control Tower'!$B$21=0),5>'Control Tower'!$B$13,5<='Control Tower'!$B$13+'Control Tower'!$B$15),-PMT('Control Tower'!$B$14/12,'Control Tower'!$B$15,$B$18),0) | H19: =IF(AND(AND('Control Tower'!$B$16=0,'Control Tower'!$B$21=0),6>'Control Tower'!$B$13,6<='Control Tower'!$B$13+'Control Tower'!$B$15),-PMT('Control Tower'!$B$14/12,'Control Tower'!$B$15,$B$18),0) | I19: =IF(AND(AND('Control Tower'!$B$16=0,'Control Tower'!$B$21=0),7>'Control Tower'!$B$13,7<='Control Tower'!$B$13+'Control Tower'!$B$15),-PMT('Control Tower'!$B$14/12,'Control Tower'!$B$15,$B$18),0) | J19: =IF(AND(AND('Control Tower'!$B$16=0,'Control Tower'!$B$21=0),8>'Control Tower'!$B$13,8<='Control Tower'!$B$13+'Control Tower'!$B$15),-PMT('Control Tower'!$B$14/12,'Control Tower'!$B$15,$B$18),0) | K19: =IF(AND(AND('Control Tower'!$B$16=0,'Control Tower'!$B$21=0),9>'Control Tower'!$B$13,9<='Control Tower'!$B$13+'Control Tower'!$B$15),-PMT('Control Tower'!$B$14/12,'Control Tower'!$B$15,$B$18),0) | L19: =IF(AND(AND('Control Tower'!$B$16=0,'Control Tower'!$B$21=0),10>'Control Tower'!$B$13,10<='Control Tower'!$B$13+'Control Tower'!$B$15),-PMT('Control Tower'!$B$14/12,'Control Tower'!$B$15,$B$18),0) | M19: =IF(AND(AND('Control Tower'!$B$16=0,'Control Tower'!$B$21=0),11>'Control Tower'!$B$13,11<='Control Tower'!$B$13+'Control Tower'!$B$15),-PMT('Control Tower'!$B$14/12,'Control Tower'!$B$15,$B$18),0) | N19: =IF(AND(AND('Control Tower'!$B$16=0,'Control Tower'!$B$21=0),12>'Control Tower'!$B$13,12<='Control Tower'!$B$13+'Control Tower'!$B$15),-PMT('Control Tower'!$B$14/12,'Control Tower'!$B$15,$B$18),0) | O19: =IF(AND(AND('Control Tower'!$B$16=0,'Control Tower'!$B$21=0),13>'Control Tower'!$B$13,13<='Control Tower'!$B$13+'Control Tower'!$B$15),-PMT('Control Tower'!$B$14/12,'Control Tower'!$B$15,$B$18),0) | P19: =IF(AND(AND('Control Tower'!$B$16=0,'Control Tower'!$B$21=0),14>'Control Tower'!$B$13,14<='Control Tower'!$B$13+'Control Tower'!$B$15),-PMT('Control Tower'!$B$14/12,'Control Tower'!$B$15,$B$18),0) | Q19: =IF(AND(AND('Control Tower'!$B$16=0,'Control Tower'!$B$21=0),15>'Control Tower'!$B$13,15<='Control Tower'!$B$13+'Control Tower'!$B$15),-PMT('Control Tower'!$B$14/12,'Control Tower'!$B$15,$B$18),0) | R19: =IF(AND(AND('Control Tower'!$B$16=0,'Control Tower'!$B$21=0),16>'Control Tower'!$B$13,16<='Control Tower'!$B$13+'Control Tower'!$B$15),-PMT('Control Tower'!$B$14/12,'Control Tower'!$B$15,$B$18),0) | S19: =IF(AND(AND('Control Tower'!$B$16=0,'Control Tower'!$B$21=0),17>'Control Tower'!$B$13,17<='Control Tower'!$B$13+'Control Tower'!$B$15),-PMT('Control Tower'!$B$14/12,'Control Tower'!$B$15,$B$18),0) | T19: =IF(AND(AND('Control Tower'!$B$16=0,'Control Tower'!$B$21=0),18>'Control Tower'!$B$13,18<='Control Tower'!$B$13+'Control Tower'!$B$15),-PMT('Control Tower'!$B$14/12,'Control Tower'!$B$15,$B$18),0) | U19: =IF(AND(AND('Control Tower'!$B$16=0,'Control Tower'!$B$21=0),19>'Control Tower'!$B$13,19<='Control Tower'!$B$13+'Control Tower'!$B$15),-PMT('Control Tower'!$B$14/12,'Control Tower'!$B$15,$B$18),0) | V19: =IF(AND(AND('Control Tower'!$B$16=0,'Control Tower'!$B$21=0),20>'Control Tower'!$B$13,20<='Control Tower'!$B$13+'Control Tower'!$B$15),-PMT('Control Tower'!$B$14/12,'Control Tower'!$B$15,$B$18),0) | W19: =IF(AND(AND('Control Tower'!$B$16=0,'Control Tower'!$B$21=0),21>'Control Tower'!$B$13,21<='Control Tower'!$B$13+'Control Tower'!$B$15),-PMT('Control Tower'!$B$14/12,'Control Tower'!$B$15,$B$18),0) | X19: =IF(AND(AND('Control Tower'!$B$16=0,'Control Tower'!$B$21=0),22>'Control Tower'!$B$13,22<='Control Tower'!$B$13+'Control Tower'!$B$15),-PMT('Control Tower'!$B$14/12,'Control Tower'!$B$15,$B$18),0) | Y19: =IF(AND(AND('Control Tower'!$B$16=0,'Control Tower'!$B$21=0),23>'Control Tower'!$B$13,23<='Control Tower'!$B$13+'Control Tower'!$B$15),-PMT('Control Tower'!$B$14/12,'Control Tower'!$B$15,$B$18),0) | Z19: =IF(AND(AND('Control Tower'!$B$16=0,'Control Tower'!$B$21=0),24>'Control Tower'!$B$13,24<='Control Tower'!$B$13+'Control Tower'!$B$15),-PMT('Control Tower'!$B$14/12,'Control Tower'!$B$15,$B$18),0) | AA19: =IF(AND(AND('Control Tower'!$B$16=0,'Control Tower'!$B$21=0),25>'Control Tower'!$B$13,25<='Control Tower'!$B$13+'Control Tower'!$B$15),-PMT('Control Tower'!$B$14/12,'Control Tower'!$B$15,$B$18),0) | AB19: =IF(AND(AND('Control Tower'!$B$16=0,'Control Tower'!$B$21=0),26>'Control Tower'!$B$13,26<='Control Tower'!$B$13+'Control Tower'!$B$15),-PMT('Control Tower'!$B$14/12,'Control Tower'!$B$15,$B$18),0) | AC19: =IF(AND(AND('Control Tower'!$B$16=0,'Control Tower'!$B$21=0),27>'Control Tower'!$B$13,27<='Control Tower'!$B$13+'Control Tower'!$B$15),-PMT('Control Tower'!$B$14/12,'Control Tower'!$B$15,$B$18),0) | AD19: =IF(AND(AND('Control Tower'!$B$16=0,'Control Tower'!$B$21=0),28>'Control Tower'!$B$13,28<='Control Tower'!$B$13+'Control Tower'!$B$15),-PMT('Control Tower'!$B$14/12,'Control Tower'!$B$15,$B$18),0) | AE19: =IF(AND(AND('Control Tower'!$B$16=0,'Control Tower'!$B$21=0),29>'Control Tower'!$B$13,29<='Control Tower'!$B$13+'Control Tower'!$B$15),-PMT('Control Tower'!$B$14/12,'Control Tower'!$B$15,$B$18),0) | AF19: =IF(AND(AND('Control Tower'!$B$16=0,'Control Tower'!$B$21=0),30>'Control Tower'!$B$13,30<='Control Tower'!$B$13+'Control Tower'!$B$15),-PMT('Control Tower'!$B$14/12,'Control Tower'!$B$15,$B$18),0) | AG19: =IF(AND(AND('Control Tower'!$B$16=0,'Control Tower'!$B$21=0),31>'Control Tower'!$B$13,31<='Control Tower'!$B$13+'Control Tower'!$B$15),-PMT('Control Tower'!$B$14/12,'Control Tower'!$B$15,$B$18),0) | AH19: =IF(AND(AND('Control Tower'!$B$16=0,'Control Tower'!$B$21=0),32>'Control Tower'!$B$13,32<='Control Tower'!$B$13+'Control Tower'!$B$15),-PMT('Control Tower'!$B$14/12,'Control Tower'!$B$15,$B$18),0) | AI19: =IF(AND(AND('Control Tower'!$B$16=0,'Control Tower'!$B$21=0),33>'Control Tower'!$B$13,33<='Control Tower'!$B$13+'Control Tower'!$B$15),-PMT('Control Tower'!$B$14/12,'Control Tower'!$B$15,$B$18),0) | AJ19: =IF(AND(AND('Control Tower'!$B$16=0,'Control Tower'!$B$21=0),34>'Control Tower'!$B$13,34<='Control Tower'!$B$13+'Control Tower'!$B$15),-PMT('Control Tower'!$B$14/12,'Control Tower'!$B$15,$B$18),0) | AK19: =IF(AND(AND('Control Tower'!$B$16=0,'Control Tower'!$B$21=0),35>'Control Tower'!$B$13,35<='Control Tower'!$B$13+'Control Tower'!$B$15),-PMT('Control Tower'!$B$14/12,'Control Tower'!$B$15,$B$18),0) | AL19: =IF(AND(AND('Control Tower'!$B$16=0,'Control Tower'!$B$21=0),36>'Control Tower'!$B$13,36<='Control Tower'!$B$13+'Control Tower'!$B$15),-PMT('Control Tower'!$B$14/12,'Control Tower'!$B$15,$B$18),0)
A20: Balloon refi - balance (end) | C20: =IF(NOT(AND('Control Tower'!$B$16=0,'Control Tower'!$B$21=0)),0,IF(1<'Control Tower'!$B$13,0,IF(1='Control Tower'!$B$13,$B$18,MAX(0,0*(1+'Control Tower'!$B$14/12)-C19)))) | D20: =IF(NOT(AND('Control Tower'!$B$16=0,'Control Tower'!$B$21=0)),0,IF(2<'Control Tower'!$B$13,0,IF(2='Control Tower'!$B$13,$B$18,MAX(0,C20*(1+'Control Tower'!$B$14/12)-D19)))) | E20: =IF(NOT(AND('Control Tower'!$B$16=0,'Control Tower'!$B$21=0)),0,IF(3<'Control Tower'!$B$13,0,IF(3='Control Tower'!$B$13,$B$18,MAX(0,D20*(1+'Control Tower'!$B$14/12)-E19)))) | F20: =IF(NOT(AND('Control Tower'!$B$16=0,'Control Tower'!$B$21=0)),0,IF(4<'Control Tower'!$B$13,0,IF(4='Control Tower'!$B$13,$B$18,MAX(0,E20*(1+'Control Tower'!$B$14/12)-F19)))) | G20: =IF(NOT(AND('Control Tower'!$B$16=0,'Control Tower'!$B$21=0)),0,IF(5<'Control Tower'!$B$13,0,IF(5='Control Tower'!$B$13,$B$18,MAX(0,F20*(1+'Control Tower'!$B$14/12)-G19)))) | H20: =IF(NOT(AND('Control Tower'!$B$16=0,'Control Tower'!$B$21=0)),0,IF(6<'Control Tower'!$B$13,0,IF(6='Control Tower'!$B$13,$B$18,MAX(0,G20*(1+'Control Tower'!$B$14/12)-H19)))) | I20: =IF(NOT(AND('Control Tower'!$B$16=0,'Control Tower'!$B$21=0)),0,IF(7<'Control Tower'!$B$13,0,IF(7='Control Tower'!$B$13,$B$18,MAX(0,H20*(1+'Control Tower'!$B$14/12)-I19)))) | J20: =IF(NOT(AND('Control Tower'!$B$16=0,'Control Tower'!$B$21=0)),0,IF(8<'Control Tower'!$B$13,0,IF(8='Control Tower'!$B$13,$B$18,MAX(0,I20*(1+'Control Tower'!$B$14/12)-J19)))) | K20: =IF(NOT(AND('Control Tower'!$B$16=0,'Control Tower'!$B$21=0)),0,IF(9<'Control Tower'!$B$13,0,IF(9='Control Tower'!$B$13,$B$18,MAX(0,J20*(1+'Control Tower'!$B$14/12)-K19)))) | L20: =IF(NOT(AND('Control Tower'!$B$16=0,'Control Tower'!$B$21=0)),0,IF(10<'Control Tower'!$B$13,0,IF(10='Control Tower'!$B$13,$B$18,MAX(0,K20*(1+'Control Tower'!$B$14/12)-L19)))) | M20: =IF(NOT(AND('Control Tower'!$B$16=0,'Control Tower'!$B$21=0)),0,IF(11<'Control Tower'!$B$13,0,IF(11='Control Tower'!$B$13,$B$18,MAX(0,L20*(1+'Control Tower'!$B$14/12)-M19)))) | N20: =IF(NOT(AND('Control Tower'!$B$16=0,'Control Tower'!$B$21=0)),0,IF(12<'Control Tower'!$B$13,0,IF(12='Control Tower'!$B$13,$B$18,MAX(0,M20*(1+'Control Tower'!$B$14/12)-N19)))) | O20: =IF(NOT(AND('Control Tower'!$B$16=0,'Control Tower'!$B$21=0)),0,IF(13<'Control Tower'!$B$13,0,IF(13='Control Tower'!$B$13,$B$18,MAX(0,N20*(1+'Control Tower'!$B$14/12)-O19)))) | P20: =IF(NOT(AND('Control Tower'!$B$16=0,'Control Tower'!$B$21=0)),0,IF(14<'Control Tower'!$B$13,0,IF(14='Control Tower'!$B$13,$B$18,MAX(0,O20*(1+'Control Tower'!$B$14/12)-P19)))) | Q20: =IF(NOT(AND('Control Tower'!$B$16=0,'Control Tower'!$B$21=0)),0,IF(15<'Control Tower'!$B$13,0,IF(15='Control Tower'!$B$13,$B$18,MAX(0,P20*(1+'Control Tower'!$B$14/12)-Q19)))) | R20: =IF(NOT(AND('Control Tower'!$B$16=0,'Control Tower'!$B$21=0)),0,IF(16<'Control Tower'!$B$13,0,IF(16='Control Tower'!$B$13,$B$18,MAX(0,Q20*(1+'Control Tower'!$B$14/12)-R19)))) | S20: =IF(NOT(AND('Control Tower'!$B$16=0,'Control Tower'!$B$21=0)),0,IF(17<'Control Tower'!$B$13,0,IF(17='Control Tower'!$B$13,$B$18,MAX(0,R20*(1+'Control Tower'!$B$14/12)-S19)))) | T20: =IF(NOT(AND('Control Tower'!$B$16=0,'Control Tower'!$B$21=0)),0,IF(18<'Control Tower'!$B$13,0,IF(18='Control Tower'!$B$13,$B$18,MAX(0,S20*(1+'Control Tower'!$B$14/12)-T19)))) | U20: =IF(NOT(AND('Control Tower'!$B$16=0,'Control Tower'!$B$21=0)),0,IF(19<'Control Tower'!$B$13,0,IF(19='Control Tower'!$B$13,$B$18,MAX(0,T20*(1+'Control Tower'!$B$14/12)-U19)))) | V20: =IF(NOT(AND('Control Tower'!$B$16=0,'Control Tower'!$B$21=0)),0,IF(20<'Control Tower'!$B$13,0,IF(20='Control Tower'!$B$13,$B$18,MAX(0,U20*(1+'Control Tower'!$B$14/12)-V19)))) | W20: =IF(NOT(AND('Control Tower'!$B$16=0,'Control Tower'!$B$21=0)),0,IF(21<'Control Tower'!$B$13,0,IF(21='Control Tower'!$B$13,$B$18,MAX(0,V20*(1+'Control Tower'!$B$14/12)-W19)))) | X20: =IF(NOT(AND('Control Tower'!$B$16=0,'Control Tower'!$B$21=0)),0,IF(22<'Control Tower'!$B$13,0,IF(22='Control Tower'!$B$13,$B$18,MAX(0,W20*(1+'Control Tower'!$B$14/12)-X19)))) | Y20: =IF(NOT(AND('Control Tower'!$B$16=0,'Control Tower'!$B$21=0)),0,IF(23<'Control Tower'!$B$13,0,IF(23='Control Tower'!$B$13,$B$18,MAX(0,X20*(1+'Control Tower'!$B$14/12)-Y19)))) | Z20: =IF(NOT(AND('Control Tower'!$B$16=0,'Control Tower'!$B$21=0)),0,IF(24<'Control Tower'!$B$13,0,IF(24='Control Tower'!$B$13,$B$18,MAX(0,Y20*(1+'Control Tower'!$B$14/12)-Z19)))) | AA20: =IF(NOT(AND('Control Tower'!$B$16=0,'Control Tower'!$B$21=0)),0,IF(25<'Control Tower'!$B$13,0,IF(25='Control Tower'!$B$13,$B$18,MAX(0,Z20*(1+'Control Tower'!$B$14/12)-AA19)))) | AB20: =IF(NOT(AND('Control Tower'!$B$16=0,'Control Tower'!$B$21=0)),0,IF(26<'Control Tower'!$B$13,0,IF(26='Control Tower'!$B$13,$B$18,MAX(0,AA20*(1+'Control Tower'!$B$14/12)-AB19)))) | AC20: =IF(NOT(AND('Control Tower'!$B$16=0,'Control Tower'!$B$21=0)),0,IF(27<'Control Tower'!$B$13,0,IF(27='Control Tower'!$B$13,$B$18,MAX(0,AB20*(1+'Control Tower'!$B$14/12)-AC19)))) | AD20: =IF(NOT(AND('Control Tower'!$B$16=0,'Control Tower'!$B$21=0)),0,IF(28<'Control Tower'!$B$13,0,IF(28='Control Tower'!$B$13,$B$18,MAX(0,AC20*(1+'Control Tower'!$B$14/12)-AD19)))) | AE20: =IF(NOT(AND('Control Tower'!$B$16=0,'Control Tower'!$B$21=0)),0,IF(29<'Control Tower'!$B$13,0,IF(29='Control Tower'!$B$13,$B$18,MAX(0,AD20*(1+'Control Tower'!$B$14/12)-AE19)))) | AF20: =IF(NOT(AND('Control Tower'!$B$16=0,'Control Tower'!$B$21=0)),0,IF(30<'Control Tower'!$B$13,0,IF(30='Control Tower'!$B$13,$B$18,MAX(0,AE20*(1+'Control Tower'!$B$14/12)-AF19)))) | AG20: =IF(NOT(AND('Control Tower'!$B$16=0,'Control Tower'!$B$21=0)),0,IF(31<'Control Tower'!$B$13,0,IF(31='Control Tower'!$B$13,$B$18,MAX(0,AF20*(1+'Control Tower'!$B$14/12)-AG19)))) | AH20: =IF(NOT(AND('Control Tower'!$B$16=0,'Control Tower'!$B$21=0)),0,IF(32<'Control Tower'!$B$13,0,IF(32='Control Tower'!$B$13,$B$18,MAX(0,AG20*(1+'Control Tower'!$B$14/12)-AH19)))) | AI20: =IF(NOT(AND('Control Tower'!$B$16=0,'Control Tower'!$B$21=0)),0,IF(33<'Control Tower'!$B$13,0,IF(33='Control Tower'!$B$13,$B$18,MAX(0,AH20*(1+'Control Tower'!$B$14/12)-AI19)))) | AJ20: =IF(NOT(AND('Control Tower'!$B$16=0,'Control Tower'!$B$21=0)),0,IF(34<'Control Tower'!$B$13,0,IF(34='Control Tower'!$B$13,$B$18,MAX(0,AI20*(1+'Control Tower'!$B$14/12)-AJ19)))) | AK20: =IF(NOT(AND('Control Tower'!$B$16=0,'Control Tower'!$B$21=0)),0,IF(35<'Control Tower'!$B$13,0,IF(35='Control Tower'!$B$13,$B$18,MAX(0,AJ20*(1+'Control Tower'!$B$14/12)-AK19)))) | AL20: =IF(NOT(AND('Control Tower'!$B$16=0,'Control Tower'!$B$21=0)),0,IF(36<'Control Tower'!$B$13,0,IF(36='Control Tower'!$B$13,$B$18,MAX(0,AK20*(1+'Control Tower'!$B$14/12)-AL19))))
A21: Balloon refi - interest | C21: =0*'Control Tower'!$B$14/12*(C19>0) | D21: =C20*'Control Tower'!$B$14/12*(D19>0) | E21: =D20*'Control Tower'!$B$14/12*(E19>0) | F21: =E20*'Control Tower'!$B$14/12*(F19>0) | G21: =F20*'Control Tower'!$B$14/12*(G19>0) | H21: =G20*'Control Tower'!$B$14/12*(H19>0) | I21: =H20*'Control Tower'!$B$14/12*(I19>0) | J21: =I20*'Control Tower'!$B$14/12*(J19>0) | K21: =J20*'Control Tower'!$B$14/12*(K19>0) | ... AL21: =AK20*'Control Tower'!$B$14/12*(AL19>0)
A22: Full refi - payment (P&I) | C22: =IF(AND('Control Tower'!$B$16=1,1>'Control Tower'!$B$17,1<='Control Tower'!$B$17+'Control Tower'!$B$20,NOT(AND('Control Tower'!$B$21=1,1>='Control Tower'!$B$22))),-PMT('Control Tower'!$B$19/12,'Control Tower'!$B$20,'Control Tower'!$B$18),0) | D22: =IF(AND('Control Tower'!$B$16=1,2>'Control Tower'!$B$17,2<='Control Tower'!$B$17+'Control Tower'!$B$20,NOT(AND('Control Tower'!$B$21=1,2>='Control Tower'!$B$22))),-PMT('Control Tower'!$B$19/12,'Control Tower'!$B$20,'Control Tower'!$B$18),0) | E22: =IF(AND('Control Tower'!$B$16=1,3>'Control Tower'!$B$17,3<='Control Tower'!$B$17+'Control Tower'!$B$20,NOT(AND('Control Tower'!$B$21=1,3>='Control Tower'!$B$22))),-PMT('Control Tower'!$B$19/12,'Control Tower'!$B$20,'Control Tower'!$B$18),0) | F22: =IF(AND('Control Tower'!$B$16=1,4>'Control Tower'!$B$17,4<='Control Tower'!$B$17+'Control Tower'!$B$20,NOT(AND('Control Tower'!$B$21=1,4>='Control Tower'!$B$22))),-PMT('Control Tower'!$B$19/12,'Control Tower'!$B$20,'Control Tower'!$B$18),0) | G22: =IF(AND('Control Tower'!$B$16=1,5>'Control Tower'!$B$17,5<='Control Tower'!$B$17+'Control Tower'!$B$20,NOT(AND('Control Tower'!$B$21=1,5>='Control Tower'!$B$22))),-PMT('Control Tower'!$B$19/12,'Control Tower'!$B$20,'Control Tower'!$B$18),0) | H22: =IF(AND('Control Tower'!$B$16=1,6>'Control Tower'!$B$17,6<='Control Tower'!$B$17+'Control Tower'!$B$20,NOT(AND('Control Tower'!$B$21=1,6>='Control Tower'!$B$22))),-PMT('Control Tower'!$B$19/12,'Control Tower'!$B$20,'Control Tower'!$B$18),0) | I22: =IF(AND('Control Tower'!$B$16=1,7>'Control Tower'!$B$17,7<='Control Tower'!$B$17+'Control Tower'!$B$20,NOT(AND('Control Tower'!$B$21=1,7>='Control Tower'!$B$22))),-PMT('Control Tower'!$B$19/12,'Control Tower'!$B$20,'Control Tower'!$B$18),0) | J22: =IF(AND('Control Tower'!$B$16=1,8>'Control Tower'!$B$17,8<='Control Tower'!$B$17+'Control Tower'!$B$20,NOT(AND('Control Tower'!$B$21=1,8>='Control Tower'!$B$22))),-PMT('Control Tower'!$B$19/12,'Control Tower'!$B$20,'Control Tower'!$B$18),0) | K22: =IF(AND('Control Tower'!$B$16=1,9>'Control Tower'!$B$17,9<='Control Tower'!$B$17+'Control Tower'!$B$20,NOT(AND('Control Tower'!$B$21=1,9>='Control Tower'!$B$22))),-PMT('Control Tower'!$B$19/12,'Control Tower'!$B$20,'Control Tower'!$B$18),0) | L22: =IF(AND('Control Tower'!$B$16=1,10>'Control Tower'!$B$17,10<='Control Tower'!$B$17+'Control Tower'!$B$20,NOT(AND('Control Tower'!$B$21=1,10>='Control Tower'!$B$22))),-PMT('Control Tower'!$B$19/12,'Control Tower'!$B$20,'Control Tower'!$B$18),0) | M22: =IF(AND('Control Tower'!$B$16=1,11>'Control Tower'!$B$17,11<='Control Tower'!$B$17+'Control Tower'!$B$20,NOT(AND('Control Tower'!$B$21=1,11>='Control Tower'!$B$22))),-PMT('Control Tower'!$B$19/12,'Control Tower'!$B$20,'Control Tower'!$B$18),0) | N22: =IF(AND('Control Tower'!$B$16=1,12>'Control Tower'!$B$17,12<='Control Tower'!$B$17+'Control Tower'!$B$20,NOT(AND('Control Tower'!$B$21=1,12>='Control Tower'!$B$22))),-PMT('Control Tower'!$B$19/12,'Control Tower'!$B$20,'Control Tower'!$B$18),0) | O22: =IF(AND('Control Tower'!$B$16=1,13>'Control Tower'!$B$17,13<='Control Tower'!$B$17+'Control Tower'!$B$20,NOT(AND('Control Tower'!$B$21=1,13>='Control Tower'!$B$22))),-PMT('Control Tower'!$B$19/12,'Control Tower'!$B$20,'Control Tower'!$B$18),0) | P22: =IF(AND('Control Tower'!$B$16=1,14>'Control Tower'!$B$17,14<='Control Tower'!$B$17+'Control Tower'!$B$20,NOT(AND('Control Tower'!$B$21=1,14>='Control Tower'!$B$22))),-PMT('Control Tower'!$B$19/12,'Control Tower'!$B$20,'Control Tower'!$B$18),0) | Q22: =IF(AND('Control Tower'!$B$16=1,15>'Control Tower'!$B$17,15<='Control Tower'!$B$17+'Control Tower'!$B$20,NOT(AND('Control Tower'!$B$21=1,15>='Control Tower'!$B$22))),-PMT('Control Tower'!$B$19/12,'Control Tower'!$B$20,'Control Tower'!$B$18),0) | R22: =IF(AND('Control Tower'!$B$16=1,16>'Control Tower'!$B$17,16<='Control Tower'!$B$17+'Control Tower'!$B$20,NOT(AND('Control Tower'!$B$21=1,16>='Control Tower'!$B$22))),-PMT('Control Tower'!$B$19/12,'Control Tower'!$B$20,'Control Tower'!$B$18),0) | S22: =IF(AND('Control Tower'!$B$16=1,17>'Control Tower'!$B$17,17<='Control Tower'!$B$17+'Control Tower'!$B$20,NOT(AND('Control Tower'!$B$21=1,17>='Control Tower'!$B$22))),-PMT('Control Tower'!$B$19/12,'Control Tower'!$B$20,'Control Tower'!$B$18),0) | T22: =IF(AND('Control Tower'!$B$16=1,18>'Control Tower'!$B$17,18<='Control Tower'!$B$17+'Control Tower'!$B$20,NOT(AND('Control Tower'!$B$21=1,18>='Control Tower'!$B$22))),-PMT('Control Tower'!$B$19/12,'Control Tower'!$B$20,'Control Tower'!$B$18),0) | U22: =IF(AND('Control Tower'!$B$16=1,19>'Control Tower'!$B$17,19<='Control Tower'!$B$17+'Control Tower'!$B$20,NOT(AND('Control Tower'!$B$21=1,19>='Control Tower'!$B$22))),-PMT('Control Tower'!$B$19/12,'Control Tower'!$B$20,'Control Tower'!$B$18),0) | V22: =IF(AND('Control Tower'!$B$16=1,20>'Control Tower'!$B$17,20<='Control Tower'!$B$17+'Control Tower'!$B$20,NOT(AND('Control Tower'!$B$21=1,20>='Control Tower'!$B$22))),-PMT('Control Tower'!$B$19/12,'Control Tower'!$B$20,'Control Tower'!$B$18),0) | W22: =IF(AND('Control Tower'!$B$16=1,21>'Control Tower'!$B$17,21<='Control Tower'!$B$17+'Control Tower'!$B$20,NOT(AND('Control Tower'!$B$21=1,21>='Control Tower'!$B$22))),-PMT('Control Tower'!$B$19/12,'Control Tower'!$B$20,'Control Tower'!$B$18),0) | X22: =IF(AND('Control Tower'!$B$16=1,22>'Control Tower'!$B$17,22<='Control Tower'!$B$17+'Control Tower'!$B$20,NOT(AND('Control Tower'!$B$21=1,22>='Control Tower'!$B$22))),-PMT('Control Tower'!$B$19/12,'Control Tower'!$B$20,'Control Tower'!$B$18),0) | Y22: =IF(AND('Control Tower'!$B$16=1,23>'Control Tower'!$B$17,23<='Control Tower'!$B$17+'Control Tower'!$B$20,NOT(AND('Control Tower'!$B$21=1,23>='Control Tower'!$B$22))),-PMT('Control Tower'!$B$19/12,'Control Tower'!$B$20,'Control Tower'!$B$18),0) | Z22: =IF(AND('Control Tower'!$B$16=1,24>'Control Tower'!$B$17,24<='Control Tower'!$B$17+'Control Tower'!$B$20,NOT(AND('Control Tower'!$B$21=1,24>='Control Tower'!$B$22))),-PMT('Control Tower'!$B$19/12,'Control Tower'!$B$20,'Control Tower'!$B$18),0) | AA22: =IF(AND('Control Tower'!$B$16=1,25>'Control Tower'!$B$17,25<='Control Tower'!$B$17+'Control Tower'!$B$20,NOT(AND('Control Tower'!$B$21=1,25>='Control Tower'!$B$22))),-PMT('Control Tower'!$B$19/12,'Control Tower'!$B$20,'Control Tower'!$B$18),0) | AB22: =IF(AND('Control Tower'!$B$16=1,26>'Control Tower'!$B$17,26<='Control Tower'!$B$17+'Control Tower'!$B$20,NOT(AND('Control Tower'!$B$21=1,26>='Control Tower'!$B$22))),-PMT('Control Tower'!$B$19/12,'Control Tower'!$B$20,'Control Tower'!$B$18),0) | AC22: =IF(AND('Control Tower'!$B$16=1,27>'Control Tower'!$B$17,27<='Control Tower'!$B$17+'Control Tower'!$B$20,NOT(AND('Control Tower'!$B$21=1,27>='Control Tower'!$B$22))),-PMT('Control Tower'!$B$19/12,'Control Tower'!$B$20,'Control Tower'!$B$18),0) | AD22: =IF(AND('Control Tower'!$B$16=1,28>'Control Tower'!$B$17,28<='Control Tower'!$B$17+'Control Tower'!$B$20,NOT(AND('Control Tower'!$B$21=1,28>='Control Tower'!$B$22))),-PMT('Control Tower'!$B$19/12,'Control Tower'!$B$20,'Control Tower'!$B$18),0) | AE22: =IF(AND('Control Tower'!$B$16=1,29>'Control Tower'!$B$17,29<='Control Tower'!$B$17+'Control Tower'!$B$20,NOT(AND('Control Tower'!$B$21=1,29>='Control Tower'!$B$22))),-PMT('Control Tower'!$B$19/12,'Control Tower'!$B$20,'Control Tower'!$B$18),0) | AF22: =IF(AND('Control Tower'!$B$16=1,30>'Control Tower'!$B$17,30<='Control Tower'!$B$17+'Control Tower'!$B$20,NOT(AND('Control Tower'!$B$21=1,30>='Control Tower'!$B$22))),-PMT('Control Tower'!$B$19/12,'Control Tower'!$B$20,'Control Tower'!$B$18),0) | AG22: =IF(AND('Control Tower'!$B$16=1,31>'Control Tower'!$B$17,31<='Control Tower'!$B$17+'Control Tower'!$B$20,NOT(AND('Control Tower'!$B$21=1,31>='Control Tower'!$B$22))),-PMT('Control Tower'!$B$19/12,'Control Tower'!$B$20,'Control Tower'!$B$18),0) | AH22: =IF(AND('Control Tower'!$B$16=1,32>'Control Tower'!$B$17,32<='Control Tower'!$B$17+'Control Tower'!$B$20,NOT(AND('Control Tower'!$B$21=1,32>='Control Tower'!$B$22))),-PMT('Control Tower'!$B$19/12,'Control Tower'!$B$20,'Control Tower'!$B$18),0) | AI22: =IF(AND('Control Tower'!$B$16=1,33>'Control Tower'!$B$17,33<='Control Tower'!$B$17+'Control Tower'!$B$20,NOT(AND('Control Tower'!$B$21=1,33>='Control Tower'!$B$22))),-PMT('Control Tower'!$B$19/12,'Control Tower'!$B$20,'Control Tower'!$B$18),0) | AJ22: =IF(AND('Control Tower'!$B$16=1,34>'Control Tower'!$B$17,34<='Control Tower'!$B$17+'Control Tower'!$B$20,NOT(AND('Control Tower'!$B$21=1,34>='Control Tower'!$B$22))),-PMT('Control Tower'!$B$19/12,'Control Tower'!$B$20,'Control Tower'!$B$18),0) | AK22: =IF(AND('Control Tower'!$B$16=1,35>'Control Tower'!$B$17,35<='Control Tower'!$B$17+'Control Tower'!$B$20,NOT(AND('Control Tower'!$B$21=1,35>='Control Tower'!$B$22))),-PMT('Control Tower'!$B$19/12,'Control Tower'!$B$20,'Control Tower'!$B$18),0) | AL22: =IF(AND('Control Tower'!$B$16=1,36>'Control Tower'!$B$17,36<='Control Tower'!$B$17+'Control Tower'!$B$20,NOT(AND('Control Tower'!$B$21=1,36>='Control Tower'!$B$22))),-PMT('Control Tower'!$B$19/12,'Control Tower'!$B$20,'Control Tower'!$B$18),0)
