Workbook
Name rhc_tier1: Inputs!$B$5
Name rhc_tier2: Inputs!$B$6
Name wage_index: Inputs!$B$7
Name labor_share: Inputs!$B$8
Name tier1_pct: Inputs!$B$9
Name seq: Inputs!$B$10
Name writeoff_pct: Inputs!$B$11
Name blended_actual: Inputs!$B$12
Name medicare_cap: Inputs!$B$13
Name rhc_escalation: Inputs!$B$14
Name avg_days_month: Inputs!$B$25
Name capture_rate: Inputs!$B$28
Name census_scenario: Inputs!$B$29
Name rn_caseload: Inputs!$B$70
Name aide_caseload: Inputs!$B$71
Name visits_rn_day: Inputs!$B$72
Name visits_aide_day: Inputs!$B$73
Name merit: Inputs!$B$74
Name benefits_load: Inputs!$B$77
Name health_pm: Inputs!$B$78
Name med_director: Inputs!$B$81
Name med_director2: Inputs!$B$82
Name med_director2_start: Inputs!$B$83
Name supplies_pd: Inputs!$B$86
Name dme_pd: Inputs!$B$87
Name pharmacy_pd: Inputs!$B$88
Name ga_utilities: Inputs!$B$91
Name ga_internet: Inputs!$B$92
Name ga_telephone: Inputs!$B$93
Name ga_bvtm: Inputs!$B$94
Name ga_emr: Inputs!$B$95
Name ga_pcr: Inputs!$B$96
Name ga_cc: Inputs!$B$97
Name ga_liability: Inputs!$B$98
Name ga_training: Inputs!$B$99
Name ga_other: Inputs!$B$100
Name ga_bankfees: Inputs!$B$101
Name ga_rent: Inputs!$B$102
Name ga_marketing: Inputs!$B$103
Name billing_fee_pct: Inputs!$B$106
Name qr_fee_pct: Inputs!$B$107
Name sba_principal: Inputs!$B$110
Name sba_rate: Inputs!$B$111
Name sba_term_mo: Inputs!$B$112
Name equity: Inputs!$B$113
Name loc_limit: Inputs!$B$114
Name loc_rate: Inputs!$B$115
Name min_cash: Inputs!$B$116
Name capex: Inputs!$B$117
Name deprec_yrs: Inputs!$B$118
Name tx_tax: Inputs!$B$119
Name license_cost: Inputs!$B$120
Name license_rate: Inputs!$B$121
Name license_term: Inputs!$B$122
Name license_amort_yrs: Inputs!$B$123
Name su_enroll: Inputs!$B$126
Name su_license: Inputs!$B$127
Name su_emr: Inputs!$B$128
Name su_supplies: Inputs!$B$129
Name su_legal: Inputs!$B$130

Sheet Inputs
A1: AZALEA HOSPICE & PALLIATIVE CARE - Tyler, TX
A2: Assumptions Engine - CHOW relaunch of Hickory Hospice (San Antonio + Tyler alternative-delivery) | blue = input | black = formula | green = cross-sheet link
A4: A. GEOGRAPHY & MEDICARE RHC RATES (FY2026, 100% Medicare)
A5: RHC per-diem, days 1-60 ($/day) | B5: 230.83
A6: RHC per-diem, days 61+ ($/day) | B6: 182.36
A7: Tyler CBSA 46340 wage index | B7: 0.88
A8: RHC labor share | B8: 0.68
A9: % patient-days in Tier 1 (days 1-60) | B9: 0.4
A10: Sequestration reduction | B10: 0.02
A11: Write-offs (% of gross) | B11: 0.0015
A12: Blended NET rate per PD - ACTUAL ($/day) | B12: 181
A13: Medicare aggregate cap / beneficiary ($/yr) | B13: 35361.44
A14: Medicare RHC rate escalation (annual) | B14: 0.025
A16: A2. DERIVED RATE BUILD (formulas)
A17: Wage-index adjustment factor | B17: =Inputs!$B$8*Inputs!$B$7+(1-Inputs!$B$8)
A18: Wage-adjusted rate, days 1-60 | B18: =Inputs!$B$5*Inputs!$B$17
A19: Wage-adjusted rate, days 61+ | B19: =Inputs!$B$6*Inputs!$B$17
A20: Blended GROSS rate ($/PD) | B20: =Inputs!$B$9*Inputs!$B$18+(1-Inputs!$B$9)*Inputs!$B$19
A21: Blended NET rate ($/PD) [model] | B21: =Inputs!$B$20*(1-Inputs!$B$10-Inputs!$B$11)
A22: Validation: model net rate vs actual $181 | B22: =Inputs!$B$21-Inputs!$B$12 | C22: should be near $0
A24: B. TIMING
A25: Average days per month | B25: 30.4
A27: C. CENSUS - PATIENT-MIGRATION RAMP (front-loaded M1-M2)
A28: Patient-migration capture rate | B28: 1
A29: Census scenario (1=Base flat, 2=Upside growth) | B29: 1
A31: ADC path - BASE (100% capture, flat steady-state) | C31: 12 | D31: 19.8 | E31: 22 | F31: 22.2 | G31: 22.4 | H31: 22.7 | I31: 22.9 | J31: 23.1 | K31: 23.3 | L31: 23.6 | M31: 23.8 | N31: 24 | O31: 30.5 | P31: 37 | Q31: 43.5 | R31: 50 | S31: 51.5 | T31: 53 | U31: 54.5 | V31: 56
A32: ADC path - UPSIDE (referral growth) | C32: 12 | D32: 19.8 | E32: 22 | F32: 23 | G32: 24 | H32: 25 | I32: 26 | J32: 27 | K32: 28 | L32: 29 | M32: 30 | N32: 31 | O32: 33 | P32: 35 | Q32: 37 | R32: 39 | S32: 44 | T32: 50 | U32: 55 | V32: 60
A33: EFFECTIVE ADC = chosen path x capture | C33: =IF(Inputs!$B$29=2,C32,C31)*Inputs!$B$28 | D33: =IF(Inputs!$B$29=2,D32,D31)*Inputs!$B$28 | E33: =IF(Inputs!$B$29=2,E32,E31)*Inputs!$B$28 | F33: =IF(Inputs!$B$29=2,F32,F31)*Inputs!$B$28 | G33: =IF(Inputs!$B$29=2,G32,G31)*Inputs!$B$28 | H33: =IF(Inputs!$B$29=2,H32,H31)*Inputs!$B$28 | I33: =IF(Inputs!$B$29=2,I32,I31)*Inputs!$B$28 | J33: =IF(Inputs!$B$29=2,J32,J31)*Inputs!$B$28 | ... V33: =IF(Inputs!$B$29=2,V32,V31)*Inputs!$B$28
A35: D. STAGGERED FT ROSTER (named hires)
A36: Name | B36: Role | C36: Annual salary | D36: Start month | E36: Cost group | F36: Status
A37: Brad Woodard | B37: Administrator / Director | C37: 120000 | D37: 1 | E37: Indirect (SG&A) | F37: Filled
A38: Angie Frost | B38: RN Case Manager | C38: 77504 | D38: 1 | E38: Direct (COGS) | F38: Filled
A39: Tanisha Robison | B39: CNA / Hospice Aide | C39: 46511 | D39: 1 | E39: Direct (COGS) | F39: Filled
A40: Dana Davenport | B40: Director of Clinical Services | C40: 110000 | D40: 2 | E40: Indirect (SG&A) | F40: Filled
A41: Silas Shelton | B41: Administrator | C41: 130000 | D41: 3 | E41: Indirect (SG&A) | F41: Filled
A42: Jodi McCollum | B42: RN Case Manager (2nd seat) | C42: 75008 | D42: 4 | E42: Direct (COGS) | F42: OPEN REQ
A43: Director of Business Development | B43: Sales / referrals (growth driver) | C43: 95000 | D43: 6 | E43: Indirect (SG&A) | F43: Filled
A44: Capacity hire - 2nd CNA | B44: CNA / Hospice Aide (capacity-driven, triggers ADC>=25) | C44: 46511 | D44: 13 | E44: Direct (COGS) | F44: Filled
A45: FT Social Worker (MSW) | B45: Core IDG MSW (converts PRN SW to salaried) | C45: 58000 | D45: 14 | E45: Direct (COGS) | F45: Filled
A46: FT LVN - visits / on-call | B46: Core IDG LVN (converts PRN LVN to salaried) | C46: 52000 | D46: 16 | E46: Direct (COGS) | F46: Filled
A47: FT Chaplain | B47: Core IDG spiritual care (converts PRN chaplain to FT) | C47: 55000 | D47: 18 | E47: Direct (COGS) | F47: Filled
A48: Capacity hire - 3rd RN | B48: RN Case Manager (capacity-driven, ADC>=30) | C48: 76256 | D48: 13 | E48: Direct (COGS) | F48: Filled
... A58: Volunteer Coordinator | B58: Medicare CoP requirement | volunteer hours | C58: 50000 | D58: 26 | E58: Indirect (SG&A) | F58: Filled
A59: Rhonda Smith - Office Mgr (PRN, W-2) | B59: Per-visit / part-time office support | C59: 34000
A61: D2. PRN / PER-VISIT ROSTER (census-driven)
A62: Role | C62: Visits / pt / mo | D62: Rate / visit
A63: PRN On-Call LVN (Kendricks-Tuck, Foster) | C63: 0.6 | D63: 100
A64: PRN Chaplain (Ector, Johnson) | C64: 0.75 | D64: 75
A65: PRN Social Worker (Sanders) | C65: 1 | D65: 75
A66: PRN Nurse Practitioner (Rogers) | C66: 0.15 | D66: 200
A67: PRN CNA / per-visit (Henson, Mills) | C67: 0.5 | D67: 21
A69: E. STAFFING RATIOS (Y2-Y3 capacity reference)
A70: RN case-manager caseload (1 : N ADC) | B70: 12
A71: CNA / aide caseload (1 : N ADC) | B71: 10
A72: Target visits / RN / day | B72: 5.5
A73: Target visits / aide / day | B73: 6
A74: Annual merit / COL increase (Y2, Y3) | B74: 0.03
A76: F. BENEFITS & EMPLOYER BURDEN
A77: Benefits load on W-2 wages | B77: 0.1827
A78: Health insurance ($/FT employee/mo) | B78: 550
A80: F2. MEDICAL DIRECTORS (1099 - no benefits)
A81: Medical Director 1 (1099, $/mo) | B81: 4000
A82: Medical Director 2 (1099, $/mo, conditional) | B82: 5000
A83: Medical Director 2 start month | B83: 22
A85: G. PATIENT-RELATED COGS (per patient-day, trued to actuals)
A86: Medical supplies ($/patient-day) | B86: 3.99
A87: DME ($/patient-day) | B87: 1.77
A88: Pharmacy ($/patient-day) | B88: 3.23
A90: G2. FIXED MONTHLY G&A (trued to actuals)
A91: Utilities | B91: 293
A92: Internet | B92: 779
A93: Telephone / fax | B93: 403
A94: After-hours messaging (BVTM) | B94: 48
A95: EMR system | B95: 1281
A96: PCR (CPM) | B96: 1001
A97: Credit-card fees | B97: 1004
A98: Liability / D&O insurance | B98: 250
A99: Training / CEUs | B99: 100
A100: Other (client) | B100: 1050
A101: Bank / payroll fees | B101: 1750
A102: Facility rent | B102: 3000
A103: Marketing / patient acquisition | B103: 3000
A105: G3. VARIABLE G&A
A106: Outsourced billing fee (% of gross) | B106: 0.015
A107: QR payment fee (% of gross) | B107: 0.0075
A109: H. CAPITAL STRUCTURE (startup - NO acquisition)
A110: SBA 7(a) loan principal ($) | B110: 500000
A111: SBA interest rate (APR) | B111: 0.115
A112: SBA term (months) | B112: 120
A113: Owner equity injection ($) | B113: 250000
A114: Working-capital line limit ($) | B114: 100000
A115: Working-capital line rate (APR) | B115: 0.105
A116: Minimum cash floor ($) | B116: 25000
A117: Startup capex - equipment ($) | B117: 15000
A118: Depreciation / amortization life (yrs) | B118: 5
A119: TX franchise/margin tax (eff.) | B119: 0.00375
A120: Hickory Medicare license - acquisition cost ($) | B120: 300000
A121: License note interest rate (APR) | B121: 0.06
... A123: License intangible amortization life (yrs) | B123: 15
A125: H2. STARTUP ONE-TIME USES (Sources & Uses)
...

Sheet Dashboard
A1: AZALEA HOSPICE & PALLIATIVE CARE - Tyler, TX
A2: Operations Dashboard - live KPIs (all formula-driven from the engine)
A4: KEY PERFORMANCE INDICATORS
A5: Y3 run-rate net revenue | C5: Y3 EBITDA margin | E5: Min cash balance
A6: =SUM('Operating Budget'!S6:V6) | C6: =SUM('Operating Budget'!S24:V24)/SUM('Operating Budget'!S6:V6) | E6: =MIN('Cash Flow & BS'!C21:V21)
A8: Min DSCR (Y1 monthly) | C8: Peak working-capital draw | E8: Blended net rate / PD
A9: =MIN('Debt Schedule'!C29:N29) | C9: =MAX('Cash Flow & BS'!C20:V20) | E9: =Inputs!$B$21

Sheet Actuals vs Budget
A1: AZALEA HOSPICE & PALLIATIVE CARE - Tyler, TX
A2: Monthly Actuals vs Budget - enter month actuals (blue); variance auto-flags > 10%
A4: Reporting month (1-12) | B4: 3
A6: Line | B6: Budget | C6: Actual | D6: Variance | E6: Flag
A7: Net revenue | B7: =INDEX('Operating Budget'!C6:N6,$B$4) | C7: 0 | D7: =IF(B7=0,0,(C7-B7)/B7) | E7: =IF(ABS(D7)>0.1,"FLAG >10%","ok")
A8: Total COGS | B8: =INDEX('Operating Budget'!C14:N14,$B$4) | C8: 0 | D8: =IF(B8=0,0,(C8-B8)/B8) | E8: =IF(ABS(D8)>0.1,"FLAG >10%","ok")
A9: Gross profit | B9: =INDEX('Operating Budget'!C15:N15,$B$4) | C9: 0 | D9: =IF(B9=0,0,(C9-B9)/B9) | E9: =IF(ABS(D9)>0.1,"FLAG >10%","ok")
A10: Total SG&A | B10: =INDEX('Operating Budget'!C23:N23,$B$4) | C10: 0 | D10: =IF(B10=0,0,(C10-B10)/B10) | E10: =IF(ABS(D10)>0.1,"FLAG >10%","ok")
A11: EBITDA | B11: =INDEX('Operating Budget'!C24:N24,$B$4) | C11: 0 | D11: =IF(B11=0,0,(C11-B11)/B11) | E11: =IF(ABS(D11)>0.1,"FLAG >10%","ok")
A12: Net income | B12: =INDEX('Operating Budget'!C34:N34,$B$4) | C12: 0 | D12: =IF(B12=0,0,(C12-B12)/B12) | E12: =IF(ABS(D12)>0.1,"FLAG >10%","ok")
A14: Budget pulls the selected month from the engine; enter actuals from the close. Flag fires when |variance| > 10%.

Sheet Staffing Tracker
A1: AZALEA HOSPICE & PALLIATIVE CARE - Tyler, TX
A2: Staffing Tracker - staggered-hire calendar | capacity vs demand | open requisitions
A4: HIRE CALENDAR
A5: Name | B5: Role | C5: Annual salary | D5: Start month | E5: Status
A6: Brad Woodard | B6: Administrator / Director | C6: =Inputs!$C$37 | D6: =Inputs!$D$37 | E6: Filled
A7: Angie Frost | B7: RN Case Manager | C7: =Inputs!$C$38 | D7: =Inputs!$D$38 | E7: Filled
A8: Tanisha Robison | B8: CNA / Hospice Aide | C8: =Inputs!$C$39 | D8: =Inputs!$D$39 | E8: Filled
A9: Dana Davenport | B9: Director of Clinical Services | C9: =Inputs!$C$40 | D9: =Inputs!$D$40 | E9: Filled
A10: Silas Shelton | B10: Administrator | C10: =Inputs!$C$41 | D10: =Inputs!$D$41 | E10: Filled
A11: Jodi McCollum | B11: RN Case Manager (2nd seat) | C11: =Inputs!$C$42 | D11: =Inputs!$D$42 | E11: OPEN REQ
A12: Director of Business Development | B12: Sales / referrals (growth driver) | C12: =Inputs!$C$43 | D12: =Inputs!$D$43 | E12: Filled
A13: Capacity hire - 2nd CNA | B13: CNA / Hospice Aide (capacity-driven, triggers ADC>=25) | C13: =Inputs!$C$44 | D13: =Inputs!$D$44 | E13: Filled
A14: FT Social Worker (MSW) | B14: Core IDG MSW (converts PRN SW to salaried) | C14: =Inputs!$C$45 | D14: =Inputs!$D$45 | E14: Filled
A15: FT LVN - visits / on-call | B15: Core IDG LVN (converts PRN LVN to salaried) | C15: =Inputs!$C$46 | D15: =Inputs!$D$46 | E15: Filled
A16: FT Chaplain | B16: Core IDG spiritual care (converts PRN chaplain to FT) | C16: =Inputs!$C$47 | D16: =Inputs!$D$47 | E16: Filled
A17: Capacity hire - 3rd RN | B17: RN Case Manager (capacity-driven, ADC>=30) | C17: =Inputs!$C$48 | D17: =Inputs!$D$48 | E17: Filled
A18: Capacity hire - 3rd CNA | B18: CNA / Hospice Aide (capacity-driven, ADC>=32) | C18: =Inputs!$C$49 | D18: =Inputs!$D$49 | E18: Filled
A19: Capacity hire - 4th RN | B19: RN Case Manager (capacity-driven, ADC>=38) | C19: =Inputs!$C$50 | D19: =Inputs!$D$50 | E19: Filled
A20: Capacity hire - 4th CNA | B20: CNA / Hospice Aide (capacity-driven, ADC>=40) | C20: =Inputs!$C$51 | D20: =Inputs!$D$51 | E20: Filled
A21: Capacity hire - 5th RN | B21: RN Case Manager (capacity-driven, ADC>=48) | C21: =Inputs!$C$52 | D21: =Inputs!$D$52 | E21: Filled
A22: Capacity hire - 5th CNA | B22: CNA / Hospice Aide (capacity-driven, ADC>=50) | C22: =Inputs!$C$53 | D22: =Inputs!$D$53 | E22: Filled
A23: Capacity hire - 6th CNA | B23: CNA / Hospice Aide (capacity-driven, ADC>=54) | C23: =Inputs!$C$54 | D23: =Inputs!$D$54 | E23: Filled
A24: Capacity hire - 6th RN | B24: RN Case Manager (capacity-driven, ADC>=55) | C24: =Inputs!$C$55 | D24: =Inputs!$D$55 | E24: Filled
A25: Quality / Compliance Manager | B25: QAPI program | CoP compliance | surveys | C25: =Inputs!$C$56 | D25: =Inputs!$D$56 | E25: Filled
A26: Intake / Admissions Coordinator | B26: Referral intake | IDG admit coordination | C26: =Inputs!$C$57 | D26: =Inputs!$D$57 | E26: Filled
A27: Volunteer Coordinator | B27: Medicare CoP requirement | volunteer hours | C27: =Inputs!$C$58 | D27: =Inputs!$D$58 | E27: Filled
A29: CAPACITY vs DEMAND (steady-state ADC 22)
A30: RN case managers needed = ADC ÷ caseload | C30: =ROUNDUP('Revenue Model'!E10/Inputs!$B$70,0)
A31: Aides needed = ADC ÷ caseload | C31: =ROUNDUP('Revenue Model'!E10/Inputs!$B$71,0)
A32: Target visits / RN / day | C32: =Inputs!$B$72
A33: Target visits / aide / day | C33: =Inputs!$B$73
A35: Jodi McCollum's 2nd RN-CM seat is funded but vacant - modeled to start M4 as census coverage requires. Track real churn beyond this one open req.

Sheet Cap & Payroll
A1: AZALEA HOSPICE & PALLIATIVE CARE - Tyler, TX
A2: Medicare Cap Monitor (inherited day-counts) + Payroll Reconciliation
A4: MEDICARE AGGREGATE CAP - by year
C5: Year 1 | D5: Year 2 | E5: Year 3
A6: Unique beneficiaries (est.) | C6: 40 | D6: 55 | E6: 60
A7: Cap allowable = beneficiaries x cap | C7: =C6*Inputs!$B$13 | D7: =D6*Inputs!$B$13 | E7: =E6*Inputs!$B$13
A8: Gross Medicare revenue | C8: =SUM('Revenue Model'!C14:N14) | D8: =SUM('Revenue Model'!O14:R14) | E8: =SUM('Revenue Model'!S14:V14)
A9: Cap headroom (allowable - gross) | C9: =C7-C8 | D9: =D7-D8 | E9: =E7-E8
A11: PAYROLL RECONCILIATION (actual semi-monthly vs model)
A12: Run | B12: 1st half | C12: 2nd half | D12: Month total
A13: Apr 2025 | B13: 22921.54 | C13: 22765.1 | D13: =B13+C13
A14: May 2025 | B14: 22117.27 | C14: 21499.29 | D14: =B14+C14
A15: Jun 2025 | B15: 31000 | C15: 27000 | D15: =B15+C15
A16: Model total labor (M3 steady) | D16: ='Staffing & Payroll'!E53+'Staffing & Payroll'!E54
A18: Cap monitor uses inherited mid-episode day-counts (estimate beneficiaries), not fresh admits. Payroll ties the 3 actual semi-monthly runs to the model's loaded labor.

Sheet Revenue Model
A1: AZALEA HOSPICE & PALLIATIVE CARE - Tyler, TX
A2: Revenue Model - 100% Medicare RHC | accrual basis
A4: RHC RATE (per patient-day) - linked from Inputs
A5: Blended GROSS rate ($/PD) | B5: =Inputs!$B$20
A6: Blended NET rate ($/PD) | B6: =Inputs!$B$21
A8: ($ per period) | C8: YEAR 1 - monthly | O8: YEAR 2 - quarterly | S8: YEAR 3 - quarterly
C9: M1 | D9: M2 | E9: M3 | F9: M4 | G9: M5 | H9: M6 | I9: M7 | J9: M8 | K9: M9 | L9: M10 | M9: M11 | N9: M12 | O9: Y2 Q1 | P9: Y2 Q2 | Q9: Y2 Q3 | R9: Y2 Q4 | S9: Y3 Q1 | T9: Y3 Q2 | U9: Y3 Q3 | V9: Y3 Q4
A10: Average daily census (ADC) | C10: =Inputs!C$33 | D10: =Inputs!D$33 | E10: =Inputs!E$33 | F10: =Inputs!F$33 | G10: =Inputs!G$33 | H10: =Inputs!H$33 | I10: =Inputs!I$33 | J10: =Inputs!J$33 | ... V10: =Inputs!V$33
A11: Days in period | C11: =Inputs!$B$25*1 | D11: =Inputs!$B$25*1 | E11: =Inputs!$B$25*1 | F11: =Inputs!$B$25*1 | G11: =Inputs!$B$25*1 | H11: =Inputs!$B$25*1 | I11: =Inputs!$B$25*1 | J11: =Inputs!$B$25*1 | ... N11: =Inputs!$B$25*1 | O11: =Inputs!$B$25*3 | P11: =Inputs!$B$25*3 | Q11: =Inputs!$B$25*3 | R11: =Inputs!$B$25*3 | S11: =Inputs!$B$25*3 | T11: =Inputs!$B$25*3 | U11: =Inputs!$B$25*3 | V11: =Inputs!$B$25*3
A12: Patient-days | C12: =C10*C11 | D12: =D10*D11 | E12: =E10*E11 | F12: =F10*F11 | G12: =G10*G11 | H12: =H10*H11 | I12: =I10*I11 | J12: =J10*J11 | ... V12: =V10*V11
A13: Rate escalation factor (Y1 = 1.000, Y2+ compounded) | C13: =1 | D13: =1 | E13: =1 | F13: =1 | G13: =1 | H13: =1 | I13: =1 | J13: =1 | ... N13: =1 | O13: =(1+Inputs!$B$14)^1 | P13: =(1+Inputs!$B$14)^1 | Q13: =(1+Inputs!$B$14)^1 | R13: =(1+Inputs!$B$14)^1 | S13: =(1+Inputs!$B$14)^2 | T13: =(1+Inputs!$B$14)^2 | U13: =(1+Inputs!$B$14)^2 | V13: =(1+Inputs!$B$14)^2
A14: Gross Medicare revenue | C14: =C12*Inputs!$B$20*C13 | D14: =D12*Inputs!$B$20*D13 | E14: =E12*Inputs!$B$20*E13 | F14: =F12*Inputs!$B$20*F13 | G14: =G12*Inputs!$B$20*G13 | H14: =H12*Inputs!$B$20*H13 | I14: =I12*Inputs!$B$20*I13 | J14: =J12*Inputs!$B$20*J13 | ... V14: =V12*Inputs!$B$20*V13
A15: Less: sequestration | C15: =-C14*Inputs!$B$10 | D15: =-D14*Inputs!$B$10 | E15: =-E14*Inputs!$B$10 | F15: =-F14*Inputs!$B$10 | G15: =-G14*Inputs!$B$10 | H15: =-H14*Inputs!$B$10 | I15: =-I14*Inputs!$B$10 | J15: =-J14*Inputs!$B$10 | ... V15: =-V14*Inputs!$B$10
A16: Less: write-offs | C16: =-C14*Inputs!$B$11 | D16: =-D14*Inputs!$B$11 | E16: =-E14*Inputs!$B$11 | F16: =-F14*Inputs!$B$11 | G16: =-G14*Inputs!$B$11 | H16: =-H14*Inputs!$B$11 | I16: =-I14*Inputs!$B$11 | J16: =-J14*Inputs!$B$11 | ... V16: =-V14*Inputs!$B$11
A17: NET REVENUE | C17: =C14*(1-Inputs!$B$10-Inputs!$B$11) | D17: =D14*(1-Inputs!$B$10-Inputs!$B$11) | E17: =E14*(1-Inputs!$B$10-Inputs!$B$11) | F17: =F14*(1-Inputs!$B$10-Inputs!$B$11) | G17: =G14*(1-Inputs!$B$10-Inputs!$B$11) | H17: =H14*(1-Inputs!$B$10-Inputs!$B$11) | I17: =I14*(1-Inputs!$B$10-Inputs!$B$11) | J17: =J14*(1-Inputs!$B$10-Inputs!$B$11) | ... V17: =V14*(1-Inputs!$B$10-Inputs!$B$11)
A19: Memo: net revenue per patient-day | C19: =IF(C12=0,0,C17/C12) | D19: =IF(D12=0,0,D17/D12) | E19: =IF(E12=0,0,E17/E12) | F19: =IF(F12=0,0,F17/F12) | G19: =IF(G12=0,0,G17/G12) | H19: =IF(H12=0,0,H17/H12) | I19: =IF(I12=0,0,I17/I12) | J19: =IF(J12=0,0,J17/J12) | ... V19: =IF(V12=0,0,V17/V12)

Sheet Staffing & Payroll
A1: AZALEA HOSPICE & PALLIATIVE CARE - Tyler, TX
A2: Staffing & Payroll - staggered hires + census-driven PRN | burden on W-2 only | Med Director 1099 (no benefits)
A4: ($ per period) | C4: YEAR 1 - monthly | O4: YEAR 2 - quarterly | S4: YEAR 3 - quarterly
C5: M1 | D5: M2 | E5: M3 | F5: M4 | G5: M5 | H5: M6 | I5: M7 | J5: M8 | K5: M9 | L5: M10 | M5: M11 | N5: M12 | O5: Y2 Q1 | P5: Y2 Q2 | Q5: Y2 Q3 | R5: Y2 Q4 | S5: Y3 Q1 | T5: Y3 Q2 | U5: Y3 Q3 | V5: Y3 Q4
A6: ADC (driver) | C6: ='Revenue Model'!C10 | D6: ='Revenue Model'!D10 | E6: ='Revenue Model'!E10 | F6: ='Revenue Model'!F10 | G6: ='Revenue Model'!G10 | H6: ='Revenue Model'!H10 | I6: ='Revenue Model'!I10 | J6: ='Revenue Model'!J10 | ... V6: ='Revenue Model'!V10
A7: DIRECT-CARE FT SALARIES (Cost of Care)
A8: Brad Woodard - Administrator / Director | C8: =IF(1>=Inputs!$D$37,Inputs!$C$37/12*1*1,0) | D8: =IF(2>=Inputs!$D$37,Inputs!$C$37/12*1*1,0) | E8: =IF(3>=Inputs!$D$37,Inputs!$C$37/12*1*1,0) | F8: =IF(4>=Inputs!$D$37,Inputs!$C$37/12*1*1,0) | G8: =IF(5>=Inputs!$D$37,Inputs!$C$37/12*1*1,0) | H8: =IF(6>=Inputs!$D$37,Inputs!$C$37/12*1*1,0) | I8: =IF(7>=Inputs!$D$37,Inputs!$C$37/12*1*1,0) | J8: =IF(8>=Inputs!$D$37,Inputs!$C$37/12*1*1,0) | K8: =IF(9>=Inputs!$D$37,Inputs!$C$37/12*1*1,0) | L8: =IF(10>=Inputs!$D$37,Inputs!$C$37/12*1*1,0) | M8: =IF(11>=Inputs!$D$37,Inputs!$C$37/12*1*1,0) | N8: =IF(12>=Inputs!$D$37,Inputs!$C$37/12*1*1,0) | O8: =IF(15>=Inputs!$D$37,Inputs!$C$37/12*3*(1+Inputs!$B$74)^1,0) | P8: =IF(18>=Inputs!$D$37,Inputs!$C$37/12*3*(1+Inputs!$B$74)^1,0) | Q8: =IF(21>=Inputs!$D$37,Inputs!$C$37/12*3*(1+Inputs!$B$74)^1,0) | R8: =IF(24>=Inputs!$D$37,Inputs!$C$37/12*3*(1+Inputs!$B$74)^1,0) | S8: =IF(27>=Inputs!$D$37,Inputs!$C$37/12*3*(1+Inputs!$B$74)^2,0) | T8: =IF(30>=Inputs!$D$37,Inputs!$C$37/12*3*(1+Inputs!$B$74)^2,0) | U8: =IF(33>=Inputs!$D$37,Inputs!$C$37/12*3*(1+Inputs!$B$74)^2,0) | V8: =IF(36>=Inputs!$D$37,Inputs!$C$37/12*3*(1+Inputs!$B$74)^2,0)
A9: Angie Frost - RN Case Manager | C9: =IF(1>=Inputs!$D$38,Inputs!$C$38/12*1*1,0) | D9: =IF(2>=Inputs!$D$38,Inputs!$C$38/12*1*1,0) | E9: =IF(3>=Inputs!$D$38,Inputs!$C$38/12*1*1,0) | F9: =IF(4>=Inputs!$D$38,Inputs!$C$38/12*1*1,0) | G9: =IF(5>=Inputs!$D$38,Inputs!$C$38/12*1*1,0) | H9: =IF(6>=Inputs!$D$38,Inputs!$C$38/12*1*1,0) | I9: =IF(7>=Inputs!$D$38,Inputs!$C$38/12*1*1,0) | J9: =IF(8>=Inputs!$D$38,Inputs!$C$38/12*1*1,0) | K9: =IF(9>=Inputs!$D$38,Inputs!$C$38/12*1*1,0) | L9: =IF(10>=Inputs!$D$38,Inputs!$C$38/12*1*1,0) | M9: =IF(11>=Inputs!$D$38,Inputs!$C$38/12*1*1,0) | N9: =IF(12>=Inputs!$D$38,Inputs!$C$38/12*1*1,0) | O9: =IF(15>=Inputs!$D$38,Inputs!$C$38/12*3*(1+Inputs!$B$74)^1,0) | P9: =IF(18>=Inputs!$D$38,Inputs!$C$38/12*3*(1+Inputs!$B$74)^1,0) | Q9: =IF(21>=Inputs!$D$38,Inputs!$C$38/12*3*(1+Inputs!$B$74)^1,0) | R9: =IF(24>=Inputs!$D$38,Inputs!$C$38/12*3*(1+Inputs!$B$74)^1,0) | S9: =IF(27>=Inputs!$D$38,Inputs!$C$38/12*3*(1+Inputs!$B$74)^2,0) | T9: =IF(30>=Inputs!$D$38,Inputs!$C$38/12*3*(1+Inputs!$B$74)^2,0) | U9: =IF(33>=Inputs!$D$38,Inputs!$C$38/12*3*(1+Inputs!$B$74)^2,0) | V9: =IF(36>=Inputs!$D$38,Inputs!$C$38/12*3*(1+Inputs!$B$74)^2,0)
A10: Tanisha Robison - CNA / Hospice Aide | C10: =IF(1>=Inputs!$D$39,Inputs!$C$39/12*1*1,0) | D10: =IF(2>=Inputs!$D$39,Inputs!$C$39/12*1*1,0) | E10: =IF(3>=Inputs!$D$39,Inputs!$C$39/12*1*1,0) | F10: =IF(4>=Inputs!$D$39,Inputs!$C$39/12*1*1,0) | G10: =IF(5>=Inputs!$D$39,Inputs!$C$39/12*1*1,0) | H10: =IF(6>=Inputs!$D$39,Inputs!$C$39/12*1*1,0) | I10: =IF(7>=Inputs!$D$39,Inputs!$C$39/12*1*1,0) | J10: =IF(8>=Inputs!$D$39,Inputs!$C$39/12*1*1,0) | K10: =IF(9>=Inputs!$D$39,Inputs!$C$39/12*1*1,0) | L10: =IF(10>=Inputs!$D$39,Inputs!$C$39/12*1*1,0) | M10: =IF(11>=Inputs!$D$39,Inputs!$C$39/12*1*1,0) | N10: =IF(12>=Inputs!$D$39,Inputs!$C$39/12*1*1,0) | O10: =IF(15>=Inputs!$D$39,Inputs!$C$39/12*3*(1+Inputs!$B$74)^1,0) | P10: =IF(18>=Inputs!$D$39,Inputs!$C$39/12*3*(1+Inputs!$B$74)^1,0) | Q10: =IF(21>=Inputs!$D$39,Inputs!$C$39/12*3*(1+Inputs!$B$74)^1,0) | R10: =IF(24>=Inputs!$D$39,Inputs!$C$39/12*3*(1+Inputs!$B$74)^1,0) | S10: =IF(27>=Inputs!$D$39,Inputs!$C$39/12*3*(1+Inputs!$B$74)^2,0) | T10: =IF(30>=Inputs!$D$39,Inputs!$C$39/12*3*(1+Inputs!$B$74)^2,0) | U10: =IF(33>=Inputs!$D$39,Inputs!$C$39/12*3*(1+Inputs!$B$74)^2,0) | V10: =IF(36>=Inputs!$D$39,Inputs!$C$39/12*3*(1+Inputs!$B$74)^2,0)
A11: Dana Davenport - Director of Clinical Services | C11: =IF(1>=Inputs!$D$40,Inputs!$C$40/12*1*1,0) | D11: =IF(2>=Inputs!$D$40,Inputs!$C$40/12*1*1,0) | E11: =IF(3>=Inputs!$D$40,Inputs!$C$40/12*1*1,0) | F11: =IF(4>=Inputs!$D$40,Inputs!$C$40/12*1*1,0) | G11: =IF(5>=Inputs!$D$40,Inputs!$C$40/12*1*1,0) | H11: =IF(6>=Inputs!$D$40,Inputs!$C$40/12*1*1,0) | I11: =IF(7>=Inputs!$D$40,Inputs!$C$40/12*1*1,0) | J11: =IF(8>=Inputs!$D$40,Inputs!$C$40/12*1*1,0) | K11: =IF(9>=Inputs!$D$40,Inputs!$C$40/12*1*1,0) | L11: =IF(10>=Inputs!$D$40,Inputs!$C$40/12*1*1,0) | M11: =IF(11>=Inputs!$D$40,Inputs!$C$40/12*1*1,0) | N11: =IF(12>=Inputs!$D$40,Inputs!$C$40/12*1*1,0) | O11: =IF(15>=Inputs!$D$40,Inputs!$C$40/12*3*(1+Inputs!$B$74)^1,0) | P11: =IF(18>=Inputs!$D$40,Inputs!$C$40/12*3*(1+Inputs!$B$74)^1,0) | Q11: =IF(21>=Inputs!$D$40,Inputs!$C$40/12*3*(1+Inputs!$B$74)^1,0) | R11: =IF(24>=Inputs!$D$40,Inputs!$C$40/12*3*(1+Inputs!$B$74)^1,0) | S11: =IF(27>=Inputs!$D$40,Inputs!$C$40/12*3*(1+Inputs!$B$74)^2,0) | T11: =IF(30>=Inputs!$D$40,Inputs!$C$40/12*3*(1+Inputs!$B$74)^2,0) | U11: =IF(33>=Inputs!$D$40,Inputs!$C$40/12*3*(1+Inputs!$B$74)^2,0) | V11: =IF(36>=Inputs!$D$40,Inputs!$C$40/12*3*(1+Inputs!$B$74)^2,0)
A12: Silas Shelton - Administrator | C12: =IF(1>=Inputs!$D$41,Inputs!$C$41/12*1*1,0) | D12: =IF(2>=Inputs!$D$41,Inputs!$C$41/12*1*1,0) | E12: =IF(3>=Inputs!$D$41,Inputs!$C$41/12*1*1,0) | F12: =IF(4>=Inputs!$D$41,Inputs!$C$41/12*1*1,0) | G12: =IF(5>=Inputs!$D$41,Inputs!$C$41/12*1*1,0) | H12: =IF(6>=Inputs!$D$41,Inputs!$C$41/12*1*1,0) | I12: =IF(7>=Inputs!$D$41,Inputs!$C$41/12*1*1,0) | J12: =IF(8>=Inputs!$D$41,Inputs!$C$41/12*1*1,0) | K12: =IF(9>=Inputs!$D$41,Inputs!$C$41/12*1*1,0) | L12: =IF(10>=Inputs!$D$41,Inputs!$C$41/12*1*1,0) | M12: =IF(11>=Inputs!$D$41,Inputs!$C$41/12*1*1,0) | N12: =IF(12>=Inputs!$D$41,Inputs!$C$41/12*1*1,0) | O12: =IF(15>=Inputs!$D$41,Inputs!$C$41/12*3*(1+Inputs!$B$74)^1,0) | P12: =IF(18>=Inputs!$D$41,Inputs!$C$41/12*3*(1+Inputs!$B$74)^1,0) | Q12: =IF(21>=Inputs!$D$41,Inputs!$C$41/12*3*(1+Inputs!$B$74)^1,0) | R12: =IF(24>=Inputs!$D$41,Inputs!$C$41/12*3*(1+Inputs!$B$74)^1,0) | S12: =IF(27>=Inputs!$D$41,Inputs!$C$41/12*3*(1+Inputs!$B$74)^2,0) | T12: =IF(30>=Inputs!$D$41,Inputs!$C$41/12*3*(1+Inputs!$B$74)^2,0) | U12: =IF(33>=Inputs!$D$41,Inputs!$C$41/12*3*(1+Inputs!$B$74)^2,0) | V12: =IF(36>=Inputs!$D$41,Inputs!$C$41/12*3*(1+Inputs!$B$74)^2,0)
A13: Jodi McCollum - RN Case Manager (2nd seat) [OPEN REQ] | C13: =IF(1>=Inputs!$D$42,Inputs!$C$42/12*1*1,0) | D13: =IF(2>=Inputs!$D$42,Inputs!$C$42/12*1*1,0) | E13: =IF(3>=Inputs!$D$42,Inputs!$C$42/12*1*1,0) | F13: =IF(4>=Inputs!$D$42,Inputs!$C$42/12*1*1,0) | G13: =IF(5>=Inputs!$D$42,Inputs!$C$42/12*1*1,0) | H13: =IF(6>=Inputs!$D$42,Inputs!$C$42/12*1*1,0) | I13: =IF(7>=Inputs!$D$42,Inputs!$C$42/12*1*1,0) | J13: =IF(8>=Inputs!$D$42,Inputs!$C$42/12*1*1,0) | K13: =IF(9>=Inputs!$D$42,Inputs!$C$42/12*1*1,0) | L13: =IF(10>=Inputs!$D$42,Inputs!$C$42/12*1*1,0) | M13: =IF(11>=Inputs!$D$42,Inputs!$C$42/12*1*1,0) | N13: =IF(12>=Inputs!$D$42,Inputs!$C$42/12*1*1,0) | O13: =IF(15>=Inputs!$D$42,Inputs!$C$42/12*3*(1+Inputs!$B$74)^1,0) | P13: =IF(18>=Inputs!$D$42,Inputs!$C$42/12*3*(1+Inputs!$B$74)^1,0) | Q13: =IF(21>=Inputs!$D$42,Inputs!$C$42/12*3*(1+Inputs!$B$74)^1,0) | R13: =IF(24>=Inputs!$D$42,Inputs!$C$42/12*3*(1+Inputs!$B$74)^1,0) | S13: =IF(27>=Inputs!$D$42,Inputs!$C$42/12*3*(1+Inputs!$B$74)^2,0) | T13: =IF(30>=Inputs!$D$42,Inputs!$C$42/12*3*(1+Inputs!$B$74)^2,0) | U13: =IF(33>=Inputs!$D$42,Inputs!$C$42/12*3*(1+Inputs!$B$74)^2,0) | V13: =IF(36>=Inputs!$D$42,Inputs!$C$42/12*3*(1+Inputs!$B$74)^2,0)
A14: Director of Business Development - Sales / referrals (growth driver) | C14: =IF(1>=Inputs!$D$43,Inputs!$C$43/12*1*1,0) | D14: =IF(2>=Inputs!$D$43,Inputs!$C$43/12*1*1,0) | E14: =IF(3>=Inputs!$D$43,Inputs!$C$43/12*1*1,0) | F14: =IF(4>=Inputs!$D$43,Inputs!$C$43/12*1*1,0) | G14: =IF(5>=Inputs!$D$43,Inputs!$C$43/12*1*1,0) | H14: =IF(6>=Inputs!$D$43,Inputs!$C$43/12*1*1,0) | I14: =IF(7>=Inputs!$D$43,Inputs!$C$43/12*1*1,0) | J14: =IF(8>=Inputs!$D$43,Inputs!$C$43/12*1*1,0) | K14: =IF(9>=Inputs!$D$43,Inputs!$C$43/12*1*1,0) | L14: =IF(10>=Inputs!$D$43,Inputs!$C$43/12*1*1,0) | M14: =IF(11>=Inputs!$D$43,Inputs!$C$43/12*1*1,0) | N14: =IF(12>=Inputs!$D$43,Inputs!$C$43/12*1*1,0) | O14: =IF(15>=Inputs!$D$43,Inputs!$C$43/12*3*(1+Inputs!$B$74)^1,0) | P14: =IF(18>=Inputs!$D$43,Inputs!$C$43/12*3*(1+Inputs!$B$74)^1,0) | Q14: =IF(21>=Inputs!$D$43,Inputs!$C$43/12*3*(1+Inputs!$B$74)^1,0) | R14: =IF(24>=Inputs!$D$43,Inputs!$C$43/12*3*(1+Inputs!$B$74)^1,0) | S14: =IF(27>=Inputs!$D$43,Inputs!$C$43/12*3*(1+Inputs!$B$74)^2,0) | T14: =IF(30>=Inputs!$D$43,Inputs!$C$43/12*3*(1+Inputs!$B$74)^2,0) | U14: =IF(33>=Inputs!$D$43,Inputs!$C$43/12*3*(1+Inputs!$B$74)^2,0) | V14: =IF(36>=Inputs!$D$43,Inputs!$C$43/12*3*(1+Inputs!$B$74)^2,0)
A15: Capacity hire - 2nd CNA - CNA / Hospice Aide (capacity-driven, triggers ADC>=25) | C15: =IF(1>=Inputs!$D$44,Inputs!$C$44/12*1*1,0) | D15: =IF(2>=Inputs!$D$44,Inputs!$C$44/12*1*1,0) | E15: =IF(3>=Inputs!$D$44,Inputs!$C$44/12*1*1,0) | F15: =IF(4>=Inputs!$D$44,Inputs!$C$44/12*1*1,0) | G15: =IF(5>=Inputs!$D$44,Inputs!$C$44/12*1*1,0) | H15: =IF(6>=Inputs!$D$44,Inputs!$C$44/12*1*1,0) | I15: =IF(7>=Inputs!$D$44,Inputs!$C$44/12*1*1,0) | J15: =IF(8>=Inputs!$D$44,Inputs!$C$44/12*1*1,0) | K15: =IF(9>=Inputs!$D$44,Inputs!$C$44/12*1*1,0) | L15: =IF(10>=Inputs!$D$44,Inputs!$C$44/12*1*1,0) | M15: =IF(11>=Inputs!$D$44,Inputs!$C$44/12*1*1,0) | N15: =IF(12>=Inputs!$D$44,Inputs!$C$44/12*1*1,0) | O15: =IF(15>=Inputs!$D$44,Inputs!$C$44/12*3*(1+Inputs!$B$74)^1,0) | P15: =IF(18>=Inputs!$D$44,Inputs!$C$44/12*3*(1+Inputs!$B$74)^1,0) | Q15: =IF(21>=Inputs!$D$44,Inputs!$C$44/12*3*(1+Inputs!$B$74)^1,0) | R15: =IF(24>=Inputs!$D$44,Inputs!$C$44/12*3*(1+Inputs!$B$74)^1,0) | S15: =IF(27>=Inputs!$D$44,Inputs!$C$44/12*3*(1+Inputs!$B$74)^2,0) | T15: =IF(30>=Inputs!$D$44,Inputs!$C$44/12*3*(1+Inputs!$B$74)^2,0) | U15: =IF(33>=Inputs!$D$44,Inputs!$C$44/12*3*(1+Inputs!$B$74)^2,0) | V15: =IF(36>=Inputs!$D$44,Inputs!$C$44/12*3*(1+Inputs!$B$74)^2,0)
A16: FT Social Worker (MSW) - Core IDG MSW (converts PRN SW to salaried) | C16: =IF(1>=Inputs!$D$45,Inputs!$C$45/12*1*1,0) | D16: =IF(2>=Inputs!$D$45,Inputs!$C$45/12*1*1,0) | E16: =IF(3>=Inputs!$D$45,Inputs!$C$45/12*1*1,0) | F16: =IF(4>=Inputs!$D$45,Inputs!$C$45/12*1*1,0) | G16: =IF(5>=Inputs!$D$45,Inputs!$C$45/12*1*1,0) | H16: =IF(6>=Inputs!$D$45,Inputs!$C$45/12*1*1,0) | I16: =IF(7>=Inputs!$D$45,Inputs!$C$45/12*1*1,0) | J16: =IF(8>=Inputs!$D$45,Inputs!$C$45/12*1*1,0) | K16: =IF(9>=Inputs!$D$45,Inputs!$C$45/12*1*1,0) | L16: =IF(10>=Inputs!$D$45,Inputs!$C$45/12*1*1,0) | M16: =IF(11>=Inputs!$D$45,Inputs!$C$45/12*1*1,0) | N16: =IF(12>=Inputs!$D$45,Inputs!$C$45/12*1*1,0) | O16: =IF(15>=Inputs!$D$45,Inputs!$C$45/12*3*(1+Inputs!$B$74)^1,0) | P16: =IF(18>=Inputs!$D$45,Inputs!$C$45/12*3*(1+Inputs!$B$74)^1,0) | Q16: =IF(21>=Inputs!$D$45,Inputs!$C$45/12*3*(1+Inputs!$B$74)^1,0) | R16: =IF(24>=Inputs!$D$45,Inputs!$C$45/12*3*(1+Inputs!$B$74)^1,0) | S16: =IF(27>=Inputs!$D$45,Inputs!$C$45/12*3*(1+Inputs!$B$74)^2,0) | T16: =IF(30>=Inputs!$D$45,Inputs!$C$45/12*3*(1+Inputs!$B$74)^2,0) | U16: =IF(33>=Inputs!$D$45,Inputs!$C$45/12*3*(1+Inputs!$B$74)^2,0) | V16: =IF(36>=Inputs!$D$45,Inputs!$C$45/12*3*(1+Inputs!$B$74)^2,0)
A17: FT LVN - visits / on-call - Core IDG LVN (converts PRN LVN to salaried) | C17: =IF(1>=Inputs!$D$46,Inputs!$C$46/12*1*1,0) | D17: =IF(2>=Inputs!$D$46,Inputs!$C$46/12*1*1,0) | E17: =IF(3>=Inputs!$D$46,Inputs!$C$46/12*1*1,0) | F17: =IF(4>=Inputs!$D$46,Inputs!$C$46/12*1*1,0) | G17: =IF(5>=Inputs!$D$46,Inputs!$C$46/12*1*1,0) | H17: =IF(6>=Inputs!$D$46,Inputs!$C$46/12*1*1,0) | I17: =IF(7>=Inputs!$D$46,Inputs!$C$46/12*1*1,0) | J17: =IF(8>=Inputs!$D$46,Inputs!$C$46/12*1*1,0) | K17: =IF(9>=Inputs!$D$46,Inputs!$C$46/12*1*1,0) | L17: =IF(10>=Inputs!$D$46,Inputs!$C$46/12*1*1,0) | M17: =IF(11>=Inputs!$D$46,Inputs!$C$46/12*1*1,0) | N17: =IF(12>=Inputs!$D$46,Inputs!$C$46/12*1*1,0) | O17: =IF(15>=Inputs!$D$46,Inputs!$C$46/12*3*(1+Inputs!$B$74)^1,0) | P17: =IF(18>=Inputs!$D$46,Inputs!$C$46/12*3*(1+Inputs!$B$74)^1,0) | Q17: =IF(21>=Inputs!$D$46,Inputs!$C$46/12*3*(1+Inputs!$B$74)^1,0) | R17: =IF(24>=Inputs!$D$46,Inputs!$C$46/12*3*(1+Inputs!$B$74)^1,0) | S17: =IF(27>=Inputs!$D$46,Inputs!$C$46/12*3*(1+Inputs!$B$74)^2,0) | T17: =IF(30>=Inputs!$D$46,Inputs!$C$46/12*3*(1+Inputs!$B$74)^2,0) | U17: =IF(33>=Inputs!$D$46,Inputs!$C$46/12*3*(1+Inputs!$B$74)^2,0) | V17: =IF(36>=Inputs!$D$46,Inputs!$C$46/12*3*(1+Inputs!$B$74)^2,0)
A18: FT Chaplain - Core IDG spiritual care (converts PRN chaplain to FT) | C18: =IF(1>=Inputs!$D$47,Inputs!$C$47/12*1*1,0) | D18: =IF(2>=Inputs!$D$47,Inputs!$C$47/12*1*1,0) | E18: =IF(3>=Inputs!$D$47,Inputs!$C$47/12*1*1,0) | F18: =IF(4>=Inputs!$D$47,Inputs!$C$47/12*1*1,0) | G18: =IF(5>=Inputs!$D$47,Inputs!$C$47/12*1*1,0) | H18: =IF(6>=Inputs!$D$47,Inputs!$C$47/12*1*1,0) | I18: =IF(7>=Inputs!$D$47,Inputs!$C$47/12*1*1,0) | J18: =IF(8>=Inputs!$D$47,Inputs!$C$47/12*1*1,0) | K18: =IF(9>=Inputs!$D$47,Inputs!$C$47/12*1*1,0) | L18: =IF(10>=Inputs!$D$47,Inputs!$C$47/12*1*1,0) | M18: =IF(11>=Inputs!$D$47,Inputs!$C$47/12*1*1,0) | N18: =IF(12>=Inputs!$D$47,Inputs!$C$47/12*1*1,0) | O18: =IF(15>=Inputs!$D$47,Inputs!$C$47/12*3*(1+Inputs!$B$74)^1,0) | P18: =IF(18>=Inputs!$D$47,Inputs!$C$47/12*3*(1+Inputs!$B$74)^1,0) | Q18: =IF(21>=Inputs!$D$47,Inputs!$C$47/12*3*(1+Inputs!$B$74)^1,0) | R18: =IF(24>=Inputs!$D$47,Inputs!$C$47/12*3*(1+Inputs!$B$74)^1,0) | S18: =IF(27>=Inputs!$D$47,Inputs!$C$47/12*3*(1+Inputs!$B$74)^2,0) | T18: =IF(30>=Inputs!$D$47,Inputs!$C$47/12*3*(1+Inputs!$B$74)^2,0) | U18: =IF(33>=Inputs!$D$47,Inputs!$C$47/12*3*(1+Inputs!$B$74)^2,0) | V18: =IF(36>=Inputs!$D$47,Inputs!$C$47/12*3*(1+Inputs!$B$74)^2,0)
A19: Capacity hire - 3rd RN - RN Case Manager (capacity-driven, ADC>=30) | C19: =IF(1>=Inputs!$D$48,Inputs!$C$48/12*1*1,0) | D19: =IF(2>=Inputs!$D$48,Inputs!$C$48/12*1*1,0) | E19: =IF(3>=Inputs!$D$48,Inputs!$C$48/12*1*1,0) | F19: =IF(4>=Inputs!$D$48,Inputs!$C$48/12*1*1,0) | G19: =IF(5>=Inputs!$D$48,Inputs!$C$48/12*1*1,0) | H19: =IF(6>=Inputs!$D$48,Inputs!$C$48/12*1*1,0) | I19: =IF(7>=Inputs!$D$48,Inputs!$C$48/12*1*1,0) | J19: =IF(8>=Inputs!$D$48,Inputs!$C$48/12*1*1,0) | K19: =IF(9>=Inputs!$D$48,Inputs!$C$48/12*1*1,0) | L19: =IF(10>=Inputs!$D$48,Inputs!$C$48/12*1*1,0) | M19: =IF(11>=Inputs!$D$48,Inputs!$C$48/12*1*1,0) | N19: =IF(12>=Inputs!$D$48,Inputs!$C$48/12*1*1,0) | O19: =IF(15>=Inputs!$D$48,Inputs!$C$48/12*3*(1+Inputs!$B$74)^1,0) | P19: =IF(18>=Inputs!$D$48,Inputs!$C$48/12*3*(1+Inputs!$B$74)^1,0) | Q19: =IF(21>=Inputs!$D$48,Inputs!$C$48/12*3*(1+Inputs!$B$74)^1,0) | R19: =IF(24>=Inputs!$D$48,Inputs!$C$48/12*3*(1+Inputs!$B$74)^1,0) | S19: =IF(27>=Inputs!$D$48,Inputs!$C$48/12*3*(1+Inputs!$B$74)^2,0) | T19: =IF(30>=Inputs!$D$48,Inputs!$C$48/12*3*(1+Inputs!$B$74)^2,0) | U19: =IF(33>=Inputs!$D$48,Inputs!$C$48/12*3*(1+Inputs!$B$74)^2,0) | V19: =IF(36>=Inputs!$D$48,Inputs!$C$48/12*3*(1+Inputs!$B$74)^2,0)
A20: Capacity hire - 3rd CNA - CNA / Hospice Aide (capacity-driven, ADC>=32) | C20: =IF(1>=Inputs!$D$49,Inputs!$C$49/12*1*1,0) | D20: =IF(2>=Inputs!$D$49,Inputs!$C$49/12*1*1,0) | E20: =IF(3>=Inputs!$D$49,Inputs!$C$49/12*1*1,0) | F20: =IF(4>=Inputs!$D$49,Inputs!$C$49/12*1*1,0) | G20: =IF(5>=Inputs!$D$49,Inputs!$C$49/12*1*1,0) | H20: =IF(6>=Inputs!$D$49,Inputs!$C$49/12*1*1,0) | I20: =IF(7>=Inputs!$D$49,Inputs!$C$49/12*1*1,0) | J20: =IF(8>=Inputs!$D$49,Inputs!$C$49/12*1*1,0) | K20: =IF(9>=Inputs!$D$49,Inputs!$C$49/12*1*1,0) | L20: =IF(10>=Inputs!$D$49,Inputs!$C$49/12*1*1,0) | M20: =IF(11>=Inputs!$D$49,Inputs!$C$49/12*1*1,0) | N20: =IF(12>=Inputs!$D$49,Inputs!$C$49/12*1*1,0) | O20: =IF(15>=Inputs!$D$49,Inputs!$C$49/12*3*(1+Inputs!$B$74)^1,0) | P20: =IF(18>=Inputs!$D$49,Inputs!$C$49/12*3*(1+Inputs!$B$74)^1,0) | Q20: =IF(21>=Inputs!$D$49,Inputs!$C$49/12*3*(1+Inputs!$B$74)^1,0) | R20: =IF(24>=Inputs!$D$49,Inputs!$C$49/12*3*(1+Inputs!$B$74)^1,0) | S20: =IF(27>=Inputs!$D$49,Inputs!$C$49/12*3*(1+Inputs!$B$74)^2,0) | T20: =IF(30>=Inputs!$D$49,Inputs!$C$49/12*3*(1+Inputs!$B$74)^2,0) | U20: =IF(33>=Inputs!$D$49,Inputs!$C$49/12*3*(1+Inputs!$B$74)^2,0) | V20: =IF(36>=Inputs!$D$49,Inputs!$C$49/12*3*(1+Inputs!$B$74)^2,0)
A21: Capacity hire - 4th RN - RN Case Manager (capacity-driven, ADC>=38) | C21: =IF(1>=Inputs!$D$50,Inputs!$C$50/12*1*1,0) | D21: =IF(2>=Inputs!$D$50,Inputs!$C$50/12*1*1,0) | E21: =IF(3>=Inputs!$D$50,Inputs!$C$50/12*1*1,0) | F21: =IF(4>=Inputs!$D$50,Inputs!$C$50/12*1*1,0) | G21: =IF(5>=Inputs!$D$50,Inputs!$C$50/12*1*1,0) | H21: =IF(6>=Inputs!$D$50,Inputs!$C$50/12*1*1,0) | I21: =IF(7>=Inputs!$D$50,Inputs!$C$50/12*1*1,0) | J21: =IF(8>=Inputs!$D$50,Inputs!$C$50/12*1*1,0) | K21: =IF(9>=Inputs!$D$50,Inputs!$C$50/12*1*1,0) | L21: =IF(10>=Inputs!$D$50,Inputs!$C$50/12*1*1,0) | M21: =IF(11>=Inputs!$D$50,Inputs!$C$50/12*1*1,0) | N21: =IF(12>=Inputs!$D$50,Inputs!$C$50/12*1*1,0) | O21: =IF(15>=Inputs!$D$50,Inputs!$C$50/12*3*(1+Inputs!$B$74)^1,0) | P21: =IF(18>=Inputs!$D$50,Inputs!$C$50/12*3*(1+Inputs!$B$74)^1,0) | Q21: =IF(21>=Inputs!$D$50,Inputs!$C$50/12*3*(1+Inputs!$B$74)^1,0) | R21: =IF(24>=Inputs!$D$50,Inputs!$C$50/12*3*(1+Inputs!$B$74)^1,0) | S21: =IF(27>=Inputs!$D$50,Inputs!$C$50/12*3*(1+Inputs!$B$74)^2,0) | T21: =IF(30>=Inputs!$D$50,Inputs!$C$50/12*3*(1+Inputs!$B$74)^2,0) | U21: =IF(33>=Inputs!$D$50,Inputs!$C$50/12*3*(1+Inputs!$B$74)^2,0) | V21: =IF(36>=Inputs!$D$50,Inputs!$C$50/12*3*(1+Inputs!$B$74)^2,0)
A22: Capacity hire - 4th CNA - CNA / Hospice Aide (capacity-driven, ADC>=40) | C22: =IF(1>=Inputs!$D$51,Inputs!$C$51/12*1*1,0) | D22: =IF(2>=Inputs!$D$51,Inputs!$C$51/12*1*1,0) | E22: =IF(3>=Inputs!$D$51,Inputs!$C$51/12*1*1,0) | F22: =IF(4>=Inputs!$D$51,Inputs!$C$51/12*1*1,0) | G22: =IF(5>=Inputs!$D$51,Inputs!$C$51/12*1*1,0) | H22: =IF(6>=Inputs!$D$51,Inputs!$C$51/12*1*1,0) | I22: =IF(7>=Inputs!$D$51,Inputs!$C$51/12*1*1,0) | J22: =IF(8>=Inputs!$D$51,Inputs!$C$51/12*1*1,0) | K22: =IF(9>=Inputs!$D$51,Inputs!$C$51/12*1*1,0) | L22: =IF(10>=Inputs!$D$51,Inputs!$C$51/12*1*1,0) | M22: =IF(11>=Inputs!$D$51,Inputs!$C$51/12*1*1,0) | N22: =IF(12>=Inputs!$D$51,Inputs!$C$51/12*1*1,0) | O22: =IF(15>=Inputs!$D$51,Inputs!$C$51/12*3*(1+Inputs!$B$74)^1,0) | P22: =IF(18>=Inputs!$D$51,Inputs!$C$51/12*3*(1+Inputs!$B$74)^1,0) | Q22: =IF(21>=Inputs!$D$51,Inputs!$C$51/12*3*(1+Inputs!$B$74)^1,0) | R22: =IF(24>=Inputs!$D$51,Inputs!$C$51/12*3*(1+Inputs!$B$74)^1,0) | S22: =IF(27>=Inputs!$D$51,Inputs!$C$51/12*3*(1+Inputs!$B$74)^2,0) | T22: =IF(30>=Inputs!$D$51,Inputs!$C$51/12*3*(1+Inputs!$B$74)^2,0) | U22: =IF(33>=Inputs!$D$51,Inputs!$C$51/12*3*(1+Inputs!$B$74)^2,0) | V22: =IF(36>=Inputs!$D$51,Inputs!$C$51/12*3*(1+Inputs!$B$74)^2,0)
A23: Capacity hire - 5th RN - RN Case Manager (capacity-driven, ADC>=48) | C23: =IF(1>=Inputs!$D$52,Inputs!$C$52/12*1*1,0) | D23: =IF(2>=Inputs!$D$52,Inputs!$C$52/12*1*1,0) | E23: =IF(3>=Inputs!$D$52,Inputs!$C$52/12*1*1,0) | F23: =IF(4>=Inputs!$D$52,Inputs!$C$52/12*1*1,0) | G23: =IF(5>=Inputs!$D$52,Inputs!$C$52/12*1*1,0) | H23: =IF(6>=Inputs!$D$52,Inputs!$C$52/12*1*1,0) | I23: =IF(7>=Inputs!$D$52,Inputs!$C$52/12*1*1,0) | J23: =IF(8>=Inputs!$D$52,Inputs!$C$52/12*1*1,0) | K23: =IF(9>=Inputs!$D$52,Inputs!$C$52/12*1*1,0) | L23: =IF(10>=Inputs!$D$52,Inputs!$C$52/12*1*1,0) | M23: =IF(11>=Inputs!$D$52,Inputs!$C$52/12*1*1,0) | N23: =IF(12>=Inputs!$D$52,Inputs!$C$52/12*1*1,0) | O23: =IF(15>=Inputs!$D$52,Inputs!$C$52/12*3*(1+Inputs!$B$74)^1,0) | P23: =IF(18>=Inputs!$D$52,Inputs!$C$52/12*3*(1+Inputs!$B$74)^1,0) | Q23: =IF(21>=Inputs!$D$52,Inputs!$C$52/12*3*(1+Inputs!$B$74)^1,0) | R23: =IF(24>=Inputs!$D$52,Inputs!$C$52/12*3*(1+Inputs!$B$74)^1,0) | S23: =IF(27>=Inputs!$D$52,Inputs!$C$52/12*3*(1+Inputs!$B$74)^2,0) | T23: =IF(30>=Inputs!$D$52,Inputs!$C$52/12*3*(1+Inputs!$B$74)^2,0) | U23: =IF(33>=Inputs!$D$52,Inputs!$C$52/12*3*(1+Inputs!$B$74)^2,0) | V23: =IF(36>=Inputs!$D$52,Inputs!$C$52/12*3*(1+Inputs!$B$74)^2,0)
A24: Capacity hire - 5th CNA - CNA / Hospice Aide (capacity-driven, ADC>=50) | C24: =IF(1>=Inputs!$D$53,Inputs!$C$53/12*1*1,0) | D24: =IF(2>=Inputs!$D$53,Inputs!$C$53/12*1*1,0) | E24: =IF(3>=Inputs!$D$53,Inputs!$C$53/12*1*1,0) | F24: =IF(4>=Inputs!$D$53,Inputs!$C$53/12*1*1,0) | G24: =IF(5>=Inputs!$D$53,Inputs!$C$53/12*1*1,0) | H24: =IF(6>=Inputs!$D$53,Inputs!$C$53/12*1*1,0) | I24: =IF(7>=Inputs!$D$53,Inputs!$C$53/12*1*1,0) | J24: =IF(8>=Inputs!$D$53,Inputs!$C$53/12*1*1,0) | K24: =IF(9>=Inputs!$D$53,Inputs!$C$53/12*1*1,0) | L24: =IF(10>=Inputs!$D$53,Inputs!$C$53/12*1*1,0) | M24: =IF(11>=Inputs!$D$53,Inputs!$C$53/12*1*1,0) | N24: =IF(12>=Inputs!$D$53,Inputs!$C$53/12*1*1,0) | O24: =IF(15>=Inputs!$D$53,Inputs!$C$53/12*3*(1+Inputs!$B$74)^1,0) | P24: =IF(18>=Inputs!$D$53,Inputs!$C$53/12*3*(1+Inputs!$B$74)^1,0) | Q24: =IF(21>=Inputs!$D$53,Inputs!$C$53/12*3*(1+Inputs!$B$74)^1,0) | R24: =IF(24>=Inputs!$D$53,Inputs!$C$53/12*3*(1+Inputs!$B$74)^1,0) | S24: =IF(27>=Inputs!$D$53,Inputs!$C$53/12*3*(1+Inputs!$B$74)^2,0) | T24: =IF(30>=Inputs!$D$53,Inputs!$C$53/12*3*(1+Inputs!$B$74)^2,0) | U24: =IF(33>=Inputs!$D$53,Inputs!$C$53/12*3*(1+Inputs!$B$74)^2,0) | V24: =IF(36>=Inputs!$D$53,Inputs!$C$53/12*3*(1+Inputs!$B$74)^2,0)
A25: Capacity hire - 6th CNA - CNA / Hospice Aide (capacity-driven, ADC>=54) | C25: =IF(1>=Inputs!$D$54,Inputs!$C$54/12*1*1,0) | D25: =IF(2>=Inputs!$D$54,Inputs!$C$54/12*1*1,0) | E25: =IF(3>=Inputs!$D$54,Inputs!$C$54/12*1*1,0) | F25: =IF(4>=Inputs!$D$54,Inputs!$C$54/12*1*1,0) | G25: =IF(5>=Inputs!$D$54,Inputs!$C$54/12*1*1,0) | H25: =IF(6>=Inputs!$D$54,Inputs!$C$54/12*1*1,0) | I25: =IF(7>=Inputs!$D$54,Inputs!$C$54/12*1*1,0) | J25: =IF(8>=Inputs!$D$54,Inputs!$C$54/12*1*1,0) | K25: =IF(9>=Inputs!$D$54,Inputs!$C$54/12*1*1,0) | L25: =IF(10>=Inputs!$D$54,Inputs!$C$54/12*1*1,0) | M25: =IF(11>=Inputs!$D$54,Inputs!$C$54/12*1*1,0) | N25: =IF(12>=Inputs!$D$54,Inputs!$C$54/12*1*1,0) | O25: =IF(15>=Inputs!$D$54,Inputs!$C$54/12*3*(1+Inputs!$B$74)^1,0) | P25: =IF(18>=Inputs!$D$54,Inputs!$C$54/12*3*(1+Inputs!$B$74)^1,0) | Q25: =IF(21>=Inputs!$D$54,Inputs!$C$54/12*3*(1+Inputs!$B$74)^1,0) | R25: =IF(24>=Inputs!$D$54,Inputs!$C$54/12*3*(1+Inputs!$B$74)^1,0) | S25: =IF(27>=Inputs!$D$54,Inputs!$C$54/12*3*(1+Inputs!$B$74)^2,0) | T25: =IF(30>=Inputs!$D$54,Inputs!$C$54/12*3*(1+Inputs!$B$74)^2,0) | U25: =IF(33>=Inputs!$D$54,Inputs!$C$54/12*3*(1+Inputs!$B$74)^2,0) | V25: =IF(36>=Inputs!$D$54,Inputs!$C$54/12*3*(1+Inputs!$B$74)^2,0)
A26: Capacity hire - 6th RN - RN Case Manager (capacity-driven, ADC>=55) | C26: =IF(1>=Inputs!$D$55,Inputs!$C$55/12*1*1,0) | D26: =IF(2>=Inputs!$D$55,Inputs!$C$55/12*1*1,0) | E26: =IF(3>=Inputs!$D$55,Inputs!$C$55/12*1*1,0) | F26: =IF(4>=Inputs!$D$55,Inputs!$C$55/12*1*1,0) | G26: =IF(5>=Inputs!$D$55,Inputs!$C$55/12*1*1,0) | H26: =IF(6>=Inputs!$D$55,Inputs!$C$55/12*1*1,0) | I26: =IF(7>=Inputs!$D$55,Inputs!$C$55/12*1*1,0) | J26: =IF(8>=Inputs!$D$55,Inputs!$C$55/12*1*1,0) | K26: =IF(9>=Inputs!$D$55,Inputs!$C$55/12*1*1,0) | L26: =IF(10>=Inputs!$D$55,Inputs!$C$55/12*1*1,0) | M26: =IF(11>=Inputs!$D$55,Inputs!$C$55/12*1*1,0) | N26: =IF(12>=Inputs!$D$55,Inputs!$C$55/12*1*1,0) | O26: =IF(15>=Inputs!$D$55,Inputs!$C$55/12*3*(1+Inputs!$B$74)^1,0) | P26: =IF(18>=Inputs!$D$55,Inputs!$C$55/12*3*(1+Inputs!$B$74)^1,0) | Q26: =IF(21>=Inputs!$D$55,Inputs!$C$55/12*3*(1+Inputs!$B$74)^1,0) | R26: =IF(24>=Inputs!$D$55,Inputs!$C$55/12*3*(1+Inputs!$B$74)^1,0) | S26: =IF(27>=Inputs!$D$55,Inputs!$C$55/12*3*(1+Inputs!$B$74)^2,0) | T26: =IF(30>=Inputs!$D$55,Inputs!$C$55/12*3*(1+Inputs!$B$74)^2,0) | U26: =IF(33>=Inputs!$D$55,Inputs!$C$55/12*3*(1+Inputs!$B$74)^2,0) | V26: =IF(36>=Inputs!$D$55,Inputs!$C$55/12*3*(1+Inputs!$B$74)^2,0)
A27: Quality / Compliance Manager - QAPI program | CoP compliance | surveys | C27: =IF(1>=Inputs!$D$56,Inputs!$C$56/12*1*1,0) | D27: =IF(2>=Inputs!$D$56,Inputs!$C$56/12*1*1,0) | E27: =IF(3>=Inputs!$D$56,Inputs!$C$56/12*1*1,0) | F27: =IF(4>=Inputs!$D$56,Inputs!$C$56/12*1*1,0) | G27: =IF(5>=Inputs!$D$56,Inputs!$C$56/12*1*1,0) | H27: =IF(6>=Inputs!$D$56,Inputs!$C$56/12*1*1,0) | I27: =IF(7>=Inputs!$D$56,Inputs!$C$56/12*1*1,0) | J27: =IF(8>=Inputs!$D$56,Inputs!$C$56/12*1*1,0) | K27: =IF(9>=Inputs!$D$56,Inputs!$C$56/12*1*1,0) | L27: =IF(10>=Inputs!$D$56,Inputs!$C$56/12*1*1,0) | M27: =IF(11>=Inputs!$D$56,Inputs!$C$56/12*1*1,0) | N27: =IF(12>=Inputs!$D$56,Inputs!$C$56/12*1*1,0) | O27: =IF(15>=Inputs!$D$56,Inputs!$C$56/12*3*(1+Inputs!$B$74)^1,0) | P27: =IF(18>=Inputs!$D$56,Inputs!$C$56/12*3*(1+Inputs!$B$74)^1,0) | Q27: =IF(21>=Inputs!$D$56,Inputs!$C$56/12*3*(1+Inputs!$B$74)^1,0) | R27: =IF(24>=Inputs!$D$56,Inputs!$C$56/12*3*(1+Inputs!$B$74)^1,0) | S27: =IF(27>=Inputs!$D$56,Inputs!$C$56/12*3*(1+Inputs!$B$74)^2,0) | T27: =IF(30>=Inputs!$D$56,Inputs!$C$56/12*3*(1+Inputs!$B$74)^2,0) | U27: =IF(33>=Inputs!$D$56,Inputs!$C$56/12*3*(1+Inputs!$B$74)^2,0) | V27: =IF(36>=Inputs!$D$56,Inputs!$C$56/12*3*(1+Inputs!$B$74)^2,0)
A28: Intake / Admissions Coordinator - Referral intake | IDG admit coordination | C28: =IF(1>=Inputs!$D$57,Inputs!$C$57/12*1*1,0) | D28: =IF(2>=Inputs!$D$57,Inputs!$C$57/12*1*1,0) | E28: =IF(3>=Inputs!$D$57,Inputs!$C$57/12*1*1,0) | F28: =IF(4>=Inputs!$D$57,Inputs!$C$57/12*1*1,0) | G28: =IF(5>=Inputs!$D$57,Inputs!$C$57/12*1*1,0) | H28: =IF(6>=Inputs!$D$57,Inputs!$C$57/12*1*1,0) | I28: =IF(7>=Inputs!$D$57,Inputs!$C$57/12*1*1,0) | J28: =IF(8>=Inputs!$D$57,Inputs!$C$57/12*1*1,0) | K28: =IF(9>=Inputs!$D$57,Inputs!$C$57/12*1*1,0) | L28: =IF(10>=Inputs!$D$57,Inputs!$C$57/12*1*1,0) | M28: =IF(11>=Inputs!$D$57,Inputs!$C$57/12*1*1,0) | N28: =IF(12>=Inputs!$D$57,Inputs!$C$57/12*1*1,0) | O28: =IF(15>=Inputs!$D$57,Inputs!$C$57/12*3*(1+Inputs!$B$74)^1,0) | P28: =IF(18>=Inputs!$D$57,Inputs!$C$57/12*3*(1+Inputs!$B$74)^1,0) | Q28: =IF(21>=Inputs!$D$57,Inputs!$C$57/12*3*(1+Inputs!$B$74)^1,0) | R28: =IF(24>=Inputs!$D$57,Inputs!$C$57/12*3*(1+Inputs!$B$74)^1,0) | S28: =IF(27>=Inputs!$D$57,Inputs!$C$57/12*3*(1+Inputs!$B$74)^2,0) | T28: =IF(30>=Inputs!$D$57,Inputs!$C$57/12*3*(1+Inputs!$B$74)^2,0) | U28: =IF(33>=Inputs!$D$57,Inputs!$C$57/12*3*(1+Inputs!$B$74)^2,0) | V28: =IF(36>=Inputs!$D$57,Inputs!$C$57/12*3*(1+Inputs!$B$74)^2,0)
A29: Volunteer Coordinator - Medicare CoP requirement | volunteer hours | C29: =IF(1>=Inputs!$D$58,Inputs!$C$58/12*1*1,0) | D29: =IF(2>=Inputs!$D$58,Inputs!$C$58/12*1*1,0) | E29: =IF(3>=Inputs!$D$58,Inputs!$C$58/12*1*1,0) | F29: =IF(4>=Inputs!$D$58,Inputs!$C$58/12*1*1,0) | G29: =IF(5>=Inputs!$D$58,Inputs!$C$58/12*1*1,0) | H29: =IF(6>=Inputs!$D$58,Inputs!$C$58/12*1*1,0) | I29: =IF(7>=Inputs!$D$58,Inputs!$C$58/12*1*1,0) | J29: =IF(8>=Inputs!$D$58,Inputs!$C$58/12*1*1,0) | K29: =IF(9>=Inputs!$D$58,Inputs!$C$58/12*1*1,0) | L29: =IF(10>=Inputs!$D$58,Inputs!$C$58/12*1*1,0) | M29: =IF(11>=Inputs!$D$58,Inputs!$C$58/12*1*1,0) | N29: =IF(12>=Inputs!$D$58,Inputs!$C$58/12*1*1,0) | O29: =IF(15>=Inputs!$D$58,Inputs!$C$58/12*3*(1+Inputs!$B$74)^1,0) | P29: =IF(18>=Inputs!$D$58,Inputs!$C$58/12*3*(1+Inputs!$B$74)^1,0) | Q29: =IF(21>=Inputs!$D$58,Inputs!$C$58/12*3*(1+Inputs!$B$74)^1,0) | R29: =IF(24>=Inputs!$D$58,Inputs!$C$58/12*3*(1+Inputs!$B$74)^1,0) | S29: =IF(27>=Inputs!$D$58,Inputs!$C$58/12*3*(1+Inputs!$B$74)^2,0) | T29: =IF(30>=Inputs!$D$58,Inputs!$C$58/12*3*(1+Inputs!$B$74)^2,0) | U29: =IF(33>=Inputs!$D$58,Inputs!$C$58/12*3*(1+Inputs!$B$74)^2,0) | V29: =IF(36>=Inputs!$D$58,Inputs!$C$58/12*3*(1+Inputs!$B$74)^2,0)
A30: Subtotal - direct-care FT salaries | C30: =C9+C10+C13+C15+C16+C17+C18+C19+C20+C21+C22+C23+C24+C25+C26 | D30: =D9+D10+D13+D15+D16+D17+D18+D19+D20+D21+D22+D23+D24+D25+D26 | E30: =E9+E10+E13+E15+E16+E17+E18+E19+E20+E21+E22+E23+E24+E25+E26 | F30: =F9+F10+F13+F15+F16+F17+F18+F19+F20+F21+F22+F23+F24+F25+F26 | G30: =G9+G10+G13+G15+G16+G17+G18+G19+G20+G21+G22+G23+G24+G25+G26 | H30: =H9+H10+H13+H15+H16+H17+H18+H19+H20+H21+H22+H23+H24+H25+H26 | I30: =I9+I10+I13+I15+I16+I17+I18+I19+I20+I21+I22+I23+I24+I25+I26 | J30: =J9+J10+J13+J15+J16+J17+J18+J19+J20+J21+J22+J23+J24+J25+J26 | ... V30: =V9+V10+V13+V15+V16+V17+V18+V19+V20+V21+V22+V23+V24+V25+V26
A32: PRN / PER-VISIT DIRECT CARE (census-driven)
A33: PRN On-Call LVN (Kendricks-Tuck, Foster) | C33: =C6*Inputs!$C$63*Inputs!$D$63*1 | D33: =D6*Inputs!$C$63*Inputs!$D$63*1 | E33: =E6*Inputs!$C$63*Inputs!$D$63*1 | F33: =F6*Inputs!$C$63*Inputs!$D$63*1 | G33: =G6*Inputs!$C$63*Inputs!$D$63*1 | H33: =H6*Inputs!$C$63*Inputs!$D$63*1 | I33: =I6*Inputs!$C$63*Inputs!$D$63*1 | J33: =J6*Inputs!$C$63*Inputs!$D$63*1 | ... N33: =N6*Inputs!$C$63*Inputs!$D$63*1 | O33: =O6*Inputs!$C$63*Inputs!$D$63*3 | P33: =P6*Inputs!$C$63*Inputs!$D$63*3 | Q33: =Q6*Inputs!$C$63*Inputs!$D$63*3 | R33: =R6*Inputs!$C$63*Inputs!$D$63*3 | S33: =S6*Inputs!$C$63*Inputs!$D$63*3 | T33: =T6*Inputs!$C$63*Inputs!$D$63*3 | U33: =U6*Inputs!$C$63*Inputs!$D$63*3 | V33: =V6*Inputs!$C$63*Inputs!$D$63*3
A34: PRN Chaplain (Ector, Johnson) | C34: =C6*Inputs!$C$64*Inputs!$D$64*1 | D34: =D6*Inputs!$C$64*Inputs!$D$64*1 | E34: =E6*Inputs!$C$64*Inputs!$D$64*1 | F34: =F6*Inputs!$C$64*Inputs!$D$64*1 | G34: =G6*Inputs!$C$64*Inputs!$D$64*1 | H34: =H6*Inputs!$C$64*Inputs!$D$64*1 | I34: =I6*Inputs!$C$64*Inputs!$D$64*1 | J34: =J6*Inputs!$C$64*Inputs!$D$64*1 | ... N34: =N6*Inputs!$C$64*Inputs!$D$64*1 | O34: =O6*Inputs!$C$64*Inputs!$D$64*3 | P34: =P6*Inputs!$C$64*Inputs!$D$64*3 | Q34: =Q6*Inputs!$C$64*Inputs!$D$64*3 | R34: =R6*Inputs!$C$64*Inputs!$D$64*3 | S34: =S6*Inputs!$C$64*Inputs!$D$64*3 | T34: =T6*Inputs!$C$64*Inputs!$D$64*3 | U34: =U6*Inputs!$C$64*Inputs!$D$64*3 | V34: =V6*Inputs!$C$64*Inputs!$D$64*3
A35: PRN Social Worker (Sanders) | C35: =C6*Inputs!$C$65*Inputs!$D$65*1 | D35: =D6*Inputs!$C$65*Inputs!$D$65*1 | E35: =E6*Inputs!$C$65*Inputs!$D$65*1 | F35: =F6*Inputs!$C$65*Inputs!$D$65*1 | G35: =G6*Inputs!$C$65*Inputs!$D$65*1 | H35: =H6*Inputs!$C$65*Inputs!$D$65*1 | I35: =I6*Inputs!$C$65*Inputs!$D$65*1 | J35: =J6*Inputs!$C$65*Inputs!$D$65*1 | ... N35: =N6*Inputs!$C$65*Inputs!$D$65*1 | O35: =O6*Inputs!$C$65*Inputs!$D$65*3 | P35: =P6*Inputs!$C$65*Inputs!$D$65*3 | Q35: =Q6*Inputs!$C$65*Inputs!$D$65*3 | R35: =R6*Inputs!$C$65*Inputs!$D$65*3 | S35: =S6*Inputs!$C$65*Inputs!$D$65*3 | T35: =T6*Inputs!$C$65*Inputs!$D$65*3 | U35: =U6*Inputs!$C$65*Inputs!$D$65*3 | V35: =V6*Inputs!$C$65*Inputs!$D$65*3
A36: PRN Nurse Practitioner (Rogers) | C36: =C6*Inputs!$C$66*Inputs!$D$66*1 | D36: =D6*Inputs!$C$66*Inputs!$D$66*1 | E36: =E6*Inputs!$C$66*Inputs!$D$66*1 | F36: =F6*Inputs!$C$66*Inputs!$D$66*1 | G36: =G6*Inputs!$C$66*Inputs!$D$66*1 | H36: =H6*Inputs!$C$66*Inputs!$D$66*1 | I36: =I6*Inputs!$C$66*Inputs!$D$66*1 | J36: =J6*Inputs!$C$66*Inputs!$D$66*1 | ... N36: =N6*Inputs!$C$66*Inputs!$D$66*1 | O36: =O6*Inputs!$C$66*Inputs!$D$66*3 | P36: =P6*Inputs!$C$66*Inputs!$D$66*3 | Q36: =Q6*Inputs!$C$66*Inputs!$D$66*3 | R36: =R6*Inputs!$C$66*Inputs!$D$66*3 | S36: =S6*Inputs!$C$66*Inputs!$D$66*3 | T36: =T6*Inputs!$C$66*Inputs!$D$66*3 | U36: =U6*Inputs!$C$66*Inputs!$D$66*3 | V36: =V6*Inputs!$C$66*Inputs!$D$66*3
A37: PRN CNA / per-visit (Henson, Mills) | C37: =C6*Inputs!$C$67*Inputs!$D$67*1 | D37: =D6*Inputs!$C$67*Inputs!$D$67*1 | E37: =E6*Inputs!$C$67*Inputs!$D$67*1 | F37: =F6*Inputs!$C$67*Inputs!$D$67*1 | G37: =G6*Inputs!$C$67*Inputs!$D$67*1 | H37: =H6*Inputs!$C$67*Inputs!$D$67*1 | I37: =I6*Inputs!$C$67*Inputs!$D$67*1 | J37: =J6*Inputs!$C$67*Inputs!$D$67*1 | ... N37: =N6*Inputs!$C$67*Inputs!$D$67*1 | O37: =O6*Inputs!$C$67*Inputs!$D$67*3 | P37: =P6*Inputs!$C$67*Inputs!$D$67*3 | Q37: =Q6*Inputs!$C$67*Inputs!$D$67*3 | R37: =R6*Inputs!$C$67*Inputs!$D$67*3 | S37: =S6*Inputs!$C$67*Inputs!$D$67*3 | T37: =T6*Inputs!$C$67*Inputs!$D$67*3 | U37: =U6*Inputs!$C$67*Inputs!$D$67*3 | V37: =V6*Inputs!$C$67*Inputs!$D$67*3
A38: Subtotal - PRN visit wages | C38: =C33+C34+C35+C36+C37 | D38: =D33+D34+D35+D36+D37 | E38: =E33+E34+E35+E36+E37 | F38: =F33+F34+F35+F36+F37 | G38: =G33+G34+G35+G36+G37 | H38: =H33+H34+H35+H36+H37 | I38: =I33+I34+I35+I36+I37 | J38: =J33+J34+J35+J36+J37 | ... V38: =V33+V34+V35+V36+V37
A39: Medical Director 1 + 2 (1099, MD2 conditional) | C39: =Inputs!$B$81*1+IF(1>=Inputs!$B$83,Inputs!$B$82*1,0) | D39: =Inputs!$B$81*1+IF(2>=Inputs!$B$83,Inputs!$B$82*1,0) | E39: =Inputs!$B$81*1+IF(3>=Inputs!$B$83,Inputs!$B$82*1,0) | F39: =Inputs!$B$81*1+IF(4>=Inputs!$B$83,Inputs!$B$82*1,0) | G39: =Inputs!$B$81*1+IF(5>=Inputs!$B$83,Inputs!$B$82*1,0) | H39: =Inputs!$B$81*1+IF(6>=Inputs!$B$83,Inputs!$B$82*1,0) | I39: =Inputs!$B$81*1+IF(7>=Inputs!$B$83,Inputs!$B$82*1,0) | J39: =Inputs!$B$81*1+IF(8>=Inputs!$B$83,Inputs!$B$82*1,0) | K39: =Inputs!$B$81*1+IF(9>=Inputs!$B$83,Inputs!$B$82*1,0) | L39: =Inputs!$B$81*1+IF(10>=Inputs!$B$83,Inputs!$B$82*1,0) | M39: =Inputs!$B$81*1+IF(11>=Inputs!$B$83,Inputs!$B$82*1,0) | N39: =Inputs!$B$81*1+IF(12>=Inputs!$B$83,Inputs!$B$82*1,0) | O39: =Inputs!$B$81*3+IF(15>=Inputs!$B$83,Inputs!$B$82*3,0) | P39: =Inputs!$B$81*3+IF(18>=Inputs!$B$83,Inputs!$B$82*3,0) | Q39: =Inputs!$B$81*3+IF(21>=Inputs!$B$83,Inputs!$B$82*3,0) | R39: =Inputs!$B$81*3+IF(24>=Inputs!$B$83,Inputs!$B$82*3,0) | S39: =Inputs!$B$81*3+IF(27>=Inputs!$B$83,Inputs!$B$82*3,0) | T39: =Inputs!$B$81*3+IF(30>=Inputs!$B$83,Inputs!$B$82*3,0) | U39: =Inputs!$B$81*3+IF(33>=Inputs!$B$83,Inputs!$B$82*3,0) | V39: =Inputs!$B$81*3+IF(36>=Inputs!$B$83,Inputs!$B$82*3,0)
A41: INDIRECT LABOR (SG&A overhead)
A42: Subtotal - indirect FT salaries | C42: =C8+C11+C12+C14+C27+C28+C29 | D42: =D8+D11+D12+D14+D27+D28+D29 | E42: =E8+E11+E12+E14+E27+E28+E29 | F42: =F8+F11+F12+F14+F27+F28+F29 | G42: =G8+G11+G12+G14+G27+G28+G29 | H42: =H8+H11+H12+H14+H27+H28+H29 | I42: =I8+I11+I12+I14+I27+I28+I29 | J42: =J8+J11+J12+J14+J27+J28+J29 | ... V42: =V8+V11+V12+V14+V27+V28+V29
A43: Rhonda Smith - Office Mgr (PRN, W-2) | C43: =Inputs!$C$59/12*1*1 | D43: =Inputs!$C$59/12*1*1 | E43: =Inputs!$C$59/12*1*1 | F43: =Inputs!$C$59/12*1*1 | G43: =Inputs!$C$59/12*1*1 | H43: =Inputs!$C$59/12*1*1 | I43: =Inputs!$C$59/12*1*1 | J43: =Inputs!$C$59/12*1*1 | ... N43: =Inputs!$C$59/12*1*1 | O43: =Inputs!$C$59/12*3*(1+Inputs!$B$74)^1 | P43: =Inputs!$C$59/12*3*(1+Inputs!$B$74)^1 | Q43: =Inputs!$C$59/12*3*(1+Inputs!$B$74)^1 | R43: =Inputs!$C$59/12*3*(1+Inputs!$B$74)^1 | S43: =Inputs!$C$59/12*3*(1+Inputs!$B$74)^2 | T43: =Inputs!$C$59/12*3*(1+Inputs!$B$74)^2 | U43: =Inputs!$C$59/12*3*(1+Inputs!$B$74)^2 | V43: =Inputs!$C$59/12*3*(1+Inputs!$B$74)^2
A45: EMPLOYER BURDEN & BENEFITS (W-2 only)
A46: Direct W-2 wage base (FT direct + PRN) | C46: =C30+C38 | D46: =D30+D38 | E46: =E30+E38 | F46: =F30+F38 | G46: =G30+G38 | H46: =H30+H38 | I46: =I30+I38 | J46: =J30+J38 | ... V46: =V30+V38
A47: Indirect W-2 wage base (FT indirect + Rhonda) | C47: =C42+C43 | D47: =D42+D43 | E47: =E42+E43 | F47: =F42+F43 | G47: =G42+G43 | H47: =H42+H43 | I47: =I42+I43 | J47: =J42+J43 | ... V47: =V42+V43
A48: Burden - direct (load %) | C48: =C46*Inputs!$B$77 | D48: =D46*Inputs!$B$77 | E48: =E46*Inputs!$B$77 | F48: =F46*Inputs!$B$77 | G48: =G46*Inputs!$B$77 | H48: =H46*Inputs!$B$77 | I48: =I46*Inputs!$B$77 | J48: =J46*Inputs!$B$77 | ... V48: =V46*Inputs!$B$77
A49: Burden - indirect (load %) | C49: =C47*Inputs!$B$77 | D49: =D47*Inputs!$B$77 | E49: =E47*Inputs!$B$77 | F49: =F47*Inputs!$B$77 | G49: =G47*Inputs!$B$77 | H49: =H47*Inputs!$B$77 | I49: =I47*Inputs!$B$77 | J49: =J47*Inputs!$B$77 | ... V49: =V47*Inputs!$B$77
A50: Health insurance - direct FT | C50: =Inputs!$B$78*(IF(1>=Inputs!$D$38,1,0)+IF(1>=Inputs!$D$39,1,0)+IF(1>=Inputs!$D$42,1,0)+IF(1>=Inputs!$D$44,1,0)+IF(1>=Inputs!$D$45,1,0)+IF(1>=Inputs!$D$46,1,0)+IF(1>=Inputs!$D$47,1,0)+IF(1>=Inputs!$D$48,1,0)+IF(1>=Inputs!$D$49,1,0)+IF(1>=Inputs!$D$50,1,0)+IF(1>=Inputs!$D$51,1,0)+IF(1>=Inputs!$D$52,1,0)+IF(1>=Inputs!$D$53,1,0)+IF(1>=Inputs!$D$54,1,0)+IF(1>=Inputs!$D$55,1,0))*1 | D50: =Inputs!$B$78*(IF(2>=Inputs!$D$38,1,0)+IF(2>=Inputs!$D$39,1,0)+IF(2>=Inputs!$D$42,1,0)+IF(2>=Inputs!$D$44,1,0)+IF(2>=Inputs!$D$45,1,0)+IF(2>=Inputs!$D$46,1,0)+IF(2>=Inputs!$D$47,1,0)+IF(2>=Inputs!$D$48,1,0)+IF(2>=Inputs!$D$49,1,0)+IF(2>=Inputs!$D$50,1,0)+IF(2>=Inputs!$D$51,1,0)+IF(2>=Inputs!$D$52,1,0)+IF(2>=Inputs!$D$53,1,0)+IF(2>=Inputs!$D$54,1,0)+IF(2>=Inputs!$D$55,1,0))*1 | E50: =Inputs!$B$78*(IF(3>=Inputs!$D$38,1,0)+IF(3>=Inputs!$D$39,1,0)+IF(3>=Inputs!$D$42,1,0)+IF(3>=Inputs!$D$44,1,0)+IF(3>=Inputs!$D$45,1,0)+IF(3>=Inputs!$D$46,1,0)+IF(3>=Inputs!$D$47,1,0)+IF(3>=Inputs!$D$48,1,0)+IF(3>=Inputs!$D$49,1,0)+IF(3>=Inputs!$D$50,1,0)+IF(3>=Inputs!$D$51,1,0)+IF(3>=Inputs!$D$52,1,0)+IF(3>=Inputs!$D$53,1,0)+IF(3>=Inputs!$D$54,1,0)+IF(3>=Inputs!$D$55,1,0))*1 | F50: =Inputs!$B$78*(IF(4>=Inputs!$D$38,1,0)+IF(4>=Inputs!$D$39,1,0)+IF(4>=Inputs!$D$42,1,0)+IF(4>=Inputs!$D$44,1,0)+IF(4>=Inputs!$D$45,1,0)+IF(4>=Inputs!$D$46,1,0)+IF(4>=Inputs!$D$47,1,0)+IF(4>=Inputs!$D$48,1,0)+IF(4>=Inputs!$D$49,1,0)+IF(4>=Inputs!$D$50,1,0)+IF(4>=Inputs!$D$51,1,0)+IF(4>=Inputs!$D$52,1,0)+IF(4>=Inputs!$D$53,1,0)+IF(4>=Inputs!$D$54,1,0)+IF(4>=Inputs!$D$55,1,0))*1 | G50: =Inputs!$B$78*(IF(5>=Inputs!$D$38,1,0)+IF(5>=Inputs!$D$39,1,0)+IF(5>=Inputs!$D$42,1,0)+IF(5>=Inputs!$D$44,1,0)+IF(5>=Inputs!$D$45,1,0)+IF(5>=Inputs!$D$46,1,0)+IF(5>=Inputs!$D$47,1,0)+IF(5>=Inputs!$D$48,1,0)+IF(5>=Inputs!$D$49,1,0)+IF(5>=Inputs!$D$50,1,0)+IF(5>=Inputs!$D$51,1,0)+IF(5>=Inputs!$D$52,1,0)+IF(5>=Inputs!$D$53,1,0)+IF(5>=Inputs!$D$54,1,0)+IF(5>=Inputs!$D$55,1,0))*1 | H50: =Inputs!$B$78*(IF(6>=Inputs!$D$38,1,0)+IF(6>=Inputs!$D$39,1,0)+IF(6>=Inputs!$D$42,1,0)+IF(6>=Inputs!$D$44,1,0)+IF(6>=Inputs!$D$45,1,0)+IF(6>=Inputs!$D$46,1,0)+IF(6>=Inputs!$D$47,1,0)+IF(6>=Inputs!$D$48,1,0)+IF(6>=Inputs!$D$49,1,0)+IF(6>=Inputs!$D$50,1,0)+IF(6>=Inputs!$D$51,1,0)+IF(6>=Inputs!$D$52,1,0)+IF(6>=Inputs!$D$53,1,0)+IF(6>=Inputs!$D$54,1,0)+IF(6>=Inputs!$D$55,1,0))*1 | I50: =Inputs!$B$78*(IF(7>=Inputs!$D$38,1,0)+IF(7>=Inputs!$D$39,1,0)+IF(7>=Inputs!$D$42,1,0)+IF(7>=Inputs!$D$44,1,0)+IF(7>=Inputs!$D$45,1,0)+IF(7>=Inputs!$D$46,1,0)+IF(7>=Inputs!$D$47,1,0)+IF(7>=Inputs!$D$48,1,0)+IF(7>=Inputs!$D$49,1,0)+IF(7>=Inputs!$D$50,1,0)+IF(7>=Inputs!$D$51,1,0)+IF(7>=Inputs!$D$52,1,0)+IF(7>=Inputs!$D$53,1,0)+IF(7>=Inputs!$D$54,1,0)+IF(7>=Inputs!$D$55,1,0))*1 | J50: =Inputs!$B$78*(IF(8>=Inputs!$D$38,1,0)+IF(8>=Inputs!$D$39,1,0)+IF(8>=Inputs!$D$42,1,0)+IF(8>=Inputs!$D$44,1,0)+IF(8>=Inputs!$D$45,1,0)+IF(8>=Inputs!$D$46,1,0)+IF(8>=Inputs!$D$47,1,0)+IF(8>=Inputs!$D$48,1,0)+IF(8>=Inputs!$D$49,1,0)+IF(8>=Inputs!$D$50,1,0)+IF(8>=Inputs!$D$51,1,0)+IF(8>=Inputs!$D$52,1,0)+IF(8>=Inputs!$D$53,1,0)+IF(8>=Inputs!$D$54,1,0)+IF(8>=Inputs!$D$55,1,0))*1 | K50: =Inputs!$B$78*(IF(9>=Inputs!$D$38,1,0)+IF(9>=Inputs!$D$39,1,0)+IF(9>=Inputs!$D$42,1,0)+IF(9>=Inputs!$D$44,1,0)+IF(9>=Inputs!$D$45,1,0)+IF(9>=Inputs!$D$46,1,0)+IF(9>=Inputs!$D$47,1,0)+IF(9>=Inputs!$D$48,1,0)+IF(9>=Inputs!$D$49,1,0)+IF(9>=Inputs!$D$50,1,0)+IF(9>=Inputs!$D$51,1,0)+IF(9>=Inputs!$D$52,1,0)+IF(9>=Inputs!$D$53,1,0)+IF(9>=Inputs!$D$54,1,0)+IF(9>=Inputs!$D$55,1,0))*1 | L50: =Inputs!$B$78*(IF(10>=Inputs!$D$38,1,0)+IF(10>=Inputs!$D$39,1,0)+IF(10>=Inputs!$D$42,1,0)+IF(10>=Inputs!$D$44,1,0)+IF(10>=Inputs!$D$45,1,0)+IF(10>=Inputs!$D$46,1,0)+IF(10>=Inputs!$D$47,1,0)+IF(10>=Inputs!$D$48,1,0)+IF(10>=Inputs!$D$49,1,0)+IF(10>=Inputs!$D$50,1,0)+IF(10>=Inputs!$D$51,1,0)+IF(10>=Inputs!$D$52,1,0)+IF(10>=Inputs!$D$53,1,0)+IF(10>=Inputs!$D$54,1,0)+IF(10>=Inputs!$D$55,1,0))*1 | M50: =Inputs!$B$78*(IF(11>=Inputs!$D$38,1,0)+IF(11>=Inputs!$D$39,1,0)+IF(11>=Inputs!$D$42,1,0)+IF(11>=Inputs!$D$44,1,0)+IF(11>=Inputs!$D$45,1,0)+IF(11>=Inputs!$D$46,1,0)+IF(11>=Inputs!$D$47,1,0)+IF(11>=Inputs!$D$48,1,0)+IF(11>=Inputs!$D$49,1,0)+IF(11>=Inputs!$D$50,1,0)+IF(11>=Inputs!$D$51,1,0)+IF(11>=Inputs!$D$52,1,0)+IF(11>=Inputs!$D$53,1,0)+IF(11>=Inputs!$D$54,1,0)+IF(11>=Inputs!$D$55,1,0))*1 | N50: =Inputs!$B$78*(IF(12>=Inputs!$D$38,1,0)+IF(12>=Inputs!$D$39,1,0)+IF(12>=Inputs!$D$42,1,0)+IF(12>=Inputs!$D$44,1,0)+IF(12>=Inputs!$D$45,1,0)+IF(12>=Inputs!$D$46,1,0)+IF(12>=Inputs!$D$47,1,0)+IF(12>=Inputs!$D$48,1,0)+IF(12>=Inputs!$D$49,1,0)+IF(12>=Inputs!$D$50,1,0)+IF(12>=Inputs!$D$51,1,0)+IF(12>=Inputs!$D$52,1,0)+IF(12>=Inputs!$D$53,1,0)+IF(12>=Inputs!$D$54,1,0)+IF(12>=Inputs!$D$55,1,0))*1 | O50: =Inputs!$B$78*(IF(15>=Inputs!$D$38,1,0)+IF(15>=Inputs!$D$39,1,0)+IF(15>=Inputs!$D$42,1,0)+IF(15>=Inputs!$D$44,1,0)+IF(15>=Inputs!$D$45,1,0)+IF(15>=Inputs!$D$46,1,0)+IF(15>=Inputs!$D$47,1,0)+IF(15>=Inputs!$D$48,1,0)+IF(15>=Inputs!$D$49,1,0)+IF(15>=Inputs!$D$50,1,0)+IF(15>=Inputs!$D$51,1,0)+IF(15>=Inputs!$D$52,1,0)+IF(15>=Inputs!$D$53,1,0)+IF(15>=Inputs!$D$54,1,0)+IF(15>=Inputs!$D$55,1,0))*3 | P50: =Inputs!$B$78*(IF(18>=Inputs!$D$38,1,0)+IF(18>=Inputs!$D$39,1,0)+IF(18>=Inputs!$D$42,1,0)+IF(18>=Inputs!$D$44,1,0)+IF(18>=Inputs!$D$45,1,0)+IF(18>=Inputs!$D$46,1,0)+IF(18>=Inputs!$D$47,1,0)+IF(18>=Inputs!$D$48,1,0)+IF(18>=Inputs!$D$49,1,0)+IF(18>=Inputs!$D$50,1,0)+IF(18>=Inputs!$D$51,1,0)+IF(18>=Inputs!$D$52,1,0)+IF(18>=Inputs!$D$53,1,0)+IF(18>=Inputs!$D$54,1,0)+IF(18>=Inputs!$D$55,1,0))*3 | Q50: =Inputs!$B$78*(IF(21>=Inputs!$D$38,1,0)+IF(21>=Inputs!$D$39,1,0)+IF(21>=Inputs!$D$42,1,0)+IF(21>=Inputs!$D$44,1,0)+IF(21>=Inputs!$D$45,1,0)+IF(21>=Inputs!$D$46,1,0)+IF(21>=Inputs!$D$47,1,0)+IF(21>=Inputs!$D$48,1,0)+IF(21>=Inputs!$D$49,1,0)+IF(21>=Inputs!$D$50,1,0)+IF(21>=Inputs!$D$51,1,0)+IF(21>=Inputs!$D$52,1,0)+IF(21>=Inputs!$D$53,1,0)+IF(21>=Inputs!$D$54,1,0)+IF(21>=Inputs!$D$55,1,0))*3 | R50: =Inputs!$B$78*(IF(24>=Inputs!$D$38,1,0)+IF(24>=Inputs!$D$39,1,0)+IF(24>=Inputs!$D$42,1,0)+IF(24>=Inputs!$D$44,1,0)+IF(24>=Inputs!$D$45,1,0)+IF(24>=Inputs!$D$46,1,0)+IF(24>=Inputs!$D$47,1,0)+IF(24>=Inputs!$D$48,1,0)+IF(24>=Inputs!$D$49,1,0)+IF(24>=Inputs!$D$50,1,0)+IF(24>=Inputs!$D$51,1,0)+IF(24>=Inputs!$D$52,1,0)+IF(24>=Inputs!$D$53,1,0)+IF(24>=Inputs!$D$54,1,0)+IF(24>=Inputs!$D$55,1,0))*3 | S50: =Inputs!$B$78*(IF(27>=Inputs!$D$38,1,0)+IF(27>=Inputs!$D$39,1,0)+IF(27>=Inputs!$D$42,1,0)+IF(27>=Inputs!$D$44,1,0)+IF(27>=Inputs!$D$45,1,0)+IF(27>=Inputs!$D$46,1,0)+IF(27>=Inputs!$D$47,1,0)+IF(27>=Inputs!$D$48,1,0)+IF(27>=Inputs!$D$49,1,0)+IF(27>=Inputs!$D$50,1,0)+IF(27>=Inputs!$D$51,1,0)+IF(27>=Inputs!$D$52,1,0)+IF(27>=Inputs!$D$53,1,0)+IF(27>=Inputs!$D$54,1,0)+IF(27>=Inputs!$D$55,1,0))*3 | T50: =Inputs!$B$78*(IF(30>=Inputs!$D$38,1,0)+IF(30>=Inputs!$D$39,1,0)+IF(30>=Inputs!$D$42,1,0)+IF(30>=Inputs!$D$44,1,0)+IF(30>=Inputs!$D$45,1,0)+IF(30>=Inputs!$D$46,1,0)+IF(30>=Inputs!$D$47,1,0)+IF(30>=Inputs!$D$48,1,0)+IF(30>=Inputs!$D$49,1,0)+IF(30>=Inputs!$D$50,1,0)+IF(30>=Inputs!$D$51,1,0)+IF(30>=Inputs!$D$52,1,0)+IF(30>=Inputs!$D$53,1,0)+IF(30>=Inputs!$D$54,1,0)+IF(30>=Inputs!$D$55,1,0))*3 | U50: =Inputs!$B$78*(IF(33>=Inputs!$D$38,1,0)+IF(33>=Inputs!$D$39,1,0)+IF(33>=Inputs!$D$42,1,0)+IF(33>=Inputs!$D$44,1,0)+IF(33>=Inputs!$D$45,1,0)+IF(33>=Inputs!$D$46,1,0)+IF(33>=Inputs!$D$47,1,0)+IF(33>=Inputs!$D$48,1,0)+IF(33>=Inputs!$D$49,1,0)+IF(33>=Inputs!$D$50,1,0)+IF(33>=Inputs!$D$51,1,0)+IF(33>=Inputs!$D$52,1,0)+IF(33>=Inputs!$D$53,1,0)+IF(33>=Inputs!$D$54,1,0)+IF(33>=Inputs!$D$55,1,0))*3 | V50: =Inputs!$B$78*(IF(36>=Inputs!$D$38,1,0)+IF(36>=Inputs!$D$39,1,0)+IF(36>=Inputs!$D$42,1,0)+IF(36>=Inputs!$D$44,1,0)+IF(36>=Inputs!$D$45,1,0)+IF(36>=Inputs!$D$46,1,0)+IF(36>=Inputs!$D$47,1,0)+IF(36>=Inputs!$D$48,1,0)+IF(36>=Inputs!$D$49,1,0)+IF(36>=Inputs!$D$50,1,0)+IF(36>=Inputs!$D$51,1,0)+IF(36>=Inputs!$D$52,1,0)+IF(36>=Inputs!$D$53,1,0)+IF(36>=Inputs!$D$54,1,0)+IF(36>=Inputs!$D$55,1,0))*3
A51: Health insurance - indirect FT | C51: =Inputs!$B$78*(IF(1>=Inputs!$D$37,1,0)+IF(1>=Inputs!$D$40,1,0)+IF(1>=Inputs!$D$41,1,0)+IF(1>=Inputs!$D$43,1,0)+IF(1>=Inputs!$D$56,1,0)+IF(1>=Inputs!$D$57,1,0)+IF(1>=Inputs!$D$58,1,0))*1 | D51: =Inputs!$B$78*(IF(2>=Inputs!$D$37,1,0)+IF(2>=Inputs!$D$40,1,0)+IF(2>=Inputs!$D$41,1,0)+IF(2>=Inputs!$D$43,1,0)+IF(2>=Inputs!$D$56,1,0)+IF(2>=Inputs!$D$57,1,0)+IF(2>=Inputs!$D$58,1,0))*1 | E51: =Inputs!$B$78*(IF(3>=Inputs!$D$37,1,0)+IF(3>=Inputs!$D$40,1,0)+IF(3>=Inputs!$D$41,1,0)+IF(3>=Inputs!$D$43,1,0)+IF(3>=Inputs!$D$56,1,0)+IF(3>=Inputs!$D$57,1,0)+IF(3>=Inputs!$D$58,1,0))*1 | F51: =Inputs!$B$78*(IF(4>=Inputs!$D$37,1,0)+IF(4>=Inputs!$D$40,1,0)+IF(4>=Inputs!$D$41,1,0)+IF(4>=Inputs!$D$43,1,0)+IF(4>=Inputs!$D$56,1,0)+IF(4>=Inputs!$D$57,1,0)+IF(4>=Inputs!$D$58,1,0))*1 | G51: =Inputs!$B$78*(IF(5>=Inputs!$D$37,1,0)+IF(5>=Inputs!$D$40,1,0)+IF(5>=Inputs!$D$41,1,0)+IF(5>=Inputs!$D$43,1,0)+IF(5>=Inputs!$D$56,1,0)+IF(5>=Inputs!$D$57,1,0)+IF(5>=Inputs!$D$58,1,0))*1 | H51: =Inputs!$B$78*(IF(6>=Inputs!$D$37,1,0)+IF(6>=Inputs!$D$40,1,0)+IF(6>=Inputs!$D$41,1,0)+IF(6>=Inputs!$D$43,1,0)+IF(6>=Inputs!$D$56,1,0)+IF(6>=Inputs!$D$57,1,0)+IF(6>=Inputs!$D$58,1,0))*1 | I51: =Inputs!$B$78*(IF(7>=Inputs!$D$37,1,0)+IF(7>=Inputs!$D$40,1,0)+IF(7>=Inputs!$D$41,1,0)+IF(7>=Inputs!$D$43,1,0)+IF(7>=Inputs!$D$56,1,0)+IF(7>=Inputs!$D$57,1,0)+IF(7>=Inputs!$D$58,1,0))*1 | J51: =Inputs!$B$78*(IF(8>=Inputs!$D$37,1,0)+IF(8>=Inputs!$D$40,1,0)+IF(8>=Inputs!$D$41,1,0)+IF(8>=Inputs!$D$43,1,0)+IF(8>=Inputs!$D$56,1,0)+IF(8>=Inputs!$D$57,1,0)+IF(8>=Inputs!$D$58,1,0))*1 | K51: =Inputs!$B$78*(IF(9>=Inputs!$D$37,1,0)+IF(9>=Inputs!$D$40,1,0)+IF(9>=Inputs!$D$41,1,0)+IF(9>=Inputs!$D$43,1,0)+IF(9>=Inputs!$D$56,1,0)+IF(9>=Inputs!$D$57,1,0)+IF(9>=Inputs!$D$58,1,0))*1 | L51: =Inputs!$B$78*(IF(10>=Inputs!$D$37,1,0)+IF(10>=Inputs!$D$40,1,0)+IF(10>=Inputs!$D$41,1,0)+IF(10>=Inputs!$D$43,1,0)+IF(10>=Inputs!$D$56,1,0)+IF(10>=Inputs!$D$57,1,0)+IF(10>=Inputs!$D$58,1,0))*1 | M51: =Inputs!$B$78*(IF(11>=Inputs!$D$37,1,0)+IF(11>=Inputs!$D$40,1,0)+IF(11>=Inputs!$D$41,1,0)+IF(11>=Inputs!$D$43,1,0)+IF(11>=Inputs!$D$56,1,0)+IF(11>=Inputs!$D$57,1,0)+IF(11>=Inputs!$D$58,1,0))*1 | N51: =Inputs!$B$78*(IF(12>=Inputs!$D$37,1,0)+IF(12>=Inputs!$D$40,1,0)+IF(12>=Inputs!$D$41,1,0)+IF(12>=Inputs!$D$43,1,0)+IF(12>=Inputs!$D$56,1,0)+IF(12>=Inputs!$D$57,1,0)+IF(12>=Inputs!$D$58,1,0))*1 | O51: =Inputs!$B$78*(IF(15>=Inputs!$D$37,1,0)+IF(15>=Inputs!$D$40,1,0)+IF(15>=Inputs!$D$41,1,0)+IF(15>=Inputs!$D$43,1,0)+IF(15>=Inputs!$D$56,1,0)+IF(15>=Inputs!$D$57,1,0)+IF(15>=Inputs!$D$58,1,0))*3 | P51: =Inputs!$B$78*(IF(18>=Inputs!$D$37,1,0)+IF(18>=Inputs!$D$40,1,0)+IF(18>=Inputs!$D$41,1,0)+IF(18>=Inputs!$D$43,1,0)+IF(18>=Inputs!$D$56,1,0)+IF(18>=Inputs!$D$57,1,0)+IF(18>=Inputs!$D$58,1,0))*3 | Q51: =Inputs!$B$78*(IF(21>=Inputs!$D$37,1,0)+IF(21>=Inputs!$D$40,1,0)+IF(21>=Inputs!$D$41,1,0)+IF(21>=Inputs!$D$43,1,0)+IF(21>=Inputs!$D$56,1,0)+IF(21>=Inputs!$D$57,1,0)+IF(21>=Inputs!$D$58,1,0))*3 | R51: =Inputs!$B$78*(IF(24>=Inputs!$D$37,1,0)+IF(24>=Inputs!$D$40,1,0)+IF(24>=Inputs!$D$41,1,0)+IF(24>=Inputs!$D$43,1,0)+IF(24>=Inputs!$D$56,1,0)+IF(24>=Inputs!$D$57,1,0)+IF(24>=Inputs!$D$58,1,0))*3 | S51: =Inputs!$B$78*(IF(27>=Inputs!$D$37,1,0)+IF(27>=Inputs!$D$40,1,0)+IF(27>=Inputs!$D$41,1,0)+IF(27>=Inputs!$D$43,1,0)+IF(27>=Inputs!$D$56,1,0)+IF(27>=Inputs!$D$57,1,0)+IF(27>=Inputs!$D$58,1,0))*3 | T51: =Inputs!$B$78*(IF(30>=Inputs!$D$37,1,0)+IF(30>=Inputs!$D$40,1,0)+IF(30>=Inputs!$D$41,1,0)+IF(30>=Inputs!$D$43,1,0)+IF(30>=Inputs!$D$56,1,0)+IF(30>=Inputs!$D$57,1,0)+IF(30>=Inputs!$D$58,1,0))*3 | U51: =Inputs!$B$78*(IF(33>=Inputs!$D$37,1,0)+IF(33>=Inputs!$D$40,1,0)+IF(33>=Inputs!$D$41,1,0)+IF(33>=Inputs!$D$43,1,0)+IF(33>=Inputs!$D$56,1,0)+IF(33>=Inputs!$D$57,1,0)+IF(33>=Inputs!$D$58,1,0))*3 | V51: =Inputs!$B$78*(IF(36>=Inputs!$D$37,1,0)+IF(36>=Inputs!$D$40,1,0)+IF(36>=Inputs!$D$41,1,0)+IF(36>=Inputs!$D$43,1,0)+IF(36>=Inputs!$D$56,1,0)+IF(36>=Inputs!$D$57,1,0)+IF(36>=Inputs!$D$58,1,0))*3
A53: TOTAL DIRECT-CARE LABOR (COGS) | C53: =C30+C38+C39+C48+C50 | D53: =D30+D38+D39+D48+D50 | E53: =E30+E38+E39+E48+E50 | F53: =F30+F38+F39+F48+F50 | G53: =G30+G38+G39+G48+G50 | H53: =H30+H38+H39+H48+H50 | I53: =I30+I38+I39+I48+I50 | J53: =J30+J38+J39+J48+J50 | ... V53: =V30+V38+V39+V48+V50
A54: TOTAL INDIRECT LABOR (SG&A) | C54: =C42+C43+C49+C51 | D54: =D42+D43+D49+D51 | E54: =E42+E43+E49+E51 | F54: =F42+F43+F49+F51 | G54: =G42+G43+G49+G51 | H54: =H42+H43+H49+H51 | I54: =I42+I43+I49+I51 | J54: =J42+J43+J49+J51 | ... V54: =V42+V43+V49+V51

Sheet Operating Budget
A1: AZALEA HOSPICE & PALLIATIVE CARE - Tyler, TX
A2: Operating Budget - P&L | Net Rev - COGS = Gross Profit - SG&A = EBITDA - D&A - Interest = Net Income
A4: ($ per period) | C4: YEAR 1 - monthly | O4: YEAR 2 - quarterly | S4: YEAR 3 - quarterly
C5: M1 | D5: M2 | E5: M3 | F5: M4 | G5: M5 | H5: M6 | I5: M7 | J5: M8 | K5: M9 | L5: M10 | M5: M11 | N5: M12 | O5: Y2 Q1 | P5: Y2 Q2 | Q5: Y2 Q3 | R5: Y2 Q4 | S5: Y3 Q1 | T5: Y3 Q2 | U5: Y3 Q3 | V5: Y3 Q4
A6: NET REVENUE | C6: ='Revenue Model'!C17 | D6: ='Revenue Model'!D17 | E6: ='Revenue Model'!E17 | F6: ='Revenue Model'!F17 | G6: ='Revenue Model'!G17 | H6: ='Revenue Model'!H17 | I6: ='Revenue Model'!I17 | J6: ='Revenue Model'!J17 | ... V6: ='Revenue Model'!V17
A8: COST OF SERVICES
A9: Direct-care labor | C9: ='Staffing & Payroll'!C53 | D9: ='Staffing & Payroll'!D53 | E9: ='Staffing & Payroll'!E53 | F9: ='Staffing & Payroll'!F53 | G9: ='Staffing & Payroll'!G53 | H9: ='Staffing & Payroll'!H53 | I9: ='Staffing & Payroll'!I53 | J9: ='Staffing & Payroll'!J53 | ... V9: ='Staffing & Payroll'!V53
A10: Medical supplies | C10: ='Revenue Model'!C12*Inputs!$B$86 | D10: ='Revenue Model'!D12*Inputs!$B$86 | E10: ='Revenue Model'!E12*Inputs!$B$86 | F10: ='Revenue Model'!F12*Inputs!$B$86 | G10: ='Revenue Model'!G12*Inputs!$B$86 | H10: ='Revenue Model'!H12*Inputs!$B$86 | I10: ='Revenue Model'!I12*Inputs!$B$86 | J10: ='Revenue Model'!J12*Inputs!$B$86 | ... V10: ='Revenue Model'!V12*Inputs!$B$86
A11: DME | C11: ='Revenue Model'!C12*Inputs!$B$87 | D11: ='Revenue Model'!D12*Inputs!$B$87 | E11: ='Revenue Model'!E12*Inputs!$B$87 | F11: ='Revenue Model'!F12*Inputs!$B$87 | G11: ='Revenue Model'!G12*Inputs!$B$87 | H11: ='Revenue Model'!H12*Inputs!$B$87 | I11: ='Revenue Model'!I12*Inputs!$B$87 | J11: ='Revenue Model'!J12*Inputs!$B$87 | ... V11: ='Revenue Model'!V12*Inputs!$B$87
A12: Pharmacy | C12: ='Revenue Model'!C12*Inputs!$B$88 | D12: ='Revenue Model'!D12*Inputs!$B$88 | E12: ='Revenue Model'!E12*Inputs!$B$88 | F12: ='Revenue Model'!F12*Inputs!$B$88 | G12: ='Revenue Model'!G12*Inputs!$B$88 | H12: ='Revenue Model'!H12*Inputs!$B$88 | I12: ='Revenue Model'!I12*Inputs!$B$88 | J12: ='Revenue Model'!J12*Inputs!$B$88 | ... V12: ='Revenue Model'!V12*Inputs!$B$88
A13: Patient-related COGS subtotal | C13: =C10+C11+C12 | D13: =D10+D11+D12 | E13: =E10+E11+E12 | F13: =F10+F11+F12 | G13: =G10+G11+G12 | H13: =H10+H11+H12 | I13: =I10+I11+I12 | J13: =J10+J11+J12 | ... V13: =V10+V11+V12
A14: TOTAL COST OF SERVICES | C14: =C9+C13 | D14: =D9+D13 | E14: =E9+E13 | F14: =F9+F13 | G14: =G9+G13 | H14: =H9+H13 | I14: =I9+I13 | J14: =J9+J13 | ... V14: =V9+V13
A15: GROSS PROFIT | C15: =C6-C14 | D15: =D6-D14 | E15: =E6-E14 | F15: =F6-F14 | G15: =G6-G14 | H15: =H6-H14 | I15: =I6-I14 | J15: =J6-J14 | ... V15: =V6-V14
A16: Gross margin % | C16: =IF(C6=0,0,C15/C6) | D16: =IF(D6=0,0,D15/D6) | E16: =IF(E6=0,0,E15/E6) | F16: =IF(F6=0,0,F15/F6) | G16: =IF(G6=0,0,G15/G6) | H16: =IF(H6=0,0,H15/H6) | I16: =IF(I6=0,0,I15/I6) | J16: =IF(J6=0,0,J15/J6) | ... V16: =IF(V6=0,0,V15/V6)
A18: SELLING, GENERAL & ADMINISTRATIVE
A19: Indirect labor | C19: ='Staffing & Payroll'!C54 | D19: ='Staffing & Payroll'!D54 | E19: ='Staffing & Payroll'!E54 | F19: ='Staffing & Payroll'!F54 | G19: ='Staffing & Payroll'!G54 | H19: ='Staffing & Payroll'!H54 | I19: ='Staffing & Payroll'!I54 | J19: ='Staffing & Payroll'!J54 | ... V19: ='Staffing & Payroll'!V54
A20: Fixed G&A (utilities, EMR, billing, rent, mktg...) | C20: =SUM(Inputs!$B$91:$B$103)*1 | D20: =SUM(Inputs!$B$91:$B$103)*1 | E20: =SUM(Inputs!$B$91:$B$103)*1 | F20: =SUM(Inputs!$B$91:$B$103)*1 | G20: =SUM(Inputs!$B$91:$B$103)*1 | H20: =SUM(Inputs!$B$91:$B$103)*1 | I20: =SUM(Inputs!$B$91:$B$103)*1 | J20: =SUM(Inputs!$B$91:$B$103)*1 | ... N20: =SUM(Inputs!$B$91:$B$103)*1 | O20: =SUM(Inputs!$B$91:$B$103)*3 | P20: =SUM(Inputs!$B$91:$B$103)*3 | Q20: =SUM(Inputs!$B$91:$B$103)*3 | R20: =SUM(Inputs!$B$91:$B$103)*3 | S20: =SUM(Inputs!$B$91:$B$103)*3 | T20: =SUM(Inputs!$B$91:$B$103)*3 | U20: =SUM(Inputs!$B$91:$B$103)*3 | V20: =SUM(Inputs!$B$91:$B$103)*3
A21: Outsourced billing fee (1.5% of gross) | C21: ='Revenue Model'!C14*Inputs!$B$106 | D21: ='Revenue Model'!D14*Inputs!$B$106 | E21: ='Revenue Model'!E14*Inputs!$B$106 | F21: ='Revenue Model'!F14*Inputs!$B$106 | G21: ='Revenue Model'!G14*Inputs!$B$106 | H21: ='Revenue Model'!H14*Inputs!$B$106 | I21: ='Revenue Model'!I14*Inputs!$B$106 | J21: ='Revenue Model'!J14*Inputs!$B$106 | ... V21: ='Revenue Model'!V14*Inputs!$B$106
A22: QR payment fee (% of gross) | C22: ='Revenue Model'!C14*Inputs!$B$107 | D22: ='Revenue Model'!D14*Inputs!$B$107 | E22: ='Revenue Model'!E14*Inputs!$B$107 | F22: ='Revenue Model'!F14*Inputs!$B$107 | G22: ='Revenue Model'!G14*Inputs!$B$107 | H22: ='Revenue Model'!H14*Inputs!$B$107 | I22: ='Revenue Model'!I14*Inputs!$B$107 | J22: ='Revenue Model'!J14*Inputs!$B$107 | ... V22: ='Revenue Model'!V14*Inputs!$B$107
A23: TOTAL SG&A | C23: =C19+C20+C21+C22 | D23: =D19+D20+D21+D22 | E23: =E19+E20+E21+E22 | F23: =F19+F20+F21+F22 | G23: =G19+G20+G21+G22 | H23: =H19+H20+H21+H22 | I23: =I19+I20+I21+I22 | J23: =J19+J20+J21+J22 | ... V23: =V19+V20+V21+V22
A24: EBITDA | C24: =C15-C23 | D24: =D15-D23 | E24: =E15-E23 | F24: =F15-F23 | G24: =G15-G23 | H24: =H15-H23 | I24: =I15-I23 | J24: =J15-J23 | ... V24: =V15-V23
A25: EBITDA margin % | C25: =IF(C6=0,0,C24/C6) | D25: =IF(D6=0,0,D24/D6) | E25: =IF(E6=0,0,E24/E6) | F25: =IF(F6=0,0,F24/F6) | G25: =IF(G6=0,0,G24/G6) | H25: =IF(H6=0,0,H24/H6) | I25: =IF(I6=0,0,I24/I6) | J25: =IF(J6=0,0,J24/J6) | ... V25: =IF(V6=0,0,V24/V6)
A27: BELOW EBITDA
A28: Depreciation & amortization | C28: =Inputs!$B$140*1 | D28: =Inputs!$B$140*1 | E28: =Inputs!$B$140*1 | F28: =Inputs!$B$140*1 | G28: =Inputs!$B$140*1 | H28: =Inputs!$B$140*1 | I28: =Inputs!$B$140*1 | J28: =Inputs!$B$140*1 | ... N28: =Inputs!$B$140*1 | O28: =Inputs!$B$140*3 | P28: =Inputs!$B$140*3 | Q28: =Inputs!$B$140*3 | R28: =Inputs!$B$140*3 | S28: =Inputs!$B$140*3 | T28: =Inputs!$B$140*3 | U28: =Inputs!$B$140*3 | V28: =Inputs!$B$140*3
A29: Interest - SBA loan | C29: ='Debt Schedule'!C13 | D29: ='Debt Schedule'!D13 | E29: ='Debt Schedule'!E13 | F29: ='Debt Schedule'!F13 | G29: ='Debt Schedule'!G13 | H29: ='Debt Schedule'!H13 | I29: ='Debt Schedule'!I13 | J29: ='Debt Schedule'!J13 | ... V29: ='Debt Schedule'!V13
A30: Interest - Hickory license note | C30: ='Debt Schedule'!C21 | D30: ='Debt Schedule'!D21 | E30: ='Debt Schedule'!E21 | F30: ='Debt Schedule'!F21 | G30: ='Debt Schedule'!G21 | H30: ='Debt Schedule'!H21 | I30: ='Debt Schedule'!I21 | J30: ='Debt Schedule'!J21 | ... V30: ='Debt Schedule'!V21
A31: Interest - working-capital line | C31: ='Cash Flow & BS'!C16 | D31: ='Cash Flow & BS'!D16 | E31: ='Cash Flow & BS'!E16 | F31: ='Cash Flow & BS'!F16 | G31: ='Cash Flow & BS'!G16 | H31: ='Cash Flow & BS'!H16 | I31: ='Cash Flow & BS'!I16 | J31: ='Cash Flow & BS'!J16 | ... V31: ='Cash Flow & BS'!V16
A32: PRE-TAX INCOME | C32: =C24-C28-C29-C30-C31 | D32: =D24-D28-D29-D30-D31 | E32: =E24-E28-E29-E30-E31 | F32: =F24-F28-F29-F30-F31 | G32: =G24-G28-G29-G30-G31 | H32: =H24-H28-H29-H30-H31 | I32: =I24-I28-I29-I30-I31 | J32: =J24-J28-J29-J30-J31 | ... V32: =V24-V28-V29-V30-V31
A33: TX franchise / margin tax | C33: =IF(C32>0,C6*Inputs!$B$119,0) | D33: =IF(D32>0,D6*Inputs!$B$119,0) | E33: =IF(E32>0,E6*Inputs!$B$119,0) | F33: =IF(F32>0,F6*Inputs!$B$119,0) | G33: =IF(G32>0,G6*Inputs!$B$119,0) | H33: =IF(H32>0,H6*Inputs!$B$119,0) | I33: =IF(I32>0,I6*Inputs!$B$119,0) | J33: =IF(J32>0,J6*Inputs!$B$119,0) | ... V33: =IF(V32>0,V6*Inputs!$B$119,0)
A34: NET INCOME | C34: =C32-C33 | D34: =D32-D33 | E34: =E32-E33 | F34: =F32-F33 | G34: =G32-G33 | H34: =H32-H33 | I34: =I32-I33 | J34: =J32-J33 | ... V34: =V32-V33

Sheet Detailed P&L
A1: Azalea Hospice & Palliative Care - Tyler, TX
A2: Profit and Loss
A3: Year 1 (monthly) | Years 2-3 (annual) | model data, cash basis
B5: M1 | C5: M2 | D5: M3 | E5: M4 | F5: M5 | G5: M6 | H5: M7 | I5: M8 | J5: M9 | K5: M10 | L5: M11 | M5: M12 | N5: Year 2 | O5: Year 3 | P5: TOTAL
A6: Income
A7: Gross Billed Revenue | B7: ='Revenue Model'!C14 | C7: ='Revenue Model'!D14 | D7: ='Revenue Model'!E14 | E7: ='Revenue Model'!F14 | F7: ='Revenue Model'!G14 | G7: ='Revenue Model'!H14 | H7: ='Revenue Model'!I14 | I7: ='Revenue Model'!J14 | ... M7: ='Revenue Model'!N14 | N7: =SUM('Revenue Model'!O14:R14) | O7: =SUM('Revenue Model'!S14:V14) | P7: =SUM(B7:M7)+N7+O7
A8: Less: CDAs Adjustment | B8: =0 | C8: =0 | D8: =0 | E8: =0 | F8: =0 | G8: =0 | H8: =0 | I8: =0 | ... O8: =0 | P8: =SUM(B8:M8)+N8+O8
A9: Less: Net Due Zero (Write-offs) | B9: ='Revenue Model'!C14*Inputs!$B$11 | C9: ='Revenue Model'!D14*Inputs!$B$11 | D9: ='Revenue Model'!E14*Inputs!$B$11 | E9: ='Revenue Model'!F14*Inputs!$B$11 | F9: ='Revenue Model'!G14*Inputs!$B$11 | G9: ='Revenue Model'!H14*Inputs!$B$11 | H9: ='Revenue Model'!I14*Inputs!$B$11 | I9: ='Revenue Model'!J14*Inputs!$B$11 | ... M9: ='Revenue Model'!N14*Inputs!$B$11 | N9: =SUM('Revenue Model'!O14:R14)*Inputs!$B$11 | O9: =SUM('Revenue Model'!S14:V14)*Inputs!$B$11 | P9: =SUM(B9:M9)+N9+O9
A10: Less: Sequestration | B10: ='Revenue Model'!C14*Inputs!$B$10 | C10: ='Revenue Model'!D14*Inputs!$B$10 | D10: ='Revenue Model'!E14*Inputs!$B$10 | E10: ='Revenue Model'!F14*Inputs!$B$10 | F10: ='Revenue Model'!G14*Inputs!$B$10 | G10: ='Revenue Model'!H14*Inputs!$B$10 | H10: ='Revenue Model'!I14*Inputs!$B$10 | I10: ='Revenue Model'!J14*Inputs!$B$10 | ... M10: ='Revenue Model'!N14*Inputs!$B$10 | N10: =SUM('Revenue Model'!O14:R14)*Inputs!$B$10 | O10: =SUM('Revenue Model'!S14:V14)*Inputs!$B$10 | P10: =SUM(B10:M10)+N10+O10
A11: Less: Medication Adjustments | B11: =0 | C11: =0 | D11: =0 | E11: =0 | F11: =0 | G11: =0 | H11: =0 | I11: =0 | ... O11: =0 | P11: =SUM(B11:M11)+N11+O11
A12: Total Income | B12: =B7-B8-B9-B10-B11 | C12: =C7-C8-C9-C10-C11 | D12: =D7-D8-D9-D10-D11 | E12: =E7-E8-E9-E10-E11 | F12: =F7-F8-F9-F10-F11 | G12: =G7-G8-G9-G10-G11 | H12: =H7-H8-H9-H10-H11 | I12: =I7-I8-I9-I10-I11 | ... P12: =P7-P8-P9-P10-P11
A14: Cost of Services
A15: Pharmacy | B15: ='Revenue Model'!C12*Inputs!$B$88 | C15: ='Revenue Model'!D12*Inputs!$B$88 | D15: ='Revenue Model'!E12*Inputs!$B$88 | E15: ='Revenue Model'!F12*Inputs!$B$88 | F15: ='Revenue Model'!G12*Inputs!$B$88 | G15: ='Revenue Model'!H12*Inputs!$B$88 | H15: ='Revenue Model'!I12*Inputs!$B$88 | I15: ='Revenue Model'!J12*Inputs!$B$88 | ... M15: ='Revenue Model'!N12*Inputs!$B$88 | N15: =SUM('Revenue Model'!O12:R12)*Inputs!$B$88 | O15: =SUM('Revenue Model'!S12:V12)*Inputs!$B$88 | P15: =SUM(B15:M15)+N15+O15
A16: Medical Supplies | B16: ='Revenue Model'!C12*Inputs!$B$86 | C16: ='Revenue Model'!D12*Inputs!$B$86 | D16: ='Revenue Model'!E12*Inputs!$B$86 | E16: ='Revenue Model'!F12*Inputs!$B$86 | F16: ='Revenue Model'!G12*Inputs!$B$86 | G16: ='Revenue Model'!H12*Inputs!$B$86 | H16: ='Revenue Model'!I12*Inputs!$B$86 | I16: ='Revenue Model'!J12*Inputs!$B$86 | ... M16: ='Revenue Model'!N12*Inputs!$B$86 | N16: =SUM('Revenue Model'!O12:R12)*Inputs!$B$86 | O16: =SUM('Revenue Model'!S12:V12)*Inputs!$B$86 | P16: =SUM(B16:M16)+N16+O16
A17: Durable Medical Equipment (DME) | B17: ='Revenue Model'!C12*Inputs!$B$87 | C17: ='Revenue Model'!D12*Inputs!$B$87 | D17: ='Revenue Model'!E12*Inputs!$B$87 | E17: ='Revenue Model'!F12*Inputs!$B$87 | F17: ='Revenue Model'!G12*Inputs!$B$87 | G17: ='Revenue Model'!H12*Inputs!$B$87 | H17: ='Revenue Model'!I12*Inputs!$B$87 | I17: ='Revenue Model'!J12*Inputs!$B$87 | ... M17: ='Revenue Model'!N12*Inputs!$B$87 | N17: =SUM('Revenue Model'!O12:R12)*Inputs!$B$87 | O17: =SUM('Revenue Model'!S12:V12)*Inputs!$B$87 | P17: =SUM(B17:M17)+N17+O17
A18: Respite Care | B18: =0 | C18: =0 | D18: =0 | E18: =0 | F18: =0 | G18: =0 | H18: =0 | I18: =0 | ... O18: =0 | P18: =SUM(B18:M18)+N18+O18
A19: Transportation | B19: =0 | C19: =0 | D19: =0 | E19: =0 | F19: =0 | G19: =0 | H19: =0 | I19: =0 | ... O19: =0 | P19: =SUM(B19:M19)+N19+O19
A20: Infusion / Labs | B20: =0 | C20: =0 | D20: =0 | E20: =0 | F20: =0 | G20: =0 | H20: =0 | I20: =0 | ... O20: =0 | P20: =SUM(B20:M20)+N20+O20
A21: PT / OT / ST | B21: =0 | C21: =0 | D21: =0 | E21: =0 | F21: =0 | G21: =0 | H21: =0 | I21: =0 | ... O21: =0 | P21: =SUM(B21:M21)+N21+O21
A22: Total Cost of Services | B22: =SUM(B15:B21) | C22: =SUM(C15:C21) | D22: =SUM(D15:D21) | E22: =SUM(E15:E21) | F22: =SUM(F15:F21) | G22: =SUM(G15:G21) | H22: =SUM(H15:H21) | I22: =SUM(I15:I21) | ... P22: =SUM(P15:P21)
A24: Gross Profit | B24: =B12-B22 | C24: =C12-C22 | D24: =D12-D22 | E24: =E12-E22 | F24: =F12-F22 | G24: =G12-G22 | H24: =H12-H22 | I24: =I12-I22 | ... P24: =P12-P22
A26: Operating Expenses
A27: Payroll & Related
A28: Payroll - 1st Half | B28: =('Staffing & Payroll'!C30+'Staffing & Payroll'!C42+'Staffing & Payroll'!C38+'Staffing & Payroll'!C43)/2 | C28: =('Staffing & Payroll'!D30+'Staffing & Payroll'!D42+'Staffing & Payroll'!D38+'Staffing & Payroll'!D43)/2 | D28: =('Staffing & Payroll'!E30+'Staffing & Payroll'!E42+'Staffing & Payroll'!E38+'Staffing & Payroll'!E43)/2 | E28: =('Staffing & Payroll'!F30+'Staffing & Payroll'!F42+'Staffing & Payroll'!F38+'Staffing & Payroll'!F43)/2 | F28: =('Staffing & Payroll'!G30+'Staffing & Payroll'!G42+'Staffing & Payroll'!G38+'Staffing & Payroll'!G43)/2 | G28: =('Staffing & Payroll'!H30+'Staffing & Payroll'!H42+'Staffing & Payroll'!H38+'Staffing & Payroll'!H43)/2 | H28: =('Staffing & Payroll'!I30+'Staffing & Payroll'!I42+'Staffing & Payroll'!I38+'Staffing & Payroll'!I43)/2 | I28: =('Staffing & Payroll'!J30+'Staffing & Payroll'!J42+'Staffing & Payroll'!J38+'Staffing & Payroll'!J43)/2 | ... M28: =('Staffing & Payroll'!N30+'Staffing & Payroll'!N42+'Staffing & Payroll'!N38+'Staffing & Payroll'!N43)/2 | N28: =(SUM('Staffing & Payroll'!O30:R30)+SUM('Staffing & Payroll'!O42:R42)+SUM('Staffing & Payroll'!O38:R38)+SUM('Staffing & Payroll'!O43:R43))/2 | O28: =(SUM('Staffing & Payroll'!S30:V30)+SUM('Staffing & Payroll'!S42:V42)+SUM('Staffing & Payroll'!S38:V38)+SUM('Staffing & Payroll'!S43:V43))/2 | P28: =SUM(B28:M28)+N28+O28
A29: Payroll - 2nd Half | B29: =('Staffing & Payroll'!C30+'Staffing & Payroll'!C42+'Staffing & Payroll'!C38+'Staffing & Payroll'!C43)/2 | C29: =('Staffing & Payroll'!D30+'Staffing & Payroll'!D42+'Staffing & Payroll'!D38+'Staffing & Payroll'!D43)/2 | D29: =('Staffing & Payroll'!E30+'Staffing & Payroll'!E42+'Staffing & Payroll'!E38+'Staffing & Payroll'!E43)/2 | E29: =('Staffing & Payroll'!F30+'Staffing & Payroll'!F42+'Staffing & Payroll'!F38+'Staffing & Payroll'!F43)/2 | F29: =('Staffing & Payroll'!G30+'Staffing & Payroll'!G42+'Staffing & Payroll'!G38+'Staffing & Payroll'!G43)/2 | G29: =('Staffing & Payroll'!H30+'Staffing & Payroll'!H42+'Staffing & Payroll'!H38+'Staffing & Payroll'!H43)/2 | H29: =('Staffing & Payroll'!I30+'Staffing & Payroll'!I42+'Staffing & Payroll'!I38+'Staffing & Payroll'!I43)/2 | I29: =('Staffing & Payroll'!J30+'Staffing & Payroll'!J42+'Staffing & Payroll'!J38+'Staffing & Payroll'!J43)/2 | ... M29: =('Staffing & Payroll'!N30+'Staffing & Payroll'!N42+'Staffing & Payroll'!N38+'Staffing & Payroll'!N43)/2 | N29: =(SUM('Staffing & Payroll'!O30:R30)+SUM('Staffing & Payroll'!O42:R42)+SUM('Staffing & Payroll'!O38:R38)+SUM('Staffing & Payroll'!O43:R43))/2 | O29: =(SUM('Staffing & Payroll'!S30:V30)+SUM('Staffing & Payroll'!S42:V42)+SUM('Staffing & Payroll'!S38:V38)+SUM('Staffing & Payroll'!S43:V43))/2 | P29: =SUM(B29:M29)+N29+O29
A30: Payroll YTD Adjustments | B30: =0 | C30: =0 | D30: =0 | E30: =0 | F30: =0 | G30: =0 | H30: =0 | I30: =0 | ... O30: =0 | P30: =SUM(B30:M30)+N30+O30
A31: Employer Taxes (FUTA/SUI/FICA/WC) | B31: ='Staffing & Payroll'!C48+'Staffing & Payroll'!C49 | C31: ='Staffing & Payroll'!D48+'Staffing & Payroll'!D49 | D31: ='Staffing & Payroll'!E48+'Staffing & Payroll'!E49 | E31: ='Staffing & Payroll'!F48+'Staffing & Payroll'!F49 | F31: ='Staffing & Payroll'!G48+'Staffing & Payroll'!G49 | G31: ='Staffing & Payroll'!H48+'Staffing & Payroll'!H49 | H31: ='Staffing & Payroll'!I48+'Staffing & Payroll'!I49 | I31: ='Staffing & Payroll'!J48+'Staffing & Payroll'!J49 | ... M31: ='Staffing & Payroll'!N48+'Staffing & Payroll'!N49 | N31: =SUM('Staffing & Payroll'!O48:R48)+SUM('Staffing & Payroll'!O49:R49) | O31: =SUM('Staffing & Payroll'!S48:V48)+SUM('Staffing & Payroll'!S49:V49) | P31: =SUM(B31:M31)+N31+O31
A32: Contract Labor | B32: =0 | C32: =0 | D32: =0 | E32: =0 | F32: =0 | G32: =0 | H32: =0 | I32: =0 | ... O32: =0 | P32: =SUM(B32:M32)+N32+O32
A33: Medical Director | B33: ='Staffing & Payroll'!C39 | C33: ='Staffing & Payroll'!D39 | D33: ='Staffing & Payroll'!E39 | E33: ='Staffing & Payroll'!F39 | F33: ='Staffing & Payroll'!G39 | G33: ='Staffing & Payroll'!H39 | H33: ='Staffing & Payroll'!I39 | I33: ='Staffing & Payroll'!J39 | ... M33: ='Staffing & Payroll'!N39 | N33: =SUM('Staffing & Payroll'!O39:R39) | O33: =SUM('Staffing & Payroll'!S39:V39) | P33: =SUM(B33:M33)+N33+O33
A34: Medical Director 2 | B34: =0 | C34: =0 | D34: =0 | E34: =0 | F34: =0 | G34: =0 | H34: =0 | I34: =0 | ... O34: =0 | P34: =SUM(B34:M34)+N34+O34
A35: Intercompany Transfer | B35: =0 | C35: =0 | D35: =0 | E35: =0 | F35: =0 | G35: =0 | H35: =0 | I35: =0 | ... O35: =0 | P35: =SUM(B35:M35)+N35+O35
A36: Staff Other (health insurance) | B36: ='Staffing & Payroll'!C50+'Staffing & Payroll'!C51 | C36: ='Staffing & Payroll'!D50+'Staffing & Payroll'!D51 | D36: ='Staffing & Payroll'!E50+'Staffing & Payroll'!E51 | E36: ='Staffing & Payroll'!F50+'Staffing & Payroll'!F51 | F36: ='Staffing & Payroll'!G50+'Staffing & Payroll'!G51 | G36: ='Staffing & Payroll'!H50+'Staffing & Payroll'!H51 | H36: ='Staffing & Payroll'!I50+'Staffing & Payroll'!I51 | I36: ='Staffing & Payroll'!J50+'Staffing & Payroll'!J51 | ... M36: ='Staffing & Payroll'!N50+'Staffing & Payroll'!N51 | N36: =SUM('Staffing & Payroll'!O50:R50)+SUM('Staffing & Payroll'!O51:R51) | O36: =SUM('Staffing & Payroll'!S50:V50)+SUM('Staffing & Payroll'!S51:V51) | P36: =SUM(B36:M36)+N36+O36
A37: Total Payroll & Related | B37: =SUM(B28:B36) | C37: =SUM(C28:C36) | D37: =SUM(D28:D36) | E37: =SUM(E28:E36) | F37: =SUM(F28:F36) | G37: =SUM(G28:G36) | H37: =SUM(H28:H36) | I37: =SUM(I28:I36) | ... P37: =SUM(P28:P36)
A39: General & Administrative
A40: Bank / Payroll Fees | B40: =Inputs!$B$101 | C40: =Inputs!$B$101 | D40: =Inputs!$B$101 | E40: =Inputs!$B$101 | F40: =Inputs!$B$101 | G40: =Inputs!$B$101 | H40: =Inputs!$B$101 | I40: =Inputs!$B$101 | ... M40: =Inputs!$B$101 | N40: =Inputs!$B$101*12 | O40: =Inputs!$B$101*12 | P40: =SUM(B40:M40)+N40+O40
A41: Triple Net Rent | B41: =Inputs!$B$102 | C41: =Inputs!$B$102 | D41: =Inputs!$B$102 | E41: =Inputs!$B$102 | F41: =Inputs!$B$102 | G41: =Inputs!$B$102 | H41: =Inputs!$B$102 | I41: =Inputs!$B$102 | ... M41: =Inputs!$B$102 | N41: =Inputs!$B$102*12 | O41: =Inputs!$B$102*12 | P41: =SUM(B41:M41)+N41+O41
A42: Utilities | B42: =Inputs!$B$91 | C42: =Inputs!$B$91 | D42: =Inputs!$B$91 | E42: =Inputs!$B$91 | F42: =Inputs!$B$91 | G42: =Inputs!$B$91 | H42: =Inputs!$B$91 | I42: =Inputs!$B$91 | ... M42: =Inputs!$B$91 | N42: =Inputs!$B$91*12 | O42: =Inputs!$B$91*12 | P42: =SUM(B42:M42)+N42+O42
A43: Internet | B43: =Inputs!$B$92 | C43: =Inputs!$B$92 | D43: =Inputs!$B$92 | E43: =Inputs!$B$92 | F43: =Inputs!$B$92 | G43: =Inputs!$B$92 | H43: =Inputs!$B$92 | I43: =Inputs!$B$92 | ... M43: =Inputs!$B$92 | N43: =Inputs!$B$92*12 | O43: =Inputs!$B$92*12 | P43: =SUM(B43:M43)+N43+O43
A44: Telephone / Fax | B44: =Inputs!$B$93 | C44: =Inputs!$B$93 | D44: =Inputs!$B$93 | E44: =Inputs!$B$93 | F44: =Inputs!$B$93 | G44: =Inputs!$B$93 | H44: =Inputs!$B$93 | I44: =Inputs!$B$93 | ... M44: =Inputs!$B$93 | N44: =Inputs!$B$93*12 | O44: =Inputs!$B$93*12 | P44: =SUM(B44:M44)+N44+O44
A45: After Hours Messaging (BVTM) | B45: =Inputs!$B$94 | C45: =Inputs!$B$94 | D45: =Inputs!$B$94 | E45: =Inputs!$B$94 | F45: =Inputs!$B$94 | G45: =Inputs!$B$94 | H45: =Inputs!$B$94 | I45: =Inputs!$B$94 | ... M45: =Inputs!$B$94 | N45: =Inputs!$B$94*12 | O45: =Inputs!$B$94*12 | P45: =SUM(B45:M45)+N45+O45
A46: CFO / AP Support | B46: =0 | C46: =0 | D46: =0 | E46: =0 | F46: =0 | G46: =0 | H46: =0 | I46: =0 | ... O46: =0 | P46: =SUM(B46:M46)+N46+O46
A47: Support Services | B47: =0 | C47: =0 | D47: =0 | E47: =0 | F47: =0 | G47: =0 | H47: =0 | I47: =0 | ... O47: =0 | P47: =SUM(B47:M47)+N47+O47
A48: Messaging / CRG Signer | B48: =0 | C48: =0 | D48: =0 | E48: =0 | F48: =0 | G48: =0 | H48: =0 | I48: =0 | ... O48: =0 | P48: =SUM(B48:M48)+N48+O48
A49: NM Room & Board | B49: =0 | C49: =0 | D49: =0 | E49: =0 | F49: =0 | G49: =0 | H49: =0 | I49: =0 | ... O49: =0 | P49: =SUM(B49:M49)+N49+O49
A50: Corporate Labor | B50: =0 | C50: =0 | D50: =0 | E50: =0 | F50: =0 | G50: =0 | H50: =0 | I50: =0 | ... O50: =0 | P50: =SUM(B50:M50)+N50+O50
A51: Marketing | B51: =Inputs!$B$103 | C51: =Inputs!$B$103 | D51: =Inputs!$B$103 | E51: =Inputs!$B$103 | F51: =Inputs!$B$103 | G51: =Inputs!$B$103 | H51: =Inputs!$B$103 | I51: =Inputs!$B$103 | ... M51: =Inputs!$B$103 | N51: =Inputs!$B$103*12 | O51: =Inputs!$B$103*12 | P51: =SUM(B51:M51)+N51+O51
A52: Outsourced Billing Fee (1.5%) | B52: ='Revenue Model'!C14*Inputs!$B$106 | C52: ='Revenue Model'!D14*Inputs!$B$106 | D52: ='Revenue Model'!E14*Inputs!$B$106 | E52: ='Revenue Model'!F14*Inputs!$B$106 | F52: ='Revenue Model'!G14*Inputs!$B$106 | G52: ='Revenue Model'!H14*Inputs!$B$106 | H52: ='Revenue Model'!I14*Inputs!$B$106 | I52: ='Revenue Model'!J14*Inputs!$B$106 | ... M52: ='Revenue Model'!N14*Inputs!$B$106 | N52: =SUM('Revenue Model'!O14:R14)*Inputs!$B$106 | O52: =SUM('Revenue Model'!S14:V14)*Inputs!$B$106 | P52: =SUM(B52:M52)+N52+O52
A53: EMR System | B53: =Inputs!$B$95 | C53: =Inputs!$B$95 | D53: =Inputs!$B$95 | E53: =Inputs!$B$95 | F53: =Inputs!$B$95 | G53: =Inputs!$B$95 | H53: =Inputs!$B$95 | I53: =Inputs!$B$95 | ... M53: =Inputs!$B$95 | N53: =Inputs!$B$95*12 | O53: =Inputs!$B$95*12 | P53: =SUM(B53:M53)+N53+O53
A54: Other EMR | B54: =0 | C54: =0 | D54: =0 | E54: =0 | F54: =0 | G54: =0 | H54: =0 | I54: =0 | ... O54: =0 | P54: =SUM(B54:M54)+N54+O54
A55: PCR (CPM) | B55: =Inputs!$B$96 | C55: =Inputs!$B$96 | D55: =Inputs!$B$96 | E55: =Inputs!$B$96 | F55: =Inputs!$B$96 | G55: =Inputs!$B$96 | H55: =Inputs!$B$96 | I55: =Inputs!$B$96 | ... M55: =Inputs!$B$96 | N55: =Inputs!$B$96*12 | O55: =Inputs!$B$96*12 | P55: =SUM(B55:M55)+N55+O55
A56: Ancillary | B56: =0 | C56: =0 | D56: =0 | E56: =0 | F56: =0 | G56: =0 | H56: =0 | I56: =0 | ... O56: =0 | P56: =SUM(B56:M56)+N56+O56
A57: Liability Insurance (D&O) | B57: =Inputs!$B$98 | C57: =Inputs!$B$98 | D57: =Inputs!$B$98 | E57: =Inputs!$B$98 | F57: =Inputs!$B$98 | G57: =Inputs!$B$98 | H57: =Inputs!$B$98 | I57: =Inputs!$B$98 | ... M57: =Inputs!$B$98 | N57: =Inputs!$B$98*12 | O57: =Inputs!$B$98*12 | P57: =SUM(B57:M57)+N57+O57
A58: QR Payment Fee (0.75%) | B58: ='Revenue Model'!C14*Inputs!$B$107 | C58: ='Revenue Model'!D14*Inputs!$B$107 | D58: ='Revenue Model'!E14*Inputs!$B$107 | E58: ='Revenue Model'!F14*Inputs!$B$107 | F58: ='Revenue Model'!G14*Inputs!$B$107 | G58: ='Revenue Model'!H14*Inputs!$B$107 | H58: ='Revenue Model'!I14*Inputs!$B$107 | I58: ='Revenue Model'!J14*Inputs!$B$107 | ... M58: ='Revenue Model'!N14*Inputs!$B$107 | N58: =SUM('Revenue Model'!O14:R14)*Inputs!$B$107 | O58: =SUM('Revenue Model'!S14:V14)*Inputs!$B$107 | P58: =SUM(B58:M58)+N58+O58
A59: Training / CEUs | B59: =Inputs!$B$99 | C59: =Inputs!$B$99 | D59: =Inputs!$B$99 | E59: =Inputs!$B$99 | F59: =Inputs!$B$99 | G59: =Inputs!$B$99 | H59: =Inputs!$B$99 | I59: =Inputs!$B$99 | ... M59: =Inputs!$B$99 | N59: =Inputs!$B$99*12 | O59: =Inputs!$B$99*12 | P59: =SUM(B59:M59)+N59+O59
A60: Credit Card Fees | B60: =Inputs!$B$97 | C60: =Inputs!$B$97 | D60: =Inputs!$B$97 | E60: =Inputs!$B$97 | F60: =Inputs!$B$97 | G60: =Inputs!$B$97 | H60: =Inputs!$B$97 | I60: =Inputs!$B$97 | ... M60: =Inputs!$B$97 | N60: =Inputs!$B$97*12 | O60: =Inputs!$B$97*12 | P60: =SUM(B60:M60)+N60+O60
A61: Other (QPf) | B61: =0 | C61: =0 | D61: =0 | E61: =0 | F61: =0 | G61: =0 | H61: =0 | I61: =0 | ... O61: =0 | P61: =SUM(B61:M61)+N61+O61
A62: Other (Client) | B62: =Inputs!$B$100 | C62: =Inputs!$B$100 | D62: =Inputs!$B$100 | E62: =Inputs!$B$100 | F62: =Inputs!$B$100 | G62: =Inputs!$B$100 | H62: =Inputs!$B$100 | I62: =Inputs!$B$100 | ... M62: =Inputs!$B$100 | N62: =Inputs!$B$100*12 | O62: =Inputs!$B$100*12 | P62: =SUM(B62:M62)+N62+O62
A63: Total General & Administrative | B63: =SUM(B40:B62) | C63: =SUM(C40:C62) | D63: =SUM(D40:D62) | E63: =SUM(E40:E62) | F63: =SUM(F40:F62) | G63: =SUM(G40:G62) | H63: =SUM(H40:H62) | I63: =SUM(I40:I62) | ... P63: =SUM(P40:P62)
A65: Total Operating Expenses | B65: =B37+B63 | C65: =C37+C63 | D65: =D37+D63 | E65: =E37+E63 | F65: =F37+F63 | G65: =G37+G63 | H65: =H37+H63 | I65: =I37+I63 | ... P65: =P37+P63
A67: Net Income | B67: =B24-B65 | C67: =C24-C65 | D67: =D24-D65 | E67: =E24-E65 | F67: =F24-F65 | G67: =G24-G65 | H67: =H24-H65 | I67: =I24-I65 | ... P67: =P24-P65
A69: Net Margin % | B69: =IF(B12=0,0,B67/B12) | C69: =IF(C12=0,0,C67/C12) | D69: =IF(D12=0,0,D67/D12) | E69: =IF(E12=0,0,E67/E12) | F69: =IF(F12=0,0,F67/F12) | G69: =IF(G12=0,0,G67/G12) | H69: =IF(H12=0,0,H67/H12) | I69: =IF(I12=0,0,I67/I12) | ... P69: =IF(P12=0,0,P67/P12)
A71: Cash-basis operating P&L (QuickBooks layout): all payroll is in Operating Expenses, Cost of Services holds patient supplies only. "Net Income" here = operating result and ties to the engine's EBITDA; interest, D&A and tax are below EBITDA on the Operating Budget / 3-statement tabs.

Sheet Debt Schedule
A1: AZALEA HOSPICE & PALLIATIVE CARE - Tyler, TX
A2: Debt Schedule - SBA 7(a) + Hickory license seller note | Combined DSCR shown (target >= 1.25x)
A4: LOAN TERMS (from Inputs)
A5: SBA monthly payment (PMT) | B5: =PMT(Inputs!$B$111/12,Inputs!$B$112,-Inputs!$B$110)
A6: License note monthly payment (PMT) | B6: =PMT(Inputs!$B$121/12,Inputs!$B$122,-Inputs!$B$120)
A8: ($ per period) | C8: YEAR 1 - monthly | O8: YEAR 2 - quarterly | S8: YEAR 3 - quarterly
C9: M1 | D9: M2 | E9: M3 | F9: M4 | G9: M5 | H9: M6 | I9: M7 | J9: M8 | K9: M9 | L9: M10 | M9: M11 | N9: M12 | O9: Y2 Q1 | P9: Y2 Q2 | Q9: Y2 Q3 | R9: Y2 Q4 | S9: Y3 Q1 | T9: Y3 Q2 | U9: Y3 Q3 | V9: Y3 Q4
A10: SBA 7(a) LOAN
A11: Beginning balance | C11: =Inputs!$B$110 | D11: =C15 | E11: =D15 | F11: =E15 | G11: =F15 | H11: =G15 | I11: =H15 | J11: =I15 | K11: =J15 | ... V11: =U15
A12: Payment | C12: ='Debt Schedule'!$B$5*1 | D12: ='Debt Schedule'!$B$5*1 | E12: ='Debt Schedule'!$B$5*1 | F12: ='Debt Schedule'!$B$5*1 | G12: ='Debt Schedule'!$B$5*1 | H12: ='Debt Schedule'!$B$5*1 | I12: ='Debt Schedule'!$B$5*1 | J12: ='Debt Schedule'!$B$5*1 | ... N12: ='Debt Schedule'!$B$5*1 | O12: ='Debt Schedule'!$B$5*3 | P12: ='Debt Schedule'!$B$5*3 | Q12: ='Debt Schedule'!$B$5*3 | R12: ='Debt Schedule'!$B$5*3 | S12: ='Debt Schedule'!$B$5*3 | T12: ='Debt Schedule'!$B$5*3 | U12: ='Debt Schedule'!$B$5*3 | V12: ='Debt Schedule'!$B$5*3
A13: Interest | C13: =C11*Inputs!$B$111/12*1 | D13: =D11*Inputs!$B$111/12*1 | E13: =E11*Inputs!$B$111/12*1 | F13: =F11*Inputs!$B$111/12*1 | G13: =G11*Inputs!$B$111/12*1 | H13: =H11*Inputs!$B$111/12*1 | I13: =I11*Inputs!$B$111/12*1 | J13: =J11*Inputs!$B$111/12*1 | ... N13: =N11*Inputs!$B$111/12*1 | O13: =O11*Inputs!$B$111/12*3 | P13: =P11*Inputs!$B$111/12*3 | Q13: =Q11*Inputs!$B$111/12*3 | R13: =R11*Inputs!$B$111/12*3 | S13: =S11*Inputs!$B$111/12*3 | T13: =T11*Inputs!$B$111/12*3 | U13: =U11*Inputs!$B$111/12*3 | V13: =V11*Inputs!$B$111/12*3
A14: Principal | C14: =C12-C13 | D14: =D12-D13 | E14: =E12-E13 | F14: =F12-F13 | G14: =G12-G13 | H14: =H12-H13 | I14: =I12-I13 | J14: =J12-J13 | ... V14: =V12-V13
A15: Ending balance | C15: =C11-C14 | D15: =D11-D14 | E15: =E11-E14 | F15: =F11-F14 | G15: =G11-G14 | H15: =H11-H14 | I15: =I11-I14 | J15: =J11-J14 | ... V15: =V11-V14
A17: HICKORY LICENSE SELLER NOTE ($300K, 6%, 36 mo)
A18: Beginning balance | C18: =Inputs!$B$120 | D18: =C22 | E18: =D22 | F18: =E22 | G18: =F22 | H18: =G22 | I18: =H22 | J18: =I22 | K18: =J22 | ... V18: =U22
A19: Ending balance (closed-form) | C19: =MAX(0,C18*(1+Inputs!$B$121/12)^1-'Debt Schedule'!$B$6*((1+Inputs!$B$121/12)^1-1)/(Inputs!$B$121/12)) | D19: =MAX(0,D18*(1+Inputs!$B$121/12)^1-'Debt Schedule'!$B$6*((1+Inputs!$B$121/12)^1-1)/(Inputs!$B$121/12)) | E19: =MAX(0,E18*(1+Inputs!$B$121/12)^1-'Debt Schedule'!$B$6*((1+Inputs!$B$121/12)^1-1)/(Inputs!$B$121/12)) | F19: =MAX(0,F18*(1+Inputs!$B$121/12)^1-'Debt Schedule'!$B$6*((1+Inputs!$B$121/12)^1-1)/(Inputs!$B$121/12)) | G19: =MAX(0,G18*(1+Inputs!$B$121/12)^1-'Debt Schedule'!$B$6*((1+Inputs!$B$121/12)^1-1)/(Inputs!$B$121/12)) | H19: =MAX(0,H18*(1+Inputs!$B$121/12)^1-'Debt Schedule'!$B$6*((1+Inputs!$B$121/12)^1-1)/(Inputs!$B$121/12)) | I19: =MAX(0,I18*(1+Inputs!$B$121/12)^1-'Debt Schedule'!$B$6*((1+Inputs!$B$121/12)^1-1)/(Inputs!$B$121/12)) | J19: =MAX(0,J18*(1+Inputs!$B$121/12)^1-'Debt Schedule'!$B$6*((1+Inputs!$B$121/12)^1-1)/(Inputs!$B$121/12)) | ... N19: =MAX(0,N18*(1+Inputs!$B$121/12)^1-'Debt Schedule'!$B$6*((1+Inputs!$B$121/12)^1-1)/(Inputs!$B$121/12)) | O19: =MAX(0,O18*(1+Inputs!$B$121/12)^3-'Debt Schedule'!$B$6*((1+Inputs!$B$121/12)^3-1)/(Inputs!$B$121/12)) | P19: =MAX(0,P18*(1+Inputs!$B$121/12)^3-'Debt Schedule'!$B$6*((1+Inputs!$B$121/12)^3-1)/(Inputs!$B$121/12)) | Q19: =MAX(0,Q18*(1+Inputs!$B$121/12)^3-'Debt Schedule'!$B$6*((1+Inputs!$B$121/12)^3-1)/(Inputs!$B$121/12)) | R19: =MAX(0,R18*(1+Inputs!$B$121/12)^3-'Debt Schedule'!$B$6*((1+Inputs!$B$121/12)^3-1)/(Inputs!$B$121/12)) | S19: =MAX(0,S18*(1+Inputs!$B$121/12)^3-'Debt Schedule'!$B$6*((1+Inputs!$B$121/12)^3-1)/(Inputs!$B$121/12)) | T19: =MAX(0,T18*(1+Inputs!$B$121/12)^3-'Debt Schedule'!$B$6*((1+Inputs!$B$121/12)^3-1)/(Inputs!$B$121/12)) | U19: =MAX(0,U18*(1+Inputs!$B$121/12)^3-'Debt Schedule'!$B$6*((1+Inputs!$B$121/12)^3-1)/(Inputs!$B$121/12)) | V19: =MAX(0,V18*(1+Inputs!$B$121/12)^3-'Debt Schedule'!$B$6*((1+Inputs!$B$121/12)^3-1)/(Inputs!$B$121/12))
A20: Principal | C20: =C18-C19 | D20: =D18-D19 | E20: =E18-E19 | F20: =F18-F19 | G20: =G18-G19 | H20: =H18-H19 | I20: =I18-I19 | J20: =J18-J19 | ... V20: =V18-V19
A21: Interest | C21: =MAX(0,IF(C18=0,0,'Debt Schedule'!$B$6*1-C20)) | D21: =MAX(0,IF(D18=0,0,'Debt Schedule'!$B$6*1-D20)) | E21: =MAX(0,IF(E18=0,0,'Debt Schedule'!$B$6*1-E20)) | F21: =MAX(0,IF(F18=0,0,'Debt Schedule'!$B$6*1-F20)) | G21: =MAX(0,IF(G18=0,0,'Debt Schedule'!$B$6*1-G20)) | H21: =MAX(0,IF(H18=0,0,'Debt Schedule'!$B$6*1-H20)) | I21: =MAX(0,IF(I18=0,0,'Debt Schedule'!$B$6*1-I20)) | J21: =MAX(0,IF(J18=0,0,'Debt Schedule'!$B$6*1-J20)) | ... N21: =MAX(0,IF(N18=0,0,'Debt Schedule'!$B$6*1-N20)) | O21: =MAX(0,IF(O18=0,0,'Debt Schedule'!$B$6*3-O20)) | P21: =MAX(0,IF(P18=0,0,'Debt Schedule'!$B$6*3-P20)) | Q21: =MAX(0,IF(Q18=0,0,'Debt Schedule'!$B$6*3-Q20)) | R21: =MAX(0,IF(R18=0,0,'Debt Schedule'!$B$6*3-R20)) | S21: =MAX(0,IF(S18=0,0,'Debt Schedule'!$B$6*3-S20)) | T21: =MAX(0,IF(T18=0,0,'Debt Schedule'!$B$6*3-T20)) | U21: =MAX(0,IF(U18=0,0,'Debt Schedule'!$B$6*3-U20)) | V21: =MAX(0,IF(V18=0,0,'Debt Schedule'!$B$6*3-V20))
A22: Ending balance | C22: =C19 | D22: =D19 | E22: =E19 | F22: =F19 | G22: =G19 | H22: =H19 | I22: =I19 | J22: =J19 | ... V22: =V19
A24: COMBINED DEBT SERVICE & COVERAGE
A25: Total interest | C25: =C13+C21 | D25: =D13+D21 | E25: =E13+E21 | F25: =F13+F21 | G25: =G13+G21 | H25: =H13+H21 | I25: =I13+I21 | J25: =J13+J21 | ... V25: =V13+V21
A26: Total principal | C26: =C14+C20 | D26: =D14+D20 | E26: =E14+E20 | F26: =F14+F20 | G26: =G14+G20 | H26: =H14+H20 | I26: =I14+I20 | J26: =J14+J20 | ... V26: =V14+V20
A27: TOTAL DEBT SERVICE (P+I, combined) | C27: =C25+C26 | D27: =D25+D26 | E27: =E25+E26 | F27: =F25+F26 | G27: =G25+G26 | H27: =H25+H26 | I27: =I25+I26 | J27: =J25+J26 | ... V27: =V25+V26
A28: EBITDA (link) | C28: ='Operating Budget'!C24 | D28: ='Operating Budget'!D24 | E28: ='Operating Budget'!E24 | F28: ='Operating Budget'!F24 | G28: ='Operating Budget'!G24 | H28: ='Operating Budget'!H24 | I28: ='Operating Budget'!I24 | J28: ='Operating Budget'!J24 | ... V28: ='Operating Budget'!V24
A29: COMBINED DSCR (period) | C29: =IF(C27=0,0,C28/C27) | D29: =IF(D27=0,0,D28/D27) | E29: =IF(E27=0,0,E28/E27) | F29: =IF(F27=0,0,F28/F27) | G29: =IF(G27=0,0,G28/G27) | H29: =IF(H27=0,0,H28/H27) | I29: =IF(I27=0,0,I28/I27) | J29: =IF(J27=0,0,J28/J27) | ... V29: =IF(V27=0,0,V28/V27)

Sheet Cash Flow & BS
A1: AZALEA HOSPICE & PALLIATIVE CARE - Tyler, TX
A2: Cash Flow (indirect) & Balance Sheet - BS balances through real AR/AP/LOC, never a plug
A4: ($ per period) | B4: Opening | C4: YEAR 1 - monthly | O4: YEAR 2 - quarterly | S4: YEAR 3 - quarterly
C5: M1 | D5: M2 | E5: M3 | F5: M4 | G5: M5 | H5: M6 | I5: M7 | J5: M8 | K5: M9 | L5: M10 | M5: M11 | N5: M12 | O5: Y2 Q1 | P5: Y2 Q2 | Q5: Y2 Q3 | R5: Y2 Q4 | S5: Y3 Q1 | T5: Y3 Q2 | U5: Y3 Q3 | V5: Y3 Q4
A6: CASH FLOW (indirect method)
A7: Net income | C7: ='Operating Budget'!C34 | D7: ='Operating Budget'!D34 | E7: ='Operating Budget'!E34 | F7: ='Operating Budget'!F34 | G7: ='Operating Budget'!G34 | H7: ='Operating Budget'!H34 | I7: ='Operating Budget'!I34 | J7: ='Operating Budget'!J34 | ... V7: ='Operating Budget'!V34
A8: + Depreciation & amortization | C8: ='Operating Budget'!C28 | D8: ='Operating Budget'!D28 | E8: ='Operating Budget'!E28 | F8: ='Operating Budget'!F28 | G8: ='Operating Budget'!G28 | H8: ='Operating Budget'!H28 | I8: ='Operating Budget'!I28 | J8: ='Operating Budget'!J28 | ... V8: ='Operating Budget'!V28
A9: Accounts receivable (balance) | B9: =0 | C9: ='Revenue Model'!C17*Inputs!$B$134/'Revenue Model'!C11 | D9: ='Revenue Model'!D17*Inputs!$B$134/'Revenue Model'!D11 | E9: ='Revenue Model'!E17*Inputs!$B$134/'Revenue Model'!E11 | F9: ='Revenue Model'!F17*Inputs!$B$134/'Revenue Model'!F11 | G9: ='Revenue Model'!G17*Inputs!$B$134/'Revenue Model'!G11 | H9: ='Revenue Model'!H17*Inputs!$B$134/'Revenue Model'!H11 | I9: ='Revenue Model'!I17*Inputs!$B$134/'Revenue Model'!I11 | J9: ='Revenue Model'!J17*Inputs!$B$134/'Revenue Model'!J11 | ... V9: ='Revenue Model'!V17*Inputs!$B$134/'Revenue Model'!V11
A10: Accounts payable (balance) | B10: =0 | C10: =('Operating Budget'!C20+'Operating Budget'!C22+'Operating Budget'!C13)*Inputs!$B$135/'Revenue Model'!C11 | D10: =('Operating Budget'!D20+'Operating Budget'!D22+'Operating Budget'!D13)*Inputs!$B$135/'Revenue Model'!D11 | E10: =('Operating Budget'!E20+'Operating Budget'!E22+'Operating Budget'!E13)*Inputs!$B$135/'Revenue Model'!E11 | F10: =('Operating Budget'!F20+'Operating Budget'!F22+'Operating Budget'!F13)*Inputs!$B$135/'Revenue Model'!F11 | G10: =('Operating Budget'!G20+'Operating Budget'!G22+'Operating Budget'!G13)*Inputs!$B$135/'Revenue Model'!G11 | H10: =('Operating Budget'!H20+'Operating Budget'!H22+'Operating Budget'!H13)*Inputs!$B$135/'Revenue Model'!H11 | I10: =('Operating Budget'!I20+'Operating Budget'!I22+'Operating Budget'!I13)*Inputs!$B$135/'Revenue Model'!I11 | J10: =('Operating Budget'!J20+'Operating Budget'!J22+'Operating Budget'!J13)*Inputs!$B$135/'Revenue Model'!J11 | ... V10: =('Operating Budget'!V20+'Operating Budget'!V22+'Operating Budget'!V13)*Inputs!$B$135/'Revenue Model'!V11
A11: Less: change in accounts receivable | C11: =-(C9-B9) | D11: =-(D9-C9) | E11: =-(E9-D9) | F11: =-(F9-E9) | G11: =-(G9-F9) | H11: =-(H9-G9) | I11: =-(I9-H9) | J11: =-(J9-I9) | ... V11: =-(V9-U9)
A12: Plus: change in accounts payable | C12: =C10-B10 | D12: =D10-C10 | E12: =E10-D10 | F12: =F10-E10 | G12: =G10-F10 | H12: =H10-G10 | I12: =I10-H10 | J12: =J10-I10 | ... V12: =V10-U10
A13: Cash flow from operations | C13: =C7+C8+C11+C12 | D13: =D7+D8+D11+D12 | E13: =E7+E8+E11+E12 | F13: =F7+F8+F11+F12 | G13: =G7+G8+G11+G12 | H13: =H7+H8+H11+H12 | I13: =I7+I8+I11+I12 | J13: =J7+J8+J11+J12 | ... V13: =V7+V8+V11+V12
A14: - SBA principal repayment | C14: =-'Debt Schedule'!C14 | D14: =-'Debt Schedule'!D14 | E14: =-'Debt Schedule'!E14 | F14: =-'Debt Schedule'!F14 | G14: =-'Debt Schedule'!G14 | H14: =-'Debt Schedule'!H14 | I14: =-'Debt Schedule'!I14 | J14: =-'Debt Schedule'!J14 | ... V14: =-'Debt Schedule'!V14
A15: - Hickory license note principal | C15: =-'Debt Schedule'!C20 | D15: =-'Debt Schedule'!D20 | E15: =-'Debt Schedule'!E20 | F15: =-'Debt Schedule'!F20 | G15: =-'Debt Schedule'!G20 | H15: =-'Debt Schedule'!H20 | I15: =-'Debt Schedule'!I20 | J15: =-'Debt Schedule'!J20 | ... V15: =-'Debt Schedule'!V20
A16: Working-capital line interest | B16: =0 | C16: =B20*Inputs!$B$115*1/12 | D16: =C20*Inputs!$B$115*1/12 | E16: =D20*Inputs!$B$115*1/12 | F16: =E20*Inputs!$B$115*1/12 | G16: =F20*Inputs!$B$115*1/12 | H16: =G20*Inputs!$B$115*1/12 | I16: =H20*Inputs!$B$115*1/12 | J16: =I20*Inputs!$B$115*1/12 | ... N16: =M20*Inputs!$B$115*1/12 | O16: =N20*Inputs!$B$115*3/12 | P16: =O20*Inputs!$B$115*3/12 | Q16: =P20*Inputs!$B$115*3/12 | R16: =Q20*Inputs!$B$115*3/12 | S16: =R20*Inputs!$B$115*3/12 | T16: =S20*Inputs!$B$115*3/12 | U16: =T20*Inputs!$B$115*3/12 | V16: =U20*Inputs!$B$115*3/12
A17: Beginning cash | B17: =0 | C17: =Inputs!$B$139 | D17: =C21 | E17: =D21 | F17: =E21 | G17: =F21 | H17: =G21 | I17: =H21 | J17: =I21 | K17: =J21 | ... V17: =U21
A18: Cash before LOC sweep | C18: =C17+C13+C14+C15 | D18: =D17+D13+D14+D15 | E18: =E17+E13+E14+E15 | F18: =F17+F13+F14+F15 | G18: =G17+G13+G14+G15 | H18: =H17+H13+H14+H15 | I18: =I17+I13+I14+I15 | J18: =J17+J13+J14+J15 | ... V18: =V17+V13+V14+V15
A19: LOC draw / (repay) | C19: =IF(C18<Inputs!$B$116,Inputs!$B$116-C18,-MIN(B20,MAX(0,C18-Inputs!$B$116))) | D19: =IF(D18<Inputs!$B$116,Inputs!$B$116-D18,-MIN(C20,MAX(0,D18-Inputs!$B$116))) | E19: =IF(E18<Inputs!$B$116,Inputs!$B$116-E18,-MIN(D20,MAX(0,E18-Inputs!$B$116))) | F19: =IF(F18<Inputs!$B$116,Inputs!$B$116-F18,-MIN(E20,MAX(0,F18-Inputs!$B$116))) | G19: =IF(G18<Inputs!$B$116,Inputs!$B$116-G18,-MIN(F20,MAX(0,G18-Inputs!$B$116))) | H19: =IF(H18<Inputs!$B$116,Inputs!$B$116-H18,-MIN(G20,MAX(0,H18-Inputs!$B$116))) | I19: =IF(I18<Inputs!$B$116,Inputs!$B$116-I18,-MIN(H20,MAX(0,I18-Inputs!$B$116))) | J19: =IF(J18<Inputs!$B$116,Inputs!$B$116-J18,-MIN(I20,MAX(0,J18-Inputs!$B$116))) | ... V19: =IF(V18<Inputs!$B$116,Inputs!$B$116-V18,-MIN(U20,MAX(0,V18-Inputs!$B$116)))
A20: Working-capital line balance | B20: =0 | C20: =B20+C19 | D20: =C20+D19 | E20: =D20+E19 | F20: =E20+F19 | G20: =F20+G19 | H20: =G20+H19 | I20: =H20+I19 | J20: =I20+J19 | ... V20: =U20+V19
A21: ENDING CASH | C21: =C18+C19 | D21: =D18+D19 | E21: =E18+E19 | F21: =F18+F19 | G21: =G18+G19 | H21: =H18+H19 | I21: =I18+I19 | J21: =J18+J19 | ... V21: =V18+V19
A23: BALANCE SHEET
A24: Cash | B24: =Inputs!$B$139 | C24: =C21 | D24: =D21 | E24: =E21 | F24: =F21 | G24: =G21 | H24: =H21 | I24: =I21 | J24: =J21 | ... V24: =V21
A25: Accounts receivable | B25: =0 | C25: =C9 | D25: =D9 | E25: =E9 | F25: =F9 | G25: =G9 | H25: =H9 | I25: =I9 | J25: =J9 | ... V25: =V9
A26: PP&E, net | B26: =Inputs!$B$117 | C26: =MAX(0,B26-Inputs!$B$117/Inputs!$B$118/12*1) | D26: =MAX(0,C26-Inputs!$B$117/Inputs!$B$118/12*1) | E26: =MAX(0,D26-Inputs!$B$117/Inputs!$B$118/12*1) | F26: =MAX(0,E26-Inputs!$B$117/Inputs!$B$118/12*1) | G26: =MAX(0,F26-Inputs!$B$117/Inputs!$B$118/12*1) | H26: =MAX(0,G26-Inputs!$B$117/Inputs!$B$118/12*1) | I26: =MAX(0,H26-Inputs!$B$117/Inputs!$B$118/12*1) | J26: =MAX(0,I26-Inputs!$B$117/Inputs!$B$118/12*1) | ... N26: =MAX(0,M26-Inputs!$B$117/Inputs!$B$118/12*1) | O26: =MAX(0,N26-Inputs!$B$117/Inputs!$B$118/12*3) | P26: =MAX(0,O26-Inputs!$B$117/Inputs!$B$118/12*3) | Q26: =MAX(0,P26-Inputs!$B$117/Inputs!$B$118/12*3) | R26: =MAX(0,Q26-Inputs!$B$117/Inputs!$B$118/12*3) | S26: =MAX(0,R26-Inputs!$B$117/Inputs!$B$118/12*3) | T26: =MAX(0,S26-Inputs!$B$117/Inputs!$B$118/12*3) | U26: =MAX(0,T26-Inputs!$B$117/Inputs!$B$118/12*3) | V26: =MAX(0,U26-Inputs!$B$117/Inputs!$B$118/12*3)
A27: Startup & organizational costs, net | B27: =Inputs!$B$138 | C27: =MAX(0,B27-Inputs!$B$138/Inputs!$B$118/12*1) | D27: =MAX(0,C27-Inputs!$B$138/Inputs!$B$118/12*1) | E27: =MAX(0,D27-Inputs!$B$138/Inputs!$B$118/12*1) | F27: =MAX(0,E27-Inputs!$B$138/Inputs!$B$118/12*1) | G27: =MAX(0,F27-Inputs!$B$138/Inputs!$B$118/12*1) | H27: =MAX(0,G27-Inputs!$B$138/Inputs!$B$118/12*1) | I27: =MAX(0,H27-Inputs!$B$138/Inputs!$B$118/12*1) | J27: =MAX(0,I27-Inputs!$B$138/Inputs!$B$118/12*1) | ... N27: =MAX(0,M27-Inputs!$B$138/Inputs!$B$118/12*1) | O27: =MAX(0,N27-Inputs!$B$138/Inputs!$B$118/12*3) | P27: =MAX(0,O27-Inputs!$B$138/Inputs!$B$118/12*3) | Q27: =MAX(0,P27-Inputs!$B$138/Inputs!$B$118/12*3) | R27: =MAX(0,Q27-Inputs!$B$138/Inputs!$B$118/12*3) | S27: =MAX(0,R27-Inputs!$B$138/Inputs!$B$118/12*3) | T27: =MAX(0,S27-Inputs!$B$138/Inputs!$B$118/12*3) | U27: =MAX(0,T27-Inputs!$B$138/Inputs!$B$118/12*3) | V27: =MAX(0,U27-Inputs!$B$138/Inputs!$B$118/12*3)
A28: Hickory Medicare license intangible, net | B28: =Inputs!$B$120 | C28: =MAX(0,B28-Inputs!$B$120/Inputs!$B$123/12*1) | D28: =MAX(0,C28-Inputs!$B$120/Inputs!$B$123/12*1) | E28: =MAX(0,D28-Inputs!$B$120/Inputs!$B$123/12*1) | F28: =MAX(0,E28-Inputs!$B$120/Inputs!$B$123/12*1) | G28: =MAX(0,F28-Inputs!$B$120/Inputs!$B$123/12*1) | H28: =MAX(0,G28-Inputs!$B$120/Inputs!$B$123/12*1) | I28: =MAX(0,H28-Inputs!$B$120/Inputs!$B$123/12*1) | J28: =MAX(0,I28-Inputs!$B$120/Inputs!$B$123/12*1) | ... N28: =MAX(0,M28-Inputs!$B$120/Inputs!$B$123/12*1) | O28: =MAX(0,N28-Inputs!$B$120/Inputs!$B$123/12*3) | P28: =MAX(0,O28-Inputs!$B$120/Inputs!$B$123/12*3) | Q28: =MAX(0,P28-Inputs!$B$120/Inputs!$B$123/12*3) | R28: =MAX(0,Q28-Inputs!$B$120/Inputs!$B$123/12*3) | S28: =MAX(0,R28-Inputs!$B$120/Inputs!$B$123/12*3) | T28: =MAX(0,S28-Inputs!$B$120/Inputs!$B$123/12*3) | U28: =MAX(0,T28-Inputs!$B$120/Inputs!$B$123/12*3) | V28: =MAX(0,U28-Inputs!$B$120/Inputs!$B$123/12*3)
A29: TOTAL ASSETS | B29: =B24+B25+B26+B27+B28 | C29: =C24+C25+C26+C27+C28 | D29: =D24+D25+D26+D27+D28 | E29: =E24+E25+E26+E27+E28 | F29: =F24+F25+F26+F27+F28 | G29: =G24+G25+G26+G27+G28 | H29: =H24+H25+H26+H27+H28 | I29: =I24+I25+I26+I27+I28 | ... V29: =V24+V25+V26+V27+V28
A31: Accounts payable | B31: =0 | C31: =C10 | D31: =D10 | E31: =E10 | F31: =F10 | G31: =G10 | H31: =H10 | I31: =I10 | J31: =J10 | ... V31: =V10
A32: Working-capital line | B32: =0 | C32: =C20 | D32: =D20 | E32: =E20 | F32: =F20 | G32: =G20 | H32: =H20 | I32: =I20 | J32: =J20 | ... V32: =V20
A33: SBA loan balance | B33: =Inputs!$B$110 | C33: ='Debt Schedule'!C15 | D33: ='Debt Schedule'!D15 | E33: ='Debt Schedule'!E15 | F33: ='Debt Schedule'!F15 | G33: ='Debt Schedule'!G15 | H33: ='Debt Schedule'!H15 | I33: ='Debt Schedule'!I15 | J33: ='Debt Schedule'!J15 | ... V33: ='Debt Schedule'!V15
A34: Hickory license note balance | B34: =Inputs!$B$120 | C34: ='Debt Schedule'!C22 | D34: ='Debt Schedule'!D22 | E34: ='Debt Schedule'!E22 | F34: ='Debt Schedule'!F22 | G34: ='Debt Schedule'!G22 | H34: ='Debt Schedule'!H22 | I34: ='Debt Schedule'!I22 | J34: ='Debt Schedule'!J22 | ... V34: ='Debt Schedule'!V22
A35: Paid-in equity | B35: =Inputs!$B$113 | C35: =Inputs!$B$113 | D35: =Inputs!$B$113 | E35: =Inputs!$B$113 | F35: =Inputs!$B$113 | G35: =Inputs!$B$113 | H35: =Inputs!$B$113 | I35: =Inputs!$B$113 | ... V35: =Inputs!$B$113
A36: Retained earnings | B36: =0 | C36: =B36+C7 | D36: =C36+D7 | E36: =D36+E7 | F36: =E36+F7 | G36: =F36+G7 | H36: =G36+H7 | I36: =H36+I7 | J36: =I36+J7 | ... V36: =U36+V7
A37: TOTAL LIABILITIES & EQUITY | B37: =B31+B32+B33+B34+B35+B36 | C37: =C31+C32+C33+C34+C35+C36 | D37: =D31+D32+D33+D34+D35+D36 | E37: =E31+E32+E33+E34+E35+E36 | F37: =F31+F32+F33+F34+F35+F36 | G37: =G31+G32+G33+G34+G35+G36 | H37: =H31+H32+H33+H34+H35+H36 | I37: =I31+I32+I33+I34+I35+I36 | ... V37: =V31+V32+V33+V34+V35+V36
A38: CHECK: Assets - (L+E) to 0 | B38: =B29-B37 | C38: =C29-C37 | D38: =D29-D37 | E38: =E29-E37 | F38: =F29-F37 | G38: =G29-G37 | H38: =H29-H37 | I38: =I29-I37 | ... V38: =V29-V37

Sheet Actuals vs Model
A1: AZALEA HOSPICE & PALLIATIVE CARE - Tyler, TX
A2: Paloma Tyler actuals (Mar-Jun 2025) vs Azalea model steady-state - proof the migrated panel is a proven, EBITDA-positive book
A4: Metric | B4: Mar 2025 | C4: Apr 2025 | D4: May 2025 | E4: Jun 2025 | F4: Apr-Jun avg | G4: Model (M3) | H4: Var %
A5: Gross revenue | B5: 138295.8 | C5: 116422.51 | D5: 127893.15 | E5: 119990.52 | F5: =AVERAGE(C5:E5) | G5: ='Revenue Model'!E14 | H5: =IF(F5=0,0,(G5-F5)/F5)
A6: Less: write-offs | B6: 179.62 | C6: 177.59 | D6: 172.62 | E6: 172.62 | F6: =AVERAGE(C6:E6)
A7: Less: sequestration | B7: 3073.97 | C7: 2549.02 | D7: 2739.17 | E7: 3248.08 | F7: =AVERAGE(C7:E7)
A8: NET REVENUE | B8: =B5-B6-B7 | C8: =C5-C6-C7 | D8: =D5-D6-D7 | E8: =E5-E6-E7 | F8: =AVERAGE(C8:E8) | G8: ='Revenue Model'!E17 | H8: =IF(F8=0,0,(G8-F8)/F8)
A9: Implied ADC (net ÷ $181 ÷ days) | B9: =B8/Inputs!$B$12/31 | C9: =C8/Inputs!$B$12/30 | D9: =D8/Inputs!$B$12/31 | E9: =E8/Inputs!$B$12/30 | F9: =AVERAGE(C9:E9) | G9: ='Revenue Model'!E10 | H9: =IF(F9=0,0,(G9-F9)/F9)
A11: PATIENT-RELATED COGS (monthly $)
A12: Pharmacy | B12: 2001.11 | C12: 2149.05 | D12: 2293 | E12: 2293 | F12: =AVERAGE(C12:E12) | G12: ='Revenue Model'!E12*Inputs!$B$88 | H12: =IF(F12=0,0,(G12-F12)/F12)
A13: Medical supplies | B13: 1846.79 | C13: 1671.97 | D13: 3650 | E13: 3650 | F13: =AVERAGE(C13:E13) | G13: ='Revenue Model'!E12*Inputs!$B$86 | H13: =IF(F13=0,0,(G13-F13)/F13)
A14: DME | B14: 1200.91 | C14: 1200 | D14: 1200 | E14: 1200 | F14: =AVERAGE(C14:E14) | G14: ='Revenue Model'!E12*Inputs!$B$87 | H14: =IF(F14=0,0,(G14-F14)/F14)
A16: PAYROLL (semi-monthly actual)
A17: Payroll - 1st half | B17: 20727.47 | C17: 22921.54 | D17: 22117.27 | E17: 31000 | F17: =AVERAGE(C17:E17)
A18: Payroll - 2nd half | B18: 41512.9 | C18: 22765.1 | D18: 21499.29 | E18: 27000 | F18: =AVERAGE(C18:E18)
A19: Total monthly payroll (actual) | B19: =B17+B18 | C19: =C17+C18 | D19: =D17+D18 | E19: =E17+E18 | F19: =AVERAGE(C19:E19) | G19: ='Staffing & Payroll'!E53+'Staffing & Payroll'!E54
A21: Model steady-state (M3) reconciles to Paloma's proven Apr-Jun book: ~$118K net / ~22 ADC. Payroll differs by design - Azalea's staggered W-2 roster + benefits vs Paloma's blended run.
