Workbook

Sheet Assumptions
A1: AZALEA HOSPICE - REFUGE OPERATING MODEL
A2: Assumptions - ALL editable cells are yellow/blue. Everything downstream is formulas.
A4: A. RATES & PAYER MIX
A5: Medicare blended NET rate ($/patient-day) | B5: 181
A6: Medicaid blended NET rate ($/patient-day) | B6: 155
A7: Medicare share of patient days | B7: 0.95
A8: Rate escalation (annual, yrs 2-3) | B8: 0.025
A9: Average days per month | B9: 30.4
A11: B. CENSUS ENGINE (admissions are the operating lever - edit rows on Census tab)
A12: Average length of stay (days) | B12: 82
A13: Deaths as share of separations | B13: 0.55
A14: SCENARIO: census capture (1.00 = plan) | B14: 1
A16: C. BILLING & COLLECTIONS
A17: Days lost per late NOE (per affected admit) | B17: 5
A18: Late-NOE rate (share of admits) | B18: 0.02
A19: CHOW payment hold (months; 0/1/2) | B19: 1 | D19: MAC hold on first claims after ownership change
A20: Base collection lag (months) | B20: 1
A22: D. PAYROLL & BENEFITS (per-employee register on Payroll tab)
A23: Payroll burden (taxes/WC) on W-2 + PRN | B23: 0.1827
A24: Health insurance ($/covered head/mo) | B24: 550
A25: Health waiting period (months) | B25: 3
A26: SCENARIO: payroll adjustment (+/- %) | B26: 0
A27: Salary escalation (annual, yrs 2-3) | B27: 0.03
A28: Owner salary deferral % (0 = off; 0.40 = lever on) | B28: 0
A29: Deferral window ends (month #) | B29: 6
A30: Medical director ($/mo, contracted) | B30: 4000
A31: 2nd medical director ($/mo) | B31: 5000
A32: 2nd med director start month | B32: 18
A33: Bookkeeping/admin support (annual) | B33: 34000
A35: E. PRN PER-VISIT ROSTER (census-driven)
A36: Role | B36: Visits/pt/mo | C36: $/visit
A37: PRN On-Call LVN (Kendricks-Tuck, Foster) | B37: 0.6 | C37: 100
A38: PRN Chaplain (Ector, Johnson) | B38: 0.75 | C38: 75
A39: PRN Social Worker (Sanders) | B39: 1 | C39: 75
A40: PRN Nurse Practitioner (Rogers) | B40: 0.15 | C40: 200
A41: PRN CNA / per-visit (Henson, Mills) | B41: 0.5 | C41: 21
A43: F. PATIENT COSTS & NEW (BLIND-SPOT) LINES
A44: Patient costs $/patient-day (pharmacy+supplies+DME) | B44: 8.99 | D44: paid net-30 (following month)
A45: Mileage $/ADC/month | B45: 136.36 | D45: ~$3,000/mo at 22 ADC; paid following month
A46: Billing + QR fees (% of net revenue) | B46: 0.023
A47: Cap-liability reserve (% of Medicare revenue, accrual) | B47: 0.02
A49: G. G&A BILL-TIMING CALENDAR
A50: Line | B50: $/period | C50: Freq (mo) | D50: Pay day
A51: Facility rent | B51: 2000 | C51: 1 | D51: 1
A52: Utilities | B52: 293 | C52: 1 | D52: 15
A53: Internet | B53: 779 | C53: 1 | D53: 15
A54: Telephone / fax | B54: 403 | C54: 1 | D54: 15
A55: After-hours messaging | B55: 48 | C55: 1 | D55: 15
A56: EMR system | B56: 1281 | C56: 1 | D56: 1
A57: PCR (CPM) | B57: 1001 | C57: 1 | D57: 15
A58: Training / CEUs | B58: 100 | C58: 1 | D58: 15
A59: Other (client) | B59: 1050 | C59: 1 | D59: 15
A60: Bank / payroll fees | B60: 1750 | C60: 1 | D60: 15
A61: Marketing / patient acquisition | B61: 3000 | C61: 1 | D61: 1
A62: PL/GL insurance (corrected) | B62: 1200 | C62: 3 | D62: 1
... A64: Bereavement program | B64: 300 | C64: 1 | D64: 15
A66: H. DEAL & DEBT (base = accepted seller terms; toggles below)
A67: Purchase price | B67: 500000
A68: Down payment at closing (Jul) | B68: 125000
A69: Seller monthly payment | B69: 25000
A70: First seller payment (month #) | B70: 3 | D70: 3 = September
A71: Last seller payment (month #) | B71: 6 | D71: 6 = December
A72: Seller note rate (simple, annual) | B72: 0.06
A73: Balloon month (7 = January, per 36-month rule) | B73: 7
A74: January balloon refinance rate (APR) | B74: 0.09 | D74: personal refi that funds the balloon when the $500K refi toggle is OFF
A75: January balloon refinance term (months) | B75: 120
A76: REFI TOGGLE (1 = refinance full $500K) | B76: 0
A77: Refi funding month (3 = September) | B77: 3
A78: Refi amount | B78: 500000
A79: Refi rate (APR) | B79: 0.06
A80: Refi term (months) | B80: 36
A81: SBA TOGGLE (1 = SBA loan funds) | B81: 0
A82: SBA funding month | B82: 3
A83: SBA amount | B83: 450000
A84: SBA rate (APR) | B84: 0.105
A85: SBA term (months) | B85: 180
A87: I. OPENING & OTHER
A88: Opening cash (equity on deposit) | B88: 250000
A89: Minimum-cash floor (flag threshold) | B89: 25000
A90: License intangible amortization (years) | B90: 15
A91: TX franchise/margin tax (% of revenue if profitable) | B91: 0.00375

Sheet Census
A1: AZALEA HOSPICE - REFUGE OPERATING MODEL
A2: Census engine - admissions are BLUE inputs; flows follow ALOS. Weekly (13) then monthly (36).
A4: WEEKLY - first 13 weeks (Jul-Sep 2026)
C5: W1 | D5: W2 | E5: W3 | F5: W4 | G5: W5 | H5: W6 | I5: W7 | J5: W8 | K5: W9 | L5: W10 | M5: W11 | N5: W12 | O5: W13
A6: Admissions (per week) [INPUT] | C6: 12 | D6: 8.02 | E6: 5.62 | F6: 4.26 | G6: 2.76 | H6: 2.61 | I6: 2.65 | J6: 2.68 | K6: 2.61 | L6: 3.04 | M6: 3 | N6: 3.05 | O6: 3.1
A7: Separations (census x 7/ALOS) | C7: =0*7/'Assumptions'!$B$12 | D7: =C9*7/'Assumptions'!$B$12 | E7: =D9*7/'Assumptions'!$B$12 | F7: =E9*7/'Assumptions'!$B$12 | G7: =F9*7/'Assumptions'!$B$12 | H7: =G9*7/'Assumptions'!$B$12 | I7: =H9*7/'Assumptions'!$B$12 | J7: =I9*7/'Assumptions'!$B$12 | K7: =J9*7/'Assumptions'!$B$12 | ... O7: =N9*7/'Assumptions'!$B$12
A8: of which deaths | C8: =C7*'Assumptions'!$B$13 | D8: =D7*'Assumptions'!$B$13 | E8: =E7*'Assumptions'!$B$13 | F8: =F7*'Assumptions'!$B$13 | G8: =G7*'Assumptions'!$B$13 | H8: =H7*'Assumptions'!$B$13 | I8: =I7*'Assumptions'!$B$13 | J8: =J7*'Assumptions'!$B$13 | ... O8: =O7*'Assumptions'!$B$13
A9: End-of-week census | C9: =0+C6-C7 | D9: =C9+D6-D7 | E9: =D9+E6-E7 | F9: =E9+F6-F7 | G9: =F9+G6-G7 | H9: =G9+H6-H7 | I9: =H9+I6-I7 | J9: =I9+J6-J7 | K9: =J9+K6-K7 | ... O9: =N9+O6-O7
A10: Average census (week) | C10: =(0+C9)/2*'Assumptions'!$B$14 | D10: =(C9+D9)/2*'Assumptions'!$B$14 | E10: =(D9+E9)/2*'Assumptions'!$B$14 | F10: =(E9+F9)/2*'Assumptions'!$B$14 | G10: =(F9+G9)/2*'Assumptions'!$B$14 | H10: =(G9+H9)/2*'Assumptions'!$B$14 | I10: =(H9+I9)/2*'Assumptions'!$B$14 | J10: =(I9+J9)/2*'Assumptions'!$B$14 | K10: =(J9+K9)/2*'Assumptions'!$B$14 | ... O10: =(N9+O9)/2*'Assumptions'!$B$14
A11: Patient days (week) | C11: =C10*7 | D11: =D10*7 | E11: =E10*7 | F11: =F10*7 | G11: =G10*7 | H11: =H10*7 | I11: =I10*7 | J11: =J10*7 | ... O11: =O10*7
A13: MONTHLY - 36 months (M1-M3 tie to the weekly engine)
A14: Month # | C14: 1 | D14: 2 | E14: 3 | F14: 4 | G14: 5 | H14: 6 | I14: 7 | J14: 8 | K14: 9 | L14: 10 | M14: 11 | N14: 12 | O14: 13 | P14: 14 | Q14: 15 | R14: 16 | S14: 17 | T14: 18 | U14: 19 | V14: 20 | W14: 21 | X14: 22 | Y14: 23 | Z14: 24 | AA14: 25 | AB14: 26 | AC14: 27 | AD14: 28 | AE14: 29 | AF14: 30 | AG14: 31 | AH14: 32 | AI14: 33 | AJ14: 34 | AK14: 35 | AL14: 36
C15: Jul-26 | D15: Aug-26 | E15: Sep-26 | F15: Oct-26 | G15: Nov-26 | H15: Dec-26 | I15: Jan-27 | J15: Feb-27 | K15: Mar-27 | L15: Apr-27 | M15: May-27 | N15: Jun-27 | O15: Jul-27 | P15: Aug-27 | Q15: Sep-27 | R15: Oct-27 | S15: Nov-27 | T15: Dec-27 | U15: Jan-28 | V15: Feb-28 | W15: Mar-28 | X15: Apr-28 | Y15: May-28 | Z15: Jun-28 | AA15: Jul-28 | AB15: Aug-28 | AC15: Sep-28 | AD15: Oct-28 | AE15: Nov-28 | AF15: Dec-28 | AG15: Jan-29 | AH15: Feb-29 | AI15: Mar-29 | AJ15: Apr-29 | AK15: May-29 | AL15: Jun-29
A16: Admissions (per month) [INPUT M4+] | C16: =SUM(C6:F6) | D16: =SUM(G6:K6) | E16: =SUM(L6:O6) | F16: 13.58 | G16: 13.31 | H16: 13.79 | I16: 13.78 | J16: 14.17 | K16: 14.41 | L16: 14.7 | M16: 15.1 | N16: 15.33 | O16: 15.63 | P16: 16.03 | Q16: 16.26 | R16: 16.56 | S16: 16.95 | T16: 17.19 | U16: 17.48 | V16: 17.88 | W16: 18.11 | X16: 18.41 | Y16: 18.81 | Z16: 19.04 | AA16: 19.04 | AB16: 19.22 | AC16: 19.41 | AD16: 19.59 | AE16: 19.78 | AF16: 19.96 | AG16: 20.15 | AH16: 20.33 | AI16: 20.52 | AJ16: 20.7 | AK16: 20.89 | AL16: 21.08
A17: Separations | C17: =SUM(C7:F7) | D17: =SUM(G7:K7) | E17: =SUM(L7:O7) | F17: =E19*'Assumptions'!$B$9/'Assumptions'!$B$12 | G17: =F19*'Assumptions'!$B$9/'Assumptions'!$B$12 | H17: =G19*'Assumptions'!$B$9/'Assumptions'!$B$12 | I17: =H19*'Assumptions'!$B$9/'Assumptions'!$B$12 | J17: =I19*'Assumptions'!$B$9/'Assumptions'!$B$12 | K17: =J19*'Assumptions'!$B$9/'Assumptions'!$B$12 | L17: =K19*'Assumptions'!$B$9/'Assumptions'!$B$12 | M17: =L19*'Assumptions'!$B$9/'Assumptions'!$B$12 | ... AL17: =AK19*'Assumptions'!$B$9/'Assumptions'!$B$12
A18: of which deaths | C18: =C17*'Assumptions'!$B$13 | D18: =D17*'Assumptions'!$B$13 | E18: =E17*'Assumptions'!$B$13 | F18: =F17*'Assumptions'!$B$13 | G18: =G17*'Assumptions'!$B$13 | H18: =H17*'Assumptions'!$B$13 | I18: =I17*'Assumptions'!$B$13 | J18: =J17*'Assumptions'!$B$13 | ... AL18: =AL17*'Assumptions'!$B$13
A19: End-of-month census | C19: =F9 | D19: =K9 | E19: =O9 | F19: =E19+F16-F17 | G19: =F19+G16-G17 | H19: =G19+H16-H17 | I19: =H19+I16-I17 | J19: =I19+J16-J17 | K19: =J19+K16-K17 | L19: =K19+L16-L17 | M19: =L19+M16-M17 | ... AL19: =AK19+AL16-AL17
A20: ADC (avg daily census, x capture) | C20: =AVERAGE(C9:F9)*'Assumptions'!$B$14 | D20: =AVERAGE(G9:K9)*'Assumptions'!$B$14 | E20: =AVERAGE(L9:O9)*'Assumptions'!$B$14 | F20: =(E19+F19)/2*'Assumptions'!$B$14 | G20: =(F19+G19)/2*'Assumptions'!$B$14 | H20: =(G19+H19)/2*'Assumptions'!$B$14 | I20: =(H19+I19)/2*'Assumptions'!$B$14 | J20: =(I19+J19)/2*'Assumptions'!$B$14 | K20: =(J19+K19)/2*'Assumptions'!$B$14 | L20: =(K19+L19)/2*'Assumptions'!$B$14 | M20: =(L19+M19)/2*'Assumptions'!$B$14 | ... AL20: =(AK19+AL19)/2*'Assumptions'!$B$14
A21: Patient days (month) | C21: =C20*'Assumptions'!$B$9 | D21: =D20*'Assumptions'!$B$9 | E21: =E20*'Assumptions'!$B$9 | F21: =F20*'Assumptions'!$B$9 | G21: =G20*'Assumptions'!$B$9 | H21: =H20*'Assumptions'!$B$9 | I21: =I20*'Assumptions'!$B$9 | J21: =J20*'Assumptions'!$B$9 | ... AL21: =AL20*'Assumptions'!$B$9

Sheet Collections
A1: AZALEA HOSPICE - REFUGE OPERATING MODEL
A2: Revenue earned -> cash collected. NOE losses, sequential claims, CHOW payment hold on first claims.
A4: Month # | C4: 1 | D4: 2 | E4: 3 | F4: 4 | G4: 5 | H4: 6 | I4: 7 | J4: 8 | K4: 9 | L4: 10 | M4: 11 | N4: 12 | O4: 13 | P4: 14 | Q4: 15 | R4: 16 | S4: 17 | T4: 18 | U4: 19 | V4: 20 | W4: 21 | X4: 22 | Y4: 23 | Z4: 24 | AA4: 25 | AB4: 26 | AC4: 27 | AD4: 28 | AE4: 29 | AF4: 30 | AG4: 31 | AH4: 32 | AI4: 33 | AJ4: 34 | AK4: 35 | AL4: 36
C5: Jul-26 | D5: Aug-26 | E5: Sep-26 | F5: Oct-26 | G5: Nov-26 | H5: Dec-26 | I5: Jan-27 | J5: Feb-27 | K5: Mar-27 | L5: Apr-27 | M5: May-27 | N5: Jun-27 | O5: Jul-27 | P5: Aug-27 | Q5: Sep-27 | R5: Oct-27 | S5: Nov-27 | T5: Dec-27 | U5: Jan-28 | V5: Feb-28 | W5: Mar-28 | X5: Apr-28 | Y5: May-28 | Z5: Jun-28 | AA5: Jul-28 | AB5: Aug-28 | AC5: Sep-28 | AD5: Oct-28 | AE5: Nov-28 | AF5: Dec-28 | AG5: Jan-29 | AH5: Feb-29 | AI5: Mar-29 | AJ5: Apr-29 | AK5: May-29 | AL5: Jun-29
A6: Blended net rate ($/PD, escalated) | C6: =('Assumptions'!$B$7*'Assumptions'!$B$5+(1-'Assumptions'!$B$7)*'Assumptions'!$B$6)*(1+'Assumptions'!$B$8)^0 | D6: =('Assumptions'!$B$7*'Assumptions'!$B$5+(1-'Assumptions'!$B$7)*'Assumptions'!$B$6)*(1+'Assumptions'!$B$8)^0 | E6: =('Assumptions'!$B$7*'Assumptions'!$B$5+(1-'Assumptions'!$B$7)*'Assumptions'!$B$6)*(1+'Assumptions'!$B$8)^0 | F6: =('Assumptions'!$B$7*'Assumptions'!$B$5+(1-'Assumptions'!$B$7)*'Assumptions'!$B$6)*(1+'Assumptions'!$B$8)^0 | G6: =('Assumptions'!$B$7*'Assumptions'!$B$5+(1-'Assumptions'!$B$7)*'Assumptions'!$B$6)*(1+'Assumptions'!$B$8)^0 | H6: =('Assumptions'!$B$7*'Assumptions'!$B$5+(1-'Assumptions'!$B$7)*'Assumptions'!$B$6)*(1+'Assumptions'!$B$8)^0 | I6: =('Assumptions'!$B$7*'Assumptions'!$B$5+(1-'Assumptions'!$B$7)*'Assumptions'!$B$6)*(1+'Assumptions'!$B$8)^0 | J6: =('Assumptions'!$B$7*'Assumptions'!$B$5+(1-'Assumptions'!$B$7)*'Assumptions'!$B$6)*(1+'Assumptions'!$B$8)^0 | ... N6: =('Assumptions'!$B$7*'Assumptions'!$B$5+(1-'Assumptions'!$B$7)*'Assumptions'!$B$6)*(1+'Assumptions'!$B$8)^0 | O6: =('Assumptions'!$B$7*'Assumptions'!$B$5+(1-'Assumptions'!$B$7)*'Assumptions'!$B$6)*(1+'Assumptions'!$B$8)^1 | P6: =('Assumptions'!$B$7*'Assumptions'!$B$5+(1-'Assumptions'!$B$7)*'Assumptions'!$B$6)*(1+'Assumptions'!$B$8)^1 | Q6: =('Assumptions'!$B$7*'Assumptions'!$B$5+(1-'Assumptions'!$B$7)*'Assumptions'!$B$6)*(1+'Assumptions'!$B$8)^1 | R6: =('Assumptions'!$B$7*'Assumptions'!$B$5+(1-'Assumptions'!$B$7)*'Assumptions'!$B$6)*(1+'Assumptions'!$B$8)^1 | S6: =('Assumptions'!$B$7*'Assumptions'!$B$5+(1-'Assumptions'!$B$7)*'Assumptions'!$B$6)*(1+'Assumptions'!$B$8)^1 | T6: =('Assumptions'!$B$7*'Assumptions'!$B$5+(1-'Assumptions'!$B$7)*'Assumptions'!$B$6)*(1+'Assumptions'!$B$8)^1 | U6: =('Assumptions'!$B$7*'Assumptions'!$B$5+(1-'Assumptions'!$B$7)*'Assumptions'!$B$6)*(1+'Assumptions'!$B$8)^1 | V6: =('Assumptions'!$B$7*'Assumptions'!$B$5+(1-'Assumptions'!$B$7)*'Assumptions'!$B$6)*(1+'Assumptions'!$B$8)^1 | ... Z6: =('Assumptions'!$B$7*'Assumptions'!$B$5+(1-'Assumptions'!$B$7)*'Assumptions'!$B$6)*(1+'Assumptions'!$B$8)^1 | AA6: =('Assumptions'!$B$7*'Assumptions'!$B$5+(1-'Assumptions'!$B$7)*'Assumptions'!$B$6)*(1+'Assumptions'!$B$8)^2 | AB6: =('Assumptions'!$B$7*'Assumptions'!$B$5+(1-'Assumptions'!$B$7)*'Assumptions'!$B$6)*(1+'Assumptions'!$B$8)^2 | AC6: =('Assumptions'!$B$7*'Assumptions'!$B$5+(1-'Assumptions'!$B$7)*'Assumptions'!$B$6)*(1+'Assumptions'!$B$8)^2 | AD6: =('Assumptions'!$B$7*'Assumptions'!$B$5+(1-'Assumptions'!$B$7)*'Assumptions'!$B$6)*(1+'Assumptions'!$B$8)^2 | AE6: =('Assumptions'!$B$7*'Assumptions'!$B$5+(1-'Assumptions'!$B$7)*'Assumptions'!$B$6)*(1+'Assumptions'!$B$8)^2 | AF6: =('Assumptions'!$B$7*'Assumptions'!$B$5+(1-'Assumptions'!$B$7)*'Assumptions'!$B$6)*(1+'Assumptions'!$B$8)^2 | AG6: =('Assumptions'!$B$7*'Assumptions'!$B$5+(1-'Assumptions'!$B$7)*'Assumptions'!$B$6)*(1+'Assumptions'!$B$8)^2 | AH6: =('Assumptions'!$B$7*'Assumptions'!$B$5+(1-'Assumptions'!$B$7)*'Assumptions'!$B$6)*(1+'Assumptions'!$B$8)^2 | ... AL6: =('Assumptions'!$B$7*'Assumptions'!$B$5+(1-'Assumptions'!$B$7)*'Assumptions'!$B$6)*(1+'Assumptions'!$B$8)^2
A7: Revenue earned (PD x rate) | C7: =Census!C21*C6 | D7: =Census!D21*D6 | E7: =Census!E21*E6 | F7: =Census!F21*F6 | G7: =Census!G21*G6 | H7: =Census!H21*H6 | I7: =Census!I21*I6 | J7: =Census!J21*J6 | ... AL7: =Census!AL21*AL6
A8: less: NOE losses (late notices) | C8: =-Census!C16*'Assumptions'!$B$18*'Assumptions'!$B$17*C6 | D8: =-Census!D16*'Assumptions'!$B$18*'Assumptions'!$B$17*D6 | E8: =-Census!E16*'Assumptions'!$B$18*'Assumptions'!$B$17*E6 | F8: =-Census!F16*'Assumptions'!$B$18*'Assumptions'!$B$17*F6 | G8: =-Census!G16*'Assumptions'!$B$18*'Assumptions'!$B$17*G6 | H8: =-Census!H16*'Assumptions'!$B$18*'Assumptions'!$B$17*H6 | I8: =-Census!I16*'Assumptions'!$B$18*'Assumptions'!$B$17*I6 | J8: =-Census!J16*'Assumptions'!$B$18*'Assumptions'!$B$17*J6 | ... AL8: =-Census!AL16*'Assumptions'!$B$18*'Assumptions'!$B$17*AL6
A9: NET REVENUE (billable) | C9: =C7+C8 | D9: =D7+D8 | E9: =E7+E8 | F9: =F7+F8 | G9: =G7+G8 | H9: =H7+H8 | I9: =I7+I8 | J9: =J7+J8 | ... AL9: =AL7+AL8
A10: Collection month (svc mo + lag + hold on first claims) | C10: =1+'Assumptions'!$B$20+MAX(0,'Assumptions'!$B$19-0) | D10: =2+'Assumptions'!$B$20+MAX(0,'Assumptions'!$B$19-1) | E10: =3+'Assumptions'!$B$20+MAX(0,'Assumptions'!$B$19-2) | F10: =4+'Assumptions'!$B$20+MAX(0,'Assumptions'!$B$19-3) | G10: =5+'Assumptions'!$B$20+MAX(0,'Assumptions'!$B$19-4) | H10: =6+'Assumptions'!$B$20+MAX(0,'Assumptions'!$B$19-5) | I10: =7+'Assumptions'!$B$20+MAX(0,'Assumptions'!$B$19-6) | J10: =8+'Assumptions'!$B$20+MAX(0,'Assumptions'!$B$19-7) | K10: =9+'Assumptions'!$B$20+MAX(0,'Assumptions'!$B$19-8) | L10: =10+'Assumptions'!$B$20+MAX(0,'Assumptions'!$B$19-9) | M10: =11+'Assumptions'!$B$20+MAX(0,'Assumptions'!$B$19-10) | N10: =12+'Assumptions'!$B$20+MAX(0,'Assumptions'!$B$19-11) | O10: =13+'Assumptions'!$B$20+MAX(0,'Assumptions'!$B$19-12) | P10: =14+'Assumptions'!$B$20+MAX(0,'Assumptions'!$B$19-13) | Q10: =15+'Assumptions'!$B$20+MAX(0,'Assumptions'!$B$19-14) | R10: =16+'Assumptions'!$B$20+MAX(0,'Assumptions'!$B$19-15) | S10: =17+'Assumptions'!$B$20+MAX(0,'Assumptions'!$B$19-16) | T10: =18+'Assumptions'!$B$20+MAX(0,'Assumptions'!$B$19-17) | U10: =19+'Assumptions'!$B$20+MAX(0,'Assumptions'!$B$19-18) | V10: =20+'Assumptions'!$B$20+MAX(0,'Assumptions'!$B$19-19) | W10: =21+'Assumptions'!$B$20+MAX(0,'Assumptions'!$B$19-20) | X10: =22+'Assumptions'!$B$20+MAX(0,'Assumptions'!$B$19-21) | Y10: =23+'Assumptions'!$B$20+MAX(0,'Assumptions'!$B$19-22) | Z10: =24+'Assumptions'!$B$20+MAX(0,'Assumptions'!$B$19-23) | AA10: =25+'Assumptions'!$B$20+MAX(0,'Assumptions'!$B$19-24) | AB10: =26+'Assumptions'!$B$20+MAX(0,'Assumptions'!$B$19-25) | AC10: =27+'Assumptions'!$B$20+MAX(0,'Assumptions'!$B$19-26) | AD10: =28+'Assumptions'!$B$20+MAX(0,'Assumptions'!$B$19-27) | AE10: =29+'Assumptions'!$B$20+MAX(0,'Assumptions'!$B$19-28) | AF10: =30+'Assumptions'!$B$20+MAX(0,'Assumptions'!$B$19-29) | AG10: =31+'Assumptions'!$B$20+MAX(0,'Assumptions'!$B$19-30) | AH10: =32+'Assumptions'!$B$20+MAX(0,'Assumptions'!$B$19-31) | AI10: =33+'Assumptions'!$B$20+MAX(0,'Assumptions'!$B$19-32) | AJ10: =34+'Assumptions'!$B$20+MAX(0,'Assumptions'!$B$19-33) | AK10: =35+'Assumptions'!$B$20+MAX(0,'Assumptions'!$B$19-34) | AL10: =36+'Assumptions'!$B$20+MAX(0,'Assumptions'!$B$19-35)
A11: CASH COLLECTED | C11: =SUMPRODUCT(($C$10:$AL$10=1)*$C$9:$AL$9) | D11: =SUMPRODUCT(($C$10:$AL$10=2)*$C$9:$AL$9) | E11: =SUMPRODUCT(($C$10:$AL$10=3)*$C$9:$AL$9) | F11: =SUMPRODUCT(($C$10:$AL$10=4)*$C$9:$AL$9) | G11: =SUMPRODUCT(($C$10:$AL$10=5)*$C$9:$AL$9) | H11: =SUMPRODUCT(($C$10:$AL$10=6)*$C$9:$AL$9) | I11: =SUMPRODUCT(($C$10:$AL$10=7)*$C$9:$AL$9) | J11: =SUMPRODUCT(($C$10:$AL$10=8)*$C$9:$AL$9) | K11: =SUMPRODUCT(($C$10:$AL$10=9)*$C$9:$AL$9) | L11: =SUMPRODUCT(($C$10:$AL$10=10)*$C$9:$AL$9) | M11: =SUMPRODUCT(($C$10:$AL$10=11)*$C$9:$AL$9) | N11: =SUMPRODUCT(($C$10:$AL$10=12)*$C$9:$AL$9) | O11: =SUMPRODUCT(($C$10:$AL$10=13)*$C$9:$AL$9) | P11: =SUMPRODUCT(($C$10:$AL$10=14)*$C$9:$AL$9) | Q11: =SUMPRODUCT(($C$10:$AL$10=15)*$C$9:$AL$9) | R11: =SUMPRODUCT(($C$10:$AL$10=16)*$C$9:$AL$9) | S11: =SUMPRODUCT(($C$10:$AL$10=17)*$C$9:$AL$9) | T11: =SUMPRODUCT(($C$10:$AL$10=18)*$C$9:$AL$9) | U11: =SUMPRODUCT(($C$10:$AL$10=19)*$C$9:$AL$9) | V11: =SUMPRODUCT(($C$10:$AL$10=20)*$C$9:$AL$9) | W11: =SUMPRODUCT(($C$10:$AL$10=21)*$C$9:$AL$9) | X11: =SUMPRODUCT(($C$10:$AL$10=22)*$C$9:$AL$9) | Y11: =SUMPRODUCT(($C$10:$AL$10=23)*$C$9:$AL$9) | Z11: =SUMPRODUCT(($C$10:$AL$10=24)*$C$9:$AL$9) | AA11: =SUMPRODUCT(($C$10:$AL$10=25)*$C$9:$AL$9) | AB11: =SUMPRODUCT(($C$10:$AL$10=26)*$C$9:$AL$9) | AC11: =SUMPRODUCT(($C$10:$AL$10=27)*$C$9:$AL$9) | AD11: =SUMPRODUCT(($C$10:$AL$10=28)*$C$9:$AL$9) | AE11: =SUMPRODUCT(($C$10:$AL$10=29)*$C$9:$AL$9) | AF11: =SUMPRODUCT(($C$10:$AL$10=30)*$C$9:$AL$9) | AG11: =SUMPRODUCT(($C$10:$AL$10=31)*$C$9:$AL$9) | AH11: =SUMPRODUCT(($C$10:$AL$10=32)*$C$9:$AL$9) | AI11: =SUMPRODUCT(($C$10:$AL$10=33)*$C$9:$AL$9) | AJ11: =SUMPRODUCT(($C$10:$AL$10=34)*$C$9:$AL$9) | AK11: =SUMPRODUCT(($C$10:$AL$10=35)*$C$9:$AL$9) | AL11: =SUMPRODUCT(($C$10:$AL$10=36)*$C$9:$AL$9)
A12: AR balance (earned not yet collected) | C12: =SUM($C$9:C9)-SUM($C$11:C11) | D12: =SUM($C$9:D9)-SUM($C$11:D11) | E12: =SUM($C$9:E9)-SUM($C$11:E11) | F12: =SUM($C$9:F9)-SUM($C$11:F11) | G12: =SUM($C$9:G9)-SUM($C$11:G11) | H12: =SUM($C$9:H9)-SUM($C$11:H11) | I12: =SUM($C$9:I9)-SUM($C$11:I11) | J12: =SUM($C$9:J9)-SUM($C$11:J11) | ... AL12: =SUM($C$9:AL9)-SUM($C$11:AL11)
A14: WEEKLY RECEIPTS (13 weeks; month receipts spread across its weeks)
C15: W1 | D15: W2 | E15: W3 | F15: W4 | G15: W5 | H15: W6 | I15: W7 | J15: W8 | K15: W9 | L15: W10 | M15: W11 | N15: W12 | O15: W13
A16: Cash received (week) | C16: =C11/4 | D16: =C11/4 | E16: =C11/4 | F16: =C11/4 | G16: =D11/5 | H16: =D11/5 | I16: =D11/5 | J16: =D11/5 | K16: =D11/5 | L16: =E11/4 | M16: =E11/4 | N16: =E11/4 | O16: =E11/4

Sheet Payroll
A1: AZALEA HOSPICE - REFUGE OPERATING MODEL
A2: Per-employee register (blue inputs) -> monthly cost matrix -> summary rows. Semi-monthly cash timing on Weekly Cash tab.
A4: REGISTER (I..AT = monthly gross cost incl. scenario adj, deferral, escalation)
A5: Employee / role | B5: Salary | C5: Hire mo | D5: Direct? | E5: Hlth wait | F5: Defer % | G5: Defer end | I5: M1 | J5: M2 | K5: M3 | L5: M4 | M5: M5 | N5: M6 | O5: M7 | P5: M8 | Q5: M9 | R5: M10 | S5: M11 | T5: M12 | U5: M13 | V5: M14 | W5: M15 | X5: M16 | Y5: M17 | Z5: M18 | AA5: M19 | AB5: M20 | AC5: M21 | AD5: M22 | AE5: M23 | AF5: M24 | AG5: M25 | AH5: M26 | AI5: M27 | AJ5: M28 | AK5: M29 | AL5: M30 | AM5: M31 | AN5: M32 | AO5: M33 | AP5: M34 | AQ5: M35 | AR5: M36
A6: Brad Woodard - Administrator / Director | B6: 120000 | C6: 1 | D6: I | E6: 3 | F6: =IF(1,'Assumptions'!$B$28,0) | G6: ='Assumptions'!$B$29 | I6: =IF(1>=$C6,$B6/12*(1+'Assumptions'!$B$26)*(1+'Assumptions'!$B$27)^0*(1-IF(1<=$G6,$F6,0)),0) | J6: =IF(2>=$C6,$B6/12*(1+'Assumptions'!$B$26)*(1+'Assumptions'!$B$27)^0*(1-IF(2<=$G6,$F6,0)),0) | K6: =IF(3>=$C6,$B6/12*(1+'Assumptions'!$B$26)*(1+'Assumptions'!$B$27)^0*(1-IF(3<=$G6,$F6,0)),0) | L6: =IF(4>=$C6,$B6/12*(1+'Assumptions'!$B$26)*(1+'Assumptions'!$B$27)^0*(1-IF(4<=$G6,$F6,0)),0) | M6: =IF(5>=$C6,$B6/12*(1+'Assumptions'!$B$26)*(1+'Assumptions'!$B$27)^0*(1-IF(5<=$G6,$F6,0)),0) | N6: =IF(6>=$C6,$B6/12*(1+'Assumptions'!$B$26)*(1+'Assumptions'!$B$27)^0*(1-IF(6<=$G6,$F6,0)),0) | O6: =IF(7>=$C6,$B6/12*(1+'Assumptions'!$B$26)*(1+'Assumptions'!$B$27)^0*(1-IF(7<=$G6,$F6,0)),0) | P6: =IF(8>=$C6,$B6/12*(1+'Assumptions'!$B$26)*(1+'Assumptions'!$B$27)^0*(1-IF(8<=$G6,$F6,0)),0) | Q6: =IF(9>=$C6,$B6/12*(1+'Assumptions'!$B$26)*(1+'Assumptions'!$B$27)^0*(1-IF(9<=$G6,$F6,0)),0) | R6: =IF(10>=$C6,$B6/12*(1+'Assumptions'!$B$26)*(1+'Assumptions'!$B$27)^0*(1-IF(10<=$G6,$F6,0)),0) | S6: =IF(11>=$C6,$B6/12*(1+'Assumptions'!$B$26)*(1+'Assumptions'!$B$27)^0*(1-IF(11<=$G6,$F6,0)),0) | T6: =IF(12>=$C6,$B6/12*(1+'Assumptions'!$B$26)*(1+'Assumptions'!$B$27)^0*(1-IF(12<=$G6,$F6,0)),0) | U6: =IF(13>=$C6,$B6/12*(1+'Assumptions'!$B$26)*(1+'Assumptions'!$B$27)^1*(1-IF(13<=$G6,$F6,0)),0) | V6: =IF(14>=$C6,$B6/12*(1+'Assumptions'!$B$26)*(1+'Assumptions'!$B$27)^1*(1-IF(14<=$G6,$F6,0)),0) | W6: =IF(15>=$C6,$B6/12*(1+'Assumptions'!$B$26)*(1+'Assumptions'!$B$27)^1*(1-IF(15<=$G6,$F6,0)),0) | X6: =IF(16>=$C6,$B6/12*(1+'Assumptions'!$B$26)*(1+'Assumptions'!$B$27)^1*(1-IF(16<=$G6,$F6,0)),0) | Y6: =IF(17>=$C6,$B6/12*(1+'Assumptions'!$B$26)*(1+'Assumptions'!$B$27)^1*(1-IF(17<=$G6,$F6,0)),0) | Z6: =IF(18>=$C6,$B6/12*(1+'Assumptions'!$B$26)*(1+'Assumptions'!$B$27)^1*(1-IF(18<=$G6,$F6,0)),0) | AA6: =IF(19>=$C6,$B6/12*(1+'Assumptions'!$B$26)*(1+'Assumptions'!$B$27)^1*(1-IF(19<=$G6,$F6,0)),0) | AB6: =IF(20>=$C6,$B6/12*(1+'Assumptions'!$B$26)*(1+'Assumptions'!$B$27)^1*(1-IF(20<=$G6,$F6,0)),0) | AC6: =IF(21>=$C6,$B6/12*(1+'Assumptions'!$B$26)*(1+'Assumptions'!$B$27)^1*(1-IF(21<=$G6,$F6,0)),0) | AD6: =IF(22>=$C6,$B6/12*(1+'Assumptions'!$B$26)*(1+'Assumptions'!$B$27)^1*(1-IF(22<=$G6,$F6,0)),0) | AE6: =IF(23>=$C6,$B6/12*(1+'Assumptions'!$B$26)*(1+'Assumptions'!$B$27)^1*(1-IF(23<=$G6,$F6,0)),0) | AF6: =IF(24>=$C6,$B6/12*(1+'Assumptions'!$B$26)*(1+'Assumptions'!$B$27)^1*(1-IF(24<=$G6,$F6,0)),0) | AG6: =IF(25>=$C6,$B6/12*(1+'Assumptions'!$B$26)*(1+'Assumptions'!$B$27)^2*(1-IF(25<=$G6,$F6,0)),0) | AH6: =IF(26>=$C6,$B6/12*(1+'Assumptions'!$B$26)*(1+'Assumptions'!$B$27)^2*(1-IF(26<=$G6,$F6,0)),0) | AI6: =IF(27>=$C6,$B6/12*(1+'Assumptions'!$B$26)*(1+'Assumptions'!$B$27)^2*(1-IF(27<=$G6,$F6,0)),0) | AJ6: =IF(28>=$C6,$B6/12*(1+'Assumptions'!$B$26)*(1+'Assumptions'!$B$27)^2*(1-IF(28<=$G6,$F6,0)),0) | AK6: =IF(29>=$C6,$B6/12*(1+'Assumptions'!$B$26)*(1+'Assumptions'!$B$27)^2*(1-IF(29<=$G6,$F6,0)),0) | AL6: =IF(30>=$C6,$B6/12*(1+'Assumptions'!$B$26)*(1+'Assumptions'!$B$27)^2*(1-IF(30<=$G6,$F6,0)),0) | AM6: =IF(31>=$C6,$B6/12*(1+'Assumptions'!$B$26)*(1+'Assumptions'!$B$27)^2*(1-IF(31<=$G6,$F6,0)),0) | AN6: =IF(32>=$C6,$B6/12*(1+'Assumptions'!$B$26)*(1+'Assumptions'!$B$27)^2*(1-IF(32<=$G6,$F6,0)),0) | AO6: =IF(33>=$C6,$B6/12*(1+'Assumptions'!$B$26)*(1+'Assumptions'!$B$27)^2*(1-IF(33<=$G6,$F6,0)),0) | AP6: =IF(34>=$C6,$B6/12*(1+'Assumptions'!$B$26)*(1+'Assumptions'!$B$27)^2*(1-IF(34<=$G6,$F6,0)),0) | AQ6: =IF(35>=$C6,$B6/12*(1+'Assumptions'!$B$26)*(1+'Assumptions'!$B$27)^2*(1-IF(35<=$G6,$F6,0)),0) | AR6: =IF(36>=$C6,$B6/12*(1+'Assumptions'!$B$26)*(1+'Assumptions'!$B$27)^2*(1-IF(36<=$G6,$F6,0)),0)
A7: Angie Frost - RN Case Manager | B7: 77504 | C7: 1 | D7: D | E7: 3 | F7: =IF(0,'Assumptions'!$B$28,0) | G7: ='Assumptions'!$B$29 | I7: =IF(1>=$C7,$B7/12*(1+'Assumptions'!$B$26)*(1+'Assumptions'!$B$27)^0*(1-IF(1<=$G7,$F7,0)),0) | J7: =IF(2>=$C7,$B7/12*(1+'Assumptions'!$B$26)*(1+'Assumptions'!$B$27)^0*(1-IF(2<=$G7,$F7,0)),0) | K7: =IF(3>=$C7,$B7/12*(1+'Assumptions'!$B$26)*(1+'Assumptions'!$B$27)^0*(1-IF(3<=$G7,$F7,0)),0) | L7: =IF(4>=$C7,$B7/12*(1+'Assumptions'!$B$26)*(1+'Assumptions'!$B$27)^0*(1-IF(4<=$G7,$F7,0)),0) | M7: =IF(5>=$C7,$B7/12*(1+'Assumptions'!$B$26)*(1+'Assumptions'!$B$27)^0*(1-IF(5<=$G7,$F7,0)),0) | N7: =IF(6>=$C7,$B7/12*(1+'Assumptions'!$B$26)*(1+'Assumptions'!$B$27)^0*(1-IF(6<=$G7,$F7,0)),0) | O7: =IF(7>=$C7,$B7/12*(1+'Assumptions'!$B$26)*(1+'Assumptions'!$B$27)^0*(1-IF(7<=$G7,$F7,0)),0) | P7: =IF(8>=$C7,$B7/12*(1+'Assumptions'!$B$26)*(1+'Assumptions'!$B$27)^0*(1-IF(8<=$G7,$F7,0)),0) | Q7: =IF(9>=$C7,$B7/12*(1+'Assumptions'!$B$26)*(1+'Assumptions'!$B$27)^0*(1-IF(9<=$G7,$F7,0)),0) | R7: =IF(10>=$C7,$B7/12*(1+'Assumptions'!$B$26)*(1+'Assumptions'!$B$27)^0*(1-IF(10<=$G7,$F7,0)),0) | S7: =IF(11>=$C7,$B7/12*(1+'Assumptions'!$B$26)*(1+'Assumptions'!$B$27)^0*(1-IF(11<=$G7,$F7,0)),0) | T7: =IF(12>=$C7,$B7/12*(1+'Assumptions'!$B$26)*(1+'Assumptions'!$B$27)^0*(1-IF(12<=$G7,$F7,0)),0) | U7: =IF(13>=$C7,$B7/12*(1+'Assumptions'!$B$26)*(1+'Assumptions'!$B$27)^1*(1-IF(13<=$G7,$F7,0)),0) | V7: =IF(14>=$C7,$B7/12*(1+'Assumptions'!$B$26)*(1+'Assumptions'!$B$27)^1*(1-IF(14<=$G7,$F7,0)),0) | W7: =IF(15>=$C7,$B7/12*(1+'Assumptions'!$B$26)*(1+'Assumptions'!$B$27)^1*(1-IF(15<=$G7,$F7,0)),0) | X7: =IF(16>=$C7,$B7/12*(1+'Assumptions'!$B$26)*(1+'Assumptions'!$B$27)^1*(1-IF(16<=$G7,$F7,0)),0) | Y7: =IF(17>=$C7,$B7/12*(1+'Assumptions'!$B$26)*(1+'Assumptions'!$B$27)^1*(1-IF(17<=$G7,$F7,0)),0) | Z7: =IF(18>=$C7,$B7/12*(1+'Assumptions'!$B$26)*(1+'Assumptions'!$B$27)^1*(1-IF(18<=$G7,$F7,0)),0) | AA7: =IF(19>=$C7,$B7/12*(1+'Assumptions'!$B$26)*(1+'Assumptions'!$B$27)^1*(1-IF(19<=$G7,$F7,0)),0) | AB7: =IF(20>=$C7,$B7/12*(1+'Assumptions'!$B$26)*(1+'Assumptions'!$B$27)^1*(1-IF(20<=$G7,$F7,0)),0) | AC7: =IF(21>=$C7,$B7/12*(1+'Assumptions'!$B$26)*(1+'Assumptions'!$B$27)^1*(1-IF(21<=$G7,$F7,0)),0) | AD7: =IF(22>=$C7,$B7/12*(1+'Assumptions'!$B$26)*(1+'Assumptions'!$B$27)^1*(1-IF(22<=$G7,$F7,0)),0) | AE7: =IF(23>=$C7,$B7/12*(1+'Assumptions'!$B$26)*(1+'Assumptions'!$B$27)^1*(1-IF(23<=$G7,$F7,0)),0) | AF7: =IF(24>=$C7,$B7/12*(1+'Assumptions'!$B$26)*(1+'Assumptions'!$B$27)^1*(1-IF(24<=$G7,$F7,0)),0) | AG7: =IF(25>=$C7,$B7/12*(1+'Assumptions'!$B$26)*(1+'Assumptions'!$B$27)^2*(1-IF(25<=$G7,$F7,0)),0) | AH7: =IF(26>=$C7,$B7/12*(1+'Assumptions'!$B$26)*(1+'Assumptions'!$B$27)^2*(1-IF(26<=$G7,$F7,0)),0) | AI7: =IF(27>=$C7,$B7/12*(1+'Assumptions'!$B$26)*(1+'Assumptions'!$B$27)^2*(1-IF(27<=$G7,$F7,0)),0) | AJ7: =IF(28>=$C7,$B7/12*(1+'Assumptions'!$B$26)*(1+'Assumptions'!$B$27)^2*(1-IF(28<=$G7,$F7,0)),0) | AK7: =IF(29>=$C7,$B7/12*(1+'Assumptions'!$B$26)*(1+'Assumptions'!$B$27)^2*(1-IF(29<=$G7,$F7,0)),0) | AL7: =IF(30>=$C7,$B7/12*(1+'Assumptions'!$B$26)*(1+'Assumptions'!$B$27)^2*(1-IF(30<=$G7,$F7,0)),0) | AM7: =IF(31>=$C7,$B7/12*(1+'Assumptions'!$B$26)*(1+'Assumptions'!$B$27)^2*(1-IF(31<=$G7,$F7,0)),0) | AN7: =IF(32>=$C7,$B7/12*(1+'Assumptions'!$B$26)*(1+'Assumptions'!$B$27)^2*(1-IF(32<=$G7,$F7,0)),0) | AO7: =IF(33>=$C7,$B7/12*(1+'Assumptions'!$B$26)*(1+'Assumptions'!$B$27)^2*(1-IF(33<=$G7,$F7,0)),0) | AP7: =IF(34>=$C7,$B7/12*(1+'Assumptions'!$B$26)*(1+'Assumptions'!$B$27)^2*(1-IF(34<=$G7,$F7,0)),0) | AQ7: =IF(35>=$C7,$B7/12*(1+'Assumptions'!$B$26)*(1+'Assumptions'!$B$27)^2*(1-IF(35<=$G7,$F7,0)),0) | AR7: =IF(36>=$C7,$B7/12*(1+'Assumptions'!$B$26)*(1+'Assumptions'!$B$27)^2*(1-IF(36<=$G7,$F7,0)),0)
A8: Tanisha Robison - CNA / Hospice Aide | B8: 46511 | C8: 1 | D8: D | E8: 3 | F8: =IF(0,'Assumptions'!$B$28,0) | G8: ='Assumptions'!$B$29 | I8: =IF(1>=$C8,$B8/12*(1+'Assumptions'!$B$26)*(1+'Assumptions'!$B$27)^0*(1-IF(1<=$G8,$F8,0)),0) | J8: =IF(2>=$C8,$B8/12*(1+'Assumptions'!$B$26)*(1+'Assumptions'!$B$27)^0*(1-IF(2<=$G8,$F8,0)),0) | K8: =IF(3>=$C8,$B8/12*(1+'Assumptions'!$B$26)*(1+'Assumptions'!$B$27)^0*(1-IF(3<=$G8,$F8,0)),0) | L8: =IF(4>=$C8,$B8/12*(1+'Assumptions'!$B$26)*(1+'Assumptions'!$B$27)^0*(1-IF(4<=$G8,$F8,0)),0) | M8: =IF(5>=$C8,$B8/12*(1+'Assumptions'!$B$26)*(1+'Assumptions'!$B$27)^0*(1-IF(5<=$G8,$F8,0)),0) | N8: =IF(6>=$C8,$B8/12*(1+'Assumptions'!$B$26)*(1+'Assumptions'!$B$27)^0*(1-IF(6<=$G8,$F8,0)),0) | O8: =IF(7>=$C8,$B8/12*(1+'Assumptions'!$B$26)*(1+'Assumptions'!$B$27)^0*(1-IF(7<=$G8,$F8,0)),0) | P8: =IF(8>=$C8,$B8/12*(1+'Assumptions'!$B$26)*(1+'Assumptions'!$B$27)^0*(1-IF(8<=$G8,$F8,0)),0) | Q8: =IF(9>=$C8,$B8/12*(1+'Assumptions'!$B$26)*(1+'Assumptions'!$B$27)^0*(1-IF(9<=$G8,$F8,0)),0) | R8: =IF(10>=$C8,$B8/12*(1+'Assumptions'!$B$26)*(1+'Assumptions'!$B$27)^0*(1-IF(10<=$G8,$F8,0)),0) | S8: =IF(11>=$C8,$B8/12*(1+'Assumptions'!$B$26)*(1+'Assumptions'!$B$27)^0*(1-IF(11<=$G8,$F8,0)),0) | T8: =IF(12>=$C8,$B8/12*(1+'Assumptions'!$B$26)*(1+'Assumptions'!$B$27)^0*(1-IF(12<=$G8,$F8,0)),0) | U8: =IF(13>=$C8,$B8/12*(1+'Assumptions'!$B$26)*(1+'Assumptions'!$B$27)^1*(1-IF(13<=$G8,$F8,0)),0) | V8: =IF(14>=$C8,$B8/12*(1+'Assumptions'!$B$26)*(1+'Assumptions'!$B$27)^1*(1-IF(14<=$G8,$F8,0)),0) | W8: =IF(15>=$C8,$B8/12*(1+'Assumptions'!$B$26)*(1+'Assumptions'!$B$27)^1*(1-IF(15<=$G8,$F8,0)),0) | X8: =IF(16>=$C8,$B8/12*(1+'Assumptions'!$B$26)*(1+'Assumptions'!$B$27)^1*(1-IF(16<=$G8,$F8,0)),0) | Y8: =IF(17>=$C8,$B8/12*(1+'Assumptions'!$B$26)*(1+'Assumptions'!$B$27)^1*(1-IF(17<=$G8,$F8,0)),0) | Z8: =IF(18>=$C8,$B8/12*(1+'Assumptions'!$B$26)*(1+'Assumptions'!$B$27)^1*(1-IF(18<=$G8,$F8,0)),0) | AA8: =IF(19>=$C8,$B8/12*(1+'Assumptions'!$B$26)*(1+'Assumptions'!$B$27)^1*(1-IF(19<=$G8,$F8,0)),0) | AB8: =IF(20>=$C8,$B8/12*(1+'Assumptions'!$B$26)*(1+'Assumptions'!$B$27)^1*(1-IF(20<=$G8,$F8,0)),0) | AC8: =IF(21>=$C8,$B8/12*(1+'Assumptions'!$B$26)*(1+'Assumptions'!$B$27)^1*(1-IF(21<=$G8,$F8,0)),0) | AD8: =IF(22>=$C8,$B8/12*(1+'Assumptions'!$B$26)*(1+'Assumptions'!$B$27)^1*(1-IF(22<=$G8,$F8,0)),0) | AE8: =IF(23>=$C8,$B8/12*(1+'Assumptions'!$B$26)*(1+'Assumptions'!$B$27)^1*(1-IF(23<=$G8,$F8,0)),0) | AF8: =IF(24>=$C8,$B8/12*(1+'Assumptions'!$B$26)*(1+'Assumptions'!$B$27)^1*(1-IF(24<=$G8,$F8,0)),0) | AG8: =IF(25>=$C8,$B8/12*(1+'Assumptions'!$B$26)*(1+'Assumptions'!$B$27)^2*(1-IF(25<=$G8,$F8,0)),0) | AH8: =IF(26>=$C8,$B8/12*(1+'Assumptions'!$B$26)*(1+'Assumptions'!$B$27)^2*(1-IF(26<=$G8,$F8,0)),0) | AI8: =IF(27>=$C8,$B8/12*(1+'Assumptions'!$B$26)*(1+'Assumptions'!$B$27)^2*(1-IF(27<=$G8,$F8,0)),0) | AJ8: =IF(28>=$C8,$B8/12*(1+'Assumptions'!$B$26)*(1+'Assumptions'!$B$27)^2*(1-IF(28<=$G8,$F8,0)),0) | AK8: =IF(29>=$C8,$B8/12*(1+'Assumptions'!$B$26)*(1+'Assumptions'!$B$27)^2*(1-IF(29<=$G8,$F8,0)),0) | AL8: =IF(30>=$C8,$B8/12*(1+'Assumptions'!$B$26)*(1+'Assumptions'!$B$27)^2*(1-IF(30<=$G8,$F8,0)),0) | AM8: =IF(31>=$C8,$B8/12*(1+'Assumptions'!$B$26)*(1+'Assumptions'!$B$27)^2*(1-IF(31<=$G8,$F8,0)),0) | AN8: =IF(32>=$C8,$B8/12*(1+'Assumptions'!$B$26)*(1+'Assumptions'!$B$27)^2*(1-IF(32<=$G8,$F8,0)),0) | AO8: =IF(33>=$C8,$B8/12*(1+'Assumptions'!$B$26)*(1+'Assumptions'!$B$27)^2*(1-IF(33<=$G8,$F8,0)),0) | AP8: =IF(34>=$C8,$B8/12*(1+'Assumptions'!$B$26)*(1+'Assumptions'!$B$27)^2*(1-IF(34<=$G8,$F8,0)),0) | AQ8: =IF(35>=$C8,$B8/12*(1+'Assumptions'!$B$26)*(1+'Assumptions'!$B$27)^2*(1-IF(35<=$G8,$F8,0)),0) | AR8: =IF(36>=$C8,$B8/12*(1+'Assumptions'!$B$26)*(1+'Assumptions'!$B$27)^2*(1-IF(36<=$G8,$F8,0)),0)
A9: Dana Davenport - Director of Clinical Services | B9: 110000 | C9: 2 | D9: I | E9: 3 | F9: =IF(1,'Assumptions'!$B$28,0) | G9: ='Assumptions'!$B$29 | I9: =IF(1>=$C9,$B9/12*(1+'Assumptions'!$B$26)*(1+'Assumptions'!$B$27)^0*(1-IF(1<=$G9,$F9,0)),0) | J9: =IF(2>=$C9,$B9/12*(1+'Assumptions'!$B$26)*(1+'Assumptions'!$B$27)^0*(1-IF(2<=$G9,$F9,0)),0) | K9: =IF(3>=$C9,$B9/12*(1+'Assumptions'!$B$26)*(1+'Assumptions'!$B$27)^0*(1-IF(3<=$G9,$F9,0)),0) | L9: =IF(4>=$C9,$B9/12*(1+'Assumptions'!$B$26)*(1+'Assumptions'!$B$27)^0*(1-IF(4<=$G9,$F9,0)),0) | M9: =IF(5>=$C9,$B9/12*(1+'Assumptions'!$B$26)*(1+'Assumptions'!$B$27)^0*(1-IF(5<=$G9,$F9,0)),0) | N9: =IF(6>=$C9,$B9/12*(1+'Assumptions'!$B$26)*(1+'Assumptions'!$B$27)^0*(1-IF(6<=$G9,$F9,0)),0) | O9: =IF(7>=$C9,$B9/12*(1+'Assumptions'!$B$26)*(1+'Assumptions'!$B$27)^0*(1-IF(7<=$G9,$F9,0)),0) | P9: =IF(8>=$C9,$B9/12*(1+'Assumptions'!$B$26)*(1+'Assumptions'!$B$27)^0*(1-IF(8<=$G9,$F9,0)),0) | Q9: =IF(9>=$C9,$B9/12*(1+'Assumptions'!$B$26)*(1+'Assumptions'!$B$27)^0*(1-IF(9<=$G9,$F9,0)),0) | R9: =IF(10>=$C9,$B9/12*(1+'Assumptions'!$B$26)*(1+'Assumptions'!$B$27)^0*(1-IF(10<=$G9,$F9,0)),0) | S9: =IF(11>=$C9,$B9/12*(1+'Assumptions'!$B$26)*(1+'Assumptions'!$B$27)^0*(1-IF(11<=$G9,$F9,0)),0) | T9: =IF(12>=$C9,$B9/12*(1+'Assumptions'!$B$26)*(1+'Assumptions'!$B$27)^0*(1-IF(12<=$G9,$F9,0)),0) | U9: =IF(13>=$C9,$B9/12*(1+'Assumptions'!$B$26)*(1+'Assumptions'!$B$27)^1*(1-IF(13<=$G9,$F9,0)),0) | V9: =IF(14>=$C9,$B9/12*(1+'Assumptions'!$B$26)*(1+'Assumptions'!$B$27)^1*(1-IF(14<=$G9,$F9,0)),0) | W9: =IF(15>=$C9,$B9/12*(1+'Assumptions'!$B$26)*(1+'Assumptions'!$B$27)^1*(1-IF(15<=$G9,$F9,0)),0) | X9: =IF(16>=$C9,$B9/12*(1+'Assumptions'!$B$26)*(1+'Assumptions'!$B$27)^1*(1-IF(16<=$G9,$F9,0)),0) | Y9: =IF(17>=$C9,$B9/12*(1+'Assumptions'!$B$26)*(1+'Assumptions'!$B$27)^1*(1-IF(17<=$G9,$F9,0)),0) | Z9: =IF(18>=$C9,$B9/12*(1+'Assumptions'!$B$26)*(1+'Assumptions'!$B$27)^1*(1-IF(18<=$G9,$F9,0)),0) | AA9: =IF(19>=$C9,$B9/12*(1+'Assumptions'!$B$26)*(1+'Assumptions'!$B$27)^1*(1-IF(19<=$G9,$F9,0)),0) | AB9: =IF(20>=$C9,$B9/12*(1+'Assumptions'!$B$26)*(1+'Assumptions'!$B$27)^1*(1-IF(20<=$G9,$F9,0)),0) | AC9: =IF(21>=$C9,$B9/12*(1+'Assumptions'!$B$26)*(1+'Assumptions'!$B$27)^1*(1-IF(21<=$G9,$F9,0)),0) | AD9: =IF(22>=$C9,$B9/12*(1+'Assumptions'!$B$26)*(1+'Assumptions'!$B$27)^1*(1-IF(22<=$G9,$F9,0)),0) | AE9: =IF(23>=$C9,$B9/12*(1+'Assumptions'!$B$26)*(1+'Assumptions'!$B$27)^1*(1-IF(23<=$G9,$F9,0)),0) | AF9: =IF(24>=$C9,$B9/12*(1+'Assumptions'!$B$26)*(1+'Assumptions'!$B$27)^1*(1-IF(24<=$G9,$F9,0)),0) | AG9: =IF(25>=$C9,$B9/12*(1+'Assumptions'!$B$26)*(1+'Assumptions'!$B$27)^2*(1-IF(25<=$G9,$F9,0)),0) | AH9: =IF(26>=$C9,$B9/12*(1+'Assumptions'!$B$26)*(1+'Assumptions'!$B$27)^2*(1-IF(26<=$G9,$F9,0)),0) | AI9: =IF(27>=$C9,$B9/12*(1+'Assumptions'!$B$26)*(1+'Assumptions'!$B$27)^2*(1-IF(27<=$G9,$F9,0)),0) | AJ9: =IF(28>=$C9,$B9/12*(1+'Assumptions'!$B$26)*(1+'Assumptions'!$B$27)^2*(1-IF(28<=$G9,$F9,0)),0) | AK9: =IF(29>=$C9,$B9/12*(1+'Assumptions'!$B$26)*(1+'Assumptions'!$B$27)^2*(1-IF(29<=$G9,$F9,0)),0) | AL9: =IF(30>=$C9,$B9/12*(1+'Assumptions'!$B$26)*(1+'Assumptions'!$B$27)^2*(1-IF(30<=$G9,$F9,0)),0) | AM9: =IF(31>=$C9,$B9/12*(1+'Assumptions'!$B$26)*(1+'Assumptions'!$B$27)^2*(1-IF(31<=$G9,$F9,0)),0) | AN9: =IF(32>=$C9,$B9/12*(1+'Assumptions'!$B$26)*(1+'Assumptions'!$B$27)^2*(1-IF(32<=$G9,$F9,0)),0) | AO9: =IF(33>=$C9,$B9/12*(1+'Assumptions'!$B$26)*(1+'Assumptions'!$B$27)^2*(1-IF(33<=$G9,$F9,0)),0) | AP9: =IF(34>=$C9,$B9/12*(1+'Assumptions'!$B$26)*(1+'Assumptions'!$B$27)^2*(1-IF(34<=$G9,$F9,0)),0) | AQ9: =IF(35>=$C9,$B9/12*(1+'Assumptions'!$B$26)*(1+'Assumptions'!$B$27)^2*(1-IF(35<=$G9,$F9,0)),0) | AR9: =IF(36>=$C9,$B9/12*(1+'Assumptions'!$B$26)*(1+'Assumptions'!$B$27)^2*(1-IF(36<=$G9,$F9,0)),0)
A10: Silas Shelton - Administrator | B10: 130000 | C10: 3 | D10: I | E10: 3 | F10: =IF(1,'Assumptions'!$B$28,0) | G10: ='Assumptions'!$B$29 | I10: =IF(1>=$C10,$B10/12*(1+'Assumptions'!$B$26)*(1+'Assumptions'!$B$27)^0*(1-IF(1<=$G10,$F10,0)),0) | J10: =IF(2>=$C10,$B10/12*(1+'Assumptions'!$B$26)*(1+'Assumptions'!$B$27)^0*(1-IF(2<=$G10,$F10,0)),0) | K10: =IF(3>=$C10,$B10/12*(1+'Assumptions'!$B$26)*(1+'Assumptions'!$B$27)^0*(1-IF(3<=$G10,$F10,0)),0) | L10: =IF(4>=$C10,$B10/12*(1+'Assumptions'!$B$26)*(1+'Assumptions'!$B$27)^0*(1-IF(4<=$G10,$F10,0)),0) | M10: =IF(5>=$C10,$B10/12*(1+'Assumptions'!$B$26)*(1+'Assumptions'!$B$27)^0*(1-IF(5<=$G10,$F10,0)),0) | N10: =IF(6>=$C10,$B10/12*(1+'Assumptions'!$B$26)*(1+'Assumptions'!$B$27)^0*(1-IF(6<=$G10,$F10,0)),0) | O10: =IF(7>=$C10,$B10/12*(1+'Assumptions'!$B$26)*(1+'Assumptions'!$B$27)^0*(1-IF(7<=$G10,$F10,0)),0) | P10: =IF(8>=$C10,$B10/12*(1+'Assumptions'!$B$26)*(1+'Assumptions'!$B$27)^0*(1-IF(8<=$G10,$F10,0)),0) | Q10: =IF(9>=$C10,$B10/12*(1+'Assumptions'!$B$26)*(1+'Assumptions'!$B$27)^0*(1-IF(9<=$G10,$F10,0)),0) | R10: =IF(10>=$C10,$B10/12*(1+'Assumptions'!$B$26)*(1+'Assumptions'!$B$27)^0*(1-IF(10<=$G10,$F10,0)),0) | S10: =IF(11>=$C10,$B10/12*(1+'Assumptions'!$B$26)*(1+'Assumptions'!$B$27)^0*(1-IF(11<=$G10,$F10,0)),0) | T10: =IF(12>=$C10,$B10/12*(1+'Assumptions'!$B$26)*(1+'Assumptions'!$B$27)^0*(1-IF(12<=$G10,$F10,0)),0) | U10: =IF(13>=$C10,$B10/12*(1+'Assumptions'!$B$26)*(1+'Assumptions'!$B$27)^1*(1-IF(13<=$G10,$F10,0)),0) | V10: =IF(14>=$C10,$B10/12*(1+'Assumptions'!$B$26)*(1+'Assumptions'!$B$27)^1*(1-IF(14<=$G10,$F10,0)),0) | W10: =IF(15>=$C10,$B10/12*(1+'Assumptions'!$B$26)*(1+'Assumptions'!$B$27)^1*(1-IF(15<=$G10,$F10,0)),0) | X10: =IF(16>=$C10,$B10/12*(1+'Assumptions'!$B$26)*(1+'Assumptions'!$B$27)^1*(1-IF(16<=$G10,$F10,0)),0) | Y10: =IF(17>=$C10,$B10/12*(1+'Assumptions'!$B$26)*(1+'Assumptions'!$B$27)^1*(1-IF(17<=$G10,$F10,0)),0) | Z10: =IF(18>=$C10,$B10/12*(1+'Assumptions'!$B$26)*(1+'Assumptions'!$B$27)^1*(1-IF(18<=$G10,$F10,0)),0) | AA10: =IF(19>=$C10,$B10/12*(1+'Assumptions'!$B$26)*(1+'Assumptions'!$B$27)^1*(1-IF(19<=$G10,$F10,0)),0) | AB10: =IF(20>=$C10,$B10/12*(1+'Assumptions'!$B$26)*(1+'Assumptions'!$B$27)^1*(1-IF(20<=$G10,$F10,0)),0) | AC10: =IF(21>=$C10,$B10/12*(1+'Assumptions'!$B$26)*(1+'Assumptions'!$B$27)^1*(1-IF(21<=$G10,$F10,0)),0) | AD10: =IF(22>=$C10,$B10/12*(1+'Assumptions'!$B$26)*(1+'Assumptions'!$B$27)^1*(1-IF(22<=$G10,$F10,0)),0) | AE10: =IF(23>=$C10,$B10/12*(1+'Assumptions'!$B$26)*(1+'Assumptions'!$B$27)^1*(1-IF(23<=$G10,$F10,0)),0) | AF10: =IF(24>=$C10,$B10/12*(1+'Assumptions'!$B$26)*(1+'Assumptions'!$B$27)^1*(1-IF(24<=$G10,$F10,0)),0) | AG10: =IF(25>=$C10,$B10/12*(1+'Assumptions'!$B$26)*(1+'Assumptions'!$B$27)^2*(1-IF(25<=$G10,$F10,0)),0) | AH10: =IF(26>=$C10,$B10/12*(1+'Assumptions'!$B$26)*(1+'Assumptions'!$B$27)^2*(1-IF(26<=$G10,$F10,0)),0) | AI10: =IF(27>=$C10,$B10/12*(1+'Assumptions'!$B$26)*(1+'Assumptions'!$B$27)^2*(1-IF(27<=$G10,$F10,0)),0) | AJ10: =IF(28>=$C10,$B10/12*(1+'Assumptions'!$B$26)*(1+'Assumptions'!$B$27)^2*(1-IF(28<=$G10,$F10,0)),0) | AK10: =IF(29>=$C10,$B10/12*(1+'Assumptions'!$B$26)*(1+'Assumptions'!$B$27)^2*(1-IF(29<=$G10,$F10,0)),0) | AL10: =IF(30>=$C10,$B10/12*(1+'Assumptions'!$B$26)*(1+'Assumptions'!$B$27)^2*(1-IF(30<=$G10,$F10,0)),0) | AM10: =IF(31>=$C10,$B10/12*(1+'Assumptions'!$B$26)*(1+'Assumptions'!$B$27)^2*(1-IF(31<=$G10,$F10,0)),0) | AN10: =IF(32>=$C10,$B10/12*(1+'Assumptions'!$B$26)*(1+'Assumptions'!$B$27)^2*(1-IF(32<=$G10,$F10,0)),0) | AO10: =IF(33>=$C10,$B10/12*(1+'Assumptions'!$B$26)*(1+'Assumptions'!$B$27)^2*(1-IF(33<=$G10,$F10,0)),0) | AP10: =IF(34>=$C10,$B10/12*(1+'Assumptions'!$B$26)*(1+'Assumptions'!$B$27)^2*(1-IF(34<=$G10,$F10,0)),0) | AQ10: =IF(35>=$C10,$B10/12*(1+'Assumptions'!$B$26)*(1+'Assumptions'!$B$27)^2*(1-IF(35<=$G10,$F10,0)),0) | AR10: =IF(36>=$C10,$B10/12*(1+'Assumptions'!$B$26)*(1+'Assumptions'!$B$27)^2*(1-IF(36<=$G10,$F10,0)),0)
A11: Jodi McCollum - RN Case Manager (2nd seat) | B11: 75008 | C11: 4 | D11: D | E11: 3 | F11: =IF(0,'Assumptions'!$B$28,0) | G11: ='Assumptions'!$B$29 | I11: =IF(1>=$C11,$B11/12*(1+'Assumptions'!$B$26)*(1+'Assumptions'!$B$27)^0*(1-IF(1<=$G11,$F11,0)),0) | J11: =IF(2>=$C11,$B11/12*(1+'Assumptions'!$B$26)*(1+'Assumptions'!$B$27)^0*(1-IF(2<=$G11,$F11,0)),0) | K11: =IF(3>=$C11,$B11/12*(1+'Assumptions'!$B$26)*(1+'Assumptions'!$B$27)^0*(1-IF(3<=$G11,$F11,0)),0) | L11: =IF(4>=$C11,$B11/12*(1+'Assumptions'!$B$26)*(1+'Assumptions'!$B$27)^0*(1-IF(4<=$G11,$F11,0)),0) | M11: =IF(5>=$C11,$B11/12*(1+'Assumptions'!$B$26)*(1+'Assumptions'!$B$27)^0*(1-IF(5<=$G11,$F11,0)),0) | N11: =IF(6>=$C11,$B11/12*(1+'Assumptions'!$B$26)*(1+'Assumptions'!$B$27)^0*(1-IF(6<=$G11,$F11,0)),0) | O11: =IF(7>=$C11,$B11/12*(1+'Assumptions'!$B$26)*(1+'Assumptions'!$B$27)^0*(1-IF(7<=$G11,$F11,0)),0) | P11: =IF(8>=$C11,$B11/12*(1+'Assumptions'!$B$26)*(1+'Assumptions'!$B$27)^0*(1-IF(8<=$G11,$F11,0)),0) | Q11: =IF(9>=$C11,$B11/12*(1+'Assumptions'!$B$26)*(1+'Assumptions'!$B$27)^0*(1-IF(9<=$G11,$F11,0)),0) | R11: =IF(10>=$C11,$B11/12*(1+'Assumptions'!$B$26)*(1+'Assumptions'!$B$27)^0*(1-IF(10<=$G11,$F11,0)),0) | S11: =IF(11>=$C11,$B11/12*(1+'Assumptions'!$B$26)*(1+'Assumptions'!$B$27)^0*(1-IF(11<=$G11,$F11,0)),0) | T11: =IF(12>=$C11,$B11/12*(1+'Assumptions'!$B$26)*(1+'Assumptions'!$B$27)^0*(1-IF(12<=$G11,$F11,0)),0) | U11: =IF(13>=$C11,$B11/12*(1+'Assumptions'!$B$26)*(1+'Assumptions'!$B$27)^1*(1-IF(13<=$G11,$F11,0)),0) | V11: =IF(14>=$C11,$B11/12*(1+'Assumptions'!$B$26)*(1+'Assumptions'!$B$27)^1*(1-IF(14<=$G11,$F11,0)),0) | W11: =IF(15>=$C11,$B11/12*(1+'Assumptions'!$B$26)*(1+'Assumptions'!$B$27)^1*(1-IF(15<=$G11,$F11,0)),0) | X11: =IF(16>=$C11,$B11/12*(1+'Assumptions'!$B$26)*(1+'Assumptions'!$B$27)^1*(1-IF(16<=$G11,$F11,0)),0) | Y11: =IF(17>=$C11,$B11/12*(1+'Assumptions'!$B$26)*(1+'Assumptions'!$B$27)^1*(1-IF(17<=$G11,$F11,0)),0) | Z11: =IF(18>=$C11,$B11/12*(1+'Assumptions'!$B$26)*(1+'Assumptions'!$B$27)^1*(1-IF(18<=$G11,$F11,0)),0) | AA11: =IF(19>=$C11,$B11/12*(1+'Assumptions'!$B$26)*(1+'Assumptions'!$B$27)^1*(1-IF(19<=$G11,$F11,0)),0) | AB11: =IF(20>=$C11,$B11/12*(1+'Assumptions'!$B$26)*(1+'Assumptions'!$B$27)^1*(1-IF(20<=$G11,$F11,0)),0) | AC11: =IF(21>=$C11,$B11/12*(1+'Assumptions'!$B$26)*(1+'Assumptions'!$B$27)^1*(1-IF(21<=$G11,$F11,0)),0) | AD11: =IF(22>=$C11,$B11/12*(1+'Assumptions'!$B$26)*(1+'Assumptions'!$B$27)^1*(1-IF(22<=$G11,$F11,0)),0) | AE11: =IF(23>=$C11,$B11/12*(1+'Assumptions'!$B$26)*(1+'Assumptions'!$B$27)^1*(1-IF(23<=$G11,$F11,0)),0) | AF11: =IF(24>=$C11,$B11/12*(1+'Assumptions'!$B$26)*(1+'Assumptions'!$B$27)^1*(1-IF(24<=$G11,$F11,0)),0) | AG11: =IF(25>=$C11,$B11/12*(1+'Assumptions'!$B$26)*(1+'Assumptions'!$B$27)^2*(1-IF(25<=$G11,$F11,0)),0) | AH11: =IF(26>=$C11,$B11/12*(1+'Assumptions'!$B$26)*(1+'Assumptions'!$B$27)^2*(1-IF(26<=$G11,$F11,0)),0) | AI11: =IF(27>=$C11,$B11/12*(1+'Assumptions'!$B$26)*(1+'Assumptions'!$B$27)^2*(1-IF(27<=$G11,$F11,0)),0) | AJ11: =IF(28>=$C11,$B11/12*(1+'Assumptions'!$B$26)*(1+'Assumptions'!$B$27)^2*(1-IF(28<=$G11,$F11,0)),0) | AK11: =IF(29>=$C11,$B11/12*(1+'Assumptions'!$B$26)*(1+'Assumptions'!$B$27)^2*(1-IF(29<=$G11,$F11,0)),0) | AL11: =IF(30>=$C11,$B11/12*(1+'Assumptions'!$B$26)*(1+'Assumptions'!$B$27)^2*(1-IF(30<=$G11,$F11,0)),0) | AM11: =IF(31>=$C11,$B11/12*(1+'Assumptions'!$B$26)*(1+'Assumptions'!$B$27)^2*(1-IF(31<=$G11,$F11,0)),0) | AN11: =IF(32>=$C11,$B11/12*(1+'Assumptions'!$B$26)*(1+'Assumptions'!$B$27)^2*(1-IF(32<=$G11,$F11,0)),0) | AO11: =IF(33>=$C11,$B11/12*(1+'Assumptions'!$B$26)*(1+'Assumptions'!$B$27)^2*(1-IF(33<=$G11,$F11,0)),0) | AP11: =IF(34>=$C11,$B11/12*(1+'Assumptions'!$B$26)*(1+'Assumptions'!$B$27)^2*(1-IF(34<=$G11,$F11,0)),0) | AQ11: =IF(35>=$C11,$B11/12*(1+'Assumptions'!$B$26)*(1+'Assumptions'!$B$27)^2*(1-IF(35<=$G11,$F11,0)),0) | AR11: =IF(36>=$C11,$B11/12*(1+'Assumptions'!$B$26)*(1+'Assumptions'!$B$27)^2*(1-IF(36<=$G11,$F11,0)),0)
A12: Director of Business Development - Sales / referrals (growth driv | B12: 95000 | C12: 6 | D12: I | E12: 3 | F12: =IF(0,'Assumptions'!$B$28,0) | G12: ='Assumptions'!$B$29 | I12: =IF(1>=$C12,$B12/12*(1+'Assumptions'!$B$26)*(1+'Assumptions'!$B$27)^0*(1-IF(1<=$G12,$F12,0)),0) | J12: =IF(2>=$C12,$B12/12*(1+'Assumptions'!$B$26)*(1+'Assumptions'!$B$27)^0*(1-IF(2<=$G12,$F12,0)),0) | K12: =IF(3>=$C12,$B12/12*(1+'Assumptions'!$B$26)*(1+'Assumptions'!$B$27)^0*(1-IF(3<=$G12,$F12,0)),0) | L12: =IF(4>=$C12,$B12/12*(1+'Assumptions'!$B$26)*(1+'Assumptions'!$B$27)^0*(1-IF(4<=$G12,$F12,0)),0) | M12: =IF(5>=$C12,$B12/12*(1+'Assumptions'!$B$26)*(1+'Assumptions'!$B$27)^0*(1-IF(5<=$G12,$F12,0)),0) | N12: =IF(6>=$C12,$B12/12*(1+'Assumptions'!$B$26)*(1+'Assumptions'!$B$27)^0*(1-IF(6<=$G12,$F12,0)),0) | O12: =IF(7>=$C12,$B12/12*(1+'Assumptions'!$B$26)*(1+'Assumptions'!$B$27)^0*(1-IF(7<=$G12,$F12,0)),0) | P12: =IF(8>=$C12,$B12/12*(1+'Assumptions'!$B$26)*(1+'Assumptions'!$B$27)^0*(1-IF(8<=$G12,$F12,0)),0) | Q12: =IF(9>=$C12,$B12/12*(1+'Assumptions'!$B$26)*(1+'Assumptions'!$B$27)^0*(1-IF(9<=$G12,$F12,0)),0) | R12: =IF(10>=$C12,$B12/12*(1+'Assumptions'!$B$26)*(1+'Assumptions'!$B$27)^0*(1-IF(10<=$G12,$F12,0)),0) | S12: =IF(11>=$C12,$B12/12*(1+'Assumptions'!$B$26)*(1+'Assumptions'!$B$27)^0*(1-IF(11<=$G12,$F12,0)),0) | T12: =IF(12>=$C12,$B12/12*(1+'Assumptions'!$B$26)*(1+'Assumptions'!$B$27)^0*(1-IF(12<=$G12,$F12,0)),0) | U12: =IF(13>=$C12,$B12/12*(1+'Assumptions'!$B$26)*(1+'Assumptions'!$B$27)^1*(1-IF(13<=$G12,$F12,0)),0) | V12: =IF(14>=$C12,$B12/12*(1+'Assumptions'!$B$26)*(1+'Assumptions'!$B$27)^1*(1-IF(14<=$G12,$F12,0)),0) | W12: =IF(15>=$C12,$B12/12*(1+'Assumptions'!$B$26)*(1+'Assumptions'!$B$27)^1*(1-IF(15<=$G12,$F12,0)),0) | X12: =IF(16>=$C12,$B12/12*(1+'Assumptions'!$B$26)*(1+'Assumptions'!$B$27)^1*(1-IF(16<=$G12,$F12,0)),0) | Y12: =IF(17>=$C12,$B12/12*(1+'Assumptions'!$B$26)*(1+'Assumptions'!$B$27)^1*(1-IF(17<=$G12,$F12,0)),0) | Z12: =IF(18>=$C12,$B12/12*(1+'Assumptions'!$B$26)*(1+'Assumptions'!$B$27)^1*(1-IF(18<=$G12,$F12,0)),0) | AA12: =IF(19>=$C12,$B12/12*(1+'Assumptions'!$B$26)*(1+'Assumptions'!$B$27)^1*(1-IF(19<=$G12,$F12,0)),0) | AB12: =IF(20>=$C12,$B12/12*(1+'Assumptions'!$B$26)*(1+'Assumptions'!$B$27)^1*(1-IF(20<=$G12,$F12,0)),0) | AC12: =IF(21>=$C12,$B12/12*(1+'Assumptions'!$B$26)*(1+'Assumptions'!$B$27)^1*(1-IF(21<=$G12,$F12,0)),0) | AD12: =IF(22>=$C12,$B12/12*(1+'Assumptions'!$B$26)*(1+'Assumptions'!$B$27)^1*(1-IF(22<=$G12,$F12,0)),0) | AE12: =IF(23>=$C12,$B12/12*(1+'Assumptions'!$B$26)*(1+'Assumptions'!$B$27)^1*(1-IF(23<=$G12,$F12,0)),0) | AF12: =IF(24>=$C12,$B12/12*(1+'Assumptions'!$B$26)*(1+'Assumptions'!$B$27)^1*(1-IF(24<=$G12,$F12,0)),0) | AG12: =IF(25>=$C12,$B12/12*(1+'Assumptions'!$B$26)*(1+'Assumptions'!$B$27)^2*(1-IF(25<=$G12,$F12,0)),0) | AH12: =IF(26>=$C12,$B12/12*(1+'Assumptions'!$B$26)*(1+'Assumptions'!$B$27)^2*(1-IF(26<=$G12,$F12,0)),0) | AI12: =IF(27>=$C12,$B12/12*(1+'Assumptions'!$B$26)*(1+'Assumptions'!$B$27)^2*(1-IF(27<=$G12,$F12,0)),0) | AJ12: =IF(28>=$C12,$B12/12*(1+'Assumptions'!$B$26)*(1+'Assumptions'!$B$27)^2*(1-IF(28<=$G12,$F12,0)),0) | AK12: =IF(29>=$C12,$B12/12*(1+'Assumptions'!$B$26)*(1+'Assumptions'!$B$27)^2*(1-IF(29<=$G12,$F12,0)),0) | AL12: =IF(30>=$C12,$B12/12*(1+'Assumptions'!$B$26)*(1+'Assumptions'!$B$27)^2*(1-IF(30<=$G12,$F12,0)),0) | AM12: =IF(31>=$C12,$B12/12*(1+'Assumptions'!$B$26)*(1+'Assumptions'!$B$27)^2*(1-IF(31<=$G12,$F12,0)),0) | AN12: =IF(32>=$C12,$B12/12*(1+'Assumptions'!$B$26)*(1+'Assumptions'!$B$27)^2*(1-IF(32<=$G12,$F12,0)),0) | AO12: =IF(33>=$C12,$B12/12*(1+'Assumptions'!$B$26)*(1+'Assumptions'!$B$27)^2*(1-IF(33<=$G12,$F12,0)),0) | AP12: =IF(34>=$C12,$B12/12*(1+'Assumptions'!$B$26)*(1+'Assumptions'!$B$27)^2*(1-IF(34<=$G12,$F12,0)),0) | AQ12: =IF(35>=$C12,$B12/12*(1+'Assumptions'!$B$26)*(1+'Assumptions'!$B$27)^2*(1-IF(35<=$G12,$F12,0)),0) | AR12: =IF(36>=$C12,$B12/12*(1+'Assumptions'!$B$26)*(1+'Assumptions'!$B$27)^2*(1-IF(36<=$G12,$F12,0)),0)
A13: Capacity hire - 2nd CNA - CNA / Hospice Aide (capacity-d [census-triggered - slip if ramp lags] | B13: 46511 | C13: 2 | D13: D | E13: 3 | F13: =IF(0,'Assumptions'!$B$28,0) | G13: ='Assumptions'!$B$29 | I13: =IF(1>=$C13,$B13/12*(1+'Assumptions'!$B$26)*(1+'Assumptions'!$B$27)^0*(1-IF(1<=$G13,$F13,0)),0) | J13: =IF(2>=$C13,$B13/12*(1+'Assumptions'!$B$26)*(1+'Assumptions'!$B$27)^0*(1-IF(2<=$G13,$F13,0)),0) | K13: =IF(3>=$C13,$B13/12*(1+'Assumptions'!$B$26)*(1+'Assumptions'!$B$27)^0*(1-IF(3<=$G13,$F13,0)),0) | L13: =IF(4>=$C13,$B13/12*(1+'Assumptions'!$B$26)*(1+'Assumptions'!$B$27)^0*(1-IF(4<=$G13,$F13,0)),0) | M13: =IF(5>=$C13,$B13/12*(1+'Assumptions'!$B$26)*(1+'Assumptions'!$B$27)^0*(1-IF(5<=$G13,$F13,0)),0) | N13: =IF(6>=$C13,$B13/12*(1+'Assumptions'!$B$26)*(1+'Assumptions'!$B$27)^0*(1-IF(6<=$G13,$F13,0)),0) | O13: =IF(7>=$C13,$B13/12*(1+'Assumptions'!$B$26)*(1+'Assumptions'!$B$27)^0*(1-IF(7<=$G13,$F13,0)),0) | P13: =IF(8>=$C13,$B13/12*(1+'Assumptions'!$B$26)*(1+'Assumptions'!$B$27)^0*(1-IF(8<=$G13,$F13,0)),0) | Q13: =IF(9>=$C13,$B13/12*(1+'Assumptions'!$B$26)*(1+'Assumptions'!$B$27)^0*(1-IF(9<=$G13,$F13,0)),0) | R13: =IF(10>=$C13,$B13/12*(1+'Assumptions'!$B$26)*(1+'Assumptions'!$B$27)^0*(1-IF(10<=$G13,$F13,0)),0) | S13: =IF(11>=$C13,$B13/12*(1+'Assumptions'!$B$26)*(1+'Assumptions'!$B$27)^0*(1-IF(11<=$G13,$F13,0)),0) | T13: =IF(12>=$C13,$B13/12*(1+'Assumptions'!$B$26)*(1+'Assumptions'!$B$27)^0*(1-IF(12<=$G13,$F13,0)),0) | U13: =IF(13>=$C13,$B13/12*(1+'Assumptions'!$B$26)*(1+'Assumptions'!$B$27)^1*(1-IF(13<=$G13,$F13,0)),0) | V13: =IF(14>=$C13,$B13/12*(1+'Assumptions'!$B$26)*(1+'Assumptions'!$B$27)^1*(1-IF(14<=$G13,$F13,0)),0) | W13: =IF(15>=$C13,$B13/12*(1+'Assumptions'!$B$26)*(1+'Assumptions'!$B$27)^1*(1-IF(15<=$G13,$F13,0)),0) | X13: =IF(16>=$C13,$B13/12*(1+'Assumptions'!$B$26)*(1+'Assumptions'!$B$27)^1*(1-IF(16<=$G13,$F13,0)),0) | Y13: =IF(17>=$C13,$B13/12*(1+'Assumptions'!$B$26)*(1+'Assumptions'!$B$27)^1*(1-IF(17<=$G13,$F13,0)),0) | Z13: =IF(18>=$C13,$B13/12*(1+'Assumptions'!$B$26)*(1+'Assumptions'!$B$27)^1*(1-IF(18<=$G13,$F13,0)),0) | AA13: =IF(19>=$C13,$B13/12*(1+'Assumptions'!$B$26)*(1+'Assumptions'!$B$27)^1*(1-IF(19<=$G13,$F13,0)),0) | AB13: =IF(20>=$C13,$B13/12*(1+'Assumptions'!$B$26)*(1+'Assumptions'!$B$27)^1*(1-IF(20<=$G13,$F13,0)),0) | AC13: =IF(21>=$C13,$B13/12*(1+'Assumptions'!$B$26)*(1+'Assumptions'!$B$27)^1*(1-IF(21<=$G13,$F13,0)),0) | AD13: =IF(22>=$C13,$B13/12*(1+'Assumptions'!$B$26)*(1+'Assumptions'!$B$27)^1*(1-IF(22<=$G13,$F13,0)),0) | AE13: =IF(23>=$C13,$B13/12*(1+'Assumptions'!$B$26)*(1+'Assumptions'!$B$27)^1*(1-IF(23<=$G13,$F13,0)),0) | AF13: =IF(24>=$C13,$B13/12*(1+'Assumptions'!$B$26)*(1+'Assumptions'!$B$27)^1*(1-IF(24<=$G13,$F13,0)),0) | AG13: =IF(25>=$C13,$B13/12*(1+'Assumptions'!$B$26)*(1+'Assumptions'!$B$27)^2*(1-IF(25<=$G13,$F13,0)),0) | AH13: =IF(26>=$C13,$B13/12*(1+'Assumptions'!$B$26)*(1+'Assumptions'!$B$27)^2*(1-IF(26<=$G13,$F13,0)),0) | AI13: =IF(27>=$C13,$B13/12*(1+'Assumptions'!$B$26)*(1+'Assumptions'!$B$27)^2*(1-IF(27<=$G13,$F13,0)),0) | AJ13: =IF(28>=$C13,$B13/12*(1+'Assumptions'!$B$26)*(1+'Assumptions'!$B$27)^2*(1-IF(28<=$G13,$F13,0)),0) | AK13: =IF(29>=$C13,$B13/12*(1+'Assumptions'!$B$26)*(1+'Assumptions'!$B$27)^2*(1-IF(29<=$G13,$F13,0)),0) | AL13: =IF(30>=$C13,$B13/12*(1+'Assumptions'!$B$26)*(1+'Assumptions'!$B$27)^2*(1-IF(30<=$G13,$F13,0)),0) | AM13: =IF(31>=$C13,$B13/12*(1+'Assumptions'!$B$26)*(1+'Assumptions'!$B$27)^2*(1-IF(31<=$G13,$F13,0)),0) | AN13: =IF(32>=$C13,$B13/12*(1+'Assumptions'!$B$26)*(1+'Assumptions'!$B$27)^2*(1-IF(32<=$G13,$F13,0)),0) | AO13: =IF(33>=$C13,$B13/12*(1+'Assumptions'!$B$26)*(1+'Assumptions'!$B$27)^2*(1-IF(33<=$G13,$F13,0)),0) | AP13: =IF(34>=$C13,$B13/12*(1+'Assumptions'!$B$26)*(1+'Assumptions'!$B$27)^2*(1-IF(34<=$G13,$F13,0)),0) | AQ13: =IF(35>=$C13,$B13/12*(1+'Assumptions'!$B$26)*(1+'Assumptions'!$B$27)^2*(1-IF(35<=$G13,$F13,0)),0) | AR13: =IF(36>=$C13,$B13/12*(1+'Assumptions'!$B$26)*(1+'Assumptions'!$B$27)^2*(1-IF(36<=$G13,$F13,0)),0)
A14: FT Social Worker (MSW) - Core IDG MSW (converts PRN SW | B14: 58000 | C14: 6 | D14: D | E14: 3 | F14: =IF(0,'Assumptions'!$B$28,0) | G14: ='Assumptions'!$B$29 | I14: =IF(1>=$C14,$B14/12*(1+'Assumptions'!$B$26)*(1+'Assumptions'!$B$27)^0*(1-IF(1<=$G14,$F14,0)),0) | J14: =IF(2>=$C14,$B14/12*(1+'Assumptions'!$B$26)*(1+'Assumptions'!$B$27)^0*(1-IF(2<=$G14,$F14,0)),0) | K14: =IF(3>=$C14,$B14/12*(1+'Assumptions'!$B$26)*(1+'Assumptions'!$B$27)^0*(1-IF(3<=$G14,$F14,0)),0) | L14: =IF(4>=$C14,$B14/12*(1+'Assumptions'!$B$26)*(1+'Assumptions'!$B$27)^0*(1-IF(4<=$G14,$F14,0)),0) | M14: =IF(5>=$C14,$B14/12*(1+'Assumptions'!$B$26)*(1+'Assumptions'!$B$27)^0*(1-IF(5<=$G14,$F14,0)),0) | N14: =IF(6>=$C14,$B14/12*(1+'Assumptions'!$B$26)*(1+'Assumptions'!$B$27)^0*(1-IF(6<=$G14,$F14,0)),0) | O14: =IF(7>=$C14,$B14/12*(1+'Assumptions'!$B$26)*(1+'Assumptions'!$B$27)^0*(1-IF(7<=$G14,$F14,0)),0) | P14: =IF(8>=$C14,$B14/12*(1+'Assumptions'!$B$26)*(1+'Assumptions'!$B$27)^0*(1-IF(8<=$G14,$F14,0)),0) | Q14: =IF(9>=$C14,$B14/12*(1+'Assumptions'!$B$26)*(1+'Assumptions'!$B$27)^0*(1-IF(9<=$G14,$F14,0)),0) | R14: =IF(10>=$C14,$B14/12*(1+'Assumptions'!$B$26)*(1+'Assumptions'!$B$27)^0*(1-IF(10<=$G14,$F14,0)),0) | S14: =IF(11>=$C14,$B14/12*(1+'Assumptions'!$B$26)*(1+'Assumptions'!$B$27)^0*(1-IF(11<=$G14,$F14,0)),0) | T14: =IF(12>=$C14,$B14/12*(1+'Assumptions'!$B$26)*(1+'Assumptions'!$B$27)^0*(1-IF(12<=$G14,$F14,0)),0) | U14: =IF(13>=$C14,$B14/12*(1+'Assumptions'!$B$26)*(1+'Assumptions'!$B$27)^1*(1-IF(13<=$G14,$F14,0)),0) | V14: =IF(14>=$C14,$B14/12*(1+'Assumptions'!$B$26)*(1+'Assumptions'!$B$27)^1*(1-IF(14<=$G14,$F14,0)),0) | W14: =IF(15>=$C14,$B14/12*(1+'Assumptions'!$B$26)*(1+'Assumptions'!$B$27)^1*(1-IF(15<=$G14,$F14,0)),0) | X14: =IF(16>=$C14,$B14/12*(1+'Assumptions'!$B$26)*(1+'Assumptions'!$B$27)^1*(1-IF(16<=$G14,$F14,0)),0) | Y14: =IF(17>=$C14,$B14/12*(1+'Assumptions'!$B$26)*(1+'Assumptions'!$B$27)^1*(1-IF(17<=$G14,$F14,0)),0) | Z14: =IF(18>=$C14,$B14/12*(1+'Assumptions'!$B$26)*(1+'Assumptions'!$B$27)^1*(1-IF(18<=$G14,$F14,0)),0) | AA14: =IF(19>=$C14,$B14/12*(1+'Assumptions'!$B$26)*(1+'Assumptions'!$B$27)^1*(1-IF(19<=$G14,$F14,0)),0) | AB14: =IF(20>=$C14,$B14/12*(1+'Assumptions'!$B$26)*(1+'Assumptions'!$B$27)^1*(1-IF(20<=$G14,$F14,0)),0) | AC14: =IF(21>=$C14,$B14/12*(1+'Assumptions'!$B$26)*(1+'Assumptions'!$B$27)^1*(1-IF(21<=$G14,$F14,0)),0) | AD14: =IF(22>=$C14,$B14/12*(1+'Assumptions'!$B$26)*(1+'Assumptions'!$B$27)^1*(1-IF(22<=$G14,$F14,0)),0) | AE14: =IF(23>=$C14,$B14/12*(1+'Assumptions'!$B$26)*(1+'Assumptions'!$B$27)^1*(1-IF(23<=$G14,$F14,0)),0) | AF14: =IF(24>=$C14,$B14/12*(1+'Assumptions'!$B$26)*(1+'Assumptions'!$B$27)^1*(1-IF(24<=$G14,$F14,0)),0) | AG14: =IF(25>=$C14,$B14/12*(1+'Assumptions'!$B$26)*(1+'Assumptions'!$B$27)^2*(1-IF(25<=$G14,$F14,0)),0) | AH14: =IF(26>=$C14,$B14/12*(1+'Assumptions'!$B$26)*(1+'Assumptions'!$B$27)^2*(1-IF(26<=$G14,$F14,0)),0) | AI14: =IF(27>=$C14,$B14/12*(1+'Assumptions'!$B$26)*(1+'Assumptions'!$B$27)^2*(1-IF(27<=$G14,$F14,0)),0) | AJ14: =IF(28>=$C14,$B14/12*(1+'Assumptions'!$B$26)*(1+'Assumptions'!$B$27)^2*(1-IF(28<=$G14,$F14,0)),0) | AK14: =IF(29>=$C14,$B14/12*(1+'Assumptions'!$B$26)*(1+'Assumptions'!$B$27)^2*(1-IF(29<=$G14,$F14,0)),0) | AL14: =IF(30>=$C14,$B14/12*(1+'Assumptions'!$B$26)*(1+'Assumptions'!$B$27)^2*(1-IF(30<=$G14,$F14,0)),0) | AM14: =IF(31>=$C14,$B14/12*(1+'Assumptions'!$B$26)*(1+'Assumptions'!$B$27)^2*(1-IF(31<=$G14,$F14,0)),0) | AN14: =IF(32>=$C14,$B14/12*(1+'Assumptions'!$B$26)*(1+'Assumptions'!$B$27)^2*(1-IF(32<=$G14,$F14,0)),0) | AO14: =IF(33>=$C14,$B14/12*(1+'Assumptions'!$B$26)*(1+'Assumptions'!$B$27)^2*(1-IF(33<=$G14,$F14,0)),0) | AP14: =IF(34>=$C14,$B14/12*(1+'Assumptions'!$B$26)*(1+'Assumptions'!$B$27)^2*(1-IF(34<=$G14,$F14,0)),0) | AQ14: =IF(35>=$C14,$B14/12*(1+'Assumptions'!$B$26)*(1+'Assumptions'!$B$27)^2*(1-IF(35<=$G14,$F14,0)),0) | AR14: =IF(36>=$C14,$B14/12*(1+'Assumptions'!$B$26)*(1+'Assumptions'!$B$27)^2*(1-IF(36<=$G14,$F14,0)),0)
A15: FT LVN - visits / on-call - Core IDG LVN (converts PRN LVN | B15: 52000 | C15: 8 | D15: D | E15: 3 | F15: =IF(0,'Assumptions'!$B$28,0) | G15: ='Assumptions'!$B$29 | I15: =IF(1>=$C15,$B15/12*(1+'Assumptions'!$B$26)*(1+'Assumptions'!$B$27)^0*(1-IF(1<=$G15,$F15,0)),0) | J15: =IF(2>=$C15,$B15/12*(1+'Assumptions'!$B$26)*(1+'Assumptions'!$B$27)^0*(1-IF(2<=$G15,$F15,0)),0) | K15: =IF(3>=$C15,$B15/12*(1+'Assumptions'!$B$26)*(1+'Assumptions'!$B$27)^0*(1-IF(3<=$G15,$F15,0)),0) | L15: =IF(4>=$C15,$B15/12*(1+'Assumptions'!$B$26)*(1+'Assumptions'!$B$27)^0*(1-IF(4<=$G15,$F15,0)),0) | M15: =IF(5>=$C15,$B15/12*(1+'Assumptions'!$B$26)*(1+'Assumptions'!$B$27)^0*(1-IF(5<=$G15,$F15,0)),0) | N15: =IF(6>=$C15,$B15/12*(1+'Assumptions'!$B$26)*(1+'Assumptions'!$B$27)^0*(1-IF(6<=$G15,$F15,0)),0) | O15: =IF(7>=$C15,$B15/12*(1+'Assumptions'!$B$26)*(1+'Assumptions'!$B$27)^0*(1-IF(7<=$G15,$F15,0)),0) | P15: =IF(8>=$C15,$B15/12*(1+'Assumptions'!$B$26)*(1+'Assumptions'!$B$27)^0*(1-IF(8<=$G15,$F15,0)),0) | Q15: =IF(9>=$C15,$B15/12*(1+'Assumptions'!$B$26)*(1+'Assumptions'!$B$27)^0*(1-IF(9<=$G15,$F15,0)),0) | R15: =IF(10>=$C15,$B15/12*(1+'Assumptions'!$B$26)*(1+'Assumptions'!$B$27)^0*(1-IF(10<=$G15,$F15,0)),0) | S15: =IF(11>=$C15,$B15/12*(1+'Assumptions'!$B$26)*(1+'Assumptions'!$B$27)^0*(1-IF(11<=$G15,$F15,0)),0) | T15: =IF(12>=$C15,$B15/12*(1+'Assumptions'!$B$26)*(1+'Assumptions'!$B$27)^0*(1-IF(12<=$G15,$F15,0)),0) | U15: =IF(13>=$C15,$B15/12*(1+'Assumptions'!$B$26)*(1+'Assumptions'!$B$27)^1*(1-IF(13<=$G15,$F15,0)),0) | V15: =IF(14>=$C15,$B15/12*(1+'Assumptions'!$B$26)*(1+'Assumptions'!$B$27)^1*(1-IF(14<=$G15,$F15,0)),0) | W15: =IF(15>=$C15,$B15/12*(1+'Assumptions'!$B$26)*(1+'Assumptions'!$B$27)^1*(1-IF(15<=$G15,$F15,0)),0) | X15: =IF(16>=$C15,$B15/12*(1+'Assumptions'!$B$26)*(1+'Assumptions'!$B$27)^1*(1-IF(16<=$G15,$F15,0)),0) | Y15: =IF(17>=$C15,$B15/12*(1+'Assumptions'!$B$26)*(1+'Assumptions'!$B$27)^1*(1-IF(17<=$G15,$F15,0)),0) | Z15: =IF(18>=$C15,$B15/12*(1+'Assumptions'!$B$26)*(1+'Assumptions'!$B$27)^1*(1-IF(18<=$G15,$F15,0)),0) | AA15: =IF(19>=$C15,$B15/12*(1+'Assumptions'!$B$26)*(1+'Assumptions'!$B$27)^1*(1-IF(19<=$G15,$F15,0)),0) | AB15: =IF(20>=$C15,$B15/12*(1+'Assumptions'!$B$26)*(1+'Assumptions'!$B$27)^1*(1-IF(20<=$G15,$F15,0)),0) | AC15: =IF(21>=$C15,$B15/12*(1+'Assumptions'!$B$26)*(1+'Assumptions'!$B$27)^1*(1-IF(21<=$G15,$F15,0)),0) | AD15: =IF(22>=$C15,$B15/12*(1+'Assumptions'!$B$26)*(1+'Assumptions'!$B$27)^1*(1-IF(22<=$G15,$F15,0)),0) | AE15: =IF(23>=$C15,$B15/12*(1+'Assumptions'!$B$26)*(1+'Assumptions'!$B$27)^1*(1-IF(23<=$G15,$F15,0)),0) | AF15: =IF(24>=$C15,$B15/12*(1+'Assumptions'!$B$26)*(1+'Assumptions'!$B$27)^1*(1-IF(24<=$G15,$F15,0)),0) | AG15: =IF(25>=$C15,$B15/12*(1+'Assumptions'!$B$26)*(1+'Assumptions'!$B$27)^2*(1-IF(25<=$G15,$F15,0)),0) | AH15: =IF(26>=$C15,$B15/12*(1+'Assumptions'!$B$26)*(1+'Assumptions'!$B$27)^2*(1-IF(26<=$G15,$F15,0)),0) | AI15: =IF(27>=$C15,$B15/12*(1+'Assumptions'!$B$26)*(1+'Assumptions'!$B$27)^2*(1-IF(27<=$G15,$F15,0)),0) | AJ15: =IF(28>=$C15,$B15/12*(1+'Assumptions'!$B$26)*(1+'Assumptions'!$B$27)^2*(1-IF(28<=$G15,$F15,0)),0) | AK15: =IF(29>=$C15,$B15/12*(1+'Assumptions'!$B$26)*(1+'Assumptions'!$B$27)^2*(1-IF(29<=$G15,$F15,0)),0) | AL15: =IF(30>=$C15,$B15/12*(1+'Assumptions'!$B$26)*(1+'Assumptions'!$B$27)^2*(1-IF(30<=$G15,$F15,0)),0) | AM15: =IF(31>=$C15,$B15/12*(1+'Assumptions'!$B$26)*(1+'Assumptions'!$B$27)^2*(1-IF(31<=$G15,$F15,0)),0) | AN15: =IF(32>=$C15,$B15/12*(1+'Assumptions'!$B$26)*(1+'Assumptions'!$B$27)^2*(1-IF(32<=$G15,$F15,0)),0) | AO15: =IF(33>=$C15,$B15/12*(1+'Assumptions'!$B$26)*(1+'Assumptions'!$B$27)^2*(1-IF(33<=$G15,$F15,0)),0) | AP15: =IF(34>=$C15,$B15/12*(1+'Assumptions'!$B$26)*(1+'Assumptions'!$B$27)^2*(1-IF(34<=$G15,$F15,0)),0) | AQ15: =IF(35>=$C15,$B15/12*(1+'Assumptions'!$B$26)*(1+'Assumptions'!$B$27)^2*(1-IF(35<=$G15,$F15,0)),0) | AR15: =IF(36>=$C15,$B15/12*(1+'Assumptions'!$B$26)*(1+'Assumptions'!$B$27)^2*(1-IF(36<=$G15,$F15,0)),0)
A16: FT Chaplain - Core IDG spiritual care (conve | B16: 55000 | C16: 10 | D16: D | E16: 3 | F16: =IF(0,'Assumptions'!$B$28,0) | G16: ='Assumptions'!$B$29 | I16: =IF(1>=$C16,$B16/12*(1+'Assumptions'!$B$26)*(1+'Assumptions'!$B$27)^0*(1-IF(1<=$G16,$F16,0)),0) | J16: =IF(2>=$C16,$B16/12*(1+'Assumptions'!$B$26)*(1+'Assumptions'!$B$27)^0*(1-IF(2<=$G16,$F16,0)),0) | K16: =IF(3>=$C16,$B16/12*(1+'Assumptions'!$B$26)*(1+'Assumptions'!$B$27)^0*(1-IF(3<=$G16,$F16,0)),0) | L16: =IF(4>=$C16,$B16/12*(1+'Assumptions'!$B$26)*(1+'Assumptions'!$B$27)^0*(1-IF(4<=$G16,$F16,0)),0) | M16: =IF(5>=$C16,$B16/12*(1+'Assumptions'!$B$26)*(1+'Assumptions'!$B$27)^0*(1-IF(5<=$G16,$F16,0)),0) | N16: =IF(6>=$C16,$B16/12*(1+'Assumptions'!$B$26)*(1+'Assumptions'!$B$27)^0*(1-IF(6<=$G16,$F16,0)),0) | O16: =IF(7>=$C16,$B16/12*(1+'Assumptions'!$B$26)*(1+'Assumptions'!$B$27)^0*(1-IF(7<=$G16,$F16,0)),0) | P16: =IF(8>=$C16,$B16/12*(1+'Assumptions'!$B$26)*(1+'Assumptions'!$B$27)^0*(1-IF(8<=$G16,$F16,0)),0) | Q16: =IF(9>=$C16,$B16/12*(1+'Assumptions'!$B$26)*(1+'Assumptions'!$B$27)^0*(1-IF(9<=$G16,$F16,0)),0) | R16: =IF(10>=$C16,$B16/12*(1+'Assumptions'!$B$26)*(1+'Assumptions'!$B$27)^0*(1-IF(10<=$G16,$F16,0)),0) | S16: =IF(11>=$C16,$B16/12*(1+'Assumptions'!$B$26)*(1+'Assumptions'!$B$27)^0*(1-IF(11<=$G16,$F16,0)),0) | T16: =IF(12>=$C16,$B16/12*(1+'Assumptions'!$B$26)*(1+'Assumptions'!$B$27)^0*(1-IF(12<=$G16,$F16,0)),0) | U16: =IF(13>=$C16,$B16/12*(1+'Assumptions'!$B$26)*(1+'Assumptions'!$B$27)^1*(1-IF(13<=$G16,$F16,0)),0) | V16: =IF(14>=$C16,$B16/12*(1+'Assumptions'!$B$26)*(1+'Assumptions'!$B$27)^1*(1-IF(14<=$G16,$F16,0)),0) | W16: =IF(15>=$C16,$B16/12*(1+'Assumptions'!$B$26)*(1+'Assumptions'!$B$27)^1*(1-IF(15<=$G16,$F16,0)),0) | X16: =IF(16>=$C16,$B16/12*(1+'Assumptions'!$B$26)*(1+'Assumptions'!$B$27)^1*(1-IF(16<=$G16,$F16,0)),0) | Y16: =IF(17>=$C16,$B16/12*(1+'Assumptions'!$B$26)*(1+'Assumptions'!$B$27)^1*(1-IF(17<=$G16,$F16,0)),0) | Z16: =IF(18>=$C16,$B16/12*(1+'Assumptions'!$B$26)*(1+'Assumptions'!$B$27)^1*(1-IF(18<=$G16,$F16,0)),0) | AA16: =IF(19>=$C16,$B16/12*(1+'Assumptions'!$B$26)*(1+'Assumptions'!$B$27)^1*(1-IF(19<=$G16,$F16,0)),0) | AB16: =IF(20>=$C16,$B16/12*(1+'Assumptions'!$B$26)*(1+'Assumptions'!$B$27)^1*(1-IF(20<=$G16,$F16,0)),0) | AC16: =IF(21>=$C16,$B16/12*(1+'Assumptions'!$B$26)*(1+'Assumptions'!$B$27)^1*(1-IF(21<=$G16,$F16,0)),0) | AD16: =IF(22>=$C16,$B16/12*(1+'Assumptions'!$B$26)*(1+'Assumptions'!$B$27)^1*(1-IF(22<=$G16,$F16,0)),0) | AE16: =IF(23>=$C16,$B16/12*(1+'Assumptions'!$B$26)*(1+'Assumptions'!$B$27)^1*(1-IF(23<=$G16,$F16,0)),0) | AF16: =IF(24>=$C16,$B16/12*(1+'Assumptions'!$B$26)*(1+'Assumptions'!$B$27)^1*(1-IF(24<=$G16,$F16,0)),0) | AG16: =IF(25>=$C16,$B16/12*(1+'Assumptions'!$B$26)*(1+'Assumptions'!$B$27)^2*(1-IF(25<=$G16,$F16,0)),0) | AH16: =IF(26>=$C16,$B16/12*(1+'Assumptions'!$B$26)*(1+'Assumptions'!$B$27)^2*(1-IF(26<=$G16,$F16,0)),0) | AI16: =IF(27>=$C16,$B16/12*(1+'Assumptions'!$B$26)*(1+'Assumptions'!$B$27)^2*(1-IF(27<=$G16,$F16,0)),0) | AJ16: =IF(28>=$C16,$B16/12*(1+'Assumptions'!$B$26)*(1+'Assumptions'!$B$27)^2*(1-IF(28<=$G16,$F16,0)),0) | AK16: =IF(29>=$C16,$B16/12*(1+'Assumptions'!$B$26)*(1+'Assumptions'!$B$27)^2*(1-IF(29<=$G16,$F16,0)),0) | AL16: =IF(30>=$C16,$B16/12*(1+'Assumptions'!$B$26)*(1+'Assumptions'!$B$27)^2*(1-IF(30<=$G16,$F16,0)),0) | AM16: =IF(31>=$C16,$B16/12*(1+'Assumptions'!$B$26)*(1+'Assumptions'!$B$27)^2*(1-IF(31<=$G16,$F16,0)),0) | AN16: =IF(32>=$C16,$B16/12*(1+'Assumptions'!$B$26)*(1+'Assumptions'!$B$27)^2*(1-IF(32<=$G16,$F16,0)),0) | AO16: =IF(33>=$C16,$B16/12*(1+'Assumptions'!$B$26)*(1+'Assumptions'!$B$27)^2*(1-IF(33<=$G16,$F16,0)),0) | AP16: =IF(34>=$C16,$B16/12*(1+'Assumptions'!$B$26)*(1+'Assumptions'!$B$27)^2*(1-IF(34<=$G16,$F16,0)),0) | AQ16: =IF(35>=$C16,$B16/12*(1+'Assumptions'!$B$26)*(1+'Assumptions'!$B$27)^2*(1-IF(35<=$G16,$F16,0)),0) | AR16: =IF(36>=$C16,$B16/12*(1+'Assumptions'!$B$26)*(1+'Assumptions'!$B$27)^2*(1-IF(36<=$G16,$F16,0)),0)
A17: Capacity hire - 3rd RN - RN Case Manager (capacity-driv [census-triggered - slip if ramp lags] | B17: 76256 | C17: 4 | D17: D | E17: 3 | F17: =IF(0,'Assumptions'!$B$28,0) | G17: ='Assumptions'!$B$29 | I17: =IF(1>=$C17,$B17/12*(1+'Assumptions'!$B$26)*(1+'Assumptions'!$B$27)^0*(1-IF(1<=$G17,$F17,0)),0) | J17: =IF(2>=$C17,$B17/12*(1+'Assumptions'!$B$26)*(1+'Assumptions'!$B$27)^0*(1-IF(2<=$G17,$F17,0)),0) | K17: =IF(3>=$C17,$B17/12*(1+'Assumptions'!$B$26)*(1+'Assumptions'!$B$27)^0*(1-IF(3<=$G17,$F17,0)),0) | L17: =IF(4>=$C17,$B17/12*(1+'Assumptions'!$B$26)*(1+'Assumptions'!$B$27)^0*(1-IF(4<=$G17,$F17,0)),0) | M17: =IF(5>=$C17,$B17/12*(1+'Assumptions'!$B$26)*(1+'Assumptions'!$B$27)^0*(1-IF(5<=$G17,$F17,0)),0) | N17: =IF(6>=$C17,$B17/12*(1+'Assumptions'!$B$26)*(1+'Assumptions'!$B$27)^0*(1-IF(6<=$G17,$F17,0)),0) | O17: =IF(7>=$C17,$B17/12*(1+'Assumptions'!$B$26)*(1+'Assumptions'!$B$27)^0*(1-IF(7<=$G17,$F17,0)),0) | P17: =IF(8>=$C17,$B17/12*(1+'Assumptions'!$B$26)*(1+'Assumptions'!$B$27)^0*(1-IF(8<=$G17,$F17,0)),0) | Q17: =IF(9>=$C17,$B17/12*(1+'Assumptions'!$B$26)*(1+'Assumptions'!$B$27)^0*(1-IF(9<=$G17,$F17,0)),0) | R17: =IF(10>=$C17,$B17/12*(1+'Assumptions'!$B$26)*(1+'Assumptions'!$B$27)^0*(1-IF(10<=$G17,$F17,0)),0) | S17: =IF(11>=$C17,$B17/12*(1+'Assumptions'!$B$26)*(1+'Assumptions'!$B$27)^0*(1-IF(11<=$G17,$F17,0)),0) | T17: =IF(12>=$C17,$B17/12*(1+'Assumptions'!$B$26)*(1+'Assumptions'!$B$27)^0*(1-IF(12<=$G17,$F17,0)),0) | U17: =IF(13>=$C17,$B17/12*(1+'Assumptions'!$B$26)*(1+'Assumptions'!$B$27)^1*(1-IF(13<=$G17,$F17,0)),0) | V17: =IF(14>=$C17,$B17/12*(1+'Assumptions'!$B$26)*(1+'Assumptions'!$B$27)^1*(1-IF(14<=$G17,$F17,0)),0) | W17: =IF(15>=$C17,$B17/12*(1+'Assumptions'!$B$26)*(1+'Assumptions'!$B$27)^1*(1-IF(15<=$G17,$F17,0)),0) | X17: =IF(16>=$C17,$B17/12*(1+'Assumptions'!$B$26)*(1+'Assumptions'!$B$27)^1*(1-IF(16<=$G17,$F17,0)),0) | Y17: =IF(17>=$C17,$B17/12*(1+'Assumptions'!$B$26)*(1+'Assumptions'!$B$27)^1*(1-IF(17<=$G17,$F17,0)),0) | Z17: =IF(18>=$C17,$B17/12*(1+'Assumptions'!$B$26)*(1+'Assumptions'!$B$27)^1*(1-IF(18<=$G17,$F17,0)),0) | AA17: =IF(19>=$C17,$B17/12*(1+'Assumptions'!$B$26)*(1+'Assumptions'!$B$27)^1*(1-IF(19<=$G17,$F17,0)),0) | AB17: =IF(20>=$C17,$B17/12*(1+'Assumptions'!$B$26)*(1+'Assumptions'!$B$27)^1*(1-IF(20<=$G17,$F17,0)),0) | AC17: =IF(21>=$C17,$B17/12*(1+'Assumptions'!$B$26)*(1+'Assumptions'!$B$27)^1*(1-IF(21<=$G17,$F17,0)),0) | AD17: =IF(22>=$C17,$B17/12*(1+'Assumptions'!$B$26)*(1+'Assumptions'!$B$27)^1*(1-IF(22<=$G17,$F17,0)),0) | AE17: =IF(23>=$C17,$B17/12*(1+'Assumptions'!$B$26)*(1+'Assumptions'!$B$27)^1*(1-IF(23<=$G17,$F17,0)),0) | AF17: =IF(24>=$C17,$B17/12*(1+'Assumptions'!$B$26)*(1+'Assumptions'!$B$27)^1*(1-IF(24<=$G17,$F17,0)),0) | AG17: =IF(25>=$C17,$B17/12*(1+'Assumptions'!$B$26)*(1+'Assumptions'!$B$27)^2*(1-IF(25<=$G17,$F17,0)),0) | AH17: =IF(26>=$C17,$B17/12*(1+'Assumptions'!$B$26)*(1+'Assumptions'!$B$27)^2*(1-IF(26<=$G17,$F17,0)),0) | AI17: =IF(27>=$C17,$B17/12*(1+'Assumptions'!$B$26)*(1+'Assumptions'!$B$27)^2*(1-IF(27<=$G17,$F17,0)),0) | AJ17: =IF(28>=$C17,$B17/12*(1+'Assumptions'!$B$26)*(1+'Assumptions'!$B$27)^2*(1-IF(28<=$G17,$F17,0)),0) | AK17: =IF(29>=$C17,$B17/12*(1+'Assumptions'!$B$26)*(1+'Assumptions'!$B$27)^2*(1-IF(29<=$G17,$F17,0)),0) | AL17: =IF(30>=$C17,$B17/12*(1+'Assumptions'!$B$26)*(1+'Assumptions'!$B$27)^2*(1-IF(30<=$G17,$F17,0)),0) | AM17: =IF(31>=$C17,$B17/12*(1+'Assumptions'!$B$26)*(1+'Assumptions'!$B$27)^2*(1-IF(31<=$G17,$F17,0)),0) | AN17: =IF(32>=$C17,$B17/12*(1+'Assumptions'!$B$26)*(1+'Assumptions'!$B$27)^2*(1-IF(32<=$G17,$F17,0)),0) | AO17: =IF(33>=$C17,$B17/12*(1+'Assumptions'!$B$26)*(1+'Assumptions'!$B$27)^2*(1-IF(33<=$G17,$F17,0)),0) | AP17: =IF(34>=$C17,$B17/12*(1+'Assumptions'!$B$26)*(1+'Assumptions'!$B$27)^2*(1-IF(34<=$G17,$F17,0)),0) | AQ17: =IF(35>=$C17,$B17/12*(1+'Assumptions'!$B$26)*(1+'Assumptions'!$B$27)^2*(1-IF(35<=$G17,$F17,0)),0) | AR17: =IF(36>=$C17,$B17/12*(1+'Assumptions'!$B$26)*(1+'Assumptions'!$B$27)^2*(1-IF(36<=$G17,$F17,0)),0)
A18: Capacity hire - 3rd CNA - CNA / Hospice Aide (capacity-d [census-triggered - slip if ramp lags] | B18: 46511 | C18: 5 | D18: D | E18: 3 | F18: =IF(0,'Assumptions'!$B$28,0) | G18: ='Assumptions'!$B$29 | I18: =IF(1>=$C18,$B18/12*(1+'Assumptions'!$B$26)*(1+'Assumptions'!$B$27)^0*(1-IF(1<=$G18,$F18,0)),0) | J18: =IF(2>=$C18,$B18/12*(1+'Assumptions'!$B$26)*(1+'Assumptions'!$B$27)^0*(1-IF(2<=$G18,$F18,0)),0) | K18: =IF(3>=$C18,$B18/12*(1+'Assumptions'!$B$26)*(1+'Assumptions'!$B$27)^0*(1-IF(3<=$G18,$F18,0)),0) | L18: =IF(4>=$C18,$B18/12*(1+'Assumptions'!$B$26)*(1+'Assumptions'!$B$27)^0*(1-IF(4<=$G18,$F18,0)),0) | M18: =IF(5>=$C18,$B18/12*(1+'Assumptions'!$B$26)*(1+'Assumptions'!$B$27)^0*(1-IF(5<=$G18,$F18,0)),0) | N18: =IF(6>=$C18,$B18/12*(1+'Assumptions'!$B$26)*(1+'Assumptions'!$B$27)^0*(1-IF(6<=$G18,$F18,0)),0) | O18: =IF(7>=$C18,$B18/12*(1+'Assumptions'!$B$26)*(1+'Assumptions'!$B$27)^0*(1-IF(7<=$G18,$F18,0)),0) | P18: =IF(8>=$C18,$B18/12*(1+'Assumptions'!$B$26)*(1+'Assumptions'!$B$27)^0*(1-IF(8<=$G18,$F18,0)),0) | Q18: =IF(9>=$C18,$B18/12*(1+'Assumptions'!$B$26)*(1+'Assumptions'!$B$27)^0*(1-IF(9<=$G18,$F18,0)),0) | R18: =IF(10>=$C18,$B18/12*(1+'Assumptions'!$B$26)*(1+'Assumptions'!$B$27)^0*(1-IF(10<=$G18,$F18,0)),0) | S18: =IF(11>=$C18,$B18/12*(1+'Assumptions'!$B$26)*(1+'Assumptions'!$B$27)^0*(1-IF(11<=$G18,$F18,0)),0) | T18: =IF(12>=$C18,$B18/12*(1+'Assumptions'!$B$26)*(1+'Assumptions'!$B$27)^0*(1-IF(12<=$G18,$F18,0)),0) | U18: =IF(13>=$C18,$B18/12*(1+'Assumptions'!$B$26)*(1+'Assumptions'!$B$27)^1*(1-IF(13<=$G18,$F18,0)),0) | V18: =IF(14>=$C18,$B18/12*(1+'Assumptions'!$B$26)*(1+'Assumptions'!$B$27)^1*(1-IF(14<=$G18,$F18,0)),0) | W18: =IF(15>=$C18,$B18/12*(1+'Assumptions'!$B$26)*(1+'Assumptions'!$B$27)^1*(1-IF(15<=$G18,$F18,0)),0) | X18: =IF(16>=$C18,$B18/12*(1+'Assumptions'!$B$26)*(1+'Assumptions'!$B$27)^1*(1-IF(16<=$G18,$F18,0)),0) | Y18: =IF(17>=$C18,$B18/12*(1+'Assumptions'!$B$26)*(1+'Assumptions'!$B$27)^1*(1-IF(17<=$G18,$F18,0)),0) | Z18: =IF(18>=$C18,$B18/12*(1+'Assumptions'!$B$26)*(1+'Assumptions'!$B$27)^1*(1-IF(18<=$G18,$F18,0)),0) | AA18: =IF(19>=$C18,$B18/12*(1+'Assumptions'!$B$26)*(1+'Assumptions'!$B$27)^1*(1-IF(19<=$G18,$F18,0)),0) | AB18: =IF(20>=$C18,$B18/12*(1+'Assumptions'!$B$26)*(1+'Assumptions'!$B$27)^1*(1-IF(20<=$G18,$F18,0)),0) | AC18: =IF(21>=$C18,$B18/12*(1+'Assumptions'!$B$26)*(1+'Assumptions'!$B$27)^1*(1-IF(21<=$G18,$F18,0)),0) | AD18: =IF(22>=$C18,$B18/12*(1+'Assumptions'!$B$26)*(1+'Assumptions'!$B$27)^1*(1-IF(22<=$G18,$F18,0)),0) | AE18: =IF(23>=$C18,$B18/12*(1+'Assumptions'!$B$26)*(1+'Assumptions'!$B$27)^1*(1-IF(23<=$G18,$F18,0)),0) | AF18: =IF(24>=$C18,$B18/12*(1+'Assumptions'!$B$26)*(1+'Assumptions'!$B$27)^1*(1-IF(24<=$G18,$F18,0)),0) | AG18: =IF(25>=$C18,$B18/12*(1+'Assumptions'!$B$26)*(1+'Assumptions'!$B$27)^2*(1-IF(25<=$G18,$F18,0)),0) | AH18: =IF(26>=$C18,$B18/12*(1+'Assumptions'!$B$26)*(1+'Assumptions'!$B$27)^2*(1-IF(26<=$G18,$F18,0)),0) | AI18: =IF(27>=$C18,$B18/12*(1+'Assumptions'!$B$26)*(1+'Assumptions'!$B$27)^2*(1-IF(27<=$G18,$F18,0)),0) | AJ18: =IF(28>=$C18,$B18/12*(1+'Assumptions'!$B$26)*(1+'Assumptions'!$B$27)^2*(1-IF(28<=$G18,$F18,0)),0) | AK18: =IF(29>=$C18,$B18/12*(1+'Assumptions'!$B$26)*(1+'Assumptions'!$B$27)^2*(1-IF(29<=$G18,$F18,0)),0) | AL18: =IF(30>=$C18,$B18/12*(1+'Assumptions'!$B$26)*(1+'Assumptions'!$B$27)^2*(1-IF(30<=$G18,$F18,0)),0) | AM18: =IF(31>=$C18,$B18/12*(1+'Assumptions'!$B$26)*(1+'Assumptions'!$B$27)^2*(1-IF(31<=$G18,$F18,0)),0) | AN18: =IF(32>=$C18,$B18/12*(1+'Assumptions'!$B$26)*(1+'Assumptions'!$B$27)^2*(1-IF(32<=$G18,$F18,0)),0) | AO18: =IF(33>=$C18,$B18/12*(1+'Assumptions'!$B$26)*(1+'Assumptions'!$B$27)^2*(1-IF(33<=$G18,$F18,0)),0) | AP18: =IF(34>=$C18,$B18/12*(1+'Assumptions'!$B$26)*(1+'Assumptions'!$B$27)^2*(1-IF(34<=$G18,$F18,0)),0) | AQ18: =IF(35>=$C18,$B18/12*(1+'Assumptions'!$B$26)*(1+'Assumptions'!$B$27)^2*(1-IF(35<=$G18,$F18,0)),0) | AR18: =IF(36>=$C18,$B18/12*(1+'Assumptions'!$B$26)*(1+'Assumptions'!$B$27)^2*(1-IF(36<=$G18,$F18,0)),0)
A19: Capacity hire - 4th RN - RN Case Manager (capacity-driv [census-triggered - slip if ramp lags] | B19: 76256 | C19: 11 | D19: D | E19: 3 | F19: =IF(0,'Assumptions'!$B$28,0) | G19: ='Assumptions'!$B$29 | I19: =IF(1>=$C19,$B19/12*(1+'Assumptions'!$B$26)*(1+'Assumptions'!$B$27)^0*(1-IF(1<=$G19,$F19,0)),0) | J19: =IF(2>=$C19,$B19/12*(1+'Assumptions'!$B$26)*(1+'Assumptions'!$B$27)^0*(1-IF(2<=$G19,$F19,0)),0) | K19: =IF(3>=$C19,$B19/12*(1+'Assumptions'!$B$26)*(1+'Assumptions'!$B$27)^0*(1-IF(3<=$G19,$F19,0)),0) | L19: =IF(4>=$C19,$B19/12*(1+'Assumptions'!$B$26)*(1+'Assumptions'!$B$27)^0*(1-IF(4<=$G19,$F19,0)),0) | M19: =IF(5>=$C19,$B19/12*(1+'Assumptions'!$B$26)*(1+'Assumptions'!$B$27)^0*(1-IF(5<=$G19,$F19,0)),0) | N19: =IF(6>=$C19,$B19/12*(1+'Assumptions'!$B$26)*(1+'Assumptions'!$B$27)^0*(1-IF(6<=$G19,$F19,0)),0) | O19: =IF(7>=$C19,$B19/12*(1+'Assumptions'!$B$26)*(1+'Assumptions'!$B$27)^0*(1-IF(7<=$G19,$F19,0)),0) | P19: =IF(8>=$C19,$B19/12*(1+'Assumptions'!$B$26)*(1+'Assumptions'!$B$27)^0*(1-IF(8<=$G19,$F19,0)),0) | Q19: =IF(9>=$C19,$B19/12*(1+'Assumptions'!$B$26)*(1+'Assumptions'!$B$27)^0*(1-IF(9<=$G19,$F19,0)),0) | R19: =IF(10>=$C19,$B19/12*(1+'Assumptions'!$B$26)*(1+'Assumptions'!$B$27)^0*(1-IF(10<=$G19,$F19,0)),0) | S19: =IF(11>=$C19,$B19/12*(1+'Assumptions'!$B$26)*(1+'Assumptions'!$B$27)^0*(1-IF(11<=$G19,$F19,0)),0) | T19: =IF(12>=$C19,$B19/12*(1+'Assumptions'!$B$26)*(1+'Assumptions'!$B$27)^0*(1-IF(12<=$G19,$F19,0)),0) | U19: =IF(13>=$C19,$B19/12*(1+'Assumptions'!$B$26)*(1+'Assumptions'!$B$27)^1*(1-IF(13<=$G19,$F19,0)),0) | V19: =IF(14>=$C19,$B19/12*(1+'Assumptions'!$B$26)*(1+'Assumptions'!$B$27)^1*(1-IF(14<=$G19,$F19,0)),0) | W19: =IF(15>=$C19,$B19/12*(1+'Assumptions'!$B$26)*(1+'Assumptions'!$B$27)^1*(1-IF(15<=$G19,$F19,0)),0) | X19: =IF(16>=$C19,$B19/12*(1+'Assumptions'!$B$26)*(1+'Assumptions'!$B$27)^1*(1-IF(16<=$G19,$F19,0)),0) | Y19: =IF(17>=$C19,$B19/12*(1+'Assumptions'!$B$26)*(1+'Assumptions'!$B$27)^1*(1-IF(17<=$G19,$F19,0)),0) | Z19: =IF(18>=$C19,$B19/12*(1+'Assumptions'!$B$26)*(1+'Assumptions'!$B$27)^1*(1-IF(18<=$G19,$F19,0)),0) | AA19: =IF(19>=$C19,$B19/12*(1+'Assumptions'!$B$26)*(1+'Assumptions'!$B$27)^1*(1-IF(19<=$G19,$F19,0)),0) | AB19: =IF(20>=$C19,$B19/12*(1+'Assumptions'!$B$26)*(1+'Assumptions'!$B$27)^1*(1-IF(20<=$G19,$F19,0)),0) | AC19: =IF(21>=$C19,$B19/12*(1+'Assumptions'!$B$26)*(1+'Assumptions'!$B$27)^1*(1-IF(21<=$G19,$F19,0)),0) | AD19: =IF(22>=$C19,$B19/12*(1+'Assumptions'!$B$26)*(1+'Assumptions'!$B$27)^1*(1-IF(22<=$G19,$F19,0)),0) | AE19: =IF(23>=$C19,$B19/12*(1+'Assumptions'!$B$26)*(1+'Assumptions'!$B$27)^1*(1-IF(23<=$G19,$F19,0)),0) | AF19: =IF(24>=$C19,$B19/12*(1+'Assumptions'!$B$26)*(1+'Assumptions'!$B$27)^1*(1-IF(24<=$G19,$F19,0)),0) | AG19: =IF(25>=$C19,$B19/12*(1+'Assumptions'!$B$26)*(1+'Assumptions'!$B$27)^2*(1-IF(25<=$G19,$F19,0)),0) | AH19: =IF(26>=$C19,$B19/12*(1+'Assumptions'!$B$26)*(1+'Assumptions'!$B$27)^2*(1-IF(26<=$G19,$F19,0)),0) | AI19: =IF(27>=$C19,$B19/12*(1+'Assumptions'!$B$26)*(1+'Assumptions'!$B$27)^2*(1-IF(27<=$G19,$F19,0)),0) | AJ19: =IF(28>=$C19,$B19/12*(1+'Assumptions'!$B$26)*(1+'Assumptions'!$B$27)^2*(1-IF(28<=$G19,$F19,0)),0) | AK19: =IF(29>=$C19,$B19/12*(1+'Assumptions'!$B$26)*(1+'Assumptions'!$B$27)^2*(1-IF(29<=$G19,$F19,0)),0) | AL19: =IF(30>=$C19,$B19/12*(1+'Assumptions'!$B$26)*(1+'Assumptions'!$B$27)^2*(1-IF(30<=$G19,$F19,0)),0) | AM19: =IF(31>=$C19,$B19/12*(1+'Assumptions'!$B$26)*(1+'Assumptions'!$B$27)^2*(1-IF(31<=$G19,$F19,0)),0) | AN19: =IF(32>=$C19,$B19/12*(1+'Assumptions'!$B$26)*(1+'Assumptions'!$B$27)^2*(1-IF(32<=$G19,$F19,0)),0) | AO19: =IF(33>=$C19,$B19/12*(1+'Assumptions'!$B$26)*(1+'Assumptions'!$B$27)^2*(1-IF(33<=$G19,$F19,0)),0) | AP19: =IF(34>=$C19,$B19/12*(1+'Assumptions'!$B$26)*(1+'Assumptions'!$B$27)^2*(1-IF(34<=$G19,$F19,0)),0) | AQ19: =IF(35>=$C19,$B19/12*(1+'Assumptions'!$B$26)*(1+'Assumptions'!$B$27)^2*(1-IF(35<=$G19,$F19,0)),0) | AR19: =IF(36>=$C19,$B19/12*(1+'Assumptions'!$B$26)*(1+'Assumptions'!$B$27)^2*(1-IF(36<=$G19,$F19,0)),0)
A20: Capacity hire - 4th CNA - CNA / Hospice Aide (capacity-d [census-triggered - slip if ramp lags] | B20: 46511 | C20: 13 | D20: D | E20: 3 | F20: =IF(0,'Assumptions'!$B$28,0) | G20: ='Assumptions'!$B$29 | I20: =IF(1>=$C20,$B20/12*(1+'Assumptions'!$B$26)*(1+'Assumptions'!$B$27)^0*(1-IF(1<=$G20,$F20,0)),0) | J20: =IF(2>=$C20,$B20/12*(1+'Assumptions'!$B$26)*(1+'Assumptions'!$B$27)^0*(1-IF(2<=$G20,$F20,0)),0) | K20: =IF(3>=$C20,$B20/12*(1+'Assumptions'!$B$26)*(1+'Assumptions'!$B$27)^0*(1-IF(3<=$G20,$F20,0)),0) | L20: =IF(4>=$C20,$B20/12*(1+'Assumptions'!$B$26)*(1+'Assumptions'!$B$27)^0*(1-IF(4<=$G20,$F20,0)),0) | M20: =IF(5>=$C20,$B20/12*(1+'Assumptions'!$B$26)*(1+'Assumptions'!$B$27)^0*(1-IF(5<=$G20,$F20,0)),0) | N20: =IF(6>=$C20,$B20/12*(1+'Assumptions'!$B$26)*(1+'Assumptions'!$B$27)^0*(1-IF(6<=$G20,$F20,0)),0) | O20: =IF(7>=$C20,$B20/12*(1+'Assumptions'!$B$26)*(1+'Assumptions'!$B$27)^0*(1-IF(7<=$G20,$F20,0)),0) | P20: =IF(8>=$C20,$B20/12*(1+'Assumptions'!$B$26)*(1+'Assumptions'!$B$27)^0*(1-IF(8<=$G20,$F20,0)),0) | Q20: =IF(9>=$C20,$B20/12*(1+'Assumptions'!$B$26)*(1+'Assumptions'!$B$27)^0*(1-IF(9<=$G20,$F20,0)),0) | R20: =IF(10>=$C20,$B20/12*(1+'Assumptions'!$B$26)*(1+'Assumptions'!$B$27)^0*(1-IF(10<=$G20,$F20,0)),0) | S20: =IF(11>=$C20,$B20/12*(1+'Assumptions'!$B$26)*(1+'Assumptions'!$B$27)^0*(1-IF(11<=$G20,$F20,0)),0) | T20: =IF(12>=$C20,$B20/12*(1+'Assumptions'!$B$26)*(1+'Assumptions'!$B$27)^0*(1-IF(12<=$G20,$F20,0)),0) | U20: =IF(13>=$C20,$B20/12*(1+'Assumptions'!$B$26)*(1+'Assumptions'!$B$27)^1*(1-IF(13<=$G20,$F20,0)),0) | V20: =IF(14>=$C20,$B20/12*(1+'Assumptions'!$B$26)*(1+'Assumptions'!$B$27)^1*(1-IF(14<=$G20,$F20,0)),0) | W20: =IF(15>=$C20,$B20/12*(1+'Assumptions'!$B$26)*(1+'Assumptions'!$B$27)^1*(1-IF(15<=$G20,$F20,0)),0) | X20: =IF(16>=$C20,$B20/12*(1+'Assumptions'!$B$26)*(1+'Assumptions'!$B$27)^1*(1-IF(16<=$G20,$F20,0)),0) | Y20: =IF(17>=$C20,$B20/12*(1+'Assumptions'!$B$26)*(1+'Assumptions'!$B$27)^1*(1-IF(17<=$G20,$F20,0)),0) | Z20: =IF(18>=$C20,$B20/12*(1+'Assumptions'!$B$26)*(1+'Assumptions'!$B$27)^1*(1-IF(18<=$G20,$F20,0)),0) | AA20: =IF(19>=$C20,$B20/12*(1+'Assumptions'!$B$26)*(1+'Assumptions'!$B$27)^1*(1-IF(19<=$G20,$F20,0)),0) | AB20: =IF(20>=$C20,$B20/12*(1+'Assumptions'!$B$26)*(1+'Assumptions'!$B$27)^1*(1-IF(20<=$G20,$F20,0)),0) | AC20: =IF(21>=$C20,$B20/12*(1+'Assumptions'!$B$26)*(1+'Assumptions'!$B$27)^1*(1-IF(21<=$G20,$F20,0)),0) | AD20: =IF(22>=$C20,$B20/12*(1+'Assumptions'!$B$26)*(1+'Assumptions'!$B$27)^1*(1-IF(22<=$G20,$F20,0)),0) | AE20: =IF(23>=$C20,$B20/12*(1+'Assumptions'!$B$26)*(1+'Assumptions'!$B$27)^1*(1-IF(23<=$G20,$F20,0)),0) | AF20: =IF(24>=$C20,$B20/12*(1+'Assumptions'!$B$26)*(1+'Assumptions'!$B$27)^1*(1-IF(24<=$G20,$F20,0)),0) | AG20: =IF(25>=$C20,$B20/12*(1+'Assumptions'!$B$26)*(1+'Assumptions'!$B$27)^2*(1-IF(25<=$G20,$F20,0)),0) | AH20: =IF(26>=$C20,$B20/12*(1+'Assumptions'!$B$26)*(1+'Assumptions'!$B$27)^2*(1-IF(26<=$G20,$F20,0)),0) | AI20: =IF(27>=$C20,$B20/12*(1+'Assumptions'!$B$26)*(1+'Assumptions'!$B$27)^2*(1-IF(27<=$G20,$F20,0)),0) | AJ20: =IF(28>=$C20,$B20/12*(1+'Assumptions'!$B$26)*(1+'Assumptions'!$B$27)^2*(1-IF(28<=$G20,$F20,0)),0) | AK20: =IF(29>=$C20,$B20/12*(1+'Assumptions'!$B$26)*(1+'Assumptions'!$B$27)^2*(1-IF(29<=$G20,$F20,0)),0) | AL20: =IF(30>=$C20,$B20/12*(1+'Assumptions'!$B$26)*(1+'Assumptions'!$B$27)^2*(1-IF(30<=$G20,$F20,0)),0) | AM20: =IF(31>=$C20,$B20/12*(1+'Assumptions'!$B$26)*(1+'Assumptions'!$B$27)^2*(1-IF(31<=$G20,$F20,0)),0) | AN20: =IF(32>=$C20,$B20/12*(1+'Assumptions'!$B$26)*(1+'Assumptions'!$B$27)^2*(1-IF(32<=$G20,$F20,0)),0) | AO20: =IF(33>=$C20,$B20/12*(1+'Assumptions'!$B$26)*(1+'Assumptions'!$B$27)^2*(1-IF(33<=$G20,$F20,0)),0) | AP20: =IF(34>=$C20,$B20/12*(1+'Assumptions'!$B$26)*(1+'Assumptions'!$B$27)^2*(1-IF(34<=$G20,$F20,0)),0) | AQ20: =IF(35>=$C20,$B20/12*(1+'Assumptions'!$B$26)*(1+'Assumptions'!$B$27)^2*(1-IF(35<=$G20,$F20,0)),0) | AR20: =IF(36>=$C20,$B20/12*(1+'Assumptions'!$B$26)*(1+'Assumptions'!$B$27)^2*(1-IF(36<=$G20,$F20,0)),0)
A21: Capacity hire - 5th RN - RN Case Manager (capacity-driv [census-triggered - slip if ramp lags] | B21: 76256 | C21: 23 | D21: D | E21: 3 | F21: =IF(0,'Assumptions'!$B$28,0) | G21: ='Assumptions'!$B$29 | I21: =IF(1>=$C21,$B21/12*(1+'Assumptions'!$B$26)*(1+'Assumptions'!$B$27)^0*(1-IF(1<=$G21,$F21,0)),0) | J21: =IF(2>=$C21,$B21/12*(1+'Assumptions'!$B$26)*(1+'Assumptions'!$B$27)^0*(1-IF(2<=$G21,$F21,0)),0) | K21: =IF(3>=$C21,$B21/12*(1+'Assumptions'!$B$26)*(1+'Assumptions'!$B$27)^0*(1-IF(3<=$G21,$F21,0)),0) | L21: =IF(4>=$C21,$B21/12*(1+'Assumptions'!$B$26)*(1+'Assumptions'!$B$27)^0*(1-IF(4<=$G21,$F21,0)),0) | M21: =IF(5>=$C21,$B21/12*(1+'Assumptions'!$B$26)*(1+'Assumptions'!$B$27)^0*(1-IF(5<=$G21,$F21,0)),0) | N21: =IF(6>=$C21,$B21/12*(1+'Assumptions'!$B$26)*(1+'Assumptions'!$B$27)^0*(1-IF(6<=$G21,$F21,0)),0) | O21: =IF(7>=$C21,$B21/12*(1+'Assumptions'!$B$26)*(1+'Assumptions'!$B$27)^0*(1-IF(7<=$G21,$F21,0)),0) | P21: =IF(8>=$C21,$B21/12*(1+'Assumptions'!$B$26)*(1+'Assumptions'!$B$27)^0*(1-IF(8<=$G21,$F21,0)),0) | Q21: =IF(9>=$C21,$B21/12*(1+'Assumptions'!$B$26)*(1+'Assumptions'!$B$27)^0*(1-IF(9<=$G21,$F21,0)),0) | R21: =IF(10>=$C21,$B21/12*(1+'Assumptions'!$B$26)*(1+'Assumptions'!$B$27)^0*(1-IF(10<=$G21,$F21,0)),0) | S21: =IF(11>=$C21,$B21/12*(1+'Assumptions'!$B$26)*(1+'Assumptions'!$B$27)^0*(1-IF(11<=$G21,$F21,0)),0) | T21: =IF(12>=$C21,$B21/12*(1+'Assumptions'!$B$26)*(1+'Assumptions'!$B$27)^0*(1-IF(12<=$G21,$F21,0)),0) | U21: =IF(13>=$C21,$B21/12*(1+'Assumptions'!$B$26)*(1+'Assumptions'!$B$27)^1*(1-IF(13<=$G21,$F21,0)),0) | V21: =IF(14>=$C21,$B21/12*(1+'Assumptions'!$B$26)*(1+'Assumptions'!$B$27)^1*(1-IF(14<=$G21,$F21,0)),0) | W21: =IF(15>=$C21,$B21/12*(1+'Assumptions'!$B$26)*(1+'Assumptions'!$B$27)^1*(1-IF(15<=$G21,$F21,0)),0) | X21: =IF(16>=$C21,$B21/12*(1+'Assumptions'!$B$26)*(1+'Assumptions'!$B$27)^1*(1-IF(16<=$G21,$F21,0)),0) | Y21: =IF(17>=$C21,$B21/12*(1+'Assumptions'!$B$26)*(1+'Assumptions'!$B$27)^1*(1-IF(17<=$G21,$F21,0)),0) | Z21: =IF(18>=$C21,$B21/12*(1+'Assumptions'!$B$26)*(1+'Assumptions'!$B$27)^1*(1-IF(18<=$G21,$F21,0)),0) | AA21: =IF(19>=$C21,$B21/12*(1+'Assumptions'!$B$26)*(1+'Assumptions'!$B$27)^1*(1-IF(19<=$G21,$F21,0)),0) | AB21: =IF(20>=$C21,$B21/12*(1+'Assumptions'!$B$26)*(1+'Assumptions'!$B$27)^1*(1-IF(20<=$G21,$F21,0)),0) | AC21: =IF(21>=$C21,$B21/12*(1+'Assumptions'!$B$26)*(1+'Assumptions'!$B$27)^1*(1-IF(21<=$G21,$F21,0)),0) | AD21: =IF(22>=$C21,$B21/12*(1+'Assumptions'!$B$26)*(1+'Assumptions'!$B$27)^1*(1-IF(22<=$G21,$F21,0)),0) | AE21: =IF(23>=$C21,$B21/12*(1+'Assumptions'!$B$26)*(1+'Assumptions'!$B$27)^1*(1-IF(23<=$G21,$F21,0)),0) | AF21: =IF(24>=$C21,$B21/12*(1+'Assumptions'!$B$26)*(1+'Assumptions'!$B$27)^1*(1-IF(24<=$G21,$F21,0)),0) | AG21: =IF(25>=$C21,$B21/12*(1+'Assumptions'!$B$26)*(1+'Assumptions'!$B$27)^2*(1-IF(25<=$G21,$F21,0)),0) | AH21: =IF(26>=$C21,$B21/12*(1+'Assumptions'!$B$26)*(1+'Assumptions'!$B$27)^2*(1-IF(26<=$G21,$F21,0)),0) | AI21: =IF(27>=$C21,$B21/12*(1+'Assumptions'!$B$26)*(1+'Assumptions'!$B$27)^2*(1-IF(27<=$G21,$F21,0)),0) | AJ21: =IF(28>=$C21,$B21/12*(1+'Assumptions'!$B$26)*(1+'Assumptions'!$B$27)^2*(1-IF(28<=$G21,$F21,0)),0) | AK21: =IF(29>=$C21,$B21/12*(1+'Assumptions'!$B$26)*(1+'Assumptions'!$B$27)^2*(1-IF(29<=$G21,$F21,0)),0) | AL21: =IF(30>=$C21,$B21/12*(1+'Assumptions'!$B$26)*(1+'Assumptions'!$B$27)^2*(1-IF(30<=$G21,$F21,0)),0) | AM21: =IF(31>=$C21,$B21/12*(1+'Assumptions'!$B$26)*(1+'Assumptions'!$B$27)^2*(1-IF(31<=$G21,$F21,0)),0) | AN21: =IF(32>=$C21,$B21/12*(1+'Assumptions'!$B$26)*(1+'Assumptions'!$B$27)^2*(1-IF(32<=$G21,$F21,0)),0) | AO21: =IF(33>=$C21,$B21/12*(1+'Assumptions'!$B$26)*(1+'Assumptions'!$B$27)^2*(1-IF(33<=$G21,$F21,0)),0) | AP21: =IF(34>=$C21,$B21/12*(1+'Assumptions'!$B$26)*(1+'Assumptions'!$B$27)^2*(1-IF(34<=$G21,$F21,0)),0) | AQ21: =IF(35>=$C21,$B21/12*(1+'Assumptions'!$B$26)*(1+'Assumptions'!$B$27)^2*(1-IF(35<=$G21,$F21,0)),0) | AR21: =IF(36>=$C21,$B21/12*(1+'Assumptions'!$B$26)*(1+'Assumptions'!$B$27)^2*(1-IF(36<=$G21,$F21,0)),0)
A22: Capacity hire - 5th CNA - CNA / Hospice Aide (capacity-d [census-triggered - slip if ramp lags] | B22: 46511 | C22: 25 | D22: D | E22: 3 | F22: =IF(0,'Assumptions'!$B$28,0) | G22: ='Assumptions'!$B$29 | I22: =IF(1>=$C22,$B22/12*(1+'Assumptions'!$B$26)*(1+'Assumptions'!$B$27)^0*(1-IF(1<=$G22,$F22,0)),0) | J22: =IF(2>=$C22,$B22/12*(1+'Assumptions'!$B$26)*(1+'Assumptions'!$B$27)^0*(1-IF(2<=$G22,$F22,0)),0) | K22: =IF(3>=$C22,$B22/12*(1+'Assumptions'!$B$26)*(1+'Assumptions'!$B$27)^0*(1-IF(3<=$G22,$F22,0)),0) | L22: =IF(4>=$C22,$B22/12*(1+'Assumptions'!$B$26)*(1+'Assumptions'!$B$27)^0*(1-IF(4<=$G22,$F22,0)),0) | M22: =IF(5>=$C22,$B22/12*(1+'Assumptions'!$B$26)*(1+'Assumptions'!$B$27)^0*(1-IF(5<=$G22,$F22,0)),0) | N22: =IF(6>=$C22,$B22/12*(1+'Assumptions'!$B$26)*(1+'Assumptions'!$B$27)^0*(1-IF(6<=$G22,$F22,0)),0) | O22: =IF(7>=$C22,$B22/12*(1+'Assumptions'!$B$26)*(1+'Assumptions'!$B$27)^0*(1-IF(7<=$G22,$F22,0)),0) | P22: =IF(8>=$C22,$B22/12*(1+'Assumptions'!$B$26)*(1+'Assumptions'!$B$27)^0*(1-IF(8<=$G22,$F22,0)),0) | Q22: =IF(9>=$C22,$B22/12*(1+'Assumptions'!$B$26)*(1+'Assumptions'!$B$27)^0*(1-IF(9<=$G22,$F22,0)),0) | R22: =IF(10>=$C22,$B22/12*(1+'Assumptions'!$B$26)*(1+'Assumptions'!$B$27)^0*(1-IF(10<=$G22,$F22,0)),0) | S22: =IF(11>=$C22,$B22/12*(1+'Assumptions'!$B$26)*(1+'Assumptions'!$B$27)^0*(1-IF(11<=$G22,$F22,0)),0) | T22: =IF(12>=$C22,$B22/12*(1+'Assumptions'!$B$26)*(1+'Assumptions'!$B$27)^0*(1-IF(12<=$G22,$F22,0)),0) | U22: =IF(13>=$C22,$B22/12*(1+'Assumptions'!$B$26)*(1+'Assumptions'!$B$27)^1*(1-IF(13<=$G22,$F22,0)),0) | V22: =IF(14>=$C22,$B22/12*(1+'Assumptions'!$B$26)*(1+'Assumptions'!$B$27)^1*(1-IF(14<=$G22,$F22,0)),0) | W22: =IF(15>=$C22,$B22/12*(1+'Assumptions'!$B$26)*(1+'Assumptions'!$B$27)^1*(1-IF(15<=$G22,$F22,0)),0) | X22: =IF(16>=$C22,$B22/12*(1+'Assumptions'!$B$26)*(1+'Assumptions'!$B$27)^1*(1-IF(16<=$G22,$F22,0)),0) | Y22: =IF(17>=$C22,$B22/12*(1+'Assumptions'!$B$26)*(1+'Assumptions'!$B$27)^1*(1-IF(17<=$G22,$F22,0)),0) | Z22: =IF(18>=$C22,$B22/12*(1+'Assumptions'!$B$26)*(1+'Assumptions'!$B$27)^1*(1-IF(18<=$G22,$F22,0)),0) | AA22: =IF(19>=$C22,$B22/12*(1+'Assumptions'!$B$26)*(1+'Assumptions'!$B$27)^1*(1-IF(19<=$G22,$F22,0)),0) | AB22: =IF(20>=$C22,$B22/12*(1+'Assumptions'!$B$26)*(1+'Assumptions'!$B$27)^1*(1-IF(20<=$G22,$F22,0)),0) | AC22: =IF(21>=$C22,$B22/12*(1+'Assumptions'!$B$26)*(1+'Assumptions'!$B$27)^1*(1-IF(21<=$G22,$F22,0)),0) | AD22: =IF(22>=$C22,$B22/12*(1+'Assumptions'!$B$26)*(1+'Assumptions'!$B$27)^1*(1-IF(22<=$G22,$F22,0)),0) | AE22: =IF(23>=$C22,$B22/12*(1+'Assumptions'!$B$26)*(1+'Assumptions'!$B$27)^1*(1-IF(23<=$G22,$F22,0)),0) | AF22: =IF(24>=$C22,$B22/12*(1+'Assumptions'!$B$26)*(1+'Assumptions'!$B$27)^1*(1-IF(24<=$G22,$F22,0)),0) | AG22: =IF(25>=$C22,$B22/12*(1+'Assumptions'!$B$26)*(1+'Assumptions'!$B$27)^2*(1-IF(25<=$G22,$F22,0)),0) | AH22: =IF(26>=$C22,$B22/12*(1+'Assumptions'!$B$26)*(1+'Assumptions'!$B$27)^2*(1-IF(26<=$G22,$F22,0)),0) | AI22: =IF(27>=$C22,$B22/12*(1+'Assumptions'!$B$26)*(1+'Assumptions'!$B$27)^2*(1-IF(27<=$G22,$F22,0)),0) | AJ22: =IF(28>=$C22,$B22/12*(1+'Assumptions'!$B$26)*(1+'Assumptions'!$B$27)^2*(1-IF(28<=$G22,$F22,0)),0) | AK22: =IF(29>=$C22,$B22/12*(1+'Assumptions'!$B$26)*(1+'Assumptions'!$B$27)^2*(1-IF(29<=$G22,$F22,0)),0) | AL22: =IF(30>=$C22,$B22/12*(1+'Assumptions'!$B$26)*(1+'Assumptions'!$B$27)^2*(1-IF(30<=$G22,$F22,0)),0) | AM22: =IF(31>=$C22,$B22/12*(1+'Assumptions'!$B$26)*(1+'Assumptions'!$B$27)^2*(1-IF(31<=$G22,$F22,0)),0) | AN22: =IF(32>=$C22,$B22/12*(1+'Assumptions'!$B$26)*(1+'Assumptions'!$B$27)^2*(1-IF(32<=$G22,$F22,0)),0) | AO22: =IF(33>=$C22,$B22/12*(1+'Assumptions'!$B$26)*(1+'Assumptions'!$B$27)^2*(1-IF(33<=$G22,$F22,0)),0) | AP22: =IF(34>=$C22,$B22/12*(1+'Assumptions'!$B$26)*(1+'Assumptions'!$B$27)^2*(1-IF(34<=$G22,$F22,0)),0) | AQ22: =IF(35>=$C22,$B22/12*(1+'Assumptions'!$B$26)*(1+'Assumptions'!$B$27)^2*(1-IF(35<=$G22,$F22,0)),0) | AR22: =IF(36>=$C22,$B22/12*(1+'Assumptions'!$B$26)*(1+'Assumptions'!$B$27)^2*(1-IF(36<=$G22,$F22,0)),0)
... A27: Volunteer Coordinator - Medicare CoP requirement | vol | B27: 50000 | C27: 12 | D27: I | E27: 3 | F27: =IF(0,'Assumptions'!$B$28,0) | G27: ='Assumptions'!$B$29 | I27: =IF(1>=$C27,$B27/12*(1+'Assumptions'!$B$26)*(1+'Assumptions'!$B$27)^0*(1-IF(1<=$G27,$F27,0)),0) | J27: =IF(2>=$C27,$B27/12*(1+'Assumptions'!$B$26)*(1+'Assumptions'!$B$27)^0*(1-IF(2<=$G27,$F27,0)),0) | K27: =IF(3>=$C27,$B27/12*(1+'Assumptions'!$B$26)*(1+'Assumptions'!$B$27)^0*(1-IF(3<=$G27,$F27,0)),0) | L27: =IF(4>=$C27,$B27/12*(1+'Assumptions'!$B$26)*(1+'Assumptions'!$B$27)^0*(1-IF(4<=$G27,$F27,0)),0) | M27: =IF(5>=$C27,$B27/12*(1+'Assumptions'!$B$26)*(1+'Assumptions'!$B$27)^0*(1-IF(5<=$G27,$F27,0)),0) | N27: =IF(6>=$C27,$B27/12*(1+'Assumptions'!$B$26)*(1+'Assumptions'!$B$27)^0*(1-IF(6<=$G27,$F27,0)),0) | O27: =IF(7>=$C27,$B27/12*(1+'Assumptions'!$B$26)*(1+'Assumptions'!$B$27)^0*(1-IF(7<=$G27,$F27,0)),0) | P27: =IF(8>=$C27,$B27/12*(1+'Assumptions'!$B$26)*(1+'Assumptions'!$B$27)^0*(1-IF(8<=$G27,$F27,0)),0) | Q27: =IF(9>=$C27,$B27/12*(1+'Assumptions'!$B$26)*(1+'Assumptions'!$B$27)^0*(1-IF(9<=$G27,$F27,0)),0) | R27: =IF(10>=$C27,$B27/12*(1+'Assumptions'!$B$26)*(1+'Assumptions'!$B$27)^0*(1-IF(10<=$G27,$F27,0)),0) | S27: =IF(11>=$C27,$B27/12*(1+'Assumptions'!$B$26)*(1+'Assumptions'!$B$27)^0*(1-IF(11<=$G27,$F27,0)),0) | T27: =IF(12>=$C27,$B27/12*(1+'Assumptions'!$B$26)*(1+'Assumptions'!$B$27)^0*(1-IF(12<=$G27,$F27,0)),0) | U27: =IF(13>=$C27,$B27/12*(1+'Assumptions'!$B$26)*(1+'Assumptions'!$B$27)^1*(1-IF(13<=$G27,$F27,0)),0) | V27: =IF(14>=$C27,$B27/12*(1+'Assumptions'!$B$26)*(1+'Assumptions'!$B$27)^1*(1-IF(14<=$G27,$F27,0)),0) | W27: =IF(15>=$C27,$B27/12*(1+'Assumptions'!$B$26)*(1+'Assumptions'!$B$27)^1*(1-IF(15<=$G27,$F27,0)),0) | X27: =IF(16>=$C27,$B27/12*(1+'Assumptions'!$B$26)*(1+'Assumptions'!$B$27)^1*(1-IF(16<=$G27,$F27,0)),0) | Y27: =IF(17>=$C27,$B27/12*(1+'Assumptions'!$B$26)*(1+'Assumptions'!$B$27)^1*(1-IF(17<=$G27,$F27,0)),0) | Z27: =IF(18>=$C27,$B27/12*(1+'Assumptions'!$B$26)*(1+'Assumptions'!$B$27)^1*(1-IF(18<=$G27,$F27,0)),0) | AA27: =IF(19>=$C27,$B27/12*(1+'Assumptions'!$B$26)*(1+'Assumptions'!$B$27)^1*(1-IF(19<=$G27,$F27,0)),0) | AB27: =IF(20>=$C27,$B27/12*(1+'Assumptions'!$B$26)*(1+'Assumptions'!$B$27)^1*(1-IF(20<=$G27,$F27,0)),0) | AC27: =IF(21>=$C27,$B27/12*(1+'Assumptions'!$B$26)*(1+'Assumptions'!$B$27)^1*(1-IF(21<=$G27,$F27,0)),0) | AD27: =IF(22>=$C27,$B27/12*(1+'Assumptions'!$B$26)*(1+'Assumptions'!$B$27)^1*(1-IF(22<=$G27,$F27,0)),0) | AE27: =IF(23>=$C27,$B27/12*(1+'Assumptions'!$B$26)*(1+'Assumptions'!$B$27)^1*(1-IF(23<=$G27,$F27,0)),0) | AF27: =IF(24>=$C27,$B27/12*(1+'Assumptions'!$B$26)*(1+'Assumptions'!$B$27)^1*(1-IF(24<=$G27,$F27,0)),0) | AG27: =IF(25>=$C27,$B27/12*(1+'Assumptions'!$B$26)*(1+'Assumptions'!$B$27)^2*(1-IF(25<=$G27,$F27,0)),0) | AH27: =IF(26>=$C27,$B27/12*(1+'Assumptions'!$B$26)*(1+'Assumptions'!$B$27)^2*(1-IF(26<=$G27,$F27,0)),0) | AI27: =IF(27>=$C27,$B27/12*(1+'Assumptions'!$B$26)*(1+'Assumptions'!$B$27)^2*(1-IF(27<=$G27,$F27,0)),0) | AJ27: =IF(28>=$C27,$B27/12*(1+'Assumptions'!$B$26)*(1+'Assumptions'!$B$27)^2*(1-IF(28<=$G27,$F27,0)),0) | AK27: =IF(29>=$C27,$B27/12*(1+'Assumptions'!$B$26)*(1+'Assumptions'!$B$27)^2*(1-IF(29<=$G27,$F27,0)),0) | AL27: =IF(30>=$C27,$B27/12*(1+'Assumptions'!$B$26)*(1+'Assumptions'!$B$27)^2*(1-IF(30<=$G27,$F27,0)),0) | AM27: =IF(31>=$C27,$B27/12*(1+'Assumptions'!$B$26)*(1+'Assumptions'!$B$27)^2*(1-IF(31<=$G27,$F27,0)),0) | AN27: =IF(32>=$C27,$B27/12*(1+'Assumptions'!$B$26)*(1+'Assumptions'!$B$27)^2*(1-IF(32<=$G27,$F27,0)),0) | AO27: =IF(33>=$C27,$B27/12*(1+'Assumptions'!$B$26)*(1+'Assumptions'!$B$27)^2*(1-IF(33<=$G27,$F27,0)),0) | AP27: =IF(34>=$C27,$B27/12*(1+'Assumptions'!$B$26)*(1+'Assumptions'!$B$27)^2*(1-IF(34<=$G27,$F27,0)),0) | AQ27: =IF(35>=$C27,$B27/12*(1+'Assumptions'!$B$26)*(1+'Assumptions'!$B$27)^2*(1-IF(35<=$G27,$F27,0)),0) | AR27: =IF(36>=$C27,$B27/12*(1+'Assumptions'!$B$26)*(1+'Assumptions'!$B$27)^2*(1-IF(36<=$G27,$F27,0)),0)
A29: W-2 salaries - DIRECT (clinical) | I29: =SUMPRODUCT(($D$6:$D$27="D")*I6:I27) | J29: =SUMPRODUCT(($D$6:$D$27="D")*J6:J27) | K29: =SUMPRODUCT(($D$6:$D$27="D")*K6:K27) | L29: =SUMPRODUCT(($D$6:$D$27="D")*L6:L27) | M29: =SUMPRODUCT(($D$6:$D$27="D")*M6:M27) | N29: =SUMPRODUCT(($D$6:$D$27="D")*N6:N27) | O29: =SUMPRODUCT(($D$6:$D$27="D")*O6:O27) | P29: =SUMPRODUCT(($D$6:$D$27="D")*P6:P27) | ... AR29: =SUMPRODUCT(($D$6:$D$27="D")*AR6:AR27)
A30: W-2 salaries - INDIRECT (admin/sales) | I30: =SUMPRODUCT(($D$6:$D$27="I")*I6:I27) | J30: =SUMPRODUCT(($D$6:$D$27="I")*J6:J27) | K30: =SUMPRODUCT(($D$6:$D$27="I")*K6:K27) | L30: =SUMPRODUCT(($D$6:$D$27="I")*L6:L27) | M30: =SUMPRODUCT(($D$6:$D$27="I")*M6:M27) | N30: =SUMPRODUCT(($D$6:$D$27="I")*N6:N27) | O30: =SUMPRODUCT(($D$6:$D$27="I")*O6:O27) | P30: =SUMPRODUCT(($D$6:$D$27="I")*P6:P27) | ... AR30: =SUMPRODUCT(($D$6:$D$27="I")*AR6:AR27)
A31: W-2 total | I31: =SUM(I6:I27) | J31: =SUM(J6:J27) | K31: =SUM(K6:K27) | L31: =SUM(L6:L27) | M31: =SUM(M6:M27) | N31: =SUM(N6:N27) | O31: =SUM(O6:O27) | P31: =SUM(P6:P27) | ... AR31: =SUM(AR6:AR27)
A32: PRN per-visit staff (census-driven) | I32: =Census!C20*SUMPRODUCT(Assumptions!$B$37:$B$41,Assumptions!$C$37:$C$41) | J32: =Census!D20*SUMPRODUCT(Assumptions!$B$37:$B$41,Assumptions!$C$37:$C$41) | K32: =Census!E20*SUMPRODUCT(Assumptions!$B$37:$B$41,Assumptions!$C$37:$C$41) | L32: =Census!F20*SUMPRODUCT(Assumptions!$B$37:$B$41,Assumptions!$C$37:$C$41) | M32: =Census!G20*SUMPRODUCT(Assumptions!$B$37:$B$41,Assumptions!$C$37:$C$41) | N32: =Census!H20*SUMPRODUCT(Assumptions!$B$37:$B$41,Assumptions!$C$37:$C$41) | O32: =Census!I20*SUMPRODUCT(Assumptions!$B$37:$B$41,Assumptions!$C$37:$C$41) | P32: =Census!J20*SUMPRODUCT(Assumptions!$B$37:$B$41,Assumptions!$C$37:$C$41) | ... AR32: =Census!AL20*SUMPRODUCT(Assumptions!$B$37:$B$41,Assumptions!$C$37:$C$41)
A33: Medical director(s) (contracted) | I33: ='Assumptions'!$B$30+IF(1>='Assumptions'!$B$32,'Assumptions'!$B$31,0) | J33: ='Assumptions'!$B$30+IF(2>='Assumptions'!$B$32,'Assumptions'!$B$31,0) | K33: ='Assumptions'!$B$30+IF(3>='Assumptions'!$B$32,'Assumptions'!$B$31,0) | L33: ='Assumptions'!$B$30+IF(4>='Assumptions'!$B$32,'Assumptions'!$B$31,0) | M33: ='Assumptions'!$B$30+IF(5>='Assumptions'!$B$32,'Assumptions'!$B$31,0) | N33: ='Assumptions'!$B$30+IF(6>='Assumptions'!$B$32,'Assumptions'!$B$31,0) | O33: ='Assumptions'!$B$30+IF(7>='Assumptions'!$B$32,'Assumptions'!$B$31,0) | P33: ='Assumptions'!$B$30+IF(8>='Assumptions'!$B$32,'Assumptions'!$B$31,0) | Q33: ='Assumptions'!$B$30+IF(9>='Assumptions'!$B$32,'Assumptions'!$B$31,0) | R33: ='Assumptions'!$B$30+IF(10>='Assumptions'!$B$32,'Assumptions'!$B$31,0) | S33: ='Assumptions'!$B$30+IF(11>='Assumptions'!$B$32,'Assumptions'!$B$31,0) | T33: ='Assumptions'!$B$30+IF(12>='Assumptions'!$B$32,'Assumptions'!$B$31,0) | U33: ='Assumptions'!$B$30+IF(13>='Assumptions'!$B$32,'Assumptions'!$B$31,0) | V33: ='Assumptions'!$B$30+IF(14>='Assumptions'!$B$32,'Assumptions'!$B$31,0) | W33: ='Assumptions'!$B$30+IF(15>='Assumptions'!$B$32,'Assumptions'!$B$31,0) | X33: ='Assumptions'!$B$30+IF(16>='Assumptions'!$B$32,'Assumptions'!$B$31,0) | Y33: ='Assumptions'!$B$30+IF(17>='Assumptions'!$B$32,'Assumptions'!$B$31,0) | Z33: ='Assumptions'!$B$30+IF(18>='Assumptions'!$B$32,'Assumptions'!$B$31,0) | AA33: ='Assumptions'!$B$30+IF(19>='Assumptions'!$B$32,'Assumptions'!$B$31,0) | AB33: ='Assumptions'!$B$30+IF(20>='Assumptions'!$B$32,'Assumptions'!$B$31,0) | AC33: ='Assumptions'!$B$30+IF(21>='Assumptions'!$B$32,'Assumptions'!$B$31,0) | AD33: ='Assumptions'!$B$30+IF(22>='Assumptions'!$B$32,'Assumptions'!$B$31,0) | AE33: ='Assumptions'!$B$30+IF(23>='Assumptions'!$B$32,'Assumptions'!$B$31,0) | AF33: ='Assumptions'!$B$30+IF(24>='Assumptions'!$B$32,'Assumptions'!$B$31,0) | AG33: ='Assumptions'!$B$30+IF(25>='Assumptions'!$B$32,'Assumptions'!$B$31,0) | AH33: ='Assumptions'!$B$30+IF(26>='Assumptions'!$B$32,'Assumptions'!$B$31,0) | AI33: ='Assumptions'!$B$30+IF(27>='Assumptions'!$B$32,'Assumptions'!$B$31,0) | AJ33: ='Assumptions'!$B$30+IF(28>='Assumptions'!$B$32,'Assumptions'!$B$31,0) | AK33: ='Assumptions'!$B$30+IF(29>='Assumptions'!$B$32,'Assumptions'!$B$31,0) | AL33: ='Assumptions'!$B$30+IF(30>='Assumptions'!$B$32,'Assumptions'!$B$31,0) | AM33: ='Assumptions'!$B$30+IF(31>='Assumptions'!$B$32,'Assumptions'!$B$31,0) | AN33: ='Assumptions'!$B$30+IF(32>='Assumptions'!$B$32,'Assumptions'!$B$31,0) | AO33: ='Assumptions'!$B$30+IF(33>='Assumptions'!$B$32,'Assumptions'!$B$31,0) | AP33: ='Assumptions'!$B$30+IF(34>='Assumptions'!$B$32,'Assumptions'!$B$31,0) | AQ33: ='Assumptions'!$B$30+IF(35>='Assumptions'!$B$32,'Assumptions'!$B$31,0) | AR33: ='Assumptions'!$B$30+IF(36>='Assumptions'!$B$32,'Assumptions'!$B$31,0)
A34: Bookkeeping/admin support | I34: ='Assumptions'!$B$33/12 | J34: ='Assumptions'!$B$33/12 | K34: ='Assumptions'!$B$33/12 | L34: ='Assumptions'!$B$33/12 | M34: ='Assumptions'!$B$33/12 | N34: ='Assumptions'!$B$33/12 | O34: ='Assumptions'!$B$33/12 | P34: ='Assumptions'!$B$33/12 | ... AR34: ='Assumptions'!$B$33/12
A35: Burden (taxes/WC) | I35: =(I31+I32+I34)*'Assumptions'!$B$23 | J35: =(J31+J32+J34)*'Assumptions'!$B$23 | K35: =(K31+K32+K34)*'Assumptions'!$B$23 | L35: =(L31+L32+L34)*'Assumptions'!$B$23 | M35: =(M31+M32+M34)*'Assumptions'!$B$23 | N35: =(N31+N32+N34)*'Assumptions'!$B$23 | O35: =(O31+O32+O34)*'Assumptions'!$B$23 | P35: =(P31+P32+P34)*'Assumptions'!$B$23 | ... AR35: =(AR31+AR32+AR34)*'Assumptions'!$B$23
A36: Health insurance (after waiting period) | I36: =SUMPRODUCT((($C$6:$C$27+$E$6:$E$27)<=1)*1)*'Assumptions'!$B$24 | J36: =SUMPRODUCT((($C$6:$C$27+$E$6:$E$27)<=2)*1)*'Assumptions'!$B$24 | K36: =SUMPRODUCT((($C$6:$C$27+$E$6:$E$27)<=3)*1)*'Assumptions'!$B$24 | L36: =SUMPRODUCT((($C$6:$C$27+$E$6:$E$27)<=4)*1)*'Assumptions'!$B$24 | M36: =SUMPRODUCT((($C$6:$C$27+$E$6:$E$27)<=5)*1)*'Assumptions'!$B$24 | N36: =SUMPRODUCT((($C$6:$C$27+$E$6:$E$27)<=6)*1)*'Assumptions'!$B$24 | O36: =SUMPRODUCT((($C$6:$C$27+$E$6:$E$27)<=7)*1)*'Assumptions'!$B$24 | P36: =SUMPRODUCT((($C$6:$C$27+$E$6:$E$27)<=8)*1)*'Assumptions'!$B$24 | Q36: =SUMPRODUCT((($C$6:$C$27+$E$6:$E$27)<=9)*1)*'Assumptions'!$B$24 | R36: =SUMPRODUCT((($C$6:$C$27+$E$6:$E$27)<=10)*1)*'Assumptions'!$B$24 | S36: =SUMPRODUCT((($C$6:$C$27+$E$6:$E$27)<=11)*1)*'Assumptions'!$B$24 | T36: =SUMPRODUCT((($C$6:$C$27+$E$6:$E$27)<=12)*1)*'Assumptions'!$B$24 | U36: =SUMPRODUCT((($C$6:$C$27+$E$6:$E$27)<=13)*1)*'Assumptions'!$B$24 | V36: =SUMPRODUCT((($C$6:$C$27+$E$6:$E$27)<=14)*1)*'Assumptions'!$B$24 | W36: =SUMPRODUCT((($C$6:$C$27+$E$6:$E$27)<=15)*1)*'Assumptions'!$B$24 | X36: =SUMPRODUCT((($C$6:$C$27+$E$6:$E$27)<=16)*1)*'Assumptions'!$B$24 | Y36: =SUMPRODUCT((($C$6:$C$27+$E$6:$E$27)<=17)*1)*'Assumptions'!$B$24 | Z36: =SUMPRODUCT((($C$6:$C$27+$E$6:$E$27)<=18)*1)*'Assumptions'!$B$24 | AA36: =SUMPRODUCT((($C$6:$C$27+$E$6:$E$27)<=19)*1)*'Assumptions'!$B$24 | AB36: =SUMPRODUCT((($C$6:$C$27+$E$6:$E$27)<=20)*1)*'Assumptions'!$B$24 | AC36: =SUMPRODUCT((($C$6:$C$27+$E$6:$E$27)<=21)*1)*'Assumptions'!$B$24 | AD36: =SUMPRODUCT((($C$6:$C$27+$E$6:$E$27)<=22)*1)*'Assumptions'!$B$24 | AE36: =SUMPRODUCT((($C$6:$C$27+$E$6:$E$27)<=23)*1)*'Assumptions'!$B$24 | AF36: =SUMPRODUCT((($C$6:$C$27+$E$6:$E$27)<=24)*1)*'Assumptions'!$B$24 | AG36: =SUMPRODUCT((($C$6:$C$27+$E$6:$E$27)<=25)*1)*'Assumptions'!$B$24 | AH36: =SUMPRODUCT((($C$6:$C$27+$E$6:$E$27)<=26)*1)*'Assumptions'!$B$24 | AI36: =SUMPRODUCT((($C$6:$C$27+$E$6:$E$27)<=27)*1)*'Assumptions'!$B$24 | AJ36: =SUMPRODUCT((($C$6:$C$27+$E$6:$E$27)<=28)*1)*'Assumptions'!$B$24 | AK36: =SUMPRODUCT((($C$6:$C$27+$E$6:$E$27)<=29)*1)*'Assumptions'!$B$24 | AL36: =SUMPRODUCT((($C$6:$C$27+$E$6:$E$27)<=30)*1)*'Assumptions'!$B$24 | AM36: =SUMPRODUCT((($C$6:$C$27+$E$6:$E$27)<=31)*1)*'Assumptions'!$B$24 | AN36: =SUMPRODUCT((($C$6:$C$27+$E$6:$E$27)<=32)*1)*'Assumptions'!$B$24 | AO36: =SUMPRODUCT((($C$6:$C$27+$E$6:$E$27)<=33)*1)*'Assumptions'!$B$24 | AP36: =SUMPRODUCT((($C$6:$C$27+$E$6:$E$27)<=34)*1)*'Assumptions'!$B$24 | AQ36: =SUMPRODUCT((($C$6:$C$27+$E$6:$E$27)<=35)*1)*'Assumptions'!$B$24 | AR36: =SUMPRODUCT((($C$6:$C$27+$E$6:$E$27)<=36)*1)*'Assumptions'!$B$24
A37: TOTAL LABOR COST | I37: =I31+I32+I33+I34+I35+I36 | J37: =J31+J32+J33+J34+J35+J36 | K37: =K31+K32+K33+K34+K35+K36 | L37: =L31+L32+L33+L34+L35+L36 | M37: =M31+M32+M33+M34+M35+M36 | N37: =N31+N32+N33+N34+N35+N36 | O37: =O31+O32+O33+O34+O35+O36 | P37: =P31+P32+P33+P34+P35+P36 | ... AR37: =AR31+AR32+AR33+AR34+AR35+AR36

Sheet Monthly x36
A1: AZALEA HOSPICE - REFUGE OPERATING MODEL
A2: 36-month pro forma: P&L, debt schedules (seller / refi toggle / SBA toggle), direct-method cash, DSCR & floor flags.
A4: Month # | C4: 1 | D4: 2 | E4: 3 | F4: 4 | G4: 5 | H4: 6 | I4: 7 | J4: 8 | K4: 9 | L4: 10 | M4: 11 | N4: 12 | O4: 13 | P4: 14 | Q4: 15 | R4: 16 | S4: 17 | T4: 18 | U4: 19 | V4: 20 | W4: 21 | X4: 22 | Y4: 23 | Z4: 24 | AA4: 25 | AB4: 26 | AC4: 27 | AD4: 28 | AE4: 29 | AF4: 30 | AG4: 31 | AH4: 32 | AI4: 33 | AJ4: 34 | AK4: 35 | AL4: 36
C5: Jul-26 | D5: Aug-26 | E5: Sep-26 | F5: Oct-26 | G5: Nov-26 | H5: Dec-26 | I5: Jan-27 | J5: Feb-27 | K5: Mar-27 | L5: Apr-27 | M5: May-27 | N5: Jun-27 | O5: Jul-27 | P5: Aug-27 | Q5: Sep-27 | R5: Oct-27 | S5: Nov-27 | T5: Dec-27 | U5: Jan-28 | V5: Feb-28 | W5: Mar-28 | X5: Apr-28 | Y5: May-28 | Z5: Jun-28 | AA5: Jul-28 | AB5: Aug-28 | AC5: Sep-28 | AD5: Oct-28 | AE5: Nov-28 | AF5: Dec-28 | AG5: Jan-29 | AH5: Feb-29 | AI5: Mar-29 | AJ5: Apr-29 | AK5: May-29 | AL5: Jun-29
A6: P&L
A7: ADC | C7: =Census!C20 | D7: =Census!D20 | E7: =Census!E20 | F7: =Census!F20 | G7: =Census!G20 | H7: =Census!H20 | I7: =Census!I20 | J7: =Census!J20 | ... AL7: =Census!AL20
A8: NET REVENUE (after NOE losses) | C8: ='Collections'!C9 | D8: ='Collections'!D9 | E8: ='Collections'!E9 | F8: ='Collections'!F9 | G8: ='Collections'!G9 | H8: ='Collections'!H9 | I8: ='Collections'!I9 | J8: ='Collections'!J9 | ... AL8: ='Collections'!AL9
A9: Total labor cost | C9: ='Payroll'!I37 | D9: ='Payroll'!J37 | E9: ='Payroll'!K37 | F9: ='Payroll'!L37 | G9: ='Payroll'!M37 | H9: ='Payroll'!N37 | I9: ='Payroll'!O37 | J9: ='Payroll'!P37 | ... AL9: ='Payroll'!AR37
A10: Patient costs (pharmacy/supplies/DME) | C10: =Census!C21*'Assumptions'!$B$44 | D10: =Census!D21*'Assumptions'!$B$44 | E10: =Census!E21*'Assumptions'!$B$44 | F10: =Census!F21*'Assumptions'!$B$44 | G10: =Census!G21*'Assumptions'!$B$44 | H10: =Census!H21*'Assumptions'!$B$44 | I10: =Census!I21*'Assumptions'!$B$44 | J10: =Census!J21*'Assumptions'!$B$44 | ... AL10: =Census!AL21*'Assumptions'!$B$44
A11: Mileage | C11: =Census!C20*'Assumptions'!$B$45 | D11: =Census!D20*'Assumptions'!$B$45 | E11: =Census!E20*'Assumptions'!$B$45 | F11: =Census!F20*'Assumptions'!$B$45 | G11: =Census!G20*'Assumptions'!$B$45 | H11: =Census!H20*'Assumptions'!$B$45 | I11: =Census!I20*'Assumptions'!$B$45 | J11: =Census!J20*'Assumptions'!$B$45 | ... AL11: =Census!AL20*'Assumptions'!$B$45
A12: G&A (bill calendar, monthly-equivalent) | C12: =SUMPRODUCT(Assumptions!$B$51:$B$64/Assumptions!$C$51:$C$64) | D12: =SUMPRODUCT(Assumptions!$B$51:$B$64/Assumptions!$C$51:$C$64) | E12: =SUMPRODUCT(Assumptions!$B$51:$B$64/Assumptions!$C$51:$C$64) | F12: =SUMPRODUCT(Assumptions!$B$51:$B$64/Assumptions!$C$51:$C$64) | G12: =SUMPRODUCT(Assumptions!$B$51:$B$64/Assumptions!$C$51:$C$64) | H12: =SUMPRODUCT(Assumptions!$B$51:$B$64/Assumptions!$C$51:$C$64) | I12: =SUMPRODUCT(Assumptions!$B$51:$B$64/Assumptions!$C$51:$C$64) | J12: =SUMPRODUCT(Assumptions!$B$51:$B$64/Assumptions!$C$51:$C$64) | ... AL12: =SUMPRODUCT(Assumptions!$B$51:$B$64/Assumptions!$C$51:$C$64)
A13: Billing + QR fees (% of net) | C13: =C8*'Assumptions'!$B$46 | D13: =D8*'Assumptions'!$B$46 | E13: =E8*'Assumptions'!$B$46 | F13: =F8*'Assumptions'!$B$46 | G13: =G8*'Assumptions'!$B$46 | H13: =H8*'Assumptions'!$B$46 | I13: =I8*'Assumptions'!$B$46 | J13: =J8*'Assumptions'!$B$46 | ... AL13: =AL8*'Assumptions'!$B$46
A14: EBITDA | C14: =C8-C9-C10-C11-C12-C13 | D14: =D8-D9-D10-D11-D12-D13 | E14: =E8-E9-E10-E11-E12-E13 | F14: =F8-F9-F10-F11-F12-F13 | G14: =G8-G9-G10-G11-G12-G13 | H14: =H8-H9-H10-H11-H12-H13 | I14: =I8-I9-I10-I11-I12-I13 | J14: =J8-J9-J10-J11-J12-J13 | ... AL14: =AL8-AL9-AL10-AL11-AL12-AL13
A15: Cap-liability reserve (accrual, non-cash) | C15: =-C8*'Assumptions'!$B$7*'Assumptions'!$B$47 | D15: =-D8*'Assumptions'!$B$7*'Assumptions'!$B$47 | E15: =-E8*'Assumptions'!$B$7*'Assumptions'!$B$47 | F15: =-F8*'Assumptions'!$B$7*'Assumptions'!$B$47 | G15: =-G8*'Assumptions'!$B$7*'Assumptions'!$B$47 | H15: =-H8*'Assumptions'!$B$7*'Assumptions'!$B$47 | I15: =-I8*'Assumptions'!$B$7*'Assumptions'!$B$47 | J15: =-J8*'Assumptions'!$B$7*'Assumptions'!$B$47 | ... AL15: =-AL8*'Assumptions'!$B$7*'Assumptions'!$B$47
A16: License amortization (non-cash) | C16: =-'Assumptions'!$B$67/'Assumptions'!$B$90/12 | D16: =-'Assumptions'!$B$67/'Assumptions'!$B$90/12 | E16: =-'Assumptions'!$B$67/'Assumptions'!$B$90/12 | F16: =-'Assumptions'!$B$67/'Assumptions'!$B$90/12 | G16: =-'Assumptions'!$B$67/'Assumptions'!$B$90/12 | H16: =-'Assumptions'!$B$67/'Assumptions'!$B$90/12 | I16: =-'Assumptions'!$B$67/'Assumptions'!$B$90/12 | J16: =-'Assumptions'!$B$67/'Assumptions'!$B$90/12 | ... AL16: =-'Assumptions'!$B$67/'Assumptions'!$B$90/12
A17: DEBT - SELLER NOTE (base terms; auto-paid off if refi toggled)
A18: Seller beg balance | C18: ='Assumptions'!$B$67-'Assumptions'!$B$68 | D18: =C22 | E18: =D22 | F18: =E22 | G18: =F22 | H18: =G22 | I18: =H22 | J18: =I22 | K18: =J22 | ... AL18: =AK22
A19: Seller interest accrued (6% simple) | C19: =C18*'Assumptions'!$B$72/12 | D19: =D18*'Assumptions'!$B$72/12 | E19: =E18*'Assumptions'!$B$72/12 | F19: =F18*'Assumptions'!$B$72/12 | G19: =G18*'Assumptions'!$B$72/12 | H19: =H18*'Assumptions'!$B$72/12 | I19: =I18*'Assumptions'!$B$72/12 | J19: =J18*'Assumptions'!$B$72/12 | ... AL19: =AL18*'Assumptions'!$B$72/12
A20: Seller principal payments | C20: =IF(C18<=0,0,IF(AND('Assumptions'!$B$76=1,1='Assumptions'!$B$77),C18,IF(AND(1>='Assumptions'!$B$70,1<='Assumptions'!$B$71),'Assumptions'!$B$69,IF(1='Assumptions'!$B$73,C18,0)))) | D20: =IF(D18<=0,0,IF(AND('Assumptions'!$B$76=1,2='Assumptions'!$B$77),D18,IF(AND(2>='Assumptions'!$B$70,2<='Assumptions'!$B$71),'Assumptions'!$B$69,IF(2='Assumptions'!$B$73,D18,0)))) | E20: =IF(E18<=0,0,IF(AND('Assumptions'!$B$76=1,3='Assumptions'!$B$77),E18,IF(AND(3>='Assumptions'!$B$70,3<='Assumptions'!$B$71),'Assumptions'!$B$69,IF(3='Assumptions'!$B$73,E18,0)))) | F20: =IF(F18<=0,0,IF(AND('Assumptions'!$B$76=1,4='Assumptions'!$B$77),F18,IF(AND(4>='Assumptions'!$B$70,4<='Assumptions'!$B$71),'Assumptions'!$B$69,IF(4='Assumptions'!$B$73,F18,0)))) | G20: =IF(G18<=0,0,IF(AND('Assumptions'!$B$76=1,5='Assumptions'!$B$77),G18,IF(AND(5>='Assumptions'!$B$70,5<='Assumptions'!$B$71),'Assumptions'!$B$69,IF(5='Assumptions'!$B$73,G18,0)))) | H20: =IF(H18<=0,0,IF(AND('Assumptions'!$B$76=1,6='Assumptions'!$B$77),H18,IF(AND(6>='Assumptions'!$B$70,6<='Assumptions'!$B$71),'Assumptions'!$B$69,IF(6='Assumptions'!$B$73,H18,0)))) | I20: =IF(I18<=0,0,IF(AND('Assumptions'!$B$76=1,7='Assumptions'!$B$77),I18,IF(AND(7>='Assumptions'!$B$70,7<='Assumptions'!$B$71),'Assumptions'!$B$69,IF(7='Assumptions'!$B$73,I18,0)))) | J20: =IF(J18<=0,0,IF(AND('Assumptions'!$B$76=1,8='Assumptions'!$B$77),J18,IF(AND(8>='Assumptions'!$B$70,8<='Assumptions'!$B$71),'Assumptions'!$B$69,IF(8='Assumptions'!$B$73,J18,0)))) | K20: =IF(K18<=0,0,IF(AND('Assumptions'!$B$76=1,9='Assumptions'!$B$77),K18,IF(AND(9>='Assumptions'!$B$70,9<='Assumptions'!$B$71),'Assumptions'!$B$69,IF(9='Assumptions'!$B$73,K18,0)))) | L20: =IF(L18<=0,0,IF(AND('Assumptions'!$B$76=1,10='Assumptions'!$B$77),L18,IF(AND(10>='Assumptions'!$B$70,10<='Assumptions'!$B$71),'Assumptions'!$B$69,IF(10='Assumptions'!$B$73,L18,0)))) | M20: =IF(M18<=0,0,IF(AND('Assumptions'!$B$76=1,11='Assumptions'!$B$77),M18,IF(AND(11>='Assumptions'!$B$70,11<='Assumptions'!$B$71),'Assumptions'!$B$69,IF(11='Assumptions'!$B$73,M18,0)))) | N20: =IF(N18<=0,0,IF(AND('Assumptions'!$B$76=1,12='Assumptions'!$B$77),N18,IF(AND(12>='Assumptions'!$B$70,12<='Assumptions'!$B$71),'Assumptions'!$B$69,IF(12='Assumptions'!$B$73,N18,0)))) | O20: =IF(O18<=0,0,IF(AND('Assumptions'!$B$76=1,13='Assumptions'!$B$77),O18,IF(AND(13>='Assumptions'!$B$70,13<='Assumptions'!$B$71),'Assumptions'!$B$69,IF(13='Assumptions'!$B$73,O18,0)))) | P20: =IF(P18<=0,0,IF(AND('Assumptions'!$B$76=1,14='Assumptions'!$B$77),P18,IF(AND(14>='Assumptions'!$B$70,14<='Assumptions'!$B$71),'Assumptions'!$B$69,IF(14='Assumptions'!$B$73,P18,0)))) | Q20: =IF(Q18<=0,0,IF(AND('Assumptions'!$B$76=1,15='Assumptions'!$B$77),Q18,IF(AND(15>='Assumptions'!$B$70,15<='Assumptions'!$B$71),'Assumptions'!$B$69,IF(15='Assumptions'!$B$73,Q18,0)))) | R20: =IF(R18<=0,0,IF(AND('Assumptions'!$B$76=1,16='Assumptions'!$B$77),R18,IF(AND(16>='Assumptions'!$B$70,16<='Assumptions'!$B$71),'Assumptions'!$B$69,IF(16='Assumptions'!$B$73,R18,0)))) | S20: =IF(S18<=0,0,IF(AND('Assumptions'!$B$76=1,17='Assumptions'!$B$77),S18,IF(AND(17>='Assumptions'!$B$70,17<='Assumptions'!$B$71),'Assumptions'!$B$69,IF(17='Assumptions'!$B$73,S18,0)))) | T20: =IF(T18<=0,0,IF(AND('Assumptions'!$B$76=1,18='Assumptions'!$B$77),T18,IF(AND(18>='Assumptions'!$B$70,18<='Assumptions'!$B$71),'Assumptions'!$B$69,IF(18='Assumptions'!$B$73,T18,0)))) | U20: =IF(U18<=0,0,IF(AND('Assumptions'!$B$76=1,19='Assumptions'!$B$77),U18,IF(AND(19>='Assumptions'!$B$70,19<='Assumptions'!$B$71),'Assumptions'!$B$69,IF(19='Assumptions'!$B$73,U18,0)))) | V20: =IF(V18<=0,0,IF(AND('Assumptions'!$B$76=1,20='Assumptions'!$B$77),V18,IF(AND(20>='Assumptions'!$B$70,20<='Assumptions'!$B$71),'Assumptions'!$B$69,IF(20='Assumptions'!$B$73,V18,0)))) | W20: =IF(W18<=0,0,IF(AND('Assumptions'!$B$76=1,21='Assumptions'!$B$77),W18,IF(AND(21>='Assumptions'!$B$70,21<='Assumptions'!$B$71),'Assumptions'!$B$69,IF(21='Assumptions'!$B$73,W18,0)))) | X20: =IF(X18<=0,0,IF(AND('Assumptions'!$B$76=1,22='Assumptions'!$B$77),X18,IF(AND(22>='Assumptions'!$B$70,22<='Assumptions'!$B$71),'Assumptions'!$B$69,IF(22='Assumptions'!$B$73,X18,0)))) | Y20: =IF(Y18<=0,0,IF(AND('Assumptions'!$B$76=1,23='Assumptions'!$B$77),Y18,IF(AND(23>='Assumptions'!$B$70,23<='Assumptions'!$B$71),'Assumptions'!$B$69,IF(23='Assumptions'!$B$73,Y18,0)))) | Z20: =IF(Z18<=0,0,IF(AND('Assumptions'!$B$76=1,24='Assumptions'!$B$77),Z18,IF(AND(24>='Assumptions'!$B$70,24<='Assumptions'!$B$71),'Assumptions'!$B$69,IF(24='Assumptions'!$B$73,Z18,0)))) | AA20: =IF(AA18<=0,0,IF(AND('Assumptions'!$B$76=1,25='Assumptions'!$B$77),AA18,IF(AND(25>='Assumptions'!$B$70,25<='Assumptions'!$B$71),'Assumptions'!$B$69,IF(25='Assumptions'!$B$73,AA18,0)))) | AB20: =IF(AB18<=0,0,IF(AND('Assumptions'!$B$76=1,26='Assumptions'!$B$77),AB18,IF(AND(26>='Assumptions'!$B$70,26<='Assumptions'!$B$71),'Assumptions'!$B$69,IF(26='Assumptions'!$B$73,AB18,0)))) | AC20: =IF(AC18<=0,0,IF(AND('Assumptions'!$B$76=1,27='Assumptions'!$B$77),AC18,IF(AND(27>='Assumptions'!$B$70,27<='Assumptions'!$B$71),'Assumptions'!$B$69,IF(27='Assumptions'!$B$73,AC18,0)))) | AD20: =IF(AD18<=0,0,IF(AND('Assumptions'!$B$76=1,28='Assumptions'!$B$77),AD18,IF(AND(28>='Assumptions'!$B$70,28<='Assumptions'!$B$71),'Assumptions'!$B$69,IF(28='Assumptions'!$B$73,AD18,0)))) | AE20: =IF(AE18<=0,0,IF(AND('Assumptions'!$B$76=1,29='Assumptions'!$B$77),AE18,IF(AND(29>='Assumptions'!$B$70,29<='Assumptions'!$B$71),'Assumptions'!$B$69,IF(29='Assumptions'!$B$73,AE18,0)))) | AF20: =IF(AF18<=0,0,IF(AND('Assumptions'!$B$76=1,30='Assumptions'!$B$77),AF18,IF(AND(30>='Assumptions'!$B$70,30<='Assumptions'!$B$71),'Assumptions'!$B$69,IF(30='Assumptions'!$B$73,AF18,0)))) | AG20: =IF(AG18<=0,0,IF(AND('Assumptions'!$B$76=1,31='Assumptions'!$B$77),AG18,IF(AND(31>='Assumptions'!$B$70,31<='Assumptions'!$B$71),'Assumptions'!$B$69,IF(31='Assumptions'!$B$73,AG18,0)))) | AH20: =IF(AH18<=0,0,IF(AND('Assumptions'!$B$76=1,32='Assumptions'!$B$77),AH18,IF(AND(32>='Assumptions'!$B$70,32<='Assumptions'!$B$71),'Assumptions'!$B$69,IF(32='Assumptions'!$B$73,AH18,0)))) | AI20: =IF(AI18<=0,0,IF(AND('Assumptions'!$B$76=1,33='Assumptions'!$B$77),AI18,IF(AND(33>='Assumptions'!$B$70,33<='Assumptions'!$B$71),'Assumptions'!$B$69,IF(33='Assumptions'!$B$73,AI18,0)))) | AJ20: =IF(AJ18<=0,0,IF(AND('Assumptions'!$B$76=1,34='Assumptions'!$B$77),AJ18,IF(AND(34>='Assumptions'!$B$70,34<='Assumptions'!$B$71),'Assumptions'!$B$69,IF(34='Assumptions'!$B$73,AJ18,0)))) | AK20: =IF(AK18<=0,0,IF(AND('Assumptions'!$B$76=1,35='Assumptions'!$B$77),AK18,IF(AND(35>='Assumptions'!$B$70,35<='Assumptions'!$B$71),'Assumptions'!$B$69,IF(35='Assumptions'!$B$73,AK18,0)))) | AL20: =IF(AL18<=0,0,IF(AND('Assumptions'!$B$76=1,36='Assumptions'!$B$77),AL18,IF(AND(36>='Assumptions'!$B$70,36<='Assumptions'!$B$71),'Assumptions'!$B$69,IF(36='Assumptions'!$B$73,AL18,0))))
A21: Seller interest PAID (at payoff/balloon) | C21: =IF(OR(AND('Assumptions'!$B$76=1,1='Assumptions'!$B$77),AND('Assumptions'!$B$76=0,1='Assumptions'!$B$73)),SUM($C$19:C19),0) | D21: =IF(OR(AND('Assumptions'!$B$76=1,2='Assumptions'!$B$77),AND('Assumptions'!$B$76=0,2='Assumptions'!$B$73)),SUM($C$19:D19),0) | E21: =IF(OR(AND('Assumptions'!$B$76=1,3='Assumptions'!$B$77),AND('Assumptions'!$B$76=0,3='Assumptions'!$B$73)),SUM($C$19:E19),0) | F21: =IF(OR(AND('Assumptions'!$B$76=1,4='Assumptions'!$B$77),AND('Assumptions'!$B$76=0,4='Assumptions'!$B$73)),SUM($C$19:F19),0) | G21: =IF(OR(AND('Assumptions'!$B$76=1,5='Assumptions'!$B$77),AND('Assumptions'!$B$76=0,5='Assumptions'!$B$73)),SUM($C$19:G19),0) | H21: =IF(OR(AND('Assumptions'!$B$76=1,6='Assumptions'!$B$77),AND('Assumptions'!$B$76=0,6='Assumptions'!$B$73)),SUM($C$19:H19),0) | I21: =IF(OR(AND('Assumptions'!$B$76=1,7='Assumptions'!$B$77),AND('Assumptions'!$B$76=0,7='Assumptions'!$B$73)),SUM($C$19:I19),0) | J21: =IF(OR(AND('Assumptions'!$B$76=1,8='Assumptions'!$B$77),AND('Assumptions'!$B$76=0,8='Assumptions'!$B$73)),SUM($C$19:J19),0) | K21: =IF(OR(AND('Assumptions'!$B$76=1,9='Assumptions'!$B$77),AND('Assumptions'!$B$76=0,9='Assumptions'!$B$73)),SUM($C$19:K19),0) | L21: =IF(OR(AND('Assumptions'!$B$76=1,10='Assumptions'!$B$77),AND('Assumptions'!$B$76=0,10='Assumptions'!$B$73)),SUM($C$19:L19),0) | M21: =IF(OR(AND('Assumptions'!$B$76=1,11='Assumptions'!$B$77),AND('Assumptions'!$B$76=0,11='Assumptions'!$B$73)),SUM($C$19:M19),0) | N21: =IF(OR(AND('Assumptions'!$B$76=1,12='Assumptions'!$B$77),AND('Assumptions'!$B$76=0,12='Assumptions'!$B$73)),SUM($C$19:N19),0) | O21: =IF(OR(AND('Assumptions'!$B$76=1,13='Assumptions'!$B$77),AND('Assumptions'!$B$76=0,13='Assumptions'!$B$73)),SUM($C$19:O19),0) | P21: =IF(OR(AND('Assumptions'!$B$76=1,14='Assumptions'!$B$77),AND('Assumptions'!$B$76=0,14='Assumptions'!$B$73)),SUM($C$19:P19),0) | Q21: =IF(OR(AND('Assumptions'!$B$76=1,15='Assumptions'!$B$77),AND('Assumptions'!$B$76=0,15='Assumptions'!$B$73)),SUM($C$19:Q19),0) | R21: =IF(OR(AND('Assumptions'!$B$76=1,16='Assumptions'!$B$77),AND('Assumptions'!$B$76=0,16='Assumptions'!$B$73)),SUM($C$19:R19),0) | S21: =IF(OR(AND('Assumptions'!$B$76=1,17='Assumptions'!$B$77),AND('Assumptions'!$B$76=0,17='Assumptions'!$B$73)),SUM($C$19:S19),0) | T21: =IF(OR(AND('Assumptions'!$B$76=1,18='Assumptions'!$B$77),AND('Assumptions'!$B$76=0,18='Assumptions'!$B$73)),SUM($C$19:T19),0) | U21: =IF(OR(AND('Assumptions'!$B$76=1,19='Assumptions'!$B$77),AND('Assumptions'!$B$76=0,19='Assumptions'!$B$73)),SUM($C$19:U19),0) | V21: =IF(OR(AND('Assumptions'!$B$76=1,20='Assumptions'!$B$77),AND('Assumptions'!$B$76=0,20='Assumptions'!$B$73)),SUM($C$19:V19),0) | W21: =IF(OR(AND('Assumptions'!$B$76=1,21='Assumptions'!$B$77),AND('Assumptions'!$B$76=0,21='Assumptions'!$B$73)),SUM($C$19:W19),0) | X21: =IF(OR(AND('Assumptions'!$B$76=1,22='Assumptions'!$B$77),AND('Assumptions'!$B$76=0,22='Assumptions'!$B$73)),SUM($C$19:X19),0) | Y21: =IF(OR(AND('Assumptions'!$B$76=1,23='Assumptions'!$B$77),AND('Assumptions'!$B$76=0,23='Assumptions'!$B$73)),SUM($C$19:Y19),0) | Z21: =IF(OR(AND('Assumptions'!$B$76=1,24='Assumptions'!$B$77),AND('Assumptions'!$B$76=0,24='Assumptions'!$B$73)),SUM($C$19:Z19),0) | AA21: =IF(OR(AND('Assumptions'!$B$76=1,25='Assumptions'!$B$77),AND('Assumptions'!$B$76=0,25='Assumptions'!$B$73)),SUM($C$19:AA19),0) | AB21: =IF(OR(AND('Assumptions'!$B$76=1,26='Assumptions'!$B$77),AND('Assumptions'!$B$76=0,26='Assumptions'!$B$73)),SUM($C$19:AB19),0) | AC21: =IF(OR(AND('Assumptions'!$B$76=1,27='Assumptions'!$B$77),AND('Assumptions'!$B$76=0,27='Assumptions'!$B$73)),SUM($C$19:AC19),0) | AD21: =IF(OR(AND('Assumptions'!$B$76=1,28='Assumptions'!$B$77),AND('Assumptions'!$B$76=0,28='Assumptions'!$B$73)),SUM($C$19:AD19),0) | AE21: =IF(OR(AND('Assumptions'!$B$76=1,29='Assumptions'!$B$77),AND('Assumptions'!$B$76=0,29='Assumptions'!$B$73)),SUM($C$19:AE19),0) | AF21: =IF(OR(AND('Assumptions'!$B$76=1,30='Assumptions'!$B$77),AND('Assumptions'!$B$76=0,30='Assumptions'!$B$73)),SUM($C$19:AF19),0) | AG21: =IF(OR(AND('Assumptions'!$B$76=1,31='Assumptions'!$B$77),AND('Assumptions'!$B$76=0,31='Assumptions'!$B$73)),SUM($C$19:AG19),0) | AH21: =IF(OR(AND('Assumptions'!$B$76=1,32='Assumptions'!$B$77),AND('Assumptions'!$B$76=0,32='Assumptions'!$B$73)),SUM($C$19:AH19),0) | AI21: =IF(OR(AND('Assumptions'!$B$76=1,33='Assumptions'!$B$77),AND('Assumptions'!$B$76=0,33='Assumptions'!$B$73)),SUM($C$19:AI19),0) | AJ21: =IF(OR(AND('Assumptions'!$B$76=1,34='Assumptions'!$B$77),AND('Assumptions'!$B$76=0,34='Assumptions'!$B$73)),SUM($C$19:AJ19),0) | AK21: =IF(OR(AND('Assumptions'!$B$76=1,35='Assumptions'!$B$77),AND('Assumptions'!$B$76=0,35='Assumptions'!$B$73)),SUM($C$19:AK19),0) | AL21: =IF(OR(AND('Assumptions'!$B$76=1,36='Assumptions'!$B$77),AND('Assumptions'!$B$76=0,36='Assumptions'!$B$73)),SUM($C$19:AL19),0)
A22: Seller end balance | C22: =C18-C20 | D22: =D18-D20 | E22: =E18-E20 | F22: =F18-F20 | G22: =G18-G20 | H22: =H18-H20 | I22: =I18-I20 | J22: =J18-J20 | ... AL22: =AL18-AL20
A23: DEBT - REFI (toggle) & SBA (toggle)
A24: Refi payment (P&I, from month after funding) | C24: =IF(AND('Assumptions'!$B$76=1,1>'Assumptions'!$B$77,1<='Assumptions'!$B$77+'Assumptions'!$B$80),-PMT('Assumptions'!$B$79/12,'Assumptions'!$B$80,'Assumptions'!$B$78),0) | D24: =IF(AND('Assumptions'!$B$76=1,2>'Assumptions'!$B$77,2<='Assumptions'!$B$77+'Assumptions'!$B$80),-PMT('Assumptions'!$B$79/12,'Assumptions'!$B$80,'Assumptions'!$B$78),0) | E24: =IF(AND('Assumptions'!$B$76=1,3>'Assumptions'!$B$77,3<='Assumptions'!$B$77+'Assumptions'!$B$80),-PMT('Assumptions'!$B$79/12,'Assumptions'!$B$80,'Assumptions'!$B$78),0) | F24: =IF(AND('Assumptions'!$B$76=1,4>'Assumptions'!$B$77,4<='Assumptions'!$B$77+'Assumptions'!$B$80),-PMT('Assumptions'!$B$79/12,'Assumptions'!$B$80,'Assumptions'!$B$78),0) | G24: =IF(AND('Assumptions'!$B$76=1,5>'Assumptions'!$B$77,5<='Assumptions'!$B$77+'Assumptions'!$B$80),-PMT('Assumptions'!$B$79/12,'Assumptions'!$B$80,'Assumptions'!$B$78),0) | H24: =IF(AND('Assumptions'!$B$76=1,6>'Assumptions'!$B$77,6<='Assumptions'!$B$77+'Assumptions'!$B$80),-PMT('Assumptions'!$B$79/12,'Assumptions'!$B$80,'Assumptions'!$B$78),0) | I24: =IF(AND('Assumptions'!$B$76=1,7>'Assumptions'!$B$77,7<='Assumptions'!$B$77+'Assumptions'!$B$80),-PMT('Assumptions'!$B$79/12,'Assumptions'!$B$80,'Assumptions'!$B$78),0) | J24: =IF(AND('Assumptions'!$B$76=1,8>'Assumptions'!$B$77,8<='Assumptions'!$B$77+'Assumptions'!$B$80),-PMT('Assumptions'!$B$79/12,'Assumptions'!$B$80,'Assumptions'!$B$78),0) | K24: =IF(AND('Assumptions'!$B$76=1,9>'Assumptions'!$B$77,9<='Assumptions'!$B$77+'Assumptions'!$B$80),-PMT('Assumptions'!$B$79/12,'Assumptions'!$B$80,'Assumptions'!$B$78),0) | L24: =IF(AND('Assumptions'!$B$76=1,10>'Assumptions'!$B$77,10<='Assumptions'!$B$77+'Assumptions'!$B$80),-PMT('Assumptions'!$B$79/12,'Assumptions'!$B$80,'Assumptions'!$B$78),0) | M24: =IF(AND('Assumptions'!$B$76=1,11>'Assumptions'!$B$77,11<='Assumptions'!$B$77+'Assumptions'!$B$80),-PMT('Assumptions'!$B$79/12,'Assumptions'!$B$80,'Assumptions'!$B$78),0) | N24: =IF(AND('Assumptions'!$B$76=1,12>'Assumptions'!$B$77,12<='Assumptions'!$B$77+'Assumptions'!$B$80),-PMT('Assumptions'!$B$79/12,'Assumptions'!$B$80,'Assumptions'!$B$78),0) | O24: =IF(AND('Assumptions'!$B$76=1,13>'Assumptions'!$B$77,13<='Assumptions'!$B$77+'Assumptions'!$B$80),-PMT('Assumptions'!$B$79/12,'Assumptions'!$B$80,'Assumptions'!$B$78),0) | P24: =IF(AND('Assumptions'!$B$76=1,14>'Assumptions'!$B$77,14<='Assumptions'!$B$77+'Assumptions'!$B$80),-PMT('Assumptions'!$B$79/12,'Assumptions'!$B$80,'Assumptions'!$B$78),0) | Q24: =IF(AND('Assumptions'!$B$76=1,15>'Assumptions'!$B$77,15<='Assumptions'!$B$77+'Assumptions'!$B$80),-PMT('Assumptions'!$B$79/12,'Assumptions'!$B$80,'Assumptions'!$B$78),0) | R24: =IF(AND('Assumptions'!$B$76=1,16>'Assumptions'!$B$77,16<='Assumptions'!$B$77+'Assumptions'!$B$80),-PMT('Assumptions'!$B$79/12,'Assumptions'!$B$80,'Assumptions'!$B$78),0) | S24: =IF(AND('Assumptions'!$B$76=1,17>'Assumptions'!$B$77,17<='Assumptions'!$B$77+'Assumptions'!$B$80),-PMT('Assumptions'!$B$79/12,'Assumptions'!$B$80,'Assumptions'!$B$78),0) | T24: =IF(AND('Assumptions'!$B$76=1,18>'Assumptions'!$B$77,18<='Assumptions'!$B$77+'Assumptions'!$B$80),-PMT('Assumptions'!$B$79/12,'Assumptions'!$B$80,'Assumptions'!$B$78),0) | U24: =IF(AND('Assumptions'!$B$76=1,19>'Assumptions'!$B$77,19<='Assumptions'!$B$77+'Assumptions'!$B$80),-PMT('Assumptions'!$B$79/12,'Assumptions'!$B$80,'Assumptions'!$B$78),0) | V24: =IF(AND('Assumptions'!$B$76=1,20>'Assumptions'!$B$77,20<='Assumptions'!$B$77+'Assumptions'!$B$80),-PMT('Assumptions'!$B$79/12,'Assumptions'!$B$80,'Assumptions'!$B$78),0) | W24: =IF(AND('Assumptions'!$B$76=1,21>'Assumptions'!$B$77,21<='Assumptions'!$B$77+'Assumptions'!$B$80),-PMT('Assumptions'!$B$79/12,'Assumptions'!$B$80,'Assumptions'!$B$78),0) | X24: =IF(AND('Assumptions'!$B$76=1,22>'Assumptions'!$B$77,22<='Assumptions'!$B$77+'Assumptions'!$B$80),-PMT('Assumptions'!$B$79/12,'Assumptions'!$B$80,'Assumptions'!$B$78),0) | Y24: =IF(AND('Assumptions'!$B$76=1,23>'Assumptions'!$B$77,23<='Assumptions'!$B$77+'Assumptions'!$B$80),-PMT('Assumptions'!$B$79/12,'Assumptions'!$B$80,'Assumptions'!$B$78),0) | Z24: =IF(AND('Assumptions'!$B$76=1,24>'Assumptions'!$B$77,24<='Assumptions'!$B$77+'Assumptions'!$B$80),-PMT('Assumptions'!$B$79/12,'Assumptions'!$B$80,'Assumptions'!$B$78),0) | AA24: =IF(AND('Assumptions'!$B$76=1,25>'Assumptions'!$B$77,25<='Assumptions'!$B$77+'Assumptions'!$B$80),-PMT('Assumptions'!$B$79/12,'Assumptions'!$B$80,'Assumptions'!$B$78),0) | AB24: =IF(AND('Assumptions'!$B$76=1,26>'Assumptions'!$B$77,26<='Assumptions'!$B$77+'Assumptions'!$B$80),-PMT('Assumptions'!$B$79/12,'Assumptions'!$B$80,'Assumptions'!$B$78),0) | AC24: =IF(AND('Assumptions'!$B$76=1,27>'Assumptions'!$B$77,27<='Assumptions'!$B$77+'Assumptions'!$B$80),-PMT('Assumptions'!$B$79/12,'Assumptions'!$B$80,'Assumptions'!$B$78),0) | AD24: =IF(AND('Assumptions'!$B$76=1,28>'Assumptions'!$B$77,28<='Assumptions'!$B$77+'Assumptions'!$B$80),-PMT('Assumptions'!$B$79/12,'Assumptions'!$B$80,'Assumptions'!$B$78),0) | AE24: =IF(AND('Assumptions'!$B$76=1,29>'Assumptions'!$B$77,29<='Assumptions'!$B$77+'Assumptions'!$B$80),-PMT('Assumptions'!$B$79/12,'Assumptions'!$B$80,'Assumptions'!$B$78),0) | AF24: =IF(AND('Assumptions'!$B$76=1,30>'Assumptions'!$B$77,30<='Assumptions'!$B$77+'Assumptions'!$B$80),-PMT('Assumptions'!$B$79/12,'Assumptions'!$B$80,'Assumptions'!$B$78),0) | AG24: =IF(AND('Assumptions'!$B$76=1,31>'Assumptions'!$B$77,31<='Assumptions'!$B$77+'Assumptions'!$B$80),-PMT('Assumptions'!$B$79/12,'Assumptions'!$B$80,'Assumptions'!$B$78),0) | AH24: =IF(AND('Assumptions'!$B$76=1,32>'Assumptions'!$B$77,32<='Assumptions'!$B$77+'Assumptions'!$B$80),-PMT('Assumptions'!$B$79/12,'Assumptions'!$B$80,'Assumptions'!$B$78),0) | AI24: =IF(AND('Assumptions'!$B$76=1,33>'Assumptions'!$B$77,33<='Assumptions'!$B$77+'Assumptions'!$B$80),-PMT('Assumptions'!$B$79/12,'Assumptions'!$B$80,'Assumptions'!$B$78),0) | AJ24: =IF(AND('Assumptions'!$B$76=1,34>'Assumptions'!$B$77,34<='Assumptions'!$B$77+'Assumptions'!$B$80),-PMT('Assumptions'!$B$79/12,'Assumptions'!$B$80,'Assumptions'!$B$78),0) | AK24: =IF(AND('Assumptions'!$B$76=1,35>'Assumptions'!$B$77,35<='Assumptions'!$B$77+'Assumptions'!$B$80),-PMT('Assumptions'!$B$79/12,'Assumptions'!$B$80,'Assumptions'!$B$78),0) | AL24: =IF(AND('Assumptions'!$B$76=1,36>'Assumptions'!$B$77,36<='Assumptions'!$B$77+'Assumptions'!$B$80),-PMT('Assumptions'!$B$79/12,'Assumptions'!$B$80,'Assumptions'!$B$78),0)
A25: Refi balance (end) | C25: =IF('Assumptions'!$B$76=0,0,IF(1<'Assumptions'!$B$77,0,IF(1='Assumptions'!$B$77,'Assumptions'!$B$78,MAX(0,0*(1+'Assumptions'!$B$79/12)-C24)))) | D25: =IF('Assumptions'!$B$76=0,0,IF(2<'Assumptions'!$B$77,0,IF(2='Assumptions'!$B$77,'Assumptions'!$B$78,MAX(0,C25*(1+'Assumptions'!$B$79/12)-D24)))) | E25: =IF('Assumptions'!$B$76=0,0,IF(3<'Assumptions'!$B$77,0,IF(3='Assumptions'!$B$77,'Assumptions'!$B$78,MAX(0,D25*(1+'Assumptions'!$B$79/12)-E24)))) | F25: =IF('Assumptions'!$B$76=0,0,IF(4<'Assumptions'!$B$77,0,IF(4='Assumptions'!$B$77,'Assumptions'!$B$78,MAX(0,E25*(1+'Assumptions'!$B$79/12)-F24)))) | G25: =IF('Assumptions'!$B$76=0,0,IF(5<'Assumptions'!$B$77,0,IF(5='Assumptions'!$B$77,'Assumptions'!$B$78,MAX(0,F25*(1+'Assumptions'!$B$79/12)-G24)))) | H25: =IF('Assumptions'!$B$76=0,0,IF(6<'Assumptions'!$B$77,0,IF(6='Assumptions'!$B$77,'Assumptions'!$B$78,MAX(0,G25*(1+'Assumptions'!$B$79/12)-H24)))) | I25: =IF('Assumptions'!$B$76=0,0,IF(7<'Assumptions'!$B$77,0,IF(7='Assumptions'!$B$77,'Assumptions'!$B$78,MAX(0,H25*(1+'Assumptions'!$B$79/12)-I24)))) | J25: =IF('Assumptions'!$B$76=0,0,IF(8<'Assumptions'!$B$77,0,IF(8='Assumptions'!$B$77,'Assumptions'!$B$78,MAX(0,I25*(1+'Assumptions'!$B$79/12)-J24)))) | K25: =IF('Assumptions'!$B$76=0,0,IF(9<'Assumptions'!$B$77,0,IF(9='Assumptions'!$B$77,'Assumptions'!$B$78,MAX(0,J25*(1+'Assumptions'!$B$79/12)-K24)))) | L25: =IF('Assumptions'!$B$76=0,0,IF(10<'Assumptions'!$B$77,0,IF(10='Assumptions'!$B$77,'Assumptions'!$B$78,MAX(0,K25*(1+'Assumptions'!$B$79/12)-L24)))) | M25: =IF('Assumptions'!$B$76=0,0,IF(11<'Assumptions'!$B$77,0,IF(11='Assumptions'!$B$77,'Assumptions'!$B$78,MAX(0,L25*(1+'Assumptions'!$B$79/12)-M24)))) | N25: =IF('Assumptions'!$B$76=0,0,IF(12<'Assumptions'!$B$77,0,IF(12='Assumptions'!$B$77,'Assumptions'!$B$78,MAX(0,M25*(1+'Assumptions'!$B$79/12)-N24)))) | O25: =IF('Assumptions'!$B$76=0,0,IF(13<'Assumptions'!$B$77,0,IF(13='Assumptions'!$B$77,'Assumptions'!$B$78,MAX(0,N25*(1+'Assumptions'!$B$79/12)-O24)))) | P25: =IF('Assumptions'!$B$76=0,0,IF(14<'Assumptions'!$B$77,0,IF(14='Assumptions'!$B$77,'Assumptions'!$B$78,MAX(0,O25*(1+'Assumptions'!$B$79/12)-P24)))) | Q25: =IF('Assumptions'!$B$76=0,0,IF(15<'Assumptions'!$B$77,0,IF(15='Assumptions'!$B$77,'Assumptions'!$B$78,MAX(0,P25*(1+'Assumptions'!$B$79/12)-Q24)))) | R25: =IF('Assumptions'!$B$76=0,0,IF(16<'Assumptions'!$B$77,0,IF(16='Assumptions'!$B$77,'Assumptions'!$B$78,MAX(0,Q25*(1+'Assumptions'!$B$79/12)-R24)))) | S25: =IF('Assumptions'!$B$76=0,0,IF(17<'Assumptions'!$B$77,0,IF(17='Assumptions'!$B$77,'Assumptions'!$B$78,MAX(0,R25*(1+'Assumptions'!$B$79/12)-S24)))) | T25: =IF('Assumptions'!$B$76=0,0,IF(18<'Assumptions'!$B$77,0,IF(18='Assumptions'!$B$77,'Assumptions'!$B$78,MAX(0,S25*(1+'Assumptions'!$B$79/12)-T24)))) | U25: =IF('Assumptions'!$B$76=0,0,IF(19<'Assumptions'!$B$77,0,IF(19='Assumptions'!$B$77,'Assumptions'!$B$78,MAX(0,T25*(1+'Assumptions'!$B$79/12)-U24)))) | V25: =IF('Assumptions'!$B$76=0,0,IF(20<'Assumptions'!$B$77,0,IF(20='Assumptions'!$B$77,'Assumptions'!$B$78,MAX(0,U25*(1+'Assumptions'!$B$79/12)-V24)))) | W25: =IF('Assumptions'!$B$76=0,0,IF(21<'Assumptions'!$B$77,0,IF(21='Assumptions'!$B$77,'Assumptions'!$B$78,MAX(0,V25*(1+'Assumptions'!$B$79/12)-W24)))) | X25: =IF('Assumptions'!$B$76=0,0,IF(22<'Assumptions'!$B$77,0,IF(22='Assumptions'!$B$77,'Assumptions'!$B$78,MAX(0,W25*(1+'Assumptions'!$B$79/12)-X24)))) | Y25: =IF('Assumptions'!$B$76=0,0,IF(23<'Assumptions'!$B$77,0,IF(23='Assumptions'!$B$77,'Assumptions'!$B$78,MAX(0,X25*(1+'Assumptions'!$B$79/12)-Y24)))) | Z25: =IF('Assumptions'!$B$76=0,0,IF(24<'Assumptions'!$B$77,0,IF(24='Assumptions'!$B$77,'Assumptions'!$B$78,MAX(0,Y25*(1+'Assumptions'!$B$79/12)-Z24)))) | AA25: =IF('Assumptions'!$B$76=0,0,IF(25<'Assumptions'!$B$77,0,IF(25='Assumptions'!$B$77,'Assumptions'!$B$78,MAX(0,Z25*(1+'Assumptions'!$B$79/12)-AA24)))) | AB25: =IF('Assumptions'!$B$76=0,0,IF(26<'Assumptions'!$B$77,0,IF(26='Assumptions'!$B$77,'Assumptions'!$B$78,MAX(0,AA25*(1+'Assumptions'!$B$79/12)-AB24)))) | AC25: =IF('Assumptions'!$B$76=0,0,IF(27<'Assumptions'!$B$77,0,IF(27='Assumptions'!$B$77,'Assumptions'!$B$78,MAX(0,AB25*(1+'Assumptions'!$B$79/12)-AC24)))) | AD25: =IF('Assumptions'!$B$76=0,0,IF(28<'Assumptions'!$B$77,0,IF(28='Assumptions'!$B$77,'Assumptions'!$B$78,MAX(0,AC25*(1+'Assumptions'!$B$79/12)-AD24)))) | AE25: =IF('Assumptions'!$B$76=0,0,IF(29<'Assumptions'!$B$77,0,IF(29='Assumptions'!$B$77,'Assumptions'!$B$78,MAX(0,AD25*(1+'Assumptions'!$B$79/12)-AE24)))) | AF25: =IF('Assumptions'!$B$76=0,0,IF(30<'Assumptions'!$B$77,0,IF(30='Assumptions'!$B$77,'Assumptions'!$B$78,MAX(0,AE25*(1+'Assumptions'!$B$79/12)-AF24)))) | AG25: =IF('Assumptions'!$B$76=0,0,IF(31<'Assumptions'!$B$77,0,IF(31='Assumptions'!$B$77,'Assumptions'!$B$78,MAX(0,AF25*(1+'Assumptions'!$B$79/12)-AG24)))) | AH25: =IF('Assumptions'!$B$76=0,0,IF(32<'Assumptions'!$B$77,0,IF(32='Assumptions'!$B$77,'Assumptions'!$B$78,MAX(0,AG25*(1+'Assumptions'!$B$79/12)-AH24)))) | AI25: =IF('Assumptions'!$B$76=0,0,IF(33<'Assumptions'!$B$77,0,IF(33='Assumptions'!$B$77,'Assumptions'!$B$78,MAX(0,AH25*(1+'Assumptions'!$B$79/12)-AI24)))) | AJ25: =IF('Assumptions'!$B$76=0,0,IF(34<'Assumptions'!$B$77,0,IF(34='Assumptions'!$B$77,'Assumptions'!$B$78,MAX(0,AI25*(1+'Assumptions'!$B$79/12)-AJ24)))) | AK25: =IF('Assumptions'!$B$76=0,0,IF(35<'Assumptions'!$B$77,0,IF(35='Assumptions'!$B$77,'Assumptions'!$B$78,MAX(0,AJ25*(1+'Assumptions'!$B$79/12)-AK24)))) | AL25: =IF('Assumptions'!$B$76=0,0,IF(36<'Assumptions'!$B$77,0,IF(36='Assumptions'!$B$77,'Assumptions'!$B$78,MAX(0,AK25*(1+'Assumptions'!$B$79/12)-AL24))))
A26: Refi interest | C26: =0*'Assumptions'!$B$79/12*(C24>0) | D26: =C25*'Assumptions'!$B$79/12*(D24>0) | E26: =D25*'Assumptions'!$B$79/12*(E24>0) | F26: =E25*'Assumptions'!$B$79/12*(F24>0) | G26: =F25*'Assumptions'!$B$79/12*(G24>0) | H26: =G25*'Assumptions'!$B$79/12*(H24>0) | I26: =H25*'Assumptions'!$B$79/12*(I24>0) | J26: =I25*'Assumptions'!$B$79/12*(J24>0) | K26: =J25*'Assumptions'!$B$79/12*(K24>0) | ... AL26: =AK25*'Assumptions'!$B$79/12*(AL24>0)
A27: SBA payment (P&I) / interest | C27: =IF(AND('Assumptions'!$B$81=1,1>'Assumptions'!$B$82),-PMT('Assumptions'!$B$84/12,'Assumptions'!$B$85,'Assumptions'!$B$83),0) | D27: =IF(AND('Assumptions'!$B$81=1,2>'Assumptions'!$B$82),-PMT('Assumptions'!$B$84/12,'Assumptions'!$B$85,'Assumptions'!$B$83),0) | E27: =IF(AND('Assumptions'!$B$81=1,3>'Assumptions'!$B$82),-PMT('Assumptions'!$B$84/12,'Assumptions'!$B$85,'Assumptions'!$B$83),0) | F27: =IF(AND('Assumptions'!$B$81=1,4>'Assumptions'!$B$82),-PMT('Assumptions'!$B$84/12,'Assumptions'!$B$85,'Assumptions'!$B$83),0) | G27: =IF(AND('Assumptions'!$B$81=1,5>'Assumptions'!$B$82),-PMT('Assumptions'!$B$84/12,'Assumptions'!$B$85,'Assumptions'!$B$83),0) | H27: =IF(AND('Assumptions'!$B$81=1,6>'Assumptions'!$B$82),-PMT('Assumptions'!$B$84/12,'Assumptions'!$B$85,'Assumptions'!$B$83),0) | I27: =IF(AND('Assumptions'!$B$81=1,7>'Assumptions'!$B$82),-PMT('Assumptions'!$B$84/12,'Assumptions'!$B$85,'Assumptions'!$B$83),0) | J27: =IF(AND('Assumptions'!$B$81=1,8>'Assumptions'!$B$82),-PMT('Assumptions'!$B$84/12,'Assumptions'!$B$85,'Assumptions'!$B$83),0) | K27: =IF(AND('Assumptions'!$B$81=1,9>'Assumptions'!$B$82),-PMT('Assumptions'!$B$84/12,'Assumptions'!$B$85,'Assumptions'!$B$83),0) | L27: =IF(AND('Assumptions'!$B$81=1,10>'Assumptions'!$B$82),-PMT('Assumptions'!$B$84/12,'Assumptions'!$B$85,'Assumptions'!$B$83),0) | M27: =IF(AND('Assumptions'!$B$81=1,11>'Assumptions'!$B$82),-PMT('Assumptions'!$B$84/12,'Assumptions'!$B$85,'Assumptions'!$B$83),0) | N27: =IF(AND('Assumptions'!$B$81=1,12>'Assumptions'!$B$82),-PMT('Assumptions'!$B$84/12,'Assumptions'!$B$85,'Assumptions'!$B$83),0) | O27: =IF(AND('Assumptions'!$B$81=1,13>'Assumptions'!$B$82),-PMT('Assumptions'!$B$84/12,'Assumptions'!$B$85,'Assumptions'!$B$83),0) | P27: =IF(AND('Assumptions'!$B$81=1,14>'Assumptions'!$B$82),-PMT('Assumptions'!$B$84/12,'Assumptions'!$B$85,'Assumptions'!$B$83),0) | Q27: =IF(AND('Assumptions'!$B$81=1,15>'Assumptions'!$B$82),-PMT('Assumptions'!$B$84/12,'Assumptions'!$B$85,'Assumptions'!$B$83),0) | R27: =IF(AND('Assumptions'!$B$81=1,16>'Assumptions'!$B$82),-PMT('Assumptions'!$B$84/12,'Assumptions'!$B$85,'Assumptions'!$B$83),0) | S27: =IF(AND('Assumptions'!$B$81=1,17>'Assumptions'!$B$82),-PMT('Assumptions'!$B$84/12,'Assumptions'!$B$85,'Assumptions'!$B$83),0) | T27: =IF(AND('Assumptions'!$B$81=1,18>'Assumptions'!$B$82),-PMT('Assumptions'!$B$84/12,'Assumptions'!$B$85,'Assumptions'!$B$83),0) | U27: =IF(AND('Assumptions'!$B$81=1,19>'Assumptions'!$B$82),-PMT('Assumptions'!$B$84/12,'Assumptions'!$B$85,'Assumptions'!$B$83),0) | V27: =IF(AND('Assumptions'!$B$81=1,20>'Assumptions'!$B$82),-PMT('Assumptions'!$B$84/12,'Assumptions'!$B$85,'Assumptions'!$B$83),0) | W27: =IF(AND('Assumptions'!$B$81=1,21>'Assumptions'!$B$82),-PMT('Assumptions'!$B$84/12,'Assumptions'!$B$85,'Assumptions'!$B$83),0) | X27: =IF(AND('Assumptions'!$B$81=1,22>'Assumptions'!$B$82),-PMT('Assumptions'!$B$84/12,'Assumptions'!$B$85,'Assumptions'!$B$83),0) | Y27: =IF(AND('Assumptions'!$B$81=1,23>'Assumptions'!$B$82),-PMT('Assumptions'!$B$84/12,'Assumptions'!$B$85,'Assumptions'!$B$83),0) | Z27: =IF(AND('Assumptions'!$B$81=1,24>'Assumptions'!$B$82),-PMT('Assumptions'!$B$84/12,'Assumptions'!$B$85,'Assumptions'!$B$83),0) | AA27: =IF(AND('Assumptions'!$B$81=1,25>'Assumptions'!$B$82),-PMT('Assumptions'!$B$84/12,'Assumptions'!$B$85,'Assumptions'!$B$83),0) | AB27: =IF(AND('Assumptions'!$B$81=1,26>'Assumptions'!$B$82),-PMT('Assumptions'!$B$84/12,'Assumptions'!$B$85,'Assumptions'!$B$83),0) | AC27: =IF(AND('Assumptions'!$B$81=1,27>'Assumptions'!$B$82),-PMT('Assumptions'!$B$84/12,'Assumptions'!$B$85,'Assumptions'!$B$83),0) | AD27: =IF(AND('Assumptions'!$B$81=1,28>'Assumptions'!$B$82),-PMT('Assumptions'!$B$84/12,'Assumptions'!$B$85,'Assumptions'!$B$83),0) | AE27: =IF(AND('Assumptions'!$B$81=1,29>'Assumptions'!$B$82),-PMT('Assumptions'!$B$84/12,'Assumptions'!$B$85,'Assumptions'!$B$83),0) | AF27: =IF(AND('Assumptions'!$B$81=1,30>'Assumptions'!$B$82),-PMT('Assumptions'!$B$84/12,'Assumptions'!$B$85,'Assumptions'!$B$83),0) | AG27: =IF(AND('Assumptions'!$B$81=1,31>'Assumptions'!$B$82),-PMT('Assumptions'!$B$84/12,'Assumptions'!$B$85,'Assumptions'!$B$83),0) | AH27: =IF(AND('Assumptions'!$B$81=1,32>'Assumptions'!$B$82),-PMT('Assumptions'!$B$84/12,'Assumptions'!$B$85,'Assumptions'!$B$83),0) | AI27: =IF(AND('Assumptions'!$B$81=1,33>'Assumptions'!$B$82),-PMT('Assumptions'!$B$84/12,'Assumptions'!$B$85,'Assumptions'!$B$83),0) | AJ27: =IF(AND('Assumptions'!$B$81=1,34>'Assumptions'!$B$82),-PMT('Assumptions'!$B$84/12,'Assumptions'!$B$85,'Assumptions'!$B$83),0) | AK27: =IF(AND('Assumptions'!$B$81=1,35>'Assumptions'!$B$82),-PMT('Assumptions'!$B$84/12,'Assumptions'!$B$85,'Assumptions'!$B$83),0) | AL27: =IF(AND('Assumptions'!$B$81=1,36>'Assumptions'!$B$82),-PMT('Assumptions'!$B$84/12,'Assumptions'!$B$85,'Assumptions'!$B$83),0)
A28: Balloon refinance amount (funds Jan balloon when refi OFF) | B28: =IF('Assumptions'!$B$76=1,0,SUMPRODUCT(($C$4:$AL$4='Assumptions'!$B$73)*($C$20:$AL$20+$C$21:$AL$21)))
A29: Balloon-refi payment (P&I, from month after balloon) | C29: =IF(AND('Assumptions'!$B$76=0,1>'Assumptions'!$B$73,1<='Assumptions'!$B$73+'Assumptions'!$B$75),-PMT('Assumptions'!$B$74/12,'Assumptions'!$B$75,$B$28),0) | D29: =IF(AND('Assumptions'!$B$76=0,2>'Assumptions'!$B$73,2<='Assumptions'!$B$73+'Assumptions'!$B$75),-PMT('Assumptions'!$B$74/12,'Assumptions'!$B$75,$B$28),0) | E29: =IF(AND('Assumptions'!$B$76=0,3>'Assumptions'!$B$73,3<='Assumptions'!$B$73+'Assumptions'!$B$75),-PMT('Assumptions'!$B$74/12,'Assumptions'!$B$75,$B$28),0) | F29: =IF(AND('Assumptions'!$B$76=0,4>'Assumptions'!$B$73,4<='Assumptions'!$B$73+'Assumptions'!$B$75),-PMT('Assumptions'!$B$74/12,'Assumptions'!$B$75,$B$28),0) | G29: =IF(AND('Assumptions'!$B$76=0,5>'Assumptions'!$B$73,5<='Assumptions'!$B$73+'Assumptions'!$B$75),-PMT('Assumptions'!$B$74/12,'Assumptions'!$B$75,$B$28),0) | H29: =IF(AND('Assumptions'!$B$76=0,6>'Assumptions'!$B$73,6<='Assumptions'!$B$73+'Assumptions'!$B$75),-PMT('Assumptions'!$B$74/12,'Assumptions'!$B$75,$B$28),0) | I29: =IF(AND('Assumptions'!$B$76=0,7>'Assumptions'!$B$73,7<='Assumptions'!$B$73+'Assumptions'!$B$75),-PMT('Assumptions'!$B$74/12,'Assumptions'!$B$75,$B$28),0) | J29: =IF(AND('Assumptions'!$B$76=0,8>'Assumptions'!$B$73,8<='Assumptions'!$B$73+'Assumptions'!$B$75),-PMT('Assumptions'!$B$74/12,'Assumptions'!$B$75,$B$28),0) | K29: =IF(AND('Assumptions'!$B$76=0,9>'Assumptions'!$B$73,9<='Assumptions'!$B$73+'Assumptions'!$B$75),-PMT('Assumptions'!$B$74/12,'Assumptions'!$B$75,$B$28),0) | L29: =IF(AND('Assumptions'!$B$76=0,10>'Assumptions'!$B$73,10<='Assumptions'!$B$73+'Assumptions'!$B$75),-PMT('Assumptions'!$B$74/12,'Assumptions'!$B$75,$B$28),0) | M29: =IF(AND('Assumptions'!$B$76=0,11>'Assumptions'!$B$73,11<='Assumptions'!$B$73+'Assumptions'!$B$75),-PMT('Assumptions'!$B$74/12,'Assumptions'!$B$75,$B$28),0) | N29: =IF(AND('Assumptions'!$B$76=0,12>'Assumptions'!$B$73,12<='Assumptions'!$B$73+'Assumptions'!$B$75),-PMT('Assumptions'!$B$74/12,'Assumptions'!$B$75,$B$28),0) | O29: =IF(AND('Assumptions'!$B$76=0,13>'Assumptions'!$B$73,13<='Assumptions'!$B$73+'Assumptions'!$B$75),-PMT('Assumptions'!$B$74/12,'Assumptions'!$B$75,$B$28),0) | P29: =IF(AND('Assumptions'!$B$76=0,14>'Assumptions'!$B$73,14<='Assumptions'!$B$73+'Assumptions'!$B$75),-PMT('Assumptions'!$B$74/12,'Assumptions'!$B$75,$B$28),0) | Q29: =IF(AND('Assumptions'!$B$76=0,15>'Assumptions'!$B$73,15<='Assumptions'!$B$73+'Assumptions'!$B$75),-PMT('Assumptions'!$B$74/12,'Assumptions'!$B$75,$B$28),0) | R29: =IF(AND('Assumptions'!$B$76=0,16>'Assumptions'!$B$73,16<='Assumptions'!$B$73+'Assumptions'!$B$75),-PMT('Assumptions'!$B$74/12,'Assumptions'!$B$75,$B$28),0) | S29: =IF(AND('Assumptions'!$B$76=0,17>'Assumptions'!$B$73,17<='Assumptions'!$B$73+'Assumptions'!$B$75),-PMT('Assumptions'!$B$74/12,'Assumptions'!$B$75,$B$28),0) | T29: =IF(AND('Assumptions'!$B$76=0,18>'Assumptions'!$B$73,18<='Assumptions'!$B$73+'Assumptions'!$B$75),-PMT('Assumptions'!$B$74/12,'Assumptions'!$B$75,$B$28),0) | U29: =IF(AND('Assumptions'!$B$76=0,19>'Assumptions'!$B$73,19<='Assumptions'!$B$73+'Assumptions'!$B$75),-PMT('Assumptions'!$B$74/12,'Assumptions'!$B$75,$B$28),0) | V29: =IF(AND('Assumptions'!$B$76=0,20>'Assumptions'!$B$73,20<='Assumptions'!$B$73+'Assumptions'!$B$75),-PMT('Assumptions'!$B$74/12,'Assumptions'!$B$75,$B$28),0) | W29: =IF(AND('Assumptions'!$B$76=0,21>'Assumptions'!$B$73,21<='Assumptions'!$B$73+'Assumptions'!$B$75),-PMT('Assumptions'!$B$74/12,'Assumptions'!$B$75,$B$28),0) | X29: =IF(AND('Assumptions'!$B$76=0,22>'Assumptions'!$B$73,22<='Assumptions'!$B$73+'Assumptions'!$B$75),-PMT('Assumptions'!$B$74/12,'Assumptions'!$B$75,$B$28),0) | Y29: =IF(AND('Assumptions'!$B$76=0,23>'Assumptions'!$B$73,23<='Assumptions'!$B$73+'Assumptions'!$B$75),-PMT('Assumptions'!$B$74/12,'Assumptions'!$B$75,$B$28),0) | Z29: =IF(AND('Assumptions'!$B$76=0,24>'Assumptions'!$B$73,24<='Assumptions'!$B$73+'Assumptions'!$B$75),-PMT('Assumptions'!$B$74/12,'Assumptions'!$B$75,$B$28),0) | AA29: =IF(AND('Assumptions'!$B$76=0,25>'Assumptions'!$B$73,25<='Assumptions'!$B$73+'Assumptions'!$B$75),-PMT('Assumptions'!$B$74/12,'Assumptions'!$B$75,$B$28),0) | AB29: =IF(AND('Assumptions'!$B$76=0,26>'Assumptions'!$B$73,26<='Assumptions'!$B$73+'Assumptions'!$B$75),-PMT('Assumptions'!$B$74/12,'Assumptions'!$B$75,$B$28),0) | AC29: =IF(AND('Assumptions'!$B$76=0,27>'Assumptions'!$B$73,27<='Assumptions'!$B$73+'Assumptions'!$B$75),-PMT('Assumptions'!$B$74/12,'Assumptions'!$B$75,$B$28),0) | AD29: =IF(AND('Assumptions'!$B$76=0,28>'Assumptions'!$B$73,28<='Assumptions'!$B$73+'Assumptions'!$B$75),-PMT('Assumptions'!$B$74/12,'Assumptions'!$B$75,$B$28),0) | AE29: =IF(AND('Assumptions'!$B$76=0,29>'Assumptions'!$B$73,29<='Assumptions'!$B$73+'Assumptions'!$B$75),-PMT('Assumptions'!$B$74/12,'Assumptions'!$B$75,$B$28),0) | AF29: =IF(AND('Assumptions'!$B$76=0,30>'Assumptions'!$B$73,30<='Assumptions'!$B$73+'Assumptions'!$B$75),-PMT('Assumptions'!$B$74/12,'Assumptions'!$B$75,$B$28),0) | AG29: =IF(AND('Assumptions'!$B$76=0,31>'Assumptions'!$B$73,31<='Assumptions'!$B$73+'Assumptions'!$B$75),-PMT('Assumptions'!$B$74/12,'Assumptions'!$B$75,$B$28),0) | AH29: =IF(AND('Assumptions'!$B$76=0,32>'Assumptions'!$B$73,32<='Assumptions'!$B$73+'Assumptions'!$B$75),-PMT('Assumptions'!$B$74/12,'Assumptions'!$B$75,$B$28),0) | AI29: =IF(AND('Assumptions'!$B$76=0,33>'Assumptions'!$B$73,33<='Assumptions'!$B$73+'Assumptions'!$B$75),-PMT('Assumptions'!$B$74/12,'Assumptions'!$B$75,$B$28),0) | AJ29: =IF(AND('Assumptions'!$B$76=0,34>'Assumptions'!$B$73,34<='Assumptions'!$B$73+'Assumptions'!$B$75),-PMT('Assumptions'!$B$74/12,'Assumptions'!$B$75,$B$28),0) | AK29: =IF(AND('Assumptions'!$B$76=0,35>'Assumptions'!$B$73,35<='Assumptions'!$B$73+'Assumptions'!$B$75),-PMT('Assumptions'!$B$74/12,'Assumptions'!$B$75,$B$28),0) | AL29: =IF(AND('Assumptions'!$B$76=0,36>'Assumptions'!$B$73,36<='Assumptions'!$B$73+'Assumptions'!$B$75),-PMT('Assumptions'!$B$74/12,'Assumptions'!$B$75,$B$28),0)
A30: Balloon-refi balance (end) | C30: =IF('Assumptions'!$B$76=1,0,IF(1<'Assumptions'!$B$73,0,IF(1='Assumptions'!$B$73,$B$28,MAX(0,0*(1+'Assumptions'!$B$74/12)-C29)))) | D30: =IF('Assumptions'!$B$76=1,0,IF(2<'Assumptions'!$B$73,0,IF(2='Assumptions'!$B$73,$B$28,MAX(0,C30*(1+'Assumptions'!$B$74/12)-D29)))) | E30: =IF('Assumptions'!$B$76=1,0,IF(3<'Assumptions'!$B$73,0,IF(3='Assumptions'!$B$73,$B$28,MAX(0,D30*(1+'Assumptions'!$B$74/12)-E29)))) | F30: =IF('Assumptions'!$B$76=1,0,IF(4<'Assumptions'!$B$73,0,IF(4='Assumptions'!$B$73,$B$28,MAX(0,E30*(1+'Assumptions'!$B$74/12)-F29)))) | G30: =IF('Assumptions'!$B$76=1,0,IF(5<'Assumptions'!$B$73,0,IF(5='Assumptions'!$B$73,$B$28,MAX(0,F30*(1+'Assumptions'!$B$74/12)-G29)))) | H30: =IF('Assumptions'!$B$76=1,0,IF(6<'Assumptions'!$B$73,0,IF(6='Assumptions'!$B$73,$B$28,MAX(0,G30*(1+'Assumptions'!$B$74/12)-H29)))) | I30: =IF('Assumptions'!$B$76=1,0,IF(7<'Assumptions'!$B$73,0,IF(7='Assumptions'!$B$73,$B$28,MAX(0,H30*(1+'Assumptions'!$B$74/12)-I29)))) | J30: =IF('Assumptions'!$B$76=1,0,IF(8<'Assumptions'!$B$73,0,IF(8='Assumptions'!$B$73,$B$28,MAX(0,I30*(1+'Assumptions'!$B$74/12)-J29)))) | K30: =IF('Assumptions'!$B$76=1,0,IF(9<'Assumptions'!$B$73,0,IF(9='Assumptions'!$B$73,$B$28,MAX(0,J30*(1+'Assumptions'!$B$74/12)-K29)))) | L30: =IF('Assumptions'!$B$76=1,0,IF(10<'Assumptions'!$B$73,0,IF(10='Assumptions'!$B$73,$B$28,MAX(0,K30*(1+'Assumptions'!$B$74/12)-L29)))) | M30: =IF('Assumptions'!$B$76=1,0,IF(11<'Assumptions'!$B$73,0,IF(11='Assumptions'!$B$73,$B$28,MAX(0,L30*(1+'Assumptions'!$B$74/12)-M29)))) | N30: =IF('Assumptions'!$B$76=1,0,IF(12<'Assumptions'!$B$73,0,IF(12='Assumptions'!$B$73,$B$28,MAX(0,M30*(1+'Assumptions'!$B$74/12)-N29)))) | O30: =IF('Assumptions'!$B$76=1,0,IF(13<'Assumptions'!$B$73,0,IF(13='Assumptions'!$B$73,$B$28,MAX(0,N30*(1+'Assumptions'!$B$74/12)-O29)))) | P30: =IF('Assumptions'!$B$76=1,0,IF(14<'Assumptions'!$B$73,0,IF(14='Assumptions'!$B$73,$B$28,MAX(0,O30*(1+'Assumptions'!$B$74/12)-P29)))) | Q30: =IF('Assumptions'!$B$76=1,0,IF(15<'Assumptions'!$B$73,0,IF(15='Assumptions'!$B$73,$B$28,MAX(0,P30*(1+'Assumptions'!$B$74/12)-Q29)))) | R30: =IF('Assumptions'!$B$76=1,0,IF(16<'Assumptions'!$B$73,0,IF(16='Assumptions'!$B$73,$B$28,MAX(0,Q30*(1+'Assumptions'!$B$74/12)-R29)))) | S30: =IF('Assumptions'!$B$76=1,0,IF(17<'Assumptions'!$B$73,0,IF(17='Assumptions'!$B$73,$B$28,MAX(0,R30*(1+'Assumptions'!$B$74/12)-S29)))) | T30: =IF('Assumptions'!$B$76=1,0,IF(18<'Assumptions'!$B$73,0,IF(18='Assumptions'!$B$73,$B$28,MAX(0,S30*(1+'Assumptions'!$B$74/12)-T29)))) | U30: =IF('Assumptions'!$B$76=1,0,IF(19<'Assumptions'!$B$73,0,IF(19='Assumptions'!$B$73,$B$28,MAX(0,T30*(1+'Assumptions'!$B$74/12)-U29)))) | V30: =IF('Assumptions'!$B$76=1,0,IF(20<'Assumptions'!$B$73,0,IF(20='Assumptions'!$B$73,$B$28,MAX(0,U30*(1+'Assumptions'!$B$74/12)-V29)))) | W30: =IF('Assumptions'!$B$76=1,0,IF(21<'Assumptions'!$B$73,0,IF(21='Assumptions'!$B$73,$B$28,MAX(0,V30*(1+'Assumptions'!$B$74/12)-W29)))) | X30: =IF('Assumptions'!$B$76=1,0,IF(22<'Assumptions'!$B$73,0,IF(22='Assumptions'!$B$73,$B$28,MAX(0,W30*(1+'Assumptions'!$B$74/12)-X29)))) | Y30: =IF('Assumptions'!$B$76=1,0,IF(23<'Assumptions'!$B$73,0,IF(23='Assumptions'!$B$73,$B$28,MAX(0,X30*(1+'Assumptions'!$B$74/12)-Y29)))) | Z30: =IF('Assumptions'!$B$76=1,0,IF(24<'Assumptions'!$B$73,0,IF(24='Assumptions'!$B$73,$B$28,MAX(0,Y30*(1+'Assumptions'!$B$74/12)-Z29)))) | AA30: =IF('Assumptions'!$B$76=1,0,IF(25<'Assumptions'!$B$73,0,IF(25='Assumptions'!$B$73,$B$28,MAX(0,Z30*(1+'Assumptions'!$B$74/12)-AA29)))) | AB30: =IF('Assumptions'!$B$76=1,0,IF(26<'Assumptions'!$B$73,0,IF(26='Assumptions'!$B$73,$B$28,MAX(0,AA30*(1+'Assumptions'!$B$74/12)-AB29)))) | AC30: =IF('Assumptions'!$B$76=1,0,IF(27<'Assumptions'!$B$73,0,IF(27='Assumptions'!$B$73,$B$28,MAX(0,AB30*(1+'Assumptions'!$B$74/12)-AC29)))) | AD30: =IF('Assumptions'!$B$76=1,0,IF(28<'Assumptions'!$B$73,0,IF(28='Assumptions'!$B$73,$B$28,MAX(0,AC30*(1+'Assumptions'!$B$74/12)-AD29)))) | AE30: =IF('Assumptions'!$B$76=1,0,IF(29<'Assumptions'!$B$73,0,IF(29='Assumptions'!$B$73,$B$28,MAX(0,AD30*(1+'Assumptions'!$B$74/12)-AE29)))) | AF30: =IF('Assumptions'!$B$76=1,0,IF(30<'Assumptions'!$B$73,0,IF(30='Assumptions'!$B$73,$B$28,MAX(0,AE30*(1+'Assumptions'!$B$74/12)-AF29)))) | AG30: =IF('Assumptions'!$B$76=1,0,IF(31<'Assumptions'!$B$73,0,IF(31='Assumptions'!$B$73,$B$28,MAX(0,AF30*(1+'Assumptions'!$B$74/12)-AG29)))) | AH30: =IF('Assumptions'!$B$76=1,0,IF(32<'Assumptions'!$B$73,0,IF(32='Assumptions'!$B$73,$B$28,MAX(0,AG30*(1+'Assumptions'!$B$74/12)-AH29)))) | AI30: =IF('Assumptions'!$B$76=1,0,IF(33<'Assumptions'!$B$73,0,IF(33='Assumptions'!$B$73,$B$28,MAX(0,AH30*(1+'Assumptions'!$B$74/12)-AI29)))) | AJ30: =IF('Assumptions'!$B$76=1,0,IF(34<'Assumptions'!$B$73,0,IF(34='Assumptions'!$B$73,$B$28,MAX(0,AI30*(1+'Assumptions'!$B$74/12)-AJ29)))) | AK30: =IF('Assumptions'!$B$76=1,0,IF(35<'Assumptions'!$B$73,0,IF(35='Assumptions'!$B$73,$B$28,MAX(0,AJ30*(1+'Assumptions'!$B$74/12)-AK29)))) | AL30: =IF('Assumptions'!$B$76=1,0,IF(36<'Assumptions'!$B$73,0,IF(36='Assumptions'!$B$73,$B$28,MAX(0,AK30*(1+'Assumptions'!$B$74/12)-AL29))))
A31: Balloon-refi interest | C31: =0*'Assumptions'!$B$74/12*(C29>0) | D31: =C30*'Assumptions'!$B$74/12*(D29>0) | E31: =D30*'Assumptions'!$B$74/12*(E29>0) | F31: =E30*'Assumptions'!$B$74/12*(F29>0) | G31: =F30*'Assumptions'!$B$74/12*(G29>0) | H31: =G30*'Assumptions'!$B$74/12*(H29>0) | I31: =H30*'Assumptions'!$B$74/12*(I29>0) | J31: =I30*'Assumptions'!$B$74/12*(J29>0) | K31: =J30*'Assumptions'!$B$74/12*(K29>0) | ... AL31: =AK30*'Assumptions'!$B$74/12*(AL29>0)
A32: NET INCOME
A33: Pre-tax income | C33: =C14+C15+C16-C19-C26-C31-IF('Assumptions'!$B$81=1,'Assumptions'!$B$83*'Assumptions'!$B$84/12,0)*(C27>0) | D33: =D14+D15+D16-D19-D26-D31-IF('Assumptions'!$B$81=1,'Assumptions'!$B$83*'Assumptions'!$B$84/12,0)*(D27>0) | E33: =E14+E15+E16-E19-E26-E31-IF('Assumptions'!$B$81=1,'Assumptions'!$B$83*'Assumptions'!$B$84/12,0)*(E27>0) | F33: =F14+F15+F16-F19-F26-F31-IF('Assumptions'!$B$81=1,'Assumptions'!$B$83*'Assumptions'!$B$84/12,0)*(F27>0) | G33: =G14+G15+G16-G19-G26-G31-IF('Assumptions'!$B$81=1,'Assumptions'!$B$83*'Assumptions'!$B$84/12,0)*(G27>0) | H33: =H14+H15+H16-H19-H26-H31-IF('Assumptions'!$B$81=1,'Assumptions'!$B$83*'Assumptions'!$B$84/12,0)*(H27>0) | I33: =I14+I15+I16-I19-I26-I31-IF('Assumptions'!$B$81=1,'Assumptions'!$B$83*'Assumptions'!$B$84/12,0)*(I27>0) | J33: =J14+J15+J16-J19-J26-J31-IF('Assumptions'!$B$81=1,'Assumptions'!$B$83*'Assumptions'!$B$84/12,0)*(J27>0) | ... AL33: =AL14+AL15+AL16-AL19-AL26-AL31-IF('Assumptions'!$B$81=1,'Assumptions'!$B$83*'Assumptions'!$B$84/12,0)*(AL27>0)
A34: TX margin tax | C34: =IF(C33>0,C8*'Assumptions'!$B$91,0) | D34: =IF(D33>0,D8*'Assumptions'!$B$91,0) | E34: =IF(E33>0,E8*'Assumptions'!$B$91,0) | F34: =IF(F33>0,F8*'Assumptions'!$B$91,0) | G34: =IF(G33>0,G8*'Assumptions'!$B$91,0) | H34: =IF(H33>0,H8*'Assumptions'!$B$91,0) | I34: =IF(I33>0,I8*'Assumptions'!$B$91,0) | J34: =IF(J33>0,J8*'Assumptions'!$B$91,0) | ... AL34: =IF(AL33>0,AL8*'Assumptions'!$B$91,0)
A35: NET INCOME | C35: =C33-C34 | D35: =D33-D34 | E35: =E33-E34 | F35: =F33-F34 | G35: =G33-G34 | H35: =H33-H34 | I35: =I33-I34 | J35: =J33-J34 | ... AL35: =AL33-AL34
A36: CASH (direct method)
A37: Cash collected | C37: ='Collections'!C11 | D37: ='Collections'!D11 | E37: ='Collections'!E11 | F37: ='Collections'!F11 | G37: ='Collections'!G11 | H37: ='Collections'!H11 | I37: ='Collections'!I11 | J37: ='Collections'!J11 | ... AL37: ='Collections'!AL11
A38: Payroll & labor paid (in month) | C38: =-'Payroll'!I37 | D38: =-'Payroll'!J37 | E38: =-'Payroll'!K37 | F38: =-'Payroll'!L37 | G38: =-'Payroll'!M37 | H38: =-'Payroll'!N37 | I38: =-'Payroll'!O37 | J38: =-'Payroll'!P37 | ... AL38: =-'Payroll'!AR37
A39: Vendors: G&A (in month) + patient costs & mileage (net-30) | C39: =-C12-C13-0 | D39: =-D12-D13-(C10+C11) | E39: =-E12-E13-(D10+D11) | F39: =-F12-F13-(E10+E11) | G39: =-G12-G13-(F10+F11) | H39: =-H12-H13-(G10+G11) | I39: =-I12-I13-(H10+H11) | J39: =-J12-J13-(I10+I11) | K39: =-K12-K13-(J10+J11) | ... AL39: =-AL12-AL13-(AK10+AK11)
A40: Seller payments (incl. down M1, interest at payoff) | C40: =-C20-C21-'Assumptions'!$B$68 | D40: =-D20-D21 | E40: =-E20-E21 | F40: =-F20-F21 | G40: =-G20-G21 | H40: =-H20-H21 | I40: =-I20-I21 | J40: =-J20-J21 | K40: =-K20-K21 | ... AL40: =-AL20-AL21
A41: Financing: refi/SBA/balloon-refi proceeds and payments | C41: =IF(AND('Assumptions'!$B$76=1,1='Assumptions'!$B$77),'Assumptions'!$B$78,0)-C24+IF(AND('Assumptions'!$B$76=0,1='Assumptions'!$B$73),$B$28,0)-C29+IF(AND('Assumptions'!$B$81=1,1='Assumptions'!$B$82),'Assumptions'!$B$83,0)-C27 | D41: =IF(AND('Assumptions'!$B$76=1,2='Assumptions'!$B$77),'Assumptions'!$B$78,0)-D24+IF(AND('Assumptions'!$B$76=0,2='Assumptions'!$B$73),$B$28,0)-D29+IF(AND('Assumptions'!$B$81=1,2='Assumptions'!$B$82),'Assumptions'!$B$83,0)-D27 | E41: =IF(AND('Assumptions'!$B$76=1,3='Assumptions'!$B$77),'Assumptions'!$B$78,0)-E24+IF(AND('Assumptions'!$B$76=0,3='Assumptions'!$B$73),$B$28,0)-E29+IF(AND('Assumptions'!$B$81=1,3='Assumptions'!$B$82),'Assumptions'!$B$83,0)-E27 | F41: =IF(AND('Assumptions'!$B$76=1,4='Assumptions'!$B$77),'Assumptions'!$B$78,0)-F24+IF(AND('Assumptions'!$B$76=0,4='Assumptions'!$B$73),$B$28,0)-F29+IF(AND('Assumptions'!$B$81=1,4='Assumptions'!$B$82),'Assumptions'!$B$83,0)-F27 | G41: =IF(AND('Assumptions'!$B$76=1,5='Assumptions'!$B$77),'Assumptions'!$B$78,0)-G24+IF(AND('Assumptions'!$B$76=0,5='Assumptions'!$B$73),$B$28,0)-G29+IF(AND('Assumptions'!$B$81=1,5='Assumptions'!$B$82),'Assumptions'!$B$83,0)-G27 | H41: =IF(AND('Assumptions'!$B$76=1,6='Assumptions'!$B$77),'Assumptions'!$B$78,0)-H24+IF(AND('Assumptions'!$B$76=0,6='Assumptions'!$B$73),$B$28,0)-H29+IF(AND('Assumptions'!$B$81=1,6='Assumptions'!$B$82),'Assumptions'!$B$83,0)-H27 | I41: =IF(AND('Assumptions'!$B$76=1,7='Assumptions'!$B$77),'Assumptions'!$B$78,0)-I24+IF(AND('Assumptions'!$B$76=0,7='Assumptions'!$B$73),$B$28,0)-I29+IF(AND('Assumptions'!$B$81=1,7='Assumptions'!$B$82),'Assumptions'!$B$83,0)-I27 | J41: =IF(AND('Assumptions'!$B$76=1,8='Assumptions'!$B$77),'Assumptions'!$B$78,0)-J24+IF(AND('Assumptions'!$B$76=0,8='Assumptions'!$B$73),$B$28,0)-J29+IF(AND('Assumptions'!$B$81=1,8='Assumptions'!$B$82),'Assumptions'!$B$83,0)-J27 | K41: =IF(AND('Assumptions'!$B$76=1,9='Assumptions'!$B$77),'Assumptions'!$B$78,0)-K24+IF(AND('Assumptions'!$B$76=0,9='Assumptions'!$B$73),$B$28,0)-K29+IF(AND('Assumptions'!$B$81=1,9='Assumptions'!$B$82),'Assumptions'!$B$83,0)-K27 | L41: =IF(AND('Assumptions'!$B$76=1,10='Assumptions'!$B$77),'Assumptions'!$B$78,0)-L24+IF(AND('Assumptions'!$B$76=0,10='Assumptions'!$B$73),$B$28,0)-L29+IF(AND('Assumptions'!$B$81=1,10='Assumptions'!$B$82),'Assumptions'!$B$83,0)-L27 | M41: =IF(AND('Assumptions'!$B$76=1,11='Assumptions'!$B$77),'Assumptions'!$B$78,0)-M24+IF(AND('Assumptions'!$B$76=0,11='Assumptions'!$B$73),$B$28,0)-M29+IF(AND('Assumptions'!$B$81=1,11='Assumptions'!$B$82),'Assumptions'!$B$83,0)-M27 | N41: =IF(AND('Assumptions'!$B$76=1,12='Assumptions'!$B$77),'Assumptions'!$B$78,0)-N24+IF(AND('Assumptions'!$B$76=0,12='Assumptions'!$B$73),$B$28,0)-N29+IF(AND('Assumptions'!$B$81=1,12='Assumptions'!$B$82),'Assumptions'!$B$83,0)-N27 | O41: =IF(AND('Assumptions'!$B$76=1,13='Assumptions'!$B$77),'Assumptions'!$B$78,0)-O24+IF(AND('Assumptions'!$B$76=0,13='Assumptions'!$B$73),$B$28,0)-O29+IF(AND('Assumptions'!$B$81=1,13='Assumptions'!$B$82),'Assumptions'!$B$83,0)-O27 | P41: =IF(AND('Assumptions'!$B$76=1,14='Assumptions'!$B$77),'Assumptions'!$B$78,0)-P24+IF(AND('Assumptions'!$B$76=0,14='Assumptions'!$B$73),$B$28,0)-P29+IF(AND('Assumptions'!$B$81=1,14='Assumptions'!$B$82),'Assumptions'!$B$83,0)-P27 | Q41: =IF(AND('Assumptions'!$B$76=1,15='Assumptions'!$B$77),'Assumptions'!$B$78,0)-Q24+IF(AND('Assumptions'!$B$76=0,15='Assumptions'!$B$73),$B$28,0)-Q29+IF(AND('Assumptions'!$B$81=1,15='Assumptions'!$B$82),'Assumptions'!$B$83,0)-Q27 | R41: =IF(AND('Assumptions'!$B$76=1,16='Assumptions'!$B$77),'Assumptions'!$B$78,0)-R24+IF(AND('Assumptions'!$B$76=0,16='Assumptions'!$B$73),$B$28,0)-R29+IF(AND('Assumptions'!$B$81=1,16='Assumptions'!$B$82),'Assumptions'!$B$83,0)-R27 | S41: =IF(AND('Assumptions'!$B$76=1,17='Assumptions'!$B$77),'Assumptions'!$B$78,0)-S24+IF(AND('Assumptions'!$B$76=0,17='Assumptions'!$B$73),$B$28,0)-S29+IF(AND('Assumptions'!$B$81=1,17='Assumptions'!$B$82),'Assumptions'!$B$83,0)-S27 | T41: =IF(AND('Assumptions'!$B$76=1,18='Assumptions'!$B$77),'Assumptions'!$B$78,0)-T24+IF(AND('Assumptions'!$B$76=0,18='Assumptions'!$B$73),$B$28,0)-T29+IF(AND('Assumptions'!$B$81=1,18='Assumptions'!$B$82),'Assumptions'!$B$83,0)-T27 | U41: =IF(AND('Assumptions'!$B$76=1,19='Assumptions'!$B$77),'Assumptions'!$B$78,0)-U24+IF(AND('Assumptions'!$B$76=0,19='Assumptions'!$B$73),$B$28,0)-U29+IF(AND('Assumptions'!$B$81=1,19='Assumptions'!$B$82),'Assumptions'!$B$83,0)-U27 | V41: =IF(AND('Assumptions'!$B$76=1,20='Assumptions'!$B$77),'Assumptions'!$B$78,0)-V24+IF(AND('Assumptions'!$B$76=0,20='Assumptions'!$B$73),$B$28,0)-V29+IF(AND('Assumptions'!$B$81=1,20='Assumptions'!$B$82),'Assumptions'!$B$83,0)-V27 | W41: =IF(AND('Assumptions'!$B$76=1,21='Assumptions'!$B$77),'Assumptions'!$B$78,0)-W24+IF(AND('Assumptions'!$B$76=0,21='Assumptions'!$B$73),$B$28,0)-W29+IF(AND('Assumptions'!$B$81=1,21='Assumptions'!$B$82),'Assumptions'!$B$83,0)-W27 | X41: =IF(AND('Assumptions'!$B$76=1,22='Assumptions'!$B$77),'Assumptions'!$B$78,0)-X24+IF(AND('Assumptions'!$B$76=0,22='Assumptions'!$B$73),$B$28,0)-X29+IF(AND('Assumptions'!$B$81=1,22='Assumptions'!$B$82),'Assumptions'!$B$83,0)-X27 | Y41: =IF(AND('Assumptions'!$B$76=1,23='Assumptions'!$B$77),'Assumptions'!$B$78,0)-Y24+IF(AND('Assumptions'!$B$76=0,23='Assumptions'!$B$73),$B$28,0)-Y29+IF(AND('Assumptions'!$B$81=1,23='Assumptions'!$B$82),'Assumptions'!$B$83,0)-Y27 | Z41: =IF(AND('Assumptions'!$B$76=1,24='Assumptions'!$B$77),'Assumptions'!$B$78,0)-Z24+IF(AND('Assumptions'!$B$76=0,24='Assumptions'!$B$73),$B$28,0)-Z29+IF(AND('Assumptions'!$B$81=1,24='Assumptions'!$B$82),'Assumptions'!$B$83,0)-Z27 | AA41: =IF(AND('Assumptions'!$B$76=1,25='Assumptions'!$B$77),'Assumptions'!$B$78,0)-AA24+IF(AND('Assumptions'!$B$76=0,25='Assumptions'!$B$73),$B$28,0)-AA29+IF(AND('Assumptions'!$B$81=1,25='Assumptions'!$B$82),'Assumptions'!$B$83,0)-AA27 | AB41: =IF(AND('Assumptions'!$B$76=1,26='Assumptions'!$B$77),'Assumptions'!$B$78,0)-AB24+IF(AND('Assumptions'!$B$76=0,26='Assumptions'!$B$73),$B$28,0)-AB29+IF(AND('Assumptions'!$B$81=1,26='Assumptions'!$B$82),'Assumptions'!$B$83,0)-AB27 | AC41: =IF(AND('Assumptions'!$B$76=1,27='Assumptions'!$B$77),'Assumptions'!$B$78,0)-AC24+IF(AND('Assumptions'!$B$76=0,27='Assumptions'!$B$73),$B$28,0)-AC29+IF(AND('Assumptions'!$B$81=1,27='Assumptions'!$B$82),'Assumptions'!$B$83,0)-AC27 | AD41: =IF(AND('Assumptions'!$B$76=1,28='Assumptions'!$B$77),'Assumptions'!$B$78,0)-AD24+IF(AND('Assumptions'!$B$76=0,28='Assumptions'!$B$73),$B$28,0)-AD29+IF(AND('Assumptions'!$B$81=1,28='Assumptions'!$B$82),'Assumptions'!$B$83,0)-AD27 | AE41: =IF(AND('Assumptions'!$B$76=1,29='Assumptions'!$B$77),'Assumptions'!$B$78,0)-AE24+IF(AND('Assumptions'!$B$76=0,29='Assumptions'!$B$73),$B$28,0)-AE29+IF(AND('Assumptions'!$B$81=1,29='Assumptions'!$B$82),'Assumptions'!$B$83,0)-AE27 | AF41: =IF(AND('Assumptions'!$B$76=1,30='Assumptions'!$B$77),'Assumptions'!$B$78,0)-AF24+IF(AND('Assumptions'!$B$76=0,30='Assumptions'!$B$73),$B$28,0)-AF29+IF(AND('Assumptions'!$B$81=1,30='Assumptions'!$B$82),'Assumptions'!$B$83,0)-AF27 | AG41: =IF(AND('Assumptions'!$B$76=1,31='Assumptions'!$B$77),'Assumptions'!$B$78,0)-AG24+IF(AND('Assumptions'!$B$76=0,31='Assumptions'!$B$73),$B$28,0)-AG29+IF(AND('Assumptions'!$B$81=1,31='Assumptions'!$B$82),'Assumptions'!$B$83,0)-AG27 | AH41: =IF(AND('Assumptions'!$B$76=1,32='Assumptions'!$B$77),'Assumptions'!$B$78,0)-AH24+IF(AND('Assumptions'!$B$76=0,32='Assumptions'!$B$73),$B$28,0)-AH29+IF(AND('Assumptions'!$B$81=1,32='Assumptions'!$B$82),'Assumptions'!$B$83,0)-AH27 | AI41: =IF(AND('Assumptions'!$B$76=1,33='Assumptions'!$B$77),'Assumptions'!$B$78,0)-AI24+IF(AND('Assumptions'!$B$76=0,33='Assumptions'!$B$73),$B$28,0)-AI29+IF(AND('Assumptions'!$B$81=1,33='Assumptions'!$B$82),'Assumptions'!$B$83,0)-AI27 | AJ41: =IF(AND('Assumptions'!$B$76=1,34='Assumptions'!$B$77),'Assumptions'!$B$78,0)-AJ24+IF(AND('Assumptions'!$B$76=0,34='Assumptions'!$B$73),$B$28,0)-AJ29+IF(AND('Assumptions'!$B$81=1,34='Assumptions'!$B$82),'Assumptions'!$B$83,0)-AJ27 | AK41: =IF(AND('Assumptions'!$B$76=1,35='Assumptions'!$B$77),'Assumptions'!$B$78,0)-AK24+IF(AND('Assumptions'!$B$76=0,35='Assumptions'!$B$73),$B$28,0)-AK29+IF(AND('Assumptions'!$B$81=1,35='Assumptions'!$B$82),'Assumptions'!$B$83,0)-AK27 | AL41: =IF(AND('Assumptions'!$B$76=1,36='Assumptions'!$B$77),'Assumptions'!$B$78,0)-AL24+IF(AND('Assumptions'!$B$76=0,36='Assumptions'!$B$73),$B$28,0)-AL29+IF(AND('Assumptions'!$B$81=1,36='Assumptions'!$B$82),'Assumptions'!$B$83,0)-AL27
A42: ENDING CASH | C42: ='Assumptions'!$B$88+C37+C38+C39+C40+C41 | D42: =C42+D37+D38+D39+D40+D41 | E42: =D42+E37+E38+E39+E40+E41 | F42: =E42+F37+F38+F39+F40+F41 | G42: =F42+G37+G38+G39+G40+G41 | H42: =G42+H37+H38+H39+H40+H41 | I42: =H42+I37+I38+I39+I40+I41 | J42: =I42+J37+J38+J39+J40+J41 | K42: =J42+K37+K38+K39+K40+K41 | ... AL42: =AK42+AL37+AL38+AL39+AL40+AL41
A43: DSCR (EBITDA / recurring debt service) | C43: =IF((C24+C29+C27+IF(AND(1>='Assumptions'!$B$70,1<='Assumptions'!$B$71,'Assumptions'!$B$76=0),'Assumptions'!$B$69,0))>0,C14/(C24+C29+C27+IF(AND(1>='Assumptions'!$B$70,1<='Assumptions'!$B$71,'Assumptions'!$B$76=0),'Assumptions'!$B$69,0)),"-") | D43: =IF((D24+D29+D27+IF(AND(2>='Assumptions'!$B$70,2<='Assumptions'!$B$71,'Assumptions'!$B$76=0),'Assumptions'!$B$69,0))>0,D14/(D24+D29+D27+IF(AND(2>='Assumptions'!$B$70,2<='Assumptions'!$B$71,'Assumptions'!$B$76=0),'Assumptions'!$B$69,0)),"-") | E43: =IF((E24+E29+E27+IF(AND(3>='Assumptions'!$B$70,3<='Assumptions'!$B$71,'Assumptions'!$B$76=0),'Assumptions'!$B$69,0))>0,E14/(E24+E29+E27+IF(AND(3>='Assumptions'!$B$70,3<='Assumptions'!$B$71,'Assumptions'!$B$76=0),'Assumptions'!$B$69,0)),"-") | F43: =IF((F24+F29+F27+IF(AND(4>='Assumptions'!$B$70,4<='Assumptions'!$B$71,'Assumptions'!$B$76=0),'Assumptions'!$B$69,0))>0,F14/(F24+F29+F27+IF(AND(4>='Assumptions'!$B$70,4<='Assumptions'!$B$71,'Assumptions'!$B$76=0),'Assumptions'!$B$69,0)),"-") | G43: =IF((G24+G29+G27+IF(AND(5>='Assumptions'!$B$70,5<='Assumptions'!$B$71,'Assumptions'!$B$76=0),'Assumptions'!$B$69,0))>0,G14/(G24+G29+G27+IF(AND(5>='Assumptions'!$B$70,5<='Assumptions'!$B$71,'Assumptions'!$B$76=0),'Assumptions'!$B$69,0)),"-") | H43: =IF((H24+H29+H27+IF(AND(6>='Assumptions'!$B$70,6<='Assumptions'!$B$71,'Assumptions'!$B$76=0),'Assumptions'!$B$69,0))>0,H14/(H24+H29+H27+IF(AND(6>='Assumptions'!$B$70,6<='Assumptions'!$B$71,'Assumptions'!$B$76=0),'Assumptions'!$B$69,0)),"-") | I43: =IF((I24+I29+I27+IF(AND(7>='Assumptions'!$B$70,7<='Assumptions'!$B$71,'Assumptions'!$B$76=0),'Assumptions'!$B$69,0))>0,I14/(I24+I29+I27+IF(AND(7>='Assumptions'!$B$70,7<='Assumptions'!$B$71,'Assumptions'!$B$76=0),'Assumptions'!$B$69,0)),"-") | J43: =IF((J24+J29+J27+IF(AND(8>='Assumptions'!$B$70,8<='Assumptions'!$B$71,'Assumptions'!$B$76=0),'Assumptions'!$B$69,0))>0,J14/(J24+J29+J27+IF(AND(8>='Assumptions'!$B$70,8<='Assumptions'!$B$71,'Assumptions'!$B$76=0),'Assumptions'!$B$69,0)),"-") | K43: =IF((K24+K29+K27+IF(AND(9>='Assumptions'!$B$70,9<='Assumptions'!$B$71,'Assumptions'!$B$76=0),'Assumptions'!$B$69,0))>0,K14/(K24+K29+K27+IF(AND(9>='Assumptions'!$B$70,9<='Assumptions'!$B$71,'Assumptions'!$B$76=0),'Assumptions'!$B$69,0)),"-") | L43: =IF((L24+L29+L27+IF(AND(10>='Assumptions'!$B$70,10<='Assumptions'!$B$71,'Assumptions'!$B$76=0),'Assumptions'!$B$69,0))>0,L14/(L24+L29+L27+IF(AND(10>='Assumptions'!$B$70,10<='Assumptions'!$B$71,'Assumptions'!$B$76=0),'Assumptions'!$B$69,0)),"-") | M43: =IF((M24+M29+M27+IF(AND(11>='Assumptions'!$B$70,11<='Assumptions'!$B$71,'Assumptions'!$B$76=0),'Assumptions'!$B$69,0))>0,M14/(M24+M29+M27+IF(AND(11>='Assumptions'!$B$70,11<='Assumptions'!$B$71,'Assumptions'!$B$76=0),'Assumptions'!$B$69,0)),"-") | N43: =IF((N24+N29+N27+IF(AND(12>='Assumptions'!$B$70,12<='Assumptions'!$B$71,'Assumptions'!$B$76=0),'Assumptions'!$B$69,0))>0,N14/(N24+N29+N27+IF(AND(12>='Assumptions'!$B$70,12<='Assumptions'!$B$71,'Assumptions'!$B$76=0),'Assumptions'!$B$69,0)),"-") | O43: =IF((O24+O29+O27+IF(AND(13>='Assumptions'!$B$70,13<='Assumptions'!$B$71,'Assumptions'!$B$76=0),'Assumptions'!$B$69,0))>0,O14/(O24+O29+O27+IF(AND(13>='Assumptions'!$B$70,13<='Assumptions'!$B$71,'Assumptions'!$B$76=0),'Assumptions'!$B$69,0)),"-") | P43: =IF((P24+P29+P27+IF(AND(14>='Assumptions'!$B$70,14<='Assumptions'!$B$71,'Assumptions'!$B$76=0),'Assumptions'!$B$69,0))>0,P14/(P24+P29+P27+IF(AND(14>='Assumptions'!$B$70,14<='Assumptions'!$B$71,'Assumptions'!$B$76=0),'Assumptions'!$B$69,0)),"-") | Q43: =IF((Q24+Q29+Q27+IF(AND(15>='Assumptions'!$B$70,15<='Assumptions'!$B$71,'Assumptions'!$B$76=0),'Assumptions'!$B$69,0))>0,Q14/(Q24+Q29+Q27+IF(AND(15>='Assumptions'!$B$70,15<='Assumptions'!$B$71,'Assumptions'!$B$76=0),'Assumptions'!$B$69,0)),"-") | R43: =IF((R24+R29+R27+IF(AND(16>='Assumptions'!$B$70,16<='Assumptions'!$B$71,'Assumptions'!$B$76=0),'Assumptions'!$B$69,0))>0,R14/(R24+R29+R27+IF(AND(16>='Assumptions'!$B$70,16<='Assumptions'!$B$71,'Assumptions'!$B$76=0),'Assumptions'!$B$69,0)),"-") | S43: =IF((S24+S29+S27+IF(AND(17>='Assumptions'!$B$70,17<='Assumptions'!$B$71,'Assumptions'!$B$76=0),'Assumptions'!$B$69,0))>0,S14/(S24+S29+S27+IF(AND(17>='Assumptions'!$B$70,17<='Assumptions'!$B$71,'Assumptions'!$B$76=0),'Assumptions'!$B$69,0)),"-") | T43: =IF((T24+T29+T27+IF(AND(18>='Assumptions'!$B$70,18<='Assumptions'!$B$71,'Assumptions'!$B$76=0),'Assumptions'!$B$69,0))>0,T14/(T24+T29+T27+IF(AND(18>='Assumptions'!$B$70,18<='Assumptions'!$B$71,'Assumptions'!$B$76=0),'Assumptions'!$B$69,0)),"-") | U43: =IF((U24+U29+U27+IF(AND(19>='Assumptions'!$B$70,19<='Assumptions'!$B$71,'Assumptions'!$B$76=0),'Assumptions'!$B$69,0))>0,U14/(U24+U29+U27+IF(AND(19>='Assumptions'!$B$70,19<='Assumptions'!$B$71,'Assumptions'!$B$76=0),'Assumptions'!$B$69,0)),"-") | V43: =IF((V24+V29+V27+IF(AND(20>='Assumptions'!$B$70,20<='Assumptions'!$B$71,'Assumptions'!$B$76=0),'Assumptions'!$B$69,0))>0,V14/(V24+V29+V27+IF(AND(20>='Assumptions'!$B$70,20<='Assumptions'!$B$71,'Assumptions'!$B$76=0),'Assumptions'!$B$69,0)),"-") | W43: =IF((W24+W29+W27+IF(AND(21>='Assumptions'!$B$70,21<='Assumptions'!$B$71,'Assumptions'!$B$76=0),'Assumptions'!$B$69,0))>0,W14/(W24+W29+W27+IF(AND(21>='Assumptions'!$B$70,21<='Assumptions'!$B$71,'Assumptions'!$B$76=0),'Assumptions'!$B$69,0)),"-") | X43: =IF((X24+X29+X27+IF(AND(22>='Assumptions'!$B$70,22<='Assumptions'!$B$71,'Assumptions'!$B$76=0),'Assumptions'!$B$69,0))>0,X14/(X24+X29+X27+IF(AND(22>='Assumptions'!$B$70,22<='Assumptions'!$B$71,'Assumptions'!$B$76=0),'Assumptions'!$B$69,0)),"-") | Y43: =IF((Y24+Y29+Y27+IF(AND(23>='Assumptions'!$B$70,23<='Assumptions'!$B$71,'Assumptions'!$B$76=0),'Assumptions'!$B$69,0))>0,Y14/(Y24+Y29+Y27+IF(AND(23>='Assumptions'!$B$70,23<='Assumptions'!$B$71,'Assumptions'!$B$76=0),'Assumptions'!$B$69,0)),"-") | Z43: =IF((Z24+Z29+Z27+IF(AND(24>='Assumptions'!$B$70,24<='Assumptions'!$B$71,'Assumptions'!$B$76=0),'Assumptions'!$B$69,0))>0,Z14/(Z24+Z29+Z27+IF(AND(24>='Assumptions'!$B$70,24<='Assumptions'!$B$71,'Assumptions'!$B$76=0),'Assumptions'!$B$69,0)),"-") | AA43: =IF((AA24+AA29+AA27+IF(AND(25>='Assumptions'!$B$70,25<='Assumptions'!$B$71,'Assumptions'!$B$76=0),'Assumptions'!$B$69,0))>0,AA14/(AA24+AA29+AA27+IF(AND(25>='Assumptions'!$B$70,25<='Assumptions'!$B$71,'Assumptions'!$B$76=0),'Assumptions'!$B$69,0)),"-") | AB43: =IF((AB24+AB29+AB27+IF(AND(26>='Assumptions'!$B$70,26<='Assumptions'!$B$71,'Assumptions'!$B$76=0),'Assumptions'!$B$69,0))>0,AB14/(AB24+AB29+AB27+IF(AND(26>='Assumptions'!$B$70,26<='Assumptions'!$B$71,'Assumptions'!$B$76=0),'Assumptions'!$B$69,0)),"-") | AC43: =IF((AC24+AC29+AC27+IF(AND(27>='Assumptions'!$B$70,27<='Assumptions'!$B$71,'Assumptions'!$B$76=0),'Assumptions'!$B$69,0))>0,AC14/(AC24+AC29+AC27+IF(AND(27>='Assumptions'!$B$70,27<='Assumptions'!$B$71,'Assumptions'!$B$76=0),'Assumptions'!$B$69,0)),"-") | AD43: =IF((AD24+AD29+AD27+IF(AND(28>='Assumptions'!$B$70,28<='Assumptions'!$B$71,'Assumptions'!$B$76=0),'Assumptions'!$B$69,0))>0,AD14/(AD24+AD29+AD27+IF(AND(28>='Assumptions'!$B$70,28<='Assumptions'!$B$71,'Assumptions'!$B$76=0),'Assumptions'!$B$69,0)),"-") | AE43: =IF((AE24+AE29+AE27+IF(AND(29>='Assumptions'!$B$70,29<='Assumptions'!$B$71,'Assumptions'!$B$76=0),'Assumptions'!$B$69,0))>0,AE14/(AE24+AE29+AE27+IF(AND(29>='Assumptions'!$B$70,29<='Assumptions'!$B$71,'Assumptions'!$B$76=0),'Assumptions'!$B$69,0)),"-") | AF43: =IF((AF24+AF29+AF27+IF(AND(30>='Assumptions'!$B$70,30<='Assumptions'!$B$71,'Assumptions'!$B$76=0),'Assumptions'!$B$69,0))>0,AF14/(AF24+AF29+AF27+IF(AND(30>='Assumptions'!$B$70,30<='Assumptions'!$B$71,'Assumptions'!$B$76=0),'Assumptions'!$B$69,0)),"-") | AG43: =IF((AG24+AG29+AG27+IF(AND(31>='Assumptions'!$B$70,31<='Assumptions'!$B$71,'Assumptions'!$B$76=0),'Assumptions'!$B$69,0))>0,AG14/(AG24+AG29+AG27+IF(AND(31>='Assumptions'!$B$70,31<='Assumptions'!$B$71,'Assumptions'!$B$76=0),'Assumptions'!$B$69,0)),"-") | AH43: =IF((AH24+AH29+AH27+IF(AND(32>='Assumptions'!$B$70,32<='Assumptions'!$B$71,'Assumptions'!$B$76=0),'Assumptions'!$B$69,0))>0,AH14/(AH24+AH29+AH27+IF(AND(32>='Assumptions'!$B$70,32<='Assumptions'!$B$71,'Assumptions'!$B$76=0),'Assumptions'!$B$69,0)),"-") | AI43: =IF((AI24+AI29+AI27+IF(AND(33>='Assumptions'!$B$70,33<='Assumptions'!$B$71,'Assumptions'!$B$76=0),'Assumptions'!$B$69,0))>0,AI14/(AI24+AI29+AI27+IF(AND(33>='Assumptions'!$B$70,33<='Assumptions'!$B$71,'Assumptions'!$B$76=0),'Assumptions'!$B$69,0)),"-") | AJ43: =IF((AJ24+AJ29+AJ27+IF(AND(34>='Assumptions'!$B$70,34<='Assumptions'!$B$71,'Assumptions'!$B$76=0),'Assumptions'!$B$69,0))>0,AJ14/(AJ24+AJ29+AJ27+IF(AND(34>='Assumptions'!$B$70,34<='Assumptions'!$B$71,'Assumptions'!$B$76=0),'Assumptions'!$B$69,0)),"-") | AK43: =IF((AK24+AK29+AK27+IF(AND(35>='Assumptions'!$B$70,35<='Assumptions'!$B$71,'Assumptions'!$B$76=0),'Assumptions'!$B$69,0))>0,AK14/(AK24+AK29+AK27+IF(AND(35>='Assumptions'!$B$70,35<='Assumptions'!$B$71,'Assumptions'!$B$76=0),'Assumptions'!$B$69,0)),"-") | AL43: =IF((AL24+AL29+AL27+IF(AND(36>='Assumptions'!$B$70,36<='Assumptions'!$B$71,'Assumptions'!$B$76=0),'Assumptions'!$B$69,0))>0,AL14/(AL24+AL29+AL27+IF(AND(36>='Assumptions'!$B$70,36<='Assumptions'!$B$71,'Assumptions'!$B$76=0),'Assumptions'!$B$69,0)),"-")

Sheet Weekly Cash 13wk
A1: AZALEA HOSPICE - REFUGE OPERATING MODEL
A2: First 13 weeks (Jul-Sep 2026), the danger zone. Payroll on the 15th/EOM; vendor bills by calendar day; receipts from Collections.
C4: W1 | D4: W2 | E4: W3 | F4: W4 | G4: W5 | H4: W6 | I4: W7 | J4: W8 | K4: W9 | L4: W10 | M4: W11 | N4: W12 | O4: W13
A5: Cash received | C5: =Collections!C16 | D5: =Collections!D16 | E5: =Collections!E16 | F5: =Collections!F16 | G5: =Collections!G16 | H5: =Collections!H16 | I5: =Collections!I16 | J5: =Collections!J16 | ... O5: =Collections!O16
A6: Payroll (semi-monthly: 15th & EOM) | C6: =0 | D6: =0 | E6: =-'Payroll'!I37/2 | F6: =0 | G6: =-'Payroll'!I37/2 | H6: =0 | I6: =-'Payroll'!J37/2 | J6: =0 | K6: =-'Payroll'!J37/2 | L6: =0 | M6: =-'Payroll'!K37/2 | N6: =0 | O6: =-'Payroll'!K37/2
A7: Vendor bills (G&A calendar day) | C7: =-SUMPRODUCT((Assumptions!$D$51:$D$64>=1)*(Assumptions!$D$51:$D$64<=8)*(MOD(1-1,Assumptions!$C$51:$C$64)=0)*Assumptions!$B$51:$B$64) | D7: =-SUMPRODUCT((Assumptions!$D$51:$D$64>=9)*(Assumptions!$D$51:$D$64<=15)*(MOD(1-1,Assumptions!$C$51:$C$64)=0)*Assumptions!$B$51:$B$64) | E7: =-SUMPRODUCT((Assumptions!$D$51:$D$64>=16)*(Assumptions!$D$51:$D$64<=23)*(MOD(1-1,Assumptions!$C$51:$C$64)=0)*Assumptions!$B$51:$B$64) | F7: =-SUMPRODUCT((Assumptions!$D$51:$D$64>=24)*(Assumptions!$D$51:$D$64<=30)*(MOD(1-1,Assumptions!$C$51:$C$64)=0)*Assumptions!$B$51:$B$64) | G7: =-SUMPRODUCT((Assumptions!$D$51:$D$64>=1)*(Assumptions!$D$51:$D$64<=6)*(MOD(2-1,Assumptions!$C$51:$C$64)=0)*Assumptions!$B$51:$B$64) | H7: =-SUMPRODUCT((Assumptions!$D$51:$D$64>=7)*(Assumptions!$D$51:$D$64<=12)*(MOD(2-1,Assumptions!$C$51:$C$64)=0)*Assumptions!$B$51:$B$64) | I7: =-SUMPRODUCT((Assumptions!$D$51:$D$64>=13)*(Assumptions!$D$51:$D$64<=18)*(MOD(2-1,Assumptions!$C$51:$C$64)=0)*Assumptions!$B$51:$B$64) | J7: =-SUMPRODUCT((Assumptions!$D$51:$D$64>=19)*(Assumptions!$D$51:$D$64<=24)*(MOD(2-1,Assumptions!$C$51:$C$64)=0)*Assumptions!$B$51:$B$64) | K7: =-SUMPRODUCT((Assumptions!$D$51:$D$64>=25)*(Assumptions!$D$51:$D$64<=30)*(MOD(2-1,Assumptions!$C$51:$C$64)=0)*Assumptions!$B$51:$B$64) | L7: =-SUMPRODUCT((Assumptions!$D$51:$D$64>=1)*(Assumptions!$D$51:$D$64<=8)*(MOD(3-1,Assumptions!$C$51:$C$64)=0)*Assumptions!$B$51:$B$64) | M7: =-SUMPRODUCT((Assumptions!$D$51:$D$64>=9)*(Assumptions!$D$51:$D$64<=15)*(MOD(3-1,Assumptions!$C$51:$C$64)=0)*Assumptions!$B$51:$B$64) | N7: =-SUMPRODUCT((Assumptions!$D$51:$D$64>=16)*(Assumptions!$D$51:$D$64<=23)*(MOD(3-1,Assumptions!$C$51:$C$64)=0)*Assumptions!$B$51:$B$64) | O7: =-SUMPRODUCT((Assumptions!$D$51:$D$64>=24)*(Assumptions!$D$51:$D$64<=30)*(MOD(3-1,Assumptions!$C$51:$C$64)=0)*Assumptions!$B$51:$B$64)
A8: Patient costs + mileage (net-30: paid 15th of following month) | C8: =0 | D8: =0 | E8: =0 | F8: =0 | G8: =0 | H8: =0 | I8: =-('Monthly x36'!C10+'Monthly x36'!C11) | J8: =0 | K8: =0 | L8: =0 | M8: =-('Monthly x36'!D10+'Monthly x36'!D11) | N8: =0 | O8: =0
A9: Fees (billing/QR, with receipts) | C9: =-'Monthly x36'!C13/4 | D9: =-'Monthly x36'!C13/4 | E9: =-'Monthly x36'!C13/4 | F9: =-'Monthly x36'!C13/4 | G9: =-'Monthly x36'!D13/5 | H9: =-'Monthly x36'!D13/5 | I9: =-'Monthly x36'!D13/5 | J9: =-'Monthly x36'!D13/5 | K9: =-'Monthly x36'!D13/5 | L9: =-'Monthly x36'!E13/4 | M9: =-'Monthly x36'!E13/4 | N9: =-'Monthly x36'!E13/4 | O9: =-'Monthly x36'!E13/4
A10: Seller: down payment (wk 1) / Sept payment (wk 11) / refi if ON (wk 13) | C10: =-'Assumptions'!$B$68 | D10: =0 | E10: =0 | F10: =0 | G10: =0 | H10: =0 | I10: =0 | J10: =0 | K10: =0 | L10: =0 | M10: =-IF(AND('Assumptions'!$B$76=0,'Assumptions'!$B$70<=3),'Assumptions'!$B$69,0) | N10: =0 | O10: =IF('Assumptions'!$B$76=1,'Assumptions'!$B$78-('Monthly x36'!E18+SUM('Monthly x36'!$C$19:$E$19)),0)
A11: SBA proceeds (if toggled, lands 1st week of funding month) | C11: =IF(OR(AND('Assumptions'!$B$81=1,'Assumptions'!$B$82=1,1=1),AND('Assumptions'!$B$81=1,'Assumptions'!$B$82=2,1=5),AND('Assumptions'!$B$81=1,'Assumptions'!$B$82=3,1=10)),'Assumptions'!$B$83,0) | D11: =IF(OR(AND('Assumptions'!$B$81=1,'Assumptions'!$B$82=1,2=1),AND('Assumptions'!$B$81=1,'Assumptions'!$B$82=2,2=5),AND('Assumptions'!$B$81=1,'Assumptions'!$B$82=3,2=10)),'Assumptions'!$B$83,0) | E11: =IF(OR(AND('Assumptions'!$B$81=1,'Assumptions'!$B$82=1,3=1),AND('Assumptions'!$B$81=1,'Assumptions'!$B$82=2,3=5),AND('Assumptions'!$B$81=1,'Assumptions'!$B$82=3,3=10)),'Assumptions'!$B$83,0) | F11: =IF(OR(AND('Assumptions'!$B$81=1,'Assumptions'!$B$82=1,4=1),AND('Assumptions'!$B$81=1,'Assumptions'!$B$82=2,4=5),AND('Assumptions'!$B$81=1,'Assumptions'!$B$82=3,4=10)),'Assumptions'!$B$83,0) | G11: =IF(OR(AND('Assumptions'!$B$81=1,'Assumptions'!$B$82=1,5=1),AND('Assumptions'!$B$81=1,'Assumptions'!$B$82=2,5=5),AND('Assumptions'!$B$81=1,'Assumptions'!$B$82=3,5=10)),'Assumptions'!$B$83,0) | H11: =IF(OR(AND('Assumptions'!$B$81=1,'Assumptions'!$B$82=1,6=1),AND('Assumptions'!$B$81=1,'Assumptions'!$B$82=2,6=5),AND('Assumptions'!$B$81=1,'Assumptions'!$B$82=3,6=10)),'Assumptions'!$B$83,0) | I11: =IF(OR(AND('Assumptions'!$B$81=1,'Assumptions'!$B$82=1,7=1),AND('Assumptions'!$B$81=1,'Assumptions'!$B$82=2,7=5),AND('Assumptions'!$B$81=1,'Assumptions'!$B$82=3,7=10)),'Assumptions'!$B$83,0) | J11: =IF(OR(AND('Assumptions'!$B$81=1,'Assumptions'!$B$82=1,8=1),AND('Assumptions'!$B$81=1,'Assumptions'!$B$82=2,8=5),AND('Assumptions'!$B$81=1,'Assumptions'!$B$82=3,8=10)),'Assumptions'!$B$83,0) | K11: =IF(OR(AND('Assumptions'!$B$81=1,'Assumptions'!$B$82=1,9=1),AND('Assumptions'!$B$81=1,'Assumptions'!$B$82=2,9=5),AND('Assumptions'!$B$81=1,'Assumptions'!$B$82=3,9=10)),'Assumptions'!$B$83,0) | L11: =IF(OR(AND('Assumptions'!$B$81=1,'Assumptions'!$B$82=1,10=1),AND('Assumptions'!$B$81=1,'Assumptions'!$B$82=2,10=5),AND('Assumptions'!$B$81=1,'Assumptions'!$B$82=3,10=10)),'Assumptions'!$B$83,0) | M11: =IF(OR(AND('Assumptions'!$B$81=1,'Assumptions'!$B$82=1,11=1),AND('Assumptions'!$B$81=1,'Assumptions'!$B$82=2,11=5),AND('Assumptions'!$B$81=1,'Assumptions'!$B$82=3,11=10)),'Assumptions'!$B$83,0) | N11: =IF(OR(AND('Assumptions'!$B$81=1,'Assumptions'!$B$82=1,12=1),AND('Assumptions'!$B$81=1,'Assumptions'!$B$82=2,12=5),AND('Assumptions'!$B$81=1,'Assumptions'!$B$82=3,12=10)),'Assumptions'!$B$83,0) | O11: =IF(OR(AND('Assumptions'!$B$81=1,'Assumptions'!$B$82=1,13=1),AND('Assumptions'!$B$81=1,'Assumptions'!$B$82=2,13=5),AND('Assumptions'!$B$81=1,'Assumptions'!$B$82=3,13=10)),'Assumptions'!$B$83,0)
A12: ENDING CASH | C12: ='Assumptions'!$B$88+C5+C6+C7+C8+C9+C10+C11 | D12: =C12+D5+D6+D7+D8+D9+D10+D11 | E12: =D12+E5+E6+E7+E8+E9+E10+E11 | F12: =E12+F5+F6+F7+F8+F9+F10+F11 | G12: =F12+G5+G6+G7+G8+G9+G10+G11 | H12: =G12+H5+H6+H7+H8+H9+H10+H11 | I12: =H12+I5+I6+I7+I8+I9+I10+I11 | J12: =I12+J5+J6+J7+J8+J9+J10+J11 | K12: =J12+K5+K6+K7+K8+K9+K10+K11 | ... O12: =N12+O5+O6+O7+O8+O9+O10+O11
A14: Note: weekly receipts spread each month's collections evenly across its weeks; payroll halves on the 15th/EOM; vendor hits per the Assumptions bill calendar. Precision is operational, not accounting-grade.

Sheet Actuals vs Budget
A1: AZALEA HOSPICE - REFUGE OPERATING MODEL
A2: Enter ACTUALS monthly (blue cells); variance computes automatically. First 12 months.
C4: Jul-26 | D4: Aug-26 | E4: Sep-26 | F4: Oct-26 | G4: Nov-26 | H4: Dec-26 | I4: Jan-27 | J4: Feb-27 | K4: Mar-27 | L4: Apr-27 | M4: May-27 | N4: Jun-27
A5: Net revenue - BUDGET | C5: ='Monthly x36'!C8 | D5: ='Monthly x36'!D8 | E5: ='Monthly x36'!E8 | F5: ='Monthly x36'!F8 | G5: ='Monthly x36'!G8 | H5: ='Monthly x36'!H8 | I5: ='Monthly x36'!I8 | J5: ='Monthly x36'!J8 | ... N5: ='Monthly x36'!N8
A6: Net revenue - ACTUAL [enter]
A7: Net revenue - variance | C7: =IF(C6="","",C6-C5) | D7: =IF(D6="","",D6-D5) | E7: =IF(E6="","",E6-E5) | F7: =IF(F6="","",F6-F5) | G7: =IF(G6="","",G6-G5) | H7: =IF(H6="","",H6-H5) | I7: =IF(I6="","",I6-I5) | J7: =IF(J6="","",J6-J5) | ... N7: =IF(N6="","",N6-N5)
A9: Total labor - BUDGET | C9: ='Monthly x36'!C9 | D9: ='Monthly x36'!D9 | E9: ='Monthly x36'!E9 | F9: ='Monthly x36'!F9 | G9: ='Monthly x36'!G9 | H9: ='Monthly x36'!H9 | I9: ='Monthly x36'!I9 | J9: ='Monthly x36'!J9 | ... N9: ='Monthly x36'!N9
A10: Total labor - ACTUAL [enter]
A11: Total labor - variance | C11: =IF(C10="","",C10-C9) | D11: =IF(D10="","",D10-D9) | E11: =IF(E10="","",E10-E9) | F11: =IF(F10="","",F10-F9) | G11: =IF(G10="","",G10-G9) | H11: =IF(H10="","",H10-H9) | I11: =IF(I10="","",I10-I9) | J11: =IF(J10="","",J10-J9) | ... N11: =IF(N10="","",N10-N9)
A13: EBITDA - BUDGET | C13: ='Monthly x36'!C14 | D13: ='Monthly x36'!D14 | E13: ='Monthly x36'!E14 | F13: ='Monthly x36'!F14 | G13: ='Monthly x36'!G14 | H13: ='Monthly x36'!H14 | I13: ='Monthly x36'!I14 | J13: ='Monthly x36'!J14 | ... N13: ='Monthly x36'!N14
A14: EBITDA - ACTUAL [enter]
A15: EBITDA - variance | C15: =IF(C14="","",C14-C13) | D15: =IF(D14="","",D14-D13) | E15: =IF(E14="","",E14-E13) | F15: =IF(F14="","",F14-F13) | G15: =IF(G14="","",G14-G13) | H15: =IF(H14="","",H14-H13) | I15: =IF(I14="","",I14-I13) | J15: =IF(J14="","",J14-J13) | ... N15: =IF(N14="","",N14-N13)
A17: Ending cash - BUDGET | C17: ='Monthly x36'!C42 | D17: ='Monthly x36'!D42 | E17: ='Monthly x36'!E42 | F17: ='Monthly x36'!F42 | G17: ='Monthly x36'!G42 | H17: ='Monthly x36'!H42 | I17: ='Monthly x36'!I42 | J17: ='Monthly x36'!J42 | ... N17: ='Monthly x36'!N42
A18: Ending cash - ACTUAL [enter]
A19: Ending cash - variance | C19: =IF(C18="","",C18-C17) | D19: =IF(D18="","",D18-D17) | E19: =IF(E18="","",E18-E17) | F19: =IF(F18="","",F18-F17) | G19: =IF(G18="","",G18-G17) | H19: =IF(H18="","",H18-H17) | I19: =IF(I18="","",I18-I17) | J19: =IF(J18="","",J18-J17) | ... N19: =IF(N18="","",N18-N17)

Sheet Investor Summary
A1: AZALEA HOSPICE - REFUGE OPERATING MODEL
A2: Jim Bullard - position, debt stack, distributable view. Links to the live model.
A4: CAP TABLE
A5: Geoff Schackmann (Manager, direct) | B5: =0.399 | C5: sole 20%+ owner; personal guaranty
A6: James E. Bullard | B6: =0.195 | C6: $195,000 cash; passive; no SBA PG
A7: Silas Shelton / Dana Davenport / Brad Woodard | B7: =0.399 | C7: 13.3% each, restricted/vesting
A8: Unissued pool | B8: =0.007 | C8: reserved
A10: DEBT STACK (live)
A11: Seller note balance - end of M6 (Dec-26) | B11: ='Monthly x36'!H22
A12: Seller fully paid by | B12: =IF('Assumptions'!$B$76=1,"Sep-26 (refi)","Jan-27 (balloon)")
A13: Refi balance - end of Yr 1 (if toggled) | B13: ='Monthly x36'!N25
A15: YEAR-1 RESULTS (live)
A16: FY1 net revenue | B16: =SUM('Monthly x36'!C8:N8)
A17: FY1 EBITDA | B17: =SUM('Monthly x36'!C14:N14)
A18: FY1 net income | B18: =SUM('Monthly x36'!C35:N35)
A19: Cash at end of FY1 | B19: ='Monthly x36'!N42
A21: DISTRIBUTABLE VIEW (S-corp: strictly pro-rata)
A22: Estimated tax distribution rate | B22: 0.3
A23: FY1 tax distributions (all members) | B23: =MAX(0,SUM('Monthly x36'!C35:N35))*$B$22
A24: Jim's 19.5% share | B24: =$B$23*0.195
A25: Cash above floor at FY1 end (discretionary capacity) | B25: =MAX(0,'Monthly x36'!N42-'Assumptions'!$B$89)
A26: Note: distributions are discretionary, subject to solvency, lender covenants, and the S-corp pro-rata requirement; the OA mandates annual tax distributions.
