Workbook

Sheet Prompt Pack
A1: Azalea Hospice — Sequenced Prompt Pack
A2: Copy each prompt below into chat ONE AT A TIME, in order. Wait for me to confirm completion of each before triggering the next. Each prompt has a stop point and acceptance criteria.
A3: Stage: Pre-launch | Audience: SBA + Equity + Internal Ops | Payer: 100% Medicare RHC | Horizon: 3yr (Y1 monthly, Y2-3 quarterly) | Geo: Single CBSA | Staff: Named hires
A5: PROMPT 1 — Archive old sheets + build Inputs tab
A6: Archive all 9 existing sheets (Control Tower, COA Mapping, Census Waterfall, Revenue Model, Staffing Summary, Operating Budget, P&L, Reconciliation, Stress Tests) into a collapsed group at the back of the workbook — prefix each with 'ARCHIVE_' and group them so they're collapsed by default. Then build a new 'Inputs' tab as the primary input sheet for the rebuild, with nine labeled blocks: A) Geography & Rates (CBSA, FY26 RHC base rate, wage index, BNAF, SBI status), B) Payer Mix & Timing (100% Medicare RHC, billing lag days, sequential billing toggle), C) Census Ramp (36 months of ADC targets, average LOS, admit/discharge cadence), D) Named Staff Roster (one row per hire: name, role, start month, annual salary, FT/PT, OT eligibility — leave 20 blank rows), E) Staffing Ratios for Y2-3 (RN caseload, aide ratio, on-call coverage, indirect overhead %), F) Benefits & ER Taxes (FICA, FUTA, SUTA with wage base, WC, health $/mo per FTE, retirement %), G) Opex (mileage $/visit, med supplies $/PPD, DME $/PPD, meds $/PPD, rent, IT, insurance, licenses), H) SBA & Capital Structure (loan amount, rate, amort term, equity injection, founder contribution, LOC limit, opening cash), I) Working Capital (AR days, AP days, PPEO accrual rate, cap year start month). Yellow-fill all cells the user needs to fill. Create named ranges for every key input. Acceptance: archived sheets are collapsed at back, Inputs tab is fully laid out with empty yellow input cells, all named ranges created. STOP after this is built and confirm with me before Prompt 2.
A8: PROMPT 2 — Build Revenue tab
A9: I've filled in the Inputs tab. Build the Revenue tab now. Layout: Year 1 in monthly columns (36 columns total = Y1 12 monthly, Y2-3 8 quarters). Rows: (1) ADC pulled from Inputs Block C, (2) Patient Days = ADC × days in period, (3) RHC wage-adjusted rate = base rate × (labor share × wage index + non-labor share) + BNAF, (4) SBI adjustment if applicable, (5) Gross Revenue = Patient Days × adjusted rate, (6) Sequential Billing timing (NOE filing month vs. service month — first claim delayed if Sequential Billing on), (7) Net cash receipts with 30-day Medicare RAP-to-final lag, (8) Cap exposure tracker (cumulative payments vs. cap limit × beneficiaries served per cap year starting at Inputs Block I cap-year-start). All formulas — zero hardcoded numbers on this tab, everything references Inputs named ranges. Add a small summary block at top: Y1/Y2/Y3 gross revenue, net revenue, avg ADC, cap exposure %. Format: blue inputs (none expected here), black formulas, green cross-sheet links. Acceptance: Revenue tab built, summary block populated, no #REF/#VALUE errors, cap tracker shows running exposure. STOP and confirm with me before Prompt 3.
A11: PROMPT 3 — Build Staffing + Payroll & Benefits tabs
A12: Revenue is approved. Build the Staffing tab and the Payroll & Benefits tab. STAFFING: Y1 monthly — each named hire from Inputs Block D gets a row, FTE = 1 starting at their start month, 0 before; salary populates from their start month forward. Y2-Y3 quarterly — named roster carries forward, then a 'generic ladder' block adds positions driven by ADC and the ratios in Block E (e.g., RN FTE needed = CEILING(ADC / RN caseload), Aide FTE = CEILING(ADC × aide ratio), On-call coverage fixed by Block E). Show total FTE by role and grand total at bottom. PAYROLL & BENEFITS: pulls FTE × salary from Staffing, then calculates: ER FICA 7.65% (capped at SS wage base), FUTA (cap $7K × 0.6%), SUTA per Block F with state wage base, WC %, health $ × FTE-months, retirement %. Output gross payroll per period + fully-loaded payroll per period. Add semi-monthly payroll cash-timing offset (lag accrued-to-paid). Add GL prefix column on each row (use 4000-series for direct care wages, 4005 performance pay, 4020 contract labor, 4110/4120/4124/4125 benefits, 4130 FICA, 4131 SUTA-proposed, 4135 WC-proposed). All formulas reference Inputs and Staffing named ranges. Acceptance: Staffing FTE ramps correctly through named roster then generic ladder, Payroll totals tie to FTE×salary plus loaded benefits, GL prefixes shown. STOP and confirm before Prompt 4.
A14: PROMPT 4 — Build Operating Expenses tab
A15: Staffing + Payroll approved. Build Operating Expenses tab. Two sections: VARIABLE (keyed to ADC or Patient Days) — mileage $/visit × visits per ADC, medical supplies $/PPD × patient days, medications $/PPD × patient days, DME $/PPD × patient days, all rates from Inputs Block G. FIXED (by month/quarter) — rent, IT/EMR, liability/property/malpractice insurance, state licenses, professional fees, marketing. Add GL prefix column: 5050 DME, 5090 supplies, 5100 meds, 5110 mileage, 6010-6150 facility, 6505-6716 indirect ops, 6800 marketing. Show total opex per period at bottom, split between Direct Care COGS (5000-series + facility-allocable) and Indirect SG&A (6000-series). All formulas reference Inputs named ranges. Acceptance: variable opex scales with ADC, fixed opex stable, GL prefixes shown, COGS-vs-SG&A split clear. STOP and confirm before Prompt 5.
A17: PROMPT 5 — Build P&L + Cash Flow + Balance Sheet (3-statement)
... A27: 1. Trigger Prompt 1 first — it builds the Inputs tab. Then YOU fill in the yellow input cells (CBSA wage data, named roster, ADC ramp, SBA terms, etc.) BEFORE triggering Prompt 2. 2. After Prompt 1, the only manual data entry happens on the Inputs tab. Every downstream calculation is formulas. 3. If a prompt result looks wrong, say 'audit Prompt N output' — I'll re-check formulas before moving on. 4. To change any assumption later, edit the Inputs tab — the entire model recalculates. 5. Iterative calculation needs to be ON for the LOC auto-balance in Prompt 5 (Excel → File → Options → Formulas → Enable iterative calculation, 100 iterations, 0.001 max change). I'll remind you when we get there. 6. Old sheets (ARCHIVE_*) stay collapsed at the back — don't delete them until the new model is fully signed off by SBA + equity.

Sheet Inputs

Sheet ARCHIVE_Control Tower
A1: AZALEA HOSPICE & PALLIATIVE CARE — CONTROL TOWER (Assumptions Engine)
A2: Tyler Hospice OpCo, LLC · Lindale, TX · Go-Live June 2026 · All model values flow from this tab
A4: A. PAYROLL BURDEN (each maps to a GL account)
A5: Employer FICA / SS / Medicare | B5: 0.0765 | C5: 4130-0-Z-0 | D5: 7.65% statutory; on all W-2 wages
A6: FUTA + TX SUTA (unemployment) | B6: 0.0185 | C6: 4131-0-Z-0 ADD | D6: ~1.85% blended; on W-2 wages
A7: Workers' Compensation | B7: 0.03 | C7: 4135-0-Z-0 ADD | D7: 3% of W-2 wages; broken out per request
A8: Health Insurance ($/mo per FT employee) | B8: 500 | C8: 4110-0-Z-0 | D8: FT benefits-eligible only; PRN excluded
A10: B. TRAVEL / MILEAGE (replaces flat vehicle allowance)
A11: IRS Mileage Rate ($/mile) | B11: 0.5 | C11: 5110-R-6-X | D11: Per payroll records
A12: Visits per day (FT field clinician) | B12: 5.5 | D12: RN & CNA route productivity
A13: Round-trip miles per visit | B13: 7 | D13: Calibrated -> mileage = 2% of revenue
A14: Working days per month | B14: 21 | D14: Standard
A16: C. CASELOAD & GROWTH
A17: RN Case Manager caseload (1 : N) | B17: 15 | D17: Drives RN FTE requirement
A18: CNA / Aide caseload (1 : N) | B18: 12 | D18: Drives Aide FTE requirement
A19: Annual Merit / COL increase | B19: 0.03 | D19: Applied start of Y2 and Y3
A20: Monthly Discharge Rate | B20: 0.15 | D20: Industry standard
A21: Avg Days per Month | B21: 30.4 | D21: For per-patient-day metrics
A23: D. PRN VISIT ASSUMPTIONS (visits per patient per month x rate)
A24: On-Call LVN - visits/pt/mo | B24: 0.6 | C24: 4000-R-6-4 | D24: After-hours coverage
A25: On-Call LVN - rate per visit | B25: 100 | D25: Confirm: payroll showed $75
A26: Chaplain (SC) - visits/pt/mo | B26: 0.75 | C26: 4000-R-6-7 | D26: NHPCO 1-2/mo; conservative
A27: Chaplain - rate per visit | B27: 75 | D27: Per payroll
A28: Social Worker (MSW) - visits/pt/mo | B28: 1 | C28: 4000-R-6-6 | D28: Required assessments
A29: Social Worker - rate per visit | B29: 75 | D29: Per payroll
A30: Nurse Practitioner - visits/pt/mo | B30: 0.15 | C30: 4000-R-6-N | D30: F2F recert visits
A31: Nurse Practitioner - rate per visit | B31: 200 | D31: Per payroll
A33: E. CONTRACTED & PRN-RETAINER ROLES
A34: Medical Director ($/mo) | B34: 4000 | C34: 4020-R-6-M | D34: CoP req Day 1; contracted, no burden
A35: Silas - PRN Admin retainer ($/mo, M1-M2) | B35: 2500 | C35: 4020-0-A-0 | D35: Administrator of record; PRN
A36: Dana - PRN Clinical contract ($/mo, M1) | B36: 1500 | C36: 4020-0-C-0 | D36: DON oversight; PRN month 1
A38: F. ANNUAL BASE SALARIES - FT (Year 1) · Source: Payroll Jan-Mar 2026
A39: Brad Woodard - Marketing (M1) | B39: 120000 | C39: 4000-0-M-0 | D39: Director of Sales / Marketer
A40: Jodi McCollum - RN-CM (M1) | B40: 75005 | C40: 4000-R-6-1
A41: Tanisha Robison - Aide (M1) | B41: 46510 | C41: 4000-R-6-5
A42: Angie Frost - RN-CM (M2) | B42: 77503 | C42: 4000-R-6-1
A43: Rhonda Smith - Intake/Office (M2) | B43: 50000 | C43: 4000-0-I-0 | D43: PT; intake+admissions+office
A44: Dana Davenport - FT Clinical Admin (M2) | B44: 120000 | C44: 4000-0-C-0 | D44: Converts from PRN
A45: Clarenca Wooten - Aide (M3) | B45: 45771 | C45: 4000-R-6-5
A46: Silas Shelton - FT Administrator (M3) | B46: 150000 | C46: 4000-0-A-0 | D46: Converts from PRN retainer
A47: Generic RN hire (avg, ratio-driven) | B47: =(B40+B42)/2 -> 76254 | C47: 4000-R-6-1 | D47: Auto-added when ADC>30
A48: Generic Aide hire (avg, ratio-driven) | B48: =(B41+B45)/2 -> 46140.5 | C48: 4000-R-6-5 | D48: Auto-added when ADC>24
A50: LEGEND
A51: BLUE = input you can change
A52: BLACK = formula
A53: GREEN = cross-sheet link / GL account
A54: YELLOW = flagged: confirm or add to QBO
A56: G. REVENUE - MEDICARE RHC (FY2026 published rates)
A57: RHC rate days 1-60 ($/day, national) | B57: 230.83 | C57: 3000-R-6-0 | D57: FY2026 final rule; pre-wage-index
A58: RHC rate days 61+ ($/day, national) | B58: 182.36 | C58: 3000-R-6-0 | D58: ~FY2025 x2.6%; confirm vs rate table
A59: Tyler CBSA 46340 wage index | B59: 0.88 | D59: Confirm FY2026 hospice WI addendum
A60: RHC labor share | B60: 0.66 | D60: FY2026; non-labor 34%
A61: % patient-days in tier 1 (days 1-60) | B61: 0.45 | D61: LOS mix; tune to validate
A62: Sequestration reduction | B62: 0.02 | D62: 2% Medicare reduction (applied)
A63: Service Intensity Add-On (SIA) | B63: 0 | D63: Excluded (conservative)
A64: Billing fee (% of gross) | B64: 0.015 | D64: Deducted to net revenue
A65: Medicare aggregate cap / beneficiary | B65: 35361.44 | D65: FY2026 cap amount
A67: H. OPERATING BUDGET — DIRECT PATIENT CARE (per patient-day) & OVERHEAD
A68: DME rental ($/patient-day) | B68: 9 | C68: 5050-R-6-0 | D68: Beds, O2, lift equip
A69: Medications ($/patient-day) | B69: 3.5 | C69: 5100-R-6-0 | D69: Contracted Rx formulary
A70: Medical supplies ($/patient-day) | B70: 3 | C70: 5090-R-6-0 | D70: Dressings, gloves, PPE
A71: Continuing ed + credentialing ($/PD) | B71: 1 | C71: 6560-R-6-X | D71: Estimate — confirm
A72: Mileage (% of net revenue) | B72: 0.02 | C72: 5110-R-6-0 | D72: Blended clinical travel
A73: EMR ($/patient/month) | B73: 75 | C73: 6530-0-Z-0 | D73: Above ~14 census
A74: EMR monthly floor ($) | B74: 1000 | C74: 6530-0-Z-0 | D74: Until census ~14
A75: Facility rent ($/mo) Y1 / Y2 / Y3 | B75: 3450 | C75: Y2 5000 / Y3 7000 | D75: 7000
A76: Insurance stack ($/mo) Y1 / Y2 / Y3 | B76: 3333 | C76: Y2 3833 / Y3 4333 | D76: 4333
A77: Legal ($/mo) | B77: 2000 | C77: 6600-0-Z-0 | D77: Heavier in startup
A78: Accounting / payroll fees ($/mo) | B78: 1000 | C78: 6510-0-Z-0 | D78: Incl Gusto
A79: Regulatory consulting ($/mo) | B79: 750 | C79: 6550-0-Z-0 | D79: Lee / Harris — CHOW/PPEO
A80: Marketing — advertising ($/mo) | B80: 1200 | C80: 6800-1-M-0
A81: Marketing — brochures/materials ($/mo) | B81: 800 | C81: 6800-2-M-0
A82: Office supplies ($/mo) | B82: 500 | C82: 6650-0-Z-0
A83: Telephone / communications ($/mo) | B83: 600 | C83: 6710-0-Z-0
A84: Utilities ($/mo) | B84: 600 | C84: 6150-0-Z-0
A85: Bank service charges ($/mo) | B85: 150 | C85: 6520-0-Z-0
A86: Dues / subscriptions ($/mo) | B86: 300 | C86: 6570-0-Z-0
A88: I. CAPITAL / FINANCING
A89: Acquisition intangible ($) | B89: 300000 | C89: intangible | D89: Avant license/goodwill
A90: Intangible amortization (years) | B90: 15 | C90: amort | D90: Sec.197 straight-line
A91: SBA 7(a) principal ($) | B91: 500000 | C91: 2400
A92: SBA rate (APR) | B92: 0.115 | D92: 10-yr term
A93: SBA term (years) | B93: 10
A94: Seller note financed ($) | B94: 200000 | C94: 2400 | D94: After $50K down + M6 balloon
A95: Seller note rate | B95: 0.06 | D95: Simple, per MIPA
A96: TX franchise/margin tax (eff. rate) | B96: 0.00375 | D96: ~0.375% retail/wholesale est
A97: Hickory hospice license ($) | B97: 300000
A98: License upfront payment ($/mo, M1-M3) | B98: 25000
A99: License refi rate (APR) | B99: 0.06
A100: License refi term (months) | B100: 36

Sheet ARCHIVE_COA Mapping
A1: COA MAPPING — Staffing Lines to QuickBooks Accounts
A3: GL Account | B3: Account Name | C3: Model Line | D3: Notes
A4: 4000-R-6-1 | B4: Direct Care:Wages-RN-RHC | C4: Jodi, Angie, Generic RN | D4: Salaried RN case managers
A5: 4000-R-6-5 | B5: Direct Care:Wages-Aide-RHC | C5: Tanisha, Clarenca, Generic Aide | D5: Salaried hospice aides
A6: 4000-R-6-4 | B6: Direct Care:Wages-LVN On Call-RHC | C6: PRN On-Call LVN | D6: Per-visit, after-hours
A7: 4000-R-6-6 | B7: Direct Care:Wages-MSW-RHC | C7: PRN Social Worker | D7: Per-visit
A8: 4000-R-6-7 | B8: Direct Care:Wages-SC-RHC | C8: PRN Chaplain | D8: Per-visit spiritual care
A9: 4000-R-6-N | B9: Direct Care:Wages-Nurse Practitioner-RHC | C9: PRN NP | D9: F2F recert visits
A10: 4000-0-M-0 | B10: Indirect Expense:Wages-Marketing | C10: Brad Woodard | D10: Director of Sales
A11: 4000-0-I-0 | B11: Allocable:Intake:Wages-Intake/Admit | C11: Rhonda Smith | D11: Intake+admissions+office
A12: 4000-0-A-0 | B12: Indirect Expense:Wages-Administrative | C12: Silas (FT, M3+) | D12: Administrator
A13: 4000-0-C-0 | B13: Indirect Expense:Wages-Clinical Administration | C13: Dana (FT, M2+) | D13: DON / Clinical Services
A14: 4020-0-A-0 | B14: Indirect Expense:Contract Labor-Administrative | C14: Silas PRN retainer (M1-M2) | D14: Admin of record, PRN
... A27: 6620-0-M-0 | B27: Indirect Expense:Mileage-Marketing | C27: Brad marketing mileage | D27: Non-patient; flat budget

Sheet ARCHIVE_Census Waterfall
A1: CENSUS WATERFALL — 36-Month ADC Ramp · 15% Monthly Discharge
A2: Target ADC drives staffing & revenue. Admits = ADC growth + discharges. M1-M3 inputs; M4+ ramp.
A4: Month | B4: Year | C4: Target ADC | D4: Beg.Census | E4: Disch.Rate | F4: Discharges | G4: Admits Req'd | H4: End.Census | I4: Notes
A5: M1 | B5: Year 1 | C5: 15 | D5: 15 | E5: ='ARCHIVE_Control Tower'!$B$20 -> 0.15 | F5: =D5*E5 -> 2.25 | G5: =MAX(0,C5-D5+F5) -> 2.25 | H5: =D5+G5-F5 -> 15 | I5: CHOW transfer patients (Avant MIPA)
A6: M2 | B6: Year 1 | C6: 17 | D6: =H5 -> 15 | E6: ='ARCHIVE_Control Tower'!$B$20 -> 0.15 | F6: =D6*E6 -> 2.25 | G6: =MAX(0,C6-D6+F6) -> 4.25 | H6: =D6+G6-F6 -> 17 | I6: Referral network build
A7: M3 | B7: Year 1 | C7: 18 | D7: =H6 -> 17 | E7: ='ARCHIVE_Control Tower'!$B$20 -> 0.15 | F7: =D7*E7 -> 2.55 | G7: =MAX(0,C7-D7+F7) -> 3.55 | H7: =D7+G7-F7 -> 18
A8: M4 | B8: Year 1 | C8: 20 | D8: =H7 -> 18 | E8: ='ARCHIVE_Control Tower'!$B$20 -> 0.15 | F8: =D8*E8 -> 2.7 | G8: =MAX(0,C8-D8+F8) -> 4.7 | H8: =D8+G8-F8 -> 20
A9: M5 | B9: Year 1 | C9: 22 | D9: =H8 -> 20 | E9: ='ARCHIVE_Control Tower'!$B$20 -> 0.15 | F9: =D9*E9 -> 3 | G9: =MAX(0,C9-D9+F9) -> 5 | H9: =D9+G9-F9 -> 22
A10: M6 | B10: Year 1 | C10: 23 | D10: =H9 -> 22 | E10: ='ARCHIVE_Control Tower'!$B$20 -> 0.15 | F10: =D10*E10 -> 3.3 | G10: =MAX(0,C10-D10+F10) -> 4.3 | H10: =D10+G10-F10 -> 23
A11: M7 | B11: Year 1 | C11: 25 | D11: =H10 -> 23 | E11: ='ARCHIVE_Control Tower'!$B$20 -> 0.15 | F11: =D11*E11 -> 3.45 | G11: =MAX(0,C11-D11+F11) -> 5.45 | H11: =D11+G11-F11 -> 25
A12: M8 | B12: Year 1 | C12: 26 | D12: =H11 -> 25 | E12: ='ARCHIVE_Control Tower'!$B$20 -> 0.15 | F12: =D12*E12 -> 3.75 | G12: =MAX(0,C12-D12+F12) -> 4.75 | H12: =D12+G12-F12 -> 26
A13: M9 | B13: Year 1 | C13: 28 | D13: =H12 -> 26 | E13: ='ARCHIVE_Control Tower'!$B$20 -> 0.15 | F13: =D13*E13 -> 3.9 | G13: =MAX(0,C13-D13+F13) -> 5.9 | H13: =D13+G13-F13 -> 28
A14: M10 | B14: Year 1 | C14: 30 | D14: =H13 -> 28 | E14: ='ARCHIVE_Control Tower'!$B$20 -> 0.15 | F14: =D14*E14 -> 4.2 | G14: =MAX(0,C14-D14+F14) -> 6.2 | H14: =D14+G14-F14 -> 30
A15: M11 | B15: Year 1 | C15: 31 | D15: =H14 -> 30 | E15: ='ARCHIVE_Control Tower'!$B$20 -> 0.15 | F15: =D15*E15 -> 4.5 | G15: =MAX(0,C15-D15+F15) -> 5.5 | H15: =D15+G15-F15 -> 31
A16: M12 | B16: Year 1 | C16: 33 | D16: =H15 -> 31 | E16: ='ARCHIVE_Control Tower'!$B$20 -> 0.15 | F16: =D16*E16 -> 4.65 | G16: =MAX(0,C16-D16+F16) -> 6.65 | H16: =D16+G16-F16 -> 33 | I16: Y1 target 33 ADC (avg ~24)
A17: M13 | B17: Year 2 | C17: 34 | D17: =H16 -> 33 | E17: ='ARCHIVE_Control Tower'!$B$20 -> 0.15 | F17: =D17*E17 -> 4.95 | G17: =MAX(0,C17-D17+F17) -> 5.95 | H17: =D17+G17-F17 -> 34
A18: M14 | B18: Year 2 | C18: 36 | D18: =H17 -> 34 | E18: ='ARCHIVE_Control Tower'!$B$20 -> 0.15 | F18: =D18*E18 -> 5.1 | G18: =MAX(0,C18-D18+F18) -> 7.1 | H18: =D18+G18-F18 -> 36
A19: M15 | B19: Year 2 | C19: 37 | D19: =H18 -> 36 | E19: ='ARCHIVE_Control Tower'!$B$20 -> 0.15 | F19: =D19*E19 -> 5.4 | G19: =MAX(0,C19-D19+F19) -> 6.4 | H19: =D19+G19-F19 -> 37
A20: M16 | B20: Year 2 | C20: 39 | D20: =H19 -> 37 | E20: ='ARCHIVE_Control Tower'!$B$20 -> 0.15 | F20: =D20*E20 -> 5.55 | G20: =MAX(0,C20-D20+F20) -> 7.55 | H20: =D20+G20-F20 -> 39
A21: M17 | B21: Year 2 | C21: 40 | D21: =H20 -> 39 | E21: ='ARCHIVE_Control Tower'!$B$20 -> 0.15 | F21: =D21*E21 -> 5.85 | G21: =MAX(0,C21-D21+F21) -> 6.85 | H21: =D21+G21-F21 -> 40
A22: M18 | B22: Year 2 | C22: 42 | D22: =H21 -> 40 | E22: ='ARCHIVE_Control Tower'!$B$20 -> 0.15 | F22: =D22*E22 -> 6 | G22: =MAX(0,C22-D22+F22) -> 8 | H22: =D22+G22-F22 -> 42
A23: M19 | B23: Year 2 | C23: 43 | D23: =H22 -> 42 | E23: ='ARCHIVE_Control Tower'!$B$20 -> 0.15 | F23: =D23*E23 -> 6.3 | G23: =MAX(0,C23-D23+F23) -> 7.3 | H23: =D23+G23-F23 -> 43
A24: M20 | B24: Year 2 | C24: 44 | D24: =H23 -> 43 | E24: ='ARCHIVE_Control Tower'!$B$20 -> 0.15 | F24: =D24*E24 -> 6.45 | G24: =MAX(0,C24-D24+F24) -> 7.45 | H24: =D24+G24-F24 -> 44
A25: M21 | B25: Year 2 | C25: 46 | D25: =H24 -> 44 | E25: ='ARCHIVE_Control Tower'!$B$20 -> 0.15 | F25: =D25*E25 -> 6.6 | G25: =MAX(0,C25-D25+F25) -> 8.6 | H25: =D25+G25-F25 -> 46
A26: M22 | B26: Year 2 | C26: 47 | D26: =H25 -> 46 | E26: ='ARCHIVE_Control Tower'!$B$20 -> 0.15 | F26: =D26*E26 -> 6.9 | G26: =MAX(0,C26-D26+F26) -> 7.9 | H26: =D26+G26-F26 -> 47
A27: M23 | B27: Year 2 | C27: 49 | D27: =H26 -> 47 | E27: ='ARCHIVE_Control Tower'!$B$20 -> 0.15 | F27: =D27*E27 -> 7.05 | G27: =MAX(0,C27-D27+F27) -> 9.05 | H27: =D27+G27-F27 -> 49
A28: M24 | B28: Year 2 | C28: 50 | D28: =H27 -> 49 | E28: ='ARCHIVE_Control Tower'!$B$20 -> 0.15 | F28: =D28*E28 -> 7.35 | G28: =MAX(0,C28-D28+F28) -> 8.35 | H28: =D28+G28-F28 -> 50 | I28: Y2 target 50 ADC
A29: M25 | B29: Year 3 | C29: 51 | D29: =H28 -> 50 | E29: ='ARCHIVE_Control Tower'!$B$20 -> 0.15 | F29: =D29*E29 -> 7.5 | G29: =MAX(0,C29-D29+F29) -> 8.5 | H29: =D29+G29-F29 -> 51
A30: M26 | B30: Year 3 | C30: 52 | D30: =H29 -> 51 | E30: ='ARCHIVE_Control Tower'!$B$20 -> 0.15 | F30: =D30*E30 -> 7.65 | G30: =MAX(0,C30-D30+F30) -> 8.65 | H30: =D30+G30-F30 -> 52
A31: M27 | B31: Year 3 | C31: 52 | D31: =H30 -> 52 | E31: ='ARCHIVE_Control Tower'!$B$20 -> 0.15 | F31: =D31*E31 -> 7.8 | G31: =MAX(0,C31-D31+F31) -> 7.8 | H31: =D31+G31-F31 -> 52
A32: M28 | B32: Year 3 | C32: 53 | D32: =H31 -> 52 | E32: ='ARCHIVE_Control Tower'!$B$20 -> 0.15 | F32: =D32*E32 -> 7.8 | G32: =MAX(0,C32-D32+F32) -> 8.8 | H32: =D32+G32-F32 -> 53
A33: M29 | B33: Year 3 | C33: 54 | D33: =H32 -> 53 | E33: ='ARCHIVE_Control Tower'!$B$20 -> 0.15 | F33: =D33*E33 -> 7.95 | G33: =MAX(0,C33-D33+F33) -> 8.95 | H33: =D33+G33-F33 -> 54
A34: M30 | B34: Year 3 | C34: 55 | D34: =H33 -> 54 | E34: ='ARCHIVE_Control Tower'!$B$20 -> 0.15 | F34: =D34*E34 -> 8.1 | G34: =MAX(0,C34-D34+F34) -> 9.1 | H34: =D34+G34-F34 -> 55
A35: M31 | B35: Year 3 | C35: 56 | D35: =H34 -> 55 | E35: ='ARCHIVE_Control Tower'!$B$20 -> 0.15 | F35: =D35*E35 -> 8.25 | G35: =MAX(0,C35-D35+F35) -> 9.25 | H35: =D35+G35-F35 -> 56
A36: M32 | B36: Year 3 | C36: 57 | D36: =H35 -> 56 | E36: ='ARCHIVE_Control Tower'!$B$20 -> 0.15 | F36: =D36*E36 -> 8.4 | G36: =MAX(0,C36-D36+F36) -> 9.4 | H36: =D36+G36-F36 -> 57
A37: M33 | B37: Year 3 | C37: 58 | D37: =H36 -> 57 | E37: ='ARCHIVE_Control Tower'!$B$20 -> 0.15 | F37: =D37*E37 -> 8.55 | G37: =MAX(0,C37-D37+F37) -> 9.55 | H37: =D37+G37-F37 -> 58
A38: M34 | B38: Year 3 | C38: 58 | D38: =H37 -> 58 | E38: ='ARCHIVE_Control Tower'!$B$20 -> 0.15 | F38: =D38*E38 -> 8.7 | G38: =MAX(0,C38-D38+F38) -> 8.7 | H38: =D38+G38-F38 -> 58
A39: M35 | B39: Year 3 | C39: 59 | D39: =H38 -> 58 | E39: ='ARCHIVE_Control Tower'!$B$20 -> 0.15 | F39: =D39*E39 -> 8.7 | G39: =MAX(0,C39-D39+F39) -> 9.7 | H39: =D39+G39-F39 -> 59
A40: M36 | B40: Year 3 | C40: 60 | D40: =H39 -> 59 | E40: ='ARCHIVE_Control Tower'!$B$20 -> 0.15 | F40: =D40*E40 -> 8.85 | G40: =MAX(0,C40-D40+F40) -> 9.85 | H40: =D40+G40-F40 -> 60 | I40: Y3 target 60 ADC
A42: ANNUAL AVERAGE ADC
A43: Year 1 | C43: =AVERAGE(C5:C16) -> 24
A44: Year 2 | C44: =AVERAGE(C17:C28) -> 42.25
A45: Year 3 | C45: =AVERAGE(C29:C40) -> 55.416667

Sheet ARCHIVE_Revenue Model
A1: REVENUE MODEL — 100% Medicare RHC · FY2026 Rates · Bottom-Up with Validation
A2: Wage-adjusted FY2026 RHC rates · 2% sequestration · SIA excluded · 1.5% billing fee · all rates flow from Control Tower Section G
A4: A. RATE BUILD (per patient day)
A5: RHC rate, days 1-60 ($/day) | B5: ='ARCHIVE_Control Tower'!$B$57 -> 230.83 | C5: national, FY2026
A6: RHC rate, days 61+ ($/day) | B6: ='ARCHIVE_Control Tower'!$B$58 -> 182.36 | C6: national, FY2026
A7: Tyler CBSA 46340 wage index | B7: ='ARCHIVE_Control Tower'!$B$59 -> 0.88 | C7: confirm WI addendum
A8: Wage-index adjustment factor | B8: ='ARCHIVE_Control Tower'!$B$60*B7+(1-'ARCHIVE_Control Tower'!$B$60) -> 0.9208
A9: Wage-adjusted rate, days 1-60 | B9: =B5*B8 -> 212.54826 | C9: labor share x WI + non-labor
A10: Wage-adjusted rate, days 61+ | B10: =B6*B8 -> 167.91709
A11: % patient-days in tier 1 (1-60) | B11: ='ARCHIVE_Control Tower'!$B$61 -> 0.45 | C11: LOS mix — tune to validate
A12: Blended gross rate ($/day) | B12: =B11*B9+(1-B11)*B10 -> 188.00112 | C12: weighted by LOS mix
A13: After 2% sequestration ($/day) | B13: =B12*(1-'ARCHIVE_Control Tower'!$B$62) -> 184.24109 | C13: Medicare payment/day
A14: Net rate after billing fee ($/day) | B14: =B13*(1-'ARCHIVE_Control Tower'!$B$64) -> 181.47748 | C14: net revenue per patient day
A16: B. MONTHLY BILLED REVENUE
A17: Line | C17: M1 | D17: M2 | E17: M3 | F17: M4 | G17: M5 | H17: M6 | I17: M7 | J17: M8 | K17: M9 | L17: M10 | M17: M11 | N17: M12 | O17: M13 | P17: M14 | Q17: M15 | R17: M16 | S17: M17 | T17: M18 | U17: M19 | V17: M20 | W17: M21 | X17: M22 | Y17: M23 | Z17: M24 | AA17: M25 | AB17: M26 | AC17: M27 | AD17: M28 | AE17: M29 | AF17: M30 | AG17: M31 | AH17: M32 | AI17: M33 | AJ17: M34 | AK17: M35 | AL17: M36 | AM17: Y1 | AN17: Y2 | AO17: Y3
A18: ADC (from Census Waterfall) | C18: ='ARCHIVE_Census Waterfall'!$C$5 -> 15 | D18: ='ARCHIVE_Census Waterfall'!$C$6 -> 17 | E18: ='ARCHIVE_Census Waterfall'!$C$7 -> 18 | F18: ='ARCHIVE_Census Waterfall'!$C$8 -> 20 | G18: ='ARCHIVE_Census Waterfall'!$C$9 -> 22 | H18: ='ARCHIVE_Census Waterfall'!$C$10 -> 23 | I18: ='ARCHIVE_Census Waterfall'!$C$11 -> 25 | J18: ='ARCHIVE_Census Waterfall'!$C$12 -> 26 | K18: ='ARCHIVE_Census Waterfall'!$C$13 -> 28 | L18: ='ARCHIVE_Census Waterfall'!$C$14 -> 30 | M18: ='ARCHIVE_Census Waterfall'!$C$15 -> 31 | N18: ='ARCHIVE_Census Waterfall'!$C$16 -> 33 | O18: ='ARCHIVE_Census Waterfall'!$C$17 -> 34 | P18: ='ARCHIVE_Census Waterfall'!$C$18 -> 36 | Q18: ='ARCHIVE_Census Waterfall'!$C$19 -> 37 | R18: ='ARCHIVE_Census Waterfall'!$C$20 -> 39 | S18: ='ARCHIVE_Census Waterfall'!$C$21 -> 40 | T18: ='ARCHIVE_Census Waterfall'!$C$22 -> 42 | U18: ='ARCHIVE_Census Waterfall'!$C$23 -> 43 | V18: ='ARCHIVE_Census Waterfall'!$C$24 -> 44 | W18: ='ARCHIVE_Census Waterfall'!$C$25 -> 46 | X18: ='ARCHIVE_Census Waterfall'!$C$26 -> 47 | Y18: ='ARCHIVE_Census Waterfall'!$C$27 -> 49 | Z18: ='ARCHIVE_Census Waterfall'!$C$28 -> 50 | AA18: ='ARCHIVE_Census Waterfall'!$C$29 -> 51 | AB18: ='ARCHIVE_Census Waterfall'!$C$30 -> 52 | AC18: ='ARCHIVE_Census Waterfall'!$C$31 -> 52 | AD18: ='ARCHIVE_Census Waterfall'!$C$32 -> 53 | AE18: ='ARCHIVE_Census Waterfall'!$C$33 -> 54 | AF18: ='ARCHIVE_Census Waterfall'!$C$34 -> 55 | AG18: ='ARCHIVE_Census Waterfall'!$C$35 -> 56 | AH18: ='ARCHIVE_Census Waterfall'!$C$36 -> 57 | AI18: ='ARCHIVE_Census Waterfall'!$C$37 -> 58 | AJ18: ='ARCHIVE_Census Waterfall'!$C$38 -> 58 | AK18: ='ARCHIVE_Census Waterfall'!$C$39 -> 59 | AL18: ='ARCHIVE_Census Waterfall'!$C$40 -> 60
A19: Days in month | C19: ='ARCHIVE_Control Tower'!$B$21 -> 30.4 | D19: ='ARCHIVE_Control Tower'!$B$21 -> 30.4 | E19: ='ARCHIVE_Control Tower'!$B$21 -> 30.4 | F19: ='ARCHIVE_Control Tower'!$B$21 -> 30.4 | G19: ='ARCHIVE_Control Tower'!$B$21 -> 30.4 | H19: ='ARCHIVE_Control Tower'!$B$21 -> 30.4 | I19: ='ARCHIVE_Control Tower'!$B$21 -> 30.4 | J19: ='ARCHIVE_Control Tower'!$B$21 -> 30.4 | ... AL19: ='ARCHIVE_Control Tower'!$B$21 -> 30.4
A20: Patient-days | C20: =C18*C19 -> 456 | D20: =D18*D19 -> 516.8 | E20: =E18*E19 -> 547.2 | F20: =F18*F19 -> 608 | G20: =G18*G19 -> 668.8 | H20: =H18*H19 -> 699.2 | I20: =I18*I19 -> 760 | J20: =J18*J19 -> 790.4 | ... AL20: =AL18*AL19 -> 1824 | AM20: =SUM(C20:N20) -> 8755.2 | AN20: =SUM(O20:Z20) -> 15412.8 | AO20: =SUM(AA20:AL20) -> 20216
A21: Gross Medicare (post-sequestration) | C21: =C20*$B$13 -> 84013.939 | D21: =D20*$B$13 -> 95215.798 | E21: =E20*$B$13 -> 100816.73 | F21: =F20*$B$13 -> 112018.59 | G21: =G20*$B$13 -> 123220.44 | H21: =H20*$B$13 -> 128821.37 | I21: =I20*$B$13 -> 140023.23 | J21: =J20*$B$13 -> 145624.16 | ... AL21: =AL20*$B$13 -> 336055.76 | AM21: =SUM(C21:N21) -> 1613067.6 | AN21: =SUM(O21:Z21) -> 2839671.1 | AO21: =SUM(AA21:AL21) -> 3724618
A22: Less: billing fee (1.5%) | C22: =-C21*'ARCHIVE_Control Tower'!$B$64 -> -1260.2091 | D22: =-D21*'ARCHIVE_Control Tower'!$B$64 -> -1428.237 | E22: =-E21*'ARCHIVE_Control Tower'!$B$64 -> -1512.2509 | F22: =-F21*'ARCHIVE_Control Tower'!$B$64 -> -1680.2788 | G22: =-G21*'ARCHIVE_Control Tower'!$B$64 -> -1848.3067 | H22: =-H21*'ARCHIVE_Control Tower'!$B$64 -> -1932.3206 | I22: =-I21*'ARCHIVE_Control Tower'!$B$64 -> -2100.3485 | J22: =-J21*'ARCHIVE_Control Tower'!$B$64 -> -2184.3624 | ... AL22: =-AL21*'ARCHIVE_Control Tower'!$B$64 -> -5040.8364 | AM22: =SUM(C22:N22) -> -24196.015 | AN22: =SUM(O22:Z22) -> -42595.067 | AO22: =SUM(AA22:AL22) -> -55869.27
A23: NET REVENUE | C23: =C21+C22 -> 82753.73 | D23: =D21+D22 -> 93787.561 | E23: =E21+E22 -> 99304.476 | F23: =F21+F22 -> 110338.31 | G23: =G21+G22 -> 121372.14 | H23: =H21+H22 -> 126889.05 | I23: =I21+I22 -> 137922.88 | J23: =J21+J22 -> 143439.8 | ... AL23: =AL21+AL22 -> 331014.92 | AM23: =SUM(C23:N23) -> 1588871.6 | AN23: =SUM(O23:Z23) -> 2797076.1 | AO23: =SUM(AA23:AL23) -> 3668748.7
A25: C. VALIDATION vs HANDOFF BRIEF
A26: Net Revenue | C26: Bottom-Up (model) | D26: Brief Target | E26: Variance
A27: Year 1 | C27: =AM23 -> 1588871.6 | D27: 1605199 | E27: =(C27-D27)/D27 -> -0.010171562
A28: Year 2 | C28: =AN23 -> 2797076.1 | D28: 2628166 | E28: =(C28-D28)/D28 -> 0.064269182
A29: Year 3 | C29: =AO23 -> 3668748.7 | D29: 3580092 | E29: =(C29-D29)/D29 -> 0.024763806
A30: D. MEDICARE AGGREGATE CAP CHECK (FY2026 cap $35,361.44 / beneficiary)
B31: Beneficiaries | C31: Cap Allowable | D31: Gross Medicare | E31: Headroom | F31: Rev/Benef.
A32: Year 1 | B32: ='ARCHIVE_Census Waterfall'!D5+SUM('ARCHIVE_Census Waterfall'!G5:G16) -> 73.5 | C32: =B32*'ARCHIVE_Control Tower'!$B$65 -> 2599065.8 | D32: =AM21 -> 1613067.6 | E32: =C32-D32 -> 985998.21 | F32: =D32/B32 -> 21946.498
A33: Year 2 | B33: ='ARCHIVE_Census Waterfall'!D17+SUM('ARCHIVE_Census Waterfall'!G17:G28) -> 123.5 | C33: =B33*'ARCHIVE_Control Tower'!$B$65 -> 4367137.8 | D33: =AN21 -> 2839671.1 | E33: =C33-D33 -> 1527466.7 | F33: =D33/B33 -> 22993.289
A34: Year 3 | B34: ='ARCHIVE_Census Waterfall'!D29+SUM('ARCHIVE_Census Waterfall'!G29:G40) -> 158.25 | C34: =B34*'ARCHIVE_Control Tower'!$B$65 -> 5595947.9 | D34: =AO21 -> 3724618 | E34: =C34-D34 -> 1871329.9 | F34: =D34/B34 -> 23536.291
A35: Headroom positive = no cap liability. Note: sensitive to ALOS; 15%/mo discharge implies long stays — validate.
A37: E. COLLECTIONS TIMING — BASE CASE (first claim M2/Jul 1 · ~2-mo lag · PPEO hold M6-M8, released M9)
A38: Line | C38: M1 | D38: M2 | E38: M3 | F38: M4 | G38: M5 | H38: M6 | I38: M7 | J38: M8 | K38: M9 | L38: M10 | M38: M11 | N38: M12 | O38: M13 | P38: M14 | Q38: M15 | R38: M16 | S38: M17 | T38: M18 | U38: M19 | V38: M20 | W38: M21 | X38: M22 | Y38: M23 | Z38: M24 | AA38: M25 | AB38: M26 | AC38: M27 | AD38: M28 | AE38: M29 | AF38: M30 | AG38: M31 | AH38: M32 | AI38: M33 | AJ38: M34 | AK38: M35 | AL38: M36 | AM38: Y1 | AN38: Y2 | AO38: Y3
A39: Net revenue billed | C39: =C23 -> 82753.73 | D39: =D23 -> 93787.561 | E39: =E23 -> 99304.476 | F39: =F23 -> 110338.31 | G39: =G23 -> 121372.14 | H39: =H23 -> 126889.05 | I39: =I23 -> 137922.88 | J39: =J23 -> 143439.8 | ... AL39: =AL23 -> 331014.92 | AM39: =SUM(C39:N39) -> 1588871.6 | AN39: =SUM(O39:Z39) -> 2797076.1 | AO39: =SUM(AA39:AL39) -> 3668748.7
A40: Medicare cash collected (w/ PPEO hold) | C40: =0 -> 0 | D40: =0 -> 0 | E40: =C39 -> 82753.73 | F40: =D39 -> 93787.561 | G40: =E39 -> 99304.476 | H40: =0 -> 0 | I40: =0 -> 0 | J40: =0 -> 0 | K40: =I39+F39+G39+H39 -> 496522.38 | L40: =J39 -> 143439.8 | M40: =K39 -> 154473.63 | N40: =L39 -> 165507.46 | O40: =M39 -> 171024.38 | P40: =N39 -> 182058.21 | Q40: =O39 -> 187575.12 | R40: =P39 -> 198608.95 | S40: =Q39 -> 204125.87 | ... AL40: =AJ39 -> 319981.09 | AM40: =SUM(C40:N40) -> 1235789 | AN40: =SUM(O40:Z40) -> 2603984 | AO40: =SUM(AA40:AL40) -> 3558410.4
A41: Cumulative cash vs billed (gap) | C41: =C40-C39 -> -82753.73 | D41: =C41+D40-D39 -> -176541.29 | E41: =D41+E40-E39 -> -193092.04 | F41: =E41+F40-F39 -> -209642.78 | G41: =F41+G40-G39 -> -231710.44 | H41: =G41+H40-H39 -> -358599.5 | I41: =H41+I40-I39 -> -496522.38 | J41: =I41+J40-J39 -> -639962.18 | K41: =J41+K40-K39 -> -297913.43 | ... AL41: =AK41+AL40-AL39 -> -656512.93
A42: Max cumulative gap = working-capital bridge the $500K SBA funds.

Sheet ARCHIVE_Staffing Summary
A1: STAFFING SUMMARY — 36-Month Engine · COA-Tagged · Census-Ratio Driven
A2: Burden: FICA 7.65% + FUTA/SUTA 1.85% + WC 3% on W-2 wages · Health $500/mo per FT · Mileage $0.50/mi · Merit 3% Y2/Y3
A4: Line Item | B4: GL Account | C4: Start | D4: M1 | E4: M2 | F4: M3 | G4: M4 | H4: M5 | I4: M6 | J4: M7 | K4: M8 | L4: M9 | M4: M10 | N4: M11 | O4: M12 | P4: M13 | Q4: M14 | R4: M15 | S4: M16 | T4: M17 | U4: M18 | V4: M19 | W4: M20 | X4: M21 | Y4: M22 | Z4: M23 | AA4: M24 | AB4: M25 | AC4: M26 | AD4: M27 | AE4: M28 | AF4: M29 | AG4: M30 | AH4: M31 | AI4: M32 | AJ4: M33 | AK4: M34 | AL4: M35 | AM4: M36 | AN4: Y1 Tot | AO4: Y2 Tot | AP4: Y3 Tot
A5: DRIVERS
A6: Month Index | D6: 1 | E6: 2 | F6: 3 | G6: 4 | H6: 5 | I6: 6 | J6: 7 | K6: 8 | L6: 9 | M6: 10 | N6: 11 | O6: 12 | P6: 13 | Q6: 14 | R6: 15 | S6: 16 | T6: 17 | U6: 18 | V6: 19 | W6: 20 | X6: 21 | Y6: 22 | Z6: 23 | AA6: 24 | AB6: 25 | AC6: 26 | AD6: 27 | AE6: 28 | AF6: 29 | AG6: 30 | AH6: 31 | AI6: 32 | AJ6: 33 | AK6: 34 | AL6: 35 | AM6: 36
A7: ADC (from Census Waterfall) | D7: ='ARCHIVE_Census Waterfall'!$C$5 -> 15 | E7: ='ARCHIVE_Census Waterfall'!$C$6 -> 17 | F7: ='ARCHIVE_Census Waterfall'!$C$7 -> 18 | G7: ='ARCHIVE_Census Waterfall'!$C$8 -> 20 | H7: ='ARCHIVE_Census Waterfall'!$C$9 -> 22 | I7: ='ARCHIVE_Census Waterfall'!$C$10 -> 23 | J7: ='ARCHIVE_Census Waterfall'!$C$11 -> 25 | K7: ='ARCHIVE_Census Waterfall'!$C$12 -> 26 | L7: ='ARCHIVE_Census Waterfall'!$C$13 -> 28 | M7: ='ARCHIVE_Census Waterfall'!$C$14 -> 30 | N7: ='ARCHIVE_Census Waterfall'!$C$15 -> 31 | O7: ='ARCHIVE_Census Waterfall'!$C$16 -> 33 | P7: ='ARCHIVE_Census Waterfall'!$C$17 -> 34 | Q7: ='ARCHIVE_Census Waterfall'!$C$18 -> 36 | R7: ='ARCHIVE_Census Waterfall'!$C$19 -> 37 | S7: ='ARCHIVE_Census Waterfall'!$C$20 -> 39 | T7: ='ARCHIVE_Census Waterfall'!$C$21 -> 40 | U7: ='ARCHIVE_Census Waterfall'!$C$22 -> 42 | V7: ='ARCHIVE_Census Waterfall'!$C$23 -> 43 | W7: ='ARCHIVE_Census Waterfall'!$C$24 -> 44 | X7: ='ARCHIVE_Census Waterfall'!$C$25 -> 46 | Y7: ='ARCHIVE_Census Waterfall'!$C$26 -> 47 | Z7: ='ARCHIVE_Census Waterfall'!$C$27 -> 49 | AA7: ='ARCHIVE_Census Waterfall'!$C$28 -> 50 | AB7: ='ARCHIVE_Census Waterfall'!$C$29 -> 51 | AC7: ='ARCHIVE_Census Waterfall'!$C$30 -> 52 | AD7: ='ARCHIVE_Census Waterfall'!$C$31 -> 52 | AE7: ='ARCHIVE_Census Waterfall'!$C$32 -> 53 | AF7: ='ARCHIVE_Census Waterfall'!$C$33 -> 54 | AG7: ='ARCHIVE_Census Waterfall'!$C$34 -> 55 | AH7: ='ARCHIVE_Census Waterfall'!$C$35 -> 56 | AI7: ='ARCHIVE_Census Waterfall'!$C$36 -> 57 | AJ7: ='ARCHIVE_Census Waterfall'!$C$37 -> 58 | AK7: ='ARCHIVE_Census Waterfall'!$C$38 -> 58 | AL7: ='ARCHIVE_Census Waterfall'!$C$39 -> 59 | AM7: ='ARCHIVE_Census Waterfall'!$C$40 -> 60
A8: Salary Escalation Factor | D8: =(1+'ARCHIVE_Control Tower'!$B$19)^0 -> 1 | E8: =(1+'ARCHIVE_Control Tower'!$B$19)^0 -> 1 | F8: =(1+'ARCHIVE_Control Tower'!$B$19)^0 -> 1 | G8: =(1+'ARCHIVE_Control Tower'!$B$19)^0 -> 1 | H8: =(1+'ARCHIVE_Control Tower'!$B$19)^0 -> 1 | I8: =(1+'ARCHIVE_Control Tower'!$B$19)^0 -> 1 | J8: =(1+'ARCHIVE_Control Tower'!$B$19)^0 -> 1 | K8: =(1+'ARCHIVE_Control Tower'!$B$19)^0 -> 1 | ... O8: =(1+'ARCHIVE_Control Tower'!$B$19)^0 -> 1 | P8: =(1+'ARCHIVE_Control Tower'!$B$19)^1 -> 1.03 | Q8: =(1+'ARCHIVE_Control Tower'!$B$19)^1 -> 1.03 | R8: =(1+'ARCHIVE_Control Tower'!$B$19)^1 -> 1.03 | S8: =(1+'ARCHIVE_Control Tower'!$B$19)^1 -> 1.03 | T8: =(1+'ARCHIVE_Control Tower'!$B$19)^1 -> 1.03 | U8: =(1+'ARCHIVE_Control Tower'!$B$19)^1 -> 1.03 | V8: =(1+'ARCHIVE_Control Tower'!$B$19)^1 -> 1.03 | W8: =(1+'ARCHIVE_Control Tower'!$B$19)^1 -> 1.03 | ... AA8: =(1+'ARCHIVE_Control Tower'!$B$19)^1 -> 1.03 | AB8: =(1+'ARCHIVE_Control Tower'!$B$19)^2 -> 1.0609 | AC8: =(1+'ARCHIVE_Control Tower'!$B$19)^2 -> 1.0609 | AD8: =(1+'ARCHIVE_Control Tower'!$B$19)^2 -> 1.0609 | AE8: =(1+'ARCHIVE_Control Tower'!$B$19)^2 -> 1.0609 | AF8: =(1+'ARCHIVE_Control Tower'!$B$19)^2 -> 1.0609 | AG8: =(1+'ARCHIVE_Control Tower'!$B$19)^2 -> 1.0609 | AH8: =(1+'ARCHIVE_Control Tower'!$B$19)^2 -> 1.0609 | AI8: =(1+'ARCHIVE_Control Tower'!$B$19)^2 -> 1.0609 | ... AM8: =(1+'ARCHIVE_Control Tower'!$B$19)^2 -> 1.0609
A9: RN-CM FTEs required | D9: =ROUNDUP(D7/'ARCHIVE_Control Tower'!$B$17,0) -> 1 | E9: =ROUNDUP(E7/'ARCHIVE_Control Tower'!$B$17,0) -> 2 | F9: =ROUNDUP(F7/'ARCHIVE_Control Tower'!$B$17,0) -> 2 | G9: =ROUNDUP(G7/'ARCHIVE_Control Tower'!$B$17,0) -> 2 | H9: =ROUNDUP(H7/'ARCHIVE_Control Tower'!$B$17,0) -> 2 | I9: =ROUNDUP(I7/'ARCHIVE_Control Tower'!$B$17,0) -> 2 | J9: =ROUNDUP(J7/'ARCHIVE_Control Tower'!$B$17,0) -> 2 | K9: =ROUNDUP(K7/'ARCHIVE_Control Tower'!$B$17,0) -> 2 | ... AM9: =ROUNDUP(AM7/'ARCHIVE_Control Tower'!$B$17,0) -> 4
A10: Aide FTEs required | D10: =ROUNDUP(D7/'ARCHIVE_Control Tower'!$B$18,0) -> 2 | E10: =ROUNDUP(E7/'ARCHIVE_Control Tower'!$B$18,0) -> 2 | F10: =ROUNDUP(F7/'ARCHIVE_Control Tower'!$B$18,0) -> 2 | G10: =ROUNDUP(G7/'ARCHIVE_Control Tower'!$B$18,0) -> 2 | H10: =ROUNDUP(H7/'ARCHIVE_Control Tower'!$B$18,0) -> 2 | I10: =ROUNDUP(I7/'ARCHIVE_Control Tower'!$B$18,0) -> 2 | J10: =ROUNDUP(J7/'ARCHIVE_Control Tower'!$B$18,0) -> 3 | K10: =ROUNDUP(K7/'ARCHIVE_Control Tower'!$B$18,0) -> 3 | ... AM10: =ROUNDUP(AM7/'ARCHIVE_Control Tower'!$B$18,0) -> 5
A11: DIRECT CARE — WAGES (Cost of Care)
A12: Jodi McCollum — RN-CM | B12: 4000-R-6-1 | C12: M1 | D12: =IF(D6>=1,'ARCHIVE_Control Tower'!$B$40/12*D8,0) -> 6250.4167 | E12: =IF(E6>=1,'ARCHIVE_Control Tower'!$B$40/12*E8,0) -> 6250.4167 | F12: =IF(F6>=1,'ARCHIVE_Control Tower'!$B$40/12*F8,0) -> 6250.4167 | G12: =IF(G6>=1,'ARCHIVE_Control Tower'!$B$40/12*G8,0) -> 6250.4167 | H12: =IF(H6>=1,'ARCHIVE_Control Tower'!$B$40/12*H8,0) -> 6250.4167 | I12: =IF(I6>=1,'ARCHIVE_Control Tower'!$B$40/12*I8,0) -> 6250.4167 | J12: =IF(J6>=1,'ARCHIVE_Control Tower'!$B$40/12*J8,0) -> 6250.4167 | K12: =IF(K6>=1,'ARCHIVE_Control Tower'!$B$40/12*K8,0) -> 6250.4167 | ... AM12: =IF(AM6>=1,'ARCHIVE_Control Tower'!$B$40/12*AM8,0) -> 6631.067 | AN12: =SUM(D12:O12) -> 75005 | AO12: =SUM(P12:AA12) -> 77255.15 | AP12: =SUM(AB12:AM12) -> 79572.805
A13: Angie Frost — RN-CM | B13: 4000-R-6-1 | C13: M2 | D13: =IF(D6>=2,'ARCHIVE_Control Tower'!$B$42/12*D8,0) -> 0 | E13: =IF(E6>=2,'ARCHIVE_Control Tower'!$B$42/12*E8,0) -> 6458.5833 | F13: =IF(F6>=2,'ARCHIVE_Control Tower'!$B$42/12*F8,0) -> 6458.5833 | G13: =IF(G6>=2,'ARCHIVE_Control Tower'!$B$42/12*G8,0) -> 6458.5833 | H13: =IF(H6>=2,'ARCHIVE_Control Tower'!$B$42/12*H8,0) -> 6458.5833 | I13: =IF(I6>=2,'ARCHIVE_Control Tower'!$B$42/12*I8,0) -> 6458.5833 | J13: =IF(J6>=2,'ARCHIVE_Control Tower'!$B$42/12*J8,0) -> 6458.5833 | K13: =IF(K6>=2,'ARCHIVE_Control Tower'!$B$42/12*K8,0) -> 6458.5833 | ... AM13: =IF(AM6>=2,'ARCHIVE_Control Tower'!$B$42/12*AM8,0) -> 6851.9111 | AN13: =SUM(D13:O13) -> 71044.417 | AO13: =SUM(P13:AA13) -> 79828.09 | AP13: =SUM(AB13:AM13) -> 82222.933
A14: Generic RN hire(s) — ratio | B14: 4000-R-6-1 | C14: ADC>30 | D14: =MAX(0,D9-((IF(D6>=1,1,0))+(IF(D6>=2,1,0))))*'ARCHIVE_Control Tower'!$B$47/12*D8 -> 0 | E14: =MAX(0,E9-((IF(E6>=1,1,0))+(IF(E6>=2,1,0))))*'ARCHIVE_Control Tower'!$B$47/12*E8 -> 0 | F14: =MAX(0,F9-((IF(F6>=1,1,0))+(IF(F6>=2,1,0))))*'ARCHIVE_Control Tower'!$B$47/12*F8 -> 0 | G14: =MAX(0,G9-((IF(G6>=1,1,0))+(IF(G6>=2,1,0))))*'ARCHIVE_Control Tower'!$B$47/12*G8 -> 0 | H14: =MAX(0,H9-((IF(H6>=1,1,0))+(IF(H6>=2,1,0))))*'ARCHIVE_Control Tower'!$B$47/12*H8 -> 0 | I14: =MAX(0,I9-((IF(I6>=1,1,0))+(IF(I6>=2,1,0))))*'ARCHIVE_Control Tower'!$B$47/12*I8 -> 0 | J14: =MAX(0,J9-((IF(J6>=1,1,0))+(IF(J6>=2,1,0))))*'ARCHIVE_Control Tower'!$B$47/12*J8 -> 0 | K14: =MAX(0,K9-((IF(K6>=1,1,0))+(IF(K6>=2,1,0))))*'ARCHIVE_Control Tower'!$B$47/12*K8 -> 0 | ... AM14: =MAX(0,AM9-((IF(AM6>=1,1,0))+(IF(AM6>=2,1,0))))*'ARCHIVE_Control Tower'!$B$47/12*AM8 -> 13482.978 | AN14: =SUM(D14:O14) -> 12709 | AO14: =SUM(P14:AA14) -> 104722.16 | AP14: =SUM(AB14:AM14) -> 161795.74
A15: Tanisha Robison — Aide | B15: 4000-R-6-5 | C15: M1 | D15: =IF(D6>=1,'ARCHIVE_Control Tower'!$B$41/12*D8,0) -> 3875.8333 | E15: =IF(E6>=1,'ARCHIVE_Control Tower'!$B$41/12*E8,0) -> 3875.8333 | F15: =IF(F6>=1,'ARCHIVE_Control Tower'!$B$41/12*F8,0) -> 3875.8333 | G15: =IF(G6>=1,'ARCHIVE_Control Tower'!$B$41/12*G8,0) -> 3875.8333 | H15: =IF(H6>=1,'ARCHIVE_Control Tower'!$B$41/12*H8,0) -> 3875.8333 | I15: =IF(I6>=1,'ARCHIVE_Control Tower'!$B$41/12*I8,0) -> 3875.8333 | J15: =IF(J6>=1,'ARCHIVE_Control Tower'!$B$41/12*J8,0) -> 3875.8333 | K15: =IF(K6>=1,'ARCHIVE_Control Tower'!$B$41/12*K8,0) -> 3875.8333 | ... AM15: =IF(AM6>=1,'ARCHIVE_Control Tower'!$B$41/12*AM8,0) -> 4111.8716 | AN15: =SUM(D15:O15) -> 46510 | AO15: =SUM(P15:AA15) -> 47905.3 | AP15: =SUM(AB15:AM15) -> 49342.459
A16: Clarenca Wooten — Aide | B16: 4000-R-6-5 | C16: M3 | D16: =IF(D6>=3,'ARCHIVE_Control Tower'!$B$45/12*D8,0) -> 0 | E16: =IF(E6>=3,'ARCHIVE_Control Tower'!$B$45/12*E8,0) -> 0 | F16: =IF(F6>=3,'ARCHIVE_Control Tower'!$B$45/12*F8,0) -> 3814.25 | G16: =IF(G6>=3,'ARCHIVE_Control Tower'!$B$45/12*G8,0) -> 3814.25 | H16: =IF(H6>=3,'ARCHIVE_Control Tower'!$B$45/12*H8,0) -> 3814.25 | I16: =IF(I6>=3,'ARCHIVE_Control Tower'!$B$45/12*I8,0) -> 3814.25 | J16: =IF(J6>=3,'ARCHIVE_Control Tower'!$B$45/12*J8,0) -> 3814.25 | K16: =IF(K6>=3,'ARCHIVE_Control Tower'!$B$45/12*K8,0) -> 3814.25 | ... AM16: =IF(AM6>=3,'ARCHIVE_Control Tower'!$B$45/12*AM8,0) -> 4046.5378 | AN16: =SUM(D16:O16) -> 38142.5 | AO16: =SUM(P16:AA16) -> 47144.13 | AP16: =SUM(AB16:AM16) -> 48558.454
A17: Generic Aide hire(s) — ratio | B17: 4000-R-6-5 | C17: ADC>24 | D17: =MAX(0,D10-((IF(D6>=1,1,0))+(IF(D6>=3,1,0))))*'ARCHIVE_Control Tower'!$B$48/12*D8 -> 3845.0417 | E17: =MAX(0,E10-((IF(E6>=1,1,0))+(IF(E6>=3,1,0))))*'ARCHIVE_Control Tower'!$B$48/12*E8 -> 3845.0417 | F17: =MAX(0,F10-((IF(F6>=1,1,0))+(IF(F6>=3,1,0))))*'ARCHIVE_Control Tower'!$B$48/12*F8 -> 0 | G17: =MAX(0,G10-((IF(G6>=1,1,0))+(IF(G6>=3,1,0))))*'ARCHIVE_Control Tower'!$B$48/12*G8 -> 0 | H17: =MAX(0,H10-((IF(H6>=1,1,0))+(IF(H6>=3,1,0))))*'ARCHIVE_Control Tower'!$B$48/12*H8 -> 0 | I17: =MAX(0,I10-((IF(I6>=1,1,0))+(IF(I6>=3,1,0))))*'ARCHIVE_Control Tower'!$B$48/12*I8 -> 0 | J17: =MAX(0,J10-((IF(J6>=1,1,0))+(IF(J6>=3,1,0))))*'ARCHIVE_Control Tower'!$B$48/12*J8 -> 3845.0417 | K17: =MAX(0,K10-((IF(K6>=1,1,0))+(IF(K6>=3,1,0))))*'ARCHIVE_Control Tower'!$B$48/12*K8 -> 3845.0417 | ... AM17: =MAX(0,AM10-((IF(AM6>=1,1,0))+(IF(AM6>=3,1,0))))*'ARCHIVE_Control Tower'!$B$48/12*AM8 -> 12237.614 | AN17: =SUM(D17:O17) -> 30760.333 | AO17: =SUM(P17:AA17) -> 95049.43 | AP17: =SUM(AB17:AM17) -> 146851.37
A18: Subtotal — Direct Care Salaried Wages | D18: =SUM(D12:D17) -> 13971.292 | E18: =SUM(E12:E17) -> 20429.875 | F18: =SUM(F12:F17) -> 20399.083 | G18: =SUM(G12:G17) -> 20399.083 | H18: =SUM(H12:H17) -> 20399.083 | I18: =SUM(I12:I17) -> 20399.083 | J18: =SUM(J12:J17) -> 24244.125 | K18: =SUM(K12:K17) -> 24244.125 | ... AM18: =SUM(AM12:AM17) -> 47361.98 | AN18: =SUM(D18:O18) -> 274171.25 | AO18: =SUM(P18:AA18) -> 451904.26 | AP18: =SUM(AB18:AM18) -> 568343.76
A19: DIRECT CARE — PRN VISIT WAGES (volume = ADC x visits/pt/mo x rate)
A20: PRN On-Call LVN | B20: 4000-R-6-4 | C20: M1 | D20: =D7*'ARCHIVE_Control Tower'!$B$24*'ARCHIVE_Control Tower'!$B$25 -> 900 | E20: =E7*'ARCHIVE_Control Tower'!$B$24*'ARCHIVE_Control Tower'!$B$25 -> 1020 | F20: =F7*'ARCHIVE_Control Tower'!$B$24*'ARCHIVE_Control Tower'!$B$25 -> 1080 | G20: =G7*'ARCHIVE_Control Tower'!$B$24*'ARCHIVE_Control Tower'!$B$25 -> 1200 | H20: =H7*'ARCHIVE_Control Tower'!$B$24*'ARCHIVE_Control Tower'!$B$25 -> 1320 | I20: =I7*'ARCHIVE_Control Tower'!$B$24*'ARCHIVE_Control Tower'!$B$25 -> 1380 | J20: =J7*'ARCHIVE_Control Tower'!$B$24*'ARCHIVE_Control Tower'!$B$25 -> 1500 | K20: =K7*'ARCHIVE_Control Tower'!$B$24*'ARCHIVE_Control Tower'!$B$25 -> 1560 | ... AM20: =AM7*'ARCHIVE_Control Tower'!$B$24*'ARCHIVE_Control Tower'!$B$25 -> 3600 | AN20: =SUM(D20:O20) -> 17280 | AO20: =SUM(P20:AA20) -> 30420 | AP20: =SUM(AB20:AM20) -> 39900
A21: PRN Chaplain (SC) | B21: 4000-R-6-7 | C21: M1 | D21: =D7*'ARCHIVE_Control Tower'!$B$26*'ARCHIVE_Control Tower'!$B$27 -> 843.75 | E21: =E7*'ARCHIVE_Control Tower'!$B$26*'ARCHIVE_Control Tower'!$B$27 -> 956.25 | F21: =F7*'ARCHIVE_Control Tower'!$B$26*'ARCHIVE_Control Tower'!$B$27 -> 1012.5 | G21: =G7*'ARCHIVE_Control Tower'!$B$26*'ARCHIVE_Control Tower'!$B$27 -> 1125 | H21: =H7*'ARCHIVE_Control Tower'!$B$26*'ARCHIVE_Control Tower'!$B$27 -> 1237.5 | I21: =I7*'ARCHIVE_Control Tower'!$B$26*'ARCHIVE_Control Tower'!$B$27 -> 1293.75 | J21: =J7*'ARCHIVE_Control Tower'!$B$26*'ARCHIVE_Control Tower'!$B$27 -> 1406.25 | K21: =K7*'ARCHIVE_Control Tower'!$B$26*'ARCHIVE_Control Tower'!$B$27 -> 1462.5 | ... AM21: =AM7*'ARCHIVE_Control Tower'!$B$26*'ARCHIVE_Control Tower'!$B$27 -> 3375 | AN21: =SUM(D21:O21) -> 16200 | AO21: =SUM(P21:AA21) -> 28518.75 | AP21: =SUM(AB21:AM21) -> 37406.25
A22: PRN Social Worker (MSW) | B22: 4000-R-6-6 | C22: M1 | D22: =D7*'ARCHIVE_Control Tower'!$B$28*'ARCHIVE_Control Tower'!$B$29 -> 1125 | E22: =E7*'ARCHIVE_Control Tower'!$B$28*'ARCHIVE_Control Tower'!$B$29 -> 1275 | F22: =F7*'ARCHIVE_Control Tower'!$B$28*'ARCHIVE_Control Tower'!$B$29 -> 1350 | G22: =G7*'ARCHIVE_Control Tower'!$B$28*'ARCHIVE_Control Tower'!$B$29 -> 1500 | H22: =H7*'ARCHIVE_Control Tower'!$B$28*'ARCHIVE_Control Tower'!$B$29 -> 1650 | I22: =I7*'ARCHIVE_Control Tower'!$B$28*'ARCHIVE_Control Tower'!$B$29 -> 1725 | J22: =J7*'ARCHIVE_Control Tower'!$B$28*'ARCHIVE_Control Tower'!$B$29 -> 1875 | K22: =K7*'ARCHIVE_Control Tower'!$B$28*'ARCHIVE_Control Tower'!$B$29 -> 1950 | ... AM22: =AM7*'ARCHIVE_Control Tower'!$B$28*'ARCHIVE_Control Tower'!$B$29 -> 4500 | AN22: =SUM(D22:O22) -> 21600 | AO22: =SUM(P22:AA22) -> 38025 | AP22: =SUM(AB22:AM22) -> 49875
A23: PRN Nurse Practitioner | B23: 4000-R-6-N | C23: M1 | D23: =D7*'ARCHIVE_Control Tower'!$B$30*'ARCHIVE_Control Tower'!$B$31 -> 450 | E23: =E7*'ARCHIVE_Control Tower'!$B$30*'ARCHIVE_Control Tower'!$B$31 -> 510 | F23: =F7*'ARCHIVE_Control Tower'!$B$30*'ARCHIVE_Control Tower'!$B$31 -> 540 | G23: =G7*'ARCHIVE_Control Tower'!$B$30*'ARCHIVE_Control Tower'!$B$31 -> 600 | H23: =H7*'ARCHIVE_Control Tower'!$B$30*'ARCHIVE_Control Tower'!$B$31 -> 660 | I23: =I7*'ARCHIVE_Control Tower'!$B$30*'ARCHIVE_Control Tower'!$B$31 -> 690 | J23: =J7*'ARCHIVE_Control Tower'!$B$30*'ARCHIVE_Control Tower'!$B$31 -> 750 | K23: =K7*'ARCHIVE_Control Tower'!$B$30*'ARCHIVE_Control Tower'!$B$31 -> 780 | ... AM23: =AM7*'ARCHIVE_Control Tower'!$B$30*'ARCHIVE_Control Tower'!$B$31 -> 1800 | AN23: =SUM(D23:O23) -> 8640 | AO23: =SUM(P23:AA23) -> 15210 | AP23: =SUM(AB23:AM23) -> 19950
A24: Subtotal — PRN Visit Wages | D24: =SUM(D20:D23) -> 3318.75 | E24: =SUM(E20:E23) -> 3761.25 | F24: =SUM(F20:F23) -> 3982.5 | G24: =SUM(G20:G23) -> 4425 | H24: =SUM(H20:H23) -> 4867.5 | I24: =SUM(I20:I23) -> 5088.75 | J24: =SUM(J20:J23) -> 5531.25 | K24: =SUM(K20:K23) -> 5752.5 | ... AM24: =SUM(AM20:AM23) -> 13275 | AN24: =SUM(D24:O24) -> 63720 | AO24: =SUM(P24:AA24) -> 112173.75 | AP24: =SUM(AB24:AM24) -> 147131.25
A25: INDIRECT — WAGES (Overhead)
A26: Brad Woodard — Marketing | B26: 4000-0-M-0 | C26: M1 | D26: =IF(D6>=1,'ARCHIVE_Control Tower'!$B$39/12*D8,0) -> 10000 | E26: =IF(E6>=1,'ARCHIVE_Control Tower'!$B$39/12*E8,0) -> 10000 | F26: =IF(F6>=1,'ARCHIVE_Control Tower'!$B$39/12*F8,0) -> 10000 | G26: =IF(G6>=1,'ARCHIVE_Control Tower'!$B$39/12*G8,0) -> 10000 | H26: =IF(H6>=1,'ARCHIVE_Control Tower'!$B$39/12*H8,0) -> 10000 | I26: =IF(I6>=1,'ARCHIVE_Control Tower'!$B$39/12*I8,0) -> 10000 | J26: =IF(J6>=1,'ARCHIVE_Control Tower'!$B$39/12*J8,0) -> 10000 | K26: =IF(K6>=1,'ARCHIVE_Control Tower'!$B$39/12*K8,0) -> 10000 | ... AM26: =IF(AM6>=1,'ARCHIVE_Control Tower'!$B$39/12*AM8,0) -> 10609 | AN26: =SUM(D26:O26) -> 120000 | AO26: =SUM(P26:AA26) -> 123600 | AP26: =SUM(AB26:AM26) -> 127308
A27: Rhonda Smith — Intake/Office | B27: 4000-0-I-0 | C27: M2 | D27: =IF(D6>=2,'ARCHIVE_Control Tower'!$B$43/12*D8,0) -> 0 | E27: =IF(E6>=2,'ARCHIVE_Control Tower'!$B$43/12*E8,0) -> 4166.6667 | F27: =IF(F6>=2,'ARCHIVE_Control Tower'!$B$43/12*F8,0) -> 4166.6667 | G27: =IF(G6>=2,'ARCHIVE_Control Tower'!$B$43/12*G8,0) -> 4166.6667 | H27: =IF(H6>=2,'ARCHIVE_Control Tower'!$B$43/12*H8,0) -> 4166.6667 | I27: =IF(I6>=2,'ARCHIVE_Control Tower'!$B$43/12*I8,0) -> 4166.6667 | J27: =IF(J6>=2,'ARCHIVE_Control Tower'!$B$43/12*J8,0) -> 4166.6667 | K27: =IF(K6>=2,'ARCHIVE_Control Tower'!$B$43/12*K8,0) -> 4166.6667 | ... AM27: =IF(AM6>=2,'ARCHIVE_Control Tower'!$B$43/12*AM8,0) -> 4420.4167 | AN27: =SUM(D27:O27) -> 45833.333 | AO27: =SUM(P27:AA27) -> 51500 | AP27: =SUM(AB27:AM27) -> 53045
A28: Silas Shelton — Administrator (FT) | B28: 4000-0-A-0 | C28: M3 | D28: =IF(D6>=3,'ARCHIVE_Control Tower'!$B$46/12*D8,0) -> 0 | E28: =IF(E6>=3,'ARCHIVE_Control Tower'!$B$46/12*E8,0) -> 0 | F28: =IF(F6>=3,'ARCHIVE_Control Tower'!$B$46/12*F8,0) -> 12500 | G28: =IF(G6>=3,'ARCHIVE_Control Tower'!$B$46/12*G8,0) -> 12500 | H28: =IF(H6>=3,'ARCHIVE_Control Tower'!$B$46/12*H8,0) -> 12500 | I28: =IF(I6>=3,'ARCHIVE_Control Tower'!$B$46/12*I8,0) -> 12500 | J28: =IF(J6>=3,'ARCHIVE_Control Tower'!$B$46/12*J8,0) -> 12500 | K28: =IF(K6>=3,'ARCHIVE_Control Tower'!$B$46/12*K8,0) -> 12500 | ... AM28: =IF(AM6>=3,'ARCHIVE_Control Tower'!$B$46/12*AM8,0) -> 13261.25 | AN28: =SUM(D28:O28) -> 125000 | AO28: =SUM(P28:AA28) -> 154500 | AP28: =SUM(AB28:AM28) -> 159135
A29: Dana Davenport — Clinical Admin (FT) | B29: 4000-0-C-0 | C29: M2 | D29: =IF(D6>=2,'ARCHIVE_Control Tower'!$B$44/12*D8,0) -> 0 | E29: =IF(E6>=2,'ARCHIVE_Control Tower'!$B$44/12*E8,0) -> 10000 | F29: =IF(F6>=2,'ARCHIVE_Control Tower'!$B$44/12*F8,0) -> 10000 | G29: =IF(G6>=2,'ARCHIVE_Control Tower'!$B$44/12*G8,0) -> 10000 | H29: =IF(H6>=2,'ARCHIVE_Control Tower'!$B$44/12*H8,0) -> 10000 | I29: =IF(I6>=2,'ARCHIVE_Control Tower'!$B$44/12*I8,0) -> 10000 | J29: =IF(J6>=2,'ARCHIVE_Control Tower'!$B$44/12*J8,0) -> 10000 | K29: =IF(K6>=2,'ARCHIVE_Control Tower'!$B$44/12*K8,0) -> 10000 | ... AM29: =IF(AM6>=2,'ARCHIVE_Control Tower'!$B$44/12*AM8,0) -> 10609 | AN29: =SUM(D29:O29) -> 110000 | AO29: =SUM(P29:AA29) -> 123600 | AP29: =SUM(AB29:AM29) -> 127308
A30: Subtotal — Indirect Wages | D30: =SUM(D26:D29) -> 10000 | E30: =SUM(E26:E29) -> 24166.667 | F30: =SUM(F26:F29) -> 36666.667 | G30: =SUM(G26:G29) -> 36666.667 | H30: =SUM(H26:H29) -> 36666.667 | I30: =SUM(I26:I29) -> 36666.667 | J30: =SUM(J26:J29) -> 36666.667 | K30: =SUM(K26:K29) -> 36666.667 | ... AM30: =SUM(AM26:AM29) -> 38899.667 | AN30: =SUM(D30:O30) -> 400833.33 | AO30: =SUM(P30:AA30) -> 453200 | AP30: =SUM(AB30:AM30) -> 466796
A31: CONTRACT LABOR (no employer burden)
A32: Silas — PRN Admin retainer | B32: 4020-0-A-0 | C32: M1-2 | D32: =IF(AND(D6>=1,D6<=2),'ARCHIVE_Control Tower'!$B$35,0) -> 2500 | E32: =IF(AND(E6>=1,E6<=2),'ARCHIVE_Control Tower'!$B$35,0) -> 2500 | F32: =IF(AND(F6>=1,F6<=2),'ARCHIVE_Control Tower'!$B$35,0) -> 0 | G32: =IF(AND(G6>=1,G6<=2),'ARCHIVE_Control Tower'!$B$35,0) -> 0 | H32: =IF(AND(H6>=1,H6<=2),'ARCHIVE_Control Tower'!$B$35,0) -> 0 | I32: =IF(AND(I6>=1,I6<=2),'ARCHIVE_Control Tower'!$B$35,0) -> 0 | J32: =IF(AND(J6>=1,J6<=2),'ARCHIVE_Control Tower'!$B$35,0) -> 0 | K32: =IF(AND(K6>=1,K6<=2),'ARCHIVE_Control Tower'!$B$35,0) -> 0 | ... AM32: =IF(AND(AM6>=1,AM6<=2),'ARCHIVE_Control Tower'!$B$35,0) -> 0 | AN32: =SUM(D32:O32) -> 5000 | AO32: =SUM(P32:AA32) -> 0 | AP32: =SUM(AB32:AM32) -> 0
A33: Dana — PRN Clinical contract | B33: 4020-0-C-0 | C33: M1 | D33: =IF(D6=1,'ARCHIVE_Control Tower'!$B$36,0) -> 1500 | E33: =IF(E6=1,'ARCHIVE_Control Tower'!$B$36,0) -> 0 | F33: =IF(F6=1,'ARCHIVE_Control Tower'!$B$36,0) -> 0 | G33: =IF(G6=1,'ARCHIVE_Control Tower'!$B$36,0) -> 0 | H33: =IF(H6=1,'ARCHIVE_Control Tower'!$B$36,0) -> 0 | I33: =IF(I6=1,'ARCHIVE_Control Tower'!$B$36,0) -> 0 | J33: =IF(J6=1,'ARCHIVE_Control Tower'!$B$36,0) -> 0 | K33: =IF(K6=1,'ARCHIVE_Control Tower'!$B$36,0) -> 0 | ... AM33: =IF(AM6=1,'ARCHIVE_Control Tower'!$B$36,0) -> 0 | AN33: =SUM(D33:O33) -> 1500 | AO33: =SUM(P33:AA33) -> 0 | AP33: =SUM(AB33:AM33) -> 0
A34: Medical Director | B34: 4020-R-6-M | C34: M1 | D34: ='ARCHIVE_Control Tower'!$B$34 -> 4000 | E34: ='ARCHIVE_Control Tower'!$B$34 -> 4000 | F34: ='ARCHIVE_Control Tower'!$B$34 -> 4000 | G34: ='ARCHIVE_Control Tower'!$B$34 -> 4000 | H34: ='ARCHIVE_Control Tower'!$B$34 -> 4000 | I34: ='ARCHIVE_Control Tower'!$B$34 -> 4000 | J34: ='ARCHIVE_Control Tower'!$B$34 -> 4000 | K34: ='ARCHIVE_Control Tower'!$B$34 -> 4000 | ... AM34: ='ARCHIVE_Control Tower'!$B$34 -> 4000 | AN34: =SUM(D34:O34) -> 48000 | AO34: =SUM(P34:AA34) -> 48000 | AP34: =SUM(AB34:AM34) -> 48000
A35: Subtotal — Contract Labor | D35: =SUM(D32:D34) -> 8000 | E35: =SUM(E32:E34) -> 6500 | F35: =SUM(F32:F34) -> 4000 | G35: =SUM(G32:G34) -> 4000 | H35: =SUM(H32:H34) -> 4000 | I35: =SUM(I32:I34) -> 4000 | J35: =SUM(J32:J34) -> 4000 | K35: =SUM(K32:K34) -> 4000 | ... AM35: =SUM(AM32:AM34) -> 4000 | AN35: =SUM(D35:O35) -> 54500 | AO35: =SUM(P35:AA35) -> 48000 | AP35: =SUM(AB35:AM35) -> 48000
A36: PAYROLL BURDEN (on W-2 wages: salaried + PRN visit)
A37: W-2 Wage Base (Direct salaried + PRN + Indirect) | D37: =D18+D24+D30 -> 27290.042 | E37: =E18+E24+E30 -> 48357.792 | F37: =F18+F24+F30 -> 61048.25 | G37: =G18+G24+G30 -> 61490.75 | H37: =H18+H24+H30 -> 61933.25 | I37: =I18+I24+I30 -> 62154.5 | J37: =J18+J24+J30 -> 66442.042 | K37: =K18+K24+K30 -> 66663.292 | ... AM37: =AM18+AM24+AM30 -> 99536.646
A38: Employer FICA | B38: 4130-0-Z-0 | D38: =D37*'ARCHIVE_Control Tower'!$B$5 -> 2087.6882 | E38: =E37*'ARCHIVE_Control Tower'!$B$5 -> 3699.3711 | F38: =F37*'ARCHIVE_Control Tower'!$B$5 -> 4670.1911 | G38: =G37*'ARCHIVE_Control Tower'!$B$5 -> 4704.0424 | H38: =H37*'ARCHIVE_Control Tower'!$B$5 -> 4737.8936 | I38: =I37*'ARCHIVE_Control Tower'!$B$5 -> 4754.8192 | J38: =J37*'ARCHIVE_Control Tower'!$B$5 -> 5082.8162 | K38: =K37*'ARCHIVE_Control Tower'!$B$5 -> 5099.7418 | ... AM38: =AM37*'ARCHIVE_Control Tower'!$B$5 -> 7614.5534 | AN38: =SUM(D38:O38) -> 56512.431 | AO38: =SUM(P38:AA38) -> 77821.768 | AP38: =SUM(AB38:AM38) -> 90443.732
A39: FUTA/SUTA Unemployment | B39: 4131-0-Z-0 | D39: =D37*'ARCHIVE_Control Tower'!$B$6 -> 504.86577 | E39: =E37*'ARCHIVE_Control Tower'!$B$6 -> 894.61915 | F39: =F37*'ARCHIVE_Control Tower'!$B$6 -> 1129.3926 | G39: =G37*'ARCHIVE_Control Tower'!$B$6 -> 1137.5789 | H39: =H37*'ARCHIVE_Control Tower'!$B$6 -> 1145.7651 | I39: =I37*'ARCHIVE_Control Tower'!$B$6 -> 1149.8582 | J39: =J37*'ARCHIVE_Control Tower'!$B$6 -> 1229.1778 | K39: =K37*'ARCHIVE_Control Tower'!$B$6 -> 1233.2709 | ... AM39: =AM37*'ARCHIVE_Control Tower'!$B$6 -> 1841.428 | AN39: =SUM(D39:O39) -> 13666.405 | AO39: =SUM(P39:AA39) -> 18819.643 | AP39: =SUM(AB39:AM39) -> 21872.014
A40: Workers' Compensation | B40: 4135-0-Z-0 | D40: =D37*'ARCHIVE_Control Tower'!$B$7 -> 818.70125 | E40: =E37*'ARCHIVE_Control Tower'!$B$7 -> 1450.7338 | F40: =F37*'ARCHIVE_Control Tower'!$B$7 -> 1831.4475 | G40: =G37*'ARCHIVE_Control Tower'!$B$7 -> 1844.7225 | H40: =H37*'ARCHIVE_Control Tower'!$B$7 -> 1857.9975 | I40: =I37*'ARCHIVE_Control Tower'!$B$7 -> 1864.635 | J40: =J37*'ARCHIVE_Control Tower'!$B$7 -> 1993.2613 | K40: =K37*'ARCHIVE_Control Tower'!$B$7 -> 1999.8988 | ... AM40: =AM37*'ARCHIVE_Control Tower'!$B$7 -> 2986.0994 | AN40: =SUM(D40:O40) -> 22161.737 | AO40: =SUM(P40:AA40) -> 30518.34 | AP40: =SUM(AB40:AM40) -> 35468.13
A41: Health Insurance | B41: 4110-0-Z-0 | D41: =('ARCHIVE_Control Tower'!$B$8)*(IF(D6>=1,3,0)+IF(D6>=2,3,0)+IF(D6>=3,2,0)+MAX(0,D9-((IF(D6>=1,1,0))+(IF(D6>=2,1,0))))+MAX(0,D10-((IF(D6>=1,1,0))+(IF(D6>=3,1,0))))) -> 2000 | E41: =('ARCHIVE_Control Tower'!$B$8)*(IF(E6>=1,3,0)+IF(E6>=2,3,0)+IF(E6>=3,2,0)+MAX(0,E9-((IF(E6>=1,1,0))+(IF(E6>=2,1,0))))+MAX(0,E10-((IF(E6>=1,1,0))+(IF(E6>=3,1,0))))) -> 3500 | F41: =('ARCHIVE_Control Tower'!$B$8)*(IF(F6>=1,3,0)+IF(F6>=2,3,0)+IF(F6>=3,2,0)+MAX(0,F9-((IF(F6>=1,1,0))+(IF(F6>=2,1,0))))+MAX(0,F10-((IF(F6>=1,1,0))+(IF(F6>=3,1,0))))) -> 4000 | G41: =('ARCHIVE_Control Tower'!$B$8)*(IF(G6>=1,3,0)+IF(G6>=2,3,0)+IF(G6>=3,2,0)+MAX(0,G9-((IF(G6>=1,1,0))+(IF(G6>=2,1,0))))+MAX(0,G10-((IF(G6>=1,1,0))+(IF(G6>=3,1,0))))) -> 4000 | H41: =('ARCHIVE_Control Tower'!$B$8)*(IF(H6>=1,3,0)+IF(H6>=2,3,0)+IF(H6>=3,2,0)+MAX(0,H9-((IF(H6>=1,1,0))+(IF(H6>=2,1,0))))+MAX(0,H10-((IF(H6>=1,1,0))+(IF(H6>=3,1,0))))) -> 4000 | I41: =('ARCHIVE_Control Tower'!$B$8)*(IF(I6>=1,3,0)+IF(I6>=2,3,0)+IF(I6>=3,2,0)+MAX(0,I9-((IF(I6>=1,1,0))+(IF(I6>=2,1,0))))+MAX(0,I10-((IF(I6>=1,1,0))+(IF(I6>=3,1,0))))) -> 4000 | J41: =('ARCHIVE_Control Tower'!$B$8)*(IF(J6>=1,3,0)+IF(J6>=2,3,0)+IF(J6>=3,2,0)+MAX(0,J9-((IF(J6>=1,1,0))+(IF(J6>=2,1,0))))+MAX(0,J10-((IF(J6>=1,1,0))+(IF(J6>=3,1,0))))) -> 4500 | K41: =('ARCHIVE_Control Tower'!$B$8)*(IF(K6>=1,3,0)+IF(K6>=2,3,0)+IF(K6>=3,2,0)+MAX(0,K9-((IF(K6>=1,1,0))+(IF(K6>=2,1,0))))+MAX(0,K10-((IF(K6>=1,1,0))+(IF(K6>=3,1,0))))) -> 4500 | ... AM41: =('ARCHIVE_Control Tower'!$B$8)*(IF(AM6>=1,3,0)+IF(AM6>=2,3,0)+IF(AM6>=3,2,0)+MAX(0,AM9-((IF(AM6>=1,1,0))+(IF(AM6>=2,1,0))))+MAX(0,AM10-((IF(AM6>=1,1,0))+(IF(AM6>=3,1,0))))) -> 6500 | AN41: =SUM(D41:O41) -> 49500 | AO41: =SUM(P41:AA41) -> 68000 | AP41: =SUM(AB41:AM41) -> 78000
A42: Subtotal — Payroll Burden | D42: =SUM(D38:D41) -> 5411.2552 | E42: =SUM(E38:E41) -> 9544.724 | F42: =SUM(F38:F41) -> 11631.031 | G42: =SUM(G38:G41) -> 11686.344 | H42: =SUM(H38:H41) -> 11741.656 | I42: =SUM(I38:I41) -> 11769.312 | J42: =SUM(J38:J41) -> 12805.255 | K42: =SUM(K38:K41) -> 12832.911 | ... AM42: =SUM(AM38:AM41) -> 18942.081 | AN42: =SUM(D42:O42) -> 141840.57 | AO42: =SUM(P42:AA42) -> 195159.75 | AP42: =SUM(AB42:AM42) -> 225783.88
A43: TOTAL FULLY-LOADED LABOR (wages + burden; mileage now in OpEx)
A44: TOTAL LABOR COST | D44: =D18+D24+D30+D35+D42 -> 40701.297 | E44: =E18+E24+E30+E35+E42 -> 64402.516 | F44: =F18+F24+F30+F35+F42 -> 76679.281 | G44: =G18+G24+G30+G35+G42 -> 77177.094 | H44: =H18+H24+H30+H35+H42 -> 77674.906 | I44: =I18+I24+I30+I35+I42 -> 77923.812 | J44: =J18+J24+J30+J35+J42 -> 83247.297 | K44: =K18+K24+K30+K35+K42 -> 83496.203 | ... AM44: =AM18+AM24+AM30+AM35+AM42 -> 122478.73 | AN44: =SUM(D44:O44) -> 935065.16 | AO44: =SUM(P44:AA44) -> 1260437.8 | AP44: =SUM(AB44:AM44) -> 1456054.9
A46: VALIDATION KPIs
A47: Direct Care LABOR (wages + PRN, ex-burden) | D47: =D18+D24 -> 17290.042 | E47: =E18+E24 -> 24191.125 | F47: =F18+F24 -> 24381.583 | G47: =G18+G24 -> 24824.083 | H47: =H18+H24 -> 25266.583 | I47: =I18+I24 -> 25487.833 | J47: =J18+J24 -> 29775.375 | K47: =K18+K24 -> 29996.625 | ... AM47: =AM18+AM24 -> 60636.98
A48: Direct Care LABOR $/Patient Day (labor only; full $90-120 benchmark adds Rx/DME/supplies) | D48: =IF(D7=0,0,D47/(D7*'ARCHIVE_Control Tower'!$B$21)) -> 37.916758 | E48: =IF(E7=0,0,E47/(E7*'ARCHIVE_Control Tower'!$B$21)) -> 46.809452 | F48: =IF(F7=0,0,F47/(F7*'ARCHIVE_Control Tower'!$B$21)) -> 44.556987 | G48: =IF(G7=0,0,G47/(G7*'ARCHIVE_Control Tower'!$B$21)) -> 40.829084 | H48: =IF(H7=0,0,H47/(H7*'ARCHIVE_Control Tower'!$B$21)) -> 37.778982 | I48: =IF(I7=0,0,I47/(I7*'ARCHIVE_Control Tower'!$B$21)) -> 36.452851 | J48: =IF(J7=0,0,J47/(J7*'ARCHIVE_Control Tower'!$B$21)) -> 39.178125 | K48: =IF(K7=0,0,K47/(K7*'ARCHIVE_Control Tower'!$B$21)) -> 37.951196 | ... AM48: =IF(AM7=0,0,AM47/(AM7*'ARCHIVE_Control Tower'!$B$21)) -> 33.243958

Sheet ARCHIVE_Operating Budget
A1: OPERATING BUDGET
A2: 36-Month GL Detail
B3: GL Code | C3: Year 1 | O3: Year 2 | AA3: Year 3 | AM3: Annual | AP3: % Rev
C4: M1 | D4: M2 | E4: M3 | F4: M4 | G4: M5 | H4: M6 | I4: M7 | J4: M8 | K4: M9 | L4: M10 | M4: M11 | N4: M12 | O4: M13 | P4: M14 | Q4: M15 | R4: M16 | S4: M17 | T4: M18 | U4: M19 | V4: M20 | W4: M21 | X4: M22 | Y4: M23 | Z4: M24 | AA4: M25 | AB4: M26 | AC4: M27 | AD4: M28 | AE4: M29 | AF4: M30 | AG4: M31 | AH4: M32 | AI4: M33 | AJ4: M34 | AK4: M35 | AL4: M36 | AM4: Year 1 | AN4: Year 2 | AO4: Year 3 | AP4: (Y3)
A5: REVENUE
A6: Avg Daily Census | C6: ='ARCHIVE_Revenue Model'!C18 -> 15 | D6: ='ARCHIVE_Revenue Model'!D18 -> 17 | E6: ='ARCHIVE_Revenue Model'!E18 -> 18 | F6: ='ARCHIVE_Revenue Model'!F18 -> 20 | G6: ='ARCHIVE_Revenue Model'!G18 -> 22 | H6: ='ARCHIVE_Revenue Model'!H18 -> 23 | I6: ='ARCHIVE_Revenue Model'!I18 -> 25 | J6: ='ARCHIVE_Revenue Model'!J18 -> 26 | ... AL6: ='ARCHIVE_Revenue Model'!AL18 -> 60 | AM6: =AVERAGE(C6:N6) -> 24 | AN6: =AVERAGE(O6:Z6) -> 42.25 | AO6: =AVERAGE(AA6:AL6) -> 55.416667
A7: Total Patient Days | C7: ='ARCHIVE_Revenue Model'!C20 -> 456 | D7: ='ARCHIVE_Revenue Model'!D20 -> 516.8 | E7: ='ARCHIVE_Revenue Model'!E20 -> 547.2 | F7: ='ARCHIVE_Revenue Model'!F20 -> 608 | G7: ='ARCHIVE_Revenue Model'!G20 -> 668.8 | H7: ='ARCHIVE_Revenue Model'!H20 -> 699.2 | I7: ='ARCHIVE_Revenue Model'!I20 -> 760 | J7: ='ARCHIVE_Revenue Model'!J20 -> 790.4 | ... AO7: ='ARCHIVE_Revenue Model'!AO20 -> 20216
A8: Gross Patient Revenue | B8: 3000 | C8: ='ARCHIVE_Revenue Model'!C21 -> 84013.939 | D8: ='ARCHIVE_Revenue Model'!D21 -> 95215.798 | E8: ='ARCHIVE_Revenue Model'!E21 -> 100816.73 | F8: ='ARCHIVE_Revenue Model'!F21 -> 112018.59 | G8: ='ARCHIVE_Revenue Model'!G21 -> 123220.44 | H8: ='ARCHIVE_Revenue Model'!H21 -> 128821.37 | I8: ='ARCHIVE_Revenue Model'!I21 -> 140023.23 | J8: ='ARCHIVE_Revenue Model'!J21 -> 145624.16 | ... AO8: ='ARCHIVE_Revenue Model'!AO21 -> 3724618 | AP8: =IF(AO$10=0,0,AO8/AO$10) -> 1.0152284
A9: Billing / Collection Fee (-1.5%) | B9: 3900 | C9: ='ARCHIVE_Revenue Model'!C22 -> -1260.2091 | D9: ='ARCHIVE_Revenue Model'!D22 -> -1428.237 | E9: ='ARCHIVE_Revenue Model'!E22 -> -1512.2509 | F9: ='ARCHIVE_Revenue Model'!F22 -> -1680.2788 | G9: ='ARCHIVE_Revenue Model'!G22 -> -1848.3067 | H9: ='ARCHIVE_Revenue Model'!H22 -> -1932.3206 | I9: ='ARCHIVE_Revenue Model'!I22 -> -2100.3485 | J9: ='ARCHIVE_Revenue Model'!J22 -> -2184.3624 | ... AO9: ='ARCHIVE_Revenue Model'!AO22 -> -55869.27 | AP9: =IF(AO$10=0,0,AO9/AO$10) -> -0.015228426
A10: Net Patient Revenue | C10: ='ARCHIVE_Revenue Model'!C23 -> 82753.73 | D10: ='ARCHIVE_Revenue Model'!D23 -> 93787.561 | E10: ='ARCHIVE_Revenue Model'!E23 -> 99304.476 | F10: ='ARCHIVE_Revenue Model'!F23 -> 110338.31 | G10: ='ARCHIVE_Revenue Model'!G23 -> 121372.14 | H10: ='ARCHIVE_Revenue Model'!H23 -> 126889.05 | I10: ='ARCHIVE_Revenue Model'!I23 -> 137922.88 | J10: ='ARCHIVE_Revenue Model'!J23 -> 143439.8 | ... AO10: ='ARCHIVE_Revenue Model'!AO23 -> 3668748.7 | AP10: =IF(AO$10=0,0,AO10/AO$10) -> 1
A12: COST OF GOODS SOLD
A13: DIRECT LABOR
A14: 4000R61 Wages-RN | B14: 4000R61 | C14: ='ARCHIVE_Staffing Summary'!D12+'ARCHIVE_Staffing Summary'!D13+'ARCHIVE_Staffing Summary'!D14 -> 6250.4167 | D14: ='ARCHIVE_Staffing Summary'!E12+'ARCHIVE_Staffing Summary'!E13+'ARCHIVE_Staffing Summary'!E14 -> 12709 | E14: ='ARCHIVE_Staffing Summary'!F12+'ARCHIVE_Staffing Summary'!F13+'ARCHIVE_Staffing Summary'!F14 -> 12709 | F14: ='ARCHIVE_Staffing Summary'!G12+'ARCHIVE_Staffing Summary'!G13+'ARCHIVE_Staffing Summary'!G14 -> 12709 | G14: ='ARCHIVE_Staffing Summary'!H12+'ARCHIVE_Staffing Summary'!H13+'ARCHIVE_Staffing Summary'!H14 -> 12709 | H14: ='ARCHIVE_Staffing Summary'!I12+'ARCHIVE_Staffing Summary'!I13+'ARCHIVE_Staffing Summary'!I14 -> 12709 | I14: ='ARCHIVE_Staffing Summary'!J12+'ARCHIVE_Staffing Summary'!J13+'ARCHIVE_Staffing Summary'!J14 -> 12709 | J14: ='ARCHIVE_Staffing Summary'!K12+'ARCHIVE_Staffing Summary'!K13+'ARCHIVE_Staffing Summary'!K14 -> 12709 | ... AO14: ='ARCHIVE_Staffing Summary'!AP12+'ARCHIVE_Staffing Summary'!AP13+'ARCHIVE_Staffing Summary'!AP14 -> 323591.47 | AP14: =IF(AO$10=0,0,AO14/AO$10) -> 0.088202137
A15: 4000R62 Wages-LVN | B15: 4000R62 | C15: ='ARCHIVE_Staffing Summary'!D20 -> 900 | D15: ='ARCHIVE_Staffing Summary'!E20 -> 1020 | E15: ='ARCHIVE_Staffing Summary'!F20 -> 1080 | F15: ='ARCHIVE_Staffing Summary'!G20 -> 1200 | G15: ='ARCHIVE_Staffing Summary'!H20 -> 1320 | H15: ='ARCHIVE_Staffing Summary'!I20 -> 1380 | I15: ='ARCHIVE_Staffing Summary'!J20 -> 1500 | J15: ='ARCHIVE_Staffing Summary'!K20 -> 1560 | ... AO15: ='ARCHIVE_Staffing Summary'!AP20 -> 39900 | AP15: =IF(AO$10=0,0,AO15/AO$10) -> 0.010875643
A16: 4000R65 Wages-Aide | B16: 4000R65 | C16: ='ARCHIVE_Staffing Summary'!D15+'ARCHIVE_Staffing Summary'!D16+'ARCHIVE_Staffing Summary'!D17 -> 7720.875 | D16: ='ARCHIVE_Staffing Summary'!E15+'ARCHIVE_Staffing Summary'!E16+'ARCHIVE_Staffing Summary'!E17 -> 7720.875 | E16: ='ARCHIVE_Staffing Summary'!F15+'ARCHIVE_Staffing Summary'!F16+'ARCHIVE_Staffing Summary'!F17 -> 7690.0833 | F16: ='ARCHIVE_Staffing Summary'!G15+'ARCHIVE_Staffing Summary'!G16+'ARCHIVE_Staffing Summary'!G17 -> 7690.0833 | G16: ='ARCHIVE_Staffing Summary'!H15+'ARCHIVE_Staffing Summary'!H16+'ARCHIVE_Staffing Summary'!H17 -> 7690.0833 | H16: ='ARCHIVE_Staffing Summary'!I15+'ARCHIVE_Staffing Summary'!I16+'ARCHIVE_Staffing Summary'!I17 -> 7690.0833 | I16: ='ARCHIVE_Staffing Summary'!J15+'ARCHIVE_Staffing Summary'!J16+'ARCHIVE_Staffing Summary'!J17 -> 11535.125 | J16: ='ARCHIVE_Staffing Summary'!K15+'ARCHIVE_Staffing Summary'!K16+'ARCHIVE_Staffing Summary'!K17 -> 11535.125 | ... AO16: ='ARCHIVE_Staffing Summary'!AP15+'ARCHIVE_Staffing Summary'!AP16+'ARCHIVE_Staffing Summary'!AP17 -> 244752.28 | AP16: =IF(AO$10=0,0,AO16/AO$10) -> 0.066712741
A17: 4000R66 Wages-MSW | B17: 4000R66 | C17: ='ARCHIVE_Staffing Summary'!D22 -> 1125 | D17: ='ARCHIVE_Staffing Summary'!E22 -> 1275 | E17: ='ARCHIVE_Staffing Summary'!F22 -> 1350 | F17: ='ARCHIVE_Staffing Summary'!G22 -> 1500 | G17: ='ARCHIVE_Staffing Summary'!H22 -> 1650 | H17: ='ARCHIVE_Staffing Summary'!I22 -> 1725 | I17: ='ARCHIVE_Staffing Summary'!J22 -> 1875 | J17: ='ARCHIVE_Staffing Summary'!K22 -> 1950 | ... AO17: ='ARCHIVE_Staffing Summary'!AP22 -> 49875 | AP17: =IF(AO$10=0,0,AO17/AO$10) -> 0.013594553
A18: 4000R67 Wages-SC | B18: 4000R67 | C18: ='ARCHIVE_Staffing Summary'!D21 -> 843.75 | D18: ='ARCHIVE_Staffing Summary'!E21 -> 956.25 | E18: ='ARCHIVE_Staffing Summary'!F21 -> 1012.5 | F18: ='ARCHIVE_Staffing Summary'!G21 -> 1125 | G18: ='ARCHIVE_Staffing Summary'!H21 -> 1237.5 | H18: ='ARCHIVE_Staffing Summary'!I21 -> 1293.75 | I18: ='ARCHIVE_Staffing Summary'!J21 -> 1406.25 | J18: ='ARCHIVE_Staffing Summary'!K21 -> 1462.5 | ... AO18: ='ARCHIVE_Staffing Summary'!AP21 -> 37406.25 | AP18: =IF(AO$10=0,0,AO18/AO$10) -> 0.010195915
A19: 4000R6N Wages-NP | B19: 4000R6N | C19: ='ARCHIVE_Staffing Summary'!D23 -> 450 | D19: ='ARCHIVE_Staffing Summary'!E23 -> 510 | E19: ='ARCHIVE_Staffing Summary'!F23 -> 540 | F19: ='ARCHIVE_Staffing Summary'!G23 -> 600 | G19: ='ARCHIVE_Staffing Summary'!H23 -> 660 | H19: ='ARCHIVE_Staffing Summary'!I23 -> 690 | I19: ='ARCHIVE_Staffing Summary'!J23 -> 750 | J19: ='ARCHIVE_Staffing Summary'!K23 -> 780 | ... AO19: ='ARCHIVE_Staffing Summary'!AP23 -> 19950 | AP19: =IF(AO$10=0,0,AO19/AO$10) -> 0.0054378213
A20: Total Direct Labor | C20: =SUM(C14:C19) -> 17290.042 | D20: =SUM(D14:D19) -> 24191.125 | E20: =SUM(E14:E19) -> 24381.583 | F20: =SUM(F14:F19) -> 24824.083 | G20: =SUM(G14:G19) -> 25266.583 | H20: =SUM(H14:H19) -> 25487.833 | I20: =SUM(I14:I19) -> 29775.375 | J20: =SUM(J14:J19) -> 29996.625 | ... AO20: =SUM(AO14:AO19) -> 715475.01 | AP20: =IF(AO$10=0,0,AO20/AO$10) -> 0.19501881
A21: DIRECT BENEFITS
A22: 41300 FICA/SS (7.65%) | B22: 41300 | C22: =C20*'ARCHIVE_Control Tower'!$B$5 -> 1322.6882 | D22: =D20*'ARCHIVE_Control Tower'!$B$5 -> 1850.6211 | E22: =E20*'ARCHIVE_Control Tower'!$B$5 -> 1865.1911 | F22: =F20*'ARCHIVE_Control Tower'!$B$5 -> 1899.0424 | G22: =G20*'ARCHIVE_Control Tower'!$B$5 -> 1932.8936 | H22: =H20*'ARCHIVE_Control Tower'!$B$5 -> 1949.8193 | I22: =I20*'ARCHIVE_Control Tower'!$B$5 -> 2277.8162 | J22: =J20*'ARCHIVE_Control Tower'!$B$5 -> 2294.7418 | ... AO22: =AO20*'ARCHIVE_Control Tower'!$B$5 -> 54733.838 | AP22: =IF(AO$10=0,0,AO22/AO$10) -> 0.014918939
A23: 41300 FUTA/SUTA (1.85%) | B23: 41300 | C23: =C20*'ARCHIVE_Control Tower'!$B$6 -> 319.86577 | D23: =D20*'ARCHIVE_Control Tower'!$B$6 -> 447.53581 | E23: =E20*'ARCHIVE_Control Tower'!$B$6 -> 451.05929 | F23: =F20*'ARCHIVE_Control Tower'!$B$6 -> 459.24554 | G23: =G20*'ARCHIVE_Control Tower'!$B$6 -> 467.43179 | H23: =H20*'ARCHIVE_Control Tower'!$B$6 -> 471.52492 | I23: =I20*'ARCHIVE_Control Tower'!$B$6 -> 550.84444 | J23: =J20*'ARCHIVE_Control Tower'!$B$6 -> 554.93756 | ... AO23: =AO20*'ARCHIVE_Control Tower'!$B$6 -> 13236.288 | AP23: =IF(AO$10=0,0,AO23/AO$10) -> 0.003607848
A24: 41600 Workers Compensation (3%) | B24: 41600 | C24: =C20*'ARCHIVE_Control Tower'!$B$7 -> 518.70125 | D24: =D20*'ARCHIVE_Control Tower'!$B$7 -> 725.73375 | E24: =E20*'ARCHIVE_Control Tower'!$B$7 -> 731.4475 | F24: =F20*'ARCHIVE_Control Tower'!$B$7 -> 744.7225 | G24: =G20*'ARCHIVE_Control Tower'!$B$7 -> 757.9975 | H24: =H20*'ARCHIVE_Control Tower'!$B$7 -> 764.635 | I24: =I20*'ARCHIVE_Control Tower'!$B$7 -> 893.26125 | J24: =J20*'ARCHIVE_Control Tower'!$B$7 -> 899.89875 | ... AO24: =AO20*'ARCHIVE_Control Tower'!$B$7 -> 21464.25 | AP24: =IF(AO$10=0,0,AO24/AO$10) -> 0.0058505643
A25: 41100 Health Insurance | B25: 41100 | C25: ='ARCHIVE_Staffing Summary'!D41*(C20/('ARCHIVE_Staffing Summary'!D18+'ARCHIVE_Staffing Summary'!D24+'ARCHIVE_Staffing Summary'!D30)) -> 1267.1319 | D25: ='ARCHIVE_Staffing Summary'!E41*(D20/('ARCHIVE_Staffing Summary'!E18+'ARCHIVE_Staffing Summary'!E24+'ARCHIVE_Staffing Summary'!E30)) -> 1750.8851 | E25: ='ARCHIVE_Staffing Summary'!F41*(E20/('ARCHIVE_Staffing Summary'!F18+'ARCHIVE_Staffing Summary'!F24+'ARCHIVE_Staffing Summary'!F30)) -> 1597.5287 | F25: ='ARCHIVE_Staffing Summary'!G41*(F20/('ARCHIVE_Staffing Summary'!G18+'ARCHIVE_Staffing Summary'!G24+'ARCHIVE_Staffing Summary'!G30)) -> 1614.8174 | G25: ='ARCHIVE_Staffing Summary'!H41*(G20/('ARCHIVE_Staffing Summary'!H18+'ARCHIVE_Staffing Summary'!H24+'ARCHIVE_Staffing Summary'!H30)) -> 1631.859 | H25: ='ARCHIVE_Staffing Summary'!I41*(H20/('ARCHIVE_Staffing Summary'!I18+'ARCHIVE_Staffing Summary'!I24+'ARCHIVE_Staffing Summary'!I30)) -> 1640.2889 | I25: ='ARCHIVE_Staffing Summary'!J41*(I20/('ARCHIVE_Staffing Summary'!J18+'ARCHIVE_Staffing Summary'!J24+'ARCHIVE_Staffing Summary'!J30)) -> 2016.6326 | J25: ='ARCHIVE_Staffing Summary'!K41*(J20/('ARCHIVE_Staffing Summary'!K18+'ARCHIVE_Staffing Summary'!K24+'ARCHIVE_Staffing Summary'!K30)) -> 2024.8747 | ... AO25: ='ARCHIVE_Staffing Summary'!AP41*(AO20/('ARCHIVE_Staffing Summary'!AP18+'ARCHIVE_Staffing Summary'!AP24+'ARCHIVE_Staffing Summary'!AP30)) -> 47203.264 | AP25: =IF(AO$10=0,0,AO25/AO$10) -> 0.012866312
A26: Total Direct Benefits | C26: =SUM(C22:C25) -> 3428.3871 | D26: =SUM(D22:D25) -> 4774.7757 | E26: =SUM(E22:E25) -> 4645.2266 | F26: =SUM(F22:F25) -> 4717.8278 | G26: =SUM(G22:G25) -> 4790.1819 | H26: =SUM(H22:H25) -> 4826.268 | I26: =SUM(I22:I25) -> 5738.5545 | J26: =SUM(J22:J25) -> 5774.4528 | ... AO26: =SUM(AO22:AO25) -> 136637.64 | AP26: =IF(AO$10=0,0,AO26/AO$10) -> 0.037243663
A27: PATIENT-RELATED EXPENSES
A28: 5050 Durable Medical Equipment | B28: 5050 | C28: ='ARCHIVE_Revenue Model'!C20*'ARCHIVE_Control Tower'!$B$68 -> 4104 | D28: ='ARCHIVE_Revenue Model'!D20*'ARCHIVE_Control Tower'!$B$68 -> 4651.2 | E28: ='ARCHIVE_Revenue Model'!E20*'ARCHIVE_Control Tower'!$B$68 -> 4924.8 | F28: ='ARCHIVE_Revenue Model'!F20*'ARCHIVE_Control Tower'!$B$68 -> 5472 | G28: ='ARCHIVE_Revenue Model'!G20*'ARCHIVE_Control Tower'!$B$68 -> 6019.2 | H28: ='ARCHIVE_Revenue Model'!H20*'ARCHIVE_Control Tower'!$B$68 -> 6292.8 | I28: ='ARCHIVE_Revenue Model'!I20*'ARCHIVE_Control Tower'!$B$68 -> 6840 | J28: ='ARCHIVE_Revenue Model'!J20*'ARCHIVE_Control Tower'!$B$68 -> 7113.6 | ... AO28: ='ARCHIVE_Revenue Model'!AO20*'ARCHIVE_Control Tower'!$B$68 -> 181944 | AP28: =IF(AO$10=0,0,AO28/AO$10) -> 0.049592931
A29: 5100 Medications | B29: 5100 | C29: ='ARCHIVE_Revenue Model'!C20*'ARCHIVE_Control Tower'!$B$69 -> 1596 | D29: ='ARCHIVE_Revenue Model'!D20*'ARCHIVE_Control Tower'!$B$69 -> 1808.8 | E29: ='ARCHIVE_Revenue Model'!E20*'ARCHIVE_Control Tower'!$B$69 -> 1915.2 | F29: ='ARCHIVE_Revenue Model'!F20*'ARCHIVE_Control Tower'!$B$69 -> 2128 | G29: ='ARCHIVE_Revenue Model'!G20*'ARCHIVE_Control Tower'!$B$69 -> 2340.8 | H29: ='ARCHIVE_Revenue Model'!H20*'ARCHIVE_Control Tower'!$B$69 -> 2447.2 | I29: ='ARCHIVE_Revenue Model'!I20*'ARCHIVE_Control Tower'!$B$69 -> 2660 | J29: ='ARCHIVE_Revenue Model'!J20*'ARCHIVE_Control Tower'!$B$69 -> 2766.4 | ... AO29: ='ARCHIVE_Revenue Model'!AO20*'ARCHIVE_Control Tower'!$B$69 -> 70756 | AP29: =IF(AO$10=0,0,AO29/AO$10) -> 0.01928614
A30: 5090 Medical Supplies | B30: 5090 | C30: ='ARCHIVE_Revenue Model'!C20*'ARCHIVE_Control Tower'!$B$70 -> 1368 | D30: ='ARCHIVE_Revenue Model'!D20*'ARCHIVE_Control Tower'!$B$70 -> 1550.4 | E30: ='ARCHIVE_Revenue Model'!E20*'ARCHIVE_Control Tower'!$B$70 -> 1641.6 | F30: ='ARCHIVE_Revenue Model'!F20*'ARCHIVE_Control Tower'!$B$70 -> 1824 | G30: ='ARCHIVE_Revenue Model'!G20*'ARCHIVE_Control Tower'!$B$70 -> 2006.4 | H30: ='ARCHIVE_Revenue Model'!H20*'ARCHIVE_Control Tower'!$B$70 -> 2097.6 | I30: ='ARCHIVE_Revenue Model'!I20*'ARCHIVE_Control Tower'!$B$70 -> 2280 | J30: ='ARCHIVE_Revenue Model'!J20*'ARCHIVE_Control Tower'!$B$70 -> 2371.2 | ... AO30: ='ARCHIVE_Revenue Model'!AO20*'ARCHIVE_Control Tower'!$B$70 -> 60648 | AP30: =IF(AO$10=0,0,AO30/AO$10) -> 0.016530977
A31: 5110 Mileage Reimbursement | B31: 5110 | C31: ='ARCHIVE_Revenue Model'!C23*'ARCHIVE_Control Tower'!$B$72 -> 1655.0746 | D31: ='ARCHIVE_Revenue Model'!D23*'ARCHIVE_Control Tower'!$B$72 -> 1875.7512 | E31: ='ARCHIVE_Revenue Model'!E23*'ARCHIVE_Control Tower'!$B$72 -> 1986.0895 | F31: ='ARCHIVE_Revenue Model'!F23*'ARCHIVE_Control Tower'!$B$72 -> 2206.7661 | G31: ='ARCHIVE_Revenue Model'!G23*'ARCHIVE_Control Tower'!$B$72 -> 2427.4428 | H31: ='ARCHIVE_Revenue Model'!H23*'ARCHIVE_Control Tower'!$B$72 -> 2537.7811 | I31: ='ARCHIVE_Revenue Model'!I23*'ARCHIVE_Control Tower'!$B$72 -> 2758.4577 | J31: ='ARCHIVE_Revenue Model'!J23*'ARCHIVE_Control Tower'!$B$72 -> 2868.796 | ... AO31: ='ARCHIVE_Revenue Model'!AO23*'ARCHIVE_Control Tower'!$B$72 -> 73374.974 | AP31: =IF(AO$10=0,0,AO31/AO$10) -> 0.02
A32: 6560 Continuing Education | B32: 6560 | C32: ='ARCHIVE_Revenue Model'!C20*'ARCHIVE_Control Tower'!$B$71 -> 456 | D32: ='ARCHIVE_Revenue Model'!D20*'ARCHIVE_Control Tower'!$B$71 -> 516.8 | E32: ='ARCHIVE_Revenue Model'!E20*'ARCHIVE_Control Tower'!$B$71 -> 547.2 | F32: ='ARCHIVE_Revenue Model'!F20*'ARCHIVE_Control Tower'!$B$71 -> 608 | G32: ='ARCHIVE_Revenue Model'!G20*'ARCHIVE_Control Tower'!$B$71 -> 668.8 | H32: ='ARCHIVE_Revenue Model'!H20*'ARCHIVE_Control Tower'!$B$71 -> 699.2 | I32: ='ARCHIVE_Revenue Model'!I20*'ARCHIVE_Control Tower'!$B$71 -> 760 | J32: ='ARCHIVE_Revenue Model'!J20*'ARCHIVE_Control Tower'!$B$71 -> 790.4 | ... AO32: ='ARCHIVE_Revenue Model'!AO20*'ARCHIVE_Control Tower'!$B$71 -> 20216 | AP32: =IF(AO$10=0,0,AO32/AO$10) -> 0.0055103256
A33: Total Patient-Related Expenses | C33: =SUM(C28:C32) -> 9179.0746 | D33: =SUM(D28:D32) -> 10402.951 | E33: =SUM(E28:E32) -> 11014.89 | F33: =SUM(F28:F32) -> 12238.766 | G33: =SUM(G28:G32) -> 13462.643 | H33: =SUM(H28:H32) -> 14074.581 | I33: =SUM(I28:I32) -> 15298.458 | J33: =SUM(J28:J32) -> 15910.396 | ... AO33: =SUM(AO28:AO32) -> 406938.97 | AP33: =IF(AO$10=0,0,AO33/AO$10) -> 0.11092037
A35: TOTAL COST OF GOODS SOLD | C35: =C20+C26+C33 -> 29897.503 | D35: =D20+D26+D33 -> 39368.852 | E35: =E20+E26+E33 -> 40041.7 | F35: =F20+F26+F33 -> 41780.677 | G35: =G20+G26+G33 -> 43519.408 | H35: =H20+H26+H33 -> 44388.682 | I35: =I20+I26+I33 -> 50812.387 | J35: =J20+J26+J33 -> 51681.474 | ... AO35: =AO20+AO26+AO33 -> 1259051.6 | AP35: =IF(AO$10=0,0,AO35/AO$10) -> 0.34318285
A36: GROSS PROFIT | C36: =C10-C35 -> 52856.227 | D36: =D10-D35 -> 54418.709 | E36: =E10-E35 -> 59262.777 | F36: =F10-F35 -> 68557.63 | G36: =G10-G35 -> 77852.73 | H36: =H10-H35 -> 82500.371 | I36: =I10-I35 -> 87110.496 | J36: =J10-J35 -> 91758.325 | ... AO36: =AO10-AO35 -> 2409697.1 | AP36: =IF(AO$10=0,0,AO36/AO$10) -> 0.65681715
A37: Gross Margin % | C37: =IF(C10=0,0,C36/C10) -> 0.63871715 | D37: =IF(D10=0,0,D36/D10) -> 0.58023376 | E37: =IF(E10=0,0,E36/E10) -> 0.5967785 | F37: =IF(F10=0,0,F36/F10) -> 0.62134024 | G37: =IF(G10=0,0,G36/G10) -> 0.64143823 | H37: =IF(H10=0,0,H36/H10) -> 0.65017721 | I37: =IF(I10=0,0,I36/I10) -> 0.63158842 | J37: =IF(J10=0,0,J36/J10) -> 0.6396992 | ... AO37: =IF(AO10=0,0,AO36/AO10) -> 0.65681715
A40: SELLING, GENERAL & ADMINISTRATIVE
A41: INDIRECT LABOR
A42: 40000M0 Wages-Marketing | B42: 40000M0 | C42: ='ARCHIVE_Staffing Summary'!D26 -> 10000 | D42: ='ARCHIVE_Staffing Summary'!E26 -> 10000 | E42: ='ARCHIVE_Staffing Summary'!F26 -> 10000 | F42: ='ARCHIVE_Staffing Summary'!G26 -> 10000 | G42: ='ARCHIVE_Staffing Summary'!H26 -> 10000 | H42: ='ARCHIVE_Staffing Summary'!I26 -> 10000 | I42: ='ARCHIVE_Staffing Summary'!J26 -> 10000 | J42: ='ARCHIVE_Staffing Summary'!K26 -> 10000 | ... AO42: ='ARCHIVE_Staffing Summary'!AP26 -> 127308 | AP42: =IF(AO$10=0,0,AO42/AO$10) -> 0.03470066
A43: 40000I0 Wages-Intake/Admit | B43: 40000I0 | C43: ='ARCHIVE_Staffing Summary'!D27 -> 0 | D43: ='ARCHIVE_Staffing Summary'!E27 -> 4166.6667 | E43: ='ARCHIVE_Staffing Summary'!F27 -> 4166.6667 | F43: ='ARCHIVE_Staffing Summary'!G27 -> 4166.6667 | G43: ='ARCHIVE_Staffing Summary'!H27 -> 4166.6667 | H43: ='ARCHIVE_Staffing Summary'!I27 -> 4166.6667 | I43: ='ARCHIVE_Staffing Summary'!J27 -> 4166.6667 | J43: ='ARCHIVE_Staffing Summary'!K27 -> 4166.6667 | ... AO43: ='ARCHIVE_Staffing Summary'!AP27 -> 53045 | AP43: =IF(AO$10=0,0,AO43/AO$10) -> 0.014458608
A44: 40000A0 Wages-Administrative | B44: 40000A0 | C44: ='ARCHIVE_Staffing Summary'!D28 -> 0 | D44: ='ARCHIVE_Staffing Summary'!E28 -> 0 | E44: ='ARCHIVE_Staffing Summary'!F28 -> 12500 | F44: ='ARCHIVE_Staffing Summary'!G28 -> 12500 | G44: ='ARCHIVE_Staffing Summary'!H28 -> 12500 | H44: ='ARCHIVE_Staffing Summary'!I28 -> 12500 | I44: ='ARCHIVE_Staffing Summary'!J28 -> 12500 | J44: ='ARCHIVE_Staffing Summary'!K28 -> 12500 | ... AO44: ='ARCHIVE_Staffing Summary'!AP28 -> 159135 | AP44: =IF(AO$10=0,0,AO44/AO$10) -> 0.043375825
A45: 40000C0 Wages-Clinical Admin | B45: 40000C0 | C45: ='ARCHIVE_Staffing Summary'!D29 -> 0 | D45: ='ARCHIVE_Staffing Summary'!E29 -> 10000 | E45: ='ARCHIVE_Staffing Summary'!F29 -> 10000 | F45: ='ARCHIVE_Staffing Summary'!G29 -> 10000 | G45: ='ARCHIVE_Staffing Summary'!H29 -> 10000 | H45: ='ARCHIVE_Staffing Summary'!I29 -> 10000 | I45: ='ARCHIVE_Staffing Summary'!J29 -> 10000 | J45: ='ARCHIVE_Staffing Summary'!K29 -> 10000 | ... AO45: ='ARCHIVE_Staffing Summary'!AP29 -> 127308 | AP45: =IF(AO$10=0,0,AO45/AO$10) -> 0.03470066
A46: 40000AN Medical Director | B46: 40000AN | C46: ='ARCHIVE_Staffing Summary'!D34 -> 4000 | D46: ='ARCHIVE_Staffing Summary'!E34 -> 4000 | E46: ='ARCHIVE_Staffing Summary'!F34 -> 4000 | F46: ='ARCHIVE_Staffing Summary'!G34 -> 4000 | G46: ='ARCHIVE_Staffing Summary'!H34 -> 4000 | H46: ='ARCHIVE_Staffing Summary'!I34 -> 4000 | I46: ='ARCHIVE_Staffing Summary'!J34 -> 4000 | J46: ='ARCHIVE_Staffing Summary'!K34 -> 4000 | ... AO46: ='ARCHIVE_Staffing Summary'!AP34 -> 48000 | AP46: =IF(AO$10=0,0,AO46/AO$10) -> 0.01308348
A47: Contract Labor (Admin + Clin) | B47: 40000MC | C47: ='ARCHIVE_Staffing Summary'!D32+'ARCHIVE_Staffing Summary'!D33 -> 4000 | D47: ='ARCHIVE_Staffing Summary'!E32+'ARCHIVE_Staffing Summary'!E33 -> 2500 | E47: ='ARCHIVE_Staffing Summary'!F32+'ARCHIVE_Staffing Summary'!F33 -> 0 | F47: ='ARCHIVE_Staffing Summary'!G32+'ARCHIVE_Staffing Summary'!G33 -> 0 | G47: ='ARCHIVE_Staffing Summary'!H32+'ARCHIVE_Staffing Summary'!H33 -> 0 | H47: ='ARCHIVE_Staffing Summary'!I32+'ARCHIVE_Staffing Summary'!I33 -> 0 | I47: ='ARCHIVE_Staffing Summary'!J32+'ARCHIVE_Staffing Summary'!J33 -> 0 | J47: ='ARCHIVE_Staffing Summary'!K32+'ARCHIVE_Staffing Summary'!K33 -> 0 | ... AO47: ='ARCHIVE_Staffing Summary'!AP32+'ARCHIVE_Staffing Summary'!AP33 -> 0 | AP47: =IF(AO$10=0,0,AO47/AO$10) -> 0
A48: Total Indirect Labor | C48: =SUM(C42:C47) -> 18000 | D48: =SUM(D42:D47) -> 30666.667 | E48: =SUM(E42:E47) -> 40666.667 | F48: =SUM(F42:F47) -> 40666.667 | G48: =SUM(G42:G47) -> 40666.667 | H48: =SUM(H42:H47) -> 40666.667 | I48: =SUM(I42:I47) -> 40666.667 | J48: =SUM(J42:J47) -> 40666.667 | ... AO48: =SUM(AO42:AO47) -> 514796 | AP48: =IF(AO$10=0,0,AO48/AO$10) -> 0.14031923
A49: INDIRECT BENEFITS
A50: 41300 FICA/SS (7.65%) | B50: 41300 | C50: =(C42+C43+C44+C45)*'ARCHIVE_Control Tower'!$B$5 -> 765 | D50: =(D42+D43+D44+D45)*'ARCHIVE_Control Tower'!$B$5 -> 1848.75 | E50: =(E42+E43+E44+E45)*'ARCHIVE_Control Tower'!$B$5 -> 2805 | F50: =(F42+F43+F44+F45)*'ARCHIVE_Control Tower'!$B$5 -> 2805 | G50: =(G42+G43+G44+G45)*'ARCHIVE_Control Tower'!$B$5 -> 2805 | H50: =(H42+H43+H44+H45)*'ARCHIVE_Control Tower'!$B$5 -> 2805 | I50: =(I42+I43+I44+I45)*'ARCHIVE_Control Tower'!$B$5 -> 2805 | J50: =(J42+J43+J44+J45)*'ARCHIVE_Control Tower'!$B$5 -> 2805 | ... AO50: =(AO42+AO43+AO44+AO45)*'ARCHIVE_Control Tower'!$B$5 -> 35709.894 | AP50: =IF(AO$10=0,0,AO50/AO$10) -> 0.009733535
A51: 41300 FUTA/SUTA (1.85%) | B51: 41300 | C51: =(C42+C43+C44+C45)*'ARCHIVE_Control Tower'!$B$6 -> 185 | D51: =(D42+D43+D44+D45)*'ARCHIVE_Control Tower'!$B$6 -> 447.08333 | E51: =(E42+E43+E44+E45)*'ARCHIVE_Control Tower'!$B$6 -> 678.33333 | F51: =(F42+F43+F44+F45)*'ARCHIVE_Control Tower'!$B$6 -> 678.33333 | G51: =(G42+G43+G44+G45)*'ARCHIVE_Control Tower'!$B$6 -> 678.33333 | H51: =(H42+H43+H44+H45)*'ARCHIVE_Control Tower'!$B$6 -> 678.33333 | I51: =(I42+I43+I44+I45)*'ARCHIVE_Control Tower'!$B$6 -> 678.33333 | J51: =(J42+J43+J44+J45)*'ARCHIVE_Control Tower'!$B$6 -> 678.33333 | ... AO51: =(AO42+AO43+AO44+AO45)*'ARCHIVE_Control Tower'!$B$6 -> 8635.726 | AP51: =IF(AO$10=0,0,AO51/AO$10) -> 0.0023538614
A52: 41600 Workers Compensation (3%) | B52: 41600 | C52: =(C42+C43+C44+C45)*'ARCHIVE_Control Tower'!$B$7 -> 300 | D52: =(D42+D43+D44+D45)*'ARCHIVE_Control Tower'!$B$7 -> 725 | E52: =(E42+E43+E44+E45)*'ARCHIVE_Control Tower'!$B$7 -> 1100 | F52: =(F42+F43+F44+F45)*'ARCHIVE_Control Tower'!$B$7 -> 1100 | G52: =(G42+G43+G44+G45)*'ARCHIVE_Control Tower'!$B$7 -> 1100 | H52: =(H42+H43+H44+H45)*'ARCHIVE_Control Tower'!$B$7 -> 1100 | I52: =(I42+I43+I44+I45)*'ARCHIVE_Control Tower'!$B$7 -> 1100 | J52: =(J42+J43+J44+J45)*'ARCHIVE_Control Tower'!$B$7 -> 1100 | ... AO52: =(AO42+AO43+AO44+AO45)*'ARCHIVE_Control Tower'!$B$7 -> 14003.88 | AP52: =IF(AO$10=0,0,AO52/AO$10) -> 0.0038170726
A53: 41100 Health Insurance | B53: 41100 | C53: ='ARCHIVE_Staffing Summary'!D41-C25 -> 732.86806 | D53: ='ARCHIVE_Staffing Summary'!E41-D25 -> 1749.1149 | E53: ='ARCHIVE_Staffing Summary'!F41-E25 -> 2402.4713 | F53: ='ARCHIVE_Staffing Summary'!G41-F25 -> 2385.1826 | G53: ='ARCHIVE_Staffing Summary'!H41-G25 -> 2368.141 | H53: ='ARCHIVE_Staffing Summary'!I41-H25 -> 2359.7111 | I53: ='ARCHIVE_Staffing Summary'!J41-I25 -> 2483.3674 | J53: ='ARCHIVE_Staffing Summary'!K41-J25 -> 2475.1253 | ... AO53: ='ARCHIVE_Staffing Summary'!AP41-AO25 -> 30796.736 | AP53: =IF(AO$10=0,0,AO53/AO$10) -> 0.0083943433
A54: Total Indirect Benefits | C54: =SUM(C50:C53) -> 1982.8681 | D54: =SUM(D50:D53) -> 4769.9482 | E54: =SUM(E50:E53) -> 6985.8046 | F54: =SUM(F50:F53) -> 6968.5159 | G54: =SUM(G50:G53) -> 6951.4743 | H54: =SUM(H50:H53) -> 6943.0445 | I54: =SUM(I50:I53) -> 7066.7007 | J54: =SUM(J50:J53) -> 7058.4586 | ... AO54: =SUM(AO50:AO53) -> 89146.236 | AP54: =IF(AO$10=0,0,AO54/AO$10) -> 0.024298812
A55: FACILITY & OPERATING EXPENSES
A56: 60800 Rent | B56: 60800 | C56: ='ARCHIVE_Control Tower'!$B$75 -> 3450 | D56: ='ARCHIVE_Control Tower'!$B$75 -> 3450 | E56: ='ARCHIVE_Control Tower'!$B$75 -> 3450 | F56: ='ARCHIVE_Control Tower'!$B$75 -> 3450 | G56: ='ARCHIVE_Control Tower'!$B$75 -> 3450 | H56: ='ARCHIVE_Control Tower'!$B$75 -> 3450 | I56: ='ARCHIVE_Control Tower'!$B$75 -> 3450 | J56: ='ARCHIVE_Control Tower'!$B$75 -> 3450 | ... AO56: ='ARCHIVE_Control Tower'!$B$75 -> 3450 | AP56: =IF(AO$10=0,0,AO56/AO$10) -> 0.00094037512
A57: 65801 Insurance-Liability | B57: 65801 | C57: ='ARCHIVE_Control Tower'!$B$76 -> 3333 | D57: ='ARCHIVE_Control Tower'!$B$76 -> 3333 | E57: ='ARCHIVE_Control Tower'!$B$76 -> 3333 | F57: ='ARCHIVE_Control Tower'!$B$76 -> 3333 | G57: ='ARCHIVE_Control Tower'!$B$76 -> 3333 | H57: ='ARCHIVE_Control Tower'!$B$76 -> 3333 | I57: ='ARCHIVE_Control Tower'!$B$76 -> 3333 | J57: ='ARCHIVE_Control Tower'!$B$76 -> 3333 | ... AO57: ='ARCHIVE_Control Tower'!$B$76 -> 3333 | AP57: =IF(AO$10=0,0,AO57/AO$10) -> 0.00090848414
A58: 65007 Professional Fees / Legal | B58: 65007 | C58: ='ARCHIVE_Control Tower'!$B$77 -> 2000 | D58: ='ARCHIVE_Control Tower'!$B$77 -> 2000 | E58: ='ARCHIVE_Control Tower'!$B$77 -> 2000 | F58: ='ARCHIVE_Control Tower'!$B$77 -> 2000 | G58: ='ARCHIVE_Control Tower'!$B$77 -> 2000 | H58: ='ARCHIVE_Control Tower'!$B$77 -> 2000 | I58: ='ARCHIVE_Control Tower'!$B$77 -> 2000 | J58: ='ARCHIVE_Control Tower'!$B$77 -> 2000 | ... AO58: ='ARCHIVE_Control Tower'!$B$77 -> 2000 | AP58: =IF(AO$10=0,0,AO58/AO$10) -> 0.000545145
A59: 65100 Accounting / Payroll Fees | B59: 65100 | C59: ='ARCHIVE_Control Tower'!$B$78 -> 1000 | D59: ='ARCHIVE_Control Tower'!$B$78 -> 1000 | E59: ='ARCHIVE_Control Tower'!$B$78 -> 1000 | F59: ='ARCHIVE_Control Tower'!$B$78 -> 1000 | G59: ='ARCHIVE_Control Tower'!$B$78 -> 1000 | H59: ='ARCHIVE_Control Tower'!$B$78 -> 1000 | I59: ='ARCHIVE_Control Tower'!$B$78 -> 1000 | J59: ='ARCHIVE_Control Tower'!$B$78 -> 1000 | ... AO59: ='ARCHIVE_Control Tower'!$B$78 -> 1000 | AP59: =IF(AO$10=0,0,AO59/AO$10) -> 0.0002725725
A60: 65000 Regulatory Consulting | B60: 65000 | C60: ='ARCHIVE_Control Tower'!$B$79 -> 750 | D60: ='ARCHIVE_Control Tower'!$B$79 -> 750 | E60: ='ARCHIVE_Control Tower'!$B$79 -> 750 | F60: ='ARCHIVE_Control Tower'!$B$79 -> 750 | G60: ='ARCHIVE_Control Tower'!$B$79 -> 750 | H60: ='ARCHIVE_Control Tower'!$B$79 -> 750 | I60: ='ARCHIVE_Control Tower'!$B$79 -> 750 | J60: ='ARCHIVE_Control Tower'!$B$79 -> 750 | ... AO60: ='ARCHIVE_Control Tower'!$B$79 -> 750 | AP60: =IF(AO$10=0,0,AO60/AO$10) -> 0.00020442937
A61: 65000 EMR / Patient Mgmt System | B61: 65006 | C61: =MAX('ARCHIVE_Control Tower'!$B$74,'ARCHIVE_Control Tower'!$B$73*'ARCHIVE_Revenue Model'!C18) -> 1125 | D61: =MAX('ARCHIVE_Control Tower'!$B$74,'ARCHIVE_Control Tower'!$B$73*'ARCHIVE_Revenue Model'!D18) -> 1275 | E61: =MAX('ARCHIVE_Control Tower'!$B$74,'ARCHIVE_Control Tower'!$B$73*'ARCHIVE_Revenue Model'!E18) -> 1350 | F61: =MAX('ARCHIVE_Control Tower'!$B$74,'ARCHIVE_Control Tower'!$B$73*'ARCHIVE_Revenue Model'!F18) -> 1500 | G61: =MAX('ARCHIVE_Control Tower'!$B$74,'ARCHIVE_Control Tower'!$B$73*'ARCHIVE_Revenue Model'!G18) -> 1650 | H61: =MAX('ARCHIVE_Control Tower'!$B$74,'ARCHIVE_Control Tower'!$B$73*'ARCHIVE_Revenue Model'!H18) -> 1725 | I61: =MAX('ARCHIVE_Control Tower'!$B$74,'ARCHIVE_Control Tower'!$B$73*'ARCHIVE_Revenue Model'!I18) -> 1875 | J61: =MAX('ARCHIVE_Control Tower'!$B$74,'ARCHIVE_Control Tower'!$B$73*'ARCHIVE_Revenue Model'!J18) -> 1950 | ... AO61: =MAX('ARCHIVE_Control Tower'!$B$74,'ARCHIVE_Control Tower'!$B$73*'ARCHIVE_Revenue Model'!AO18) -> 1000 | AP61: =IF(AO$10=0,0,AO61/AO$10) -> 0.0002725725
A62: 68001 Advertising / Publications | B62: 68001 | C62: ='ARCHIVE_Control Tower'!$B$80 -> 1200 | D62: ='ARCHIVE_Control Tower'!$B$80 -> 1200 | E62: ='ARCHIVE_Control Tower'!$B$80 -> 1200 | F62: ='ARCHIVE_Control Tower'!$B$80 -> 1200 | G62: ='ARCHIVE_Control Tower'!$B$80 -> 1200 | H62: ='ARCHIVE_Control Tower'!$B$80 -> 1200 | I62: ='ARCHIVE_Control Tower'!$B$80 -> 1200 | J62: ='ARCHIVE_Control Tower'!$B$80 -> 1200 | ... AO62: ='ARCHIVE_Control Tower'!$B$80 -> 1200 | AP62: =IF(AO$10=0,0,AO62/AO$10) -> 0.000327087
A63: 68050 Material Development | B63: 68050 | C63: ='ARCHIVE_Control Tower'!$B$81 -> 800 | D63: ='ARCHIVE_Control Tower'!$B$81 -> 800 | E63: ='ARCHIVE_Control Tower'!$B$81 -> 800 | F63: ='ARCHIVE_Control Tower'!$B$81 -> 800 | G63: ='ARCHIVE_Control Tower'!$B$81 -> 800 | H63: ='ARCHIVE_Control Tower'!$B$81 -> 800 | I63: ='ARCHIVE_Control Tower'!$B$81 -> 800 | J63: ='ARCHIVE_Control Tower'!$B$81 -> 800 | ... AO63: ='ARCHIVE_Control Tower'!$B$81 -> 800 | AP63: =IF(AO$10=0,0,AO63/AO$10) -> 0.000218058
A64: 66500 Office Supplies | B64: 66500 | C64: ='ARCHIVE_Control Tower'!$B$82 -> 500 | D64: ='ARCHIVE_Control Tower'!$B$82 -> 500 | E64: ='ARCHIVE_Control Tower'!$B$82 -> 500 | F64: ='ARCHIVE_Control Tower'!$B$82 -> 500 | G64: ='ARCHIVE_Control Tower'!$B$82 -> 500 | H64: ='ARCHIVE_Control Tower'!$B$82 -> 500 | I64: ='ARCHIVE_Control Tower'!$B$82 -> 500 | J64: ='ARCHIVE_Control Tower'!$B$82 -> 500 | ... AO64: ='ARCHIVE_Control Tower'!$B$82 -> 500 | AP64: =IF(AO$10=0,0,AO64/AO$10) -> 0.00013628625
A65: 61500 Telephone & Internet | B65: 61500 | C65: ='ARCHIVE_Control Tower'!$B$83 -> 600 | D65: ='ARCHIVE_Control Tower'!$B$83 -> 600 | E65: ='ARCHIVE_Control Tower'!$B$83 -> 600 | F65: ='ARCHIVE_Control Tower'!$B$83 -> 600 | G65: ='ARCHIVE_Control Tower'!$B$83 -> 600 | H65: ='ARCHIVE_Control Tower'!$B$83 -> 600 | I65: ='ARCHIVE_Control Tower'!$B$83 -> 600 | J65: ='ARCHIVE_Control Tower'!$B$83 -> 600 | ... AO65: ='ARCHIVE_Control Tower'!$B$83 -> 600 | AP65: =IF(AO$10=0,0,AO65/AO$10) -> 0.0001635435
A66: 61500 Utilities | B66: 61500 | C66: ='ARCHIVE_Control Tower'!$B$84 -> 600 | D66: ='ARCHIVE_Control Tower'!$B$84 -> 600 | E66: ='ARCHIVE_Control Tower'!$B$84 -> 600 | F66: ='ARCHIVE_Control Tower'!$B$84 -> 600 | G66: ='ARCHIVE_Control Tower'!$B$84 -> 600 | H66: ='ARCHIVE_Control Tower'!$B$84 -> 600 | I66: ='ARCHIVE_Control Tower'!$B$84 -> 600 | J66: ='ARCHIVE_Control Tower'!$B$84 -> 600 | ... AO66: ='ARCHIVE_Control Tower'!$B$84 -> 600 | AP66: =IF(AO$10=0,0,AO66/AO$10) -> 0.0001635435
A67: 65200 Bank Service Charges | B67: 65200 | C67: ='ARCHIVE_Control Tower'!$B$85 -> 150 | D67: ='ARCHIVE_Control Tower'!$B$85 -> 150 | E67: ='ARCHIVE_Control Tower'!$B$85 -> 150 | F67: ='ARCHIVE_Control Tower'!$B$85 -> 150 | G67: ='ARCHIVE_Control Tower'!$B$85 -> 150 | H67: ='ARCHIVE_Control Tower'!$B$85 -> 150 | I67: ='ARCHIVE_Control Tower'!$B$85 -> 150 | J67: ='ARCHIVE_Control Tower'!$B$85 -> 150 | ... AO67: ='ARCHIVE_Control Tower'!$B$85 -> 150 | AP67: =IF(AO$10=0,0,AO67/AO$10) -> 4.0885875e-05
A68: 65700 Dues & Subscriptions | B68: 65700 | C68: ='ARCHIVE_Control Tower'!$B$86 -> 300 | D68: ='ARCHIVE_Control Tower'!$B$86 -> 300 | E68: ='ARCHIVE_Control Tower'!$B$86 -> 300 | F68: ='ARCHIVE_Control Tower'!$B$86 -> 300 | G68: ='ARCHIVE_Control Tower'!$B$86 -> 300 | H68: ='ARCHIVE_Control Tower'!$B$86 -> 300 | I68: ='ARCHIVE_Control Tower'!$B$86 -> 300 | J68: ='ARCHIVE_Control Tower'!$B$86 -> 300 | ... AO68: ='ARCHIVE_Control Tower'!$B$86 -> 300 | AP68: =IF(AO$10=0,0,AO68/AO$10) -> 8.1771749e-05
A69: Total Facility & Operating Expenses | C69: =SUM(C56:C68) -> 15808 | D69: =SUM(D56:D68) -> 15958 | E69: =SUM(E56:E68) -> 16033 | F69: =SUM(F56:F68) -> 16183 | G69: =SUM(G56:G68) -> 16333 | H69: =SUM(H56:H68) -> 16408 | I69: =SUM(I56:I68) -> 16558 | J69: =SUM(J56:J68) -> 16633 | ... AO69: =SUM(AO56:AO68) -> 15683 | AP69: =IF(AO$10=0,0,AO69/AO$10) -> 0.0042747545
A72: TOTAL SG&A | C72: =C48+C54+C69 -> 35790.868 | D72: =D48+D54+D69 -> 51394.615 | E72: =E48+E54+E69 -> 63685.471 | F72: =F48+F54+F69 -> 63818.183 | G72: =G48+G54+G69 -> 63951.141 | H72: =H48+H54+H69 -> 64017.711 | I72: =I48+I54+I69 -> 64291.367 | J72: =J48+J54+J69 -> 64358.125 | ... AO72: =AO48+AO54+AO69 -> 619625.24 | AP72: =IF(AO$10=0,0,AO72/AO$10) -> 0.1688928
A74: EBITDA | C74: =C36-C72 -> 17065.359 | D74: =D36-D72 -> 3024.094 | E74: =E36-E72 -> -4422.6946 | F74: =F36-F72 -> 4739.447 | G74: =G36-G72 -> 13901.589 | H74: =H36-H72 -> 18482.659 | I74: =I36-I72 -> 22819.129 | J74: =J36-J72 -> 27400.2 | ... AO74: =AO36-AO72 -> 1790071.8 | AP74: =IF(AO$10=0,0,AO74/AO$10) -> 0.48792436
A75: EBITDA Margin % | C75: =IF(C10=0,0,C74/C10) -> 0.2062186 | D75: =IF(D10=0,0,D74/D10) -> 0.032244084 | E75: =IF(E10=0,0,E74/E10) -> -0.044536709 | F75: =IF(F10=0,0,F74/F10) -> 0.042953777 | G75: =IF(G10=0,0,G74/G10) -> 0.1145369 | H75: =IF(H10=0,0,H74/H10) -> 0.14566 | I75: =IF(I10=0,0,I74/I10) -> 0.16544846 | J75: =IF(J10=0,0,J74/J10) -> 0.1910223 | ... AO75: =IF(AO10=0,0,AO74/AO10) -> 0.48792436
A77: BELOW EBITDA
A78: Amortization of Intangibles | B78: 7000 | C78: ='ARCHIVE_Control Tower'!$B$89/'ARCHIVE_Control Tower'!$B$90/12 -> 1666.6667 | D78: ='ARCHIVE_Control Tower'!$B$89/'ARCHIVE_Control Tower'!$B$90/12 -> 1666.6667 | E78: ='ARCHIVE_Control Tower'!$B$89/'ARCHIVE_Control Tower'!$B$90/12 -> 1666.6667 | F78: ='ARCHIVE_Control Tower'!$B$89/'ARCHIVE_Control Tower'!$B$90/12 -> 1666.6667 | G78: ='ARCHIVE_Control Tower'!$B$89/'ARCHIVE_Control Tower'!$B$90/12 -> 1666.6667 | H78: ='ARCHIVE_Control Tower'!$B$89/'ARCHIVE_Control Tower'!$B$90/12 -> 1666.6667 | I78: ='ARCHIVE_Control Tower'!$B$89/'ARCHIVE_Control Tower'!$B$90/12 -> 1666.6667 | J78: ='ARCHIVE_Control Tower'!$B$89/'ARCHIVE_Control Tower'!$B$90/12 -> 1666.6667 | ... AO78: ='ARCHIVE_Control Tower'!$B$89/'ARCHIVE_Control Tower'!$B$90/12 -> 1666.6667 | AP78: =IF(AO$10=0,0,AO78/AO$10) -> 0.0004542875
A79: Interest - SBA Loan | B79: 7100 | C79: ='ARCHIVE_Control Tower'!$B$91*'ARCHIVE_Control Tower'!$B$92/12 -> 4791.6667 | D79: ='ARCHIVE_Control Tower'!$B$91*'ARCHIVE_Control Tower'!$B$92/12 -> 4791.6667 | E79: ='ARCHIVE_Control Tower'!$B$91*'ARCHIVE_Control Tower'!$B$92/12 -> 4791.6667 | F79: ='ARCHIVE_Control Tower'!$B$91*'ARCHIVE_Control Tower'!$B$92/12 -> 4791.6667 | G79: ='ARCHIVE_Control Tower'!$B$91*'ARCHIVE_Control Tower'!$B$92/12 -> 4791.6667 | H79: ='ARCHIVE_Control Tower'!$B$91*'ARCHIVE_Control Tower'!$B$92/12 -> 4791.6667 | I79: ='ARCHIVE_Control Tower'!$B$91*'ARCHIVE_Control Tower'!$B$92/12 -> 4791.6667 | J79: ='ARCHIVE_Control Tower'!$B$91*'ARCHIVE_Control Tower'!$B$92/12 -> 4791.6667 | ... AO79: ='ARCHIVE_Control Tower'!$B$91*'ARCHIVE_Control Tower'!$B$92/12 -> 4791.6667 | AP79: =IF(AO$10=0,0,AO79/AO$10) -> 0.0013060766
A80: Interest - Seller Note | B80: 7100 | C80: ='ARCHIVE_Control Tower'!$B$94*'ARCHIVE_Control Tower'!$B$95/12 -> 1000 | D80: ='ARCHIVE_Control Tower'!$B$94*'ARCHIVE_Control Tower'!$B$95/12 -> 1000 | E80: ='ARCHIVE_Control Tower'!$B$94*'ARCHIVE_Control Tower'!$B$95/12 -> 1000 | F80: ='ARCHIVE_Control Tower'!$B$94*'ARCHIVE_Control Tower'!$B$95/12 -> 1000 | G80: ='ARCHIVE_Control Tower'!$B$94*'ARCHIVE_Control Tower'!$B$95/12 -> 1000 | H80: ='ARCHIVE_Control Tower'!$B$94*'ARCHIVE_Control Tower'!$B$95/12 -> 1000 | I80: ='ARCHIVE_Control Tower'!$B$94*'ARCHIVE_Control Tower'!$B$95/12 -> 1000 | J80: ='ARCHIVE_Control Tower'!$B$94*'ARCHIVE_Control Tower'!$B$95/12 -> 1000 | ... AO80: ='ARCHIVE_Control Tower'!$B$94*'ARCHIVE_Control Tower'!$B$95/12 -> 1000 | AP80: =IF(AO$10=0,0,AO80/AO$10) -> 0.0002725725
A81: License - Upfront Payment | B81: 7200 | C81: =IF(COLUMN()-2<=3,'ARCHIVE_Control Tower'!$B$98,0) -> 25000 | D81: =IF(COLUMN()-2<=3,'ARCHIVE_Control Tower'!$B$98,0) -> 25000 | E81: =IF(COLUMN()-2<=3,'ARCHIVE_Control Tower'!$B$98,0) -> 25000 | F81: =IF(COLUMN()-2<=3,'ARCHIVE_Control Tower'!$B$98,0) -> 0 | G81: =IF(COLUMN()-2<=3,'ARCHIVE_Control Tower'!$B$98,0) -> 0 | H81: =IF(COLUMN()-2<=3,'ARCHIVE_Control Tower'!$B$98,0) -> 0 | I81: =IF(COLUMN()-2<=3,'ARCHIVE_Control Tower'!$B$98,0) -> 0 | J81: =IF(COLUMN()-2<=3,'ARCHIVE_Control Tower'!$B$98,0) -> 0 | ... AL81: =IF(COLUMN()-2<=3,'ARCHIVE_Control Tower'!$B$98,0) -> 0 | AM81: =SUM(C81:N81) -> 75000 | AN81: =SUM(O81:Z81) -> 0 | AO81: =SUM(AA81:AL81) -> 0 | AP81: =IF(AO$10=0,0,AO81/AO$10) -> 0
A82: License - Refi Interest | B82: 7200 | C82: =IF(COLUMN()-2>3,-IPMT('ARCHIVE_Control Tower'!$B$99/12,COLUMN()-2-3,'ARCHIVE_Control Tower'!$B$100,'ARCHIVE_Control Tower'!$B$97-3*'ARCHIVE_Control Tower'!$B$98),0) -> 0 | D82: =IF(COLUMN()-2>3,-IPMT('ARCHIVE_Control Tower'!$B$99/12,COLUMN()-2-3,'ARCHIVE_Control Tower'!$B$100,'ARCHIVE_Control Tower'!$B$97-3*'ARCHIVE_Control Tower'!$B$98),0) -> 0 | E82: =IF(COLUMN()-2>3,-IPMT('ARCHIVE_Control Tower'!$B$99/12,COLUMN()-2-3,'ARCHIVE_Control Tower'!$B$100,'ARCHIVE_Control Tower'!$B$97-3*'ARCHIVE_Control Tower'!$B$98),0) -> 0 | F82: =IF(COLUMN()-2>3,-IPMT('ARCHIVE_Control Tower'!$B$99/12,COLUMN()-2-3,'ARCHIVE_Control Tower'!$B$100,'ARCHIVE_Control Tower'!$B$97-3*'ARCHIVE_Control Tower'!$B$98),0) -> 1125 | G82: =IF(COLUMN()-2>3,-IPMT('ARCHIVE_Control Tower'!$B$99/12,COLUMN()-2-3,'ARCHIVE_Control Tower'!$B$100,'ARCHIVE_Control Tower'!$B$97-3*'ARCHIVE_Control Tower'!$B$98),0) -> 1096.4003 | H82: =IF(COLUMN()-2>3,-IPMT('ARCHIVE_Control Tower'!$B$99/12,COLUMN()-2-3,'ARCHIVE_Control Tower'!$B$100,'ARCHIVE_Control Tower'!$B$97-3*'ARCHIVE_Control Tower'!$B$98),0) -> 1067.6576 | I82: =IF(COLUMN()-2>3,-IPMT('ARCHIVE_Control Tower'!$B$99/12,COLUMN()-2-3,'ARCHIVE_Control Tower'!$B$100,'ARCHIVE_Control Tower'!$B$97-3*'ARCHIVE_Control Tower'!$B$98),0) -> 1038.7713 | J82: =IF(COLUMN()-2>3,-IPMT('ARCHIVE_Control Tower'!$B$99/12,COLUMN()-2-3,'ARCHIVE_Control Tower'!$B$100,'ARCHIVE_Control Tower'!$B$97-3*'ARCHIVE_Control Tower'!$B$98),0) -> 1009.7404 | ... AL82: =IF(COLUMN()-2>3,-IPMT('ARCHIVE_Control Tower'!$B$99/12,COLUMN()-2-3,'ARCHIVE_Control Tower'!$B$100,'ARCHIVE_Control Tower'!$B$97-3*'ARCHIVE_Control Tower'!$B$98),0) -> 135.20445 | AM82: =SUM(C82:N82) -> 9083.3091 | AN82: =SUM(O82:Z82) -> 8341.2173 | AO82: =SUM(AA82:AL82) -> 3789.5173 | AP82: =IF(AO$10=0,0,AO82/AO$10) -> 0.0010329182
A83: Total Below-EBITDA | C83: =SUM(C78:C82) -> 32458.333 | D83: =SUM(D78:D82) -> 32458.333 | E83: =SUM(E78:E82) -> 32458.333 | F83: =SUM(F78:F82) -> 8583.3333 | G83: =SUM(G78:G82) -> 8554.7337 | H83: =SUM(H78:H82) -> 8525.991 | I83: =SUM(I78:I82) -> 8497.1046 | J83: =SUM(J78:J82) -> 8468.0738 | ... AO83: =SUM(AO78:AO82) -> 11247.851 | AP83: =IF(AO$10=0,0,AO83/AO$10) -> 0.0030658548
A85: PRE-TAX INCOME | C85: =C74-C83 -> -15392.975 | D85: =D74-D83 -> -29434.239 | E85: =E74-E83 -> -36881.028 | F85: =F74-F83 -> -3843.8863 | G85: =G74-G83 -> 5346.8549 | H85: =H74-H83 -> 9956.6684 | I85: =I74-I83 -> 14322.024 | J85: =J74-J83 -> 18932.126 | ... AO85: =AO74-AO83 -> 1778824 | AP85: =IF(AO$10=0,0,AO85/AO$10) -> 0.4848585
A86: TX Franchise Tax (0.375%) | B86: 9000 | C86: =IF(C85>0,C10*'ARCHIVE_Control Tower'!$B$96,0) -> 0 | D86: =IF(D85>0,D10*'ARCHIVE_Control Tower'!$B$96,0) -> 0 | E86: =IF(E85>0,E10*'ARCHIVE_Control Tower'!$B$96,0) -> 0 | F86: =IF(F85>0,F10*'ARCHIVE_Control Tower'!$B$96,0) -> 0 | G86: =IF(G85>0,G10*'ARCHIVE_Control Tower'!$B$96,0) -> 455.14552 | H86: =IF(H85>0,H10*'ARCHIVE_Control Tower'!$B$96,0) -> 475.83395 | I86: =IF(I85>0,I10*'ARCHIVE_Control Tower'!$B$96,0) -> 517.21081 | J86: =IF(J85>0,J10*'ARCHIVE_Control Tower'!$B$96,0) -> 537.89925 | ... AO86: =IF(AO85>0,AO10*'ARCHIVE_Control Tower'!$B$96,0) -> 13757.808 | AP86: =IF(AO$10=0,0,AO86/AO$10) -> 0.00375
A87: NET INCOME | C87: =C85-C86 -> -15392.975 | D87: =D85-D86 -> -29434.239 | E87: =E85-E86 -> -36881.028 | F87: =F85-F86 -> -3843.8863 | G87: =G85-G86 -> 4891.7094 | H87: =H85-H86 -> 9480.8344 | I87: =I85-I86 -> 13804.814 | J87: =J85-J86 -> 18394.227 | ... AO87: =AO85-AO86 -> 1765066.2 | AP87: =IF(AO$10=0,0,AO87/AO$10) -> 0.4811085

Sheet ARCHIVE_P&L
A1: PROFIT & LOSS STATEMENT
A2: 36-Month GL Detail
B3: GL Code | C3: Year 1 | O3: Year 2 | AA3: Year 3 | AM3: Annual | AP3: % Rev
C4: M1 | D4: M2 | E4: M3 | F4: M4 | G4: M5 | H4: M6 | I4: M7 | J4: M8 | K4: M9 | L4: M10 | M4: M11 | N4: M12 | O4: M13 | P4: M14 | Q4: M15 | R4: M16 | S4: M17 | T4: M18 | U4: M19 | V4: M20 | W4: M21 | X4: M22 | Y4: M23 | Z4: M24 | AA4: M25 | AB4: M26 | AC4: M27 | AD4: M28 | AE4: M29 | AF4: M30 | AG4: M31 | AH4: M32 | AI4: M33 | AJ4: M34 | AK4: M35 | AL4: M36 | AM4: Year 1 | AN4: Year 2 | AO4: Year 3 | AP4: (Y3)
A5: REVENUE
A6: Avg Daily Census | C6: ='ARCHIVE_Operating Budget'!C6 -> 15 | D6: ='ARCHIVE_Operating Budget'!D6 -> 17 | E6: ='ARCHIVE_Operating Budget'!E6 -> 18 | F6: ='ARCHIVE_Operating Budget'!F6 -> 20 | G6: ='ARCHIVE_Operating Budget'!G6 -> 22 | H6: ='ARCHIVE_Operating Budget'!H6 -> 23 | I6: ='ARCHIVE_Operating Budget'!I6 -> 25 | J6: ='ARCHIVE_Operating Budget'!J6 -> 26 | ... AO6: ='ARCHIVE_Operating Budget'!AO6 -> 55.416667
A7: Total Patient Days | C7: ='ARCHIVE_Operating Budget'!C7 -> 456 | D7: ='ARCHIVE_Operating Budget'!D7 -> 516.8 | E7: ='ARCHIVE_Operating Budget'!E7 -> 547.2 | F7: ='ARCHIVE_Operating Budget'!F7 -> 608 | G7: ='ARCHIVE_Operating Budget'!G7 -> 668.8 | H7: ='ARCHIVE_Operating Budget'!H7 -> 699.2 | I7: ='ARCHIVE_Operating Budget'!I7 -> 760 | J7: ='ARCHIVE_Operating Budget'!J7 -> 790.4 | ... AO7: ='ARCHIVE_Operating Budget'!AO7 -> 20216
A8: Gross Patient Revenue | B8: 3000 | C8: ='ARCHIVE_Operating Budget'!C8 -> 84013.939 | D8: ='ARCHIVE_Operating Budget'!D8 -> 95215.798 | E8: ='ARCHIVE_Operating Budget'!E8 -> 100816.73 | F8: ='ARCHIVE_Operating Budget'!F8 -> 112018.59 | G8: ='ARCHIVE_Operating Budget'!G8 -> 123220.44 | H8: ='ARCHIVE_Operating Budget'!H8 -> 128821.37 | I8: ='ARCHIVE_Operating Budget'!I8 -> 140023.23 | J8: ='ARCHIVE_Operating Budget'!J8 -> 145624.16 | ... AP8: ='ARCHIVE_Operating Budget'!AP8 -> 1.0152284
A9: Billing / Collection Fee (-1.5%) | B9: 3900 | C9: ='ARCHIVE_Operating Budget'!C9 -> -1260.2091 | D9: ='ARCHIVE_Operating Budget'!D9 -> -1428.237 | E9: ='ARCHIVE_Operating Budget'!E9 -> -1512.2509 | F9: ='ARCHIVE_Operating Budget'!F9 -> -1680.2788 | G9: ='ARCHIVE_Operating Budget'!G9 -> -1848.3067 | H9: ='ARCHIVE_Operating Budget'!H9 -> -1932.3206 | I9: ='ARCHIVE_Operating Budget'!I9 -> -2100.3485 | J9: ='ARCHIVE_Operating Budget'!J9 -> -2184.3624 | ... AP9: ='ARCHIVE_Operating Budget'!AP9 -> -0.015228426
A10: Net Patient Revenue | C10: ='ARCHIVE_Operating Budget'!C10 -> 82753.73 | D10: ='ARCHIVE_Operating Budget'!D10 -> 93787.561 | E10: ='ARCHIVE_Operating Budget'!E10 -> 99304.476 | F10: ='ARCHIVE_Operating Budget'!F10 -> 110338.31 | G10: ='ARCHIVE_Operating Budget'!G10 -> 121372.14 | H10: ='ARCHIVE_Operating Budget'!H10 -> 126889.05 | I10: ='ARCHIVE_Operating Budget'!I10 -> 137922.88 | J10: ='ARCHIVE_Operating Budget'!J10 -> 143439.8 | ... AP10: ='ARCHIVE_Operating Budget'!AP10 -> 1
A12: COST OF GOODS SOLD
A13: DIRECT LABOR
A14: 4000R61 Wages-RN | B14: 4000R61 | C14: ='ARCHIVE_Operating Budget'!C14 -> 6250.4167 | D14: ='ARCHIVE_Operating Budget'!D14 -> 12709 | E14: ='ARCHIVE_Operating Budget'!E14 -> 12709 | F14: ='ARCHIVE_Operating Budget'!F14 -> 12709 | G14: ='ARCHIVE_Operating Budget'!G14 -> 12709 | H14: ='ARCHIVE_Operating Budget'!H14 -> 12709 | I14: ='ARCHIVE_Operating Budget'!I14 -> 12709 | J14: ='ARCHIVE_Operating Budget'!J14 -> 12709 | ... AP14: ='ARCHIVE_Operating Budget'!AP14 -> 0.088202137
A15: 4000R62 Wages-LVN | B15: 4000R62 | C15: ='ARCHIVE_Operating Budget'!C15 -> 900 | D15: ='ARCHIVE_Operating Budget'!D15 -> 1020 | E15: ='ARCHIVE_Operating Budget'!E15 -> 1080 | F15: ='ARCHIVE_Operating Budget'!F15 -> 1200 | G15: ='ARCHIVE_Operating Budget'!G15 -> 1320 | H15: ='ARCHIVE_Operating Budget'!H15 -> 1380 | I15: ='ARCHIVE_Operating Budget'!I15 -> 1500 | J15: ='ARCHIVE_Operating Budget'!J15 -> 1560 | ... AP15: ='ARCHIVE_Operating Budget'!AP15 -> 0.010875643
A16: 4000R65 Wages-Aide | B16: 4000R65 | C16: ='ARCHIVE_Operating Budget'!C16 -> 7720.875 | D16: ='ARCHIVE_Operating Budget'!D16 -> 7720.875 | E16: ='ARCHIVE_Operating Budget'!E16 -> 7690.0833 | F16: ='ARCHIVE_Operating Budget'!F16 -> 7690.0833 | G16: ='ARCHIVE_Operating Budget'!G16 -> 7690.0833 | H16: ='ARCHIVE_Operating Budget'!H16 -> 7690.0833 | I16: ='ARCHIVE_Operating Budget'!I16 -> 11535.125 | J16: ='ARCHIVE_Operating Budget'!J16 -> 11535.125 | ... AP16: ='ARCHIVE_Operating Budget'!AP16 -> 0.066712741
A17: 4000R66 Wages-MSW | B17: 4000R66 | C17: ='ARCHIVE_Operating Budget'!C17 -> 1125 | D17: ='ARCHIVE_Operating Budget'!D17 -> 1275 | E17: ='ARCHIVE_Operating Budget'!E17 -> 1350 | F17: ='ARCHIVE_Operating Budget'!F17 -> 1500 | G17: ='ARCHIVE_Operating Budget'!G17 -> 1650 | H17: ='ARCHIVE_Operating Budget'!H17 -> 1725 | I17: ='ARCHIVE_Operating Budget'!I17 -> 1875 | J17: ='ARCHIVE_Operating Budget'!J17 -> 1950 | ... AP17: ='ARCHIVE_Operating Budget'!AP17 -> 0.013594553
A18: 4000R67 Wages-SC | B18: 4000R67 | C18: ='ARCHIVE_Operating Budget'!C18 -> 843.75 | D18: ='ARCHIVE_Operating Budget'!D18 -> 956.25 | E18: ='ARCHIVE_Operating Budget'!E18 -> 1012.5 | F18: ='ARCHIVE_Operating Budget'!F18 -> 1125 | G18: ='ARCHIVE_Operating Budget'!G18 -> 1237.5 | H18: ='ARCHIVE_Operating Budget'!H18 -> 1293.75 | I18: ='ARCHIVE_Operating Budget'!I18 -> 1406.25 | J18: ='ARCHIVE_Operating Budget'!J18 -> 1462.5 | ... AP18: ='ARCHIVE_Operating Budget'!AP18 -> 0.010195915
A19: 4000R6N Wages-NP | B19: 4000R6N | C19: ='ARCHIVE_Operating Budget'!C19 -> 450 | D19: ='ARCHIVE_Operating Budget'!D19 -> 510 | E19: ='ARCHIVE_Operating Budget'!E19 -> 540 | F19: ='ARCHIVE_Operating Budget'!F19 -> 600 | G19: ='ARCHIVE_Operating Budget'!G19 -> 660 | H19: ='ARCHIVE_Operating Budget'!H19 -> 690 | I19: ='ARCHIVE_Operating Budget'!I19 -> 750 | J19: ='ARCHIVE_Operating Budget'!J19 -> 780 | ... AP19: ='ARCHIVE_Operating Budget'!AP19 -> 0.0054378213
A20: Total Direct Labor | C20: ='ARCHIVE_Operating Budget'!C20 -> 17290.042 | D20: ='ARCHIVE_Operating Budget'!D20 -> 24191.125 | E20: ='ARCHIVE_Operating Budget'!E20 -> 24381.583 | F20: ='ARCHIVE_Operating Budget'!F20 -> 24824.083 | G20: ='ARCHIVE_Operating Budget'!G20 -> 25266.583 | H20: ='ARCHIVE_Operating Budget'!H20 -> 25487.833 | I20: ='ARCHIVE_Operating Budget'!I20 -> 29775.375 | J20: ='ARCHIVE_Operating Budget'!J20 -> 29996.625 | ... AP20: ='ARCHIVE_Operating Budget'!AP20 -> 0.19501881
A21: DIRECT BENEFITS
A22: 41300 FICA/SS (7.65%) | B22: 41300 | C22: ='ARCHIVE_Operating Budget'!C22 -> 1322.6882 | D22: ='ARCHIVE_Operating Budget'!D22 -> 1850.6211 | E22: ='ARCHIVE_Operating Budget'!E22 -> 1865.1911 | F22: ='ARCHIVE_Operating Budget'!F22 -> 1899.0424 | G22: ='ARCHIVE_Operating Budget'!G22 -> 1932.8936 | H22: ='ARCHIVE_Operating Budget'!H22 -> 1949.8193 | I22: ='ARCHIVE_Operating Budget'!I22 -> 2277.8162 | J22: ='ARCHIVE_Operating Budget'!J22 -> 2294.7418 | ... AP22: ='ARCHIVE_Operating Budget'!AP22 -> 0.014918939
A23: 41300 FUTA/SUTA (1.85%) | B23: 41300 | C23: ='ARCHIVE_Operating Budget'!C23 -> 319.86577 | D23: ='ARCHIVE_Operating Budget'!D23 -> 447.53581 | E23: ='ARCHIVE_Operating Budget'!E23 -> 451.05929 | F23: ='ARCHIVE_Operating Budget'!F23 -> 459.24554 | G23: ='ARCHIVE_Operating Budget'!G23 -> 467.43179 | H23: ='ARCHIVE_Operating Budget'!H23 -> 471.52492 | I23: ='ARCHIVE_Operating Budget'!I23 -> 550.84444 | J23: ='ARCHIVE_Operating Budget'!J23 -> 554.93756 | ... AP23: ='ARCHIVE_Operating Budget'!AP23 -> 0.003607848
A24: 41600 Workers Compensation (3%) | B24: 41600 | C24: ='ARCHIVE_Operating Budget'!C24 -> 518.70125 | D24: ='ARCHIVE_Operating Budget'!D24 -> 725.73375 | E24: ='ARCHIVE_Operating Budget'!E24 -> 731.4475 | F24: ='ARCHIVE_Operating Budget'!F24 -> 744.7225 | G24: ='ARCHIVE_Operating Budget'!G24 -> 757.9975 | H24: ='ARCHIVE_Operating Budget'!H24 -> 764.635 | I24: ='ARCHIVE_Operating Budget'!I24 -> 893.26125 | J24: ='ARCHIVE_Operating Budget'!J24 -> 899.89875 | ... AP24: ='ARCHIVE_Operating Budget'!AP24 -> 0.0058505643
A25: 41100 Health Insurance | B25: 41100 | C25: ='ARCHIVE_Operating Budget'!C25 -> 1267.1319 | D25: ='ARCHIVE_Operating Budget'!D25 -> 1750.8851 | E25: ='ARCHIVE_Operating Budget'!E25 -> 1597.5287 | F25: ='ARCHIVE_Operating Budget'!F25 -> 1614.8174 | G25: ='ARCHIVE_Operating Budget'!G25 -> 1631.859 | H25: ='ARCHIVE_Operating Budget'!H25 -> 1640.2889 | I25: ='ARCHIVE_Operating Budget'!I25 -> 2016.6326 | J25: ='ARCHIVE_Operating Budget'!J25 -> 2024.8747 | ... AP25: ='ARCHIVE_Operating Budget'!AP25 -> 0.012866312
A26: Total Direct Benefits | C26: ='ARCHIVE_Operating Budget'!C26 -> 3428.3871 | D26: ='ARCHIVE_Operating Budget'!D26 -> 4774.7757 | E26: ='ARCHIVE_Operating Budget'!E26 -> 4645.2266 | F26: ='ARCHIVE_Operating Budget'!F26 -> 4717.8278 | G26: ='ARCHIVE_Operating Budget'!G26 -> 4790.1819 | H26: ='ARCHIVE_Operating Budget'!H26 -> 4826.268 | I26: ='ARCHIVE_Operating Budget'!I26 -> 5738.5545 | J26: ='ARCHIVE_Operating Budget'!J26 -> 5774.4528 | ... AP26: ='ARCHIVE_Operating Budget'!AP26 -> 0.037243663
A27: PATIENT-RELATED EXPENSES
A28: 5050 Durable Medical Equipment | B28: 5050 | C28: ='ARCHIVE_Operating Budget'!C28 -> 4104 | D28: ='ARCHIVE_Operating Budget'!D28 -> 4651.2 | E28: ='ARCHIVE_Operating Budget'!E28 -> 4924.8 | F28: ='ARCHIVE_Operating Budget'!F28 -> 5472 | G28: ='ARCHIVE_Operating Budget'!G28 -> 6019.2 | H28: ='ARCHIVE_Operating Budget'!H28 -> 6292.8 | I28: ='ARCHIVE_Operating Budget'!I28 -> 6840 | J28: ='ARCHIVE_Operating Budget'!J28 -> 7113.6 | ... AP28: ='ARCHIVE_Operating Budget'!AP28 -> 0.049592931
A29: 5100 Medications | B29: 5100 | C29: ='ARCHIVE_Operating Budget'!C29 -> 1596 | D29: ='ARCHIVE_Operating Budget'!D29 -> 1808.8 | E29: ='ARCHIVE_Operating Budget'!E29 -> 1915.2 | F29: ='ARCHIVE_Operating Budget'!F29 -> 2128 | G29: ='ARCHIVE_Operating Budget'!G29 -> 2340.8 | H29: ='ARCHIVE_Operating Budget'!H29 -> 2447.2 | I29: ='ARCHIVE_Operating Budget'!I29 -> 2660 | J29: ='ARCHIVE_Operating Budget'!J29 -> 2766.4 | ... AP29: ='ARCHIVE_Operating Budget'!AP29 -> 0.01928614
A30: 5090 Medical Supplies | B30: 5090 | C30: ='ARCHIVE_Operating Budget'!C30 -> 1368 | D30: ='ARCHIVE_Operating Budget'!D30 -> 1550.4 | E30: ='ARCHIVE_Operating Budget'!E30 -> 1641.6 | F30: ='ARCHIVE_Operating Budget'!F30 -> 1824 | G30: ='ARCHIVE_Operating Budget'!G30 -> 2006.4 | H30: ='ARCHIVE_Operating Budget'!H30 -> 2097.6 | I30: ='ARCHIVE_Operating Budget'!I30 -> 2280 | J30: ='ARCHIVE_Operating Budget'!J30 -> 2371.2 | ... AP30: ='ARCHIVE_Operating Budget'!AP30 -> 0.016530977
A31: 5110 Mileage Reimbursement | B31: 5110 | C31: ='ARCHIVE_Operating Budget'!C31 -> 1655.0746 | D31: ='ARCHIVE_Operating Budget'!D31 -> 1875.7512 | E31: ='ARCHIVE_Operating Budget'!E31 -> 1986.0895 | F31: ='ARCHIVE_Operating Budget'!F31 -> 2206.7661 | G31: ='ARCHIVE_Operating Budget'!G31 -> 2427.4428 | H31: ='ARCHIVE_Operating Budget'!H31 -> 2537.7811 | I31: ='ARCHIVE_Operating Budget'!I31 -> 2758.4577 | J31: ='ARCHIVE_Operating Budget'!J31 -> 2868.796 | ... AP31: ='ARCHIVE_Operating Budget'!AP31 -> 0.02
A32: 6560 Continuing Education | B32: 6560 | C32: ='ARCHIVE_Operating Budget'!C32 -> 456 | D32: ='ARCHIVE_Operating Budget'!D32 -> 516.8 | E32: ='ARCHIVE_Operating Budget'!E32 -> 547.2 | F32: ='ARCHIVE_Operating Budget'!F32 -> 608 | G32: ='ARCHIVE_Operating Budget'!G32 -> 668.8 | H32: ='ARCHIVE_Operating Budget'!H32 -> 699.2 | I32: ='ARCHIVE_Operating Budget'!I32 -> 760 | J32: ='ARCHIVE_Operating Budget'!J32 -> 790.4 | ... AP32: ='ARCHIVE_Operating Budget'!AP32 -> 0.0055103256
A33: Total Patient-Related Expenses | C33: ='ARCHIVE_Operating Budget'!C33 -> 9179.0746 | D33: ='ARCHIVE_Operating Budget'!D33 -> 10402.951 | E33: ='ARCHIVE_Operating Budget'!E33 -> 11014.89 | F33: ='ARCHIVE_Operating Budget'!F33 -> 12238.766 | G33: ='ARCHIVE_Operating Budget'!G33 -> 13462.643 | H33: ='ARCHIVE_Operating Budget'!H33 -> 14074.581 | I33: ='ARCHIVE_Operating Budget'!I33 -> 15298.458 | J33: ='ARCHIVE_Operating Budget'!J33 -> 15910.396 | ... AP33: ='ARCHIVE_Operating Budget'!AP33 -> 0.11092037
A35: TOTAL COST OF GOODS SOLD | C35: ='ARCHIVE_Operating Budget'!C35 -> 29897.503 | D35: ='ARCHIVE_Operating Budget'!D35 -> 39368.852 | E35: ='ARCHIVE_Operating Budget'!E35 -> 40041.7 | F35: ='ARCHIVE_Operating Budget'!F35 -> 41780.677 | G35: ='ARCHIVE_Operating Budget'!G35 -> 43519.408 | H35: ='ARCHIVE_Operating Budget'!H35 -> 44388.682 | I35: ='ARCHIVE_Operating Budget'!I35 -> 50812.387 | J35: ='ARCHIVE_Operating Budget'!J35 -> 51681.474 | ... AP35: ='ARCHIVE_Operating Budget'!AP35 -> 0.34318285
A36: GROSS PROFIT | C36: ='ARCHIVE_Operating Budget'!C36 -> 52856.227 | D36: ='ARCHIVE_Operating Budget'!D36 -> 54418.709 | E36: ='ARCHIVE_Operating Budget'!E36 -> 59262.777 | F36: ='ARCHIVE_Operating Budget'!F36 -> 68557.63 | G36: ='ARCHIVE_Operating Budget'!G36 -> 77852.73 | H36: ='ARCHIVE_Operating Budget'!H36 -> 82500.371 | I36: ='ARCHIVE_Operating Budget'!I36 -> 87110.496 | J36: ='ARCHIVE_Operating Budget'!J36 -> 91758.325 | ... AP36: ='ARCHIVE_Operating Budget'!AP36 -> 0.65681715
A37: Gross Margin % | C37: ='ARCHIVE_Operating Budget'!C37 -> 0.63871715 | D37: ='ARCHIVE_Operating Budget'!D37 -> 0.58023376 | E37: ='ARCHIVE_Operating Budget'!E37 -> 0.5967785 | F37: ='ARCHIVE_Operating Budget'!F37 -> 0.62134024 | G37: ='ARCHIVE_Operating Budget'!G37 -> 0.64143823 | H37: ='ARCHIVE_Operating Budget'!H37 -> 0.65017721 | I37: ='ARCHIVE_Operating Budget'!I37 -> 0.63158842 | J37: ='ARCHIVE_Operating Budget'!J37 -> 0.6396992 | ... AO37: ='ARCHIVE_Operating Budget'!AO37 -> 0.65681715
A40: SELLING, GENERAL & ADMINISTRATIVE
A41: INDIRECT LABOR
A42: 40000M0 Wages-Marketing | B42: 40000M0 | C42: ='ARCHIVE_Operating Budget'!C42 -> 10000 | D42: ='ARCHIVE_Operating Budget'!D42 -> 10000 | E42: ='ARCHIVE_Operating Budget'!E42 -> 10000 | F42: ='ARCHIVE_Operating Budget'!F42 -> 10000 | G42: ='ARCHIVE_Operating Budget'!G42 -> 10000 | H42: ='ARCHIVE_Operating Budget'!H42 -> 10000 | I42: ='ARCHIVE_Operating Budget'!I42 -> 10000 | J42: ='ARCHIVE_Operating Budget'!J42 -> 10000 | ... AP42: ='ARCHIVE_Operating Budget'!AP42 -> 0.03470066
A43: 40000I0 Wages-Intake/Admit | B43: 40000I0 | C43: ='ARCHIVE_Operating Budget'!C43 -> 0 | D43: ='ARCHIVE_Operating Budget'!D43 -> 4166.6667 | E43: ='ARCHIVE_Operating Budget'!E43 -> 4166.6667 | F43: ='ARCHIVE_Operating Budget'!F43 -> 4166.6667 | G43: ='ARCHIVE_Operating Budget'!G43 -> 4166.6667 | H43: ='ARCHIVE_Operating Budget'!H43 -> 4166.6667 | I43: ='ARCHIVE_Operating Budget'!I43 -> 4166.6667 | J43: ='ARCHIVE_Operating Budget'!J43 -> 4166.6667 | ... AP43: ='ARCHIVE_Operating Budget'!AP43 -> 0.014458608
A44: 40000A0 Wages-Administrative | B44: 40000A0 | C44: ='ARCHIVE_Operating Budget'!C44 -> 0 | D44: ='ARCHIVE_Operating Budget'!D44 -> 0 | E44: ='ARCHIVE_Operating Budget'!E44 -> 12500 | F44: ='ARCHIVE_Operating Budget'!F44 -> 12500 | G44: ='ARCHIVE_Operating Budget'!G44 -> 12500 | H44: ='ARCHIVE_Operating Budget'!H44 -> 12500 | I44: ='ARCHIVE_Operating Budget'!I44 -> 12500 | J44: ='ARCHIVE_Operating Budget'!J44 -> 12500 | ... AP44: ='ARCHIVE_Operating Budget'!AP44 -> 0.043375825
A45: 40000C0 Wages-Clinical Admin | B45: 40000C0 | C45: ='ARCHIVE_Operating Budget'!C45 -> 0 | D45: ='ARCHIVE_Operating Budget'!D45 -> 10000 | E45: ='ARCHIVE_Operating Budget'!E45 -> 10000 | F45: ='ARCHIVE_Operating Budget'!F45 -> 10000 | G45: ='ARCHIVE_Operating Budget'!G45 -> 10000 | H45: ='ARCHIVE_Operating Budget'!H45 -> 10000 | I45: ='ARCHIVE_Operating Budget'!I45 -> 10000 | J45: ='ARCHIVE_Operating Budget'!J45 -> 10000 | ... AP45: ='ARCHIVE_Operating Budget'!AP45 -> 0.03470066
A46: 40000AN Medical Director | B46: 40000AN | C46: ='ARCHIVE_Operating Budget'!C46 -> 4000 | D46: ='ARCHIVE_Operating Budget'!D46 -> 4000 | E46: ='ARCHIVE_Operating Budget'!E46 -> 4000 | F46: ='ARCHIVE_Operating Budget'!F46 -> 4000 | G46: ='ARCHIVE_Operating Budget'!G46 -> 4000 | H46: ='ARCHIVE_Operating Budget'!H46 -> 4000 | I46: ='ARCHIVE_Operating Budget'!I46 -> 4000 | J46: ='ARCHIVE_Operating Budget'!J46 -> 4000 | ... AP46: ='ARCHIVE_Operating Budget'!AP46 -> 0.01308348
A47: Contract Labor (Admin + Clin) | B47: 40000MC | C47: ='ARCHIVE_Operating Budget'!C47 -> 4000 | D47: ='ARCHIVE_Operating Budget'!D47 -> 2500 | E47: ='ARCHIVE_Operating Budget'!E47 -> 0 | F47: ='ARCHIVE_Operating Budget'!F47 -> 0 | G47: ='ARCHIVE_Operating Budget'!G47 -> 0 | H47: ='ARCHIVE_Operating Budget'!H47 -> 0 | I47: ='ARCHIVE_Operating Budget'!I47 -> 0 | J47: ='ARCHIVE_Operating Budget'!J47 -> 0 | ... AP47: ='ARCHIVE_Operating Budget'!AP47 -> 0
A48: Total Indirect Labor | C48: ='ARCHIVE_Operating Budget'!C48 -> 18000 | D48: ='ARCHIVE_Operating Budget'!D48 -> 30666.667 | E48: ='ARCHIVE_Operating Budget'!E48 -> 40666.667 | F48: ='ARCHIVE_Operating Budget'!F48 -> 40666.667 | G48: ='ARCHIVE_Operating Budget'!G48 -> 40666.667 | H48: ='ARCHIVE_Operating Budget'!H48 -> 40666.667 | I48: ='ARCHIVE_Operating Budget'!I48 -> 40666.667 | J48: ='ARCHIVE_Operating Budget'!J48 -> 40666.667 | ... AP48: ='ARCHIVE_Operating Budget'!AP48 -> 0.14031923
A49: INDIRECT BENEFITS
A50: 41300 FICA/SS (7.65%) | B50: 41300 | C50: ='ARCHIVE_Operating Budget'!C50 -> 765 | D50: ='ARCHIVE_Operating Budget'!D50 -> 1848.75 | E50: ='ARCHIVE_Operating Budget'!E50 -> 2805 | F50: ='ARCHIVE_Operating Budget'!F50 -> 2805 | G50: ='ARCHIVE_Operating Budget'!G50 -> 2805 | H50: ='ARCHIVE_Operating Budget'!H50 -> 2805 | I50: ='ARCHIVE_Operating Budget'!I50 -> 2805 | J50: ='ARCHIVE_Operating Budget'!J50 -> 2805 | ... AP50: ='ARCHIVE_Operating Budget'!AP50 -> 0.009733535
A51: 41300 FUTA/SUTA (1.85%) | B51: 41300 | C51: ='ARCHIVE_Operating Budget'!C51 -> 185 | D51: ='ARCHIVE_Operating Budget'!D51 -> 447.08333 | E51: ='ARCHIVE_Operating Budget'!E51 -> 678.33333 | F51: ='ARCHIVE_Operating Budget'!F51 -> 678.33333 | G51: ='ARCHIVE_Operating Budget'!G51 -> 678.33333 | H51: ='ARCHIVE_Operating Budget'!H51 -> 678.33333 | I51: ='ARCHIVE_Operating Budget'!I51 -> 678.33333 | J51: ='ARCHIVE_Operating Budget'!J51 -> 678.33333 | ... AP51: ='ARCHIVE_Operating Budget'!AP51 -> 0.0023538614
A52: 41600 Workers Compensation (3%) | B52: 41600 | C52: ='ARCHIVE_Operating Budget'!C52 -> 300 | D52: ='ARCHIVE_Operating Budget'!D52 -> 725 | E52: ='ARCHIVE_Operating Budget'!E52 -> 1100 | F52: ='ARCHIVE_Operating Budget'!F52 -> 1100 | G52: ='ARCHIVE_Operating Budget'!G52 -> 1100 | H52: ='ARCHIVE_Operating Budget'!H52 -> 1100 | I52: ='ARCHIVE_Operating Budget'!I52 -> 1100 | J52: ='ARCHIVE_Operating Budget'!J52 -> 1100 | ... AP52: ='ARCHIVE_Operating Budget'!AP52 -> 0.0038170726
A53: 41100 Health Insurance | B53: 41100 | C53: ='ARCHIVE_Operating Budget'!C53 -> 732.86806 | D53: ='ARCHIVE_Operating Budget'!D53 -> 1749.1149 | E53: ='ARCHIVE_Operating Budget'!E53 -> 2402.4713 | F53: ='ARCHIVE_Operating Budget'!F53 -> 2385.1826 | G53: ='ARCHIVE_Operating Budget'!G53 -> 2368.141 | H53: ='ARCHIVE_Operating Budget'!H53 -> 2359.7111 | I53: ='ARCHIVE_Operating Budget'!I53 -> 2483.3674 | J53: ='ARCHIVE_Operating Budget'!J53 -> 2475.1253 | ... AP53: ='ARCHIVE_Operating Budget'!AP53 -> 0.0083943433
A54: Total Indirect Benefits | C54: ='ARCHIVE_Operating Budget'!C54 -> 1982.8681 | D54: ='ARCHIVE_Operating Budget'!D54 -> 4769.9482 | E54: ='ARCHIVE_Operating Budget'!E54 -> 6985.8046 | F54: ='ARCHIVE_Operating Budget'!F54 -> 6968.5159 | G54: ='ARCHIVE_Operating Budget'!G54 -> 6951.4743 | H54: ='ARCHIVE_Operating Budget'!H54 -> 6943.0445 | I54: ='ARCHIVE_Operating Budget'!I54 -> 7066.7007 | J54: ='ARCHIVE_Operating Budget'!J54 -> 7058.4586 | ... AP54: ='ARCHIVE_Operating Budget'!AP54 -> 0.024298812
A55: FACILITY & OPERATING EXPENSES
A56: 60800 Rent | B56: 60800 | C56: ='ARCHIVE_Operating Budget'!C56 -> 3450 | D56: ='ARCHIVE_Operating Budget'!D56 -> 3450 | E56: ='ARCHIVE_Operating Budget'!E56 -> 3450 | F56: ='ARCHIVE_Operating Budget'!F56 -> 3450 | G56: ='ARCHIVE_Operating Budget'!G56 -> 3450 | H56: ='ARCHIVE_Operating Budget'!H56 -> 3450 | I56: ='ARCHIVE_Operating Budget'!I56 -> 3450 | J56: ='ARCHIVE_Operating Budget'!J56 -> 3450 | ... AP56: ='ARCHIVE_Operating Budget'!AP56 -> 0.00094037512
A57: 65801 Insurance-Liability | B57: 65801 | C57: ='ARCHIVE_Operating Budget'!C57 -> 3333 | D57: ='ARCHIVE_Operating Budget'!D57 -> 3333 | E57: ='ARCHIVE_Operating Budget'!E57 -> 3333 | F57: ='ARCHIVE_Operating Budget'!F57 -> 3333 | G57: ='ARCHIVE_Operating Budget'!G57 -> 3333 | H57: ='ARCHIVE_Operating Budget'!H57 -> 3333 | I57: ='ARCHIVE_Operating Budget'!I57 -> 3333 | J57: ='ARCHIVE_Operating Budget'!J57 -> 3333 | ... AP57: ='ARCHIVE_Operating Budget'!AP57 -> 0.00090848414
A58: 65007 Professional Fees / Legal | B58: 65007 | C58: ='ARCHIVE_Operating Budget'!C58 -> 2000 | D58: ='ARCHIVE_Operating Budget'!D58 -> 2000 | E58: ='ARCHIVE_Operating Budget'!E58 -> 2000 | F58: ='ARCHIVE_Operating Budget'!F58 -> 2000 | G58: ='ARCHIVE_Operating Budget'!G58 -> 2000 | H58: ='ARCHIVE_Operating Budget'!H58 -> 2000 | I58: ='ARCHIVE_Operating Budget'!I58 -> 2000 | J58: ='ARCHIVE_Operating Budget'!J58 -> 2000 | ... AP58: ='ARCHIVE_Operating Budget'!AP58 -> 0.000545145
A59: 65100 Accounting / Payroll Fees | B59: 65100 | C59: ='ARCHIVE_Operating Budget'!C59 -> 1000 | D59: ='ARCHIVE_Operating Budget'!D59 -> 1000 | E59: ='ARCHIVE_Operating Budget'!E59 -> 1000 | F59: ='ARCHIVE_Operating Budget'!F59 -> 1000 | G59: ='ARCHIVE_Operating Budget'!G59 -> 1000 | H59: ='ARCHIVE_Operating Budget'!H59 -> 1000 | I59: ='ARCHIVE_Operating Budget'!I59 -> 1000 | J59: ='ARCHIVE_Operating Budget'!J59 -> 1000 | ... AP59: ='ARCHIVE_Operating Budget'!AP59 -> 0.0002725725
A60: 65000 Regulatory Consulting | B60: 65000 | C60: ='ARCHIVE_Operating Budget'!C60 -> 750 | D60: ='ARCHIVE_Operating Budget'!D60 -> 750 | E60: ='ARCHIVE_Operating Budget'!E60 -> 750 | F60: ='ARCHIVE_Operating Budget'!F60 -> 750 | G60: ='ARCHIVE_Operating Budget'!G60 -> 750 | H60: ='ARCHIVE_Operating Budget'!H60 -> 750 | I60: ='ARCHIVE_Operating Budget'!I60 -> 750 | J60: ='ARCHIVE_Operating Budget'!J60 -> 750 | ... AP60: ='ARCHIVE_Operating Budget'!AP60 -> 0.00020442937
A61: 65000 EMR / Patient Mgmt System | B61: 65006 | C61: ='ARCHIVE_Operating Budget'!C61 -> 1125 | D61: ='ARCHIVE_Operating Budget'!D61 -> 1275 | E61: ='ARCHIVE_Operating Budget'!E61 -> 1350 | F61: ='ARCHIVE_Operating Budget'!F61 -> 1500 | G61: ='ARCHIVE_Operating Budget'!G61 -> 1650 | H61: ='ARCHIVE_Operating Budget'!H61 -> 1725 | I61: ='ARCHIVE_Operating Budget'!I61 -> 1875 | J61: ='ARCHIVE_Operating Budget'!J61 -> 1950 | ... AP61: ='ARCHIVE_Operating Budget'!AP61 -> 0.0002725725
A62: 68001 Advertising / Publications | B62: 68001 | C62: ='ARCHIVE_Operating Budget'!C62 -> 1200 | D62: ='ARCHIVE_Operating Budget'!D62 -> 1200 | E62: ='ARCHIVE_Operating Budget'!E62 -> 1200 | F62: ='ARCHIVE_Operating Budget'!F62 -> 1200 | G62: ='ARCHIVE_Operating Budget'!G62 -> 1200 | H62: ='ARCHIVE_Operating Budget'!H62 -> 1200 | I62: ='ARCHIVE_Operating Budget'!I62 -> 1200 | J62: ='ARCHIVE_Operating Budget'!J62 -> 1200 | ... AP62: ='ARCHIVE_Operating Budget'!AP62 -> 0.000327087
A63: 68050 Material Development | B63: 68050 | C63: ='ARCHIVE_Operating Budget'!C63 -> 800 | D63: ='ARCHIVE_Operating Budget'!D63 -> 800 | E63: ='ARCHIVE_Operating Budget'!E63 -> 800 | F63: ='ARCHIVE_Operating Budget'!F63 -> 800 | G63: ='ARCHIVE_Operating Budget'!G63 -> 800 | H63: ='ARCHIVE_Operating Budget'!H63 -> 800 | I63: ='ARCHIVE_Operating Budget'!I63 -> 800 | J63: ='ARCHIVE_Operating Budget'!J63 -> 800 | ... AP63: ='ARCHIVE_Operating Budget'!AP63 -> 0.000218058
A64: 66500 Office Supplies | B64: 66500 | C64: ='ARCHIVE_Operating Budget'!C64 -> 500 | D64: ='ARCHIVE_Operating Budget'!D64 -> 500 | E64: ='ARCHIVE_Operating Budget'!E64 -> 500 | F64: ='ARCHIVE_Operating Budget'!F64 -> 500 | G64: ='ARCHIVE_Operating Budget'!G64 -> 500 | H64: ='ARCHIVE_Operating Budget'!H64 -> 500 | I64: ='ARCHIVE_Operating Budget'!I64 -> 500 | J64: ='ARCHIVE_Operating Budget'!J64 -> 500 | ... AP64: ='ARCHIVE_Operating Budget'!AP64 -> 0.00013628625
A65: 61500 Telephone & Internet | B65: 61500 | C65: ='ARCHIVE_Operating Budget'!C65 -> 600 | D65: ='ARCHIVE_Operating Budget'!D65 -> 600 | E65: ='ARCHIVE_Operating Budget'!E65 -> 600 | F65: ='ARCHIVE_Operating Budget'!F65 -> 600 | G65: ='ARCHIVE_Operating Budget'!G65 -> 600 | H65: ='ARCHIVE_Operating Budget'!H65 -> 600 | I65: ='ARCHIVE_Operating Budget'!I65 -> 600 | J65: ='ARCHIVE_Operating Budget'!J65 -> 600 | ... AP65: ='ARCHIVE_Operating Budget'!AP65 -> 0.0001635435
A66: 61500 Utilities | B66: 61500 | C66: ='ARCHIVE_Operating Budget'!C66 -> 600 | D66: ='ARCHIVE_Operating Budget'!D66 -> 600 | E66: ='ARCHIVE_Operating Budget'!E66 -> 600 | F66: ='ARCHIVE_Operating Budget'!F66 -> 600 | G66: ='ARCHIVE_Operating Budget'!G66 -> 600 | H66: ='ARCHIVE_Operating Budget'!H66 -> 600 | I66: ='ARCHIVE_Operating Budget'!I66 -> 600 | J66: ='ARCHIVE_Operating Budget'!J66 -> 600 | ... AP66: ='ARCHIVE_Operating Budget'!AP66 -> 0.0001635435
A67: 65200 Bank Service Charges | B67: 65200 | C67: ='ARCHIVE_Operating Budget'!C67 -> 150 | D67: ='ARCHIVE_Operating Budget'!D67 -> 150 | E67: ='ARCHIVE_Operating Budget'!E67 -> 150 | F67: ='ARCHIVE_Operating Budget'!F67 -> 150 | G67: ='ARCHIVE_Operating Budget'!G67 -> 150 | H67: ='ARCHIVE_Operating Budget'!H67 -> 150 | I67: ='ARCHIVE_Operating Budget'!I67 -> 150 | J67: ='ARCHIVE_Operating Budget'!J67 -> 150 | ... AP67: ='ARCHIVE_Operating Budget'!AP67 -> 4.0885875e-05
A68: 65700 Dues & Subscriptions | B68: 65700 | C68: ='ARCHIVE_Operating Budget'!C68 -> 300 | D68: ='ARCHIVE_Operating Budget'!D68 -> 300 | E68: ='ARCHIVE_Operating Budget'!E68 -> 300 | F68: ='ARCHIVE_Operating Budget'!F68 -> 300 | G68: ='ARCHIVE_Operating Budget'!G68 -> 300 | H68: ='ARCHIVE_Operating Budget'!H68 -> 300 | I68: ='ARCHIVE_Operating Budget'!I68 -> 300 | J68: ='ARCHIVE_Operating Budget'!J68 -> 300 | ... AP68: ='ARCHIVE_Operating Budget'!AP68 -> 8.1771749e-05
A69: Total Facility & Operating Expenses | C69: ='ARCHIVE_Operating Budget'!C69 -> 15808 | D69: ='ARCHIVE_Operating Budget'!D69 -> 15958 | E69: ='ARCHIVE_Operating Budget'!E69 -> 16033 | F69: ='ARCHIVE_Operating Budget'!F69 -> 16183 | G69: ='ARCHIVE_Operating Budget'!G69 -> 16333 | H69: ='ARCHIVE_Operating Budget'!H69 -> 16408 | I69: ='ARCHIVE_Operating Budget'!I69 -> 16558 | J69: ='ARCHIVE_Operating Budget'!J69 -> 16633 | ... AP69: ='ARCHIVE_Operating Budget'!AP69 -> 0.0042747545
A72: TOTAL SG&A | C72: ='ARCHIVE_Operating Budget'!C72 -> 35790.868 | D72: ='ARCHIVE_Operating Budget'!D72 -> 51394.615 | E72: ='ARCHIVE_Operating Budget'!E72 -> 63685.471 | F72: ='ARCHIVE_Operating Budget'!F72 -> 63818.183 | G72: ='ARCHIVE_Operating Budget'!G72 -> 63951.141 | H72: ='ARCHIVE_Operating Budget'!H72 -> 64017.711 | I72: ='ARCHIVE_Operating Budget'!I72 -> 64291.367 | J72: ='ARCHIVE_Operating Budget'!J72 -> 64358.125 | ... AP72: ='ARCHIVE_Operating Budget'!AP72 -> 0.1688928
A74: EBITDA | C74: ='ARCHIVE_Operating Budget'!C74 -> 17065.359 | D74: ='ARCHIVE_Operating Budget'!D74 -> 3024.094 | E74: ='ARCHIVE_Operating Budget'!E74 -> -4422.6946 | F74: ='ARCHIVE_Operating Budget'!F74 -> 4739.447 | G74: ='ARCHIVE_Operating Budget'!G74 -> 13901.589 | H74: ='ARCHIVE_Operating Budget'!H74 -> 18482.659 | I74: ='ARCHIVE_Operating Budget'!I74 -> 22819.129 | J74: ='ARCHIVE_Operating Budget'!J74 -> 27400.2 | ... AP74: ='ARCHIVE_Operating Budget'!AP74 -> 0.48792436
A75: EBITDA Margin % | C75: ='ARCHIVE_Operating Budget'!C75 -> 0.2062186 | D75: ='ARCHIVE_Operating Budget'!D75 -> 0.032244084 | E75: ='ARCHIVE_Operating Budget'!E75 -> -0.044536709 | F75: ='ARCHIVE_Operating Budget'!F75 -> 0.042953777 | G75: ='ARCHIVE_Operating Budget'!G75 -> 0.1145369 | H75: ='ARCHIVE_Operating Budget'!H75 -> 0.14566 | I75: ='ARCHIVE_Operating Budget'!I75 -> 0.16544846 | J75: ='ARCHIVE_Operating Budget'!J75 -> 0.1910223 | ... AO75: ='ARCHIVE_Operating Budget'!AO75 -> 0.48792436
A77: BELOW EBITDA
A78: Amortization of Intangibles | B78: 7000 | C78: ='ARCHIVE_Operating Budget'!C78 -> 1666.6667 | D78: ='ARCHIVE_Operating Budget'!D78 -> 1666.6667 | E78: ='ARCHIVE_Operating Budget'!E78 -> 1666.6667 | F78: ='ARCHIVE_Operating Budget'!F78 -> 1666.6667 | G78: ='ARCHIVE_Operating Budget'!G78 -> 1666.6667 | H78: ='ARCHIVE_Operating Budget'!H78 -> 1666.6667 | I78: ='ARCHIVE_Operating Budget'!I78 -> 1666.6667 | J78: ='ARCHIVE_Operating Budget'!J78 -> 1666.6667 | ... AP78: ='ARCHIVE_Operating Budget'!AP78 -> 0.0004542875
A79: Interest - SBA Loan | B79: 7100 | C79: ='ARCHIVE_Operating Budget'!C79 -> 4791.6667 | D79: ='ARCHIVE_Operating Budget'!D79 -> 4791.6667 | E79: ='ARCHIVE_Operating Budget'!E79 -> 4791.6667 | F79: ='ARCHIVE_Operating Budget'!F79 -> 4791.6667 | G79: ='ARCHIVE_Operating Budget'!G79 -> 4791.6667 | H79: ='ARCHIVE_Operating Budget'!H79 -> 4791.6667 | I79: ='ARCHIVE_Operating Budget'!I79 -> 4791.6667 | J79: ='ARCHIVE_Operating Budget'!J79 -> 4791.6667 | ... AP79: ='ARCHIVE_Operating Budget'!AP79 -> 0.0013060766
A80: Interest - Seller Note | B80: 7100 | C80: ='ARCHIVE_Operating Budget'!C80 -> 1000 | D80: ='ARCHIVE_Operating Budget'!D80 -> 1000 | E80: ='ARCHIVE_Operating Budget'!E80 -> 1000 | F80: ='ARCHIVE_Operating Budget'!F80 -> 1000 | G80: ='ARCHIVE_Operating Budget'!G80 -> 1000 | H80: ='ARCHIVE_Operating Budget'!H80 -> 1000 | I80: ='ARCHIVE_Operating Budget'!I80 -> 1000 | J80: ='ARCHIVE_Operating Budget'!J80 -> 1000 | ... AP80: ='ARCHIVE_Operating Budget'!AP80 -> 0.0002725725
A81: License - Upfront Payment | B81: 7200 | C81: ='ARCHIVE_Operating Budget'!C81 -> 25000 | D81: ='ARCHIVE_Operating Budget'!D81 -> 25000 | E81: ='ARCHIVE_Operating Budget'!E81 -> 25000 | F81: ='ARCHIVE_Operating Budget'!F81 -> 0 | G81: ='ARCHIVE_Operating Budget'!G81 -> 0 | H81: ='ARCHIVE_Operating Budget'!H81 -> 0 | I81: ='ARCHIVE_Operating Budget'!I81 -> 0 | J81: ='ARCHIVE_Operating Budget'!J81 -> 0 | ... AP81: ='ARCHIVE_Operating Budget'!AP81 -> 0
A82: License - Refi Interest | B82: 7200 | C82: ='ARCHIVE_Operating Budget'!C82 -> 0 | D82: ='ARCHIVE_Operating Budget'!D82 -> 0 | E82: ='ARCHIVE_Operating Budget'!E82 -> 0 | F82: ='ARCHIVE_Operating Budget'!F82 -> 1125 | G82: ='ARCHIVE_Operating Budget'!G82 -> 1096.4003 | H82: ='ARCHIVE_Operating Budget'!H82 -> 1067.6576 | I82: ='ARCHIVE_Operating Budget'!I82 -> 1038.7713 | J82: ='ARCHIVE_Operating Budget'!J82 -> 1009.7404 | ... AP82: ='ARCHIVE_Operating Budget'!AP82 -> 0.0010329182
A83: Total Below-EBITDA | C83: ='ARCHIVE_Operating Budget'!C83 -> 32458.333 | D83: ='ARCHIVE_Operating Budget'!D83 -> 32458.333 | E83: ='ARCHIVE_Operating Budget'!E83 -> 32458.333 | F83: ='ARCHIVE_Operating Budget'!F83 -> 8583.3333 | G83: ='ARCHIVE_Operating Budget'!G83 -> 8554.7337 | H83: ='ARCHIVE_Operating Budget'!H83 -> 8525.991 | I83: ='ARCHIVE_Operating Budget'!I83 -> 8497.1046 | J83: ='ARCHIVE_Operating Budget'!J83 -> 8468.0738 | ... AP83: ='ARCHIVE_Operating Budget'!AP83 -> 0.0030658548
A85: PRE-TAX INCOME | C85: ='ARCHIVE_Operating Budget'!C85 -> -15392.975 | D85: ='ARCHIVE_Operating Budget'!D85 -> -29434.239 | E85: ='ARCHIVE_Operating Budget'!E85 -> -36881.028 | F85: ='ARCHIVE_Operating Budget'!F85 -> -3843.8863 | G85: ='ARCHIVE_Operating Budget'!G85 -> 5346.8549 | H85: ='ARCHIVE_Operating Budget'!H85 -> 9956.6684 | I85: ='ARCHIVE_Operating Budget'!I85 -> 14322.024 | J85: ='ARCHIVE_Operating Budget'!J85 -> 18932.126 | ... AP85: ='ARCHIVE_Operating Budget'!AP85 -> 0.4848585
A86: TX Franchise Tax (0.375%) | B86: 9000 | C86: ='ARCHIVE_Operating Budget'!C86 -> 0 | D86: ='ARCHIVE_Operating Budget'!D86 -> 0 | E86: ='ARCHIVE_Operating Budget'!E86 -> 0 | F86: ='ARCHIVE_Operating Budget'!F86 -> 0 | G86: ='ARCHIVE_Operating Budget'!G86 -> 455.14552 | H86: ='ARCHIVE_Operating Budget'!H86 -> 475.83395 | I86: ='ARCHIVE_Operating Budget'!I86 -> 517.21081 | J86: ='ARCHIVE_Operating Budget'!J86 -> 537.89925 | ... AP86: ='ARCHIVE_Operating Budget'!AP86 -> 0.00375
A87: NET INCOME | C87: ='ARCHIVE_Operating Budget'!C87 -> -15392.975 | D87: ='ARCHIVE_Operating Budget'!D87 -> -29434.239 | E87: ='ARCHIVE_Operating Budget'!E87 -> -36881.028 | F87: ='ARCHIVE_Operating Budget'!F87 -> -3843.8863 | G87: ='ARCHIVE_Operating Budget'!G87 -> 4891.7094 | H87: ='ARCHIVE_Operating Budget'!H87 -> 9480.8344 | I87: ='ARCHIVE_Operating Budget'!I87 -> 13804.814 | J87: ='ARCHIVE_Operating Budget'!J87 -> 18394.227 | ... AP87: ='ARCHIVE_Operating Budget'!AP87 -> 0.4811085

Sheet ARCHIVE_Reconciliation
A1: Azalea Hospice — Model Reconciliation
A2: Staffing Model vs. SBA Budget | Prepared for SBA 7(a) Loan Package
A4: Metric | B4: Budget Y1 | C4: Staffing Y1 | D4: Δ Y1 | E4: Budget Y2 | F4: Staffing Y2 | G4: Δ Y2 | H4: Budget Y3 | I4: Staffing Y3 | J4: Δ Y3 | K4: Notes
A5: CENSUS
A6: Average Daily Census | B6: 25.95 | C6: 24 | D6: =C6-B6 -> -1.95 | E6: 41.45 | F6: 42.25 | G6: =F6-E6 -> 0.8 | H6: 55.08 | I6: 55.42 | J6: =I6-H6 -> 0.34 | K6: Census assumptions substantially aligned; minor timing differences
A7: Year-End ADC | B7: 32.25 | C7: 33 | D7: =C7-B7 -> 0.75 | E7: 49.5 | F7: 50 | G7: =F7-E7 -> 0.5 | H7: 59.5 | I7: 60 | J7: =I7-H7 -> 0.5 | K7: Year-end targets within 1 patient; effectively matched
A9: REVENUE
A10: Net Revenue | B10: 1605199 | C10: 1588872 | D10: =C10-B10 -> -16327 | E10: 2628166 | F10: 2797076 | G10: =F10-E10 -> 168910 | H10: 3580092 | I10: 3668749 | J10: =I10-H10 -> 88657 | K10: Revenue within 1-6%; driven by rate/mix assumptions
A12: PROFITABILITY
A13: EBITDA | B13: 30423 | C13: 279772 | D13: =C13-B13 -> 249349 | E13: 498276 | F13: 1093561 | G13: =F13-E13 -> 595285 | H13: 955488 | I13: 1525084 | J13: =I13-H13 -> 569596 | K13: Budget is conservative (SBA-appropriate); Staffing Model reflects operator upside
A14: EBITDA Margin % | B14: 0.019 | C14: 0.176 | D14: =C14-B14 -> 0.157 | E14: 0.1896 | F14: 0.391 | G14: =F14-E14 -> 0.2014 | H14: 0.2669 | I14: 0.416 | J14: =I14-H14 -> 0.1491 | K14: Budget carries full staffing ladder + G&A; Staffing Model is leaner
A15: Net Income (Pre-Tax) | B15: 9438 | C15: 189559 | D15: =C15-B15 -> 180121 | E15: 471829 | F15: 1000295 | G15: =F15-E15 -> 528466 | H15: 935142 | I15: 1430200 | J15: =I15-H15 -> 495058 | K15: Same directional story; Budget NI depressed by higher cost load
A17: COST STRUCTURE
A18: Total COGS / Cost of Care | B18: 1430476 | C18: 579007 | D18: =C18-B18 -> -851469 | E18: 1827799 | F18: 982546 | G18: =F18-E18 -> -845253 | H18: 2224286 | I18: 1259052 | J18: =I18-H18 -> -965234 | K18: Budget COGS includes full clinical IDG + supplies; Staffing Model is direct care only
A19: Total SG&A / OpEx | B19: 216174 | C19: 730092 | D19: =C19-B19 -> 513918 | E19: 340716 | F19: 720969 | G19: =F19-E19 -> 380253 | H19: 456678 | I19: 884613 | J19: =I19-H19 -> 427935 | K19: Different classification — Budget uses SG&A; Staffing Model uses OpEx (includes items Budget puts in COGS)
A21: DEAL TERMS & SBA FINANCING
A22: Purchase Price | B22: 300000 | C22: N/A | K22: Avant Hospice — 100% membership interest
A23: SBA 7(a) Principal | B23: 500000 | C23: N/A | K23: 10-yr term @ 11.5%; annual debt service $84,357
A24: Owner Equity | B24: 250000 | C24: N/A | K24: Cash injection; pre-revenue startup costs $12,900
A25: Global DSCR (3-Yr) | B25: 5.44x | C25: N/A | K25: PASS — 4.4x above SBA 1.25x floor
A27: VARIANCE EXPLANATION
A29: The SBA Budget and Staffing Model use the same census ramp and revenue assumptions but differ in cost classification and depth:
A31: 1. Census & Revenue — Aligned within 1–6%. Minor differences from rate escalation timing and payer-mix rounding.
A32: 2. EBITDA Gap — Budget carries the full clinical staffing ladder (IDG team scaled by pts-per-FTE ratios), contracted Medical Director,
A33: benefits load (~24%), and detailed G&A (facility, marketing, billing fees). Staffing Model is a lighter direct-care-only view.
A34: 3. Cost Classification — Budget separates COGS (clinical labor + patient supplies) from SG&A (admin, facility, marketing).
A35: Staffing Model groups differently: Cost of Care vs. OpEx. Dollar totals sum to similar levels when combined.
A36: 4. Deal & Financing — Budget is the definitive source for SBA terms. $500K SBA 7(a) at 11.5%, $300K acquisition (Avant), $250K equity.
A37: 5. DSCR — Global 3-year DSCR of 5.44x far exceeds SBA 1.25x floor. Y1 per-year DSCR of 1.00x is expected for a hospice startup.
A39: Conclusion: Both models tell the same story — conservative Y1, profitable Y2+, strong DSCR. The Budget is the SBA-ready document;
A40: the Staffing Model provides operational detail for internal planning.

Sheet ARCHIVE_Stress Tests
A1: STRESS TESTS — Downside Scenarios
A2: PPEO freeze modeled in full on the collections side below. Cash-runway & EBITDA columns complete once the Cash Flow tab is built.
A4: A. SCENARIO DEFINITIONS
A5: Scenario | B5: Driver | C5: Base → Stress · Period
A6: PPEO cash freeze | B6: Medicare collections | C6: Hold M6-M8 → 100% frozen 12 mo from 1st claim (M2)
A7: Revenue -20% | B7: ADC x rate | C7: 100% → 80%, full 36 mo
A8: Wage +15% | B8: All W-2 wages | C8: 100% → 115%, full 36 mo
A9: Census slip 3 mo | B9: Ramp start | C9: M1 → shift +3 mo (one-time)
A10: Combined downside | B10: Rev / Wage / Freeze | C10: -10% rev / +10% wage / 6-mo freeze
A11: B. PPEO COLLECTIONS STRESS — Base (M6-M8 hold) vs Stress (12-mo freeze)
A12: Line | C12: M1 | D12: M2 | E12: M3 | F12: M4 | G12: M5 | H12: M6 | I12: M7 | J12: M8 | K12: M9 | L12: M10 | M12: M11 | N12: M12 | O12: M13 | P12: M14 | Q12: M15 | R12: M16 | S12: M17 | T12: M18 | U12: Max/End
A13: Net revenue billed | C13: ='ARCHIVE_Revenue Model'!$C$39 -> 82753.73 | D13: ='ARCHIVE_Revenue Model'!$D$39 -> 93787.561 | E13: ='ARCHIVE_Revenue Model'!$E$39 -> 99304.476 | F13: ='ARCHIVE_Revenue Model'!$F$39 -> 110338.31 | G13: ='ARCHIVE_Revenue Model'!$G$39 -> 121372.14 | H13: ='ARCHIVE_Revenue Model'!$H$39 -> 126889.05 | I13: ='ARCHIVE_Revenue Model'!$I$39 -> 137922.88 | J13: ='ARCHIVE_Revenue Model'!$J$39 -> 143439.8 | K13: ='ARCHIVE_Revenue Model'!$K$39 -> 154473.63 | L13: ='ARCHIVE_Revenue Model'!$L$39 -> 165507.46 | M13: ='ARCHIVE_Revenue Model'!$M$39 -> 171024.38 | N13: ='ARCHIVE_Revenue Model'!$N$39 -> 182058.21 | O13: ='ARCHIVE_Revenue Model'!$O$39 -> 187575.12 | P13: ='ARCHIVE_Revenue Model'!$P$39 -> 198608.95 | Q13: ='ARCHIVE_Revenue Model'!$Q$39 -> 204125.87 | R13: ='ARCHIVE_Revenue Model'!$R$39 -> 215159.7 | S13: ='ARCHIVE_Revenue Model'!$S$39 -> 220676.61 | T13: ='ARCHIVE_Revenue Model'!$T$39 -> 231710.44
A14: Base — cash collected | C14: ='ARCHIVE_Revenue Model'!$C$40 -> 0 | D14: ='ARCHIVE_Revenue Model'!$D$40 -> 0 | E14: ='ARCHIVE_Revenue Model'!$E$40 -> 82753.73 | F14: ='ARCHIVE_Revenue Model'!$F$40 -> 93787.561 | G14: ='ARCHIVE_Revenue Model'!$G$40 -> 99304.476 | H14: ='ARCHIVE_Revenue Model'!$H$40 -> 0 | I14: ='ARCHIVE_Revenue Model'!$I$40 -> 0 | J14: ='ARCHIVE_Revenue Model'!$J$40 -> 0 | K14: ='ARCHIVE_Revenue Model'!$K$40 -> 496522.38 | L14: ='ARCHIVE_Revenue Model'!$L$40 -> 143439.8 | M14: ='ARCHIVE_Revenue Model'!$M$40 -> 154473.63 | N14: ='ARCHIVE_Revenue Model'!$N$40 -> 165507.46 | O14: ='ARCHIVE_Revenue Model'!$O$40 -> 171024.38 | P14: ='ARCHIVE_Revenue Model'!$P$40 -> 182058.21 | Q14: ='ARCHIVE_Revenue Model'!$Q$40 -> 187575.12 | R14: ='ARCHIVE_Revenue Model'!$R$40 -> 198608.95 | S14: ='ARCHIVE_Revenue Model'!$S$40 -> 204125.87 | T14: ='ARCHIVE_Revenue Model'!$T$40 -> 215159.7
A15: Base — cumulative AR gap | C15: ='ARCHIVE_Revenue Model'!$C$41 -> -82753.73 | D15: ='ARCHIVE_Revenue Model'!$D$41 -> -176541.29 | E15: ='ARCHIVE_Revenue Model'!$E$41 -> -193092.04 | F15: ='ARCHIVE_Revenue Model'!$F$41 -> -209642.78 | G15: ='ARCHIVE_Revenue Model'!$G$41 -> -231710.44 | H15: ='ARCHIVE_Revenue Model'!$H$41 -> -358599.5 | I15: ='ARCHIVE_Revenue Model'!$I$41 -> -496522.38 | J15: ='ARCHIVE_Revenue Model'!$J$41 -> -639962.18 | K15: ='ARCHIVE_Revenue Model'!$K$41 -> -297913.43 | L15: ='ARCHIVE_Revenue Model'!$L$41 -> -319981.09 | M15: ='ARCHIVE_Revenue Model'!$M$41 -> -336531.84 | N15: ='ARCHIVE_Revenue Model'!$N$41 -> -353082.58 | O15: ='ARCHIVE_Revenue Model'!$O$41 -> -369633.33 | P15: ='ARCHIVE_Revenue Model'!$P$41 -> -386184.07 | Q15: ='ARCHIVE_Revenue Model'!$Q$41 -> -402734.82 | R15: ='ARCHIVE_Revenue Model'!$R$41 -> -419285.57 | S15: ='ARCHIVE_Revenue Model'!$S$41 -> -435836.31 | T15: ='ARCHIVE_Revenue Model'!$T$41 -> -452387.06 | U15: =MIN(C15:T15) -> -639962.18
A16: Stress — cash collected (freeze) | C16: =0 -> 0 | D16: =0 -> 0 | E16: =0 -> 0 | F16: =0 -> 0 | G16: =0 -> 0 | H16: =0 -> 0 | I16: =0 -> 0 | J16: =0 -> 0 | ... O16: =0 -> 0 | P16: =SUM('ARCHIVE_Revenue Model'!$C$39:$N$39) -> 1588871.6 | Q16: ='ARCHIVE_Revenue Model'!$O$39 -> 187575.12 | R16: ='ARCHIVE_Revenue Model'!$P$39 -> 198608.95 | S16: ='ARCHIVE_Revenue Model'!$Q$39 -> 204125.87 | T16: ='ARCHIVE_Revenue Model'!$R$39 -> 215159.7
A17: Stress — cumulative AR gap | C17: =C16-C13 -> -82753.73 | D17: =C17+D16-D13 -> -176541.29 | E17: =D17+E16-E13 -> -275845.77 | F17: =E17+F16-F13 -> -386184.07 | G17: =F17+G16-G13 -> -507556.21 | H17: =G17+H16-H13 -> -634445.26 | I17: =H17+I16-I13 -> -772368.15 | J17: =I17+J16-J13 -> -915807.95 | K17: =J17+K16-K13 -> -1070281.6 | ... T17: =S17+T16-T13 -> -452387.06 | U17: =MIN(C17:T17) -> -1776446.7
A18: Max AR gap = peak working-capital need (before financing & opex). Recovery: base by M9, stress by M14.
A20: C. SCENARIO DASHBOARD (cash & EBITDA columns complete with Cash Flow tab)
A21: Scenario | B21: Peak AR Gap | E21: Min Cash | H21: Mo of Min Cash | J21: Cash-out Mo | L21: Y1 EBITDA | O21: Y3 EBITDA
A22: Base case (best) | B22: =MIN('ARCHIVE_Stress Tests'!C15:T15) -> -639962.18 | E22: → with Cash Flow
A23: PPEO freeze (12 mo) | B23: =MIN('ARCHIVE_Stress Tests'!C17:T17) -> -1776446.7 | E23: → with Cash Flow
A24: Revenue -20% | B24: — | E24: → with Cash Flow
A25: Wage +15% | B25: — | E25: → with Cash Flow
A26: Census slip 3 mo | B26: — | E26: → with Cash Flow
A27: Combined downside | B27: — | E27: → with Cash Flow
